{
  "type": "Feature",
  "properties": {
    "iso:country":"US",
    "sg:address":"44584 308th St",
    "sg:city":"Mission Hill",
    "sg:phone":"+1 605 665 7860",
    "sg:postcode":"57046",
    "sg:province":"SD",
    "sg:tags":[
        "farm",
        "soybean"
    ],
    "wof:name":"Keith Williams",
    "wof:placetype":"venue"
},
  "geometry": {"coordinates":[-97.28976,42.923435],"type":"Point"}
}