{
  "type": "Feature",
  "properties": {
    "addr:full":"21993 479th Ave Elkton SD 57026",
    "addr:housenumber":"21993",
    "addr:postcode":"57026",
    "addr:street":"479Th Ave",
    "iso:country":"US",
    "sg:address":"21993 479th Ave",
    "sg:city":"Elkton",
    "sg:classifiers":[
        {
            "category":"Farming",
            "subcategory":"Farm",
            "type":"Manufacturing & Wholesale Goods"
        }
    ],
    "sg:phone":"+1 605 693 4430",
    "sg:postcode":"57026",
    "sg:province":"SD",
    "sg:tags":[
        "crop",
        "general"
    ],
    "wof:name":"Roy Clark",
    "wof:placetype":"venue"
},
  "geometry": {"coordinates":[-96.626249,44.19637],"type":"Point"}
}