{
  "type": "Feature",
  "properties": {
    "iso:country":"US",
    "sg:address":"404 W 1st Ave",
    "sg:city":"Mitchell",
    "sg:classifiers":[
        {
            "category":"Autos & Motor Vehicles",
            "subcategory":"Automobile Sales",
            "type":"Retail Goods"
        }
    ],
    "sg:phone":"+1 605 996 1665",
    "sg:postcode":"57301",
    "sg:province":"SD",
    "sg:tags":[
        "car",
        "dealer"
    ],
    "wof:name":"Auto Shoppe",
    "wof:placetype":"venue"
},
  "geometry": {"coordinates":[-98.02968799999999,43.709503],"type":"Point"}
}