{
  "type": "Feature",
  "properties": {
    "addr:full":"550 N 5th St Rapid City SD 57701",
    "addr:housenumber":"550",
    "addr:postcode":"57701",
    "addr:street":"N 5Th St",
    "iso:country":"US",
    "sg:address":"550 N 5th St",
    "sg:city":"Rapid City",
    "sg:classifiers":[
        {
            "category":"Insurance",
            "subcategory":"Insurance Agent",
            "type":"Services"
        }
    ],
    "sg:phone":"+1 605 718 7020",
    "sg:postcode":"57701",
    "sg:province":"SD",
    "wof:name":"Jodi L Enderson",
    "wof:placetype":"venue"
},
  "geometry": {"coordinates":[-103.222623,44.086558],"type":"Point"}
}