{
  "type": "Feature",
  "properties": {
    "addr:full":"2830 Eglin St Rapid City SD 57703",
    "addr:housenumber":"2830",
    "addr:postcode":"57703",
    "addr:street":"Eglin St",
    "iso:country":"US",
    "sg:address":"2830 Eglin St",
    "sg:city":"Rapid City",
    "sg:classifiers":[
        {
            "category":"Freight",
            "type":"Transportation"
        }
    ],
    "sg:phone":"+1 605 388 8275",
    "sg:postcode":"57703",
    "sg:province":"SD",
    "sg:tags":[
        "general"
    ],
    "wof:name":"Mobile Storage Rentals",
    "wof:placetype":"venue"
},
  "geometry": {"coordinates":[-103.161953,44.097335],"type":"Point"}
}