{
  "type": "Feature",
  "properties": {
    "iso:country":"US",
    "sg:address":"320 W Rushmore St",
    "sg:city":"Spearfish",
    "sg:classifiers":[
        {
            "category":"Recreation",
            "type":"Entertainment"
        }
    ],
    "sg:phone":"+1 605 347 7551",
    "sg:postcode":"57783",
    "sg:province":"SD",
    "sg:tags":[
        "stable"
    ],
    "wof:name":"All American Horseshoeing",
    "wof:placetype":"venue"
},
  "geometry": {"coordinates":[-103.865931,44.499181],"type":"Point"}
}