{
  "type": "Feature",
  "properties": {
    "iso:country":"US",
    "sg:address":"27245 379th Ave",
    "sg:city":"Corsica",
    "sg:phone":"+1 605 243 2209",
    "sg:postcode":"57328",
    "sg:province":"SD",
    "sg:tags":[
        "telegraph"
    ],
    "wof:name":"Prime West",
    "wof:placetype":"venue"
},
  "geometry": {"coordinates":[-98.608791,43.435431],"type":"Point"}
}