{
  "type": "Feature",
  "properties": {
    "iso:country":"US",
    "sg:address":"117 Teton Ln",
    "sg:city":"Brookings",
    "sg:classifiers":[
        {
            "category":"Professional",
            "subcategory":"Management & Consulting",
            "type":"Services"
        }
    ],
    "sg:phone":"+1 605 692 3000",
    "sg:postcode":"57006",
    "sg:province":"SD",
    "wof:name":"S A Travel 1-U",
    "wof:placetype":"venue"
},
  "geometry": {"coordinates":[-96.804796,44.286566],"type":"Point"}
}