{
  "type": "Feature",
  "properties": {
    "addr:full":"1701 N Industrial Ave Sioux Falls SD 57104",
    "addr:housenumber":"1701",
    "addr:postcode":"57104",
    "addr:street":"N Industrial Ave",
    "iso:country":"US",
    "sg:address":"1701 N Industrial Ave",
    "sg:city":"Sioux Falls",
    "sg:classifiers":[
        {
            "category":"Freight",
            "type":"Transportation"
        }
    ],
    "sg:phone":"+1 605 338 2461",
    "sg:postcode":"57104",
    "sg:province":"SD",
    "sg:tags":[
        "trucking"
    ],
    "sg:website":"www.bultsmatrucking.com",
    "wof:name":"Lloyd Bultsma Trucking",
    "wof:placetype":"venue"
},
  "geometry": {"coordinates":[-96.745594,43.569015],"type":"Point"}
}