{
  "type": "Feature",
  "properties": {
    "iso:country":"US",
    "sg:address":"301 State Hwy 34",
    "sg:city":"Fort Pierre",
    "sg:classifiers":[
        {
            "category":"Wholesale",
            "subcategory":"Machinery & Supplies",
            "type":"Manufacturing & Wholesale Goods"
        }
    ],
    "sg:phone":"+1 605 223 9506",
    "sg:postcode":"57532",
    "sg:province":"SD",
    "sg:tags":[
        "contractor"
    ],
    "wof:name":"Morris Supply",
    "wof:placetype":"venue"
},
  "geometry": {"coordinates":[-100.384072,44.370357],"type":"Point"}
}