{
  "type": "Feature",
  "properties": {
    "iso:country":"US",
    "sg:address":"121 Main St",
    "sg:city":"Mission",
    "sg:classifiers":[
        {
            "category":"Government",
            "subcategory":"Office",
            "type":"Public Place"
        }
    ],
    "sg:phone":"+1 605 856 4499",
    "sg:postcode":"57551",
    "sg:province":"SD",
    "sg:tags":[
        "city",
        "taxation"
    ],
    "wof:name":"Mission City Auditor",
    "wof:placetype":"venue"
},
  "geometry": {"coordinates":[-101.733216,43.175039],"type":"Point"}
}