{
  "type": "Feature",
  "properties": {
    "addr:full":"102 Main St Henry SD 57243",
    "addr:housenumber":"102",
    "addr:postcode":"57243",
    "addr:street":"Main St",
    "iso:country":"US",
    "sg:address":"102 Main St",
    "sg:city":"Henry",
    "sg:classifiers":[
        {
            "category":"Personal",
            "subcategory":"Beauty Salon",
            "type":"Services"
        }
    ],
    "sg:phone":"+1 605 532 3474",
    "sg:postcode":"57243",
    "sg:province":"SD",
    "sg:tags":[
        "shop"
    ],
    "wof:name":"Perfect Cutting Edge",
    "wof:placetype":"venue"
},
  "geometry": {"coordinates":[-97.468338,44.879369],"type":"Point"}
}