{
  "type": "Feature",
  "properties": {
    "iso:country":"US",
    "sg:address":"405 E 3rd St",
    "sg:city":"Miller",
    "sg:classifiers":[
        {
            "category":"Building & Trades",
            "subcategory":"Construction",
            "type":"Services"
        }
    ],
    "sg:phone":"+1 605 853 2825",
    "sg:postcode":"57362",
    "sg:province":"SD",
    "sg:tags":[
        "excavating",
        "contractor"
    ],
    "wof:name":"Brad Manning Digging & Septic",
    "wof:placetype":"venue"
},
  "geometry": {"coordinates":[-98.983587,44.518335],"type":"Point"}
}