{
  "type": "Feature",
  "properties": {
    "iso:country":"US",
    "sg:address":"6103 Country Ln N",
    "sg:city":"Aberdeen",
    "sg:classifiers":[
        {
            "category":"Building & Trades",
            "subcategory":"Construction",
            "type":"Services"
        }
    ],
    "sg:phone":"+1 605 226 5975",
    "sg:postcode":"57401",
    "sg:province":"SD",
    "sg:tags":[
        "house",
        "nonresidential"
    ],
    "wof:name":"Full Range Construction",
    "wof:placetype":"venue"
},
  "geometry": {"coordinates":[-98.398225,45.442488],"type":"Point"}
}