{
  "type": "Feature",
  "properties": {
    "addr:full":"716 Main St Webster SD 57274",
    "addr:housenumber":"716",
    "addr:postcode":"57274",
    "addr:street":"Main St",
    "iso:country":"US",
    "sg:address":"716 Main St",
    "sg:city":"Webster",
    "sg:classifiers":[
        {
            "category":"Government",
            "subcategory":"Office",
            "type":"Public Place"
        }
    ],
    "sg:phone":"+1 605 345 4661",
    "sg:postcode":"57274",
    "sg:province":"SD",
    "sg:tags":[
        "federal"
    ],
    "wof:name":"Natural Resources Conservation",
    "wof:placetype":"venue"
},
  "geometry": {"coordinates":[-97.520045,45.333039],"type":"Point"}
}