{
  "type": "Feature",
  "properties": {
    "addr:full":"110 2nd St SW De Smet SD 57231",
    "addr:housenumber":"110",
    "addr:postcode":"57231",
    "addr:street":"2Nd St Sw De Smet",
    "iso:country":"US",
    "sg:address":"110 2nd St SW",
    "sg:city":"De Smet",
    "sg:phone":"+1 605 854 9155",
    "sg:postcode":"57231",
    "sg:province":"SD",
    "sg:tags":[
        "oil"
    ],
    "wof:name":"Rich's Gas & Svc",
    "wof:placetype":"venue"
},
  "geometry": {"coordinates":[-97.549882,44.386308],"type":"Point"}
}