{
  "type": "Feature",
  "properties": {
    "iso:country":"US",
    "sg:address":"680 Main St",
    "sg:city":"Scotland",
    "sg:classifiers":[
        {
            "category":"Wholesale",
            "subcategory":"Machinery & Supplies",
            "type":"Manufacturing & Wholesale Goods"
        }
    ],
    "sg:phone":"+1 605 583 4617",
    "sg:postcode":"57059",
    "sg:province":"SD",
    "sg:tags":[
        "equipment",
        "veterinarian"
    ],
    "wof:name":"Sioux Nation Ag Ctr-Scotland",
    "wof:placetype":"venue"
},
  "geometry": {"coordinates":[-97.720842,43.149657],"type":"Point"}
}