{
  "type": "Feature",
  "properties": {
    "iso:country":"US",
    "sg:address":"46250 218th St",
    "sg:city":"Volga",
    "sg:phone":"+1 605 826 4387",
    "sg:postcode":"57071",
    "sg:province":"SD",
    "sg:tags":[
        "farm",
        "corn",
        "soybean"
    ],
    "wof:name":"Oak Is It Antiques",
    "wof:placetype":"venue"
},
  "geometry": {"coordinates":[-96.94868099999999,44.2249],"type":"Point"}
}