{
  "type": "Feature",
  "properties": {
    "iso:country":"US",
    "sg:address":"2400 W Spruce St",
    "sg:city":"Mitchell",
    "sg:classifiers":[
        {
            "category":"Wholesale",
            "subcategory":"Machinery & Supplies",
            "type":"Manufacturing & Wholesale Goods"
        }
    ],
    "sg:phone":"+1 605 770 7634",
    "sg:postcode":"57301",
    "sg:province":"SD",
    "sg:tags":[
        "trailer"
    ],
    "wof:name":"Decker Sales",
    "wof:placetype":"venue"
},
  "geometry": {"coordinates":[-98.047927,43.687338],"type":"Point"}
}