{
  "type": "Feature",
  "properties": {
    "addr:full":"28533 441st Ave Freeman SD 57029",
    "addr:housenumber":"28533",
    "addr:postcode":"57029",
    "addr:street":"441St Ave",
    "iso:country":"US",
    "sg:address":"28533 441st Ave",
    "sg:city":"Freeman",
    "sg:phone":"+1 605 327 3462",
    "sg:postcode":"57029",
    "sg:province":"SD",
    "sg:tags":[
        "farm",
        "corn",
        "soybean"
    ],
    "wof:name":"Tyrone Preheim",
    "wof:placetype":"venue"
},
  "geometry": {"coordinates":[-97.37847600000001,43.25163],"type":"Point"}
}