{
  "type": "Feature",
  "properties": {
    "addr:full":"430 5th St Alexandria SD 57311",
    "addr:housenumber":"430",
    "addr:postcode":"57311",
    "addr:street":"5Th St",
    "iso:country":"US",
    "sg:address":"430 5th St",
    "sg:city":"Alexandria",
    "sg:classifiers":[
        {
            "category":"Freight",
            "type":"Transportation"
        }
    ],
    "sg:phone":"+1 605 239 4767",
    "sg:postcode":"57311",
    "sg:province":"SD",
    "sg:tags":[
        "frozen",
        "food",
        "locker",
        "plant"
    ],
    "wof:name":"Alexandria Locker",
    "wof:placetype":"venue"
},
  "geometry": {"coordinates":[-97.782479,43.654536],"type":"Point"}
}