{
  "type": "Feature",
  "properties": {
    "iso:country":"US",
    "sg:address":"825 10th St NW",
    "sg:city":"Watertown",
    "sg:classifiers":[
        {
            "category":"Restaurant",
            "type":"Food & Drink"
        }
    ],
    "sg:phone":"+1 605 882 1611",
    "sg:postcode":"57201",
    "sg:province":"SD",
    "wof:name":"Stockman's Cafe",
    "wof:placetype":"venue"
},
  "geometry": {"coordinates":[-97.131906,44.911678],"type":"Point"}
}