{
  "type": "Feature",
  "properties": {
    "iso:country":"US",
    "sg:address":"101 US Hwy 12",
    "sg:city":"Webster",
    "sg:classifiers":[
        {
            "category":"Retail",
            "subcategory":"Auto Repair",
            "type":"Services"
        }
    ],
    "sg:phone":"+1 605 345 3411",
    "sg:postcode":"57274",
    "sg:province":"SD",
    "sg:tags":[
        "body",
        "automobile",
        "painting"
    ],
    "wof:name":"Sinner Auto Body Co",
    "wof:placetype":"venue"
},
  "geometry": {"coordinates":[-97.518261,45.340987],"type":"Point"}
}