{
  "type": "Feature",
  "properties": {
    "iso:country":"US",
    "sg:address":"609 Main St",
    "sg:city":"Rapid City",
    "sg:classifiers":[
        {
            "category":"Restaurant",
            "type":"Food & Drink"
        }
    ],
    "sg:phone":"+1 605 341 3088",
    "sg:postcode":"57701",
    "sg:province":"SD",
    "wof:name":"Ristorante Marsala",
    "wof:placetype":"venue"
},
  "geometry": {"coordinates":[-103.228737,44.081266],"type":"Point"}
}