{
  "type": "Feature",
  "properties": {
    "addr:full":"918 S Minnesota Ave Sioux Falls SD 57104",
    "addr:housenumber":"918",
    "addr:postcode":"57104",
    "addr:street":"S Minnesota Ave",
    "iso:country":"US",
    "sg:address":"918 S Minnesota Ave",
    "sg:city":"Sioux Falls",
    "sg:classifiers":[
        {
            "category":"Retail",
            "subcategory":"Auto Repair",
            "type":"Services"
        }
    ],
    "sg:phone":"+1 605 332 8296",
    "sg:postcode":"57104",
    "sg:province":"SD",
    "sg:tags":[
        "glass"
    ],
    "wof:name":"Auto Glass Center",
    "wof:placetype":"venue"
},
  "geometry": {"coordinates":[-96.73119800000001,43.536887],"type":"Point"}
}