{
  "type": "Feature",
  "properties": {
    "iso:country":"US",
    "sg:address":"12629 384th Ave",
    "sg:city":"Aberdeen",
    "sg:classifiers":[
        {
            "category":"Manufacturing",
            "subcategory":"Tools & Machinery",
            "type":"Manufacturing & Wholesale Goods"
        }
    ],
    "sg:phone":"+1 605 225 1803",
    "sg:postcode":"57401",
    "sg:province":"SD",
    "sg:tags":[
        "farm",
        "equipment"
    ],
    "wof:name":"Crawford MS & F",
    "wof:placetype":"venue"
},
  "geometry": {"coordinates":[-98.556951,45.557136],"type":"Point"}
}