{
  "type": "Feature",
  "properties": {
    "addr:full":"1516 N Broadway Watertown SD 57201",
    "addr:housenumber":"1516",
    "addr:postcode":"57201",
    "addr:street":"N Broadway",
    "iso:country":"US",
    "sg:address":"1516 N Broadway",
    "sg:city":"Watertown",
    "sg:classifiers":[
        {
            "category":"Real Estate",
            "subcategory":"Real Estate Operator",
            "type":"Services"
        }
    ],
    "sg:phone":"+1 605 882 0721",
    "sg:postcode":"57201",
    "sg:province":"SD",
    "sg:tags":[
        "property",
        "lessor"
    ],
    "wof:name":"David Sueltz",
    "wof:placetype":"venue"
},
  "geometry": {"coordinates":[-97.113496,44.919942],"type":"Point"}
}