{
  "type": "Feature",
  "properties": {
    "iso:country":"US",
    "sg:address":"506 S Wilson St",
    "sg:city":"Aberdeen",
    "sg:classifiers":[
        {
            "category":"Personal",
            "type":"Services"
        }
    ],
    "sg:phone":"+1 605 229 5945",
    "sg:postcode":"57401",
    "sg:province":"SD",
    "sg:tags":[
        "welcoming",
        "newcomer",
        "for"
    ],
    "wof:name":"Hospitality Builders Inc",
    "wof:placetype":"venue"
},
  "geometry": {"coordinates":[-98.461629,45.460139],"type":"Point"}
}