{
  "type": "Feature",
  "properties": {
    "addr:full":"262 Federal Ave Rapid City SD 57702",
    "addr:housenumber":"262",
    "addr:postcode":"57702",
    "addr:street":"Federal Ave",
    "iso:country":"US",
    "sg:address":"262 Federal Ave",
    "sg:city":"Rapid City",
    "sg:classifiers":[
        {
            "category":"Professional",
            "type":"Services"
        }
    ],
    "sg:phone":"+1 605 348 0084",
    "sg:postcode":"57702",
    "sg:province":"SD",
    "wof:name":"Pkl Corp",
    "wof:placetype":"venue"
},
  "geometry": {"coordinates":[-103.274103,44.084236],"type":"Point"}
}