{
  "type": "Feature",
  "properties": {
    "iso:country":"US",
    "sg:address":"3675 Sheridan Lake Rd",
    "sg:city":"Rapid City",
    "sg:classifiers":[
        {
            "category":"Shopping",
            "subcategory":"Bicycles & Sporting Goods",
            "type":"Retail Goods"
        }
    ],
    "sg:phone":"+1 605 342 4845",
    "sg:postcode":"57702",
    "sg:province":"SD",
    "wof:name":"Daryls Pro Shop",
    "wof:placetype":"venue"
},
  "geometry": {"coordinates":[-103.267852,44.046455],"type":"Point"}
}