{
  "type": "Feature",
  "properties": {
    "addr:full":"11938 397th Ave Columbia SD 57433",
    "addr:housenumber":"11938",
    "addr:postcode":"57433",
    "addr:street":"397Th Ave",
    "iso:country":"US",
    "sg:address":"11938 397th Ave",
    "sg:city":"Columbia",
    "sg:phone":"+1 605 396 2680",
    "sg:postcode":"57433",
    "sg:province":"SD",
    "sg:tags":[
        "farm",
        "wheat",
        "soybean"
    ],
    "wof:name":"Kenneth Sieber",
    "wof:placetype":"venue"
},
  "geometry": {"coordinates":[-98.290059,45.655722],"type":"Point"}
}