{
  "type": "Feature",
  "properties": {
    "iso:country":"US",
    "sg:address":"25758 Packard Ln",
    "sg:city":"Renner",
    "sg:classifiers":[
        {
            "category":"Health Services",
            "subcategory":"Medical Lab",
            "type":"Services"
        }
    ],
    "sg:phone":"+1 605 543 5079",
    "sg:postcode":"57055",
    "sg:province":"SD",
    "sg:tags":[
        "laboratory",
        "dental"
    ],
    "wof:name":"Precision Dental Lab Inc",
    "wof:placetype":"venue"
},
  "geometry": {"coordinates":[-96.752652,43.651335],"type":"Point"}
}