{
  "type": "Feature",
  "properties": {
    "iso:country":"US",
    "sg:address":"3333 W Chicago St",
    "sg:city":"Rapid City",
    "sg:classifiers":[
        {
            "category":"Organizations",
            "subcategory":"Religious Organization",
            "type":"Services"
        }
    ],
    "sg:phone":"+1 605 342 9000",
    "sg:postcode":"57702",
    "sg:province":"SD",
    "sg:website":"www.southcanyonbaptist.org",
    "wof:name":"South Canyon Baptist Church",
    "wof:placetype":"venue"
},
  "geometry": {"coordinates":[-103.275414,44.085676],"type":"Point"}
}