{
  "type": "Feature",
  "properties": {
    "addr:full":"2020 Jackson Blvd Rapid City SD 57702",
    "addr:housenumber":"2020",
    "addr:postcode":"57702",
    "addr:street":"Jackson Blvd",
    "iso:country":"US",
    "sg:address":"2020 Jackson Blvd",
    "sg:city":"Rapid City",
    "sg:classifiers":[
        {
            "category":"Banks & Credit Unions",
            "subcategory":"Investment Brokerage",
            "type":"Services"
        }
    ],
    "sg:phone":"+1 605 348 6050",
    "sg:postcode":"57702",
    "sg:province":"SD",
    "sg:tags":[
        "consultant",
        "planning",
        "financial"
    ],
    "sg:website":"www.waddell.com",
    "wof:name":"Waddell & Reed Inc",
    "wof:placetype":"venue"
},
  "geometry": {"coordinates":[-103.253472,44.074071],"type":"Point"}
}