{
  "type": "Feature",
  "properties": {
    "iso:country":"US",
    "sg:address":"202 S Main St",
    "sg:city":"Aberdeen",
    "sg:classifiers":[
        {
            "category":"Building & Trades",
            "subcategory":"Construction",
            "type":"Services"
        }
    ],
    "sg:phone":"+1 605 229 6833",
    "sg:postcode":"57401",
    "sg:province":"SD",
    "sg:tags":[
        "heavy"
    ],
    "wof:name":"Sandmeier Construction Inc",
    "wof:placetype":"venue"
},
  "geometry": {"coordinates":[-98.488114,45.463084],"type":"Point"}
}