{
  "type": "Feature",
  "properties": {
    "iso:country":"US",
    "sg:address":"510 West Blvd",
    "sg:city":"Rapid City",
    "sg:classifiers":[
        {
            "category":"Personal",
            "subcategory":"Beauty Salon",
            "type":"Services"
        }
    ],
    "sg:phone":"+1 605 343 4168",
    "sg:postcode":"57701",
    "sg:province":"SD",
    "wof:name":"Hair Affair",
    "wof:placetype":"venue"
},
  "geometry": {"coordinates":[-103.234762,44.081338],"type":"Point"}
}