{
  "type": "Feature",
  "properties": {
    "iso:country":"US",
    "sg:address":"424 S Henry St",
    "sg:city":"Pierre",
    "sg:classifiers":[
        {
            "category":"Building & Trades",
            "subcategory":"Plumbing",
            "type":"Services"
        }
    ],
    "sg:phone":"+1 605 224 5893",
    "sg:postcode":"57501",
    "sg:province":"SD",
    "sg:tags":[
        "conditioning",
        "air",
        "system",
        "contractor"
    ],
    "wof:name":"Dakota Refrigeration Heating",
    "wof:placetype":"venue"
},
  "geometry": {"coordinates":[-100.359523,44.366947],"type":"Point"}
}