{
  "type": "Feature",
  "properties": {
    "iso:country":"US",
    "sg:address":"2310 S Louise Ave",
    "sg:city":"Sioux Falls",
    "sg:classifiers":[
        {
            "category":"Restaurant",
            "type":"Food & Drink"
        }
    ],
    "sg:menulink":"http://www.allmenus.com/sd/sioux-falls/105062-carinos-italian-grill/menu/",
    "sg:phone":"+1 605 361 7222",
    "sg:postcode":"57106",
    "sg:province":"SD",
    "sg:tags":[
        "american",
        "italian"
    ],
    "wof:name":"Carino's Italian Grill",
    "wof:placetype":"venue"
},
  "geometry": {"coordinates":[-96.77831399999999,43.52689],"type":"Point"}
}