{
  "type": "Feature",
  "properties": {
    "iso:country":"US",
    "sg:address":"24506 461st Ave",
    "sg:city":"Colton",
    "sg:classifiers":[
        {
            "category":"Farming",
            "subcategory":"Farm",
            "type":"Manufacturing & Wholesale Goods"
        }
    ],
    "sg:phone":"+1 605 446 3969",
    "sg:postcode":"57018",
    "sg:province":"SD",
    "sg:tags":[
        "crop",
        "general"
    ],
    "wof:name":"Dean Baumberger",
    "wof:placetype":"venue"
},
  "geometry": {"coordinates":[-96.990632,43.833111],"type":"Point"}
}