{
  "type": "Feature",
  "properties": {
    "addr:full":"2503 Maple Ave Rapid City SD 57701",
    "addr:housenumber":"2503",
    "addr:postcode":"57701",
    "addr:street":"Maple Ave",
    "iso:country":"US",
    "sg:address":"2503 Maple Ave",
    "sg:city":"Rapid City",
    "sg:classifiers":[
        {
            "category":"Retail",
            "subcategory":"Portrait Studio",
            "type":"Services"
        }
    ],
    "sg:phone":"+1 605 343 8515",
    "sg:postcode":"57701",
    "sg:province":"SD",
    "sg:tags":[
        "photographer"
    ],
    "wof:name":"Monte Walter Photography",
    "wof:placetype":"venue"
},
  "geometry": {"coordinates":[-103.21414900000001,44.061485],"type":"Point"}
}