{
  "type": "Feature",
  "properties": {
    "iso:country":"US",
    "sg:address":"910 15th St SW",
    "sg:city":"Huron",
    "sg:classifiers":[
        {
            "category":"Real Estate",
            "subcategory":"Real Estate Operator",
            "type":"Services"
        }
    ],
    "sg:phone":"+1 605 352 7012",
    "sg:postcode":"57350",
    "sg:province":"SD",
    "sg:tags":[
        "building",
        "apartment"
    ],
    "wof:name":"Huron Apartments",
    "wof:placetype":"venue"
},
  "geometry": {"coordinates":[-98.230513,44.34888],"type":"Point"}
}