{
  "type": "Feature",
  "properties": {
    "addr:full":"1508 Sioux Trl Brookings SD 57006",
    "addr:housenumber":"1508",
    "addr:postcode":"57006",
    "addr:street":"Sioux Trl",
    "iso:country":"US",
    "sg:address":"1508 Sioux Trl",
    "sg:city":"Brookings",
    "sg:classifiers":[
        {
            "category":"Professional",
            "subcategory":"Business Services",
            "type":"Services"
        }
    ],
    "sg:phone":"+1 605 692 1592",
    "sg:postcode":"57006",
    "sg:province":"SD",
    "wof:name":"Aamots Auctioners Farms",
    "wof:placetype":"venue"
},
  "geometry": {"coordinates":[-96.800656,44.288825],"type":"Point"}
}