{
  "type": "Feature",
  "properties": {
    "iso:country":"US",
    "sg:address":"307 E 12th St",
    "sg:city":"Sioux Falls",
    "sg:classifiers":[
        {
            "category":"Professional",
            "subcategory":"Accounting & Tax Preparation",
            "type":"Services"
        }
    ],
    "sg:phone":"+1 605 338 5590",
    "sg:postcode":"57104",
    "sg:province":"SD",
    "sg:tags":[
        "return"
    ],
    "wof:name":"Jj Cards & More",
    "wof:placetype":"venue"
},
  "geometry": {"coordinates":[-96.722356,43.543386],"type":"Point"}
}