{
  "type": "Feature",
  "properties": {
    "addr:full":"1020 Empire Mall Sioux Falls SD 57106",
    "addr:housenumber":"1020",
    "addr:postcode":"57106",
    "addr:street":"Empire Mall",
    "iso:country":"US",
    "sg:address":"1020 Empire Mall",
    "sg:city":"Sioux Falls",
    "sg:classifiers":[
        {
            "category":"Utilities",
            "subcategory":"Mobile Phone",
            "type":"Services"
        }
    ],
    "sg:phone":"+1 605 361 4397",
    "sg:postcode":"57106",
    "sg:province":"SD",
    "sg:tags":[
        "telephone",
        "cellular"
    ],
    "wof:name":"Verizon Wireless",
    "wof:placetype":"venue"
},
  "geometry": {"coordinates":[-96.77479599999999,43.514226],"type":"Point"}
}