{
  "type": "Feature",
  "properties": {
    "iso:country":"US",
    "sg:address":"2050 W Main St",
    "sg:city":"Rapid City",
    "sg:classifiers":[
        {
            "category":"Recreation",
            "type":"Entertainment"
        }
    ],
    "sg:phone":"+1 605 431 7889",
    "sg:postcode":"57702",
    "sg:province":"SD",
    "sg:tags":[
        "instruction",
        "yoga"
    ],
    "sg:website":"www.rapidcityyoga.com",
    "wof:name":"Yoga Studio",
    "wof:placetype":"venue"
},
  "geometry": {"coordinates":[-103.254745,44.081528],"type":"Point"}
}