{
  "type": "Feature",
  "properties": {
    "addr:full":"201 Main Ave Geddes SD 57342",
    "addr:housenumber":"201",
    "addr:postcode":"57342",
    "addr:street":"Main Ave",
    "iso:country":"US",
    "sg:address":"201 Main Ave",
    "sg:city":"Geddes",
    "sg:classifiers":[
        {
            "category":"Retail",
            "subcategory":"Repair Shop",
            "type":"Services"
        }
    ],
    "sg:phone":"+1 605 337 2200",
    "sg:postcode":"57342",
    "sg:province":"SD",
    "sg:tags":[
        "related"
    ],
    "wof:name":"Darwin's Repair",
    "wof:placetype":"venue"
},
  "geometry": {"coordinates":[-98.69559099999999,43.254452],"type":"Point"}
}