{
  "type": "Feature",
  "properties": {
    "addr:full":"800 E 48th St Sioux Falls SD 57104",
    "addr:housenumber":"800",
    "addr:postcode":"57104",
    "addr:street":"E 48Th St",
    "iso:country":"US",
    "sg:address":"800 E 48th St",
    "sg:city":"Sioux Falls",
    "sg:classifiers":[
        {
            "category":"Wholesale",
            "subcategory":"Machinery & Supplies",
            "type":"Manufacturing & Wholesale Goods"
        }
    ],
    "sg:phone":"+1 605 335 2292",
    "sg:postcode":"57104",
    "sg:province":"SD",
    "sg:tags":[
        "janitor"
    ],
    "sg:website":"www.hillyard.com",
    "wof:name":"Hillyard",
    "wof:placetype":"venue"
},
  "geometry": {"coordinates":[-96.715512,43.589403],"type":"Point"}
}