{
  "type": "Feature",
  "properties": {
    "iso:country":"US",
    "sg:address":"1304 Main St",
    "sg:city":"Sturgis",
    "sg:classifiers":[
        {
            "category":"Bars & Pubs",
            "type":"Food & Drink"
        }
    ],
    "sg:phone":"+1 605 423 9904",
    "sg:postcode":"57785",
    "sg:province":"SD",
    "wof:name":"One Eyed Jack Saloon",
    "wof:placetype":"venue"
},
  "geometry": {"coordinates":[-103.515495,44.414534],"type":"Point"}
}