{
  "type": "Feature",
  "properties": {
    "iso:country":"US",
    "sg:address":"907 Jackson Blvd",
    "sg:city":"Rapid City",
    "sg:classifiers":[
        {
            "category":"Health Services",
            "subcategory":"Doctor",
            "type":"Services"
        }
    ],
    "sg:phone":"+1 605 388 0930",
    "sg:postcode":"57702",
    "sg:province":"SD",
    "sg:tags":[
        "dentist"
    ],
    "sg:website":"www.dentalimplantologist.com",
    "wof:name":"Soderstrom Implant Dentistry",
    "wof:placetype":"venue"
},
  "geometry": {"coordinates":[-103.250323,44.077895],"type":"Point"}
}