{
  "type": "Feature",
  "properties": {
    "addr:full":"26908 Tallgrass Ave Sioux Falls SD 57108",
    "addr:postcode":"26908;57108",
    "addr:street":"Tallgrass Ave",
    "iso:country":"US",
    "sg:address":"26908 Tallgrass Ave",
    "sg:city":"Sioux Falls",
    "sg:classifiers":[
        {
            "category":"Communications",
            "subcategory":"Radio Station",
            "type":"Services"
        }
    ],
    "sg:phone":"+1 605 339 1270",
    "sg:postcode":"57108",
    "sg:province":"SD",
    "sg:tags":[
        "company",
        "broadcasting"
    ],
    "sg:website":"www.knwc.org",
    "wof:name":"KNWC AM & FM",
    "wof:placetype":"venue"
},
  "geometry": {"coordinates":[-96.787119,43.488658],"type":"Point"}
}