{
  "type": "Feature",
  "properties": {
    "iso:country":"US",
    "sg:address":"15 Dakota St",
    "sg:city":"Aberdeen",
    "sg:classifiers":[
        {
            "category":"Professional",
            "subcategory":"Business Services",
            "type":"Services"
        }
    ],
    "sg:phone":"+1 605 225 8432",
    "sg:postcode":"57401",
    "sg:province":"SD",
    "wof:name":"Aberdeen Grain Inspection Inc",
    "wof:placetype":"venue"
},
  "geometry": {"coordinates":[-98.474555,45.46578],"type":"Point"}
}