{
  "type": "Feature",
  "properties": {
    "iso:country":"US",
    "sg:address":"300 S Prairie St",
    "sg:city":"Worthing",
    "sg:classifiers":[
        {
            "category":"Organizations",
            "subcategory":"Religious Organization",
            "type":"Services"
        }
    ],
    "sg:phone":"+1 605 372 4743",
    "sg:postcode":"57077",
    "sg:province":"SD",
    "sg:tags":[
        "church"
    ],
    "wof:name":"St Edward's Catholic Church",
    "wof:placetype":"venue"
},
  "geometry": {"coordinates":[-96.767117,43.327647],"type":"Point"}
}