{
  "type": "Feature",
  "properties": {
    "iso:country":"US",
    "sg:address":"400 E 40th St",
    "sg:city":"Sioux Falls",
    "sg:classifiers":[
        {
            "category":"Building & Trades",
            "subcategory":"Construction",
            "type":"Services"
        }
    ],
    "sg:phone":"+1 605 331 6910",
    "sg:postcode":"57104",
    "sg:province":"SD",
    "sg:tags":[
        "steel",
        "warehouse",
        "industrial",
        "contractor"
    ],
    "wof:name":"Daren Construction Inc",
    "wof:placetype":"venue"
},
  "geometry": {"coordinates":[-96.722568,43.585589],"type":"Point"}
}