{
  "type": "Feature",
  "properties": {
    "addr:full":"710 6th Ave SW Aberdeen SD 57401",
    "addr:housenumber":"710",
    "addr:postcode":"57401",
    "addr:street":"6Th Ave Sw",
    "iso:country":"US",
    "sg:address":"710 6th Ave SW",
    "sg:city":"Aberdeen",
    "sg:classifiers":[
        {
            "category":"Wholesale",
            "subcategory":"Electrical",
            "type":"Manufacturing & Wholesale Goods"
        }
    ],
    "sg:phone":"+1 605 229 5284",
    "sg:postcode":"57401",
    "sg:province":"SD",
    "sg:tags":[
        "electric",
        "motor"
    ],
    "wof:name":"J T Electric Motor Svc Inc",
    "wof:placetype":"venue"
},
  "geometry": {"coordinates":[-98.499487,45.459509],"type":"Point"}
}