{
  "type": "Feature",
  "properties": {
    "iso:country":"US",
    "sg:address":"1505 W 7th St",
    "sg:city":"Webster",
    "sg:classifiers":[
        {
            "category":"Freight",
            "type":"Transportation"
        }
    ],
    "sg:phone":"+1 605 345 3250",
    "sg:postcode":"57274",
    "sg:province":"SD",
    "wof:name":"P&K Transportation Inc",
    "wof:placetype":"venue"
},
  "geometry": {"coordinates":[-97.530159,45.344547],"type":"Point"}
}