{
  "type": "Feature",
  "properties": {
    "iso:country":"US",
    "sg:address":"616 Mount Rushmore Rd",
    "sg:city":"Custer",
    "sg:classifiers":[
        {
            "category":"Home & Garden",
            "subcategory":"Furniture",
            "type":"Retail Goods"
        }
    ],
    "sg:phone":"+1 605 673 2595",
    "sg:postcode":"57730",
    "sg:province":"SD",
    "sg:tags":[
        "builder",
        "custom"
    ],
    "wof:name":"Gold Camp Home & Timber Supply",
    "wof:placetype":"venue"
},
  "geometry": {"coordinates":[-103.598054,43.766746],"type":"Point"}
}