{
  "type": "Feature",
  "properties": {
    "iso:country":"US",
    "sg:address":"1100 4th Ave E",
    "sg:city":"Mobridge",
    "sg:classifiers":[
        {
            "category":"Real Estate",
            "subcategory":"Real Estate Agent",
            "type":"Services"
        }
    ],
    "sg:phone":"+1 605 845 3560",
    "sg:postcode":"57601",
    "sg:province":"SD",
    "wof:name":"W M Richardson",
    "wof:placetype":"venue"
},
  "geometry": {"coordinates":[-100.428092,45.543585],"type":"Point"}
}