{
  "type": "Feature",
  "properties": {
    "iso:country":"US",
    "sg:address":"1200 E 57th St",
    "sg:city":"Sioux Falls",
    "sg:classifiers":[
        {
            "category":"Insurance",
            "subcategory":"Insurance Agent",
            "type":"Services"
        }
    ],
    "sg:phone":"+1 605 339 2990",
    "sg:postcode":"57108",
    "sg:province":"SD",
    "wof:name":"State Farm Insurance",
    "wof:placetype":"venue"
},
  "geometry": {"coordinates":[-96.708395,43.500364],"type":"Point"}
}