{
  "type": "Feature",
  "properties": {
    "iso:country":"US",
    "sg:address":"4900 S Minnesota Ave",
    "sg:city":"Sioux Falls",
    "sg:classifiers":[
        {
            "category":"Manufacturing",
            "subcategory":"Printing",
            "type":"Manufacturing & Wholesale Goods"
        }
    ],
    "sg:phone":"+1 605 367 1770",
    "sg:postcode":"57108",
    "sg:province":"SD",
    "sg:tags":[
        "lithographic",
        "commercial"
    ],
    "wof:name":"One Sheet Printers",
    "wof:placetype":"venue"
},
  "geometry": {"coordinates":[-96.72955,43.498412],"type":"Point"}
}