{
  "type": "Feature",
  "properties": {
    "iso:country":"US",
    "sg:address":"2105 S Minnesota Ave",
    "sg:city":"Sioux Falls",
    "sg:classifiers":[
        {
            "category":"Shopping",
            "subcategory":"Florist",
            "type":"Retail Goods"
        }
    ],
    "sg:phone":"+1 605 336 2758",
    "sg:postcode":"57105",
    "sg:province":"SD",
    "wof:name":"Anderson's & Kelley's Flowers",
    "wof:placetype":"venue"
},
  "geometry": {"coordinates":[-96.731345,43.524873],"type":"Point"}
}