{
  "type": "Feature",
  "properties": {
    "iso:country":"US",
    "sg:address":"1310 N Maple Ave",
    "sg:city":"Rapid City",
    "sg:classifiers":[
        {
            "category":"Education",
            "subcategory":"Junior College",
            "type":"Public Place"
        }
    ],
    "sg:phone":"+1 605 342 6123",
    "sg:postcode":"57701",
    "sg:province":"SD",
    "sg:tags":[
        "technical",
        "institute"
    ],
    "wof:name":"Institute For Ministry Dev",
    "wof:placetype":"venue"
},
  "geometry": {"coordinates":[-103.211574,44.097089],"type":"Point"}
}