{
  "type": "Feature",
  "properties": {
    "iso:country":"US",
    "sg:address":"402 4th St",
    "sg:city":"Chester",
    "sg:classifiers":[
        {
            "category":"Home & Garden",
            "subcategory":"Hardware",
            "type":"Retail Goods"
        }
    ],
    "sg:phone":"+1 605 489 2121",
    "sg:postcode":"57016",
    "sg:province":"SD",
    "wof:name":"Chester Hardware",
    "wof:placetype":"venue"
},
  "geometry": {"coordinates":[-96.927677,43.894834],"type":"Point"}
}