{
  "type": "Feature",
  "properties": {
    "iso:country":"US",
    "sg:address":"26285 389th Ave",
    "sg:city":"Stickney",
    "sg:classifiers":[
        {
            "category":"Freight",
            "type":"Transportation"
        }
    ],
    "sg:phone":"+1 605 732 4422",
    "sg:postcode":"57375",
    "sg:province":"SD",
    "sg:tags":[
        "operator",
        "local",
        "trucking"
    ],
    "wof:name":"Vernon Punt Trucking",
    "wof:placetype":"venue"
},
  "geometry": {"coordinates":[-98.423077,43.572874],"type":"Point"}
}