{
  "type": "Feature",
  "properties": {
    "iso:country":"US",
    "sg:address":"305 N Boyd St",
    "sg:city":"Aberdeen",
    "sg:classifiers":[
        {
            "category":"Retail",
            "subcategory":"Laundry & Dry Cleaning",
            "type":"Services"
        }
    ],
    "sg:phone":"+1 605 226 1983",
    "sg:postcode":"57401",
    "sg:province":"SD",
    "wof:name":"Aberdeen Carpet Cleaning",
    "wof:placetype":"venue"
},
  "geometry": {"coordinates":[-98.468753,45.470903],"type":"Point"}
}