{
  "type": "Feature",
  "properties": {
    "addr:full":"2650 Jackson Blvd Rapid City SD 57702",
    "addr:housenumber":"2650",
    "addr:postcode":"57702",
    "addr:street":"Jackson Blvd",
    "iso:country":"US",
    "sg:address":"2650 Jackson Blvd",
    "sg:city":"Rapid City",
    "sg:classifiers":[
        {
            "category":"Organizations",
            "subcategory":"Religious Organization",
            "type":"Services"
        }
    ],
    "sg:phone":"+1 605 341 9090",
    "sg:postcode":"57702",
    "sg:province":"SD",
    "wof:name":"Black Hills Community Church",
    "wof:placetype":"venue"
},
  "geometry": {"coordinates":[-103.26367,44.06968],"type":"Point"}
}