{
  "type": "Feature",
  "properties": {
    "iso:country":"US",
    "sg:address":"300 W 3rd St",
    "sg:city":"Delmont",
    "sg:classifiers":[
        {
            "category":"Organizations",
            "subcategory":"Religious Organization",
            "type":"Services"
        }
    ],
    "sg:phone":"+1 605 724 2168",
    "sg:postcode":"57330",
    "sg:province":"SD",
    "sg:tags":[
        "church"
    ],
    "wof:name":"Bethany United Ch Of Christ",
    "wof:placetype":"venue"
},
  "geometry": {"coordinates":[-98.165084,43.265555],"type":"Point"}
}