{
  "type": "Feature",
  "properties": {
    "iso:country":"US",
    "sg:address":"538 Mount Rushmore Rd",
    "sg:city":"Custer",
    "sg:classifiers":[
        {
            "category":"Freight",
            "type":"Transportation"
        }
    ],
    "sg:phone":"+1 605 673 3687",
    "sg:postcode":"57730",
    "sg:province":"SD",
    "wof:name":"Southern Hills Trnsprtn Svc",
    "wof:placetype":"venue"
},
  "geometry": {"coordinates":[-103.599293,43.766432],"type":"Point"}
}