{
  "type": "Feature",
  "properties": {
    "addr:full":"3311 Dover St Rapid City SD 57702",
    "addr:housenumber":"3311",
    "addr:postcode":"57702",
    "addr:street":"Dover St",
    "iso:country":"US",
    "sg:address":"3311 Dover St",
    "sg:city":"Rapid City",
    "sg:classifiers":[
        {
            "category":"Real Estate",
            "subcategory":"Developer",
            "type":"Services"
        }
    ],
    "sg:phone":"+1 605 343 8301",
    "sg:postcode":"57702",
    "sg:province":"SD",
    "wof:name":"L J Enterprise",
    "wof:placetype":"venue"
},
  "geometry": {"coordinates":[-103.275904,44.067784],"type":"Point"}
}