{
  "type": "Feature",
  "properties": {
    "iso:country":"US",
    "sg:address":"24882 397th Ave",
    "sg:city":"Mount Vernon",
    "sg:phone":"+1 605 236 5679",
    "sg:postcode":"57363",
    "sg:province":"SD",
    "sg:tags":[
        "wheat",
        "beef",
        "farm",
        "cash",
        "grain",
        "cattle",
        "feedlot"
    ],
    "wof:name":"Mark A Meier Farm",
    "wof:placetype":"venue"
},
  "geometry": {"coordinates":[-98.265756,43.777941],"type":"Point"}
}