{
  "type": "Feature",
  "properties": {
    "iso:country":"US",
    "sg:address":"22143 430th Ave",
    "sg:city":"Carthage",
    "sg:phone":"+1 605 772 4198",
    "sg:postcode":"57323",
    "sg:province":"SD",
    "sg:tags":[
        "farm",
        "corn",
        "soybean"
    ],
    "wof:name":"Ronald Moe",
    "wof:placetype":"venue"
},
  "geometry": {"coordinates":[-97.609616,44.179062],"type":"Point"}
}