{
  "type": "Feature",
  "properties": {
    "addr:full":"220 S Bahnson Ave Sioux Falls SD 57103",
    "addr:housenumber":"220",
    "addr:postcode":"57103",
    "addr:street":"S Bahnson Ave",
    "iso:country":"US",
    "sg:address":"220 S Bahnson Ave",
    "sg:city":"Sioux Falls",
    "sg:classifiers":[
        {
            "category":"Professional",
            "subcategory":"Accounting & Tax Preparation",
            "type":"Services"
        }
    ],
    "sg:phone":"+1 605 275 3940",
    "sg:postcode":"57103",
    "sg:province":"SD",
    "sg:tags":[
        "bookkeeping",
        "general"
    ],
    "wof:name":"Swier Business Svc",
    "wof:placetype":"venue"
},
  "geometry": {"coordinates":[-96.68231299999999,43.545174],"type":"Point"}
}