{
  "type": "Feature",
  "properties": {
    "addr:full":"140 E Jackson Blvd Spearfish SD 57783",
    "addr:housenumber":"140",
    "addr:postcode":"57783",
    "addr:street":"E Jackson Blvd",
    "iso:country":"US",
    "sg:address":"140 E Jackson Blvd",
    "sg:city":"Spearfish",
    "sg:classifiers":[
        {
            "category":"Banks & Credit Unions",
            "subcategory":"Bank",
            "type":"Services"
        }
    ],
    "sg:phone":"+1 605 642 2725",
    "sg:postcode":"57783",
    "sg:province":"SD",
    "sg:website":"www.pioneerbankandtrust.com",
    "wof:name":"Pioneer Bank & Trust",
    "wof:placetype":"venue"
},
  "geometry": {"coordinates":[-103.858322,44.491296],"type":"Point"}
}