{
  "type": "Feature",
  "properties": {
    "iso:country":"US",
    "sg:address":"219 N Main St",
    "sg:city":"Salem",
    "sg:classifiers":[
        {
            "category":"Shopping",
            "subcategory":"Florist",
            "type":"Retail Goods"
        }
    ],
    "sg:phone":"+1 605 425 2459",
    "sg:postcode":"57058",
    "sg:province":"SD",
    "wof:name":"Floral Bokay & Gifts",
    "wof:placetype":"venue"
},
  "geometry": {"coordinates":[-97.387428,43.726248],"type":"Point"}
}