{
  "type": "Feature",
  "properties": {
    "addr:full":"24530 480th Ave Dell Rapids SD 57022",
    "addr:housenumber":"24530",
    "addr:postcode":"57022",
    "addr:street":"480Th Ave",
    "iso:country":"US",
    "sg:address":"24530 480th Ave",
    "sg:city":"Dell Rapids",
    "sg:classifiers":[
        {
            "category":"Farming",
            "subcategory":"Livestock Farm",
            "type":"Manufacturing & Wholesale Goods"
        }
    ],
    "sg:phone":"+1 605 428 5668",
    "sg:postcode":"57022",
    "sg:province":"SD",
    "sg:tags":[
        "hog",
        "or",
        "feedlot"
    ],
    "wof:name":"Rave John",
    "wof:placetype":"venue"
},
  "geometry": {"coordinates":[-96.615837,43.832653],"type":"Point"}
}