{
  "type": "Feature",
  "properties": {
    "addr:full":"44373 256th St Salem SD 57058",
    "addr:housenumber":"44373",
    "addr:postcode":"57058",
    "addr:street":"256Th St",
    "iso:country":"US",
    "sg:address":"44373 256th St",
    "sg:city":"Salem",
    "sg:phone":"+1 605 425 2473",
    "sg:postcode":"57058",
    "sg:province":"SD",
    "sg:tags":[
        "farm",
        "corn"
    ],
    "wof:name":"Hubert Koch",
    "wof:placetype":"venue"
},
  "geometry": {"coordinates":[-97.347392,43.673448],"type":"Point"}
}