{
  "type": "Feature",
  "properties": {
    "iso:country":"US",
    "sg:address":"19875 399th Ave",
    "sg:city":"Huron",
    "sg:phone":"+1 605 352 5539",
    "sg:postcode":"57350",
    "sg:province":"SD",
    "sg:tags":[
        "real",
        "lessor",
        "farm",
        "corn",
        "soybean",
        "property"
    ],
    "wof:name":"Paul Kleinsasser",
    "wof:placetype":"venue"
},
  "geometry": {"coordinates":[-98.23450200000001,44.504759],"type":"Point"}
}