{
  "type": "Feature",
  "properties": {
    "iso:country":"US",
    "sg:address":"1613 S Melanie Ln",
    "sg:city":"Sioux Falls",
    "sg:classifiers":[
        {
            "category":"Freight",
            "type":"Transportation"
        }
    ],
    "sg:phone":"+1 605 376 1064",
    "sg:postcode":"57103",
    "sg:province":"SD",
    "wof:name":"Liben Bros Transport",
    "wof:placetype":"venue"
},
  "geometry": {"coordinates":[-96.675027,43.531045],"type":"Point"}
}