{
  "type": "Feature",
  "properties": {
    "iso:country":"US",
    "sg:address":"606 5th Ave",
    "sg:city":"Wilmot",
    "sg:classifiers":[
        {
            "category":"Social Services",
            "subcategory":"Child Care",
            "type":"Services"
        }
    ],
    "sg:phone":"+1 605 938 4472",
    "sg:postcode":"57279",
    "sg:province":"SD",
    "sg:tags":[
        "day"
    ],
    "wof:name":"Degreef Jennifer Day Care",
    "wof:placetype":"venue"
},
  "geometry": {"coordinates":[-96.861956,45.409674],"type":"Point"}
}