{
  "type": "Feature",
  "properties": {
    "iso:country":"US",
    "sg:address":"5413 W 41st St",
    "sg:city":"Sioux Falls",
    "sg:classifiers":[
        {
            "category":"Home & Garden",
            "subcategory":"Household Appliances",
            "type":"Retail Goods"
        }
    ],
    "sg:phone":"+1 605 361 8926",
    "sg:postcode":"57106",
    "sg:province":"SD",
    "sg:tags":[
        "cleaners",
        "vacuum"
    ],
    "wof:name":"Aerus Electrolux",
    "wof:placetype":"venue"
},
  "geometry": {"coordinates":[-96.792385,43.514735],"type":"Point"}
}