{
  "type": "Feature",
  "properties": {
    "iso:country":"US",
    "sg:address":"127 W Grant St",
    "sg:city":"Spearfish",
    "sg:classifiers":[
        {
            "category":"Recreation",
            "subcategory":"Arcade",
            "type":"Entertainment"
        }
    ],
    "sg:phone":"+1 605 722 7027",
    "sg:postcode":"57783",
    "sg:province":"SD",
    "sg:tags":[
        "casino"
    ],
    "wof:name":"Grant Street Liquor & Casino",
    "wof:placetype":"venue"
},
  "geometry": {"coordinates":[-103.85874099999999,44.487753],"type":"Point"}
}