{
  "type": "Feature",
  "properties": {
    "iso:country":"US",
    "sg:address":"40769 272nd St",
    "sg:city":"Dimock",
    "sg:classifiers":[
        {
            "category":"Farming",
            "subcategory":"Farm",
            "type":"Manufacturing & Wholesale Goods"
        }
    ],
    "sg:phone":"+1 605 928 3080",
    "sg:postcode":"57331",
    "sg:province":"SD",
    "sg:tags":[
        "crop",
        "general"
    ],
    "wof:name":"M & H Hunting Enterprises LLC",
    "wof:placetype":"venue"
},
  "geometry": {"coordinates":[-98.044777,43.441797],"type":"Point"}
}