{
  "type": "Feature",
  "properties": {
    "addr:full":"17763 486th Ave Gary SD 57259",
    "addr:housenumber":"17763",
    "addr:postcode":"57259",
    "addr:street":"486Th Ave",
    "iso:country":"US",
    "sg:address":"17763 486th Ave",
    "sg:city":"Gary",
    "sg:classifiers":[
        {
            "category":"Farming",
            "subcategory":"Livestock Farm",
            "type":"Manufacturing & Wholesale Goods"
        }
    ],
    "sg:phone":"+1 605 272 5212",
    "sg:postcode":"57259",
    "sg:province":"SD",
    "sg:tags":[
        "beef",
        "feedlot",
        "cattle"
    ],
    "wof:name":"Keimig Gurard",
    "wof:placetype":"venue"
},
  "geometry": {"coordinates":[-96.47662099999999,45.069704],"type":"Point"}
}