{
  "type": "Feature",
  "properties": {
    "iso:country":"US",
    "sg:address":"505 12th St SE",
    "sg:city":"Watertown",
    "sg:classifiers":[
        {
            "category":"Banks & Credit Unions",
            "subcategory":"Bank",
            "type":"Services"
        }
    ],
    "sg:phone":"+1 605 882 1034",
    "sg:postcode":"57201",
    "sg:province":"SD",
    "sg:tags":[
        "loan",
        "real estate"
    ],
    "sg:website":"www.americanhm.com",
    "wof:name":"American Home Mortgage",
    "wof:placetype":"venue"
},
  "geometry": {"coordinates":[-97.09764800000001,44.890881],"type":"Point"}
}