{
  "type": "Feature",
  "properties": {
    "iso:country":"US",
    "sg:address":"101 N Commercial St",
    "sg:city":"Clark",
    "sg:classifiers":[
        {
            "category":"Professional",
            "type":"Services"
        }
    ],
    "sg:phone":"+1 605 532 3258",
    "sg:postcode":"57225",
    "sg:province":"SD",
    "sg:tags":[
        "establishment"
    ],
    "wof:name":"Hurley & Assoc",
    "wof:placetype":"venue"
},
  "geometry": {"coordinates":[-97.733268,44.878855],"type":"Point"}
}