{
  "type": "Feature",
  "properties": {
    "iso:country":"US",
    "sg:address":"706 Shannon St",
    "sg:city":"Wallace",
    "sg:classifiers":[
        {
            "category":"Professional",
            "type":"Services"
        }
    ],
    "sg:phone":"+1 605 758 2242",
    "sg:postcode":"57272",
    "sg:province":"SD",
    "sg:tags":[
        "establishment"
    ],
    "wof:name":"Meyer & Meyer",
    "wof:placetype":"venue"
},
  "geometry": {"coordinates":[-97.481965,45.084887],"type":"Point"}
}