{
  "type": "Feature",
  "properties": {
    "iso:country":"US",
    "sg:address":"265 Westshore Dr",
    "sg:city":"North Sioux City",
    "sg:classifiers":[
        {
            "category":"Home & Garden",
            "subcategory":"Building Materials",
            "type":"Retail Goods"
        }
    ],
    "sg:phone":"+1 605 232 3377",
    "sg:postcode":"57049",
    "sg:province":"SD",
    "wof:name":"Artistic Glass",
    "wof:placetype":"venue"
},
  "geometry": {"coordinates":[-96.52672800000001,42.541366],"type":"Point"}
}