{
  "type": "Feature",
  "properties": {
    "iso:country":"US",
    "sg:address":"102 W 5th Ave",
    "sg:city":"Mitchell",
    "sg:classifiers":[
        {
            "category":"Social Services",
            "subcategory":"Child Care",
            "type":"Services"
        }
    ],
    "sg:phone":"+1 605 996 5554",
    "sg:postcode":"57301",
    "sg:province":"SD",
    "sg:tags":[
        "agency",
        "employment"
    ],
    "wof:name":"Complete Career Center Inc",
    "wof:placetype":"venue"
},
  "geometry": {"coordinates":[-98.025578,43.713586],"type":"Point"}
}