{
  "type": "Feature",
  "properties": {
    "iso:country":"US",
    "sg:address":"309 Church Ave",
    "sg:city":"Montrose",
    "sg:classifiers":[
        {
            "category":"Education",
            "subcategory":"School",
            "type":"Public Place"
        }
    ],
    "sg:phone":"+1 605 363 5025",
    "sg:postcode":"57048",
    "sg:province":"SD",
    "wof:name":"Montrose School District 43-2",
    "wof:placetype":"venue"
},
  "geometry": {"coordinates":[-97.186767,43.698733],"type":"Point"}
}