{
  "type": "Feature",
  "properties": {
    "iso:country":"US",
    "sg:address":"12859 404th Ave",
    "sg:city":"Groton",
    "sg:phone":"+1 605 397 8110",
    "sg:postcode":"57445",
    "sg:province":"SD",
    "sg:tags":[
        "farm",
        "corn",
        "wheat",
        "soybean"
    ],
    "wof:name":"Lee Thompson",
    "wof:placetype":"venue"
},
  "geometry": {"coordinates":[-98.14437599999999,45.521778],"type":"Point"}
}