{
  "type": "Feature",
  "properties": {
    "addr:full":"1001 9th Ave SE Watertown SD 57201",
    "addr:housenumber":"1001",
    "addr:postcode":"57201",
    "addr:street":"9Th Ave Se",
    "iso:country":"US",
    "sg:address":"1001 9th Ave SE",
    "sg:city":"Watertown",
    "sg:classifiers":[
        {
            "category":"Restaurant",
            "type":"Food & Drink"
        }
    ],
    "sg:phone":"+1 605 886 3897",
    "sg:postcode":"57201",
    "sg:province":"SD",
    "wof:name":"Angelina's Inc",
    "wof:placetype":"venue"
},
  "geometry": {"coordinates":[-97.102001,44.890071],"type":"Point"}
}