{
  "type": "Feature",
  "properties": {
    "iso:country":"US",
    "sg:address":"3408 S Western Ave",
    "sg:city":"Sioux Falls",
    "sg:classifiers":[
        {
            "category":"Restaurant",
            "type":"Food & Drink"
        }
    ],
    "sg:phone":"+1 605 331 6333",
    "sg:postcode":"57105",
    "sg:province":"SD",
    "sg:tags":[
        "eating"
    ],
    "wof:name":"China Town Buffet",
    "wof:placetype":"venue"
},
  "geometry": {"coordinates":[-96.751019,43.513791],"type":"Point"}
}