{
  "type": "Feature",
  "properties": {
    "iso:country":"US",
    "sg:address":"6011 Ackerman Ln",
    "sg:city":"Black Hawk",
    "sg:classifiers":[
        {
            "category":"Wholesale",
            "subcategory":"Construction Materials",
            "type":"Manufacturing & Wholesale Goods"
        },
        {
            "category":"Home & Garden",
            "subcategory":"Mobile Homes",
            "type":"Retail Goods"
        }
    ],
    "sg:phone":"+1 605 787 9504",
    "sg:postcode":"57718",
    "sg:province":"SD",
    "sg:tags":[
        "parts"
    ],
    "wof:name":"West River Industries Inc",
    "wof:placetype":"venue"
},
  "geometry": {"coordinates":[-103.304965,44.143121],"type":"Point"}
}