{
  "type": "Feature",
  "properties": {
    "iso:country":"US",
    "sg:address":"324 W 41st St",
    "sg:city":"Sioux Falls",
    "sg:classifiers":[
        {
            "category":"Autos & Motor Vehicles",
            "subcategory":"Automobile Sales",
            "type":"Retail Goods"
        }
    ],
    "sg:phone":"+1 605 221 0655",
    "sg:postcode":"57105",
    "sg:province":"SD",
    "sg:tags":[
        "car",
        "dealer"
    ],
    "wof:name":"Premier Moter Cars",
    "wof:placetype":"venue"
},
  "geometry": {"coordinates":[-96.731055,43.514926],"type":"Point"}
}