{
  "type": "Feature",
  "properties": {
    "iso:country":"US",
    "sg:address":"36910 196th St",
    "sg:city":"Saint Lawrence",
    "sg:phone":"+1 605 853 2582",
    "sg:postcode":"57373",
    "sg:province":"SD",
    "sg:tags":[
        "farm",
        "corn",
        "wheat"
    ],
    "wof:name":"Edward Watkins",
    "wof:placetype":"venue"
},
  "geometry": {"coordinates":[-98.80527600000001,44.547643],"type":"Point"}
}