{
  "type": "Feature",
  "properties": {
    "iso:country":"US",
    "sg:address":"45915 210th St",
    "sg:city":"Volga",
    "sg:classifiers":[
        {
            "category":"Farming",
            "subcategory":"Livestock Farm",
            "type":"Manufacturing & Wholesale Goods"
        }
    ],
    "sg:phone":"+1 605 627 9400",
    "sg:postcode":"57071",
    "sg:province":"SD",
    "sg:tags":[
        "feedlot",
        "hog",
        "or",
        "beef",
        "cattle"
    ],
    "wof:name":"Gary Knutson",
    "wof:placetype":"venue"
},
  "geometry": {"coordinates":[-97.02611,44.340737],"type":"Point"}
}