{
  "type": "Feature",
  "properties": {
    "addr:full":"222 N Derby Ln North Sioux City SD 57049",
    "addr:housenumber":"222",
    "addr:postcode":"57049",
    "addr:street":"N Derby Ln North",
    "iso:country":"US",
    "sg:address":"222 N Derby Ln",
    "sg:city":"North Sioux City",
    "sg:classifiers":[
        {
            "category":"Personal",
            "type":"Services"
        }
    ],
    "sg:phone":"+1 605 235 9826",
    "sg:postcode":"57049",
    "sg:province":"SD",
    "wof:name":"Anytime Tan",
    "wof:placetype":"venue"
},
  "geometry": {"coordinates":[-96.49605,42.525257],"type":"Point"}
}