{
  "type": "Feature",
  "properties": {
    "addr:full":"418 2nd Ave E Sisseton SD 57262",
    "addr:housenumber":"418",
    "addr:postcode":"57262",
    "addr:street":"2Nd Ave E Sisseton",
    "iso:country":"US",
    "sg:address":"418 2nd Ave E",
    "sg:city":"Sisseton",
    "sg:classifiers":[
        {
            "category":"Insurance",
            "subcategory":"Insurance Agent",
            "type":"Services"
        }
    ],
    "sg:phone":"+1 605 698 7316",
    "sg:postcode":"57262",
    "sg:province":"SD",
    "wof:name":"Farmers Union Insurance",
    "wof:placetype":"venue"
},
  "geometry": {"coordinates":[-97.048427,45.66444],"type":"Point"}
}