{
  "type": "Feature",
  "properties": {
    "addr:full":"801 W National Guard Dr Sioux Falls SD 57104",
    "addr:housenumber":"801",
    "addr:postcode":"57104",
    "addr:street":"W;Dr",
    "iso:country":"US",
    "sg:address":"801 W National Guard Dr",
    "sg:city":"Sioux Falls",
    "sg:classifiers":[
        {
            "category":"Government",
            "subcategory":"Office",
            "type":"Public Place"
        }
    ],
    "sg:phone":"+1 605 330 4923",
    "sg:postcode":"57104",
    "sg:province":"SD",
    "sg:tags":[
        "state",
        "security"
    ],
    "wof:name":"Army National Guard Recruiter",
    "wof:placetype":"venue"
},
  "geometry": {"coordinates":[-96.729466,43.592631],"type":"Point"}
}