{
  "type": "Feature",
  "properties": {
    "iso:country":"US",
    "sg:address":"47147 292nd St",
    "sg:city":"Beresford",
    "sg:classifiers":[
        {
            "category":"Farming",
            "subcategory":"Farm",
            "type":"Manufacturing & Wholesale Goods"
        }
    ],
    "sg:phone":"+1 605 957 4189",
    "sg:postcode":"57004",
    "sg:province":"SD",
    "sg:tags":[
        "crop",
        "general"
    ],
    "wof:name":"Jensen Kirk",
    "wof:placetype":"venue"
},
  "geometry": {"coordinates":[-96.777006,43.156135],"type":"Point"}
}