{
  "type": "Feature",
  "properties": {
    "iso:country":"US",
    "sg:address":"58 3rd Ave",
    "sg:city":"Lake Andes",
    "sg:classifiers":[
        {
            "category":"Government",
            "subcategory":"Office",
            "type":"Public Place"
        }
    ],
    "sg:phone":"+1 605 487 7694",
    "sg:postcode":"57356",
    "sg:province":"SD",
    "sg:tags":[
        "city"
    ],
    "sg:website":"www.lakeandes.com",
    "wof:name":"Lake Andes City Hall",
    "wof:placetype":"venue"
},
  "geometry": {"coordinates":[-98.541554,43.157209],"type":"Point"}
}