{
  "type": "Feature",
  "properties": {
    "iso:country":"US",
    "sg:address":"24347 173rd Ave",
    "sg:city":"Caputa",
    "sg:phone":"+1 605 993 6541",
    "sg:postcode":"57725",
    "sg:province":"SD",
    "sg:tags":[
        "farm",
        "wheat"
    ],
    "wof:name":"Joyce Jensen LLP",
    "wof:placetype":"venue"
},
  "geometry": {"coordinates":[-102.597179,43.871784],"type":"Point"}
}