{
  "type": "Feature",
  "properties": {
    "iso:country":"US",
    "sg:address":"608 E 8th St",
    "sg:city":"Dell Rapids",
    "sg:classifiers":[
        {
            "category":"Organizations",
            "subcategory":"Religious Organization",
            "type":"Services"
        }
    ],
    "sg:phone":"+1 605 428 3390",
    "sg:postcode":"57022",
    "sg:province":"SD",
    "sg:tags":[
        "church"
    ],
    "wof:name":"St Mary Catholic Church",
    "wof:placetype":"venue"
},
  "geometry": {"coordinates":[-96.708247,43.827209],"type":"Point"}
}