{
  "type": "Feature",
  "properties": {
    "iso:country":"US",
    "sg:address":"351 Wisconsin Ave SW",
    "sg:city":"Huron",
    "sg:classifiers":[
        {
            "category":"Organizations",
            "subcategory":"Professional Association",
            "type":"Services"
        }
    ],
    "sg:phone":"+1 605 352 9492",
    "sg:postcode":"57350",
    "sg:province":"SD",
    "sg:tags":[
        "business",
        "trade"
    ],
    "wof:name":"South Dakota Assn Of Co-Op",
    "wof:placetype":"venue"
},
  "geometry": {"coordinates":[-98.215909,44.362646],"type":"Point"}
}