{
  "type": "Feature",
  "properties": {
    "iso:country":"US",
    "sg:address":"1402 S Minnesota Ave",
    "sg:city":"Sioux Falls",
    "sg:classifiers":[
        {
            "category":"Professional",
            "subcategory":"Computer Services",
            "type":"Services"
        }
    ],
    "sg:phone":"+1 605 335 1050",
    "sg:postcode":"57105",
    "sg:province":"SD",
    "sg:tags":[
        "repair"
    ],
    "wof:name":"International Business Equip",
    "wof:placetype":"venue"
},
  "geometry": {"coordinates":[-96.731199,43.532169],"type":"Point"}
}