{
  "type": "Feature",
  "properties": {
    "iso:country":"US",
    "sg:address":"104 S Garfield Ave",
    "sg:city":"Pierre",
    "sg:classifiers":[
        {
            "category":"Government",
            "subcategory":"Office",
            "type":"Public Place"
        }
    ],
    "sg:phone":"+1 605 773 3162",
    "sg:postcode":"57501",
    "sg:province":"SD",
    "sg:tags":[
        "management",
        "vehicle"
    ],
    "wof:name":"Fleet",
    "wof:placetype":"venue"
},
  "geometry": {"coordinates":[-100.31649299999999,44.364465],"type":"Point"}
}