{
  "type": "Feature",
  "properties": {
    "iso:country":"US",
    "sg:address":"241 N Nebraska St",
    "sg:city":"Salem",
    "sg:classifiers":[
        {
            "category":"Autos & Motor Vehicles",
            "subcategory":"Automobile Sales",
            "type":"Retail Goods"
        }
    ],
    "sg:phone":"+1 605 425 2501",
    "sg:postcode":"57058",
    "sg:province":"SD",
    "sg:tags":[
        "car",
        "dealer"
    ],
    "wof:name":"Salem Sales Inc",
    "wof:placetype":"venue"
},
  "geometry": {"coordinates":[-97.388938,43.728594],"type":"Point"}
}