{
  "type": "Feature",
  "properties": {
    "iso:country":"US",
    "sg:address":"2415 Mount Rushmore Rd",
    "sg:city":"Rapid City",
    "sg:classifiers":[
        {
            "category":"Restaurant",
            "type":"Food & Drink"
        }
    ],
    "sg:phone":"+1 605 341 0387",
    "sg:postcode":"57701",
    "sg:province":"SD",
    "sg:website":"www.subway.com",
    "wof:name":"Subway Sandwiches & Salads",
    "wof:placetype":"venue"
},
  "geometry": {"coordinates":[-103.232485,44.061484],"type":"Point"}
}