{
  "type": "Feature",
  "properties": {
    "iso:country":"US",
    "sg:address":"35822 279th St",
    "sg:city":"Platte",
    "sg:phone":"+1 605 337 3605",
    "sg:postcode":"57369",
    "sg:province":"SD",
    "sg:tags":[
        "farm",
        "field",
        "crop"
    ],
    "wof:name":"County Connection LLP",
    "wof:placetype":"venue"
},
  "geometry": {"coordinates":[-99.004953,43.341887],"type":"Point"}
}