{
  "type": "Feature",
  "properties": {
    "addr:full":"13121 170th Ave Lodgepole SD 57640",
    "addr:housenumber":"13121",
    "addr:postcode":"57640",
    "addr:street":"170Th Ave",
    "iso:country":"US",
    "sg:address":"13121 170th Ave",
    "sg:city":"Lodgepole",
    "sg:classifiers":[
        {
            "category":"Farming",
            "subcategory":"Livestock Farm",
            "type":"Manufacturing & Wholesale Goods"
        }
    ],
    "sg:phone":"+1 605 244 7115",
    "sg:postcode":"57640",
    "sg:province":"SD",
    "sg:tags":[
        "beef",
        "feedlot",
        "cattle"
    ],
    "wof:name":"Dick Woll",
    "wof:placetype":"venue"
},
  "geometry": {"coordinates":[-102.642788,45.499094],"type":"Point"}
}