{
  "type": "Feature",
  "properties": {
    "iso:country":"US",
    "sg:address":"42837 State Hwy 42",
    "sg:city":"Emery",
    "sg:classifiers":[
        {
            "category":"Professional",
            "type":"Services"
        }
    ],
    "sg:phone":"+1 605 999 0620",
    "sg:postcode":"57332",
    "sg:province":"SD",
    "sg:tags":[
        "attendant",
        "park"
    ],
    "wof:name":"Diana J Willis",
    "wof:placetype":"venue"
},
  "geometry": {"coordinates":[-97.646452,43.543233],"type":"Point"}
}