{
  "type": "Feature",
  "properties": {
    "addr:full":"30523 408th Ave Avon SD 57315",
    "addr:housenumber":"30523",
    "addr:postcode":"57315",
    "addr:street":"408Th Ave",
    "iso:country":"US",
    "sg:address":"30523 408th Ave",
    "sg:city":"Avon",
    "sg:classifiers":[
        {
            "category":"Farming",
            "subcategory":"Dairy Farm",
            "type":"Manufacturing & Wholesale Goods"
        }
    ],
    "sg:phone":"+1 605 286 3543",
    "sg:postcode":"57315",
    "sg:province":"SD",
    "wof:name":"A&D Namminga",
    "wof:placetype":"venue"
},
  "geometry": {"coordinates":[-98.03031900000001,42.959673],"type":"Point"}
}