{
  "type": "Feature",
  "properties": {
    "addr:full":"48070 257th St Brandon SD 57005",
    "addr:housenumber":"48070",
    "addr:postcode":"57005",
    "addr:street":"257Th St",
    "iso:country":"US",
    "sg:address":"48070 257th St",
    "sg:city":"Brandon",
    "sg:classifiers":[
        {
            "category":"Social Services",
            "subcategory":"Child Care",
            "type":"Services"
        }
    ],
    "sg:phone":"+1 605 582 7483",
    "sg:postcode":"57005",
    "sg:province":"SD",
    "wof:name":"Ricky's Day Care Svc",
    "wof:placetype":"venue"
},
  "geometry": {"coordinates":[-96.597649,43.659669],"type":"Point"}
}