{
  "type": "Feature",
  "properties": {
    "iso:country":"US",
    "sg:address":"3138 S Minnesota Ave",
    "sg:city":"Sioux Falls",
    "sg:classifiers":[
        {
            "category":"Professional",
            "subcategory":"Business Services",
            "type":"Services"
        }
    ],
    "sg:phone":"+1 605 334 3803",
    "sg:postcode":"57105",
    "sg:province":"SD",
    "wof:name":"Abbey Carpet By Rita",
    "wof:placetype":"venue"
},
  "geometry": {"coordinates":[-96.731165,43.516128],"type":"Point"}
}