{
  "type": "Feature",
  "properties": {
    "iso:country":"US",
    "sg:address":"44249 175th St",
    "sg:city":"Hazel",
    "sg:classifiers":[
        {
            "category":"Farming",
            "subcategory":"Livestock Farm",
            "type":"Manufacturing & Wholesale Goods"
        }
    ],
    "sg:phone":"+1 605 886 2339",
    "sg:postcode":"57242",
    "sg:province":"SD",
    "sg:tags":[
        "beef",
        "feedlot",
        "cattle"
    ],
    "wof:name":"Paulsen Farms",
    "wof:placetype":"venue"
},
  "geometry": {"coordinates":[-97.363708,44.847403],"type":"Point"}
}