{
  "type": "Feature",
  "properties": {
    "addr:full":"919 Main St Rapid City SD 57701",
    "addr:housenumber":"919",
    "addr:postcode":"57701",
    "addr:street":"Main St",
    "iso:country":"US",
    "sg:address":"919 Main St",
    "sg:city":"Rapid City",
    "sg:classifiers":[
        {
            "category":"Utilities",
            "subcategory":"Telephone",
            "type":"Services"
        }
    ],
    "sg:phone":"+1 605 348 1021",
    "sg:postcode":"57701",
    "sg:province":"SD",
    "sg:tags":[
        "company"
    ],
    "wof:name":"MCI/Btna",
    "wof:placetype":"venue"
},
  "geometry": {"coordinates":[-103.23432,44.082092],"type":"Point"}
}