{
  "type": "Feature",
  "properties": {
    "iso:country":"US",
    "sg:address":"218 E Lake Dr",
    "sg:city":"Estelline",
    "sg:phone":"+1 605 873 2155",
    "sg:postcode":"57234",
    "sg:province":"SD",
    "sg:tags":[
        "farm",
        "corn",
        "soybean"
    ],
    "wof:name":"John Runia",
    "wof:placetype":"venue"
},
  "geometry": {"coordinates":[-97.043763,44.587312],"type":"Point"}
}