{
  "type": "Feature",
  "properties": {
    "addr:full":"2101 W Main St Rapid City SD 57702",
    "addr:housenumber":"2101",
    "addr:postcode":"57702",
    "addr:street":"W Main St",
    "iso:country":"US",
    "sg:address":"2101 W Main St",
    "sg:city":"Rapid City",
    "sg:classifiers":[
        {
            "category":"Shopping",
            "subcategory":"Pharmacy",
            "type":"Retail Goods"
        }
    ],
    "sg:phone":"+1 605 343 4445",
    "sg:postcode":"57702",
    "sg:province":"SD",
    "wof:name":"Boyds Drug Mart",
    "wof:placetype":"venue"
},
  "geometry": {"coordinates":[-103.254572,44.081324],"type":"Point"}
}