{
  "type": "Feature",
  "properties": {
    "addr:full":"1340 25th St SW Watertown SD 57201",
    "addr:housenumber":"1340",
    "addr:postcode":"57201",
    "addr:street":"25Th St Sw",
    "iso:country":"US",
    "sg:address":"1340 25th St SW",
    "sg:city":"Watertown",
    "sg:classifiers":[
        {
            "category":"Retail",
            "subcategory":"Animal Services",
            "type":"Services"
        }
    ],
    "sg:phone":"+1 605 882 3342",
    "sg:postcode":"57201",
    "sg:province":"SD",
    "sg:tags":[
        "pet",
        "boarding",
        "sitting"
    ],
    "wof:name":"Lakeview Kennel Dog & Cat",
    "wof:placetype":"venue"
},
  "geometry": {"coordinates":[-97.154538,44.88528],"type":"Point"}
}