{
  "type": "Feature",
  "properties": {
    "addr:full":"1013 Main St Gregory SD 57533",
    "addr:housenumber":"1013",
    "addr:postcode":"57533",
    "addr:street":"Main St",
    "iso:country":"US",
    "sg:address":"1013 Main St",
    "sg:city":"Gregory",
    "sg:classifiers":[
        {
            "category":"Retail",
            "subcategory":"Laundry & Dry Cleaning",
            "type":"Services"
        }
    ],
    "sg:phone":"+1 605 835 9321",
    "sg:postcode":"57533",
    "sg:province":"SD",
    "wof:name":"Julis Carpet Cleaning",
    "wof:placetype":"venue"
},
  "geometry": {"coordinates":[-99.430796,43.237621],"type":"Point"}
}