{
  "type": "Feature",
  "properties": {
    "iso:country":"US",
    "sg:address":"26158 455th Ave",
    "sg:city":"Humboldt",
    "sg:classifiers":[
        {
            "category":"Building & Trades",
            "subcategory":"Electrical",
            "type":"Services"
        }
    ],
    "sg:phone":"+1 605 363 3150",
    "sg:postcode":"57035",
    "sg:province":"SD",
    "sg:tags":[
        "repair",
        "mfg",
        "tv",
        "station",
        "radio",
        "tower"
    ],
    "wof:name":"Cooper Communications",
    "wof:placetype":"venue"
},
  "geometry": {"coordinates":[-97.109333,43.593177],"type":"Point"}
}