{
  "type": "Feature",
  "properties": {
    "iso:country":"US",
    "sg:address":"47056 258th St",
    "sg:city":"Sioux Falls",
    "sg:phone":"+1 605 543 5334",
    "sg:postcode":"57107",
    "sg:province":"SD",
    "sg:tags":[
        "farm",
        "field",
        "corn",
        "soybean",
        "crop"
    ],
    "wof:name":"Benson Brothers",
    "wof:placetype":"venue"
},
  "geometry": {"coordinates":[-96.79991699999999,43.645335],"type":"Point"}
}