{
  "type": "Feature",
  "properties": {
    "iso:country":"US",
    "sg:address":"1800 N M Ave",
    "sg:city":"Sioux Falls",
    "sg:classifiers":[
        {
            "category":"Manufacturing",
            "subcategory":"Paper Products",
            "type":"Manufacturing & Wholesale Goods"
        }
    ],
    "sg:phone":"+1 605 334 0334",
    "sg:postcode":"57104",
    "sg:province":"SD",
    "sg:tags":[
        "bag"
    ],
    "wof:name":"Covalence Plastics",
    "wof:placetype":"venue"
},
  "geometry": {"coordinates":[-96.749545,43.571171],"type":"Point"}
}