{
  "type": "Feature",
  "properties": {
    "iso:country":"US",
    "sg:address":"28479 329th Ave",
    "sg:city":"Dallas",
    "sg:classifiers":[
        {
            "category":"Farming",
            "subcategory":"Livestock Farm",
            "type":"Manufacturing & Wholesale Goods"
        }
    ],
    "sg:phone":"+1 605 835 9668",
    "sg:postcode":"57529",
    "sg:province":"SD",
    "sg:tags":[
        "wheat",
        "beef",
        "cash",
        "grain",
        "cattle",
        "feedlot"
    ],
    "wof:name":"Gary L Ekroth",
    "wof:placetype":"venue"
},
  "geometry": {"coordinates":[-99.593443,43.273062],"type":"Point"}
}