{
  "type": "Feature",
  "properties": {
    "iso:country":"US",
    "sg:address":"41446 15th St",
    "sg:city":"Springfield",
    "sg:phone":"+1 605 369 2894",
    "sg:postcode":"57062",
    "sg:province":"SD",
    "sg:tags":[
        "farm",
        "corn",
        "soybean"
    ],
    "wof:name":"Cal Jelsma",
    "wof:placetype":"venue"
},
  "geometry": {"coordinates":[-97.90924800000001,42.861625],"type":"Point"}
}