{
  "type": "Feature",
  "properties": {
    "iso:country":"US",
    "sg:address":"738 Jennings Ave",
    "sg:city":"Hot Springs",
    "sg:classifiers":[
        {
            "category":"Personal",
            "type":"Services"
        }
    ],
    "sg:phone":"+1 605 745 7715",
    "sg:postcode":"57747",
    "sg:province":"SD",
    "sg:tags":[
        "food"
    ],
    "wof:name":"Earth Goods Natural Foods",
    "wof:placetype":"venue"
},
  "geometry": {"coordinates":[-103.475999,43.432054],"type":"Point"}
}