{
  "type": "Feature",
  "properties": {
    "addr:full":"446 Custer Ave NE Huron SD 57350",
    "addr:housenumber":"446",
    "addr:postcode":"57350",
    "addr:street":"Custer Ave Ne",
    "iso:country":"US",
    "sg:address":"446 Custer Ave NE",
    "sg:city":"Huron",
    "sg:classifiers":[
        {
            "category":"Farming",
            "subcategory":"Farm & Veterinary Services",
            "type":"Manufacturing & Wholesale Goods"
        }
    ],
    "sg:phone":"+1 605 352 0500",
    "sg:postcode":"57350",
    "sg:province":"SD",
    "sg:tags":[
        "control",
        "weed"
    ],
    "wof:name":"Beadle County Weed & Pest",
    "wof:placetype":"venue"
},
  "geometry": {"coordinates":[-98.174145,44.365873],"type":"Point"}
}