{
  "type": "Feature",
  "properties": {
    "addr:full":"1400 Maple St Yankton SD 57078",
    "addr:housenumber":"1400",
    "addr:postcode":"57078",
    "addr:street":"Maple St",
    "iso:country":"US",
    "sg:address":"1400 Maple St",
    "sg:city":"Yankton",
    "sg:classifiers":[
        {
            "category":"Organizations",
            "subcategory":"Religious Organization",
            "type":"Services"
        }
    ],
    "sg:phone":"+1 605 668 0766",
    "sg:postcode":"57078",
    "sg:province":"SD",
    "sg:tags":[
        "church"
    ],
    "wof:name":"Emmanuel Church",
    "wof:placetype":"venue"
},
  "geometry": {"coordinates":[-97.40355099999999,42.881605],"type":"Point"}
}