{
  "type": "Feature",
  "properties": {
    "iso:country":"US",
    "sg:address":"1400 Maple St",
    "sg:city":"Yankton",
    "sg:classifiers":[
        {
            "category":"Organizations",
            "subcategory":"Religious Organization",
            "type":"Services"
        }
    ],
    "sg:phone":"+1 605 668 0766",
    "sg:postcode":"57078",
    "sg:province":"SD",
    "sg:tags":[
        "church"
    ],
    "wof:name":"Emmanuel Church",
    "wof:placetype":"venue"
},
  "geometry": {"coordinates":[-97.403551,42.881605],"type":"Point"}
}