{
  "type": "Feature",
  "properties": {
    "addr:full":"400 S Ellis Rd Sioux Falls SD 57106",
    "addr:housenumber":"400",
    "addr:postcode":"57106",
    "addr:street":"S Ellis Rd",
    "iso:country":"US",
    "sg:address":"400 S Ellis Rd",
    "sg:city":"Sioux Falls",
    "sg:classifiers":[
        {
            "category":"Freight",
            "type":"Transportation"
        }
    ],
    "sg:phone":"+1 605 731 0000",
    "sg:postcode":"57106",
    "sg:province":"SD",
    "sg:tags":[
        "broker",
        "customs"
    ],
    "wof:name":"Great Plains Customs",
    "wof:placetype":"venue"
},
  "geometry": {"coordinates":[-96.830669,43.54345],"type":"Point"}
}