{
  "type": "Feature",
  "properties": {
    "addr:full":"312 Kansas Ave SE Huron SD 57350",
    "addr:postcode":"57350",
    "addr:street":"312 Kansas Ave Se",
    "iso:country":"US",
    "sg:address":"312 Kansas Ave SE",
    "sg:city":"Huron",
    "sg:classifiers":[
        {
            "category":"Personal",
            "subcategory":"Barber",
            "type":"Services"
        }
    ],
    "sg:phone":"+1 605 352 9163",
    "sg:postcode":"57350",
    "sg:province":"SD",
    "sg:tags":[
        "shop"
    ],
    "wof:name":"Look Well Barber Shop",
    "wof:placetype":"venue"
},
  "geometry": {"coordinates":[-98.21235799999999,44.363099],"type":"Point"}
}