{
  "type": "Feature",
  "properties": {
    "addr:full":"113 Rainbow St Yankton SD 57078",
    "addr:housenumber":"113",
    "addr:postcode":"57078",
    "addr:street":"Rainbow St",
    "iso:country":"US",
    "sg:address":"113 Rainbow St",
    "sg:city":"Yankton",
    "sg:classifiers":[
        {
            "category":"Social Services",
            "subcategory":"Child Care",
            "type":"Services"
        }
    ],
    "sg:phone":"+1 605 665 6725",
    "sg:postcode":"57078",
    "sg:province":"SD",
    "sg:tags":[
        "day"
    ],
    "wof:name":"Rainbow Street Daycare",
    "wof:placetype":"venue"
},
  "geometry": {"coordinates":[-97.45231099999999,42.856912],"type":"Point"}
}