{
  "type": "Feature",
  "properties": {
    "iso:country":"US",
    "sg:address":"1800 N Main St",
    "sg:city":"Mitchell",
    "sg:classifiers":[
        {
            "category":"Cinema",
            "subcategory":"Movie Rental",
            "type":"Entertainment"
        }
    ],
    "sg:phone":"+1 605 996 9360",
    "sg:postcode":"57301",
    "sg:province":"SD",
    "sg:tags":[
        "leasing",
        "video",
        "disc",
        "tape"
    ],
    "wof:name":"Coborn's Video",
    "wof:placetype":"venue"
},
  "geometry": {"coordinates":[-98.0257,43.727563],"type":"Point"}
}