{
  "type": "Feature",
  "properties": {
    "iso:country":"US",
    "sg:address":"1300 N Harrison Ave",
    "sg:city":"Pierre",
    "sg:classifiers":[
        {
            "category":"Real Estate",
            "subcategory":"Real Estate Operator",
            "type":"Services"
        }
    ],
    "sg:phone":"+1 605 224 9255",
    "sg:postcode":"57501",
    "sg:province":"SD",
    "sg:tags":[
        "apartment"
    ],
    "wof:name":"Carriage House",
    "wof:placetype":"venue"
},
  "geometry": {"coordinates":[-100.322358,44.375361],"type":"Point"}
}