{
  "type": "Feature",
  "properties": {
    "iso:country":"US",
    "sg:address":"2400 N Louise Ave",
    "sg:city":"Sioux Falls",
    "sg:classifiers":[
        {
            "category":"Restaurant",
            "type":"Food & Drink"
        }
    ],
    "sg:phone":"+1 605 336 0650",
    "sg:postcode":"57107",
    "sg:province":"SD",
    "sg:tags":[
        "banquet",
        "rooms"
    ],
    "sg:website":"www.ramkota.com",
    "wof:name":"Ramkota Hotel",
    "wof:placetype":"venue"
},
  "geometry": {"coordinates":[-96.77083500000001,43.575455],"type":"Point"}
}