{
  "type": "Feature",
  "properties": {
    "addr:full":"1901 Broadway St Yankton SD 57078",
    "addr:housenumber":"1901",
    "addr:postcode":"57078",
    "addr:street":"Broadway St",
    "iso:country":"US",
    "sg:address":"1901 Broadway St",
    "sg:city":"Yankton",
    "sg:classifiers":[
        {
            "category":"Building & Trades",
            "subcategory":"Construction",
            "type":"Services"
        }
    ],
    "sg:phone":"+1 605 660 4680",
    "sg:postcode":"57078",
    "sg:province":"SD",
    "sg:tags":[
        "general",
        "contractor"
    ],
    "wof:name":"Mondragon Construction",
    "wof:placetype":"venue"
},
  "geometry": {"coordinates":[-97.396739,42.888872],"type":"Point"}
}