{
  "type": "Feature",
  "properties": {
    "addr:full":"234 W Kansas St Spearfish SD 57783",
    "addr:housenumber":"234",
    "addr:postcode":"57783",
    "addr:street":"W Kansas St",
    "iso:country":"US",
    "sg:address":"234 W Kansas St",
    "sg:city":"Spearfish",
    "sg:classifiers":[
        {
            "category":"Professional",
            "subcategory":"Business Services",
            "type":"Services"
        }
    ],
    "sg:phone":"+1 605 642 2989",
    "sg:postcode":"57783",
    "sg:province":"SD",
    "sg:tags":[
        "operation"
    ],
    "wof:name":"Spearfish Harley Connection",
    "wof:placetype":"venue"
},
  "geometry": {"coordinates":[-103.86159600000001,44.491977],"type":"Point"}
}