{
  "type": "Feature",
  "properties": {
    "addr:full":"30025 US Hwy 81 Utica SD 57067",
    "addr:postcode":"30025;57067",
    "addr:street":"Us Hwy 81",
    "iso:country":"US",
    "sg:address":"30025 US Hwy 81",
    "sg:city":"Utica",
    "sg:classifiers":[
        {
            "category":"Farming",
            "subcategory":"Livestock Farm",
            "type":"Manufacturing & Wholesale Goods"
        }
    ],
    "sg:phone":"+1 605 665 0610",
    "sg:postcode":"57067",
    "sg:province":"SD",
    "sg:tags":[
        "feedlot",
        "hog",
        "or",
        "beef",
        "cattle"
    ],
    "wof:name":"Mike Manas",
    "wof:placetype":"venue"
},
  "geometry": {"coordinates":[-97.39880100000001,43.038846],"type":"Point"}
}