{
  "type": "Feature",
  "properties": {
    "addr:full":"55 2nd St Lead SD 57754",
    "addr:housenumber":"55",
    "addr:postcode":"57754",
    "addr:street":"2Nd St",
    "iso:country":"US",
    "sg:address":"55 2nd St",
    "sg:city":"Lead",
    "sg:classifiers":[
        {
            "category":"Building & Trades",
            "subcategory":"Construction",
            "type":"Services"
        }
    ],
    "sg:phone":"+1 605 722 6811",
    "sg:postcode":"57754",
    "sg:province":"SD",
    "sg:tags":[
        "concrete",
        "contractor"
    ],
    "wof:name":"Top Notch Concrete",
    "wof:placetype":"venue"
},
  "geometry": {"coordinates":[-103.777153,44.350215],"type":"Point"}
}