{
  "type": "Feature",
  "properties": {
    "iso:country":"US",
    "sg:address":"2025 Jackson Blvd",
    "sg:city":"Rapid City",
    "sg:classifiers":[
        {
            "category":"Real Estate",
            "subcategory":"Real Estate Agent",
            "type":"Services"
        }
    ],
    "sg:phone":"+1 605 381 7292",
    "sg:postcode":"57702",
    "sg:province":"SD",
    "wof:name":"All Hills Realty",
    "wof:placetype":"venue"
},
  "geometry": {"coordinates":[-103.253302,44.074039],"type":"Point"}
}