{
  "type": "Feature",
  "properties": {
    "addr:full":"1601 E River Blvd Sioux Falls SD 57104",
    "addr:housenumber":"1601",
    "addr:postcode":"57104",
    "addr:street":"E River Blvd",
    "iso:country":"US",
    "sg:address":"1601 E River Blvd",
    "sg:city":"Sioux Falls",
    "sg:classifiers":[
        {
            "category":"Building & Trades",
            "subcategory":"Landscaping Services",
            "type":"Services"
        }
    ],
    "sg:phone":"+1 605 332 6770",
    "sg:postcode":"57104",
    "sg:province":"SD",
    "sg:tags":[
        "tree"
    ],
    "wof:name":"Tree Garden",
    "wof:placetype":"venue"
},
  "geometry": {"coordinates":[-96.708117,43.538919],"type":"Point"}
}