{
  "type": "Feature",
  "properties": {
    "iso:country":"US",
    "sg:address":"5513 W 12th St",
    "sg:city":"Sioux Falls",
    "sg:classifiers":[
        {
            "category":"Retail",
            "subcategory":"Auto Repair",
            "type":"Services"
        }
    ],
    "sg:phone":"+1 605 940 5434",
    "sg:postcode":"57106",
    "sg:province":"SD",
    "sg:tags":[
        "automotive"
    ],
    "wof:name":"Sewing Products",
    "wof:placetype":"venue"
},
  "geometry": {"coordinates":[-96.795818,43.543898],"type":"Point"}
}