{
  "type": "Feature",
  "properties": {
    "iso:country":"US",
    "sg:address":"3609 Sturgis Rd",
    "sg:city":"Rapid City",
    "sg:classifiers":[
        {
            "category":"Recreation",
            "subcategory":"Arcade",
            "type":"Entertainment"
        },
        {
            "category":"Travel",
            "subcategory":"Hotels & Motels",
            "type":"Entertainment"
        }
    ],
    "sg:phone":"+1 605 342 0315",
    "sg:postcode":"57702",
    "sg:province":"SD",
    "sg:tags":[
        "operation",
        "casino"
    ],
    "wof:name":"Chicago Street Casino",
    "wof:placetype":"venue"
},
  "geometry": {"coordinates":[-103.27591099999999,44.083311],"type":"Point"}
}