{
  "type": "Feature",
  "properties": {
    "addr:full":"505 Vanderhorck St Britton SD 57430",
    "addr:housenumber":"505",
    "addr:postcode":"57430",
    "addr:street":"Vanderhorck St",
    "iso:country":"US",
    "sg:address":"505 Vanderhorck St",
    "sg:city":"Britton",
    "sg:classifiers":[
        {
            "category":"Government",
            "subcategory":"Office",
            "type":"Public Place"
        }
    ],
    "sg:phone":"+1 605 448 2391",
    "sg:postcode":"57430",
    "sg:province":"SD",
    "sg:tags":[
        "federal",
        "planning",
        "dev"
    ],
    "wof:name":"USDA Rural Development",
    "wof:placetype":"venue"
},
  "geometry": {"coordinates":[-97.747501,45.791181],"type":"Point"}
}