{
  "type": "Feature",
  "properties": {
    "addr:full":"1512 S Raymond Cir Sioux Falls SD 57106",
    "addr:housenumber":"1512",
    "addr:postcode":"57106",
    "addr:street":"S Raymond Cir",
    "iso:country":"US",
    "sg:address":"1512 S Raymond Cir",
    "sg:city":"Sioux Falls",
    "sg:classifiers":[
        {
            "category":"Home & Garden",
            "subcategory":"Building Materials",
            "type":"Retail Goods"
        }
    ],
    "sg:phone":"+1 605 361 9977",
    "sg:postcode":"57106",
    "sg:province":"SD",
    "sg:tags":[
        "door"
    ],
    "wof:name":"Jim's Garage Door Sales & Svc",
    "wof:placetype":"venue"
},
  "geometry": {"coordinates":[-96.801619,43.53208],"type":"Point"}
}