{
  "type": "Feature",
  "properties": {
    "addr:full":"405 E 4th St Yankton SD 57078",
    "addr:housenumber":"405",
    "addr:postcode":"57078",
    "addr:street":"E 4Th St",
    "iso:country":"US",
    "sg:address":"405 E 4th St",
    "sg:city":"Yankton",
    "sg:classifiers":[
        {
            "category":"Retail",
            "subcategory":"Auto Repair",
            "type":"Services"
        }
    ],
    "sg:phone":"+1 605 665 8683",
    "sg:postcode":"57078",
    "sg:province":"SD",
    "sg:tags":[
        "general"
    ],
    "wof:name":"Greggs Automotive LLC",
    "wof:placetype":"venue"
},
  "geometry": {"coordinates":[-97.38744800000001,42.870933],"type":"Point"}
}