{
  "type": "Feature",
  "properties": {
    "iso:country":"US",
    "sg:address":"3409 Main St",
    "sg:city":"Selby",
    "sg:classifiers":[
        {
            "category":"Government",
            "subcategory":"Police Station",
            "type":"Public Place"
        }
    ],
    "sg:phone":"+1 605 649 7800",
    "sg:postcode":"57472",
    "sg:province":"SD",
    "sg:tags":[
        "department"
    ],
    "wof:name":"Selby Police Dept",
    "wof:placetype":"venue"
},
  "geometry": {"coordinates":[-100.03210900000001,45.506345],"type":"Point"}
}