{
  "type": "Feature",
  "properties": {
    "iso:country":"US",
    "sg:address":"121 4th Ave SW",
    "sg:city":"Aberdeen",
    "sg:classifiers":[
        {
            "category":"Professional",
            "subcategory":"Management & Consulting",
            "type":"Services"
        }
    ],
    "sg:phone":"+1 605 229 0878",
    "sg:postcode":"57401",
    "sg:province":"SD",
    "sg:tags":[
        "consultant",
        "business"
    ],
    "wof:name":"Continental Management Inc",
    "wof:placetype":"venue"
},
  "geometry": {"coordinates":[-98.489778,45.461018],"type":"Point"}
}