{
  "type": "Feature",
  "properties": {
    "iso:country":"US",
    "sg:address":"115 S Courtland St",
    "sg:city":"Chamberlain",
    "sg:classifiers":[
        {
            "category":"Utilities",
            "subcategory":"Mobile Phone",
            "type":"Services"
        }
    ],
    "sg:phone":"+1 605 734 5531",
    "sg:postcode":"57325",
    "sg:province":"SD",
    "sg:tags":[
        "telephone",
        "cellular"
    ],
    "wof:name":"Cellular One",
    "wof:placetype":"venue"
},
  "geometry": {"coordinates":[-99.33146000000001,43.811069],"type":"Point"}
}