{
  "type": "Feature",
  "properties": {
    "addr:full":"301 W 43rd St Sioux Falls SD 57105",
    "addr:housenumber":"301",
    "addr:postcode":"57105",
    "addr:street":"W 43Rd St",
    "iso:country":"US",
    "sg:address":"301 W 43rd St",
    "sg:city":"Sioux Falls",
    "sg:classifiers":[
        {
            "category":"Retail",
            "subcategory":"Auto Repair",
            "type":"Services"
        }
    ],
    "sg:phone":"+1 605 335 1905",
    "sg:postcode":"57105",
    "sg:province":"SD",
    "wof:name":"Autowerks Import Parts",
    "wof:placetype":"venue"
},
  "geometry": {"coordinates":[-96.73124,43.513045],"type":"Point"}
}