{
  "type": "Feature",
  "properties": {
    "addr:full":"2301 N Marion Rd Sioux Falls SD 57107",
    "addr:housenumber":"2301",
    "addr:postcode":"57107",
    "addr:street":"N Marion Rd",
    "iso:country":"US",
    "sg:address":"2301 N Marion Rd",
    "sg:city":"Sioux Falls",
    "sg:classifiers":[
        {
            "category":"Building & Trades",
            "subcategory":"Construction",
            "type":"Services"
        }
    ],
    "sg:phone":"+1 605 339 2297",
    "sg:postcode":"57107",
    "sg:province":"SD",
    "sg:tags":[
        "general",
        "contractor"
    ],
    "wof:name":"Metric Contracting Svc",
    "wof:placetype":"venue"
},
  "geometry": {"coordinates":[-96.79109699999999,43.571407],"type":"Point"}
}