{
  "type": "Feature",
  "properties": {
    "iso:country":"US",
    "sg:address":"2815 E 26th St",
    "sg:city":"Sioux Falls",
    "sg:classifiers":[
        {
            "category":"Professional",
            "subcategory":"Employment Agencies",
            "type":"Services"
        }
    ],
    "sg:phone":"+1 605 334 0619",
    "sg:postcode":"57103",
    "sg:province":"SD",
    "sg:tags":[
        "help",
        "supply"
    ],
    "wof:name":"Professional Image By Rosemary",
    "wof:placetype":"venue"
},
  "geometry": {"coordinates":[-96.686894,43.529217],"type":"Point"}
}