{
  "type": "Feature",
  "properties": {
    "addr:full":"32080 US Hwy 14 Harrold SD 57522",
    "addr:postcode":"32080;57522",
    "addr:street":"Us Hwy 14",
    "iso:country":"US",
    "sg:address":"32080 US Hwy 14",
    "sg:city":"Harrold",
    "sg:classifiers":[
        {
            "category":"Farming",
            "subcategory":"Farm & Veterinary Services",
            "type":"Manufacturing & Wholesale Goods"
        }
    ],
    "sg:phone":"+1 605 875 3375",
    "sg:postcode":"57522",
    "sg:province":"SD",
    "sg:tags":[
        "aerial",
        "applicator"
    ],
    "wof:name":"Custom Air Inc",
    "wof:placetype":"venue"
},
  "geometry": {"coordinates":[-99.75317,44.527035],"type":"Point"}
}