{
  "type": "Feature",
  "properties": {
    "addr:full":"618 7th Ave W Mobridge SD 57601",
    "addr:housenumber":"618",
    "addr:postcode":"57601",
    "addr:street":"7Th Ave W Mobridge",
    "iso:country":"US",
    "sg:address":"618 7th Ave W",
    "sg:city":"Mobridge",
    "sg:classifiers":[
        {
            "category":"Real Estate",
            "subcategory":"Real Estate Operator",
            "type":"Services"
        }
    ],
    "sg:phone":"+1 605 845 5307",
    "sg:postcode":"57601",
    "sg:province":"SD",
    "sg:tags":[
        "apartment"
    ],
    "wof:name":"Riverview Apts",
    "wof:placetype":"venue"
},
  "geometry": {"coordinates":[-100.443915,45.539269],"type":"Point"}
}