{
  "type": "Feature",
  "properties": {
    "addr:full":"400 Lakota Ave Brandon SD 57005",
    "addr:housenumber":"400",
    "addr:postcode":"57005",
    "addr:street":"Lakota Ave",
    "iso:country":"US",
    "sg:address":"400 Lakota Ave",
    "sg:city":"Brandon",
    "sg:classifiers":[
        {
            "category":"Home & Garden",
            "subcategory":"Hardware",
            "type":"Retail Goods"
        }
    ],
    "sg:phone":"+1 605 582 6732",
    "sg:postcode":"57005",
    "sg:province":"SD",
    "sg:tags":[
        "saw"
    ],
    "sg:website":"www.mikesworkshop.com",
    "wof:name":"Mike's Workshop Inc",
    "wof:placetype":"venue"
},
  "geometry": {"coordinates":[-96.594627,43.588825],"type":"Point"}
}