{
  "type": "Feature",
  "properties": {
    "addr:full":"7978 Jasmine Ln Rapid City SD 57702",
    "addr:housenumber":"7978",
    "addr:postcode":"57702",
    "addr:street":"Jasmine Ln",
    "iso:country":"US",
    "sg:address":"7978 Jasmine Ln",
    "sg:city":"Rapid City",
    "sg:classifiers":[
        {
            "category":"Retail",
            "subcategory":"Repair Shop",
            "type":"Services"
        }
    ],
    "sg:phone":"+1 605 343 2537",
    "sg:postcode":"57702",
    "sg:province":"SD",
    "sg:tags":[
        "water",
        "equipment",
        "softening"
    ],
    "wof:name":"Good Water Co",
    "wof:placetype":"venue"
},
  "geometry": {"coordinates":[-103.323151,44.009274],"type":"Point"}
}