{
  "type": "Feature",
  "properties": {
    "addr:full":"509 W 5th St Canton SD 57013",
    "addr:housenumber":"509",
    "addr:postcode":"57013",
    "addr:street":"W 5Th St",
    "iso:country":"US",
    "sg:address":"509 W 5th St",
    "sg:city":"Canton",
    "sg:classifiers":[
        {
            "category":"Restaurant",
            "type":"Food & Drink"
        },
        {
            "category":"Food & Beverages",
            "subcategory":"Groceries & Convenience Stores",
            "type":"Retail Goods"
        }
    ],
    "sg:menulink":"http://www.allmenus.com/sd/canton/225088-caseys-general-store/menu/",
    "sg:phone":"+1 605 987 3431",
    "sg:postcode":"57013",
    "sg:province":"SD",
    "sg:tags":[
        "american",
        "pizza"
    ],
    "wof:name":"Casey's General Store",
    "wof:placetype":"venue"
},
  "geometry": {"coordinates":[-96.59837,43.300908],"type":"Point"}
}