{
  "type": "Feature",
  "properties": {
    "iso:country":"US",
    "sg:address":"30826 408th Ave",
    "sg:city":"Avon",
    "sg:phone":"+1 605 286 3860",
    "sg:postcode":"57315",
    "sg:province":"SD",
    "sg:tags":[
        "farm",
        "corn",
        "grain",
        "cash"
    ],
    "wof:name":"Jim Tjeerdsma",
    "wof:placetype":"venue"
},
  "geometry": {"coordinates":[-98.03025599999999,42.916592],"type":"Point"}
}