{
  "type": "Feature",
  "properties": {
    "iso:country":"US",
    "sg:address":"1316 S Cliff Ave",
    "sg:city":"Sioux Falls",
    "sg:classifiers":[
        {
            "category":"Recreation",
            "subcategory":"Arcade",
            "type":"Entertainment"
        }
    ],
    "sg:phone":"+1 605 373 0882",
    "sg:postcode":"57105",
    "sg:province":"SD",
    "sg:tags":[
        "casino"
    ],
    "wof:name":"Aces Casino",
    "wof:placetype":"venue"
},
  "geometry": {"coordinates":[-96.711224,43.534043],"type":"Point"}
}