{
  "type": "Feature",
  "properties": {
    "iso:country":"US",
    "sg:address":"42012 120th St",
    "sg:city":"Langford",
    "sg:classifiers":[
        {
            "category":"Farming",
            "subcategory":"Livestock Farm",
            "type":"Manufacturing & Wholesale Goods"
        }
    ],
    "sg:phone":"+1 605 493 6789",
    "sg:postcode":"57454",
    "sg:province":"SD",
    "sg:tags":[
        "beef",
        "feedlot",
        "cattle"
    ],
    "wof:name":"Wayne J Nelson Cattle Company",
    "wof:placetype":"venue"
},
  "geometry": {"coordinates":[-97.812546,45.646113],"type":"Point"}
}