{
  "type": "Feature",
  "properties": {
    "addr:full":"124 W Main St Pierpont SD 57448",
    "addr:housenumber":"124",
    "addr:postcode":"57448",
    "addr:street":"W Main St",
    "iso:country":"US",
    "sg:address":"124 W Main St",
    "sg:city":"Pierpont",
    "sg:classifiers":[
        {
            "category":"Autos & Motor Vehicles",
            "subcategory":"Automobile Sales",
            "type":"Retail Goods"
        }
    ],
    "sg:phone":"+1 605 325 3379",
    "sg:postcode":"57448",
    "sg:province":"SD",
    "sg:tags":[
        "car",
        "dealer"
    ],
    "wof:name":"Louie's Auto Sales",
    "wof:placetype":"venue"
},
  "geometry": {"coordinates":[-99.475779,45.578846],"type":"Point"}
}