{
  "type": "Feature",
  "properties": {
    "iso:country":"US",
    "sg:address":"17223 373rd Ave",
    "sg:city":"Redfield",
    "sg:classifiers":[
        {
            "category":"Farming",
            "subcategory":"Livestock Farm",
            "type":"Manufacturing & Wholesale Goods"
        }
    ],
    "sg:phone":"+1 605 472 3176",
    "sg:postcode":"57469",
    "sg:province":"SD",
    "sg:tags":[
        "beef",
        "equine",
        "feedlot",
        "cattle"
    ],
    "wof:name":"Joseph Lutter",
    "wof:placetype":"venue"
},
  "geometry": {"coordinates":[-98.72587799999999,44.893161],"type":"Point"}
}