{
  "type": "Feature",
  "properties": {
    "iso:country":"US",
    "sg:address":"22531 440th Ave",
    "sg:city":"Winfred",
    "sg:classifiers":[
        {
            "category":"Farming",
            "subcategory":"Farm",
            "type":"Manufacturing & Wholesale Goods"
        }
    ],
    "sg:phone":"+1 605 772 4222",
    "sg:postcode":"57076",
    "sg:province":"SD",
    "wof:name":"Lewis Farms",
    "wof:placetype":"venue"
},
  "geometry": {"coordinates":[-97.410448,44.112598],"type":"Point"}
}