{
  "type": "Feature",
  "properties": {
    "iso:country":"US",
    "sg:address":"19702 427th Ave",
    "sg:city":"Iroquois",
    "sg:phone":"+1 605 854 3008",
    "sg:postcode":"57353",
    "sg:province":"SD",
    "sg:tags":[
        "farm",
        "corn",
        "wheat"
    ],
    "wof:name":"Lyle Forbes",
    "wof:placetype":"venue"
},
  "geometry": {"coordinates":[-97.672909,44.526919],"type":"Point"}
}