{
  "type": "Feature",
  "properties": {
    "iso:country":"US",
    "sg:address":"30415 187th St",
    "sg:city":"Onida",
    "sg:classifiers":[
        {
            "category":"Farming",
            "subcategory":"Farm",
            "type":"Manufacturing & Wholesale Goods"
        }
    ],
    "sg:phone":"+1 605 258 2296",
    "sg:postcode":"57564",
    "sg:province":"SD",
    "wof:name":"Chris Huse",
    "wof:placetype":"venue"
},
  "geometry": {"coordinates":[-100.077607,44.678903],"type":"Point"}
}