{
  "type": "Feature",
  "properties": {
    "iso:country":"US",
    "sg:address":"32855 133rd St",
    "sg:city":"Bowdle",
    "sg:phone":"+1 605 285 6467",
    "sg:postcode":"57428",
    "sg:province":"SD",
    "sg:tags":[
        "farm",
        "wheat",
        "corn",
        "grain",
        "cash"
    ],
    "wof:name":"Blumhardt Wilbert",
    "wof:placetype":"venue"
},
  "geometry": {"coordinates":[-99.600081,45.462999],"type":"Point"}
}