{
  "type": "Feature",
  "properties": {
    "iso:country":"US",
    "sg:address":"23200 396th Ave",
    "sg:city":"Woonsocket",
    "sg:classifiers":[
        {
            "category":"Farming",
            "subcategory":"Dairy Farm",
            "type":"Manufacturing & Wholesale Goods"
        }
    ],
    "sg:phone":"+1 605 796 4613",
    "sg:postcode":"57385",
    "sg:province":"SD",
    "wof:name":"Arthur Larson Farm",
    "wof:placetype":"venue"
},
  "geometry": {"coordinates":[-98.291519,44.024876],"type":"Point"}
}