{
  "type": "Feature",
  "properties": {
    "iso:country":"US",
    "sg:address":"5017 S Louise Ave",
    "sg:city":"Sioux Falls",
    "sg:classifiers":[
        {
            "category":"Utilities",
            "subcategory":"Mobile Phone",
            "type":"Services"
        }
    ],
    "sg:phone":"+1 605 271 6100",
    "sg:postcode":"57108",
    "sg:province":"SD",
    "sg:tags":[
        "telephone",
        "cellular"
    ],
    "wof:name":"Alltel Authorize Agent Pro",
    "wof:placetype":"venue"
},
  "geometry": {"coordinates":[-96.771018,43.498897],"type":"Point"}
}