{
  "type": "Feature",
  "properties": {
    "addr:full":"310 N Main St Mitchell SD 57301",
    "addr:housenumber":"310",
    "addr:postcode":"57301",
    "addr:street":"N Main St",
    "iso:country":"US",
    "sg:address":"310 N Main St",
    "sg:city":"Mitchell",
    "sg:classifiers":[
        {
            "category":"Shopping",
            "type":"Retail Goods"
        }
    ],
    "sg:phone":"+1 605 996 1822",
    "sg:postcode":"57301",
    "sg:province":"SD",
    "sg:tags":[
        "merchandise"
    ],
    "wof:name":"Dakota Hearing Instruments",
    "wof:placetype":"venue"
},
  "geometry": {"coordinates":[-98.02549399999999,43.712396],"type":"Point"}
}