{
  "type": "Feature",
  "properties": {
    "addr:full":"1357 Dakota Ave N Huron SD 57350",
    "addr:housenumber":"1357",
    "addr:postcode":"57350",
    "addr:street":"Dakota Ave N",
    "iso:country":"US",
    "sg:address":"1357 Dakota Ave N",
    "sg:city":"Huron",
    "sg:classifiers":[
        {
            "category":"Government",
            "subcategory":"Fire Station",
            "type":"Public Place"
        }
    ],
    "sg:phone":"+1 605 353 8520",
    "sg:postcode":"57350",
    "sg:province":"SD",
    "sg:tags":[
        "protection"
    ],
    "wof:name":"Huron City Fire Dept Main",
    "wof:placetype":"venue"
},
  "geometry": {"coordinates":[-98.214327,44.382919],"type":"Point"}
}