{
  "type": "Feature",
  "properties": {
    "iso:country":"US",
    "sg:address":"23064 365th Ave",
    "sg:city":"Wessington Spgs",
    "sg:classifiers":[
        {
            "category":"Farming",
            "subcategory":"Farm",
            "type":"Manufacturing & Wholesale Goods"
        },
        {
            "category":"Farming",
            "subcategory":"Farm & Veterinary Services",
            "type":"Manufacturing & Wholesale Goods"
        }
    ],
    "sg:phone":"+1 605 539 1361",
    "sg:postcode":"57382",
    "sg:province":"SD",
    "sg:tags":[
        "breeder",
        "livestock",
        "general"
    ],
    "wof:name":"Spring Valley Colony Ranch",
    "wof:placetype":"venue"
},
  "geometry": {"coordinates":[-98.888308,44.039669],"type":"Point"}
}