{
  "type": "Feature",
  "properties": {
    "iso:country":"US",
    "sg:address":"303 W 6th St",
    "sg:city":"Hartford",
    "sg:classifiers":[
        {
            "category":"Health Services",
            "subcategory":"Health Practitioner",
            "type":"Services"
        }
    ],
    "sg:phone":"+1 605 528 7368",
    "sg:postcode":"57033",
    "sg:province":"SD",
    "sg:tags":[
        "occupational",
        "therapist"
    ],
    "wof:name":"South Dakota Occupational Thpy",
    "wof:placetype":"venue"
},
  "geometry": {"coordinates":[-96.948744,43.628286],"type":"Point"}
}