{
  "type": "Feature",
  "properties": {
    "iso:country":"US",
    "sg:address":"44244 218th St",
    "sg:city":"Oldham",
    "sg:classifiers":[
        {
            "category":"Professional",
            "type":"Services"
        }
    ],
    "sg:phone":"+1 605 482 8545",
    "sg:postcode":"57051",
    "sg:province":"SD",
    "wof:name":"David Folsland",
    "wof:placetype":"venue"
},
  "geometry": {"coordinates":[-97.37109700000001,44.223872],"type":"Point"}
}