{
  "type": "Feature",
  "properties": {
    "iso:country":"US",
    "sg:address":"26157 439th Ave",
    "sg:city":"Bridgewater",
    "sg:phone":"+1 605 729 2347",
    "sg:postcode":"57319",
    "sg:province":"SD",
    "sg:tags":[
        "farm",
        "corn",
        "wheat"
    ],
    "wof:name":"Bruce Rasmussen",
    "wof:placetype":"venue"
},
  "geometry": {"coordinates":[-97.428175,43.590592],"type":"Point"}
}