{
  "type": "Feature",
  "properties": {
    "iso:country":"US",
    "sg:address":"305 S 3rd St E",
    "sg:city":"Stockholm",
    "sg:classifiers":[
        {
            "category":"Organizations",
            "subcategory":"Religious Organization",
            "type":"Services"
        }
    ],
    "sg:phone":"+1 605 676 2304",
    "sg:postcode":"57264",
    "sg:province":"SD",
    "sg:tags":[
        "church"
    ],
    "wof:name":"Elm Evangelical Covenant Chr",
    "wof:placetype":"venue"
},
  "geometry": {"coordinates":[-96.798159,45.098033],"type":"Point"}
}