{
  "type": "Feature",
  "properties": {
    "iso:country":"US",
    "sg:address":"38664 267th St",
    "sg:city":"Stickney",
    "sg:classifiers":[
        {
            "category":"Farming",
            "subcategory":"Livestock Farm",
            "type":"Manufacturing & Wholesale Goods"
        }
    ],
    "sg:phone":"+1 605 732 4651",
    "sg:postcode":"57375",
    "sg:province":"SD",
    "sg:tags":[
        "beef",
        "feedlot",
        "cattle"
    ],
    "wof:name":"Larry Vreugdenhil",
    "wof:placetype":"venue"
},
  "geometry": {"coordinates":[-98.485503,43.513163],"type":"Point"}
}