{
  "type": "Feature",
  "properties": {
    "addr:full":"45345 311th St Meckling SD 57069",
    "addr:housenumber":"45345",
    "addr:postcode":"57069",
    "addr:street":"311Th St",
    "iso:country":"US",
    "sg:address":"45345 311th St",
    "sg:city":"Meckling",
    "sg:classifiers":[
        {
            "category":"Farming",
            "subcategory":"Farm",
            "type":"Manufacturing & Wholesale Goods"
        },
        {
            "category":"Recreation",
            "type":"Entertainment"
        }
    ],
    "sg:phone":"+1 605 624 2800",
    "sg:postcode":"57069",
    "sg:province":"SD",
    "sg:tags":[
        "trip",
        "hunting"
    ],
    "wof:name":"E Circle E Hunting Farms",
    "wof:placetype":"venue"
},
  "geometry": {"coordinates":[-97.13454,42.881012],"type":"Point"}
}