{
  "type": "Feature",
  "properties": {
    "iso:country":"US",
    "sg:address":"2800 Broadway St",
    "sg:city":"Yankton",
    "sg:classifiers":[
        {
            "category":"Restaurant",
            "type":"Food & Drink"
        }
    ],
    "sg:phone":"+1 605 260 0157",
    "sg:postcode":"57078",
    "sg:province":"SD",
    "wof:name":"Sonic Drive-In",
    "wof:placetype":"venue"
},
  "geometry": {"coordinates":[-97.39741100000001,42.902708],"type":"Point"}
}