{
  "type": "Feature",
  "properties": {
    "iso:country":"US",
    "sg:address":"30491 179th St",
    "sg:city":"Agar",
    "sg:classifiers":[
        {
            "category":"Farming",
            "subcategory":"Farm",
            "type":"Manufacturing & Wholesale Goods"
        }
    ],
    "sg:phone":"+1 605 258 2746",
    "sg:postcode":"57520",
    "sg:province":"SD",
    "sg:tags":[
        "crop",
        "general"
    ],
    "wof:name":"Paul Brandt",
    "wof:placetype":"venue"
},
  "geometry": {"coordinates":[-100.06870000000001,44.794531],"type":"Point"}
}