{
  "type": "Feature",
  "properties": {
    "iso:country":"US",
    "sg:address":"2622 13th Ave SE",
    "sg:city":"Aberdeen",
    "sg:classifiers":[
        {
            "category":"Professional",
            "subcategory":"Business Services",
            "type":"Services"
        }
    ],
    "sg:phone":"+1 605 226 0845",
    "sg:postcode":"57401",
    "sg:province":"SD",
    "wof:name":"Yeske Family Ltd Partnership",
    "wof:placetype":"venue"
},
  "geometry": {"coordinates":[-98.45098900000001,45.450457],"type":"Point"}
}