{
  "type": "Feature",
  "properties": {
    "iso:country":"US",
    "sg:address":"811 Main St",
    "sg:city":"Faulkton",
    "sg:classifiers":[
        {
            "category":"Professional",
            "subcategory":"Lawyer & Legal Services",
            "type":"Services"
        }
    ],
    "sg:phone":"+1 605 598 4330",
    "sg:postcode":"57438",
    "sg:province":"SD",
    "sg:tags":[
        "attorney"
    ],
    "wof:name":"Bormann Law Office",
    "wof:placetype":"venue"
},
  "geometry": {"coordinates":[-99.12423,45.034965],"type":"Point"}
}