{
  "type": "Feature",
  "properties": {
    "addr:full":"905 Dobson St Armour SD 57313",
    "addr:housenumber":"905",
    "addr:postcode":"57313",
    "addr:street":"Dobson St",
    "iso:country":"US",
    "sg:address":"905 Dobson St",
    "sg:city":"Armour",
    "sg:classifiers":[
        {
            "category":"Education",
            "subcategory":"School",
            "type":"Public Place"
        }
    ],
    "sg:phone":"+1 605 724 2698",
    "sg:postcode":"57313",
    "sg:province":"SD",
    "sg:website":"www.armour.k12.sd.us",
    "wof:name":"Armour High School",
    "wof:placetype":"venue"
},
  "geometry": {"coordinates":[-98.34796799999999,43.320853],"type":"Point"}
}