{
  "type": "Feature",
  "properties": {
    "addr:full":"117 N Main St Chamberlain SD 57325",
    "addr:housenumber":"117",
    "addr:postcode":"57325",
    "addr:street":"N Main St",
    "iso:country":"US",
    "sg:address":"117 N Main St",
    "sg:city":"Chamberlain",
    "sg:classifiers":[
        {
            "category":"Professional",
            "subcategory":"Accounting & Tax Preparation",
            "type":"Services"
        }
    ],
    "sg:phone":"+1 605 734 6055",
    "sg:postcode":"57325",
    "sg:province":"SD",
    "sg:tags":[
        "accountant"
    ],
    "wof:name":"Endorf Lurken Olson & Co",
    "wof:placetype":"venue"
},
  "geometry": {"coordinates":[-99.32987900000001,43.811615],"type":"Point"}
}