{
  "type": "Feature",
  "properties": {
    "iso:country":"US",
    "sg:address":"420 7th Ave E",
    "sg:city":"Sisseton",
    "sg:classifiers":[
        {
            "category":"Social Services",
            "type":"Services"
        }
    ],
    "sg:phone":"+1 605 698 3061",
    "sg:postcode":"57262",
    "sg:province":"SD",
    "wof:name":"Area 4 Senior Nutrition Center",
    "wof:placetype":"venue"
},
  "geometry": {"coordinates":[-97.041993,45.664499],"type":"Point"}
}