{
  "type": "Feature",
  "properties": {
    "addr:full":"601 Lazelle St Sturgis SD 57785",
    "addr:housenumber":"601",
    "addr:postcode":"57785",
    "addr:street":"Lazelle St",
    "iso:country":"US",
    "sg:address":"601 Lazelle St",
    "sg:city":"Sturgis",
    "sg:classifiers":[
        {
            "category":"Retail",
            "subcategory":"Portrait Studio",
            "type":"Services"
        }
    ],
    "sg:phone":"+1 605 347 2922",
    "sg:postcode":"57785",
    "sg:province":"SD",
    "sg:tags":[
        "photographer"
    ],
    "wof:name":"T & M Photographic Studio Inc",
    "wof:placetype":"venue"
},
  "geometry": {"coordinates":[-103.50103799999999,44.415002],"type":"Point"}
}