{
  "type": "Feature",
  "properties": {
    "iso:country":"US",
    "sg:address":"47272 254th St",
    "sg:city":"Baltic",
    "sg:classifiers":[
        {
            "category":"Building & Trades",
            "subcategory":"Construction",
            "type":"Services"
        }
    ],
    "sg:phone":"+1 605 529 5978",
    "sg:postcode":"57003",
    "sg:province":"SD",
    "sg:tags":[
        "house"
    ],
    "wof:name":"Bunkers Const Donald",
    "wof:placetype":"venue"
},
  "geometry": {"coordinates":[-96.76598,43.703295],"type":"Point"}
}