{
  "type": "Feature",
  "properties": {
    "iso:country":"US",
    "sg:address":"709 State Ave E",
    "sg:city":"Estelline",
    "sg:classifiers":[
        {
            "category":"Organizations",
            "subcategory":"Religious Organization",
            "type":"Services"
        }
    ],
    "sg:phone":"+1 605 873 2332",
    "sg:postcode":"57234",
    "sg:province":"SD",
    "sg:tags":[
        "church"
    ],
    "wof:name":"Trinity Lutheran Church",
    "wof:placetype":"venue"
},
  "geometry": {"coordinates":[-96.899325,44.572833],"type":"Point"}
}