{
  "type": "Feature",
  "properties": {
    "iso:country":"US",
    "sg:address":"29167 406th Ave",
    "sg:city":"Tripp",
    "sg:classifiers":[
        {
            "category":"Farming",
            "subcategory":"Livestock Farm",
            "type":"Manufacturing & Wholesale Goods"
        }
    ],
    "sg:phone":"+1 605 935 6878",
    "sg:postcode":"57376",
    "sg:province":"SD",
    "sg:tags":[
        "feedlot",
        "grain",
        "cash",
        "beef",
        "cattle"
    ],
    "wof:name":"Keith Frey",
    "wof:placetype":"venue"
},
  "geometry": {"coordinates":[-98.069374,43.15414],"type":"Point"}
}