{
  "type": "Feature",
  "properties": {
    "iso:country":"US",
    "sg:address":"40633 257th St",
    "sg:city":"Mitchell",
    "sg:classifiers":[
        {
            "category":"Retail",
            "subcategory":"Repair Shop",
            "type":"Services"
        }
    ],
    "sg:phone":"+1 605 996 4861",
    "sg:postcode":"57301",
    "sg:province":"SD",
    "wof:name":"J & N Tractor Repair",
    "wof:placetype":"venue"
},
  "geometry": {"coordinates":[-98.071228,43.658424],"type":"Point"}
}