{
  "type": "Feature",
  "properties": {
    "iso:country":"US",
    "sg:address":"405 E Omaha St",
    "sg:city":"Rapid City",
    "sg:classifiers":[
        {
            "category":"Arts & Performance",
            "subcategory":"Theater",
            "type":"Entertainment"
        }
    ],
    "sg:phone":"+1 605 348 8869",
    "sg:postcode":"57701",
    "sg:province":"SD",
    "sg:tags":[
        "live",
        "music"
    ],
    "sg:website":"www.cmusic.com",
    "wof:name":"Complete Music",
    "wof:placetype":"venue"
},
  "geometry": {"coordinates":[-103.203778,44.081354],"type":"Point"}
}