{
  "type": "Feature",
  "properties": {
    "addr:full":"100 W Elm St Mitchell SD 57301",
    "addr:housenumber":"100",
    "addr:postcode":"57301",
    "addr:street":"W Elm St",
    "iso:country":"US",
    "sg:address":"100 W Elm St",
    "sg:city":"Mitchell",
    "sg:classifiers":[
        {
            "category":"Freight",
            "type":"Transportation"
        }
    ],
    "sg:phone":"+1 605 996 4339",
    "sg:postcode":"57301",
    "sg:province":"SD",
    "sg:tags":[
        "special"
    ],
    "wof:name":"B & L Storage",
    "wof:placetype":"venue"
},
  "geometry": {"coordinates":[-98.02540399999999,43.70364],"type":"Point"}
}