{
  "type": "Feature",
  "properties": {
    "addr:full":"17014 373rd Ave Redfield SD 57469",
    "addr:housenumber":"17014",
    "addr:postcode":"57469",
    "addr:street":"373Rd Ave",
    "iso:country":"US",
    "sg:address":"17014 373rd Ave",
    "sg:city":"Redfield",
    "sg:phone":"+1 605 472 0275",
    "sg:postcode":"57469",
    "sg:province":"SD",
    "sg:tags":[
        "farm",
        "corn",
        "soybean"
    ],
    "wof:name":"Ralph Roth",
    "wof:placetype":"venue"
},
  "geometry": {"coordinates":[-98.716573,44.925962],"type":"Point"}
}