{
  "type": "Feature",
  "properties": {
    "iso:country":"US",
    "sg:address":"408 N 3rd St",
    "sg:city":"Arlington",
    "sg:classifiers":[
        {
            "category":"Personal",
            "subcategory":"Beauty Salon",
            "type":"Services"
        }
    ],
    "sg:phone":"+1 605 983 5583",
    "sg:postcode":"57212",
    "sg:province":"SD",
    "sg:tags":[
        "shop"
    ],
    "wof:name":"Claras Beauty Salon",
    "wof:placetype":"venue"
},
  "geometry": {"coordinates":[-97.13164500000001,44.367215],"type":"Point"}
}