{
  "type": "Feature",
  "properties": {
    "iso:country":"US",
    "sg:address":"16590 227th St",
    "sg:city":"New Underwood",
    "sg:classifiers":[
        {
            "category":"Farming",
            "subcategory":"Livestock Farm",
            "type":"Manufacturing & Wholesale Goods"
        }
    ],
    "sg:phone":"+1 605 754 6737",
    "sg:postcode":"57761",
    "sg:province":"SD",
    "sg:tags":[
        "beef",
        "feedlot",
        "cattle"
    ],
    "wof:name":"Howard Knuppe",
    "wof:placetype":"venue"
},
  "geometry": {"coordinates":[-102.73047699999999,44.110871],"type":"Point"}
}