{
  "type": "Feature",
  "properties": {
    "addr:full":"1401 Mill St Belle Fourche SD 57717",
    "addr:housenumber":"1401",
    "addr:postcode":"57717",
    "addr:street":"Mill St",
    "iso:country":"US",
    "sg:address":"1401 Mill St",
    "sg:city":"Belle Fourche",
    "sg:classifiers":[
        {
            "category":"Restaurant",
            "type":"Food & Drink"
        }
    ],
    "sg:menulink":"http://www.allmenus.com/sd/belle-fourche/96386-taco-johns/menu/",
    "sg:phone":"+1 605 892 6436",
    "sg:postcode":"57717",
    "sg:province":"SD",
    "sg:tags":[
        "american",
        "mexican"
    ],
    "wof:name":"Taco John's",
    "wof:placetype":"venue"
},
  "geometry": {"coordinates":[-103.85504,44.66263],"type":"Point"}
}