{
  "type": "Feature",
  "properties": {
    "iso:country":"US",
    "sg:address":"3932 S Western Ave",
    "sg:city":"Sioux Falls",
    "sg:classifiers":[
        {
            "category":"Health Services",
            "subcategory":"Hospital",
            "type":"Services"
        }
    ],
    "sg:phone":"+1 605 331 5540",
    "sg:postcode":"57105",
    "sg:province":"SD",
    "sg:tags":[
        "facility",
        "rehabilitation",
        "for",
        "outpatient"
    ],
    "wof:name":"Mc Kennon Hospital",
    "wof:placetype":"venue"
},
  "geometry": {"coordinates":[-96.751001,43.509915],"type":"Point"}
}