{
  "type": "Feature",
  "properties": {
    "addr:full":"47226 258th St Renner SD 57055",
    "addr:housenumber":"47226",
    "addr:postcode":"57055",
    "addr:street":"258Th St",
    "iso:country":"US",
    "sg:address":"47226 258th St",
    "sg:city":"Renner",
    "sg:classifiers":[
        {
            "category":"Retail",
            "subcategory":"Repair Shop",
            "type":"Services"
        }
    ],
    "sg:phone":"+1 605 543 6870",
    "sg:postcode":"57055",
    "sg:province":"SD",
    "sg:tags":[
        "sharpening"
    ],
    "wof:name":"MTS Saws Inc",
    "wof:placetype":"venue"
},
  "geometry": {"coordinates":[-96.763628,43.64535],"type":"Point"}
}