{
  "type": "Feature",
  "properties": {
    "iso:country":"US",
    "sg:address":"2203 Hwy 12 W",
    "sg:city":"Aberdeen",
    "sg:classifiers":[
        {
            "category":"Autos & Motor Vehicles",
            "subcategory":"Automobile Sales",
            "type":"Retail Goods"
        }
    ],
    "sg:phone":"+1 605 225 4115",
    "sg:postcode":"57401",
    "sg:province":"SD",
    "sg:tags":[
        "car",
        "used"
    ],
    "wof:name":"Starlite Motors",
    "wof:placetype":"venue"
},
  "geometry": {"coordinates":[-98.523385,45.458935],"type":"Point"}
}