{
  "type": "Feature",
  "properties": {
    "iso:country":"US",
    "sg:address":"39512 193rd St",
    "sg:city":"Hitchcock",
    "sg:phone":"+1 605 266 2881",
    "sg:postcode":"57348",
    "sg:province":"SD",
    "sg:tags":[
        "farm",
        "soybean"
    ],
    "wof:name":"Wietings Farms",
    "wof:placetype":"venue"
},
  "geometry": {"coordinates":[-98.31901499999999,44.589237],"type":"Point"}
}