{
  "type": "Feature",
  "properties": {
    "iso:country":"US",
    "sg:address":"2113 S Minnesota Ave",
    "sg:city":"Sioux Falls",
    "sg:classifiers":[
        {
            "category":"Food & Beverages",
            "subcategory":"Meat & Fish",
            "type":"Retail Goods"
        }
    ],
    "sg:phone":"+1 605 336 3104",
    "sg:postcode":"57105",
    "sg:province":"SD",
    "sg:website":"www.looksmarket.com",
    "wof:name":"Look's Meat Market & Gourmet",
    "wof:placetype":"venue"
},
  "geometry": {"coordinates":[-96.731348,43.524959],"type":"Point"}
}