{
  "type": "Feature",
  "properties": {
    "iso:country":"US",
    "sg:address":"2023 1st Ave",
    "sg:city":"Rapid City",
    "sg:classifiers":[
        {
            "category":"Manufacturing",
            "subcategory":"Buildings",
            "type":"Manufacturing & Wholesale Goods"
        }
    ],
    "sg:phone":"+1 605 343 3090",
    "sg:postcode":"57702",
    "sg:province":"SD",
    "sg:tags":[
        "home",
        "log",
        "cabin"
    ],
    "wof:name":"Mountain Woodworks",
    "wof:placetype":"venue"
},
  "geometry": {"coordinates":[-103.274571,44.065689],"type":"Point"}
}