{
  "type": "Feature",
  "properties": {
    "iso:country":"US",
    "sg:address":"20593 476th Ave",
    "sg:city":"White",
    "sg:phone":"+1 605 629 6571",
    "sg:postcode":"57276",
    "sg:province":"SD",
    "sg:tags":[
        "farm",
        "wheat"
    ],
    "wof:name":"Mike Thompson",
    "wof:placetype":"venue"
},
  "geometry": {"coordinates":[-96.686829,44.398832],"type":"Point"}
}