{
  "type": "Feature",
  "properties": {
    "iso:country":"US",
    "sg:address":"1335 7th St NW",
    "sg:city":"Watertown",
    "sg:classifiers":[
        {
            "category":"Building & Trades",
            "subcategory":"Construction",
            "type":"Services"
        }
    ],
    "sg:phone":"+1 605 882 1584",
    "sg:postcode":"57201",
    "sg:province":"SD",
    "sg:tags":[
        "excavating",
        "contractor"
    ],
    "wof:name":"Gene Day Excavating",
    "wof:placetype":"venue"
},
  "geometry": {"coordinates":[-97.126687,44.917332],"type":"Point"}
}