{
  "type": "Feature",
  "properties": {
    "iso:country":"US",
    "sg:address":"211 S 3rd St",
    "sg:city":"Howard",
    "sg:classifiers":[
        {
            "category":"Building & Trades",
            "subcategory":"Electrical",
            "type":"Services"
        }
    ],
    "sg:phone":"+1 605 772 5816",
    "sg:postcode":"57332",
    "sg:province":"SD",
    "sg:tags":[
        "electric",
        "contractor"
    ],
    "wof:name":"Bob's Electric",
    "wof:placetype":"venue"
},
  "geometry": {"coordinates":[-97.622668,43.600643],"type":"Point"}
}