{
  "type": "Feature",
  "properties": {
    "addr:full":"3200 W Maple St Sioux Falls SD 57107",
    "addr:housenumber":"3200",
    "addr:postcode":"57107",
    "addr:street":"W Maple St",
    "iso:country":"US",
    "sg:address":"3200 W Maple St",
    "sg:city":"Sioux Falls",
    "sg:classifiers":[
        {
            "category":"Travel",
            "subcategory":"Hotels & Motels",
            "type":"Entertainment"
        }
    ],
    "sg:phone":"+1 605 336 0650",
    "sg:postcode":"57107",
    "sg:province":"SD",
    "sg:tags":[
        "drinking",
        "eating",
        "operation"
    ],
    "sg:website":"www.ramkota.com",
    "wof:name":"Best Western Inn",
    "wof:placetype":"venue"
},
  "geometry": {"coordinates":[-96.769739,43.572968],"type":"Point"}
}