{
  "type": "Feature",
  "properties": {
    "iso:country":"US",
    "sg:address":"39392 280th St",
    "sg:city":"Armour",
    "sg:classifiers":[
        {
            "category":"Farming",
            "subcategory":"Dairy Farm",
            "type":"Manufacturing & Wholesale Goods"
        }
    ],
    "sg:phone":"+1 605 724 2109",
    "sg:postcode":"57313",
    "sg:province":"SD",
    "sg:tags":[
        "hog",
        "beef",
        "corn",
        "fe",
        "cattle",
        "or",
        "feedlot"
    ],
    "wof:name":"Ron Hinckley",
    "wof:placetype":"venue"
},
  "geometry": {"coordinates":[-98.30836499999999,43.326024],"type":"Point"}
}