{
  "type": "Feature",
  "properties": {
    "iso:country":"US",
    "sg:address":"102 Main St",
    "sg:city":"Piedmont",
    "sg:classifiers":[
        {
            "category":"Shopping",
            "subcategory":"Bicycles & Sporting Goods",
            "type":"Retail Goods"
        }
    ],
    "sg:phone":"+1 605 787 4700",
    "sg:postcode":"57769",
    "sg:province":"SD",
    "sg:tags":[
        "equipment",
        "golf",
        "supply"
    ],
    "wof:name":"Engineering Emporium",
    "wof:placetype":"venue"
},
  "geometry": {"coordinates":[-103.387884,44.232219],"type":"Point"}
}