{
  "type": "Feature",
  "properties": {
    "addr:full":"332 W Main St Lead SD 57754",
    "addr:housenumber":"332",
    "addr:postcode":"57754",
    "addr:street":"W Main St",
    "iso:country":"US",
    "sg:address":"332 W Main St",
    "sg:city":"Lead",
    "sg:classifiers":[
        {
            "category":"Real Estate",
            "subcategory":"Surveying",
            "type":"Services"
        }
    ],
    "sg:phone":"+1 605 722 3840",
    "sg:postcode":"57754",
    "sg:province":"SD",
    "sg:tags":[
        "surveyor"
    ],
    "wof:name":"Ponderosa Land Surveys",
    "wof:placetype":"venue"
},
  "geometry": {"coordinates":[-103.76660800000001,44.352061],"type":"Point"}
}