{
  "type": "Feature",
  "properties": {
    "iso:country":"US",
    "sg:address":"25809 Trade Ave",
    "sg:city":"Sioux Falls",
    "sg:classifiers":[
        {
            "category":"Retail",
            "subcategory":"Auto Rental",
            "type":"Services"
        }
    ],
    "sg:phone":"+1 605 543 6640",
    "sg:postcode":"57107",
    "sg:province":"SD",
    "sg:tags":[
        "truck",
        "tractor",
        "trailer"
    ],
    "wof:name":"Fowlds Brothers Trucking Inc",
    "wof:placetype":"venue"
},
  "geometry": {"coordinates":[-96.76666899999999,43.644638],"type":"Point"}
}