{
  "type": "Feature",
  "properties": {
    "addr:full":"47757 Co Rd 1b Elk Point SD 57025",
    "addr:housenumber":"47757;1b",
    "addr:postcode":"57025",
    "addr:street":"Co Rd",
    "iso:country":"US",
    "sg:address":"47757 Co Rd 1b",
    "sg:city":"Elk Point",
    "sg:classifiers":[
        {
            "category":"Wholesale",
            "subcategory":"Hardware",
            "type":"Manufacturing & Wholesale Goods"
        }
    ],
    "sg:phone":"+1 605 356 2332",
    "sg:postcode":"57025",
    "sg:province":"SD",
    "sg:tags":[
        "refrigerating"
    ],
    "wof:name":"A & A Refrigeration Svc",
    "wof:placetype":"venue"
},
  "geometry": {"coordinates":[-96.656514,42.672242],"type":"Point"}
}