{
  "type": "Feature",
  "properties": {
    "iso:country":"US",
    "sg:address":"105 W Saint Andrews Dr",
    "sg:city":"Sioux Falls",
    "sg:classifiers":[
        {
            "category":"Building & Trades",
            "subcategory":"Construction",
            "type":"Services"
        }
    ],
    "sg:phone":"+1 605 335 8664",
    "sg:postcode":"57108",
    "sg:province":"SD",
    "sg:tags":[
        "contractor"
    ],
    "wof:name":"Wooden Tradtionals",
    "wof:placetype":"venue"
},
  "geometry": {"coordinates":[-96.722864,43.496177],"type":"Point"}
}