{
  "type": "Feature",
  "properties": {
    "addr:full":"30334 408th Ave Avon SD 57315",
    "addr:housenumber":"30334",
    "addr:postcode":"57315",
    "addr:street":"408Th Ave",
    "iso:country":"US",
    "sg:address":"30334 408th Ave",
    "sg:city":"Avon",
    "sg:classifiers":[
        {
            "category":"Farming",
            "subcategory":"Dairy Farm",
            "type":"Manufacturing & Wholesale Goods"
        }
    ],
    "sg:phone":"+1 605 286 3305",
    "sg:postcode":"57315",
    "sg:province":"SD",
    "wof:name":"Bertus Farms",
    "wof:placetype":"venue"
},
  "geometry": {"coordinates":[-98.03026,42.985004],"type":"Point"}
}