{
  "type": "Feature",
  "properties": {
    "iso:country":"US",
    "sg:address":"1200 Clark St",
    "sg:city":"Rapid City",
    "sg:classifiers":[
        {
            "category":"Social Services",
            "type":"Services"
        }
    ],
    "sg:phone":"+1 605 393 0387",
    "sg:postcode":"57701",
    "sg:province":"SD",
    "sg:tags":[
        "support",
        "group"
    ],
    "wof:name":"Parkinsons Support Group",
    "wof:placetype":"venue"
},
  "geometry": {"coordinates":[-103.240053,44.074771],"type":"Point"}
}