{
  "type": "Feature",
  "properties": {
    "iso:country":"US",
    "sg:address":"26449 487th Ave",
    "sg:city":"Valley Springs",
    "sg:classifiers":[
        {
            "category":"Farming",
            "subcategory":"Livestock Farm",
            "type":"Manufacturing & Wholesale Goods"
        }
    ],
    "sg:phone":"+1 605 757 6594",
    "sg:postcode":"57068",
    "sg:province":"SD",
    "sg:tags":[
        "animal",
        "general"
    ],
    "wof:name":"Scholtens Farm",
    "wof:placetype":"venue"
},
  "geometry": {"coordinates":[-96.47242,43.552431],"type":"Point"}
}