{
  "type": "Feature",
  "properties": {
    "addr:full":"44867 303rd St Volin SD 57072",
    "addr:housenumber":"44867",
    "addr:postcode":"57072",
    "addr:street":"303Rd St",
    "iso:country":"US",
    "sg:address":"44867 303rd St",
    "sg:city":"Volin",
    "sg:phone":"+1 605 267 2380",
    "sg:postcode":"57072",
    "sg:province":"SD",
    "sg:tags":[
        "farm",
        "corn",
        "soybean"
    ],
    "wof:name":"David Hoxeng",
    "wof:placetype":"venue"
},
  "geometry": {"coordinates":[-97.209941,42.996136],"type":"Point"}
}