{
  "type": "Feature",
  "properties": {
    "addr:full":"801 W Blackhawk St Sioux Falls SD 57104",
    "addr:housenumber":"801",
    "addr:postcode":"57104",
    "addr:street":"W Blackhawk St",
    "iso:country":"US",
    "sg:address":"801 W Blackhawk St",
    "sg:city":"Sioux Falls",
    "sg:classifiers":[
        {
            "category":"Professional",
            "subcategory":"Printing & Photocopies",
            "type":"Services"
        }
    ],
    "sg:phone":"+1 605 357 8687",
    "sg:postcode":"57104",
    "sg:province":"SD",
    "sg:tags":[
        "contractor"
    ],
    "wof:name":"Sioux Falls Builders Exchange",
    "wof:placetype":"venue"
},
  "geometry": {"coordinates":[-96.73853699999999,43.568179],"type":"Point"}
}