{
  "type": "Feature",
  "properties": {
    "addr:full":"1001 Memory Ln Yankton SD 57078",
    "addr:housenumber":"1001",
    "addr:postcode":"57078",
    "addr:street":"Memory Ln",
    "iso:country":"US",
    "sg:address":"1001 Memory Ln",
    "sg:city":"Yankton",
    "sg:classifiers":[
        {
            "category":"Real Estate",
            "subcategory":"Real Estate Agent",
            "type":"Services"
        }
    ],
    "sg:phone":"+1 605 665 4512",
    "sg:postcode":"57078",
    "sg:province":"SD",
    "wof:name":"Midwest Associates Inc",
    "wof:placetype":"venue"
},
  "geometry": {"coordinates":[-97.38105299999999,42.878205],"type":"Point"}
}