{
  "type": "Feature",
  "properties": {
    "addr:full":"42549 300th St Scotland SD 57059",
    "addr:housenumber":"42549",
    "addr:postcode":"57059",
    "addr:street":"300Th St",
    "iso:country":"US",
    "sg:address":"42549 300th St",
    "sg:city":"Scotland",
    "sg:classifiers":[
        {
            "category":"Farming",
            "subcategory":"Livestock Farm",
            "type":"Manufacturing & Wholesale Goods"
        }
    ],
    "sg:phone":"+1 605 364 7493",
    "sg:postcode":"57059",
    "sg:province":"SD",
    "sg:tags":[
        "beef",
        "feedlot",
        "cattle"
    ],
    "wof:name":"Kenneth Kloucek Farm",
    "wof:placetype":"venue"
},
  "geometry": {"coordinates":[-97.69413900000001,43.039067],"type":"Point"}
}