{
  "type": "Feature",
  "properties": {
    "addr:full":"1808 Cardinal Ln Huron SD 57350",
    "addr:housenumber":"1808",
    "addr:postcode":"57350",
    "addr:street":"Cardinal Ln",
    "iso:country":"US",
    "sg:address":"1808 Cardinal Ln",
    "sg:city":"Huron",
    "sg:phone":"+1 605 353 1176",
    "sg:postcode":"57350",
    "sg:province":"SD",
    "sg:tags":[
        "farm",
        "corn",
        "soybean"
    ],
    "wof:name":"Rich Langbehm",
    "wof:placetype":"venue"
},
  "geometry": {"coordinates":[-98.22517999999999,44.345298],"type":"Point"}
}