{
  "type": "Feature",
  "properties": {
    "iso:country":"US",
    "sg:address":"25 Knollwood Dr",
    "sg:city":"Rapid City",
    "sg:classifiers":[
        {
            "category":"Real Estate",
            "subcategory":"Real Estate Operator",
            "type":"Services"
        }
    ],
    "sg:phone":"+1 605 341 4090",
    "sg:postcode":"57701",
    "sg:province":"SD",
    "sg:tags":[
        "apartment"
    ],
    "wof:name":"Knollwood Townhouses",
    "wof:placetype":"venue"
},
  "geometry": {"coordinates":[-103.21859000000001,44.102931],"type":"Point"}
}