{
  "type": "Feature",
  "properties": {
    "iso:country":"US",
    "sg:address":"937 23rd St SW",
    "sg:city":"Watertown",
    "sg:classifiers":[
        {
            "category":"Home & Garden",
            "subcategory":"Building Materials",
            "type":"Retail Goods"
        }
    ],
    "sg:phone":"+1 605 882 3534",
    "sg:postcode":"57201",
    "sg:province":"SD",
    "sg:tags":[
        "glass",
        "window",
        "plate"
    ],
    "wof:name":"Carloson's Glass & Mirror",
    "wof:placetype":"venue"
},
  "geometry": {"coordinates":[-97.150132,44.889562],"type":"Point"}
}