{
  "type": "Feature",
  "properties": {
    "iso:country":"US",
    "sg:address":"924 Broadway St",
    "sg:city":"Yankton",
    "sg:classifiers":[
        {
            "category":"Freight",
            "type":"Transportation"
        }
    ],
    "sg:phone":"+1 605 665 7413",
    "sg:postcode":"57078",
    "sg:province":"SD",
    "sg:tags":[
        "mover"
    ],
    "wof:name":"Vanderhule Moving & Storage",
    "wof:placetype":"venue"
},
  "geometry": {"coordinates":[-97.396749,42.877393],"type":"Point"}
}