{
  "type": "Feature",
  "properties": {
    "iso:country":"US",
    "sg:address":"412 3rd St",
    "sg:city":"Rapid City",
    "sg:classifiers":[
        {
            "category":"Manufacturing",
            "subcategory":"Printing",
            "type":"Manufacturing & Wholesale Goods"
        }
    ],
    "sg:phone":"+1 605 342 2757",
    "sg:postcode":"57701",
    "sg:province":"SD",
    "sg:tags":[
        "printer"
    ],
    "wof:name":"Padilla Printing",
    "wof:placetype":"venue"
},
  "geometry": {"coordinates":[-103.22127399999999,44.080276],"type":"Point"}
}