{
  "type": "Feature",
  "properties": {
    "iso:country":"US",
    "sg:address":"406 Mulberry St",
    "sg:city":"Yankton",
    "sg:classifiers":[
        {
            "category":"Building & Trades",
            "subcategory":"Plumbing",
            "type":"Services"
        }
    ],
    "sg:phone":"+1 605 665 5643",
    "sg:postcode":"57078",
    "sg:province":"SD",
    "sg:tags":[
        "contractor"
    ],
    "wof:name":"Wohls Plumbing & Heating",
    "wof:placetype":"venue"
},
  "geometry": {"coordinates":[-97.387417,42.872275],"type":"Point"}
}