{
  "type": "Feature",
  "properties": {
    "addr:full":"29878 449th Ave Irene SD 57037",
    "addr:housenumber":"29878",
    "addr:postcode":"57037",
    "addr:street":"449Th Ave",
    "iso:country":"US",
    "sg:address":"29878 449th Ave",
    "sg:city":"Irene",
    "sg:phone":"+1 605 263 3940",
    "sg:postcode":"57037",
    "sg:province":"SD",
    "sg:tags":[
        "farm",
        "corn"
    ],
    "wof:name":"TLC Vending",
    "wof:placetype":"venue"
},
  "geometry": {"coordinates":[-97.214685,43.068401],"type":"Point"}
}