{
  "type": "Feature",
  "properties": {
    "iso:country":"US",
    "sg:address":"201 Badger St",
    "sg:city":"Elkton",
    "sg:classifiers":[
        {
            "category":"Wholesale",
            "subcategory":"Machinery & Supplies",
            "type":"Manufacturing & Wholesale Goods"
        }
    ],
    "sg:phone":"+1 605 542 5071",
    "sg:postcode":"57026",
    "sg:province":"SD",
    "sg:tags":[
        "commercial",
        "fan"
    ],
    "sg:website":"www.tcf.com",
    "wof:name":"Twin City Fan & Blower Co",
    "wof:placetype":"venue"
},
  "geometry": {"coordinates":[-96.477747,44.236263],"type":"Point"}
}