{
  "type": "Feature",
  "properties": {
    "iso:country":"US",
    "sg:address":"2200 N Maple Ave",
    "sg:city":"Rapid City",
    "sg:classifiers":[
        {
            "category":"Restaurant",
            "type":"Food & Drink"
        }
    ],
    "sg:menulink":"http://www.allmenus.com/sd/rapid-city/123017-quiznos-sub/menu/",
    "sg:phone":"+1 605 388 1164",
    "sg:postcode":"57701",
    "sg:province":"SD",
    "sg:tags":[
        "wrap",
        "american",
        "sandwich"
    ],
    "wof:name":"Quiznos Sub",
    "wof:placetype":"venue"
},
  "geometry": {"coordinates":[-103.20795,44.108481],"type":"Point"}
}