{
  "type": "Feature",
  "properties": {
    "addr:full":"606 W 33rd St Sioux Falls SD 57105",
    "addr:housenumber":"606",
    "addr:postcode":"57105",
    "addr:street":"W 33Rd St",
    "iso:country":"US",
    "sg:address":"606 W 33rd St",
    "sg:city":"Sioux Falls",
    "sg:classifiers":[
        {
            "category":"Real Estate",
            "subcategory":"Real Estate Agent",
            "type":"Services"
        }
    ],
    "sg:phone":"+1 605 360 2177",
    "sg:postcode":"57105",
    "sg:province":"SD",
    "wof:name":"Joan Cota Real Estate",
    "wof:placetype":"venue"
},
  "geometry": {"coordinates":[-96.73368000000001,43.522161],"type":"Point"}
}