{
  "type": "Feature",
  "properties": {
    "iso:country":"US",
    "sg:address":"725 Meade St",
    "sg:city":"Rapid City",
    "sg:classifiers":[
        {
            "category":"Health Services",
            "subcategory":"Doctor",
            "type":"Services"
        }
    ],
    "sg:phone":"+1 605 399 4300",
    "sg:postcode":"57701",
    "sg:province":"SD",
    "sg:tags":[
        "physician",
        "surgeon"
    ],
    "wof:name":"Heart Doctors",
    "wof:placetype":"venue"
},
  "geometry": {"coordinates":[-103.231843,44.063261],"type":"Point"}
}