{
  "type": "Feature",
  "properties": {
    "iso:country":"US",
    "sg:address":"526 SE 4th St",
    "sg:city":"Madison",
    "sg:classifiers":[
        {
            "category":"Building & Trades",
            "subcategory":"Pest Control",
            "type":"Services"
        }
    ],
    "sg:phone":"+1 605 256 0368",
    "sg:postcode":"57042",
    "sg:province":"SD",
    "wof:name":"Horizon Spraying",
    "wof:placetype":"venue"
},
  "geometry": {"coordinates":[-97.107861,44.000622],"type":"Point"}
}