{
  "type": "Feature",
  "properties": {
    "iso:country":"US",
    "sg:address":"1615 N Harrison Ave",
    "sg:city":"Pierre",
    "sg:classifiers":[
        {
            "category":"Banks & Credit Unions",
            "subcategory":"Investment Brokerage",
            "type":"Services"
        }
    ],
    "sg:phone":"+1 605 224 6777",
    "sg:postcode":"57501",
    "sg:province":"SD",
    "sg:tags":[
        "consultant",
        "planning",
        "financial"
    ],
    "wof:name":"American Express Financial Adv",
    "wof:placetype":"venue"
},
  "geometry": {"coordinates":[-100.319506,44.376504],"type":"Point"}
}