{
  "type": "Feature",
  "properties": {
    "iso:country":"US",
    "sg:address":"2040 W Main St",
    "sg:city":"Rapid City",
    "sg:classifiers":[
        {
            "category":"Government",
            "subcategory":"Office",
            "type":"Public Place"
        }
    ],
    "sg:phone":"+1 605 394 2510",
    "sg:postcode":"57702",
    "sg:province":"SD",
    "wof:name":"South Dakota Engineering",
    "wof:placetype":"venue"
},
  "geometry": {"coordinates":[-103.254874,44.081564],"type":"Point"}
}