{
  "type": "Feature",
  "properties": {
    "addr:full":"336 1st Ave Ipswich SD 57451",
    "addr:housenumber":"336",
    "addr:postcode":"57451",
    "addr:street":"1St Ave",
    "iso:country":"US",
    "sg:address":"336 1st Ave",
    "sg:city":"Ipswich",
    "sg:classifiers":[
        {
            "category":"Government",
            "subcategory":"Post Office",
            "type":"Public Place"
        }
    ],
    "sg:phone":"+1 605 426 6091",
    "sg:postcode":"57451",
    "sg:province":"SD",
    "wof:name":"US Post Office",
    "wof:placetype":"venue"
},
  "geometry": {"coordinates":[-99.028829,45.444389],"type":"Point"}
}