{
  "type": "Feature",
  "properties": {
    "iso:country":"US",
    "sg:address":"616 Wilson Ave",
    "sg:city":"Brookings",
    "sg:classifiers":[
        {
            "category":"Recreation",
            "subcategory":"Arcade",
            "type":"Entertainment"
        }
    ],
    "sg:phone":"+1 605 692 5801",
    "sg:postcode":"57006",
    "sg:province":"SD",
    "sg:tags":[
        "amusement",
        "devices"
    ],
    "wof:name":"Hicks Enterprises",
    "wof:placetype":"venue"
},
  "geometry": {"coordinates":[-96.80745899999999,44.312825],"type":"Point"}
}