{
  "type": "Feature",
  "properties": {
    "iso:country":"US",
    "sg:address":"3710 N Lewis Ave",
    "sg:city":"Sioux Falls",
    "sg:classifiers":[
        {
            "category":"Autos & Motor Vehicles",
            "subcategory":"Automobile Sales",
            "type":"Retail Goods"
        }
    ],
    "sg:phone":"+1 605 334 9765",
    "sg:postcode":"57104",
    "sg:province":"SD",
    "wof:name":"Wicks Truck Trailers Inc",
    "wof:placetype":"venue"
},
  "geometry": {"coordinates":[-96.701317,43.586365],"type":"Point"}
}