{
  "type": "Feature",
  "properties": {
    "addr:full":"335 Mount Rushmore Rd Custer SD 57730",
    "addr:housenumber":"335",
    "addr:postcode":"57730",
    "addr:street":"Mount Rushmore Rd",
    "iso:country":"US",
    "sg:address":"335 Mount Rushmore Rd",
    "sg:city":"Custer",
    "sg:classifiers":[
        {
            "category":"Ice Cream",
            "type":"Food & Drink"
        }
    ],
    "sg:menulink":"http://www.allmenus.com/sd/custer/192710-dairy-queen/menu/",
    "sg:phone":"+1 605 673 5556",
    "sg:postcode":"57730",
    "sg:province":"SD",
    "sg:tags":[
        "burger",
        "american"
    ],
    "wof:name":"Dairy Queen",
    "wof:placetype":"venue"
},
  "geometry": {"coordinates":[-103.60269599999999,43.765613],"type":"Point"}
}