{
  "type": "Feature",
  "properties": {
    "iso:country":"US",
    "sg:address":"2705 1st Ave",
    "sg:city":"Selby",
    "sg:classifiers":[
        {
            "category":"Personal",
            "subcategory":"Beauty Salon",
            "type":"Services"
        }
    ],
    "sg:phone":"+1 605 649 7763",
    "sg:postcode":"57472",
    "sg:province":"SD",
    "wof:name":"Patel's Beauty Shop",
    "wof:placetype":"venue"
},
  "geometry": {"coordinates":[-100.027755,45.505392],"type":"Point"}
}