{
  "type": "Feature",
  "properties": {
    "addr:full":"29130 468th Ave Beresford SD 57004",
    "addr:housenumber":"29130",
    "addr:postcode":"57004",
    "addr:street":"468Th Ave",
    "iso:country":"US",
    "sg:address":"29130 468th Ave",
    "sg:city":"Beresford",
    "sg:classifiers":[
        {
            "category":"Farming",
            "subcategory":"Farm",
            "type":"Manufacturing & Wholesale Goods"
        }
    ],
    "sg:phone":"+1 605 957 4490",
    "sg:postcode":"57004",
    "sg:province":"SD",
    "sg:tags":[
        "crop",
        "general"
    ],
    "wof:name":"Lowell Bartels",
    "wof:placetype":"venue"
},
  "geometry": {"coordinates":[-96.84542399999999,43.166091],"type":"Point"}
}