{
  "type": "Feature",
  "properties": {
    "addr:full":"700 N Helen Ave Sioux Falls SD 57104",
    "addr:housenumber":"700",
    "addr:postcode":"57104",
    "addr:street":"N Helen Ave",
    "iso:country":"US",
    "sg:address":"700 N Helen Ave",
    "sg:city":"Sioux Falls",
    "sg:classifiers":[
        {
            "category":"Home & Garden",
            "subcategory":"Building Materials",
            "type":"Retail Goods"
        }
    ],
    "sg:phone":"+1 605 334 7070",
    "sg:postcode":"57104",
    "sg:province":"SD",
    "sg:tags":[
        "siding"
    ],
    "wof:name":"Contractors Siding & Windows",
    "wof:placetype":"venue"
},
  "geometry": {"coordinates":[-96.766082,43.557475],"type":"Point"}
}