{
  "type": "Feature",
  "properties": {
    "addr:full":"27096 Kerslake Pl Tea SD 57064",
    "addr:postcode":"27096;57064",
    "addr:street":"Kerslake Pl",
    "iso:country":"US",
    "sg:address":"27096 Kerslake Pl",
    "sg:city":"Tea",
    "sg:classifiers":[
        {
            "category":"Retail",
            "subcategory":"Repair Shop",
            "type":"Services"
        }
    ],
    "sg:phone":"+1 605 498 0006",
    "sg:postcode":"57064",
    "sg:province":"SD",
    "sg:tags":[
        "upholsterer"
    ],
    "wof:name":"Cliff Avenue Upholstery",
    "wof:placetype":"venue"
},
  "geometry": {"coordinates":[-96.81751300000001,43.464797],"type":"Point"}
}