{
  "type": "Feature",
  "properties": {
    "iso:country":"US",
    "sg:address":"2123 Jackson Blvd",
    "sg:city":"Rapid City",
    "sg:classifiers":[
        {
            "category":"Food & Beverages",
            "subcategory":"Specialty",
            "type":"Retail Goods"
        }
    ],
    "sg:phone":"+1 605 716 9210",
    "sg:postcode":"57702",
    "sg:province":"SD",
    "sg:tags":[
        "tea",
        "coffee"
    ],
    "wof:name":"Capuccino Charlie's",
    "wof:placetype":"venue"
},
  "geometry": {"coordinates":[-103.255332,44.072386],"type":"Point"}
}