{
  "type": "Feature",
  "properties": {
    "iso:country":"US",
    "sg:address":"3211 W Sencore Dr",
    "sg:city":"Sioux Falls",
    "sg:classifiers":[
        {
            "category":"Professional",
            "subcategory":"Management & Consulting",
            "type":"Services"
        }
    ],
    "sg:phone":"+1 605 334 2371",
    "sg:postcode":"57107",
    "sg:province":"SD",
    "sg:tags":[
        "consultant",
        "motel",
        "hotel"
    ],
    "sg:website":"www.regency-mgmt.com",
    "wof:name":"Regency Hotel Management",
    "wof:placetype":"venue"
},
  "geometry": {"coordinates":[-96.76779399999999,43.575463],"type":"Point"}
}