{
  "type": "Feature",
  "properties": {
    "iso:country":"US",
    "sg:address":"821 Jackson Blvd",
    "sg:city":"Rapid City",
    "sg:classifiers":[
        {
            "category":"Shopping",
            "type":"Retail Goods"
        }
    ],
    "sg:phone":"+1 605 342 5902",
    "sg:postcode":"57702",
    "sg:province":"SD",
    "sg:tags":[
        "hearing",
        "equipment",
        "supply",
        "impaired"
    ],
    "wof:name":"Rapid City Hearing Aid Ctr",
    "wof:placetype":"venue"
},
  "geometry": {"coordinates":[-103.250639,44.077263],"type":"Point"}
}