{
  "type": "Feature",
  "properties": {
    "iso:country":"US",
    "sg:address":"1900 Hoffman Rd",
    "sg:city":"North Sioux City",
    "sg:phone":"+1 605 232 4109",
    "sg:postcode":"57049",
    "sg:province":"SD",
    "sg:tags":[
        "farm",
        "wheat",
        "soybean"
    ],
    "wof:name":"Clyde Hoffman",
    "wof:placetype":"venue"
},
  "geometry": {"coordinates":[-96.517864,42.508788],"type":"Point"}
}