{
  "type": "Feature",
  "properties": {
    "iso:country":"US",
    "sg:address":"105 Main St",
    "sg:city":"Montrose",
    "sg:classifiers":[
        {
            "category":"Government",
            "subcategory":"Post Office",
            "type":"Public Place"
        }
    ],
    "sg:phone":"+1 605 363 5119",
    "sg:postcode":"57048",
    "sg:province":"SD",
    "wof:name":"US Post Office",
    "wof:placetype":"venue"
},
  "geometry": {"coordinates":[-97.185127,43.70095],"type":"Point"}
}