{
  "type": "Feature",
  "properties": {
    "addr:full":"46698 197th St Bruce SD 57220",
    "addr:housenumber":"46698",
    "addr:postcode":"57220",
    "addr:street":"197Th St",
    "iso:country":"US",
    "sg:address":"46698 197th St",
    "sg:city":"Bruce",
    "sg:classifiers":[
        {
            "category":"Farming",
            "subcategory":"Farm",
            "type":"Manufacturing & Wholesale Goods"
        }
    ],
    "sg:phone":"+1 605 873 2343",
    "sg:postcode":"57220",
    "sg:province":"SD",
    "sg:tags":[
        "crop",
        "general"
    ],
    "wof:name":"Steve Casjene",
    "wof:placetype":"venue"
},
  "geometry": {"coordinates":[-96.872348,44.529227],"type":"Point"}
}