{
  "type": "Feature",
  "properties": {
    "iso:country":"US",
    "sg:address":"125 Waterloo St",
    "sg:city":"Rapid City",
    "sg:classifiers":[
        {
            "category":"Recreation",
            "type":"Entertainment"
        }
    ],
    "sg:phone":"+1 605 394 4167",
    "sg:postcode":"57701",
    "sg:province":"SD",
    "sg:tags":[
        "parks"
    ],
    "wof:name":"Rapid City Recreation Dept",
    "wof:placetype":"venue"
},
  "geometry": {"coordinates":[-103.205822,44.083439],"type":"Point"}
}