{
  "type": "Feature",
  "properties": {
    "iso:country":"US",
    "sg:address":"921 9th Ave",
    "sg:city":"Brandon",
    "sg:classifiers":[
        {
            "category":"Shopping",
            "type":"Retail Goods"
        }
    ],
    "sg:phone":"+1 605 582 8255",
    "sg:postcode":"57005",
    "sg:province":"SD",
    "sg:tags":[
        "chemical"
    ],
    "wof:name":"Front Line Chemicals",
    "wof:placetype":"venue"
},
  "geometry": {"coordinates":[-96.575681,43.60577],"type":"Point"}
}