{
  "type": "Feature",
  "properties": {
    "iso:country":"US",
    "sg:address":"104 Main Ave N",
    "sg:city":"Wagner",
    "sg:classifiers":[
        {
            "category":"Personal",
            "subcategory":"Beauty Salon",
            "type":"Services"
        }
    ],
    "sg:phone":"+1 605 384 4767",
    "sg:postcode":"57380",
    "sg:province":"SD",
    "sg:tags":[
        "shop"
    ],
    "wof:name":"Rejuve",
    "wof:placetype":"venue"
},
  "geometry": {"coordinates":[-98.29358,43.082606],"type":"Point"}
}