{
  "type": "Feature",
  "properties": {
    "addr:full":"25965 374th Ave White Lake SD 57383",
    "addr:housenumber":"25965",
    "addr:postcode":"57383",
    "addr:street":"374Th Ave",
    "iso:country":"US",
    "sg:address":"25965 374th Ave",
    "sg:city":"White Lake",
    "sg:classifiers":[
        {
            "category":"Farming",
            "subcategory":"Livestock Farm",
            "type":"Manufacturing & Wholesale Goods"
        }
    ],
    "sg:phone":"+1 605 249 2503",
    "sg:postcode":"57383",
    "sg:province":"SD",
    "sg:tags":[
        "corn",
        "wheat",
        "feedlot",
        "beef",
        "cattle"
    ],
    "wof:name":"Dale Beckmann",
    "wof:placetype":"venue"
},
  "geometry": {"coordinates":[-98.71384999999999,43.627771],"type":"Point"}
}