{
  "type": "Feature",
  "properties": {
    "addr:full":"1743 Dakota Ave S Huron SD 57350",
    "addr:housenumber":"1743",
    "addr:postcode":"57350",
    "addr:street":"Dakota Ave S",
    "iso:country":"US",
    "sg:address":"1743 Dakota Ave S",
    "sg:city":"Huron",
    "sg:classifiers":[
        {
            "category":"Utilities",
            "subcategory":"Mobile Phone",
            "type":"Services"
        }
    ],
    "sg:phone":"+1 605 352 7400",
    "sg:postcode":"57350",
    "sg:province":"SD",
    "sg:tags":[
        "telephone",
        "cellular"
    ],
    "wof:name":"Cellular Connection",
    "wof:placetype":"venue"
},
  "geometry": {"coordinates":[-98.214242,44.346052],"type":"Point"}
}