{
  "type": "Feature",
  "properties": {
    "iso:country":"US",
    "sg:address":"1711 Minnekahta Ave",
    "sg:city":"Hot Springs",
    "sg:classifiers":[
        {
            "category":"Professional",
            "subcategory":"Lawyer & Legal Services",
            "type":"Services"
        }
    ],
    "sg:phone":"+1 605 745 6774",
    "sg:postcode":"57747",
    "sg:province":"SD",
    "sg:tags":[
        "attorney"
    ],
    "wof:name":"Koehn Law Office",
    "wof:placetype":"venue"
},
  "geometry": {"coordinates":[-103.484508,43.435101],"type":"Point"}
}