{
  "type": "Feature",
  "properties": {
    "iso:country":"US",
    "sg:address":"1002 S Dakota St Ste 102",
    "sg:city":"Milbank",
    "sg:classifiers":[
        {
            "category":"Professional",
            "subcategory":"Lawyer & Legal Services",
            "type":"Services"
        }
    ],
    "sg:phone":"+1 605 432 5133",
    "sg:postcode":"57252",
    "sg:province":"SD",
    "sg:tags":[
        "attorney",
        "practice"
    ],
    "wof:name":"Nelson Law Office",
    "wof:placetype":"venue"
},
  "geometry": {"coordinates":[-96.62047699999999,45.22794],"type":"Point"}
}