{
  "type": "Feature",
  "properties": {
    "iso:country":"US",
    "sg:address":"13282 308th Ave",
    "sg:city":"Selby",
    "sg:classifiers":[
        {
            "category":"Farming",
            "subcategory":"Livestock Farm",
            "type":"Manufacturing & Wholesale Goods"
        }
    ],
    "sg:phone":"+1 605 649 7041",
    "sg:postcode":"57472",
    "sg:province":"SD",
    "sg:tags":[
        "animal",
        "general"
    ],
    "wof:name":"Donald C Lemler",
    "wof:placetype":"venue"
},
  "geometry": {"coordinates":[-100.017638,45.466767],"type":"Point"}
}