{
  "type": "Feature",
  "properties": {
    "iso:country":"US",
    "sg:address":"626 2nd St",
    "sg:city":"Sturgis",
    "sg:classifiers":[
        {
            "category":"Building & Trades",
            "subcategory":"Construction",
            "type":"Services"
        }
    ],
    "sg:phone":"+1 605 347 8613",
    "sg:postcode":"57785",
    "sg:province":"SD",
    "sg:tags":[
        "heavy"
    ],
    "wof:name":"Homesite Development",
    "wof:placetype":"venue"
},
  "geometry": {"coordinates":[-103.512612,44.418376],"type":"Point"}
}