{
  "type": "Feature",
  "properties": {
    "addr:full":"1312 S Cliff Ave Sioux Falls SD 57105",
    "addr:housenumber":"1312",
    "addr:postcode":"57105",
    "addr:street":"S Cliff Ave",
    "iso:country":"US",
    "sg:address":"1312 S Cliff Ave",
    "sg:city":"Sioux Falls",
    "sg:classifiers":[
        {
            "category":"Building & Trades",
            "subcategory":"Plumbing",
            "type":"Services"
        }
    ],
    "sg:phone":"+1 605 339 4492",
    "sg:postcode":"57105",
    "sg:province":"SD",
    "sg:tags":[
        "plumbing",
        "contractor"
    ],
    "wof:name":"All In One",
    "wof:placetype":"venue"
},
  "geometry": {"coordinates":[-96.711223,43.534005],"type":"Point"}
}