{
  "type": "Feature",
  "properties": {
    "addr:full":"47450 213th St Aurora SD 57002",
    "addr:housenumber":"47450",
    "addr:postcode":"57002",
    "addr:street":"213Th St",
    "iso:country":"US",
    "sg:address":"47450 213th St",
    "sg:city":"Aurora",
    "sg:phone":"+1 605 693 3962",
    "sg:postcode":"57002",
    "sg:province":"SD",
    "sg:tags":[
        "farm",
        "grain",
        "cash"
    ],
    "wof:name":"Charles Slocum",
    "wof:placetype":"venue"
},
  "geometry": {"coordinates":[-96.72954799999999,44.296924],"type":"Point"}
}