{
  "type": "Feature",
  "properties": {
    "iso:country":"US",
    "sg:address":"403 N Kiwanis Ave",
    "sg:city":"Sioux Falls",
    "sg:classifiers":[
        {
            "category":"Manufacturing",
            "subcategory":"Signs",
            "type":"Manufacturing & Wholesale Goods"
        }
    ],
    "sg:phone":"+1 605 336 7031",
    "sg:postcode":"57104",
    "sg:province":"SD",
    "sg:tags":[
        "neon",
        "mfg"
    ],
    "wof:name":"Ace Neon Sign & Service Inc",
    "wof:placetype":"venue"
},
  "geometry": {"coordinates":[-96.761223,43.552326],"type":"Point"}
}