{
  "type": "Feature",
  "properties": {
    "iso:country":"US",
    "sg:address":"114 Commercial Ave SE",
    "sg:city":"Highmore",
    "sg:classifiers":[
        {
            "category":"Banks & Credit Unions",
            "subcategory":"Bank",
            "type":"Services"
        }
    ],
    "sg:phone":"+1 605 852 2177",
    "sg:postcode":"57345",
    "sg:province":"SD",
    "wof:name":"Heartland State Bank",
    "wof:placetype":"venue"
},
  "geometry": {"coordinates":[-99.44009,44.519868],"type":"Point"}
}