{
  "type": "Feature",
  "properties": {
    "addr:full":"3908 Parkridge Dr Rapid City SD 57702",
    "addr:housenumber":"3908",
    "addr:postcode":"57702",
    "addr:street":"Parkridge Dr",
    "iso:country":"US",
    "sg:address":"3908 Parkridge Dr",
    "sg:city":"Rapid City",
    "sg:classifiers":[
        {
            "category":"Cinema",
            "subcategory":"Movie Rental",
            "type":"Entertainment"
        }
    ],
    "sg:phone":"+1 605 342 6026",
    "sg:postcode":"57702",
    "sg:province":"SD",
    "sg:tags":[
        "video",
        "tape"
    ],
    "wof:name":"Lynns Video",
    "wof:placetype":"venue"
},
  "geometry": {"coordinates":[-103.279269,44.046298],"type":"Point"}
}