{
  "type": "Feature",
  "properties": {
    "iso:country":"US",
    "sg:address":"1408 S 6th St",
    "sg:city":"Aberdeen",
    "sg:classifiers":[
        {
            "category":"Retail",
            "subcategory":"Laundry & Dry Cleaning",
            "type":"Services"
        }
    ],
    "sg:phone":"+1 605 229 0289",
    "sg:postcode":"57401",
    "sg:province":"SD",
    "sg:tags":[
        "cleaners"
    ],
    "wof:name":"Aberdeen Clean-All",
    "wof:placetype":"venue"
},
  "geometry": {"coordinates":[-98.496653,45.450117],"type":"Point"}
}