{
  "type": "Feature",
  "properties": {
    "iso:country":"US",
    "sg:address":"17990 Polo Dr",
    "sg:city":"Orient",
    "sg:classifiers":[
        {
            "category":"Travel",
            "subcategory":"Hotels & Motels",
            "type":"Entertainment"
        }
    ],
    "sg:phone":"+1 605 392 2399",
    "sg:postcode":"57467",
    "sg:province":"SD",
    "sg:tags":[
        "operation"
    ],
    "wof:name":"Cherlys Catering",
    "wof:placetype":"venue"
},
  "geometry": {"coordinates":[-99.108059,44.781032],"type":"Point"}
}