{
  "type": "Feature",
  "properties": {
    "addr:full":"17478 457th Ave Watertown SD 57201",
    "addr:housenumber":"17478",
    "addr:postcode":"57201",
    "addr:street":"457Th Ave",
    "iso:country":"US",
    "sg:address":"17478 457th Ave",
    "sg:city":"Watertown",
    "sg:phone":"+1 605 882 0431",
    "sg:postcode":"57201",
    "sg:province":"SD",
    "sg:tags":[
        "farm",
        "grain",
        "cash"
    ],
    "wof:name":"Raml Bob Farm of",
    "wof:placetype":"venue"
},
  "geometry": {"coordinates":[-97.067578,44.850146],"type":"Point"}
}