{
  "type": "Feature",
  "properties": {
    "iso:country":"US",
    "sg:address":"39211 133rd St",
    "sg:city":"Aberdeen",
    "sg:phone":"+1 605 725 6999",
    "sg:postcode":"57401",
    "sg:province":"SD",
    "sg:tags":[
        "agricultural",
        "product"
    ],
    "wof:name":"Precision Ag Solutions",
    "wof:placetype":"venue"
},
  "geometry": {"coordinates":[-98.386729,45.458546],"type":"Point"}
}