{
  "type": "Feature",
  "properties": {
    "iso:country":"US",
    "sg:address":"215 10th St NW",
    "sg:city":"Watertown",
    "sg:classifiers":[
        {
            "category":"Professional",
            "subcategory":"Lawyer & Legal Services",
            "type":"Services"
        }
    ],
    "sg:phone":"+1 605 886 0010",
    "sg:postcode":"57201",
    "sg:province":"SD",
    "sg:tags":[
        "attorney"
    ],
    "sg:website":"www.schoenbecklaw.com",
    "wof:name":"Schoenbeck Law Office",
    "wof:placetype":"venue"
},
  "geometry": {"coordinates":[-97.131345,44.903354],"type":"Point"}
}