{
  "type": "Feature",
  "properties": {
    "iso:country":"US",
    "sg:address":"1800 Broadway St",
    "sg:city":"Yankton",
    "sg:classifiers":[
        {
            "category":"Real Estate",
            "subcategory":"Surveying",
            "type":"Services"
        }
    ],
    "sg:phone":"+1 605 665 5571",
    "sg:postcode":"57078",
    "sg:province":"SD",
    "sg:tags":[
        "surveyor"
    ],
    "wof:name":"Johnson Engineering Co",
    "wof:placetype":"venue"
},
  "geometry": {"coordinates":[-97.396513,42.886055],"type":"Point"}
}