{
  "type": "Feature",
  "properties": {
    "addr:full":"4305 E 28th St Sioux Falls SD 57103",
    "addr:housenumber":"4305",
    "addr:postcode":"57103",
    "addr:street":"E 28Th St",
    "iso:country":"US",
    "sg:address":"4305 E 28th St",
    "sg:city":"Sioux Falls",
    "sg:classifiers":[
        {
            "category":"Real Estate",
            "subcategory":"Real Estate Agent",
            "type":"Services"
        }
    ],
    "sg:phone":"+1 605 332 0755",
    "sg:postcode":"57103",
    "sg:province":"SD",
    "wof:name":"Myers Real Estate",
    "wof:placetype":"venue"
},
  "geometry": {"coordinates":[-96.674886,43.52736],"type":"Point"}
}