{
  "type": "Feature",
  "properties": {
    "iso:country":"US",
    "sg:address":"1220 Mount Rushmore Rd",
    "sg:city":"Rapid City",
    "sg:classifiers":[
        {
            "category":"Banks & Credit Unions",
            "subcategory":"Bank",
            "type":"Services"
        }
    ],
    "sg:phone":"+1 605 716 7373",
    "sg:postcode":"57701",
    "sg:province":"SD",
    "sg:tags":[
        "mortgage",
        "loan",
        "broker",
        "real estate"
    ],
    "sg:website":"www.premierhomenet.com",
    "wof:name":"Premier Home Mortgage LLC",
    "wof:placetype":"venue"
},
  "geometry": {"coordinates":[-103.232335,44.073972],"type":"Point"}
}