{
  "type": "Feature",
  "properties": {
    "iso:country":"US",
    "sg:address":"1231 E 57th St",
    "sg:city":"Sioux Falls",
    "sg:classifiers":[
        {
            "category":"Food & Beverages",
            "subcategory":"Groceries & Convenience Stores",
            "type":"Retail Goods"
        }
    ],
    "sg:phone":"+1 605 271 7171",
    "sg:postcode":"57108",
    "sg:province":"SD",
    "sg:tags":[
        "product"
    ],
    "wof:name":"Sunshine Foods",
    "wof:placetype":"venue"
},
  "geometry": {"coordinates":[-96.708918,43.500285],"type":"Point"}
}