{
  "type": "Feature",
  "properties": {
    "iso:country":"US",
    "sg:address":"4208 S Florence Ave",
    "sg:city":"Sioux Falls",
    "sg:classifiers":[
        {
            "category":"Real Estate",
            "subcategory":"Real Estate Agent",
            "type":"Services"
        }
    ],
    "sg:phone":"+1 605 261 1148",
    "sg:postcode":"57103",
    "sg:province":"SD",
    "sg:tags":[
        "inspection"
    ],
    "wof:name":"A-1 Home Inspections",
    "wof:placetype":"venue"
},
  "geometry": {"coordinates":[-96.674474,43.506693],"type":"Point"}
}