{
  "type": "Feature",
  "properties": {
    "iso:country":"US",
    "sg:address":"811 W Summit St",
    "sg:city":"Lead",
    "sg:classifiers":[
        {
            "category":"Building & Trades",
            "subcategory":"Cleaning & Sanitation",
            "type":"Services"
        }
    ],
    "sg:phone":"+1 605 584 3171",
    "sg:postcode":"57754",
    "sg:province":"SD",
    "sg:tags":[
        "janitor"
    ],
    "wof:name":"Mc Gruder & Wagner",
    "wof:placetype":"venue"
},
  "geometry": {"coordinates":[-103.772494,44.347556],"type":"Point"}
}