{
  "type": "Feature",
  "properties": {
    "iso:country":"US",
    "sg:address":"410 4th St",
    "sg:city":"Brookings",
    "sg:classifiers":[
        {
            "category":"Shopping",
            "subcategory":"Shoes",
            "type":"Retail Goods"
        }
    ],
    "sg:phone":"+1 605 692 2414",
    "sg:postcode":"57006",
    "sg:province":"SD",
    "wof:name":"Bartling's Shoes",
    "wof:placetype":"venue"
},
  "geometry": {"coordinates":[-96.798495,44.309038],"type":"Point"}
}