{
  "type": "Feature",
  "properties": {
    "iso:country":"US",
    "sg:address":"45631 162nd St",
    "sg:city":"Watertown",
    "sg:classifiers":[
        {
            "category":"Building & Trades",
            "subcategory":"Construction",
            "type":"Services"
        }
    ],
    "sg:phone":"+1 605 882 1912",
    "sg:postcode":"57201",
    "sg:province":"SD",
    "sg:tags":[
        "industrial"
    ],
    "wof:name":"Northern Con-Agg Inc",
    "wof:placetype":"venue"
},
  "geometry": {"coordinates":[-97.079215,45.035153],"type":"Point"}
}