{
  "type": "Feature",
  "properties": {
    "iso:country":"US",
    "sg:address":"28053 397th Ave",
    "sg:city":"Armour",
    "sg:phone":"+1 605 779 6551",
    "sg:postcode":"57313",
    "sg:province":"SD",
    "sg:tags":[
        "farm",
        "grain",
        "cash"
    ],
    "wof:name":"Dwight Brenner",
    "wof:placetype":"venue"
},
  "geometry": {"coordinates":[-98.246708,43.317951],"type":"Point"}
}