{
  "type": "Feature",
  "properties": {
    "iso:country":"US",
    "sg:address":"196 E 6th St",
    "sg:city":"Sioux Falls",
    "sg:classifiers":[
        {
            "category":"Professional",
            "subcategory":"Business Services",
            "type":"Services"
        }
    ],
    "sg:phone":"+1 605 332 0472",
    "sg:postcode":"57104",
    "sg:province":"SD",
    "sg:tags":[
        "interior",
        "design"
    ],
    "wof:name":"Carmody Kathryn Intr Design",
    "wof:placetype":"venue"
},
  "geometry": {"coordinates":[-96.72551,43.551291],"type":"Point"}
}