{
  "type": "Feature",
  "properties": {
    "addr:full":"821 Jackson Blvd Rapid City SD 57702",
    "addr:housenumber":"821",
    "addr:postcode":"57702",
    "addr:street":"Jackson Blvd",
    "iso:country":"US",
    "sg:address":"821 Jackson Blvd",
    "sg:city":"Rapid City",
    "sg:classifiers":[
        {
            "category":"Insurance",
            "subcategory":"Insurance Agent",
            "type":"Services"
        }
    ],
    "sg:phone":"+1 605 342 1311",
    "sg:postcode":"57702",
    "sg:province":"SD",
    "wof:name":"American Family Insurance",
    "wof:placetype":"venue"
},
  "geometry": {"coordinates":[-103.25063900000001,44.077263],"type":"Point"}
}