{
  "type": "Feature",
  "properties": {
    "addr:full":"602 W Grand Xing Mobridge SD 57601",
    "addr:housenumber":"602",
    "addr:postcode":"57601",
    "addr:street":"W Grand Xing",
    "iso:country":"US",
    "sg:address":"602 W Grand Xing",
    "sg:city":"Mobridge",
    "sg:classifiers":[
        {
            "category":"Food & Beverages",
            "subcategory":"Liquor & Beverages",
            "type":"Retail Goods"
        }
    ],
    "sg:phone":"+1 605 845 2350",
    "sg:postcode":"57601",
    "sg:province":"SD",
    "wof:name":"Bottle Shop",
    "wof:placetype":"venue"
},
  "geometry": {"coordinates":[-100.442505,45.537444],"type":"Point"}
}