{
  "type": "Feature",
  "properties": {
    "iso:country":"US",
    "sg:address":"1060 Empire Mall",
    "sg:city":"Sioux Falls",
    "sg:classifiers":[
        {
            "category":"Shopping",
            "subcategory":"Clothing, Apparel, & Fashions",
            "type":"Retail Goods"
        }
    ],
    "sg:phone":"+1 605 361 2045",
    "sg:postcode":"57106",
    "sg:province":"SD",
    "sg:website":"www.buckle.com",
    "wof:name":"Buckle",
    "wof:placetype":"venue"
},
  "geometry": {"coordinates":[-96.774796,43.514227],"type":"Point"}
}