{
  "type": "Feature",
  "properties": {
    "iso:country":"US",
    "sg:address":"1623 6th Ave SE",
    "sg:city":"Aberdeen",
    "sg:classifiers":[
        {
            "category":"Recreation",
            "type":"Entertainment"
        }
    ],
    "sg:phone":"+1 605 225 0088",
    "sg:postcode":"57401",
    "sg:province":"SD",
    "sg:tags":[
        "club",
        "sport"
    ],
    "sg:website":"www.aberdeensoccer.com",
    "wof:name":"Aberdeen Soccer Assn",
    "wof:placetype":"venue"
},
  "geometry": {"coordinates":[-98.464386,45.459273],"type":"Point"}
}