{
  "type": "Feature",
  "properties": {
    "addr:full":"40870 110th St Hecla SD 57446",
    "addr:housenumber":"40870",
    "addr:postcode":"57446",
    "addr:street":"110Th St",
    "iso:country":"US",
    "sg:address":"40870 110th St",
    "sg:city":"Hecla",
    "sg:phone":"+1 605 994 2394",
    "sg:postcode":"57446",
    "sg:province":"SD",
    "sg:tags":[
        "farm",
        "corn"
    ],
    "wof:name":"Dinger Verl",
    "wof:placetype":"venue"
},
  "geometry": {"coordinates":[-98.04791899999999,45.791696],"type":"Point"}
}