{
  "type": "Feature",
  "properties": {
    "iso:country":"US",
    "sg:address":"4001 Wild Flower Dr",
    "sg:city":"Rapid City",
    "sg:classifiers":[
        {
            "category":"Shopping",
            "subcategory":"Gifts & Souvenirs",
            "type":"Retail Goods"
        }
    ],
    "sg:phone":"+1 605 399 1674",
    "sg:postcode":"57701",
    "sg:province":"SD",
    "wof:name":"Longaberger Baskets and Potery",
    "wof:placetype":"venue"
},
  "geometry": {"coordinates":[-103.197872,44.045072],"type":"Point"}
}