{
  "type": "Feature",
  "properties": {
    "iso:country":"US",
    "sg:address":"416 S Walker St",
    "sg:city":"Vermillion",
    "sg:classifiers":[
        {
            "category":"Organizations",
            "subcategory":"Religious Organization",
            "type":"Services"
        }
    ],
    "sg:phone":"+1 605 624 4478",
    "sg:postcode":"57069",
    "sg:province":"SD",
    "sg:tags":[
        "church"
    ],
    "wof:name":"St Agnes Catholic Church Inc",
    "wof:placetype":"venue"
},
  "geometry": {"coordinates":[-96.918432,42.775195],"type":"Point"}
}