{
  "type": "Feature",
  "properties": {
    "iso:country":"US",
    "sg:address":"505 W Custer Ave",
    "sg:city":"Gettysburg",
    "sg:classifiers":[
        {
            "category":"Wholesale",
            "subcategory":"Dairy",
            "type":"Manufacturing & Wholesale Goods"
        }
    ],
    "sg:phone":"+1 605 765 9502",
    "sg:postcode":"57442",
    "sg:province":"SD",
    "sg:tags":[
        "product"
    ],
    "wof:name":"Cass Clay Creamery  Inc",
    "wof:placetype":"venue"
},
  "geometry": {"coordinates":[-99.963131,45.014758],"type":"Point"}
}