{
  "type": "Feature",
  "properties": {
    "iso:country":"US",
    "sg:address":"300 E Main St",
    "sg:city":"Canova",
    "sg:classifiers":[
        {
            "category":"Organizations",
            "subcategory":"Religious Organization",
            "type":"Services"
        }
    ],
    "sg:phone":"+1 605 523 2260",
    "sg:postcode":"57321",
    "sg:province":"SD",
    "sg:tags":[
        "church"
    ],
    "wof:name":"Canova Congregational Church",
    "wof:placetype":"venue"
},
  "geometry": {"coordinates":[-97.50004199999999,43.881102],"type":"Point"}
}