{
  "type": "Feature",
  "properties": {
    "iso:country":"US",
    "sg:address":"222 Timberline Ct",
    "sg:city":"Rapid City",
    "sg:classifiers":[
        {
            "category":"Professional",
            "type":"Services"
        }
    ],
    "sg:phone":"+1 605 343 4252",
    "sg:postcode":"57702",
    "sg:province":"SD",
    "sg:tags":[
        "gallery"
    ],
    "sg:website":"www.eckmanfineart.com",
    "wof:name":"Eckman Fine Art",
    "wof:placetype":"venue"
},
  "geometry": {"coordinates":[-103.32473899999999,44.087144],"type":"Point"}
}