{
  "type": "Feature",
  "properties": {
    "addr:full":"603 Ash St W Sisseton SD 57262",
    "addr:housenumber":"603",
    "addr:postcode":"57262",
    "addr:street":"Ash St W",
    "iso:country":"US",
    "sg:address":"603 Ash St W",
    "sg:city":"Sisseton",
    "sg:classifiers":[
        {
            "category":"Organizations",
            "subcategory":"Religious Organization",
            "type":"Services"
        }
    ],
    "sg:phone":"+1 605 698 3356",
    "sg:postcode":"57262",
    "sg:province":"SD",
    "sg:tags":[
        "church"
    ],
    "wof:name":"Sisseton Alliance Church",
    "wof:placetype":"venue"
},
  "geometry": {"coordinates":[-97.05996500000001,45.662864],"type":"Point"}
}