{
  "type": "Feature",
  "properties": {
    "iso:country":"US",
    "sg:address":"3600 S Duluth Ave",
    "sg:city":"Sioux Falls",
    "sg:classifiers":[
        {
            "category":"Organizations",
            "subcategory":"Non-profit Organization",
            "type":"Services"
        },
        {
            "category":"Social Services",
            "subcategory":"Job Training",
            "type":"Services"
        }
    ],
    "sg:phone":"+1 605 334 4220",
    "sg:postcode":"57105",
    "sg:province":"SD",
    "sg:tags":[
        "rehabilitation",
        "vocational"
    ],
    "sg:website":"www.dakotabilities.com",
    "wof:name":"Dakotabilities Inc",
    "wof:placetype":"venue"
},
  "geometry": {"coordinates":[-96.733602,43.512203],"type":"Point"}
}