{
  "type": "Feature",
  "properties": {
    "addr:full":"445 S 6th St Hot Springs SD 57747",
    "addr:housenumber":"445",
    "addr:postcode":"57747",
    "addr:street":"S 6Th St",
    "iso:country":"US",
    "sg:address":"445 S 6th St",
    "sg:city":"Hot Springs",
    "sg:classifiers":[
        {
            "category":"Real Estate",
            "subcategory":"Real Estate Agent",
            "type":"Services"
        }
    ],
    "sg:phone":"+1 605 745 6656",
    "sg:postcode":"57747",
    "sg:province":"SD",
    "wof:name":"Dakota Hills Realty",
    "wof:placetype":"venue"
},
  "geometry": {"coordinates":[-103.47123000000001,43.428094],"type":"Point"}
}