{
  "type": "Feature",
  "properties": {
    "iso:country":"US",
    "sg:address":"1125 N Lacrosse St",
    "sg:city":"Rapid City",
    "sg:classifiers":[
        {
            "category":"Building & Trades",
            "subcategory":"Construction",
            "type":"Services"
        }
    ],
    "sg:phone":"+1 605 342 8592",
    "sg:postcode":"57701",
    "sg:province":"SD",
    "sg:tags":[
        "general",
        "contractor"
    ],
    "wof:name":"Strohbeck Construction",
    "wof:placetype":"venue"
},
  "geometry": {"coordinates":[-103.201768,44.095442],"type":"Point"}
}