{
  "type": "Feature",
  "properties": {
    "addr:full":"1841 Baltimore Ave Hot Springs SD 57747",
    "addr:housenumber":"1841",
    "addr:postcode":"57747",
    "addr:street":"Baltimore Ave",
    "iso:country":"US",
    "sg:address":"1841 Baltimore Ave",
    "sg:city":"Hot Springs",
    "sg:classifiers":[
        {
            "category":"Organizations",
            "subcategory":"Religious Organization",
            "type":"Services"
        }
    ],
    "sg:phone":"+1 605 745 3067",
    "sg:postcode":"57747",
    "sg:province":"SD",
    "wof:name":"Catholic Daughters of AME",
    "wof:placetype":"venue"
},
  "geometry": {"coordinates":[-103.484488,43.42765],"type":"Point"}
}