{
  "type": "Feature",
  "properties": {
    "iso:country":"US",
    "sg:address":"17625 461st Ave",
    "sg:city":"Watertown",
    "sg:classifiers":[
        {
            "category":"Farming",
            "subcategory":"Farm",
            "type":"Manufacturing & Wholesale Goods"
        }
    ],
    "sg:phone":"+1 605 886 6856",
    "sg:postcode":"57201",
    "sg:province":"SD",
    "sg:tags":[
        "crop",
        "general"
    ],
    "wof:name":"Mack Farms",
    "wof:placetype":"venue"
},
  "geometry": {"coordinates":[-96.98604,44.830218],"type":"Point"}
}