{
  "type": "Feature",
  "properties": {
    "iso:country":"US",
    "sg:address":"6812 Deadwood Ave N",
    "sg:city":"Rapid City",
    "sg:classifiers":[
        {
            "category":"Recreation",
            "subcategory":"Amusement Park",
            "type":"Entertainment"
        }
    ],
    "sg:phone":"+1 605 787 5517",
    "sg:postcode":"57702",
    "sg:province":"SD",
    "sg:tags":[
        "park"
    ],
    "wof:name":"Little Jon Memorial Park Inc",
    "wof:placetype":"venue"
},
  "geometry": {"coordinates":[-103.275055,44.154521],"type":"Point"}
}