{
  "type": "Feature",
  "properties": {
    "addr:full":"44028 267th St Bridgewater SD 57319",
    "addr:housenumber":"44028",
    "addr:postcode":"57319",
    "addr:street":"267Th St",
    "iso:country":"US",
    "sg:address":"44028 267th St",
    "sg:city":"Bridgewater",
    "sg:classifiers":[
        {
            "category":"Farming",
            "subcategory":"Dairy Farm",
            "type":"Manufacturing & Wholesale Goods"
        }
    ],
    "sg:phone":"+1 605 648 3155",
    "sg:postcode":"57319",
    "sg:province":"SD",
    "wof:name":"Heemstra Frm",
    "wof:placetype":"venue"
},
  "geometry": {"coordinates":[-97.407685,43.514395],"type":"Point"}
}