{
  "type": "Feature",
  "properties": {
    "iso:country":"US",
    "sg:address":"120 S Lincoln St",
    "sg:city":"Aberdeen",
    "sg:classifiers":[
        {
            "category":"Professional",
            "subcategory":"Lawyer & Legal Services",
            "type":"Services"
        }
    ],
    "sg:phone":"+1 605 225 6522",
    "sg:postcode":"57401",
    "sg:province":"SD",
    "sg:tags":[
        "attorney"
    ],
    "wof:name":"Gellhaus & Gellhaus",
    "wof:placetype":"venue"
},
  "geometry": {"coordinates":[-98.486684,45.463919],"type":"Point"}
}