{
  "type": "Feature",
  "properties": {
    "iso:country":"US",
    "sg:address":"607 N Sagehorn Dr",
    "sg:city":"Hartford",
    "sg:classifiers":[
        {
            "category":"Building & Trades",
            "subcategory":"Construction",
            "type":"Services"
        }
    ],
    "sg:phone":"+1 605 201 3617",
    "sg:postcode":"57033",
    "sg:province":"SD",
    "sg:tags":[
        "repairing",
        "remodeling",
        "contractor"
    ],
    "wof:name":"Crown Construction",
    "wof:placetype":"venue"
},
  "geometry": {"coordinates":[-96.932676,43.626498],"type":"Point"}
}