{
  "type": "Feature",
  "properties": {
    "iso:country":"US",
    "sg:address":"1403 Pearl St",
    "sg:city":"Faulkton",
    "sg:classifiers":[
        {
            "category":"Social Services",
            "subcategory":"Child Care",
            "type":"Services"
        }
    ],
    "sg:phone":"+1 605 598 6588",
    "sg:postcode":"57438",
    "sg:province":"SD",
    "sg:tags":[
        "kindergarten",
        "academic",
        "school"
    ],
    "wof:name":"Rainbow Connection Preschool",
    "wof:placetype":"venue"
},
  "geometry": {"coordinates":[-99.134088,45.031658],"type":"Point"}
}