{
  "type": "Feature",
  "properties": {
    "iso:country":"US",
    "sg:address":"924 E Redwood Blvd",
    "sg:city":"Brandon",
    "sg:classifiers":[
        {
            "category":"Freight",
            "type":"Transportation"
        }
    ],
    "sg:phone":"+1 605 582 7086",
    "sg:postcode":"57005",
    "sg:province":"SD",
    "sg:tags":[
        "commercial",
        "storage"
    ],
    "wof:name":"Staz-In Self Storage",
    "wof:placetype":"venue"
},
  "geometry": {"coordinates":[-96.575708,43.601987],"type":"Point"}
}