{
  "type": "Feature",
  "properties": {
    "iso:country":"US",
    "sg:address":"2709 S 4th Ave",
    "sg:city":"Sioux Falls",
    "sg:classifiers":[
        {
            "category":"Real Estate",
            "subcategory":"Real Estate Operator",
            "type":"Services"
        }
    ],
    "sg:phone":"+1 605 334 2361",
    "sg:postcode":"57105",
    "sg:province":"SD",
    "sg:tags":[
        "property",
        "management"
    ],
    "wof:name":"Lloyd L Eagan Co",
    "wof:placetype":"venue"
},
  "geometry": {"coordinates":[-96.721297,43.51766],"type":"Point"}
}