{
  "type": "Feature",
  "properties": {
    "iso:country":"US",
    "sg:address":"46926 85th St",
    "sg:city":"Tea",
    "sg:classifiers":[
        {
            "category":"Wholesale",
            "subcategory":"Auto Parts",
            "type":"Manufacturing & Wholesale Goods"
        },
        {
            "category":"Wholesale",
            "subcategory":"Scrap",
            "type":"Manufacturing & Wholesale Goods"
        }
    ],
    "sg:phone":"+1 605 368 2448",
    "sg:postcode":"57106",
    "sg:province":"SD",
    "sg:tags":[
        "automobile",
        "material",
        "used",
        "rebuilt"
    ],
    "wof:name":"Johnson's Salvage",
    "wof:placetype":"venue"
},
  "geometry": {"coordinates":[-96.818068,43.475611],"type":"Point"}
}