{
  "type": "Feature",
  "properties": {
    "addr:full":"118 18th St NE Watertown SD 57201",
    "addr:housenumber":"118",
    "addr:postcode":"57201",
    "addr:street":"18Th St Ne",
    "iso:country":"US",
    "sg:address":"118 18th St NE",
    "sg:city":"Watertown",
    "sg:classifiers":[
        {
            "category":"Professional",
            "type":"Services"
        }
    ],
    "sg:phone":"+1 605 882 0159",
    "sg:postcode":"57201",
    "sg:province":"SD",
    "wof:name":"Finishing Touch",
    "wof:placetype":"venue"
},
  "geometry": {"coordinates":[-97.08807,44.90191],"type":"Point"}
}