{
  "type": "Feature",
  "properties": {
    "addr:full":"826 6th Ave SE Aberdeen SD 57401",
    "addr:housenumber":"826",
    "addr:postcode":"57401",
    "addr:street":"6Th Ave Se",
    "iso:country":"US",
    "sg:address":"826 6th Ave SE",
    "sg:city":"Aberdeen",
    "sg:classifiers":[
        {
            "category":"Building & Trades",
            "subcategory":"Construction",
            "type":"Services"
        }
    ],
    "sg:phone":"+1 605 226 9074",
    "sg:postcode":"57401",
    "sg:province":"SD",
    "sg:tags":[
        "repair",
        "special",
        "contractor"
    ],
    "wof:name":"Marshall Spas and Pools Inc",
    "wof:placetype":"venue"
},
  "geometry": {"coordinates":[-98.475026,45.458925],"type":"Point"}
}