{
  "type": "Feature",
  "properties": {
    "addr:full":"45911 263rd St Hartford SD 57033",
    "addr:housenumber":"45911",
    "addr:postcode":"57033",
    "addr:street":"263Rd St",
    "iso:country":"US",
    "sg:address":"45911 263rd St",
    "sg:city":"Hartford",
    "sg:phone":"+1 605 526 6455",
    "sg:postcode":"57033",
    "sg:province":"SD",
    "sg:tags":[
        "farm",
        "corn",
        "soybean"
    ],
    "wof:name":"Roger Carls",
    "wof:placetype":"venue"
},
  "geometry": {"coordinates":[-97.019424,43.572224],"type":"Point"}
}