{
  "type": "Feature",
  "properties": {
    "iso:country":"US",
    "sg:address":"1108 W Bailey St",
    "sg:city":"Sioux Falls",
    "sg:classifiers":[
        {
            "category":"Banks & Credit Unions",
            "subcategory":"Bank",
            "type":"Services"
        }
    ],
    "sg:phone":"+1 605 428 4488",
    "sg:postcode":"57104",
    "sg:province":"SD",
    "sg:tags":[
        "broker",
        "mortgage"
    ],
    "wof:name":"Strategic Financial Solutions",
    "wof:placetype":"venue"
},
  "geometry": {"coordinates":[-96.743577,43.561522],"type":"Point"}
}