{
  "type": "Feature",
  "properties": {
    "iso:country":"US",
    "sg:address":"33307 209th St",
    "sg:city":"Highmore",
    "sg:phone":"+1 605 852 2895",
    "sg:postcode":"57345",
    "sg:province":"SD",
    "sg:tags":[
        "farm",
        "wheat",
        "grain",
        "cash"
    ],
    "wof:name":"William Knox",
    "wof:placetype":"venue"
},
  "geometry": {"coordinates":[-99.54580199999999,44.352773],"type":"Point"}
}