{
  "type": "Feature",
  "properties": {
    "iso:country":"US",
    "sg:address":"2320 W 49th St",
    "sg:city":"Sioux Falls",
    "sg:classifiers":[
        {
            "category":"Professional",
            "subcategory":"Business Services",
            "type":"Services"
        }
    ],
    "sg:phone":"+1 605 336 9490",
    "sg:postcode":"57105",
    "sg:province":"SD",
    "sg:tags":[
        "cashing",
        "protection",
        "check",
        "system"
    ],
    "sg:website":"www.haugeassociates.com",
    "wof:name":"Check-Mate",
    "wof:placetype":"venue"
},
  "geometry": {"coordinates":[-96.75262600000001,43.508493],"type":"Point"}
}