{
  "type": "Feature",
  "properties": {
    "iso:country":"US",
    "sg:address":"515 9th St",
    "sg:city":"Rapid City",
    "sg:classifiers":[
        {
            "category":"Government",
            "subcategory":"Office",
            "type":"Public Place"
        }
    ],
    "sg:phone":"+1 605 348 4434",
    "sg:postcode":"57701",
    "sg:province":"SD",
    "sg:tags":[
        "federal"
    ],
    "wof:name":"US General Svc Adm",
    "wof:placetype":"venue"
},
  "geometry": {"coordinates":[-103.232949,44.081096],"type":"Point"}
}