{
  "type": "Feature",
  "properties": {
    "addr:full":"1402 N Mable Ave Sioux Falls SD 57103",
    "addr:housenumber":"1402",
    "addr:postcode":"57103",
    "addr:street":"N Mable Ave",
    "iso:country":"US",
    "sg:address":"1402 N Mable Ave",
    "sg:city":"Sioux Falls",
    "sg:classifiers":[
        {
            "category":"Autos & Motor Vehicles",
            "subcategory":"Automobile Sales",
            "type":"Retail Goods"
        }
    ],
    "sg:phone":"+1 605 336 8877",
    "sg:postcode":"57103",
    "sg:province":"SD",
    "sg:tags":[
        "car",
        "used",
        "dealer"
    ],
    "wof:name":"Los Angles Auto Sales",
    "wof:placetype":"venue"
},
  "geometry": {"coordinates":[-96.70508100000001,43.563004],"type":"Point"}
}