{
  "type": "Feature",
  "properties": {
    "iso:country":"US",
    "sg:address":"107 N Hickory St",
    "sg:city":"Avon",
    "sg:classifiers":[
        {
            "category":"Building & Trades",
            "subcategory":"Plumbing",
            "type":"Services"
        }
    ],
    "sg:phone":"+1 605 286 3201",
    "sg:postcode":"57315",
    "sg:province":"SD",
    "sg:tags":[
        "plumbing",
        "contractor"
    ],
    "wof:name":"Elliott Plumbing & Heating",
    "wof:placetype":"venue"
},
  "geometry": {"coordinates":[-98.061661,43.004034],"type":"Point"}
}