{
  "type": "Feature",
  "properties": {
    "addr:full":"801 N Lake Ave Sioux Falls SD 57104",
    "addr:housenumber":"801",
    "addr:postcode":"57104",
    "addr:street":"N Lake Ave",
    "iso:country":"US",
    "sg:address":"801 N Lake Ave",
    "sg:city":"Sioux Falls",
    "sg:classifiers":[
        {
            "category":"Professional",
            "subcategory":"Advertising",
            "type":"Services"
        }
    ],
    "sg:phone":"+1 605 977 1577",
    "sg:postcode":"57104",
    "sg:province":"SD",
    "sg:tags":[
        "mail",
        "job",
        "s",
        "direct"
    ],
    "wof:name":"CHAPEL CRAFT PRODUCTS",
    "wof:placetype":"venue"
},
  "geometry": {"coordinates":[-96.74574699999999,43.55467],"type":"Point"}
}