{
  "type": "Feature",
  "properties": {
    "iso:country":"US",
    "sg:address":"2801 N Jaycee Ln",
    "sg:city":"Sioux Falls",
    "sg:classifiers":[
        {
            "category":"Parking",
            "type":"Transportation"
        }
    ],
    "sg:phone":"+1 605 336 8154",
    "sg:postcode":"57104",
    "sg:province":"SD",
    "sg:tags":[
        "automobile"
    ],
    "wof:name":"Standard Parking Corporation",
    "wof:placetype":"venue"
},
  "geometry": {"coordinates":[-96.728808,43.582846],"type":"Point"}
}