{
  "type": "Feature",
  "properties": {
    "iso:country":"US",
    "sg:address":"2120 9th St",
    "sg:city":"Rapid City",
    "sg:classifiers":[
        {
            "category":"Building & Trades",
            "subcategory":"Construction",
            "type":"Services"
        }
    ],
    "sg:phone":"+1 605 348 0247",
    "sg:postcode":"57701",
    "sg:province":"SD",
    "wof:name":"Bartels & Sons Cnstr LLC",
    "wof:placetype":"venue"
},
  "geometry": {"coordinates":[-103.234212,44.064621],"type":"Point"}
}