{
  "type": "Feature",
  "properties": {
    "iso:country":"US",
    "sg:address":"806 8th St",
    "sg:city":"Springfield",
    "sg:classifiers":[
        {
            "category":"Health Services",
            "subcategory":"Doctor",
            "type":"Services"
        }
    ],
    "sg:phone":"+1 605 369 2627",
    "sg:postcode":"57062",
    "sg:province":"SD",
    "sg:tags":[
        "clinic"
    ],
    "wof:name":"Springfield Family Clinic",
    "wof:placetype":"venue"
},
  "geometry": {"coordinates":[-97.896882,42.854284],"type":"Point"}
}