{
  "type": "Feature",
  "properties": {
    "addr:full":"8317 W 42nd St Sioux Falls SD 57106",
    "addr:housenumber":"8317",
    "addr:postcode":"57106",
    "addr:street":"W 42Nd St",
    "iso:country":"US",
    "sg:address":"8317 W 42nd St",
    "sg:city":"Sioux Falls",
    "sg:classifiers":[
        {
            "category":"Building & Trades",
            "subcategory":"Electrical",
            "type":"Services"
        }
    ],
    "sg:phone":"+1 605 361 8159",
    "sg:postcode":"57106",
    "sg:province":"SD",
    "sg:tags":[
        "electrical",
        "contractor"
    ],
    "wof:name":"Alliance Electric",
    "wof:placetype":"venue"
},
  "geometry": {"coordinates":[-96.828484,43.513296],"type":"Point"}
}