{
  "type": "Feature",
  "properties": {
    "iso:country":"US",
    "sg:address":"110 E Main St",
    "sg:city":"Warner",
    "sg:classifiers":[
        {
            "category":"Organizations",
            "subcategory":"Religious Organization",
            "type":"Services"
        }
    ],
    "sg:phone":"+1 605 229 0428",
    "sg:postcode":"57479",
    "sg:province":"SD",
    "sg:tags":[
        "church"
    ],
    "wof:name":"St John Lutheran Church",
    "wof:placetype":"venue"
},
  "geometry": {"coordinates":[-98.493044,45.325491],"type":"Point"}
}