{
  "type": "Feature",
  "properties": {
    "addr:full":"701 S Sycamore Ave Sioux Falls SD 57110",
    "addr:housenumber":"701",
    "addr:postcode":"57110",
    "addr:street":"S Sycamore Ave",
    "iso:country":"US",
    "sg:address":"701 S Sycamore Ave",
    "sg:city":"Sioux Falls",
    "sg:classifiers":[
        {
            "category":"Restaurant",
            "type":"Food & Drink"
        }
    ],
    "sg:menulink":"http://www.allmenus.com/sd/sioux-falls/225102-caseys-general-store/menu/",
    "sg:phone":"+1 605 332 6961",
    "sg:postcode":"57110",
    "sg:province":"SD",
    "sg:tags":[
        "american",
        "pizza"
    ],
    "wof:name":"Casey's General Store",
    "wof:placetype":"venue"
},
  "geometry": {"coordinates":[-96.671494,43.541271],"type":"Point"}
}