{
  "type": "Feature",
  "properties": {
    "iso:country":"US",
    "sg:address":"445 S Hawthorne Ave",
    "sg:city":"Sioux Falls",
    "sg:classifiers":[
        {
            "category":"Building & Trades",
            "subcategory":"Construction",
            "type":"Services"
        }
    ],
    "sg:phone":"+1 605 336 3811",
    "sg:postcode":"57104",
    "sg:province":"SD",
    "sg:tags":[
        "contractor"
    ],
    "wof:name":"James L House",
    "wof:placetype":"venue"
},
  "geometry": {"coordinates":[-96.748794,43.542426],"type":"Point"}
}