{
  "type": "Feature",
  "properties": {
    "addr:full":"620 N Nebraska St Salem SD 57058",
    "addr:housenumber":"620",
    "addr:postcode":"57058",
    "addr:street":"N Nebraska St",
    "iso:country":"US",
    "sg:address":"620 N Nebraska St",
    "sg:city":"Salem",
    "sg:classifiers":[
        {
            "category":"Insurance",
            "subcategory":"Insurance Agent",
            "type":"Services"
        }
    ],
    "sg:phone":"+1 605 425 3140",
    "sg:postcode":"57058",
    "sg:province":"SD",
    "wof:name":"Blindert Insurance",
    "wof:placetype":"venue"
},
  "geometry": {"coordinates":[-97.388876,43.730218],"type":"Point"}
}