{
  "type": "Feature",
  "properties": {
    "iso:country":"US",
    "sg:address":"2121 W 33rd St",
    "sg:city":"Sioux Falls",
    "sg:classifiers":[
        {
            "category":"Organizations",
            "subcategory":"Religious Organization",
            "type":"Services"
        }
    ],
    "sg:phone":"+1 605 332 2303",
    "sg:postcode":"57105",
    "sg:province":"SD",
    "sg:website":"www.faithtemplesd.com",
    "wof:name":"Faith Temple Church",
    "wof:placetype":"venue"
},
  "geometry": {"coordinates":[-96.75222,43.522032],"type":"Point"}
}