{
  "type": "Feature",
  "properties": {
    "addr:full":"3508 S Minnesota Ave Sioux Falls SD 57105",
    "addr:housenumber":"3508",
    "addr:postcode":"57105",
    "addr:street":"S Minnesota Ave",
    "iso:country":"US",
    "sg:address":"3508 S Minnesota Ave",
    "sg:city":"Sioux Falls",
    "sg:classifiers":[
        {
            "category":"Shopping",
            "type":"Retail Goods"
        }
    ],
    "sg:phone":"+1 605 335 4004",
    "sg:postcode":"57105",
    "sg:province":"SD",
    "sg:tags":[
        "pet",
        "food",
        "supply"
    ],
    "wof:name":"All City Pet Care",
    "wof:placetype":"venue"
},
  "geometry": {"coordinates":[-96.731173,43.511839],"type":"Point"}
}