{
  "type": "Feature",
  "properties": {
    "iso:country":"US",
    "sg:address":"1009 S Main St",
    "sg:city":"Aberdeen",
    "sg:classifiers":[
        {
            "category":"Shopping",
            "subcategory":"Used Merchandise",
            "type":"Retail Goods"
        }
    ],
    "sg:phone":"+1 605 226 2782",
    "sg:postcode":"57401",
    "sg:province":"SD",
    "sg:tags":[
        "furniture"
    ],
    "wof:name":"Schmidts Antq & Collectables",
    "wof:placetype":"venue"
},
  "geometry": {"coordinates":[-98.487964,45.454765],"type":"Point"}
}