{
  "type": "Feature",
  "properties": {
    "addr:full":"206 N Main St Howard SD 57349",
    "addr:housenumber":"206",
    "addr:postcode":"57349",
    "addr:street":"N Main St",
    "iso:country":"US",
    "sg:address":"206 N Main St",
    "sg:city":"Howard",
    "sg:classifiers":[
        {
            "category":"Social Services",
            "subcategory":"Child Care",
            "type":"Services"
        }
    ],
    "sg:phone":"+1 605 772 5137",
    "sg:postcode":"57349",
    "sg:province":"SD",
    "wof:name":"Childrens Care Corner",
    "wof:placetype":"venue"
},
  "geometry": {"coordinates":[-97.526729,44.013639],"type":"Point"}
}