{
  "type": "Feature",
  "properties": {
    "addr:full":"1703 Mesa Dr Rapid City SD 57702",
    "addr:housenumber":"1703",
    "addr:postcode":"57702",
    "addr:street":"Mesa Dr",
    "iso:country":"US",
    "sg:address":"1703 Mesa Dr",
    "sg:city":"Rapid City",
    "sg:classifiers":[
        {
            "category":"Manufacturing",
            "subcategory":"Lumber",
            "type":"Manufacturing & Wholesale Goods"
        }
    ],
    "sg:phone":"+1 605 342 3101",
    "sg:postcode":"57702",
    "sg:province":"SD",
    "sg:tags":[
        "forestry"
    ],
    "wof:name":"Martin Tarby",
    "wof:placetype":"venue"
},
  "geometry": {"coordinates":[-103.255523,44.067538],"type":"Point"}
}