{
  "type": "Feature",
  "properties": {
    "iso:country":"US",
    "sg:address":"203 E 11th Ave",
    "sg:city":"Webster",
    "sg:classifiers":[
        {
            "category":"Personal",
            "subcategory":"Beauty Salon",
            "type":"Services"
        }
    ],
    "sg:phone":"+1 605 345 3233",
    "sg:postcode":"57274",
    "sg:province":"SD",
    "sg:tags":[
        "shop"
    ],
    "wof:name":"Jans Eleventh AV Beauty Salon",
    "wof:placetype":"venue"
},
  "geometry": {"coordinates":[-97.516565,45.336306],"type":"Point"}
}