{
  "type": "Feature",
  "properties": {
    "iso:country":"US",
    "sg:address":"1517 N Harrison Ave",
    "sg:city":"Pierre",
    "sg:classifiers":[
        {
            "category":"Real Estate",
            "subcategory":"Real Estate Agent",
            "type":"Services"
        }
    ],
    "sg:phone":"+1 605 224 0441",
    "sg:postcode":"57501",
    "sg:province":"SD",
    "wof:name":"Ag Property Inc",
    "wof:placetype":"venue"
},
  "geometry": {"coordinates":[-100.318393,44.377214],"type":"Point"}
}