{
  "type": "Feature",
  "properties": {
    "addr:full":"4244 Canyon Lake Dr Rapid City SD 57702",
    "addr:housenumber":"4244",
    "addr:postcode":"57702",
    "addr:street":"Canyon Lake Dr",
    "iso:country":"US",
    "sg:address":"4244 Canyon Lake Dr",
    "sg:city":"Rapid City",
    "sg:classifiers":[
        {
            "category":"Food & Beverages",
            "subcategory":"Liquor & Beverages",
            "type":"Retail Goods"
        }
    ],
    "sg:phone":"+1 605 342 7639",
    "sg:postcode":"57702",
    "sg:province":"SD",
    "sg:tags":[
        "alcoholic"
    ],
    "wof:name":"Canyon Lake Liquors Ltd",
    "wof:placetype":"venue"
},
  "geometry": {"coordinates":[-103.288962,44.062446],"type":"Point"}
}