{
  "type": "Feature",
  "properties": {
    "addr:full":"24166 395th Ave Letcher SD 57359",
    "addr:housenumber":"24166",
    "addr:postcode":"57359",
    "addr:street":"395Th Ave",
    "iso:country":"US",
    "sg:address":"24166 395th Ave",
    "sg:city":"Letcher",
    "sg:classifiers":[
        {
            "category":"Farming",
            "subcategory":"Farm",
            "type":"Manufacturing & Wholesale Goods"
        }
    ],
    "sg:phone":"+1 605 248 2261",
    "sg:postcode":"57359",
    "sg:province":"SD",
    "wof:name":"Selland & Sons",
    "wof:placetype":"venue"
},
  "geometry": {"coordinates":[-98.31152,43.885104],"type":"Point"}
}