{
  "type": "Feature",
  "properties": {
    "iso:country":"US",
    "sg:address":"2120 W Main St",
    "sg:city":"Rapid City",
    "sg:classifiers":[
        {
            "category":"Utilities",
            "subcategory":"Mobile Phone",
            "type":"Services"
        }
    ],
    "sg:phone":"+1 605 394 8883",
    "sg:postcode":"57702",
    "sg:province":"SD",
    "sg:tags":[
        "telephone",
        "cellular"
    ],
    "wof:name":"Cellular Center",
    "wof:placetype":"venue"
},
  "geometry": {"coordinates":[-103.25343700000001,44.081273],"type":"Point"}
}