{
  "type": "Feature",
  "properties": {
    "iso:country":"US",
    "sg:address":"600 N Derby Ln",
    "sg:city":"North Sioux City",
    "sg:classifiers":[
        {
            "category":"Building & Trades",
            "subcategory":"Construction",
            "type":"Services"
        }
    ],
    "sg:phone":"+1 605 232 4000",
    "sg:postcode":"57049",
    "sg:province":"SD",
    "sg:tags":[
        "general",
        "contractor"
    ],
    "wof:name":"Wegher Construction Co",
    "wof:placetype":"venue"
},
  "geometry": {"coordinates":[-96.49706500000001,42.526655],"type":"Point"}
}