{
  "type": "Feature",
  "properties": {
    "iso:country":"US",
    "sg:address":"1308 Cedar St",
    "sg:city":"Brandon",
    "sg:classifiers":[
        {
            "category":"Health Services",
            "subcategory":"Doctor",
            "type":"Services"
        }
    ],
    "sg:phone":"+1 605 582 7102",
    "sg:postcode":"57005",
    "sg:province":"SD",
    "sg:tags":[
        "dentist"
    ],
    "wof:name":"Michael R Juba DDS",
    "wof:placetype":"venue"
},
  "geometry": {"coordinates":[-96.57215600000001,43.59046],"type":"Point"}
}