{
  "type": "Feature",
  "properties": {
    "addr:full":"15631 453rd Ave South Shore SD 57263",
    "addr:housenumber":"15631",
    "addr:postcode":"57263",
    "addr:street":"453Rd Ave",
    "iso:country":"US",
    "sg:address":"15631 453rd Ave",
    "sg:city":"South Shore",
    "sg:classifiers":[
        {
            "category":"Farming",
            "subcategory":"Livestock Farm",
            "type":"Manufacturing & Wholesale Goods"
        }
    ],
    "sg:phone":"+1 605 886 6682",
    "sg:postcode":"57263",
    "sg:province":"SD",
    "sg:tags":[
        "beef",
        "feedlot",
        "cattle"
    ],
    "wof:name":"Laverne Schmig",
    "wof:placetype":"venue"
},
  "geometry": {"coordinates":[-97.14431,45.132642],"type":"Point"}
}