{
  "type": "Feature",
  "properties": {
    "iso:country":"US",
    "sg:address":"426 Hunters Ridge Rd",
    "sg:city":"Brookings",
    "sg:classifiers":[
        {
            "category":"Professional",
            "subcategory":"Testing Lab",
            "type":"Services"
        }
    ],
    "sg:phone":"+1 605 692 5169",
    "sg:postcode":"57006",
    "sg:province":"SD",
    "sg:tags":[
        "laboratory"
    ],
    "wof:name":"Chase Consulting",
    "wof:placetype":"venue"
},
  "geometry": {"coordinates":[-96.798059,44.285207],"type":"Point"}
}