{
  "type": "Feature",
  "properties": {
    "iso:country":"US",
    "sg:address":"1947 Dakota Ave S",
    "sg:city":"Huron",
    "sg:classifiers":[
        {
            "category":"Autos & Motor Vehicles",
            "subcategory":"Fuel & Gas Station",
            "type":"Retail Goods"
        }
    ],
    "sg:phone":"+1 605 352 0551",
    "sg:postcode":"57350",
    "sg:province":"SD",
    "sg:tags":[
        "filling",
        "station",
        "convenience",
        "store"
    ],
    "wof:name":"Qb Conoco",
    "wof:placetype":"venue"
},
  "geometry": {"coordinates":[-98.214242,44.343533],"type":"Point"}
}