{
  "type": "Feature",
  "properties": {
    "iso:country":"US",
    "sg:address":"132 St John St",
    "sg:city":"Mansfield",
    "sg:classifiers":[
        {
            "category":"Retail",
            "subcategory":"Auto Repair",
            "type":"Services"
        }
    ],
    "sg:phone":"+1 605 887 3466",
    "sg:postcode":"57460",
    "sg:province":"SD",
    "sg:tags":[
        "repairing",
        "automobile"
    ],
    "wof:name":"Chandler Repair",
    "wof:placetype":"venue"
},
  "geometry": {"coordinates":[-98.564459,45.241634],"type":"Point"}
}