{
  "type": "Feature",
  "properties": {
    "addr:full":"3714 Medary Ave Brookings SD 57006",
    "addr:postcode":"3714;57006",
    "addr:street":"Medary Ave",
    "iso:country":"US",
    "sg:address":"3714 Medary Ave",
    "sg:city":"Brookings",
    "sg:classifiers":[
        {
            "category":"Insurance",
            "subcategory":"Insurance Agent",
            "type":"Services"
        }
    ],
    "sg:phone":"+1 605 693 3424",
    "sg:postcode":"57006",
    "sg:province":"SD",
    "wof:name":"Dawson Corp Service",
    "wof:placetype":"venue"
},
  "geometry": {"coordinates":[-96.78795599999999,44.34972],"type":"Point"}
}