{
  "type": "Feature",
  "properties": {
    "iso:country":"US",
    "sg:address":"1100 W Norway Ave",
    "sg:city":"Mitchell",
    "sg:classifiers":[
        {
            "category":"Freight",
            "type":"Transportation"
        }
    ],
    "sg:phone":"+1 605 999 1916",
    "sg:postcode":"57301",
    "sg:province":"SD",
    "sg:tags":[
        "operator",
        "trucking"
    ],
    "wof:name":"John Cypher Trucking",
    "wof:placetype":"venue"
},
  "geometry": {"coordinates":[-98.039411,43.694805],"type":"Point"}
}