{
  "type": "Feature",
  "properties": {
    "iso:country":"US",
    "sg:address":"817 N State St",
    "sg:city":"Aberdeen",
    "sg:classifiers":[
        {
            "category":"Organizations",
            "subcategory":"Community Association",
            "type":"Services"
        }
    ],
    "sg:phone":"+1 605 225 7028",
    "sg:postcode":"57401",
    "sg:province":"SD",
    "wof:name":"United Commercial Travelers",
    "wof:placetype":"venue"
},
  "geometry": {"coordinates":[-98.479368,45.4746],"type":"Point"}
}