{
  "type": "Feature",
  "properties": {
    "addr:full":"920 S Washington St Aberdeen SD 57401",
    "addr:housenumber":"920",
    "addr:postcode":"57401",
    "addr:street":"S Washington St",
    "iso:country":"US",
    "sg:address":"920 S Washington St",
    "sg:city":"Aberdeen",
    "sg:classifiers":[
        {
            "category":"Building & Trades",
            "subcategory":"Construction",
            "type":"Services"
        }
    ],
    "sg:phone":"+1 605 380 8414",
    "sg:postcode":"57401",
    "sg:province":"SD",
    "sg:tags":[
        "house"
    ],
    "wof:name":"Las Construction",
    "wof:placetype":"venue"
},
  "geometry": {"coordinates":[-98.485257,45.455871],"type":"Point"}
}