{
  "type": "Feature",
  "properties": {
    "addr:full":"1699 Sedivy Ln Rapid City SD 57703",
    "addr:housenumber":"1699",
    "addr:postcode":"57703",
    "addr:street":"Sedivy Ln",
    "iso:country":"US",
    "sg:address":"1699 Sedivy Ln",
    "sg:city":"Rapid City",
    "sg:classifiers":[
        {
            "category":"Wholesale",
            "subcategory":"Dairy",
            "type":"Manufacturing & Wholesale Goods"
        }
    ],
    "sg:phone":"+1 605 348 1500",
    "sg:postcode":"57703",
    "sg:province":"SD",
    "sg:tags":[
        "frozen",
        "dessert",
        "ice",
        "cream"
    ],
    "wof:name":"H P Hood LLC",
    "wof:placetype":"venue"
},
  "geometry": {"coordinates":[-103.176654,44.072137],"type":"Point"}
}