{
  "type": "Feature",
  "properties": {
    "iso:country":"US",
    "sg:address":"514 N Crawford Rd",
    "sg:city":"Vermillion",
    "sg:classifiers":[
        {
            "category":"Organizations",
            "subcategory":"Religious Organization",
            "type":"Services"
        }
    ],
    "sg:phone":"+1 605 624 8809",
    "sg:postcode":"57069",
    "sg:province":"SD",
    "sg:tags":[
        "church"
    ],
    "wof:name":"Assembly Of God Church",
    "wof:placetype":"venue"
},
  "geometry": {"coordinates":[-96.90522300000001,42.784614],"type":"Point"}
}