{
  "type": "Feature",
  "properties": {
    "iso:country":"US",
    "sg:address":"44468 162nd St",
    "sg:city":"Florence",
    "sg:phone":"+1 605 758 2534",
    "sg:postcode":"57235",
    "sg:province":"SD",
    "sg:tags":[
        "farm",
        "soybean"
    ],
    "wof:name":"Lyle Tschakert",
    "wof:placetype":"venue"
},
  "geometry": {"coordinates":[-97.31868900000001,45.035511],"type":"Point"}
}