{
  "type": "Feature",
  "properties": {
    "addr:full":"2712 S Sandstone Cir Sioux Falls SD 57103",
    "addr:housenumber":"2712",
    "addr:postcode":"57103",
    "addr:street":"S Sandstone Cir",
    "iso:country":"US",
    "sg:address":"2712 S Sandstone Cir",
    "sg:city":"Sioux Falls",
    "sg:classifiers":[
        {
            "category":"Professional",
            "subcategory":"Advertising",
            "type":"Services"
        }
    ],
    "sg:phone":"+1 605 575 2525",
    "sg:postcode":"57103",
    "sg:province":"SD",
    "sg:tags":[
        "counselor"
    ],
    "wof:name":"Pinnacle Creative Svc",
    "wof:placetype":"venue"
},
  "geometry": {"coordinates":[-96.679339,43.519767],"type":"Point"}
}