{
  "type": "Feature",
  "properties": {
    "addr:full":"506 Main St Tyndall SD 57066",
    "addr:housenumber":"506",
    "addr:postcode":"57066",
    "addr:street":"Main St",
    "iso:country":"US",
    "sg:address":"506 Main St",
    "sg:city":"Tyndall",
    "sg:classifiers":[
        {
            "category":"Retail",
            "subcategory":"Veterinary Services",
            "type":"Services"
        }
    ],
    "sg:phone":"+1 605 589 3932",
    "sg:postcode":"57066",
    "sg:province":"SD",
    "sg:tags":[
        "veterinarian"
    ],
    "wof:name":"Tyndall Veterinary Clinic",
    "wof:placetype":"venue"
},
  "geometry": {"coordinates":[-97.862702,42.988177],"type":"Point"}
}