{
  "type": "Feature",
  "properties": {
    "addr:full":"410 E Monroe St Rapid City SD 57701",
    "addr:housenumber":"410",
    "addr:postcode":"57701",
    "addr:street":"E Monroe St",
    "iso:country":"US",
    "sg:address":"410 E Monroe St",
    "sg:city":"Rapid City",
    "sg:classifiers":[
        {
            "category":"Social Services",
            "subcategory":"Child Care",
            "type":"Services"
        }
    ],
    "sg:phone":"+1 605 341 6448",
    "sg:postcode":"57701",
    "sg:province":"SD",
    "sg:tags":[
        "kindergarten",
        "academic",
        "school"
    ],
    "wof:name":"Youth & Family Svc Head Start",
    "wof:placetype":"venue"
},
  "geometry": {"coordinates":[-103.203841,44.09037],"type":"Point"}
}