{
  "type": "Feature",
  "properties": {
    "iso:country":"US",
    "sg:address":"18892 390th Ave",
    "sg:city":"Hitchcock",
    "sg:classifiers":[
        {
            "category":"Freight",
            "type":"Transportation"
        }
    ],
    "sg:phone":"+1 605 266 2894",
    "sg:postcode":"57348",
    "sg:province":"SD",
    "sg:tags":[
        "storage"
    ],
    "wof:name":"A-1 Storage",
    "wof:placetype":"venue"
},
  "geometry": {"coordinates":[-98.422589,44.648336],"type":"Point"}
}