{
  "type": "Feature",
  "properties": {
    "iso:country":"US",
    "sg:address":"3401 S Gateway Blvd",
    "sg:city":"Sioux Falls",
    "sg:classifiers":[
        {
            "category":"Travel",
            "subcategory":"Hotels & Motels",
            "type":"Entertainment"
        }
    ],
    "sg:phone":"+1 605 361 9240",
    "sg:postcode":"57106",
    "sg:province":"SD",
    "sg:tags":[
        "operation"
    ],
    "sg:website":"www.daysinn.com",
    "wof:name":"Days Inn",
    "wof:placetype":"venue"
},
  "geometry": {"coordinates":[-96.783036,43.512972],"type":"Point"}
}