{
  "type": "Feature",
  "properties": {
    "iso:country":"US",
    "sg:address":"215 S 5th St",
    "sg:city":"Menno",
    "sg:classifiers":[
        {
            "category":"Bars & Pubs",
            "type":"Food & Drink"
        }
    ],
    "sg:phone":"+1 605 387 5454",
    "sg:postcode":"57045",
    "sg:province":"SD",
    "wof:name":"Schnitz",
    "wof:placetype":"venue"
},
  "geometry": {"coordinates":[-97.578078,43.239694],"type":"Point"}
}