{
  "type": "Feature",
  "properties": {
    "iso:country":"US",
    "sg:address":"224 E Holly Blvd",
    "sg:city":"Brandon",
    "sg:classifiers":[
        {
            "category":"Personal",
            "subcategory":"Beauty Salon",
            "type":"Services"
        }
    ],
    "sg:phone":"+1 605 582 6474",
    "sg:postcode":"57005",
    "sg:province":"SD",
    "sg:tags":[
        "shop"
    ],
    "wof:name":"Stylin Bahr",
    "wof:placetype":"venue"
},
  "geometry": {"coordinates":[-96.589684,43.594714],"type":"Point"}
}