{
  "type": "Feature",
  "properties": {
    "addr:full":"416 Veterans Ave Sisseton SD 57262",
    "addr:housenumber":"416",
    "addr:postcode":"57262",
    "addr:street":"Veterans Ave",
    "iso:country":"US",
    "sg:address":"416 Veterans Ave",
    "sg:city":"Sisseton",
    "sg:classifiers":[
        {
            "category":"Home & Garden",
            "subcategory":"Household Appliances",
            "type":"Retail Goods"
        }
    ],
    "sg:phone":"+1 605 698 4298",
    "sg:postcode":"57262",
    "sg:province":"SD",
    "wof:name":"Don Hannasch Maytag Home Appl",
    "wof:placetype":"venue"
},
  "geometry": {"coordinates":[-97.049763,45.664481],"type":"Point"}
}