{
  "type": "Feature",
  "properties": {
    "iso:country":"US",
    "sg:address":"1720 Commerce Ln",
    "sg:city":"Webster",
    "sg:classifiers":[
        {
            "category":"Manufacturing",
            "subcategory":"Chemicals & Compounds",
            "type":"Manufacturing & Wholesale Goods"
        }
    ],
    "sg:phone":"+1 605 345 3046",
    "sg:postcode":"57274",
    "sg:province":"SD",
    "sg:tags":[
        "glass",
        "product",
        "fiber"
    ],
    "wof:name":"Dakota Fiberglass",
    "wof:placetype":"venue"
},
  "geometry": {"coordinates":[-97.524822,45.34374],"type":"Point"}
}