{
  "type": "Feature",
  "properties": {
    "iso:country":"US",
    "sg:address":"14 3rd Ave SE",
    "sg:city":"Aberdeen",
    "sg:classifiers":[
        {
            "category":"Bars & Pubs",
            "type":"Food & Drink"
        }
    ],
    "sg:phone":"+1 605 229 1936",
    "sg:postcode":"57401",
    "sg:province":"SD",
    "sg:tags":[
        "drinking"
    ],
    "wof:name":"Circus Sports Bar & Grill",
    "wof:placetype":"venue"
},
  "geometry": {"coordinates":[-98.48791,45.462053],"type":"Point"}
}