{
  "type": "Feature",
  "properties": {
    "addr:full":"1001 Lazelle St Sturgis SD 57785",
    "addr:housenumber":"1001",
    "addr:postcode":"57785",
    "addr:street":"Lazelle St",
    "iso:country":"US",
    "sg:address":"1001 Lazelle St",
    "sg:city":"Sturgis",
    "sg:classifiers":[
        {
            "category":"Professional",
            "subcategory":"Accounting & Tax Preparation",
            "type":"Services"
        }
    ],
    "sg:phone":"+1 605 347 2628",
    "sg:postcode":"57785",
    "sg:province":"SD",
    "sg:tags":[
        "accountant"
    ],
    "wof:name":"Ketel Thorstenson",
    "wof:placetype":"venue"
},
  "geometry": {"coordinates":[-103.511251,44.415518],"type":"Point"}
}