{
  "type": "Feature",
  "properties": {
    "iso:country":"US",
    "sg:address":"1399 10th Ave W",
    "sg:city":"Mobridge",
    "sg:classifiers":[
        {
            "category":"Travel",
            "subcategory":"Hotels & Motels",
            "type":"Entertainment"
        }
    ],
    "sg:phone":"+1 605 845 2750",
    "sg:postcode":"57601",
    "sg:province":"SD",
    "wof:name":"Hbe Corporation",
    "wof:placetype":"venue"
},
  "geometry": {"coordinates":[-100.448318,45.545511],"type":"Point"}
}