{
  "type": "Feature",
  "properties": {
    "addr:full":"1741 Dakota Ave S Huron SD 57350",
    "addr:housenumber":"1741",
    "addr:postcode":"57350",
    "addr:street":"Dakota Ave S",
    "iso:country":"US",
    "sg:address":"1741 Dakota Ave S",
    "sg:city":"Huron",
    "sg:classifiers":[
        {
            "category":"Personal",
            "subcategory":"Beauty Salon",
            "type":"Services"
        }
    ],
    "sg:phone":"+1 605 352 4320",
    "sg:postcode":"57350",
    "sg:province":"SD",
    "sg:tags":[
        "shop"
    ],
    "wof:name":"Studio 35",
    "wof:placetype":"venue"
},
  "geometry": {"coordinates":[-98.214241,44.346077],"type":"Point"}
}