{
  "type": "Feature",
  "properties": {
    "iso:country":"US",
    "sg:address":"3226 E Fairground Loop",
    "sg:city":"Spearfish",
    "sg:classifiers":[
        {
            "category":"Retail",
            "subcategory":"Auto Repair",
            "type":"Services"
        }
    ],
    "sg:phone":"+1 605 642 9095",
    "sg:postcode":"57783",
    "sg:province":"SD",
    "sg:tags":[
        "wrecker"
    ],
    "sg:website":"www.sunshinetowing.com",
    "wof:name":"Sunshine Towing",
    "wof:placetype":"venue"
},
  "geometry": {"coordinates":[-103.88644600000001,44.519899],"type":"Point"}
}