{
  "type": "Feature",
  "properties": {
    "iso:country":"US",
    "sg:address":"680 N Lacrosse St",
    "sg:city":"Rapid City",
    "sg:classifiers":[
        {
            "category":"Shopping",
            "subcategory":"Tobacco",
            "type":"Retail Goods"
        }
    ],
    "sg:phone":"+1 605 343 7742",
    "sg:postcode":"57701",
    "sg:province":"SD",
    "sg:tags":[
        "cigarette",
        "product",
        "cigar",
        "dealer"
    ],
    "wof:name":"Tobacco Warehouse Rapid City",
    "wof:placetype":"venue"
},
  "geometry": {"coordinates":[-103.201785,44.089521],"type":"Point"}
}