{
  "type": "Feature",
  "properties": {
    "addr:full":"405 S 2nd St Parkston SD 57366",
    "addr:housenumber":"405",
    "addr:postcode":"57366",
    "addr:street":"S 2Nd St",
    "iso:country":"US",
    "sg:address":"405 S 2nd St",
    "sg:city":"Parkston",
    "sg:classifiers":[
        {
            "category":"Real Estate",
            "subcategory":"Real Estate Operator",
            "type":"Services"
        }
    ],
    "sg:phone":"+1 605 928 3744",
    "sg:postcode":"57366",
    "sg:province":"SD",
    "sg:tags":[
        "property",
        "lessor"
    ],
    "wof:name":"Robert Wegehaupt",
    "wof:placetype":"venue"
},
  "geometry": {"coordinates":[-97.98739,43.391589],"type":"Point"}
}