{
  "type": "Feature",
  "properties": {
    "iso:country":"US",
    "sg:address":"509 Main St",
    "sg:city":"Gregory",
    "sg:classifiers":[
        {
            "category":"Cinema",
            "subcategory":"Movie Rental",
            "type":"Entertainment"
        }
    ],
    "sg:phone":"+1 605 835 8213",
    "sg:postcode":"57533",
    "sg:province":"SD",
    "sg:tags":[
        "leasing",
        "video",
        "disc",
        "tape"
    ],
    "wof:name":"Video Express",
    "wof:placetype":"venue"
},
  "geometry": {"coordinates":[-99.430769,43.232131],"type":"Point"}
}