{
  "type": "Feature",
  "properties": {
    "iso:country":"US",
    "sg:address":"4800 N 4th Ave",
    "sg:city":"Sioux Falls",
    "sg:classifiers":[
        {
            "category":"Social Services",
            "subcategory":"Child Care",
            "type":"Services"
        }
    ],
    "sg:phone":"+1 605 731 3888",
    "sg:postcode":"57104",
    "sg:province":"SD",
    "sg:website":"www.brighthorizon.com",
    "wof:name":"Citibank Family Ctr Daycare",
    "wof:placetype":"venue"
},
  "geometry": {"coordinates":[-96.723553,43.600401],"type":"Point"}
}