{
  "type": "Feature",
  "properties": {
    "iso:country":"US",
    "sg:address":"3908 W 41st St",
    "sg:city":"Sioux Falls",
    "sg:classifiers":[
        {
            "category":"Travel",
            "subcategory":"Hotels & Motels",
            "type":"Entertainment"
        }
    ],
    "sg:phone":"+1 605 362 0148",
    "sg:postcode":"57106",
    "sg:province":"SD",
    "sg:tags":[
        "operation"
    ],
    "wof:name":"Empire Casino",
    "wof:placetype":"venue"
},
  "geometry": {"coordinates":[-96.77411499999999,43.51491],"type":"Point"}
}