{
  "type": "Feature",
  "properties": {
    "iso:country":"US",
    "sg:address":"816 6th St",
    "sg:city":"Rapid City",
    "sg:classifiers":[
        {
            "category":"Professional",
            "subcategory":"Lawyer & Legal Services",
            "type":"Services"
        }
    ],
    "sg:phone":"+1 605 348 2527",
    "sg:postcode":"57701",
    "sg:province":"SD",
    "sg:tags":[
        "attorney"
    ],
    "wof:name":"Jefferies Law Office",
    "wof:placetype":"venue"
},
  "geometry": {"coordinates":[-103.228158,44.076984],"type":"Point"}
}