{
  "type": "Feature",
  "properties": {
    "iso:country":"US",
    "sg:address":"27775 317th Ave",
    "sg:city":"Winner",
    "sg:classifiers":[
        {
            "category":"Building & Trades",
            "subcategory":"Construction",
            "type":"Services"
        }
    ],
    "sg:phone":"+1 605 842 3101",
    "sg:postcode":"57580",
    "sg:province":"SD",
    "sg:tags":[
        "carpentry",
        "contractor"
    ],
    "wof:name":"Oak Tree",
    "wof:placetype":"venue"
},
  "geometry": {"coordinates":[-99.830607,43.375441],"type":"Point"}
}