{
  "type": "Feature",
  "properties": {
    "addr:full":"13676 Neck Yoke Rd Rapid City SD 57702",
    "addr:postcode":"13676;57702",
    "addr:street":"Neck Yoke Rd",
    "iso:country":"US",
    "sg:address":"13676 Neck Yoke Rd",
    "sg:city":"Rapid City",
    "sg:classifiers":[
        {
            "category":"Government",
            "subcategory":"Fire Station",
            "type":"Public Place"
        }
    ],
    "sg:phone":"+1 605 343 8615",
    "sg:postcode":"57702",
    "sg:province":"SD",
    "sg:tags":[
        "state"
    ],
    "wof:name":"Fire Protection Services of Th",
    "wof:placetype":"venue"
},
  "geometry": {"coordinates":[-103.32408,43.942924],"type":"Point"}
}