{
  "type": "Feature",
  "properties": {
    "iso:country":"US",
    "sg:address":"26552 N Shore Pl",
    "sg:city":"Hartford",
    "sg:classifiers":[
        {
            "category":"Shopping",
            "subcategory":"Computers & Home Electronics",
            "type":"Retail Goods"
        }
    ],
    "sg:phone":"+1 605 526 4381",
    "sg:postcode":"57033",
    "sg:province":"SD",
    "wof:name":"Cab Computers & More",
    "wof:placetype":"venue"
},
  "geometry": {"coordinates":[-96.958908,43.539861],"type":"Point"}
}