{
  "type": "Feature",
  "properties": {
    "iso:country":"US",
    "sg:address":"815 S Marion Rd",
    "sg:city":"Sioux Falls",
    "sg:classifiers":[
        {
            "category":"Restaurant",
            "type":"Food & Drink"
        }
    ],
    "sg:phone":"+1 605 373 9662",
    "sg:postcode":"57106",
    "sg:province":"SD",
    "wof:name":"Bogey's Bar Grill & Casino",
    "wof:placetype":"venue"
},
  "geometry": {"coordinates":[-96.790986,43.537405],"type":"Point"}
}