{
  "type": "Feature",
  "properties": {
    "iso:country":"US",
    "sg:address":"803 E Milbank Ave",
    "sg:city":"Milbank",
    "sg:classifiers":[
        {
            "category":"Health Services",
            "subcategory":"Doctor",
            "type":"Services"
        }
    ],
    "sg:phone":"+1 605 432 4587",
    "sg:postcode":"57252",
    "sg:province":"SD",
    "sg:tags":[
        "clinic"
    ],
    "sg:website":"www.milbankdocs.org",
    "wof:name":"Milbank Medical Ctr",
    "wof:placetype":"venue"
},
  "geometry": {"coordinates":[-96.62721999999999,45.222872],"type":"Point"}
}