{
  "type": "Feature",
  "properties": {
    "iso:country":"US",
    "sg:address":"1645 University Ave",
    "sg:city":"Hot Springs",
    "sg:classifiers":[
        {
            "category":"Retail",
            "subcategory":"Self-service Laundry",
            "type":"Services"
        },
        {
            "category":"Autos & Motor Vehicles",
            "subcategory":"Fuel & Gas Station",
            "type":"Retail Goods"
        }
    ],
    "sg:phone":"+1 605 745 6228",
    "sg:postcode":"57747",
    "sg:province":"SD",
    "sg:tags":[
        "station",
        "gasoline",
        "coin"
    ],
    "wof:name":"Mike's Place",
    "wof:placetype":"venue"
},
  "geometry": {"coordinates":[-103.48114700000001,43.429815],"type":"Point"}
}