{
  "type": "Feature",
  "properties": {
    "iso:country":"US",
    "sg:address":"515 S Jessica Ave",
    "sg:city":"Sioux Falls",
    "sg:classifiers":[
        {
            "category":"Professional",
            "subcategory":"Business Services",
            "type":"Services"
        }
    ],
    "sg:phone":"+1 605 332 7698",
    "sg:postcode":"57103",
    "sg:province":"SD",
    "wof:name":"Schoenrogge Ltd Partnership",
    "wof:placetype":"venue"
},
  "geometry": {"coordinates":[-96.702741,43.542273],"type":"Point"}
}