{
  "type": "Feature",
  "properties": {
    "addr:full":"1320 S Main Ave Sioux Falls SD 57105",
    "addr:housenumber":"1320",
    "addr:postcode":"57105",
    "addr:street":"S Main Ave",
    "iso:country":"US",
    "sg:address":"1320 S Main Ave",
    "sg:city":"Sioux Falls",
    "sg:classifiers":[
        {
            "category":"Professional",
            "subcategory":"Employment Agencies",
            "type":"Services"
        }
    ],
    "sg:phone":"+1 605 977 0895",
    "sg:postcode":"57105",
    "sg:province":"SD",
    "sg:tags":[
        "consulting",
        "business"
    ],
    "wof:name":"Innovative Medical Staffing",
    "wof:placetype":"venue"
},
  "geometry": {"coordinates":[-96.72747099999999,43.533233],"type":"Point"}
}