{
  "type": "Feature",
  "properties": {
    "addr:full":"45015 282nd St Hurley SD 57036",
    "addr:housenumber":"45015",
    "addr:postcode":"57036",
    "addr:street":"282Nd St",
    "iso:country":"US",
    "sg:address":"45015 282nd St",
    "sg:city":"Hurley",
    "sg:classifiers":[
        {
            "category":"Farming",
            "subcategory":"Farm",
            "type":"Manufacturing & Wholesale Goods"
        }
    ],
    "sg:phone":"+1 605 238 5637",
    "sg:postcode":"57036",
    "sg:province":"SD",
    "sg:tags":[
        "crop",
        "general"
    ],
    "wof:name":"Roland Spomer",
    "wof:placetype":"venue"
},
  "geometry": {"coordinates":[-97.193173,43.299858],"type":"Point"}
}