{
  "type": "Feature",
  "properties": {
    "iso:country":"US",
    "sg:address":"225 N Main St",
    "sg:city":"Avon",
    "sg:classifiers":[
        {
            "category":"Personal",
            "subcategory":"Beauty Salon",
            "type":"Services"
        }
    ],
    "sg:phone":"+1 605 286 3928",
    "sg:postcode":"57315",
    "sg:province":"SD",
    "wof:name":"Deb & Nyla's Hair Styling",
    "wof:placetype":"venue"
},
  "geometry": {"coordinates":[-98.060244,43.004959],"type":"Point"}
}