{
  "type": "Feature",
  "properties": {
    "addr:full":"311 S Van Buren Ave Pierre SD 57501",
    "addr:housenumber":"311",
    "addr:postcode":"57501",
    "addr:street":"S Van Buren Ave",
    "iso:country":"US",
    "sg:address":"311 S Van Buren Ave",
    "sg:city":"Pierre",
    "sg:classifiers":[
        {
            "category":"Real Estate",
            "subcategory":"Real Estate Operator",
            "type":"Services"
        }
    ],
    "sg:phone":"+1 605 224 7963",
    "sg:postcode":"57501",
    "sg:province":"SD",
    "sg:tags":[
        "building",
        "special",
        "nonresidential"
    ],
    "wof:name":"Mid-Dakota Storage",
    "wof:placetype":"venue"
},
  "geometry": {"coordinates":[-100.33143800000001,44.36151],"type":"Point"}
}