{
  "type": "Feature",
  "properties": {
    "addr:full":"104 W 12th St Sioux Falls SD 57104",
    "addr:housenumber":"104",
    "addr:postcode":"57104",
    "addr:street":"W 12Th St",
    "iso:country":"US",
    "sg:address":"104 W 12th St",
    "sg:city":"Sioux Falls",
    "sg:classifiers":[
        {
            "category":"Retail",
            "subcategory":"Auto Repair",
            "type":"Services"
        }
    ],
    "sg:phone":"+1 605 336 3108",
    "sg:postcode":"57104",
    "sg:province":"SD",
    "sg:tags":[
        "transmission"
    ],
    "wof:name":"Jack Egge Automatic Trans Svc",
    "wof:placetype":"venue"
},
  "geometry": {"coordinates":[-96.72820900000001,43.543548],"type":"Point"}
}