{
  "type": "Feature",
  "properties": {
    "iso:country":"US",
    "sg:address":"211 W Main St",
    "sg:city":"Lead",
    "sg:classifiers":[
        {
            "category":"Organizations",
            "subcategory":"Labor Organization",
            "type":"Services"
        }
    ],
    "sg:phone":"+1 605 717 4949",
    "sg:postcode":"57754",
    "sg:province":"SD",
    "wof:name":"IUOE Local 49",
    "wof:placetype":"venue"
},
  "geometry": {"coordinates":[-103.765658,44.351976],"type":"Point"}
}