{
  "type": "Feature",
  "properties": {
    "iso:country":"US",
    "sg:address":"21 N Broadway",
    "sg:city":"Watertown",
    "sg:classifiers":[
        {
            "category":"Shopping",
            "subcategory":"Bicycles & Sporting Goods",
            "type":"Retail Goods"
        }
    ],
    "sg:phone":"+1 605 753 9001",
    "sg:postcode":"57201",
    "sg:province":"SD",
    "wof:name":"Flatland Extreme",
    "wof:placetype":"venue"
},
  "geometry": {"coordinates":[-97.114192,44.901488],"type":"Point"}
}