{
  "type": "Feature",
  "properties": {
    "addr:full":"420 S Garfield Ave Pierre SD 57501",
    "addr:housenumber":"420",
    "addr:postcode":"57501",
    "addr:street":"S Garfield Ave",
    "iso:country":"US",
    "sg:address":"420 S Garfield Ave",
    "sg:city":"Pierre",
    "sg:classifiers":[
        {
            "category":"Government",
            "subcategory":"Office",
            "type":"Public Place"
        }
    ],
    "sg:phone":"+1 605 945 1319",
    "sg:postcode":"57501",
    "sg:province":"SD",
    "wof:name":"Clinical Enigeering-Dhhs/Phs",
    "wof:placetype":"venue"
},
  "geometry": {"coordinates":[-100.316473,44.360695],"type":"Point"}
}