{
  "type": "Feature",
  "properties": {
    "iso:country":"US",
    "sg:address":"200 S Derby Ln",
    "sg:city":"North Sioux City",
    "sg:classifiers":[
        {
            "category":"Building & Trades",
            "subcategory":"Construction",
            "type":"Services"
        }
    ],
    "sg:phone":"+1 605 232 5891",
    "sg:postcode":"57049",
    "sg:province":"SD",
    "sg:tags":[
        "sewer",
        "contractor"
    ],
    "wof:name":"D A Davis Co",
    "wof:placetype":"venue"
},
  "geometry": {"coordinates":[-96.497294,42.521761],"type":"Point"}
}