{
  "type": "Feature",
  "properties": {
    "addr:full":"402 W Grand Xing Mobridge SD 57601",
    "addr:housenumber":"402",
    "addr:postcode":"57601",
    "addr:street":"W Grand Xing",
    "iso:country":"US",
    "sg:address":"402 W Grand Xing",
    "sg:city":"Mobridge",
    "sg:classifiers":[
        {
            "category":"Insurance",
            "subcategory":"Insurance Agent",
            "type":"Services"
        }
    ],
    "sg:phone":"+1 605 845 7778",
    "sg:postcode":"57601",
    "sg:province":"SD",
    "wof:name":"American Family Insurance",
    "wof:placetype":"venue"
},
  "geometry": {"coordinates":[-100.43964,45.537456],"type":"Point"}
}