{
  "type": "Feature",
  "properties": {
    "addr:full":"207 E Capitol Ave Pierre SD 57501",
    "addr:housenumber":"207",
    "addr:postcode":"57501",
    "addr:street":"E Capitol Ave",
    "iso:country":"US",
    "sg:address":"207 E Capitol Ave",
    "sg:city":"Pierre",
    "sg:classifiers":[
        {
            "category":"Communications",
            "subcategory":"Radio Station",
            "type":"Services"
        }
    ],
    "sg:phone":"+1 605 224 4999",
    "sg:postcode":"57501",
    "sg:province":"SD",
    "sg:tags":[
        "company",
        "broadcasting"
    ],
    "wof:name":"KSQP",
    "wof:placetype":"venue"
},
  "geometry": {"coordinates":[-100.35056,44.368336],"type":"Point"}
}