{
  "type": "Feature",
  "properties": {
    "addr:full":"3047 Player Dr Rapid City SD 57702",
    "addr:housenumber":"3047",
    "addr:postcode":"57702",
    "addr:street":"Player Dr",
    "iso:country":"US",
    "sg:address":"3047 Player Dr",
    "sg:city":"Rapid City",
    "sg:classifiers":[
        {
            "category":"Health Services",
            "subcategory":"Doctor",
            "type":"Services"
        }
    ],
    "sg:phone":"+1 605 391 4307",
    "sg:postcode":"57702",
    "sg:province":"SD",
    "sg:tags":[
        "dentist"
    ],
    "wof:name":"David Rempel",
    "wof:placetype":"venue"
},
  "geometry": {"coordinates":[-103.275761,44.055432],"type":"Point"}
}