{
  "type": "Feature",
  "properties": {
    "iso:country":"US",
    "sg:address":"320 N Summit Ave",
    "sg:city":"Sioux Falls",
    "sg:classifiers":[
        {
            "category":"Education",
            "subcategory":"Special Training",
            "type":"Public Place"
        }
    ],
    "sg:phone":"+1 605 335 6524",
    "sg:postcode":"57104",
    "sg:province":"SD",
    "sg:tags":[
        "self",
        "motivational",
        "improvement"
    ],
    "wof:name":"Rebecca Dunn Inc",
    "wof:placetype":"venue"
},
  "geometry": {"coordinates":[-96.73558,43.550955],"type":"Point"}
}