{
  "type": "Feature",
  "properties": {
    "iso:country":"US",
    "sg:address":"2086 Main St",
    "sg:city":"Bowdle",
    "sg:classifiers":[
        {
            "category":"Government",
            "subcategory":"Post Office",
            "type":"Public Place"
        }
    ],
    "sg:phone":"+1 605 285 6262",
    "sg:postcode":"57428",
    "sg:province":"SD",
    "wof:name":"US Post Office",
    "wof:placetype":"venue"
},
  "geometry": {"coordinates":[-99.652499,45.453071],"type":"Point"}
}