{
  "type": "Feature",
  "properties": {
    "iso:country":"US",
    "sg:address":"315 N Washington St",
    "sg:city":"Viborg",
    "sg:classifiers":[
        {
            "category":"Health Services",
            "subcategory":"Doctor",
            "type":"Services"
        }
    ],
    "sg:phone":"+1 605 326 5161",
    "sg:postcode":"57070",
    "sg:province":"SD",
    "sg:tags":[
        "physician",
        "surgeon"
    ],
    "sg:website":"www.pioneermemorial.org",
    "wof:name":"Pioneer Memorial Hospital",
    "wof:placetype":"venue"
},
  "geometry": {"coordinates":[-97.08424100000001,43.174968],"type":"Point"}
}