{
  "type": "Feature",
  "properties": {
    "iso:country":"US",
    "sg:address":"1101 E Spruce St",
    "sg:city":"Mitchell",
    "sg:classifiers":[
        {
            "category":"Personal",
            "subcategory":"Beauty Salon",
            "type":"Services"
        }
    ],
    "sg:phone":"+1 605 995 1444",
    "sg:postcode":"57301",
    "sg:province":"SD",
    "wof:name":"Smart Style Family Hair Salon",
    "wof:placetype":"venue"
},
  "geometry": {"coordinates":[-98.024186,43.687428],"type":"Point"}
}