{
  "type": "Feature",
  "properties": {
    "iso:country":"US",
    "sg:address":"101 E Kemp Ave",
    "sg:city":"Watertown",
    "sg:classifiers":[
        {
            "category":"Shopping",
            "subcategory":"Computers & Home Electronics",
            "type":"Retail Goods"
        }
    ],
    "sg:phone":"+1 605 886 0905",
    "sg:postcode":"57201",
    "sg:province":"SD",
    "sg:tags":[
        "equipment",
        "dealer"
    ],
    "wof:name":"Alpha Omega Computer Elect",
    "wof:placetype":"venue"
},
  "geometry": {"coordinates":[-97.112878,44.900115],"type":"Point"}
}