{
  "type": "Feature",
  "properties": {
    "iso:country":"US",
    "sg:address":"960 22nd Ave S",
    "sg:city":"Brookings",
    "sg:classifiers":[
        {
            "category":"Shopping",
            "subcategory":"Optical Goods",
            "type":"Retail Goods"
        }
    ],
    "sg:phone":"+1 605 692 8262",
    "sg:postcode":"57006",
    "sg:province":"SD",
    "wof:name":"Total Eyewear University Mall",
    "wof:placetype":"venue"
},
  "geometry": {"coordinates":[-96.768398,44.295021],"type":"Point"}
}