{
  "type": "Feature",
  "properties": {
    "addr:full":"1039 4th St NE Watertown SD 57201",
    "addr:housenumber":"1039",
    "addr:postcode":"57201",
    "addr:street":"4Th St Ne",
    "iso:country":"US",
    "sg:address":"1039 4th St NE",
    "sg:city":"Watertown",
    "sg:classifiers":[
        {
            "category":"Real Estate",
            "subcategory":"Real Estate Agent",
            "type":"Services"
        }
    ],
    "sg:phone":"+1 605 882 9677",
    "sg:postcode":"57201",
    "sg:province":"SD",
    "sg:tags":[
        "appraiser"
    ],
    "wof:name":"First Service Appraisal",
    "wof:placetype":"venue"
},
  "geometry": {"coordinates":[-97.10691799999999,44.91359],"type":"Point"}
}