{
  "type": "Feature",
  "properties": {
    "addr:full":"602 Jefferson Ave Frankfort SD 57440",
    "addr:housenumber":"602",
    "addr:postcode":"57440",
    "addr:street":"Jefferson Ave",
    "iso:country":"US",
    "sg:address":"602 Jefferson Ave",
    "sg:city":"Frankfort",
    "sg:classifiers":[
        {
            "category":"Recreation",
            "type":"Entertainment"
        }
    ],
    "sg:phone":"+1 605 472 3623",
    "sg:postcode":"57440",
    "sg:province":"SD",
    "sg:tags":[
        "hall",
        "auditorium"
    ],
    "wof:name":"Frankfort Community Ctr",
    "wof:placetype":"venue"
},
  "geometry": {"coordinates":[-98.305307,44.875546],"type":"Point"}
}