{
  "type": "Feature",
  "properties": {
    "addr:full":"306 James Pl Yankton SD 57078",
    "addr:housenumber":"306",
    "addr:postcode":"57078",
    "addr:street":"James Pl",
    "iso:country":"US",
    "sg:address":"306 James Pl",
    "sg:city":"Yankton",
    "sg:classifiers":[
        {
            "category":"Building & Trades",
            "subcategory":"Construction",
            "type":"Services"
        }
    ],
    "sg:phone":"+1 605 665 1192",
    "sg:postcode":"57078",
    "sg:province":"SD",
    "sg:tags":[
        "house"
    ],
    "wof:name":"Jan Rahn Const",
    "wof:placetype":"venue"
},
  "geometry": {"coordinates":[-97.390084,42.892185],"type":"Point"}
}