{
  "type": "Feature",
  "properties": {
    "addr:full":"102 Dakota Ave Colton SD 57068",
    "addr:housenumber":"102",
    "addr:postcode":"57068",
    "addr:street":"Dakota Ave",
    "iso:country":"US",
    "sg:address":"102 Dakota Ave",
    "sg:city":"Colton",
    "sg:classifiers":[
        {
            "category":"Organizations",
            "subcategory":"Religious Organization",
            "type":"Services"
        }
    ],
    "sg:phone":"+1 605 446 3909",
    "sg:postcode":"57068",
    "sg:province":"SD",
    "sg:tags":[
        "church"
    ],
    "wof:name":"First Reformed Church",
    "wof:placetype":"venue"
},
  "geometry": {"coordinates":[-96.470647,43.579481],"type":"Point"}
}