{
  "type": "Feature",
  "properties": {
    "addr:full":"810 3rd Ave SE Aberdeen SD 57401",
    "addr:housenumber":"810",
    "addr:postcode":"57401",
    "addr:street":"3Rd Ave Se",
    "iso:country":"US",
    "sg:address":"810 3rd Ave SE",
    "sg:city":"Aberdeen",
    "sg:classifiers":[
        {
            "category":"Wholesale",
            "subcategory":"Groceries",
            "type":"Manufacturing & Wholesale Goods"
        }
    ],
    "sg:phone":"+1 605 225 1275",
    "sg:postcode":"57401",
    "sg:province":"SD",
    "sg:tags":[
        "food",
        "broker"
    ],
    "sg:website":"www.hrsfoodservice.com",
    "wof:name":"HRS-Hogg Restaurant Svc",
    "wof:placetype":"venue"
},
  "geometry": {"coordinates":[-98.476186,45.462127],"type":"Point"}
}