{
  "type": "Feature",
  "properties": {
    "iso:country":"US",
    "sg:address":"1011 E Philadelphia St",
    "sg:city":"Rapid City",
    "sg:classifiers":[
        {
            "category":"Wholesale",
            "subcategory":"Machinery & Supplies",
            "type":"Manufacturing & Wholesale Goods"
        }
    ],
    "sg:phone":"+1 605 342 0788",
    "sg:postcode":"57701",
    "sg:province":"SD",
    "sg:tags":[
        "janitor"
    ],
    "wof:name":"Black Hills Chemical & Jntrl",
    "wof:placetype":"venue"
},
  "geometry": {"coordinates":[-103.194568,44.085678],"type":"Point"}
}