{
  "type": "Feature",
  "properties": {
    "iso:country":"US",
    "sg:address":"7408 E Plymouth Rd",
    "sg:city":"Sioux Falls",
    "sg:classifiers":[
        {
            "category":"Retail",
            "subcategory":"Repair Shop",
            "type":"Services"
        }
    ],
    "sg:phone":"+1 605 332 9109",
    "sg:postcode":"57110",
    "sg:province":"SD",
    "sg:tags":[
        "sales",
        "boat"
    ],
    "wof:name":"Duckys Marine Inc",
    "wof:placetype":"venue"
},
  "geometry": {"coordinates":[-96.632503,43.534904],"type":"Point"}
}