{
  "type": "Feature",
  "properties": {
    "iso:country":"US",
    "sg:address":"1100 W 12th St",
    "sg:city":"Sioux Falls",
    "sg:classifiers":[
        {
            "category":"Shopping",
            "subcategory":"Florist",
            "type":"Retail Goods"
        }
    ],
    "sg:phone":"+1 605 334 7720",
    "sg:postcode":"57104",
    "sg:province":"SD",
    "sg:tags":[
        "flower",
        "gift"
    ],
    "wof:name":"Four Seasons Flourists",
    "wof:placetype":"venue"
},
  "geometry": {"coordinates":[-96.742566,43.543955],"type":"Point"}
}