{
  "type": "Feature",
  "properties": {
    "iso:country":"US",
    "sg:address":"17264 US Hwy 281",
    "sg:city":"Redfield",
    "sg:classifiers":[
        {
            "category":"Retail",
            "subcategory":"Repair Shop",
            "type":"Services"
        }
    ],
    "sg:phone":"+1 605 472 0517",
    "sg:postcode":"57469",
    "sg:province":"SD",
    "wof:name":"Country Supply",
    "wof:placetype":"venue"
},
  "geometry": {"coordinates":[-98.51316,44.89073],"type":"Point"}
}