{
  "type": "Feature",
  "properties": {
    "iso:country":"US",
    "sg:address":"105 S Broadway Ave",
    "sg:city":"Marion",
    "sg:phone":"+1 605 648 3140",
    "sg:postcode":"57043",
    "sg:province":"SD",
    "sg:tags":[
        "farm",
        "soybean"
    ],
    "wof:name":"Darwin Gortmaker",
    "wof:placetype":"venue"
},
  "geometry": {"coordinates":[-97.260732,43.422282],"type":"Point"}
}