{
  "type": "Feature",
  "properties": {
    "iso:country":"US",
    "sg:address":"301 1st Ave",
    "sg:city":"Montrose",
    "sg:classifiers":[
        {
            "category":"Freight",
            "type":"Transportation"
        }
    ],
    "sg:phone":"+1 605 363 5009",
    "sg:postcode":"57048",
    "sg:province":"SD",
    "sg:tags":[
        "trucking"
    ],
    "wof:name":"Kenny Katzer Trucking Inc",
    "wof:placetype":"venue"
},
  "geometry": {"coordinates":[-97.183651,43.698813],"type":"Point"}
}