{
  "type": "Feature",
  "properties": {
    "iso:country":"US",
    "sg:address":"2000 W 6th St",
    "sg:city":"Sioux Falls",
    "sg:classifiers":[
        {
            "category":"Real Estate",
            "subcategory":"Real Estate Operator",
            "type":"Services"
        }
    ],
    "sg:phone":"+1 605 334 9660",
    "sg:postcode":"57104",
    "sg:province":"SD",
    "sg:tags":[
        "apartment"
    ],
    "wof:name":"Mallard Cove Apartments",
    "wof:placetype":"venue"
},
  "geometry": {"coordinates":[-96.75268699999999,43.551188],"type":"Point"}
}