{
  "type": "Feature",
  "properties": {
    "addr:full":"1300 9th Ave SE Watertown SD 57201",
    "addr:housenumber":"1300",
    "addr:postcode":"57201",
    "addr:street":"9Th Ave Se",
    "iso:country":"US",
    "sg:address":"1300 9th Ave SE",
    "sg:city":"Watertown",
    "sg:classifiers":[
        {
            "category":"Shopping",
            "subcategory":"Bicycles & Sporting Goods",
            "type":"Retail Goods"
        }
    ],
    "sg:phone":"+1 605 882 3478",
    "sg:postcode":"57201",
    "sg:province":"SD",
    "sg:website":"www.dunhamssports.com",
    "wof:name":"Dunham's Sports",
    "wof:placetype":"venue"
},
  "geometry": {"coordinates":[-97.09560399999999,44.890063],"type":"Point"}
}