{
  "type": "Feature",
  "properties": {
    "addr:full":"1430 N Minnesota Ave Sioux Falls SD 57104",
    "addr:housenumber":"1430",
    "addr:postcode":"57104",
    "addr:street":"N Minnesota Ave",
    "iso:country":"US",
    "sg:address":"1430 N Minnesota Ave",
    "sg:city":"Sioux Falls",
    "sg:classifiers":[
        {
            "category":"Restaurant",
            "type":"Food & Drink"
        }
    ],
    "sg:phone":"+1 605 338 9713",
    "sg:postcode":"57104",
    "sg:province":"SD",
    "wof:name":"K C's Family Restaurant",
    "wof:placetype":"venue"
},
  "geometry": {"coordinates":[-96.73126499999999,43.565483],"type":"Point"}
}