{
  "type": "Feature",
  "properties": {
    "iso:country":"US",
    "sg:address":"163 W Main St",
    "sg:city":"Lead",
    "sg:classifiers":[
        {
            "category":"Communications",
            "subcategory":"Film & Video Production",
            "type":"Services"
        }
    ],
    "sg:phone":"+1 605 584 1400",
    "sg:postcode":"57754",
    "sg:province":"SD",
    "wof:name":"Historical Footprints Inc",
    "wof:placetype":"venue"
},
  "geometry": {"coordinates":[-103.765568,44.351987],"type":"Point"}
}