{
  "type": "Feature",
  "properties": {
    "iso:country":"US",
    "sg:address":"101 Main St E",
    "sg:city":"Bonesteel",
    "sg:classifiers":[
        {
            "category":"Personal",
            "subcategory":"Beauty Salon",
            "type":"Services"
        }
    ],
    "sg:phone":"+1 605 654 2184",
    "sg:postcode":"57382",
    "sg:province":"SD",
    "wof:name":"Style Shop",
    "wof:placetype":"venue"
},
  "geometry": {"coordinates":[-98.57089,44.079387],"type":"Point"}
}