{
  "type": "Feature",
  "properties": {
    "iso:country":"US",
    "sg:address":"240 1st St S",
    "sg:city":"Brookings",
    "sg:classifiers":[
        {
            "category":"Building & Trades",
            "subcategory":"Construction",
            "type":"Services"
        }
    ],
    "sg:phone":"+1 605 697 7887",
    "sg:postcode":"57006",
    "sg:province":"SD",
    "sg:tags":[
        "refuse",
        "system",
        "contractor"
    ],
    "wof:name":"Jerred Roll-of Services",
    "wof:placetype":"venue"
},
  "geometry": {"coordinates":[-96.801096,44.306727],"type":"Point"}
}