{
  "type": "Feature",
  "properties": {
    "iso:country":"US",
    "sg:address":"1887 Harmony Heights Ln",
    "sg:city":"Rapid City",
    "sg:classifiers":[
        {
            "category":"Organizations",
            "subcategory":"Non-profit Organization",
            "type":"Services"
        }
    ],
    "sg:phone":"+1 605 343 1091",
    "sg:postcode":"57702",
    "sg:province":"SD",
    "sg:tags":[
        "information",
        "alcoholism",
        "treatment"
    ],
    "sg:website":"www.aa.org",
    "wof:name":"Alcoholics Anonymous",
    "wof:placetype":"venue"
},
  "geometry": {"coordinates":[-103.24291599999999,44.104662],"type":"Point"}
}