{
  "type": "Feature",
  "properties": {
    "addr:full":"412 W Spruce St Mitchell SD 57301",
    "addr:housenumber":"412",
    "addr:postcode":"57301",
    "addr:street":"W Spruce St",
    "iso:country":"US",
    "sg:address":"412 W Spruce St",
    "sg:city":"Mitchell",
    "sg:classifiers":[
        {
            "category":"Insurance",
            "subcategory":"Insurance Agent",
            "type":"Services"
        }
    ],
    "sg:phone":"+1 605 996 0836",
    "sg:postcode":"57301",
    "sg:province":"SD",
    "wof:name":"Primerica",
    "wof:placetype":"venue"
},
  "geometry": {"coordinates":[-98.036677,43.687357],"type":"Point"}
}