{
  "type": "Feature",
  "properties": {
    "iso:country":"US",
    "sg:address":"803 Industrial Ave",
    "sg:city":"Rapid City",
    "sg:classifiers":[
        {
            "category":"Building & Trades",
            "subcategory":"Construction",
            "type":"Services"
        }
    ],
    "sg:phone":"+1 605 355 0933",
    "sg:postcode":"57702",
    "sg:province":"SD",
    "sg:tags":[
        "excavating",
        "contractor"
    ],
    "wof:name":"Site Work Specialists Inc",
    "wof:placetype":"venue"
},
  "geometry": {"coordinates":[-103.26480100000001,44.091347],"type":"Point"}
}