{
  "type": "Feature",
  "properties": {
    "iso:country":"US",
    "sg:address":"3640 S Hwy 79",
    "sg:city":"Rapid City",
    "sg:classifiers":[
        {
            "category":"Wholesale",
            "subcategory":"Farm Supplies",
            "type":"Manufacturing & Wholesale Goods"
        },
        {
            "category":"Shopping",
            "type":"Retail Goods"
        }
    ],
    "sg:phone":"+1 605 348 0059",
    "sg:postcode":"57701",
    "sg:province":"SD",
    "sg:tags":[
        "feed",
        "seed"
    ],
    "wof:name":"Rapid Feed & Seed",
    "wof:placetype":"venue"
},
  "geometry": {"coordinates":[-103.191699,44.048398],"type":"Point"}
}