{
  "type": "Feature",
  "properties": {
    "iso:country":"US",
    "sg:address":"2220 N Haines Ave",
    "sg:city":"Rapid City",
    "sg:classifiers":[
        {
            "category":"Home & Garden",
            "subcategory":"Home Furnishings",
            "type":"Retail Goods"
        }
    ],
    "sg:phone":"+1 605 341 0672",
    "sg:postcode":"57701",
    "sg:province":"SD",
    "wof:name":"Pier 1",
    "wof:placetype":"venue"
},
  "geometry": {"coordinates":[-103.22165099999999,44.10688],"type":"Point"}
}