{
  "type": "Feature",
  "properties": {
    "iso:country":"US",
    "sg:address":"1106 Christine Ave",
    "sg:city":"Brookings",
    "sg:classifiers":[
        {
            "category":"Personal",
            "subcategory":"Beauty Salon",
            "type":"Services"
        }
    ],
    "sg:phone":"+1 605 691 5186",
    "sg:postcode":"57006",
    "sg:province":"SD",
    "sg:tags":[
        "shop"
    ],
    "wof:name":"Tejay's House Of Hair",
    "wof:placetype":"venue"
},
  "geometry": {"coordinates":[-96.783579,44.293722],"type":"Point"}
}