{
  "type": "Feature",
  "properties": {
    "iso:country":"US",
    "sg:address":"7 Chestnut St W",
    "sg:city":"Sisseton",
    "sg:classifiers":[
        {
            "category":"Government",
            "subcategory":"Office",
            "type":"Public Place"
        }
    ],
    "sg:phone":"+1 605 698 4219",
    "sg:postcode":"57262",
    "sg:province":"SD",
    "wof:name":"Tribal Health Adm",
    "wof:placetype":"venue"
},
  "geometry": {"coordinates":[-97.051035,45.667476],"type":"Point"}
}