{
  "type": "Feature",
  "properties": {
    "iso:country":"US",
    "sg:address":"1008 W 5th St",
    "sg:city":"Canton",
    "sg:classifiers":[
        {
            "category":"Restaurant",
            "type":"Food & Drink"
        }
    ],
    "sg:menulink":"http://www.allmenus.com/sd/canton/144753-subway/menu/",
    "sg:phone":"+1 605 764 8782",
    "sg:postcode":"57013",
    "sg:province":"SD",
    "sg:tags":[
        "american",
        "sandwich"
    ],
    "wof:name":"Subway",
    "wof:placetype":"venue"
},
  "geometry": {"coordinates":[-96.605135,43.300982],"type":"Point"}
}