{
  "type": "Feature",
  "properties": {
    "addr:full":"20 US Hwy 12 Webster SD 57274",
    "addr:housenumber":"20",
    "addr:postcode":"57274",
    "addr:street":"Us Hwy 12",
    "iso:country":"US",
    "sg:address":"20 US Hwy 12",
    "sg:city":"Webster",
    "sg:classifiers":[
        {
            "category":"Food & Beverages",
            "subcategory":"Groceries & Convenience Stores",
            "type":"Retail Goods"
        }
    ],
    "sg:phone":"+1 605 345 4735",
    "sg:postcode":"57274",
    "sg:province":"SD",
    "wof:name":"Amoco Food Shop",
    "wof:placetype":"venue"
},
  "geometry": {"coordinates":[-97.518562,45.340912],"type":"Point"}
}