{
  "type": "Feature",
  "properties": {
    "iso:country":"US",
    "sg:address":"401 Main Ave",
    "sg:city":"Brookings",
    "sg:classifiers":[
        {
            "category":"Communications",
            "subcategory":"News Services",
            "type":"Services"
        },
        {
            "category":"Bars & Pubs",
            "type":"Food & Drink"
        }
    ],
    "sg:phone":"+1 605 692 2921",
    "sg:postcode":"57006",
    "sg:province":"SD",
    "sg:tags":[
        "drinking",
        "product",
        "tobacco"
    ],
    "wof:name":"Ray's Corner",
    "wof:placetype":"venue"
},
  "geometry": {"coordinates":[-96.79860499999999,44.310282],"type":"Point"}
}