{
  "type": "Feature",
  "properties": {
    "addr:full":"1212 Oregon St Rapid City SD 57701",
    "addr:housenumber":"1212",
    "addr:postcode":"57701",
    "addr:street":"Oregon St",
    "iso:country":"US",
    "sg:address":"1212 Oregon St",
    "sg:city":"Rapid City",
    "sg:classifiers":[
        {
            "category":"Wholesale",
            "subcategory":"Electrical",
            "type":"Manufacturing & Wholesale Goods"
        }
    ],
    "sg:phone":"+1 605 343 8363",
    "sg:postcode":"57701",
    "sg:province":"SD",
    "sg:tags":[
        "electronic"
    ],
    "wof:name":"Avs",
    "wof:placetype":"venue"
},
  "geometry": {"coordinates":[-103.194239,44.051912],"type":"Point"}
}