{
  "type": "Feature",
  "properties": {
    "iso:country":"US",
    "sg:address":"25540 473rd Ave",
    "sg:city":"Renner",
    "sg:classifiers":[
        {
            "category":"Shopping",
            "subcategory":"Florist",
            "type":"Retail Goods"
        }
    ],
    "sg:phone":"+1 605 543 5251",
    "sg:postcode":"57055",
    "sg:province":"SD",
    "sg:tags":[
        "business"
    ],
    "wof:name":"Down To Earth Interiorscape",
    "wof:placetype":"venue"
},
  "geometry": {"coordinates":[-96.751344,43.679711],"type":"Point"}
}