{
  "type": "Feature",
  "properties": {
    "addr:full":"306 S Sioux Blvd Brandon SD 57005",
    "addr:housenumber":"306",
    "addr:postcode":"57005",
    "addr:street":"S Sioux Blvd",
    "iso:country":"US",
    "sg:address":"306 S Sioux Blvd",
    "sg:city":"Brandon",
    "sg:classifiers":[
        {
            "category":"Professional",
            "subcategory":"Management & Consulting",
            "type":"Services"
        }
    ],
    "sg:phone":"+1 605 582 8641",
    "sg:postcode":"57005",
    "sg:province":"SD",
    "sg:tags":[
        "fuel"
    ],
    "wof:name":"Alaris Group",
    "wof:placetype":"venue"
},
  "geometry": {"coordinates":[-96.591791,43.59152],"type":"Point"}
}