{
  "type": "Feature",
  "properties": {
    "iso:country":"US",
    "sg:address":"4900 S Technopolis Dr",
    "sg:city":"Sioux Falls",
    "sg:classifiers":[
        {
            "category":"Banks & Credit Unions",
            "subcategory":"Bank",
            "type":"Services"
        }
    ],
    "sg:phone":"+1 605 362 1234",
    "sg:postcode":"57106",
    "sg:province":"SD",
    "sg:tags":[
        "loan",
        "real estate"
    ],
    "wof:name":"Midwest Family Lending",
    "wof:placetype":"venue"
},
  "geometry": {"coordinates":[-96.774657,43.501995],"type":"Point"}
}