{
  "type": "Feature",
  "properties": {
    "iso:country":"US",
    "sg:address":"42418 310th St",
    "sg:city":"Tabor",
    "sg:classifiers":[
        {
            "category":"Building & Trades",
            "subcategory":"Construction",
            "type":"Services"
        }
    ],
    "sg:phone":"+1 605 463 2380",
    "sg:postcode":"57063",
    "sg:province":"SD",
    "sg:tags":[
        "water",
        "well",
        "drilling"
    ],
    "wof:name":"Well Doctor & Repair",
    "wof:placetype":"venue"
},
  "geometry": {"coordinates":[-97.702946,42.893982],"type":"Point"}
}