{
  "type": "Feature",
  "properties": {
    "iso:country":"US",
    "sg:address":"1915 Ash Ave",
    "sg:city":"Rapid City",
    "sg:classifiers":[
        {
            "category":"Professional",
            "type":"Services"
        }
    ],
    "sg:phone":"+1 605 342 1328",
    "sg:postcode":"57703",
    "sg:province":"SD",
    "sg:tags":[
        "establishment"
    ],
    "wof:name":"Border States Paving",
    "wof:placetype":"venue"
},
  "geometry": {"coordinates":[-103.187991,44.066733],"type":"Point"}
}