{
  "type": "Feature",
  "properties": {
    "addr:city":"Yankton",
    "addr:full":"610 Summit St Yankton, Sd 57078-3858",
    "addr:house_number":"610",
    "addr:housenumber":"610",
    "addr:phone":"+1 605-665-3898",
    "addr:postcode":"57078-3858",
    "addr:road":"Summit St",
    "addr:state":"SD",
    "addr:street":"Summit St",
    "iso:country":"US",
    "sg:address":"610 Summit St",
    "sg:city":"Yankton",
    "sg:classifiers":[
        {
            "category":"Government",
            "subcategory":"Office",
            "type":"Public Place"
        }
    ],
    "sg:phone":"+1 605 665 3898",
    "sg:postcode":"57078",
    "sg:province":"SD",
    "wof:name":"Yankton County Historical Society",
    "wof:placetype":"venue"
},
  "geometry": {"coordinates":[-97.40733,42.87447],"type":"Point"}
}