{
  "type": "Feature",
  "properties": {
    "iso:country":"US",
    "sg:address":"610 Summit St",
    "sg:city":"Yankton",
    "sg:classifiers":[
        {
            "category":"Government",
            "subcategory":"Office",
            "type":"Public Place"
        }
    ],
    "sg:phone":"+1 605 665 3898",
    "sg:postcode":"57078",
    "sg:province":"SD",
    "wof:name":"Yankton County Museum",
    "wof:placetype":"venue"
},
  "geometry": {"coordinates":[-97.407406,42.875271],"type":"Point"}
}