{
  "type": "Feature",
  "properties": {
    "iso:country":"US",
    "sg:address":"221 Swanzey St",
    "sg:city":"Keystone",
    "sg:classifiers":[
        {
            "category":"Restaurant",
            "type":"Food & Drink"
        }
    ],
    "sg:phone":"+1 605 666 5002",
    "sg:postcode":"57751",
    "sg:province":"SD",
    "wof:name":"Uncle Tom's Rib Shack",
    "wof:placetype":"venue"
},
  "geometry": {"coordinates":[-103.423306,43.893299],"type":"Point"}
}