{
  "type": "Feature",
  "properties": {
    "iso:country":"US",
    "sg:address":"47774 309th St",
    "sg:city":"Alcester",
    "sg:classifiers":[
        {
            "category":"Farming",
            "subcategory":"Livestock Farm",
            "type":"Manufacturing & Wholesale Goods"
        }
    ],
    "sg:phone":"+1 605 565 2559",
    "sg:postcode":"57001",
    "sg:province":"SD",
    "sg:tags":[
        "beef",
        "feedlot",
        "cattle"
    ],
    "wof:name":"Winquist Farms",
    "wof:placetype":"venue"
},
  "geometry": {"coordinates":[-96.651339,42.909126],"type":"Point"}
}