{
  "type": "Feature",
  "properties": {
    "iso:country":"US",
    "sg:address":"106 W 7th St",
    "sg:city":"Freeman",
    "sg:classifiers":[
        {
            "category":"Social Services",
            "subcategory":"Adult Care",
            "type":"Services"
        }
    ],
    "sg:phone":"+1 605 925 4994",
    "sg:postcode":"57029",
    "sg:province":"SD",
    "sg:tags":[
        "home",
        "residential"
    ],
    "wof:name":"Salem Mennonite Home For Aged",
    "wof:placetype":"venue"
},
  "geometry": {"coordinates":[-97.437379,43.348513],"type":"Point"}
}