{
  "type": "Feature",
  "properties": {
    "iso:country":"US",
    "sg:address":"38926 264th St",
    "sg:city":"Stickney",
    "sg:classifiers":[
        {
            "category":"Farming",
            "subcategory":"Fish & Marine Products",
            "type":"Manufacturing & Wholesale Goods"
        }
    ],
    "sg:phone":"+1 605 732 4402",
    "sg:postcode":"57375",
    "sg:province":"SD",
    "sg:tags":[
        "preserves",
        "fishing",
        "hunting"
    ],
    "wof:name":"S & H Hunting",
    "wof:placetype":"venue"
},
  "geometry": {"coordinates":[-98.40344899999999,43.556489],"type":"Point"}
}