{
  "type": "Feature",
  "properties": {
    "iso:country":"US",
    "sg:address":"202 Girard Ave",
    "sg:city":"Newell",
    "sg:phone":"+1 605 456 2650",
    "sg:postcode":"57760",
    "sg:province":"SD",
    "sg:tags":[
        "oil",
        "gasoline"
    ],
    "wof:name":"Dalcam Oil Co Inc",
    "wof:placetype":"venue"
},
  "geometry": {"coordinates":[-103.420626,44.711245],"type":"Point"}
}