{
  "type": "Feature",
  "properties": {
    "iso:country":"US",
    "sg:address":"3505 E Anoka Cir",
    "sg:city":"Sioux Falls",
    "sg:classifiers":[
        {
            "category":"Professional",
            "type":"Services"
        }
    ],
    "sg:phone":"+1 605 338 4548",
    "sg:postcode":"57103",
    "sg:province":"SD",
    "wof:name":"Payment Services Inc",
    "wof:placetype":"venue"
},
  "geometry": {"coordinates":[-96.681987,43.52088],"type":"Point"}
}