{
  "type": "Feature",
  "properties": {
    "iso:country":"US",
    "sg:address":"1011 Main St",
    "sg:city":"Wilmot",
    "sg:classifiers":[
        {
            "category":"Freight",
            "type":"Transportation"
        }
    ],
    "sg:phone":"+1 605 938 4112",
    "sg:postcode":"57279",
    "sg:province":"SD",
    "sg:tags":[
        "cartage",
        "trucking"
    ],
    "wof:name":"Deutsch Trucking",
    "wof:placetype":"venue"
},
  "geometry": {"coordinates":[-96.85309,45.409793],"type":"Point"}
}