{
  "type": "Feature",
  "properties": {
    "iso:country":"US",
    "sg:address":"5912 W Bristol Dr",
    "sg:city":"Sioux Falls",
    "sg:classifiers":[
        {
            "category":"Building & Trades",
            "subcategory":"Construction",
            "type":"Services"
        }
    ],
    "sg:phone":"+1 605 360 1754",
    "sg:postcode":"57106",
    "sg:province":"SD",
    "sg:tags":[
        "siding",
        "contractor"
    ],
    "wof:name":"CRC Seamless Siding",
    "wof:placetype":"venue"
},
  "geometry": {"coordinates":[-96.798901,43.526199],"type":"Point"}
}