{
  "type": "Feature",
  "properties": {
    "iso:country":"US",
    "sg:address":"4204 S Cathy Ave",
    "sg:city":"Sioux Falls",
    "sg:classifiers":[
        {
            "category":"Wholesale",
            "subcategory":"Machinery & Supplies",
            "type":"Manufacturing & Wholesale Goods"
        }
    ],
    "sg:phone":"+1 605 361 3355",
    "sg:postcode":"57106",
    "sg:province":"SD",
    "sg:tags":[
        "equipment",
        "industrial"
    ],
    "wof:name":"Hydraulic Components",
    "wof:placetype":"venue"
},
  "geometry": {"coordinates":[-96.788356,43.506323],"type":"Point"}
}