{
  "type": "Feature",
  "properties": {
    "addr:full":"813 N Main St Spearfish SD 57783",
    "addr:housenumber":"813",
    "addr:postcode":"57783",
    "addr:street":"N Main St",
    "iso:country":"US",
    "sg:address":"813 N Main St",
    "sg:city":"Spearfish",
    "sg:classifiers":[
        {
            "category":"Food & Beverages",
            "subcategory":"Groceries & Convenience Stores",
            "type":"Retail Goods"
        }
    ],
    "sg:phone":"+1 605 642 5881",
    "sg:postcode":"57783",
    "sg:province":"SD",
    "sg:tags":[
        "station",
        "gasoline"
    ],
    "wof:name":"Mini Mart 445",
    "wof:placetype":"venue"
},
  "geometry": {"coordinates":[-103.859624,44.492056],"type":"Point"}
}