{
  "type": "Feature",
  "properties": {
    "addr:full":"700 12th St SE Madison SD 57042",
    "addr:housenumber":"700",
    "addr:postcode":"57042",
    "addr:street":"12Th St Se",
    "iso:country":"US",
    "sg:address":"700 12th St SE",
    "sg:city":"Madison",
    "sg:classifiers":[
        {
            "category":"Manufacturing",
            "subcategory":"Rubber & Plastics",
            "type":"Manufacturing & Wholesale Goods"
        }
    ],
    "sg:phone":"+1 605 256 9632",
    "sg:postcode":"57042",
    "sg:province":"SD",
    "sg:website":"www.gamurdock.com",
    "wof:name":"G A Murdock Inc",
    "wof:placetype":"venue"
},
  "geometry": {"coordinates":[-97.106582,43.990932],"type":"Point"}
}