{
  "type": "Feature",
  "properties": {
    "iso:country":"US",
    "sg:address":"2900 S Phillips Ave",
    "sg:city":"Sioux Falls",
    "sg:classifiers":[
        {
            "category":"Shopping",
            "subcategory":"Computers & Home Electronics",
            "type":"Retail Goods"
        }
    ],
    "sg:phone":"+1 605 334 9200",
    "sg:postcode":"57105",
    "sg:province":"SD",
    "sg:tags":[
        "software"
    ],
    "wof:name":"Luminous Software LLC",
    "wof:placetype":"venue"
},
  "geometry": {"coordinates":[-96.726236,43.517578],"type":"Point"}
}