{
  "type": "Feature",
  "properties": {
    "addr:full":"711 E Wells Ave Pierre SD 57501",
    "addr:housenumber":"711",
    "addr:postcode":"57501",
    "addr:street":"E Wells Ave",
    "iso:country":"US",
    "sg:address":"711 E Wells Ave",
    "sg:city":"Pierre",
    "sg:classifiers":[
        {
            "category":"Government",
            "subcategory":"Office",
            "type":"Public Place"
        }
    ],
    "sg:phone":"+1 605 773 3301",
    "sg:postcode":"57501",
    "sg:province":"SD",
    "sg:tags":[
        "administrative",
        "program",
        "economic",
        "general"
    ],
    "wof:name":"Tourism Department of",
    "wof:placetype":"venue"
},
  "geometry": {"coordinates":[-100.34302099999999,44.364019],"type":"Point"}
}