{
  "type": "Feature",
  "properties": {
    "iso:country":"US",
    "sg:address":"305 Jefferson Ave",
    "sg:city":"Murdo",
    "sg:classifiers":[
        {
            "category":"Education",
            "subcategory":"School",
            "type":"Public Place"
        }
    ],
    "sg:phone":"+1 605 669 2297",
    "sg:postcode":"57559",
    "sg:province":"SD",
    "wof:name":"Murdo Elementary School",
    "wof:placetype":"venue"
},
  "geometry": {"coordinates":[-100.70893599999999,43.888598],"type":"Point"}
}