{
  "type": "Feature",
  "properties": {
    "iso:country":"US",
    "sg:address":"801 Laframboise Dr",
    "sg:city":"Fort Pierre",
    "sg:classifiers":[
        {
            "category":"Freight",
            "type":"Transportation"
        }
    ],
    "sg:phone":"+1 605 223 9630",
    "sg:postcode":"57532",
    "sg:province":"SD",
    "sg:tags":[
        "operator",
        "local",
        "trucking"
    ],
    "wof:name":"J & S Trucking",
    "wof:placetype":"venue"
},
  "geometry": {"coordinates":[-100.369192,44.346579],"type":"Point"}
}