{
  "type": "Feature",
  "properties": {
    "addr:full":"200 N Phillips Ave Sioux Falls SD 57104",
    "addr:housenumber":"200",
    "addr:postcode":"57104",
    "addr:street":"N Phillips Ave",
    "iso:country":"US",
    "sg:address":"200 N Phillips Ave",
    "sg:city":"Sioux Falls",
    "sg:classifiers":[
        {
            "category":"Professional",
            "subcategory":"Business Services",
            "type":"Services"
        }
    ],
    "sg:phone":"+1 605 336 1620",
    "sg:postcode":"57104",
    "sg:province":"SD",
    "sg:tags":[
        "information",
        "bureau",
        "convention"
    ],
    "sg:website":"www.siouxfallschamber.com",
    "wof:name":"Sioux Falls Convention Bureau",
    "wof:placetype":"venue"
},
  "geometry": {"coordinates":[-96.726823,43.549929],"type":"Point"}
}