{
  "type": "Feature",
  "properties": {
    "iso:country":"US",
    "sg:address":"1008 32nd Ave",
    "sg:city":"Brookings",
    "sg:classifiers":[
        {
            "category":"Professional",
            "subcategory":"Management & Consulting",
            "type":"Services"
        }
    ],
    "sg:phone":"+1 605 692 3187",
    "sg:postcode":"57006",
    "sg:province":"SD",
    "sg:tags":[
        "agricultural",
        "consultant"
    ],
    "wof:name":"Animal Science Consulting",
    "wof:placetype":"venue"
},
  "geometry": {"coordinates":[-96.752666,44.316352],"type":"Point"}
}