{
  "type": "Feature",
  "properties": {
    "iso:country":"US",
    "sg:address":"1205 N Harrison Ave",
    "sg:city":"Pierre",
    "sg:classifiers":[
        {
            "category":"Insurance",
            "subcategory":"Insurance Agent",
            "type":"Services"
        }
    ],
    "sg:phone":"+1 605 224 5509",
    "sg:postcode":"57501",
    "sg:province":"SD",
    "wof:name":"New York Life Insurance Co",
    "wof:placetype":"venue"
},
  "geometry": {"coordinates":[-100.324958,44.374187],"type":"Point"}
}