{
  "type": "Feature",
  "properties": {
    "iso:country":"US",
    "sg:address":"147 N 5th St",
    "sg:city":"Custer",
    "sg:classifiers":[
        {
            "category":"Education",
            "subcategory":"School",
            "type":"Public Place"
        }
    ],
    "sg:phone":"+1 605 673 3154",
    "sg:postcode":"57730",
    "sg:province":"SD",
    "sg:tags":[
        "dist"
    ],
    "wof:name":"Custer Sch Dist 16-1",
    "wof:placetype":"venue"
},
  "geometry": {"coordinates":[-103.600933,43.767391],"type":"Point"}
}