{
  "type": "Feature",
  "properties": {
    "iso:country":"US",
    "sg:address":"1200 S Jay St",
    "sg:city":"Aberdeen",
    "sg:classifiers":[
        {
            "category":"Education",
            "subcategory":"School",
            "type":"Public Place"
        }
    ],
    "sg:phone":"+1 605 626 3359",
    "sg:postcode":"57401",
    "sg:province":"SD",
    "sg:tags":[
        "academic",
        "special"
    ],
    "wof:name":"North Central Special Ed Coop",
    "wof:placetype":"venue"
},
  "geometry": {"coordinates":[-98.483604,45.452742],"type":"Point"}
}