{
  "type": "Feature",
  "properties": {
    "addr:full":"1425 9th Ave SW Watertown SD 57201",
    "addr:housenumber":"1425",
    "addr:postcode":"57201",
    "addr:street":"9Th Ave Sw",
    "iso:country":"US",
    "sg:address":"1425 9th Ave SW",
    "sg:city":"Watertown",
    "sg:classifiers":[
        {
            "category":"Wholesale",
            "subcategory":"Chemicals & Plastics",
            "type":"Manufacturing & Wholesale Goods"
        }
    ],
    "sg:phone":"+1 605 882 1163",
    "sg:postcode":"57201",
    "sg:province":"SD",
    "wof:name":"Rosen Agricultural Chemicals",
    "wof:placetype":"venue"
},
  "geometry": {"coordinates":[-97.138672,44.890127],"type":"Point"}
}