{
  "type": "Feature",
  "properties": {
    "iso:country":"US",
    "sg:address":"17781 467th Ave",
    "sg:city":"Goodwin",
    "sg:phone":"+1 605 793 2468",
    "sg:postcode":"57265",
    "sg:province":"SD",
    "sg:tags":[
        "farm",
        "corn"
    ],
    "wof:name":"Roger Brokseick",
    "wof:placetype":"venue"
},
  "geometry": {"coordinates":[-96.86755100000001,45.03443],"type":"Point"}
}