{
  "type": "Feature",
  "properties": {
    "addr:full":"918 E North St Rapid City SD 57701",
    "addr:housenumber":"918",
    "addr:postcode":"57701",
    "addr:street":"E North St",
    "iso:country":"US",
    "sg:address":"918 E North St",
    "sg:city":"Rapid City",
    "sg:classifiers":[
        {
            "category":"Restaurant",
            "type":"Food & Drink"
        }
    ],
    "sg:menulink":"http://www.allmenus.com/sd/rapid-city/144793-subway/menu/",
    "sg:phone":"+1 605 342 2847",
    "sg:postcode":"57701",
    "sg:province":"SD",
    "sg:tags":[
        "american",
        "sandwich"
    ],
    "wof:name":"Subway",
    "wof:placetype":"venue"
},
  "geometry": {"coordinates":[-103.196304,44.087558],"type":"Point"}
}