{
  "type": "Feature",
  "properties": {
    "addr:full":"403 Main Ave Britton SD 57430",
    "addr:housenumber":"403",
    "addr:postcode":"57430",
    "addr:street":"Main Ave",
    "iso:country":"US",
    "sg:address":"403 Main Ave",
    "sg:city":"Britton",
    "sg:classifiers":[
        {
            "category":"Organizations",
            "subcategory":"Religious Organization",
            "type":"Services"
        }
    ],
    "sg:phone":"+1 605 448 5103",
    "sg:postcode":"57430",
    "sg:province":"SD",
    "sg:tags":[
        "church"
    ],
    "wof:name":"St John's Luth Chr Mo Synod",
    "wof:placetype":"venue"
},
  "geometry": {"coordinates":[-97.750468,45.795412],"type":"Point"}
}