{
  "type": "Feature",
  "properties": {
    "iso:country":"US",
    "sg:address":"6 Sampson St",
    "sg:city":"Deadwood",
    "sg:classifiers":[
        {
            "category":"Professional",
            "subcategory":"Research",
            "type":"Services"
        }
    ],
    "sg:phone":"+1 605 578 1158",
    "sg:postcode":"57732",
    "sg:province":"SD",
    "sg:tags":[
        "environmental",
        "ecological"
    ],
    "wof:name":"Frontier Environmental Svc Inc",
    "wof:placetype":"venue"
},
  "geometry": {"coordinates":[-103.716362,44.382301],"type":"Point"}
}