{
  "type": "Feature",
  "properties": {
    "iso:country":"US",
    "sg:address":"9 Lee St",
    "sg:city":"Deadwood",
    "sg:classifiers":[
        {
            "category":"Recreation",
            "subcategory":"Arcade",
            "type":"Entertainment"
        }
    ],
    "sg:phone":"+1 605 578 1952",
    "sg:postcode":"57732",
    "sg:province":"SD",
    "sg:tags":[
        "casino"
    ],
    "wof:name":"Wooden Nickel",
    "wof:placetype":"venue"
},
  "geometry": {"coordinates":[-103.730228,44.376853],"type":"Point"}
}