{
  "type": "Feature",
  "properties": {
    "addr:full":"14186 323rd Ave Tolstoy SD 57475",
    "addr:housenumber":"14186",
    "addr:postcode":"57475",
    "addr:street":"323Rd Ave",
    "iso:country":"US",
    "sg:address":"14186 323rd Ave",
    "sg:city":"Tolstoy",
    "sg:classifiers":[
        {
            "category":"Farming",
            "subcategory":"Farm",
            "type":"Manufacturing & Wholesale Goods"
        }
    ],
    "sg:phone":"+1 605 948 2281",
    "sg:postcode":"57475",
    "sg:province":"SD",
    "sg:tags":[
        "crop",
        "general"
    ],
    "wof:name":"H Rausch",
    "wof:placetype":"venue"
},
  "geometry": {"coordinates":[-99.708438,45.339372],"type":"Point"}
}