{
  "type": "Feature",
  "properties": {
    "iso:country":"US",
    "sg:address":"5316 W 33rd St",
    "sg:city":"Sioux Falls",
    "sg:classifiers":[
        {
            "category":"Building & Trades",
            "subcategory":"Construction",
            "type":"Services"
        }
    ],
    "sg:phone":"+1 605 361 6216",
    "sg:postcode":"57106",
    "sg:province":"SD",
    "sg:tags":[
        "general",
        "contractor"
    ],
    "wof:name":"Prairie Contracting",
    "wof:placetype":"venue"
},
  "geometry": {"coordinates":[-96.793035,43.521757],"type":"Point"}
}