{
  "type": "Feature",
  "properties": {
    "iso:country":"US",
    "sg:address":"535 S Summit Ave",
    "sg:city":"Sioux Falls",
    "sg:classifiers":[
        {
            "category":"Personal",
            "type":"Services"
        }
    ],
    "sg:phone":"+1 605 360 6955",
    "sg:postcode":"57104",
    "sg:province":"SD",
    "sg:tags":[
        "therapist",
        "massage"
    ],
    "wof:name":"Inner Sanctuary Therapeutic",
    "wof:placetype":"venue"
},
  "geometry": {"coordinates":[-96.735637,43.541037],"type":"Point"}
}