{
  "type": "Feature",
  "properties": {
    "iso:country":"US",
    "sg:address":"960 Dakota Dunes Blvd",
    "sg:city":"Dakota Dunes",
    "sg:classifiers":[
        {
            "category":"Professional",
            "type":"Services"
        }
    ],
    "sg:phone":"+1 605 232 3002",
    "sg:postcode":"57049",
    "sg:province":"SD",
    "sg:tags":[
        "establishment"
    ],
    "wof:name":"Dakota Dunes Cid",
    "wof:placetype":"venue"
},
  "geometry": {"coordinates":[-96.492902,42.491512],"type":"Point"}
}