{
  "type": "Feature",
  "properties": {
    "iso:country":"US",
    "sg:address":"25866 467th Ave",
    "sg:city":"Sioux Falls",
    "sg:phone":"+1 605 528 6724",
    "sg:postcode":"57107",
    "sg:province":"SD",
    "sg:tags":[
        "farm",
        "field",
        "crop"
    ],
    "wof:name":"Helgaas Steffen",
    "wof:placetype":"venue"
},
  "geometry": {"coordinates":[-96.870897,43.632977],"type":"Point"}
}