{
  "type": "Feature",
  "properties": {
    "addr:full":"104 E 4th St White Lake SD 57362",
    "addr:housenumber":"104",
    "addr:postcode":"57362",
    "addr:street":"E 4Th St",
    "iso:country":"US",
    "sg:address":"104 E 4th St",
    "sg:city":"White Lake",
    "sg:classifiers":[
        {
            "category":"Food & Beverages",
            "subcategory":"Groceries & Convenience Stores",
            "type":"Retail Goods"
        }
    ],
    "sg:phone":"+1 605 249 2320",
    "sg:postcode":"57362",
    "sg:province":"SD",
    "wof:name":"A Bar Z",
    "wof:placetype":"venue"
},
  "geometry": {"coordinates":[-98.988612,44.519338],"type":"Point"}
}