{
  "type": "Feature",
  "properties": {
    "addr:full":"1016 West Blvd Rapid City SD 57701",
    "addr:housenumber":"1016",
    "addr:postcode":"57701",
    "addr:street":"West Blvd",
    "iso:country":"US",
    "sg:address":"1016 West Blvd",
    "sg:city":"Rapid City",
    "sg:classifiers":[
        {
            "category":"Farming",
            "subcategory":"Livestock Farm",
            "type":"Manufacturing & Wholesale Goods"
        }
    ],
    "sg:phone":"+1 605 721 9250",
    "sg:postcode":"57701",
    "sg:province":"SD",
    "sg:tags":[
        "sale"
    ],
    "wof:name":"Sam Hurst",
    "wof:placetype":"venue"
},
  "geometry": {"coordinates":[-103.23606700000001,44.076089],"type":"Point"}
}