{
  "type": "Feature",
  "properties": {
    "iso:country":"US",
    "sg:address":"601 W 41st St",
    "sg:city":"Sioux Falls",
    "sg:classifiers":[
        {
            "category":"Food & Beverages",
            "subcategory":"Candy",
            "type":"Retail Goods"
        }
    ],
    "sg:phone":"+1 605 339 4778",
    "sg:postcode":"57105",
    "sg:province":"SD",
    "wof:name":"Puppys Popcorn Co",
    "wof:placetype":"venue"
},
  "geometry": {"coordinates":[-96.733733,43.514855],"type":"Point"}
}