{
  "type": "Feature",
  "properties": {
    "addr:full":"211 Pierre St Blunt SD 57522",
    "addr:housenumber":"211",
    "addr:postcode":"57522",
    "addr:street":"Pierre St",
    "iso:country":"US",
    "sg:address":"211 Pierre St",
    "sg:city":"Blunt",
    "sg:classifiers":[
        {
            "category":"Food & Beverages",
            "subcategory":"Groceries & Convenience Stores",
            "type":"Retail Goods"
        }
    ],
    "sg:phone":"+1 605 962 6221",
    "sg:postcode":"57522",
    "sg:province":"SD",
    "sg:tags":[
        "grocer"
    ],
    "wof:name":"Blunt Cash Store",
    "wof:placetype":"venue"
},
  "geometry": {"coordinates":[-99.989003,44.512395],"type":"Point"}
}