{
  "type": "Feature",
  "properties": {
    "iso:country":"US",
    "sg:address":"43510 188th St",
    "sg:city":"Willow Lake",
    "sg:classifiers":[
        {
            "category":"Farming",
            "subcategory":"Farm & Veterinary Services",
            "type":"Manufacturing & Wholesale Goods"
        }
    ],
    "sg:phone":"+1 605 625 5002",
    "sg:postcode":"57278",
    "sg:province":"SD",
    "sg:tags":[
        "livestock"
    ],
    "wof:name":"Marvin Virchow",
    "wof:placetype":"venue"
},
  "geometry": {"coordinates":[-97.497824,44.659678],"type":"Point"}
}