{
  "type": "Feature",
  "properties": {
    "iso:country":"US",
    "sg:address":"30524 298th St",
    "sg:city":"Winner",
    "sg:classifiers":[
        {
            "category":"Farming",
            "subcategory":"Farm",
            "type":"Manufacturing & Wholesale Goods"
        }
    ],
    "sg:phone":"+1 605 557 3274",
    "sg:postcode":"57580",
    "sg:province":"SD",
    "sg:tags":[
        "crop",
        "general"
    ],
    "wof:name":"Lloyd Moore",
    "wof:placetype":"venue"
},
  "geometry": {"coordinates":[-100.06039199999999,43.08257],"type":"Point"}
}