{
  "type": "Feature",
  "properties": {
    "addr:full":"439 S Pierre St Pierre SD 57501",
    "addr:housenumber":"439",
    "addr:postcode":"57501",
    "addr:street":"S Pierre St",
    "iso:country":"US",
    "sg:address":"439 S Pierre St",
    "sg:city":"Pierre",
    "sg:classifiers":[
        {
            "category":"Retail",
            "subcategory":"Funeral Services",
            "type":"Services"
        }
    ],
    "sg:phone":"+1 605 895 2481",
    "sg:postcode":"57501",
    "sg:province":"SD",
    "sg:tags":[
        "director"
    ],
    "wof:name":"Isburg Hofmeister Funeral",
    "wof:placetype":"venue"
},
  "geometry": {"coordinates":[-100.355453,44.365198],"type":"Point"}
}