{
  "type": "Feature",
  "properties": {
    "iso:country":"US",
    "sg:address":"337 Marian Ave",
    "sg:city":"Brookings",
    "sg:classifiers":[
        {
            "category":"Education",
            "subcategory":"Special Training",
            "type":"Public Place"
        }
    ],
    "sg:phone":"+1 605 692 6056",
    "sg:postcode":"57006",
    "sg:province":"SD",
    "wof:name":"Skills USA Vica",
    "wof:placetype":"venue"
},
  "geometry": {"coordinates":[-96.771388,44.302922],"type":"Point"}
}