{
  "type": "Feature",
  "properties": {
    "iso:country":"US",
    "sg:address":"904 Pearl St",
    "sg:city":"Yankton",
    "sg:classifiers":[
        {
            "category":"Real Estate",
            "subcategory":"Real Estate Operator",
            "type":"Services"
        }
    ],
    "sg:phone":"+1 605 668 0069",
    "sg:postcode":"57078",
    "sg:province":"SD",
    "sg:tags":[
        "building",
        "apartment"
    ],
    "wof:name":"William Harris",
    "wof:placetype":"venue"
},
  "geometry": {"coordinates":[-97.385615,42.878942],"type":"Point"}
}