{
  "type": "Feature",
  "properties": {
    "iso:country":"US",
    "sg:address":"105 5th Ave",
    "sg:city":"Martin",
    "sg:classifiers":[
        {
            "category":"Home & Garden",
            "subcategory":"Garden Supply",
            "type":"Retail Goods"
        }
    ],
    "sg:phone":"+1 605 685 6513",
    "sg:postcode":"57551",
    "sg:province":"SD",
    "sg:tags":[
        "lawn",
        "mower"
    ],
    "wof:name":"Bill's Sales & Svc",
    "wof:placetype":"venue"
},
  "geometry": {"coordinates":[-101.73862699999999,43.174309],"type":"Point"}
}