{
  "type": "Feature",
  "properties": {
    "iso:country":"US",
    "sg:address":"120 Knollwood Dr",
    "sg:city":"Rapid City",
    "sg:classifiers":[
        {
            "category":"Organizations",
            "subcategory":"Professional Association",
            "type":"Services"
        }
    ],
    "sg:phone":"+1 605 341 9939",
    "sg:postcode":"57701",
    "sg:province":"SD",
    "wof:name":"Teton Coalition",
    "wof:placetype":"venue"
},
  "geometry": {"coordinates":[-103.216432,44.103029],"type":"Point"}
}