{
  "type": "Feature",
  "properties": {
    "iso:country":"US",
    "sg:address":"2350 Wisconsin Ave SW",
    "sg:city":"Huron",
    "sg:classifiers":[
        {
            "category":"Communications",
            "subcategory":"Film & Video Production",
            "type":"Services"
        }
    ],
    "sg:phone":"+1 605 352 1435",
    "sg:postcode":"57350",
    "sg:province":"SD",
    "sg:tags":[
        "duplication",
        "tape"
    ],
    "wof:name":"American Home Video Prsrvtn",
    "wof:placetype":"venue"
},
  "geometry": {"coordinates":[-98.21611,44.338041],"type":"Point"}
}