{
  "type": "Feature",
  "properties": {
    "iso:country":"US",
    "sg:address":"811 7th Ave W",
    "sg:city":"Brookings",
    "sg:classifiers":[
        {
            "category":"Organizations",
            "subcategory":"Community Association",
            "type":"Services"
        }
    ],
    "sg:phone":"+1 605 692 6698",
    "sg:postcode":"57006",
    "sg:province":"SD",
    "wof:name":"Sdarl Alumni Assoc Inc",
    "wof:placetype":"venue"
},
  "geometry": {"coordinates":[-96.793622,44.315409],"type":"Point"}
}