{
  "type": "Feature",
  "properties": {
    "addr:full":"2010 W Main St Rapid City SD 57702",
    "addr:housenumber":"2010",
    "addr:postcode":"57702",
    "addr:street":"W Main St",
    "iso:country":"US",
    "sg:address":"2010 W Main St",
    "sg:city":"Rapid City",
    "sg:classifiers":[
        {
            "category":"Restaurant",
            "type":"Food & Drink"
        }
    ],
    "sg:phone":"+1 605 343 5824",
    "sg:postcode":"57702",
    "sg:province":"SD",
    "wof:name":"Millstone",
    "wof:placetype":"venue"
},
  "geometry": {"coordinates":[-103.255433,44.081675],"type":"Point"}
}