{
  "type": "Feature",
  "properties": {
    "iso:country":"US",
    "sg:address":"307 W 3rd Ave",
    "sg:city":"Milbank",
    "sg:classifiers":[
        {
            "category":"Retail",
            "subcategory":"Auto Repair",
            "type":"Services"
        }
    ],
    "sg:phone":"+1 605 432 4015",
    "sg:postcode":"57252",
    "sg:province":"SD",
    "sg:tags":[
        "automotive"
    ],
    "wof:name":"Country Detailers",
    "wof:placetype":"venue"
},
  "geometry": {"coordinates":[-96.644344,45.220044],"type":"Point"}
}