{
  "type": "Feature",
  "properties": {
    "iso:country":"US",
    "sg:address":"714 Circle Dr",
    "sg:city":"Rapid City",
    "sg:classifiers":[
        {
            "category":"Shopping",
            "subcategory":"Beauty & Cosmetics",
            "type":"Retail Goods"
        }
    ],
    "sg:phone":"+1 605 348 9628",
    "sg:postcode":"57702",
    "sg:province":"SD",
    "sg:tags":[
        "merchandise"
    ],
    "wof:name":"Jane Heying",
    "wof:placetype":"venue"
},
  "geometry": {"coordinates":[-103.288113,44.079579],"type":"Point"}
}