{
  "type": "Feature",
  "properties": {
    "addr:full":"103 W Broad Ave Flandreau SD 57028",
    "addr:housenumber":"103",
    "addr:postcode":"57028",
    "addr:street":"W Broad Ave",
    "iso:country":"US",
    "sg:address":"103 W Broad Ave",
    "sg:city":"Flandreau",
    "sg:classifiers":[
        {
            "category":"Real Estate",
            "subcategory":"Real Estate Operator",
            "type":"Services"
        }
    ],
    "sg:phone":"+1 605 997 5233",
    "sg:postcode":"57028",
    "sg:province":"SD",
    "sg:tags":[
        "apartment"
    ],
    "wof:name":"Foxcroft Apartments",
    "wof:placetype":"venue"
},
  "geometry": {"coordinates":[-96.597326,44.043624],"type":"Point"}
}