{
  "type": "Feature",
  "properties": {
    "iso:country":"US",
    "sg:address":"1003 State Hwy 50",
    "sg:city":"Yankton",
    "sg:classifiers":[
        {
            "category":"Autos & Motor Vehicles",
            "subcategory":"Auto Supplies",
            "type":"Retail Goods"
        }
    ],
    "sg:phone":"+1 605 665 7565",
    "sg:postcode":"57078",
    "sg:province":"SD",
    "sg:tags":[
        "battery"
    ],
    "wof:name":"Midwest Battery Doctors",
    "wof:placetype":"venue"
},
  "geometry": {"coordinates":[-97.40754099999999,42.908744],"type":"Point"}
}