{
  "type": "Feature",
  "properties": {
    "iso:country":"US",
    "sg:address":"518 6th St",
    "sg:city":"Rapid City",
    "sg:classifiers":[
        {
            "category":"Professional",
            "subcategory":"Secretarial Services",
            "type":"Services"
        }
    ],
    "sg:phone":"+1 605 342 0277",
    "sg:postcode":"57701",
    "sg:province":"SD",
    "sg:tags":[
        "processing",
        "word"
    ],
    "wof:name":"Word Pro's",
    "wof:placetype":"venue"
},
  "geometry": {"coordinates":[-103.227182,44.080195],"type":"Point"}
}