{
  "type": "Feature",
  "properties": {
    "addr:full":"46874 207th St Brookings SD 57006",
    "addr:housenumber":"46874",
    "addr:postcode":"57006",
    "addr:street":"207Th St",
    "iso:country":"US",
    "sg:address":"46874 207th St",
    "sg:city":"Brookings",
    "sg:classifiers":[
        {
            "category":"Farming",
            "subcategory":"Livestock Farm",
            "type":"Manufacturing & Wholesale Goods"
        }
    ],
    "sg:phone":"+1 605 693 4263",
    "sg:postcode":"57006",
    "sg:province":"SD",
    "sg:tags":[
        "hog",
        "or",
        "feedlot"
    ],
    "wof:name":"Erma Sutton",
    "wof:placetype":"venue"
},
  "geometry": {"coordinates":[-96.834875,44.384196],"type":"Point"}
}