{
  "type": "Feature",
  "properties": {
    "addr:full":"402 S Harrison Ave Pierre SD 57501",
    "addr:housenumber":"402",
    "addr:postcode":"57501",
    "addr:street":"S Harrison Ave",
    "iso:country":"US",
    "sg:address":"402 S Harrison Ave",
    "sg:city":"Pierre",
    "sg:classifiers":[
        {
            "category":"Railroad",
            "type":"Transportation"
        }
    ],
    "sg:phone":"+1 605 224 0207",
    "sg:postcode":"57501",
    "sg:province":"SD",
    "wof:name":"Dakota Minnesota & Eastern",
    "wof:placetype":"venue"
},
  "geometry": {"coordinates":[-100.32988400000001,44.359981],"type":"Point"}
}