{
  "type": "Feature",
  "properties": {
    "iso:country":"US",
    "sg:address":"1339 9th Ave SE",
    "sg:city":"Watertown",
    "sg:classifiers":[
        {
            "category":"Sports & Exercise",
            "subcategory":"Gym",
            "type":"Entertainment"
        }
    ],
    "sg:phone":"+1 605 753 3200",
    "sg:postcode":"57201",
    "sg:province":"SD",
    "sg:tags":[
        "club",
        "health",
        "studio",
        "gymnasium"
    ],
    "wof:name":"Curves",
    "wof:placetype":"venue"
},
  "geometry": {"coordinates":[-97.09511999999999,44.890134],"type":"Point"}
}