{
  "type": "Feature",
  "properties": {
    "iso:country":"US",
    "sg:address":"811 Columbus St",
    "sg:city":"Rapid City",
    "sg:classifiers":[
        {
            "category":"Health Services",
            "subcategory":"Clinic",
            "type":"Services"
        }
    ],
    "sg:phone":"+1 605 343 3007",
    "sg:postcode":"57701",
    "sg:province":"SD",
    "wof:name":"Kirby-Hague Health Care PC",
    "wof:placetype":"venue"
},
  "geometry": {"coordinates":[-103.233761,44.077632],"type":"Point"}
}