{
  "type": "Feature",
  "properties": {
    "addr:full":"104 W 4th Ave Milbank SD 57252",
    "addr:housenumber":"104",
    "addr:postcode":"57252",
    "addr:street":"W 4Th Ave",
    "iso:country":"US",
    "sg:address":"104 W 4th Ave",
    "sg:city":"Milbank",
    "sg:classifiers":[
        {
            "category":"Health Services",
            "subcategory":"Doctor",
            "type":"Services"
        }
    ],
    "sg:phone":"+1 605 432 5011",
    "sg:postcode":"57252",
    "sg:province":"SD",
    "sg:tags":[
        "dentist"
    ],
    "wof:name":"Northeast Orthodontic Assoc",
    "wof:placetype":"venue"
},
  "geometry": {"coordinates":[-96.640067,45.21886],"type":"Point"}
}