{
  "type": "Feature",
  "properties": {
    "iso:country":"US",
    "sg:address":"319 Main St",
    "sg:city":"Astoria",
    "sg:classifiers":[
        {
            "category":"Education",
            "subcategory":"School",
            "type":"Public Place"
        }
    ],
    "sg:phone":"+1 605 832 2111",
    "sg:postcode":"57213",
    "sg:province":"SD",
    "wof:name":"Astoria School",
    "wof:placetype":"venue"
},
  "geometry": {"coordinates":[-96.541383,44.558285],"type":"Point"}
}