{
  "type": "Feature",
  "properties": {
    "addr:full":"202 Maple St E Sisseton SD 57262",
    "addr:housenumber":"202",
    "addr:postcode":"57262",
    "addr:street":"Maple St E Sisseton",
    "iso:country":"US",
    "sg:address":"202 Maple St E",
    "sg:city":"Sisseton",
    "sg:classifiers":[
        {
            "category":"Organizations",
            "subcategory":"Religious Organization",
            "type":"Services"
        }
    ],
    "sg:phone":"+1 605 698 7146",
    "sg:postcode":"57262",
    "sg:province":"SD",
    "sg:tags":[
        "church"
    ],
    "wof:name":"First Presbyterian Church",
    "wof:placetype":"venue"
},
  "geometry": {"coordinates":[-97.047067,45.663669],"type":"Point"}
}