{
  "type": "Feature",
  "properties": {
    "iso:country":"US",
    "sg:address":"20734 419th Ave",
    "sg:city":"Iroquois",
    "sg:phone":"+1 605 546 2372",
    "sg:postcode":"57353",
    "sg:province":"SD",
    "sg:tags":[
        "co",
        "farm",
        "cash",
        "crop",
        "grain",
        "wheat",
        "harvesting"
    ],
    "wof:name":"Hugh Evans",
    "wof:placetype":"venue"
},
  "geometry": {"coordinates":[-97.83304200000001,44.378105],"type":"Point"}
}