{
  "type": "Feature",
  "properties": {
    "iso:country":"US",
    "sg:address":"1545 Quarterback Ct",
    "sg:city":"Huron",
    "sg:classifiers":[
        {
            "category":"Building & Trades",
            "subcategory":"Plumbing",
            "type":"Services"
        },
        {
            "category":"Home & Garden",
            "subcategory":"Garden Supply",
            "type":"Retail Goods"
        }
    ],
    "sg:phone":"+1 605 352 0815",
    "sg:postcode":"57350",
    "sg:province":"SD",
    "sg:tags":[
        "sprinkler",
        "contractor"
    ],
    "wof:name":"Jim & Jake's Sprinkler Systems",
    "wof:placetype":"venue"
},
  "geometry": {"coordinates":[-98.217095,44.348767],"type":"Point"}
}