{
  "type": "Feature",
  "properties": {
    "addr:full":"120 15th St NE Watertown SD 57201",
    "addr:housenumber":"120",
    "addr:postcode":"57201",
    "addr:street":"15Th St Ne",
    "iso:country":"US",
    "sg:address":"120 15th St NE",
    "sg:city":"Watertown",
    "sg:classifiers":[
        {
            "category":"Manufacturing",
            "subcategory":"Signs",
            "type":"Manufacturing & Wholesale Goods"
        }
    ],
    "sg:phone":"+1 605 886 4545",
    "sg:postcode":"57201",
    "sg:province":"SD",
    "sg:tags":[
        "specialty",
        "mfg"
    ],
    "wof:name":"Sign Specialties",
    "wof:placetype":"venue"
},
  "geometry": {"coordinates":[-97.09162999999999,44.902859],"type":"Point"}
}