{
  "type": "Feature",
  "properties": {
    "iso:country":"US",
    "sg:address":"912 S 12th St",
    "sg:city":"Aberdeen",
    "sg:classifiers":[
        {
            "category":"Retail",
            "subcategory":"Auto Repair",
            "type":"Services"
        }
    ],
    "sg:phone":"+1 605 226 8506",
    "sg:postcode":"57401",
    "sg:province":"SD",
    "sg:tags":[
        "general"
    ],
    "wof:name":"Performance Products & Repair",
    "wof:placetype":"venue"
},
  "geometry": {"coordinates":[-98.505666,45.455144],"type":"Point"}
}