{
  "type": "Feature",
  "properties": {
    "iso:country":"US",
    "sg:address":"1105 E Sioux Ave",
    "sg:city":"Pierre",
    "sg:classifiers":[
        {
            "category":"Shopping",
            "subcategory":"Used Merchandise",
            "type":"Retail Goods"
        }
    ],
    "sg:phone":"+1 605 945 0150",
    "sg:postcode":"57501",
    "sg:province":"SD",
    "wof:name":"Hospice Thrift Store",
    "wof:placetype":"venue"
},
  "geometry": {"coordinates":[-100.337585,44.360279],"type":"Point"}
}