{
  "type": "Feature",
  "properties": {
    "addr:full":"319 S Coteau St Pierre SD 57501",
    "addr:housenumber":"319",
    "addr:postcode":"57501",
    "addr:street":"S Coteau St",
    "iso:country":"US",
    "sg:address":"319 S Coteau St",
    "sg:city":"Pierre",
    "sg:classifiers":[
        {
            "category":"Social Services",
            "type":"Services"
        }
    ],
    "sg:phone":"+1 605 773 4937",
    "sg:postcode":"57501",
    "sg:province":"SD",
    "sg:tags":[
        "information",
        "planning",
        "center",
        "family"
    ],
    "wof:name":"Hughes County",
    "wof:placetype":"venue"
},
  "geometry": {"coordinates":[-100.352659,44.365845],"type":"Point"}
}