{
  "type": "Feature",
  "properties": {
    "addr:full":"309 S Railroad Ave Jefferson SD 57038",
    "addr:housenumber":"309",
    "addr:postcode":"57038",
    "addr:street":"S Railroad Ave",
    "iso:country":"US",
    "sg:address":"309 S Railroad Ave",
    "sg:city":"Jefferson",
    "sg:classifiers":[
        {
            "category":"Recreation",
            "type":"Entertainment"
        }
    ],
    "sg:phone":"+1 605 966 5597",
    "sg:postcode":"57038",
    "sg:province":"SD",
    "sg:tags":[
        "hall",
        "auditorium"
    ],
    "wof:name":"Community Center",
    "wof:placetype":"venue"
},
  "geometry": {"coordinates":[-96.56068,42.602466],"type":"Point"}
}