{
  "type": "Feature",
  "properties": {
    "iso:country":"US",
    "sg:address":"5209 W 41st St",
    "sg:city":"Sioux Falls",
    "sg:classifiers":[
        {
            "category":"Utilities",
            "subcategory":"Mobile Phone",
            "type":"Services"
        },
        {
            "category":"Shopping",
            "type":"Retail Goods"
        }
    ],
    "sg:phone":"+1 605 323 1492",
    "sg:postcode":"57106",
    "sg:province":"SD",
    "sg:tags":[
        "equipment",
        "telephone",
        "cellular",
        "supply"
    ],
    "wof:name":"Western Wireless Corp",
    "wof:placetype":"venue"
},
  "geometry": {"coordinates":[-96.790869,43.514735],"type":"Point"}
}