{
  "type": "Feature",
  "properties": {
    "iso:country":"US",
    "sg:address":"216 2nd Ave",
    "sg:city":"Castlewood",
    "sg:classifiers":[
        {
            "category":"Retail",
            "subcategory":"Repair Shop",
            "type":"Services"
        }
    ],
    "sg:phone":"+1 605 793 2635",
    "sg:postcode":"57223",
    "sg:province":"SD",
    "sg:tags":[
        "welding"
    ],
    "wof:name":"White's Welding",
    "wof:placetype":"venue"
},
  "geometry": {"coordinates":[-97.03036,44.724829],"type":"Point"}
}