{
  "type": "Feature",
  "properties": {
    "iso:country":"US",
    "sg:address":"3224 S Pillsberry Ave",
    "sg:city":"Sioux Falls",
    "sg:classifiers":[
        {
            "category":"Building & Trades",
            "subcategory":"Landscaping Services",
            "type":"Services"
        }
    ],
    "sg:phone":"+1 605 333 0382",
    "sg:postcode":"57103",
    "sg:province":"SD",
    "sg:tags":[
        "landscape",
        "contractor"
    ],
    "wof:name":"Peters Landscaping & Lawn Care",
    "wof:placetype":"venue"
},
  "geometry": {"coordinates":[-96.674246,43.517446],"type":"Point"}
}