{
  "type": "Feature",
  "properties": {
    "iso:country":"US",
    "sg:address":"200 E Center St",
    "sg:city":"Madison",
    "sg:classifiers":[
        {
            "category":"Government",
            "subcategory":"Court House",
            "type":"Public Place"
        }
    ],
    "sg:phone":"+1 605 256 5285",
    "sg:postcode":"57042",
    "sg:province":"SD",
    "sg:tags":[
        "state"
    ],
    "wof:name":"Circuit Court Judge",
    "wof:placetype":"venue"
},
  "geometry": {"coordinates":[-97.112543,44.005109],"type":"Point"}
}