{
  "type": "Feature",
  "properties": {
    "addr:full":"107 W Commercial Ave Gettysburg SD 57442",
    "addr:housenumber":"107",
    "addr:postcode":"57442",
    "addr:street":"W Commercial Ave",
    "iso:country":"US",
    "sg:address":"107 W Commercial Ave",
    "sg:city":"Gettysburg",
    "sg:classifiers":[
        {
            "category":"Shopping",
            "subcategory":"Bicycles & Sporting Goods",
            "type":"Retail Goods"
        }
    ],
    "sg:phone":"+1 605 765 2183",
    "sg:postcode":"57442",
    "sg:province":"SD",
    "sg:tags":[
        "gun",
        "gunsmith"
    ],
    "sg:website":"www.truevalue.com",
    "wof:name":"True Value Hardware",
    "wof:placetype":"venue"
},
  "geometry": {"coordinates":[-99.957098,45.011481],"type":"Point"}
}