{
  "type": "Feature",
  "properties": {
    "addr:full":"196 Main St Mc Intosh SD 57601",
    "addr:housenumber":"196",
    "addr:postcode":"57601",
    "addr:street":"Main St",
    "iso:country":"US",
    "sg:address":"196 Main St",
    "sg:city":"Mc Intosh",
    "sg:classifiers":[
        {
            "category":"Home & Garden",
            "subcategory":"Building Materials",
            "type":"Retail Goods"
        }
    ],
    "sg:phone":"+1 605 273 4333",
    "sg:postcode":"57601",
    "sg:province":"SD",
    "sg:tags":[
        "paint"
    ],
    "wof:name":"Rye Lumber & Trustworthy Hdwr",
    "wof:placetype":"venue"
},
  "geometry": {"coordinates":[-100.433802,45.533391],"type":"Point"}
}