{
  "type": "Feature",
  "properties": {
    "iso:country":"US",
    "sg:address":"3201 Hall St",
    "sg:city":"Rapid City",
    "sg:classifiers":[
        {
            "category":"Real Estate",
            "subcategory":"Real Estate Agent",
            "type":"Services"
        }
    ],
    "sg:phone":"+1 605 341 5000",
    "sg:postcode":"57702",
    "sg:province":"SD",
    "wof:name":"Flack-Hoffman Inc Realtors",
    "wof:placetype":"venue"
},
  "geometry": {"coordinates":[-103.273889,44.080821],"type":"Point"}
}