{
  "type": "Feature",
  "properties": {
    "addr:full":"1010 Fresno Ave Hot Springs SD 57747",
    "addr:housenumber":"1010",
    "addr:postcode":"57747",
    "addr:street":"Fresno Ave",
    "iso:country":"US",
    "sg:address":"1010 Fresno Ave",
    "sg:city":"Hot Springs",
    "sg:classifiers":[
        {
            "category":"Building & Trades",
            "subcategory":"Construction",
            "type":"Services"
        }
    ],
    "sg:phone":"+1 605 745 6457",
    "sg:postcode":"57747",
    "sg:province":"SD",
    "sg:tags":[
        "excavation"
    ],
    "wof:name":"Caldwell Construction Inc",
    "wof:placetype":"venue"
},
  "geometry": {"coordinates":[-103.47248500000001,43.423186],"type":"Point"}
}