{
  "type": "Feature",
  "properties": {
    "iso:country":"US",
    "sg:address":"213 N Meyer Ln",
    "sg:city":"Sioux Falls",
    "sg:classifiers":[
        {
            "category":"Real Estate",
            "subcategory":"Real Estate Operator",
            "type":"Services"
        }
    ],
    "sg:phone":"+1 605 332 0624",
    "sg:postcode":"57103",
    "sg:province":"SD",
    "sg:tags":[
        "property",
        "lessor"
    ],
    "wof:name":"Norma Baartman",
    "wof:placetype":"venue"
},
  "geometry": {"coordinates":[-96.67424699999999,43.545345],"type":"Point"}
}