{
  "type": "Feature",
  "properties": {
    "addr:full":"29074 N Wheeler Rd Geddes SD 57342",
    "addr:housenumber":"29074",
    "addr:postcode":"57342",
    "addr:street":"N Wheeler Rd",
    "iso:country":"US",
    "sg:address":"29074 N Wheeler Rd",
    "sg:city":"Geddes",
    "sg:classifiers":[
        {
            "category":"Banks & Credit Unions",
            "subcategory":"Financial Services",
            "type":"Services"
        }
    ],
    "sg:phone":"+1 605 337 3215",
    "sg:postcode":"57342",
    "sg:province":"SD",
    "sg:tags":[
        "trust",
        "management"
    ],
    "wof:name":"Hennings Family Trust",
    "wof:placetype":"venue"
},
  "geometry": {"coordinates":[-98.82539199999999,43.187355],"type":"Point"}
}