{
  "type": "Feature",
  "properties": {
    "iso:country":"US",
    "sg:address":"10 E Kemp Ave",
    "sg:city":"Watertown",
    "sg:classifiers":[
        {
            "category":"Food & Beverages",
            "subcategory":"Bakery",
            "type":"Retail Goods"
        }
    ],
    "sg:phone":"+1 605 753 5715",
    "sg:postcode":"57201",
    "sg:province":"SD",
    "sg:tags":[
        "baker"
    ],
    "wof:name":"Sugar Shack",
    "wof:placetype":"venue"
},
  "geometry": {"coordinates":[-97.114081,44.900245],"type":"Point"}
}