{
  "type": "Feature",
  "properties": {
    "iso:country":"US",
    "sg:address":"650 12th St SE",
    "sg:city":"Huron",
    "sg:classifiers":[
        {
            "category":"Manufacturing",
            "subcategory":"Food",
            "type":"Manufacturing & Wholesale Goods"
        }
    ],
    "sg:phone":"+1 605 796 4910",
    "sg:postcode":"57350",
    "sg:province":"SD",
    "sg:tags":[
        "frozen",
        "specialty",
        "mfg"
    ],
    "wof:name":"Tenos Tacos",
    "wof:placetype":"venue"
},
  "geometry": {"coordinates":[-98.20381999999999,44.35265],"type":"Point"}
}