{
  "type": "Feature",
  "properties": {
    "iso:country":"US",
    "sg:address":"415 Western Ave",
    "sg:city":"Brookings",
    "sg:classifiers":[
        {
            "category":"Government",
            "subcategory":"Office",
            "type":"Public Place"
        }
    ],
    "sg:phone":"+1 605 697 6387",
    "sg:postcode":"57006",
    "sg:province":"SD",
    "sg:tags":[
        "village"
    ],
    "wof:name":"Brookings City Animal Shelter",
    "wof:placetype":"venue"
},
  "geometry": {"coordinates":[-96.80873099999999,44.31027],"type":"Point"}
}