{
  "type": "Feature",
  "properties": {
    "addr:full":"324 4th St NE Watertown SD 57201",
    "addr:housenumber":"324",
    "addr:postcode":"57201",
    "addr:street":"4Th St Ne",
    "iso:country":"US",
    "sg:address":"324 4th St NE",
    "sg:city":"Watertown",
    "sg:classifiers":[
        {
            "category":"Health Services",
            "subcategory":"Doctor",
            "type":"Services"
        }
    ],
    "sg:phone":"+1 605 886 8866",
    "sg:postcode":"57201",
    "sg:province":"SD",
    "sg:tags":[
        "dentist"
    ],
    "wof:name":"Family Dental Care",
    "wof:placetype":"venue"
},
  "geometry": {"coordinates":[-97.106819,44.904643],"type":"Point"}
}