{
  "type": "Feature",
  "properties": {
    "iso:country":"US",
    "sg:address":"105 S Egan Ave",
    "sg:city":"Madison",
    "sg:classifiers":[
        {
            "category":"Shopping",
            "subcategory":"Clothing, Apparel, & Fashions",
            "type":"Retail Goods"
        }
    ],
    "sg:phone":"+1 605 256 2728",
    "sg:postcode":"57042",
    "sg:province":"SD",
    "sg:tags":[
        "furnishing"
    ],
    "wof:name":"Stan's Men's Shop",
    "wof:placetype":"venue"
},
  "geometry": {"coordinates":[-97.1141,44.005032],"type":"Point"}
}