{
  "type": "Feature",
  "properties": {
    "iso:country":"US",
    "sg:address":"18516 Fairpoint Rd",
    "sg:city":"Union Center",
    "sg:classifiers":[
        {
            "category":"Travel",
            "subcategory":"Campground",
            "type":"Entertainment"
        }
    ],
    "sg:phone":"+1 605 985 5932",
    "sg:postcode":"57787",
    "sg:province":"SD",
    "sg:tags":[
        "camp"
    ],
    "wof:name":"Hodgman Ranch",
    "wof:placetype":"venue"
},
  "geometry": {"coordinates":[-102.796369,44.69355],"type":"Point"}
}