{
  "type": "Feature",
  "properties": {
    "iso:country":"US",
    "sg:address":"202 Saint Olaf Ave",
    "sg:city":"Baltic",
    "sg:classifiers":[
        {
            "category":"Banks & Credit Unions",
            "subcategory":"Bank",
            "type":"Services"
        }
    ],
    "sg:phone":"+1 605 782 5940",
    "sg:postcode":"57003",
    "sg:province":"SD",
    "wof:name":"First National Bank",
    "wof:placetype":"venue"
},
  "geometry": {"coordinates":[-96.739504,43.760199],"type":"Point"}
}