{
  "type": "Feature",
  "properties": {
    "iso:country":"US",
    "sg:address":"2525 Dyess Ave",
    "sg:city":"Rapid City",
    "sg:classifiers":[
        {
            "category":"Home & Garden",
            "subcategory":"Building Materials",
            "type":"Retail Goods"
        }
    ],
    "sg:phone":"+1 605 341 8667",
    "sg:postcode":"57701",
    "sg:province":"SD",
    "sg:tags":[
        "door"
    ],
    "sg:website":"www.commercialdoorinc.com",
    "wof:name":"Commercial Door & Specialties",
    "wof:placetype":"venue"
},
  "geometry": {"coordinates":[-103.171575,44.110195],"type":"Point"}
}