{
  "type": "Feature",
  "properties": {
    "iso:country":"US",
    "sg:address":"47542 197th St",
    "sg:city":"Toronto",
    "sg:phone":"+1 605 794 4431",
    "sg:postcode":"57268",
    "sg:province":"SD",
    "sg:tags":[
        "real",
        "wheat",
        "lessor",
        "farm",
        "corn",
        "soybean",
        "property"
    ],
    "wof:name":"Robert King",
    "wof:placetype":"venue"
},
  "geometry": {"coordinates":[-96.69840600000001,44.528572],"type":"Point"}
}