{
  "type": "Feature",
  "properties": {
    "addr:full":"204 S 4th St Ofc Milbank SD 57252",
    "addr:housenumber":"204",
    "addr:postcode":"57252",
    "addr:street":"S 4Th St",
    "iso:country":"US",
    "sg:address":"204 S 4th St Ofc",
    "sg:city":"Milbank",
    "sg:classifiers":[
        {
            "category":"Real Estate",
            "subcategory":"Real Estate Operator",
            "type":"Services"
        }
    ],
    "sg:phone":"+1 605 432 4077",
    "sg:postcode":"57252",
    "sg:province":"SD",
    "sg:tags":[
        "apartment"
    ],
    "wof:name":"Decota Nights",
    "wof:placetype":"venue"
},
  "geometry": {"coordinates":[-96.632957,45.220911],"type":"Point"}
}