{
  "type": "Feature",
  "properties": {
    "iso:country":"US",
    "sg:address":"3310 N Potsdam Ave",
    "sg:city":"Sioux Falls",
    "sg:classifiers":[
        {
            "category":"Freight",
            "type":"Transportation"
        }
    ],
    "sg:phone":"+1 605 977 0719",
    "sg:postcode":"57104",
    "sg:province":"SD",
    "sg:tags":[
        "operator",
        "local",
        "trucking"
    ],
    "wof:name":"2 Guys On Move",
    "wof:placetype":"venue"
},
  "geometry": {"coordinates":[-96.69521,43.580553],"type":"Point"}
}