{
  "type": "Feature",
  "properties": {
    "iso:country":"US",
    "sg:address":"3001 Broadway St",
    "sg:city":"Yankton",
    "sg:classifiers":[
        {
            "category":"Shopping",
            "subcategory":"Department Store",
            "type":"Retail Goods"
        }
    ],
    "sg:phone":"+1 605 665 1425",
    "sg:postcode":"57078",
    "sg:province":"SD",
    "sg:website":"www.walmart.com",
    "wof:name":"Wal-Mart",
    "wof:placetype":"venue"
},
  "geometry": {"coordinates":[-97.39765300000001,42.904835],"type":"Point"}
}