{
  "type": "Feature",
  "properties": {
    "addr:full":"1315 N Haines Ave Rapid City SD 57701",
    "addr:housenumber":"1315",
    "addr:postcode":"57701",
    "addr:street":"N Haines Ave",
    "iso:country":"US",
    "sg:address":"1315 N Haines Ave",
    "sg:city":"Rapid City",
    "sg:classifiers":[
        {
            "category":"Shopping",
            "subcategory":"Gifts & Souvenirs",
            "type":"Retail Goods"
        }
    ],
    "sg:phone":"+1 605 341 7024",
    "sg:postcode":"57701",
    "sg:province":"SD",
    "wof:name":"Mouse In House Discount GI",
    "wof:placetype":"venue"
},
  "geometry": {"coordinates":[-103.221913,44.098363],"type":"Point"}
}