{
  "type": "Feature",
  "properties": {
    "iso:country":"US",
    "sg:address":"211 West Blvd N",
    "sg:city":"Rapid City",
    "sg:classifiers":[
        {
            "category":"Social Services",
            "subcategory":"Job Training",
            "type":"Services"
        }
    ],
    "sg:phone":"+1 605 342 4294",
    "sg:postcode":"57701",
    "sg:province":"SD",
    "sg:tags":[
        "rehabilitation"
    ],
    "wof:name":"Friendship House-Men & Women",
    "wof:placetype":"venue"
},
  "geometry": {"coordinates":[-103.233216,44.087724],"type":"Point"}
}