{
  "type": "Feature",
  "properties": {
    "addr:full":"44674 256th St Montrose SD 57048",
    "addr:housenumber":"44674",
    "addr:postcode":"57048",
    "addr:street":"256Th St",
    "iso:country":"US",
    "sg:address":"44674 256th St",
    "sg:city":"Montrose",
    "sg:classifiers":[
        {
            "category":"Building & Trades",
            "subcategory":"Construction",
            "type":"Services"
        }
    ],
    "sg:phone":"+1 605 363 5056",
    "sg:postcode":"57048",
    "sg:province":"SD",
    "sg:tags":[
        "general",
        "contractor"
    ],
    "wof:name":"Hoiten Construction",
    "wof:placetype":"venue"
},
  "geometry": {"coordinates":[-97.273717,43.673649],"type":"Point"}
}