{
  "type": "Feature",
  "properties": {
    "addr:full":"1819 Olwien St Brookings SD 57006",
    "addr:housenumber":"1819",
    "addr:postcode":"57006",
    "addr:street":"Olwien St",
    "iso:country":"US",
    "sg:address":"1819 Olwien St",
    "sg:city":"Brookings",
    "sg:classifiers":[
        {
            "category":"Government",
            "subcategory":"Office",
            "type":"Public Place"
        }
    ],
    "sg:phone":"+1 605 688 4786",
    "sg:postcode":"57006",
    "sg:province":"SD",
    "sg:tags":[
        "wildlife",
        "conservation"
    ],
    "wof:name":"Game Fish and Parks SD Dept",
    "wof:placetype":"venue"
},
  "geometry": {"coordinates":[-96.774051,44.304762],"type":"Point"}
}