{
  "type": "Feature",
  "properties": {
    "iso:country":"US",
    "sg:address":"519 W 4th Ave",
    "sg:city":"Milbank",
    "sg:classifiers":[
        {
            "category":"Wholesale",
            "subcategory":"Farm Supplies",
            "type":"Manufacturing & Wholesale Goods"
        }
    ],
    "sg:phone":"+1 605 432 4531",
    "sg:postcode":"57252",
    "sg:province":"SD",
    "sg:tags":[
        "grain"
    ],
    "wof:name":"Western Consolidated Coop",
    "wof:placetype":"venue"
},
  "geometry": {"coordinates":[-96.647075,45.218843],"type":"Point"}
}