{
  "type": "Feature",
  "properties": {
    "addr:full":"3001 Broadway Ave Yankton SD 57078",
    "addr:housenumber":"3001",
    "addr:postcode":"57078",
    "addr:street":"Broadway Ave",
    "iso:country":"US",
    "sg:address":"3001 Broadway Ave",
    "sg:city":"Yankton",
    "sg:classifiers":[
        {
            "category":"Restaurant",
            "type":"Food & Drink"
        }
    ],
    "sg:menulink":"http://www.allmenus.com/sd/yankton/144765-subway/menu/",
    "sg:phone":"+1 605 665 2821",
    "sg:postcode":"57078",
    "sg:province":"SD",
    "sg:tags":[
        "american",
        "sandwich"
    ],
    "wof:name":"Subway",
    "wof:placetype":"venue"
},
  "geometry": {"coordinates":[-97.397668,42.907049],"type":"Point"}
}