{
  "type": "Feature",
  "properties": {
    "iso:country":"US",
    "sg:address":"835 N Indiana Ave",
    "sg:city":"Sioux Falls",
    "sg:classifiers":[
        {
            "category":"Building & Trades",
            "subcategory":"Construction",
            "type":"Services"
        }
    ],
    "sg:phone":"+1 605 731 1830",
    "sg:postcode":"57103",
    "sg:province":"SD",
    "sg:tags":[
        "masonry"
    ],
    "wof:name":"Gordon Contracting",
    "wof:placetype":"venue"
},
  "geometry": {"coordinates":[-96.71575900000001,43.557055],"type":"Point"}
}