{
  "type": "Feature",
  "properties": {
    "addr:full":"48304 205th St White SD 57276",
    "addr:housenumber":"48304",
    "addr:postcode":"57276",
    "addr:street":"205Th St",
    "iso:country":"US",
    "sg:address":"48304 205th St",
    "sg:city":"White",
    "sg:classifiers":[
        {
            "category":"Farming",
            "subcategory":"Livestock Farm",
            "type":"Manufacturing & Wholesale Goods"
        }
    ],
    "sg:phone":"+1 605 629 6381",
    "sg:postcode":"57276",
    "sg:province":"SD",
    "sg:tags":[
        "ranch"
    ],
    "wof:name":"L-Cedar Ranch",
    "wof:placetype":"venue"
},
  "geometry": {"coordinates":[-96.545309,44.412536],"type":"Point"}
}