{
  "type": "Feature",
  "properties": {
    "iso:country":"US",
    "sg:address":"30209 480th Ave",
    "sg:city":"Alcester",
    "sg:classifiers":[
        {
            "category":"Building & Trades",
            "subcategory":"Construction",
            "type":"Services"
        }
    ],
    "sg:phone":"+1 605 934 2776",
    "sg:postcode":"57001",
    "sg:province":"SD",
    "sg:tags":[
        "excavation",
        "contractor"
    ],
    "wof:name":"Pearson Dirt Construction",
    "wof:placetype":"venue"
},
  "geometry": {"coordinates":[-96.608397,43.010098],"type":"Point"}
}