{
  "type": "Feature",
  "properties": {
    "addr:full":"538 W Jackson Blvd Spearfish SD 57783",
    "addr:housenumber":"538",
    "addr:postcode":"57783",
    "addr:street":"W Jackson Blvd",
    "iso:country":"US",
    "sg:address":"538 W Jackson Blvd",
    "sg:city":"Spearfish",
    "sg:classifiers":[
        {
            "category":"Retail",
            "subcategory":"Auto Repair",
            "type":"Services"
        }
    ],
    "sg:phone":"+1 605 642 7142",
    "sg:postcode":"57783",
    "sg:province":"SD",
    "sg:tags":[
        "automotive"
    ],
    "wof:name":"Motor Service",
    "wof:placetype":"venue"
},
  "geometry": {"coordinates":[-103.866742,44.490669],"type":"Point"}
}