{
  "type": "Feature",
  "properties": {
    "addr:full":"308 N Main St Mitchell SD 57301",
    "addr:housenumber":"308",
    "addr:postcode":"57301",
    "addr:street":"N Main St",
    "iso:country":"US",
    "sg:address":"308 N Main St",
    "sg:city":"Mitchell",
    "sg:classifiers":[
        {
            "category":"Manufacturing",
            "subcategory":"Printing",
            "type":"Manufacturing & Wholesale Goods"
        }
    ],
    "sg:phone":"+1 605 996 0342",
    "sg:postcode":"57301",
    "sg:province":"SD",
    "sg:tags":[
        "print",
        "shop"
    ],
    "wof:name":"Harvey E Johnston",
    "wof:placetype":"venue"
},
  "geometry": {"coordinates":[-98.02549399999999,43.712417],"type":"Point"}
}