{
  "type": "Feature",
  "properties": {
    "iso:country":"US",
    "sg:address":"44270 251st St",
    "sg:city":"Salem",
    "sg:phone":"+1 605 425 2445",
    "sg:postcode":"57058",
    "sg:province":"SD",
    "sg:tags":[
        "farm",
        "corn",
        "soybean"
    ],
    "wof:name":"Scheier John",
    "wof:placetype":"venue"
},
  "geometry": {"coordinates":[-97.355463,43.745836],"type":"Point"}
}