{
  "type": "Feature",
  "properties": {
    "iso:country":"US",
    "sg:address":"2490 Rusty Spur Ct",
    "sg:city":"Rapid City",
    "sg:classifiers":[
        {
            "category":"Building & Trades",
            "subcategory":"Equipment Rental",
            "type":"Services"
        }
    ],
    "sg:phone":"+1 605 399 3285",
    "sg:postcode":"57703",
    "sg:province":"SD",
    "sg:tags":[
        "scaffolding"
    ],
    "wof:name":"Construction Systems Inc",
    "wof:placetype":"venue"
},
  "geometry": {"coordinates":[-103.175242,43.974329],"type":"Point"}
}