{
  "type": "Feature",
  "properties": {
    "iso:country":"US",
    "sg:address":"3800 9th Ave SE",
    "sg:city":"Watertown",
    "sg:classifiers":[
        {
            "category":"Restaurant",
            "type":"Food & Drink"
        }
    ],
    "sg:phone":"+1 605 882 4531",
    "sg:postcode":"57201",
    "sg:province":"SD",
    "sg:website":"www.subway.com",
    "wof:name":"Subway Sandwiches & Salads",
    "wof:placetype":"venue"
},
  "geometry": {"coordinates":[-97.05510099999999,44.889889],"type":"Point"}
}