{
  "type": "Feature",
  "properties": {
    "iso:country":"US",
    "sg:address":"3121 W Chicago St",
    "sg:city":"Rapid City",
    "sg:classifiers":[
        {
            "category":"Organizations",
            "subcategory":"Non-profit Organization",
            "type":"Services"
        }
    ],
    "sg:phone":"+1 605 348 7850",
    "sg:postcode":"57702",
    "sg:province":"SD",
    "wof:name":"Black Hills Home Bldrs Assn",
    "wof:placetype":"venue"
},
  "geometry": {"coordinates":[-103.27032,44.085483],"type":"Point"}
}