{
  "type": "Feature",
  "properties": {
    "iso:country":"US",
    "sg:address":"415 Main Ave",
    "sg:city":"Brookings",
    "sg:classifiers":[
        {
            "category":"Shopping",
            "subcategory":"Florist",
            "type":"Retail Goods"
        }
    ],
    "sg:phone":"+1 605 697 1734",
    "sg:postcode":"57006",
    "sg:province":"SD",
    "wof:name":"Bloomingvilla",
    "wof:placetype":"venue"
},
  "geometry": {"coordinates":[-96.798681,44.310116],"type":"Point"}
}