{
  "type": "Feature",
  "properties": {
    "addr:full":"3534 S Western Ave Sioux Falls SD 57105",
    "addr:housenumber":"3534",
    "addr:postcode":"57105",
    "addr:street":"S Western Ave",
    "iso:country":"US",
    "sg:address":"3534 S Western Ave",
    "sg:city":"Sioux Falls",
    "sg:classifiers":[
        {
            "category":"Shopping",
            "subcategory":"Crafts & Fabrics",
            "type":"Retail Goods"
        }
    ],
    "sg:phone":"+1 605 221 0450",
    "sg:postcode":"57105",
    "sg:province":"SD",
    "sg:tags":[
        "shop"
    ],
    "sg:website":"www.millendtextile.com",
    "wof:name":"Mill End Textiles",
    "wof:placetype":"venue"
},
  "geometry": {"coordinates":[-96.75108,43.511545],"type":"Point"}
}