{
  "type": "Feature",
  "properties": {
    "addr:full":"110 E 1st Ave Mitchell SD 57301",
    "addr:housenumber":"110",
    "addr:postcode":"57301",
    "addr:street":"E 1St Ave",
    "iso:country":"US",
    "sg:address":"110 E 1st Ave",
    "sg:city":"Mitchell",
    "sg:classifiers":[
        {
            "category":"Banks & Credit Unions",
            "subcategory":"Bank",
            "type":"Services"
        }
    ],
    "sg:phone":"+1 605 996 7209",
    "sg:postcode":"57301",
    "sg:province":"SD",
    "sg:tags":[
        "loan"
    ],
    "wof:name":"Money Station",
    "wof:placetype":"venue"
},
  "geometry": {"coordinates":[-98.024181,43.709565],"type":"Point"}
}