{
  "type": "Feature",
  "properties": {
    "iso:country":"US",
    "sg:address":"290 7th St SW",
    "sg:city":"Huron",
    "sg:classifiers":[
        {
            "category":"Social Services",
            "type":"Services"
        }
    ],
    "sg:phone":"+1 605 352 8291",
    "sg:postcode":"57350",
    "sg:province":"SD",
    "sg:tags":[
        "senior",
        "citizen"
    ],
    "wof:name":"Huron Area Senior Ctr",
    "wof:placetype":"venue"
},
  "geometry": {"coordinates":[-98.21861199999999,44.358398],"type":"Point"}
}