{
  "type": "Feature",
  "properties": {
    "iso:country":"US",
    "sg:address":"1226 Dakota Ave S",
    "sg:city":"Huron",
    "sg:classifiers":[
        {
            "category":"Real Estate",
            "subcategory":"Real Estate Agent",
            "type":"Services"
        }
    ],
    "sg:phone":"+1 605 352 4228",
    "sg:postcode":"57350",
    "sg:province":"SD",
    "sg:website":"www.haskellagency.com",
    "wof:name":"Haskell Agency",
    "wof:placetype":"venue"
},
  "geometry": {"coordinates":[-98.21406899999999,44.352222],"type":"Point"}
}