{
  "type": "Feature",
  "properties": {
    "iso:country":"US",
    "sg:address":"410 1st Ave E",
    "sg:city":"Clark",
    "sg:classifiers":[
        {
            "category":"Insurance",
            "subcategory":"Insurance Agent",
            "type":"Services"
        }
    ],
    "sg:phone":"+1 605 532 5202",
    "sg:postcode":"57225",
    "sg:province":"SD",
    "wof:name":"Farm Bureau Insurance",
    "wof:placetype":"venue"
},
  "geometry": {"coordinates":[-97.72955899999999,44.877542],"type":"Point"}
}