{
  "type": "Feature",
  "properties": {
    "addr:full":"43146 US Hwy 14 De Smet SD 57231",
    "addr:postcode":"43146;57231",
    "addr:street":"Us Hwy 14 De Smet",
    "iso:country":"US",
    "sg:address":"43146 US Hwy 14",
    "sg:city":"De Smet",
    "sg:classifiers":[
        {
            "category":"Farming",
            "subcategory":"Farm",
            "type":"Manufacturing & Wholesale Goods"
        }
    ],
    "sg:phone":"+1 605 854 3793",
    "sg:postcode":"57231",
    "sg:province":"SD",
    "sg:tags":[
        "crop",
        "general"
    ],
    "wof:name":"Tom Peckenpaugh",
    "wof:placetype":"venue"
},
  "geometry": {"coordinates":[-97.57866300000001,44.383221],"type":"Point"}
}