{
  "type": "Feature",
  "properties": {
    "iso:country":"US",
    "sg:address":"541 Mount Rushmore Rd",
    "sg:city":"Custer",
    "sg:classifiers":[
        {
            "category":"Food & Beverages",
            "subcategory":"Bakery",
            "type":"Retail Goods"
        }
    ],
    "sg:phone":"+1 605 673 5003",
    "sg:postcode":"57730",
    "sg:province":"SD",
    "sg:tags":[
        "baker"
    ],
    "wof:name":"Laube's Pastry Shoppe",
    "wof:placetype":"venue"
},
  "geometry": {"coordinates":[-103.59938,43.766565],"type":"Point"}
}