{
  "type": "Feature",
  "properties": {
    "addr:full":"1752 McDonald Dr Huron SD 57350",
    "addr:housenumber":"1752",
    "addr:postcode":"57350",
    "addr:street":"Mcdonald Dr",
    "iso:country":"US",
    "sg:address":"1752 McDonald Dr",
    "sg:city":"Huron",
    "sg:classifiers":[
        {
            "category":"Farming",
            "subcategory":"Farm",
            "type":"Manufacturing & Wholesale Goods"
        }
    ],
    "sg:phone":"+1 605 352 7728",
    "sg:postcode":"57350",
    "sg:province":"SD",
    "sg:tags":[
        "crop",
        "general"
    ],
    "wof:name":"Mike Brosnan",
    "wof:placetype":"venue"
},
  "geometry": {"coordinates":[-98.222112,44.346076],"type":"Point"}
}