{
  "type": "Feature",
  "properties": {
    "addr:full":"1324 Cedar St Brandon SD 57005",
    "addr:housenumber":"1324",
    "addr:postcode":"57005",
    "addr:street":"Cedar St",
    "iso:country":"US",
    "sg:address":"1324 Cedar St",
    "sg:city":"Brandon",
    "sg:classifiers":[
        {
            "category":"Shopping",
            "subcategory":"Florist",
            "type":"Retail Goods"
        }
    ],
    "sg:phone":"+1 605 582 3733",
    "sg:postcode":"57005",
    "sg:province":"SD",
    "wof:name":"Flower Mill",
    "wof:placetype":"venue"
},
  "geometry": {"coordinates":[-96.571955,43.59046],"type":"Point"}
}