{
  "type": "Feature",
  "properties": {
    "iso:country":"US",
    "sg:address":"27297 Hemlock Ave",
    "sg:city":"Tea",
    "sg:classifiers":[
        {
            "category":"Home & Garden",
            "subcategory":"Carpets & Floor Coverings",
            "type":"Retail Goods"
        }
    ],
    "sg:phone":"+1 605 368 2696",
    "sg:postcode":"57064",
    "sg:province":"SD",
    "wof:name":"Hartson Floor Covering",
    "wof:placetype":"venue"
},
  "geometry": {"coordinates":[-96.820044,43.432287],"type":"Point"}
}