{
  "type": "Feature",
  "properties": {
    "addr:full":"200 S Main St Lennox SD 57039",
    "addr:housenumber":"200",
    "addr:postcode":"57039",
    "addr:street":"S Main St",
    "iso:country":"US",
    "sg:address":"200 S Main St",
    "sg:city":"Lennox",
    "sg:classifiers":[
        {
            "category":"Government",
            "subcategory":"Post Office",
            "type":"Public Place"
        }
    ],
    "sg:phone":"+1 605 647 2265",
    "sg:postcode":"57039",
    "sg:province":"SD",
    "wof:name":"US Post Office",
    "wof:placetype":"venue"
},
  "geometry": {"coordinates":[-96.89173700000001,43.354289],"type":"Point"}
}