{
  "type": "Feature",
  "properties": {
    "addr:full":"1801 S Western Ave Sioux Falls SD 57105",
    "addr:housenumber":"1801",
    "addr:postcode":"57105",
    "addr:street":"S Western Ave",
    "iso:country":"US",
    "sg:address":"1801 S Western Ave",
    "sg:city":"Sioux Falls",
    "sg:classifiers":[
        {
            "category":"Autos & Motor Vehicles",
            "subcategory":"Fuel & Gas Station",
            "type":"Retail Goods"
        }
    ],
    "sg:phone":"+1 605 334 3661",
    "sg:postcode":"57105",
    "sg:province":"SD",
    "sg:tags":[
        "oil"
    ],
    "wof:name":"Phillips 66",
    "wof:placetype":"venue"
},
  "geometry": {"coordinates":[-96.751222,43.527629],"type":"Point"}
}