{
  "type": "Feature",
  "properties": {
    "iso:country":"US",
    "sg:address":"540 Mountain View Rd",
    "sg:city":"Rapid City",
    "sg:classifiers":[
        {
            "category":"Shopping",
            "subcategory":"Pharmacy",
            "type":"Retail Goods"
        }
    ],
    "sg:phone":"+1 605 342 0090",
    "sg:postcode":"57702",
    "sg:province":"SD",
    "wof:name":"Walgreens",
    "wof:placetype":"venue"
},
  "geometry": {"coordinates":[-103.251955,44.081656],"type":"Point"}
}