{
  "type": "Feature",
  "properties": {
    "iso:country":"US",
    "sg:address":"115 N Tyler Ave",
    "sg:city":"Pierre",
    "sg:classifiers":[
        {
            "category":"Retail",
            "subcategory":"Laundry & Dry Cleaning",
            "type":"Services"
        }
    ],
    "sg:phone":"+1 605 224 1212",
    "sg:postcode":"57501",
    "sg:province":"SD",
    "sg:tags":[
        "cleaners",
        "rug",
        "carpet"
    ],
    "wof:name":"Captain Clean",
    "wof:placetype":"venue"
},
  "geometry": {"coordinates":[-100.32803,44.365683],"type":"Point"}
}