{
  "type": "Feature",
  "properties": {
    "iso:country":"US",
    "sg:address":"600 31st St SE",
    "sg:city":"Watertown",
    "sg:classifiers":[
        {
            "category":"Building & Trades",
            "subcategory":"Construction",
            "type":"Services"
        }
    ],
    "sg:phone":"+1 605 886 2257",
    "sg:postcode":"57201",
    "sg:province":"SD",
    "sg:tags":[
        "product",
        "asphalt"
    ],
    "wof:name":"F J Mc Laughlin Co",
    "wof:placetype":"venue"
},
  "geometry": {"coordinates":[-97.065901,44.892192],"type":"Point"}
}