{
  "type": "Feature",
  "properties": {
    "addr:full":"1321 E Havens St Mitchell SD 57301",
    "addr:housenumber":"1321",
    "addr:postcode":"57301",
    "addr:street":"E Havens St",
    "iso:country":"US",
    "sg:address":"1321 E Havens St",
    "sg:city":"Mitchell",
    "sg:classifiers":[
        {
            "category":"Bus Charters",
            "type":"Transportation"
        }
    ],
    "sg:phone":"+1 605 996 2440",
    "sg:postcode":"57301",
    "sg:province":"SD",
    "sg:tags":[
        "rental"
    ],
    "wof:name":"Dietrick Bus Svc",
    "wof:placetype":"venue"
},
  "geometry": {"coordinates":[-98.00704399999999,43.702175],"type":"Point"}
}