{
  "type": "Feature",
  "properties": {
    "iso:country":"US",
    "sg:address":"37964 213th St",
    "sg:city":"Wessington",
    "sg:classifiers":[
        {
            "category":"Farming",
            "subcategory":"Livestock Farm",
            "type":"Manufacturing & Wholesale Goods"
        }
    ],
    "sg:phone":"+1 605 883 4590",
    "sg:postcode":"57381",
    "sg:province":"SD",
    "sg:tags":[
        "beef",
        "feedlot",
        "cattle"
    ],
    "wof:name":"Eggleston Charoleis & Angus",
    "wof:placetype":"venue"
},
  "geometry": {"coordinates":[-98.586272,44.298218],"type":"Point"}
}