{
  "type": "Feature",
  "properties": {
    "addr:full":"2809 S Minnesota Ave Sioux Falls SD 57105",
    "addr:housenumber":"2809",
    "addr:postcode":"57105",
    "addr:street":"S Minnesota Ave",
    "iso:country":"US",
    "sg:address":"2809 S Minnesota Ave",
    "sg:city":"Sioux Falls",
    "sg:classifiers":[
        {
            "category":"Retail",
            "subcategory":"Laundry & Dry Cleaning",
            "type":"Services"
        }
    ],
    "sg:phone":"+1 605 336 1905",
    "sg:postcode":"57105",
    "sg:province":"SD",
    "sg:tags":[
        "pressing"
    ],
    "wof:name":"Valet Cleaners",
    "wof:placetype":"venue"
},
  "geometry": {"coordinates":[-96.731328,43.519503],"type":"Point"}
}