{
  "type": "Feature",
  "properties": {
    "iso:country":"US",
    "sg:address":"608 Haley Dr",
    "sg:city":"Whitewood",
    "sg:classifiers":[
        {
            "category":"Manufacturing",
            "subcategory":"Buildings",
            "type":"Manufacturing & Wholesale Goods"
        }
    ],
    "sg:phone":"+1 605 269 2213",
    "sg:postcode":"57793",
    "sg:province":"SD",
    "sg:tags":[
        "home",
        "log",
        "cabin"
    ],
    "wof:name":"Hale's House Logs",
    "wof:placetype":"venue"
},
  "geometry": {"coordinates":[-103.63291599999999,44.459573],"type":"Point"}
}