{
  "type": "Feature",
  "properties": {
    "iso:country":"US",
    "sg:address":"105 N School Ave",
    "sg:city":"White",
    "sg:classifiers":[
        {
            "category":"Retail",
            "subcategory":"Auto Repair",
            "type":"Services"
        }
    ],
    "sg:phone":"+1 605 629 3111",
    "sg:postcode":"57276",
    "sg:province":"SD",
    "sg:tags":[
        "repairing",
        "automobile"
    ],
    "wof:name":"Thomsen Garage",
    "wof:placetype":"venue"
},
  "geometry": {"coordinates":[-96.64993200000001,44.435733],"type":"Point"}
}