{
  "type": "Feature",
  "properties": {
    "addr:full":"47193 255th St Renner SD 57055",
    "addr:housenumber":"47193",
    "addr:postcode":"57055",
    "addr:street":"255Th St",
    "iso:country":"US",
    "sg:address":"47193 255th St",
    "sg:city":"Renner",
    "sg:classifiers":[
        {
            "category":"Retail",
            "subcategory":"Auto Repair",
            "type":"Services"
        }
    ],
    "sg:phone":"+1 605 543 5413",
    "sg:postcode":"57055",
    "sg:province":"SD",
    "sg:tags":[
        "body"
    ],
    "wof:name":"Morefield Repair",
    "wof:placetype":"venue"
},
  "geometry": {"coordinates":[-96.772346,43.688725],"type":"Point"}
}