{
  "type": "Feature",
  "properties": {
    "iso:country":"US",
    "sg:address":"902 Roosevelt St",
    "sg:city":"Winner",
    "sg:classifiers":[
        {
            "category":"Real Estate",
            "subcategory":"Real Estate Operator",
            "type":"Services"
        }
    ],
    "sg:phone":"+1 605 842 3677",
    "sg:postcode":"57580",
    "sg:province":"SD",
    "sg:tags":[
        "property",
        "lessor"
    ],
    "wof:name":"Dorothy Vanneman",
    "wof:placetype":"venue"
},
  "geometry": {"coordinates":[-99.843998,43.369962],"type":"Point"}
}