{
  "type": "Feature",
  "properties": {
    "iso:country":"US",
    "sg:address":"1212 E 10th St",
    "sg:city":"Sioux Falls",
    "sg:classifiers":[
        {
            "category":"Banks & Credit Unions",
            "subcategory":"Bank",
            "type":"Services"
        }
    ],
    "sg:phone":"+1 605 332 7800",
    "sg:postcode":"57103",
    "sg:province":"SD",
    "sg:tags":[
        "loan"
    ],
    "wof:name":"North American Title Loans",
    "wof:placetype":"venue"
},
  "geometry": {"coordinates":[-96.710243,43.546754],"type":"Point"}
}