{
  "type": "Feature",
  "properties": {
    "addr:full":"3209 S Carolyn Ave Sioux Falls SD 57106",
    "addr:housenumber":"3209",
    "addr:postcode":"57106",
    "addr:street":"S Carolyn Ave",
    "iso:country":"US",
    "sg:address":"3209 S Carolyn Ave",
    "sg:city":"Sioux Falls",
    "sg:classifiers":[
        {
            "category":"Insurance",
            "subcategory":"Insurance Agent",
            "type":"Services"
        }
    ],
    "sg:phone":"+1 605 362 9991",
    "sg:postcode":"57106",
    "sg:province":"SD",
    "sg:tags":[
        "processing"
    ],
    "wof:name":"Farmers Insurance Group",
    "wof:placetype":"venue"
},
  "geometry": {"coordinates":[-96.778594,43.516101],"type":"Point"}
}