{
  "type": "Feature",
  "properties": {
    "addr:full":"1509 S Minnesota Ave Sioux Falls SD 57105",
    "addr:housenumber":"1509",
    "addr:postcode":"57105",
    "addr:street":"S Minnesota Ave",
    "iso:country":"US",
    "sg:address":"1509 S Minnesota Ave",
    "sg:city":"Sioux Falls",
    "sg:classifiers":[
        {
            "category":"Banks & Credit Unions",
            "subcategory":"Investment Brokerage",
            "type":"Services"
        }
    ],
    "sg:phone":"+1 605 335 1693",
    "sg:postcode":"57105",
    "sg:province":"SD",
    "sg:tags":[
        "consultant",
        "planning",
        "financial"
    ],
    "sg:website":"www.ameriprise.com",
    "wof:name":"Ameriprise Financial",
    "wof:placetype":"venue"
},
  "geometry": {"coordinates":[-96.73136700000001,43.531318],"type":"Point"}
}