{
  "type": "Feature",
  "properties": {
    "iso:country":"US",
    "sg:address":"106 S Veterans St",
    "sg:city":"Flandreau",
    "sg:classifiers":[
        {
            "category":"Organizations",
            "subcategory":"Religious Organization",
            "type":"Services"
        }
    ],
    "sg:phone":"+1 605 997 2139",
    "sg:postcode":"57028",
    "sg:province":"SD",
    "sg:tags":[
        "church"
    ],
    "wof:name":"Big Sioux Baptist Mission",
    "wof:placetype":"venue"
},
  "geometry": {"coordinates":[-96.60781799999999,44.048363],"type":"Point"}
}