{
  "type": "Feature",
  "properties": {
    "iso:country":"US",
    "sg:address":"747 Washington Ave N",
    "sg:city":"Madison",
    "sg:classifiers":[
        {
            "category":"Home & Garden",
            "subcategory":"Furniture",
            "type":"Retail Goods"
        }
    ],
    "sg:phone":"+1 605 256 4000",
    "sg:postcode":"57042",
    "sg:province":"SD",
    "sg:website":"www.montgomerysfurnitureoutlet.com",
    "wof:name":"Montgomery's Furniture",
    "wof:placetype":"venue"
},
  "geometry": {"coordinates":[-97.109882,44.0118],"type":"Point"}
}