{
  "type": "Feature",
  "properties": {
    "addr:full":"1716 S Minnesota Ave Sioux Falls SD 57105",
    "addr:housenumber":"1716",
    "addr:postcode":"57105",
    "addr:street":"S Minnesota Ave",
    "iso:country":"US",
    "sg:address":"1716 S Minnesota Ave",
    "sg:city":"Sioux Falls",
    "sg:classifiers":[
        {
            "category":"Restaurant",
            "type":"Food & Drink"
        }
    ],
    "sg:phone":"+1 605 339 3322",
    "sg:postcode":"57105",
    "sg:province":"SD",
    "sg:website":"www.kaladisbistro.com",
    "wof:name":"Kaladi's",
    "wof:placetype":"venue"
},
  "geometry": {"coordinates":[-96.73121500000001,43.52956],"type":"Point"}
}