{
  "type": "Feature",
  "properties": {
    "iso:country":"US",
    "sg:address":"926 Main St",
    "sg:city":"Rapid City",
    "sg:classifiers":[
        {
            "category":"Building & Trades",
            "subcategory":"Cleaning & Sanitation",
            "type":"Services"
        }
    ],
    "sg:phone":"+1 605 348 2854",
    "sg:postcode":"57701",
    "sg:province":"SD",
    "sg:tags":[
        "janitor"
    ],
    "wof:name":"Captain Clean Janitorial Svc",
    "wof:placetype":"venue"
},
  "geometry": {"coordinates":[-103.234058,44.08224],"type":"Point"}
}