{
  "type": "Feature",
  "properties": {
    "iso:country":"US",
    "sg:address":"47054 104th St",
    "sg:city":"Sioux Falls",
    "sg:classifiers":[
        {
            "category":"Shopping",
            "subcategory":"Bicycles & Sporting Goods",
            "type":"Retail Goods"
        }
    ],
    "sg:phone":"+1 605 368 2800",
    "sg:postcode":"57108",
    "sg:province":"SD",
    "sg:tags":[
        "equipment",
        "playground"
    ],
    "wof:name":"Backyard Adventures",
    "wof:placetype":"venue"
},
  "geometry": {"coordinates":[-96.79386100000001,43.458317],"type":"Point"}
}