{
  "type": "Feature",
  "properties": {
    "addr:full":"21315 396th Ave Huron SD 57350",
    "addr:housenumber":"21315",
    "addr:postcode":"57350",
    "addr:street":"396Th Ave",
    "iso:country":"US",
    "sg:address":"21315 396th Ave",
    "sg:city":"Huron",
    "sg:classifiers":[
        {
            "category":"Farming",
            "subcategory":"Livestock Farm",
            "type":"Manufacturing & Wholesale Goods"
        }
    ],
    "sg:phone":"+1 605 352 2545",
    "sg:postcode":"57350",
    "sg:province":"SD",
    "sg:tags":[
        "ranch"
    ],
    "wof:name":"Ringneck Ranch",
    "wof:placetype":"venue"
},
  "geometry": {"coordinates":[-98.29546000000001,44.296182],"type":"Point"}
}