{
  "type": "Feature",
  "properties": {
    "iso:country":"US",
    "sg:address":"14821 Alkali Rd",
    "sg:city":"Sturgis",
    "sg:classifiers":[
        {
            "category":"Farming",
            "subcategory":"Livestock Farm",
            "type":"Manufacturing & Wholesale Goods"
        }
    ],
    "sg:phone":"+1 605 347 2207",
    "sg:postcode":"57785",
    "sg:province":"SD",
    "sg:tags":[
        "wheat",
        "beef",
        "feedlot",
        "cattle"
    ],
    "wof:name":"Leo Grubl",
    "wof:placetype":"venue"
},
  "geometry": {"coordinates":[-103.387433,44.422774],"type":"Point"}
}