{
  "type": "Feature",
  "properties": {
    "iso:country":"US",
    "sg:address":"111 Poplar Ave",
    "sg:city":"Rapid City",
    "sg:classifiers":[
        {
            "category":"Freight",
            "type":"Transportation"
        }
    ],
    "sg:phone":"+1 605 716 5966",
    "sg:postcode":"57701",
    "sg:province":"SD",
    "wof:name":"Lynn's Inc Transportation",
    "wof:placetype":"venue"
},
  "geometry": {"coordinates":[-103.195553,44.081542],"type":"Point"}
}