{
  "type": "Feature",
  "properties": {
    "iso:country":"US",
    "sg:address":"908 E 62nd St",
    "sg:city":"Sioux Falls",
    "sg:classifiers":[
        {
            "category":"Insurance",
            "subcategory":"Insurance Agent",
            "type":"Services"
        }
    ],
    "sg:phone":"+1 605 274 6370",
    "sg:postcode":"57108",
    "sg:province":"SD",
    "wof:name":"Horace Mann",
    "wof:placetype":"venue"
},
  "geometry": {"coordinates":[-96.712081,43.495706],"type":"Point"}
}