{
  "type": "Feature",
  "properties": {
    "addr:full":"2720 W 12th St Sioux Falls SD 57104",
    "addr:housenumber":"2720",
    "addr:postcode":"57104",
    "addr:street":"W 12Th St",
    "iso:country":"US",
    "sg:address":"2720 W 12th St",
    "sg:city":"Sioux Falls",
    "sg:classifiers":[
        {
            "category":"Restaurant",
            "type":"Food & Drink"
        }
    ],
    "sg:menulink":"http://www.allmenus.com/sd/sioux-falls/144763-subway/menu/",
    "sg:phone":"+1 605 335 0940",
    "sg:postcode":"57104",
    "sg:province":"SD",
    "sg:tags":[
        "american",
        "sandwich"
    ],
    "wof:name":"Subway",
    "wof:placetype":"venue"
},
  "geometry": {"coordinates":[-96.761611,43.543911],"type":"Point"}
}