{
  "type": "Feature",
  "properties": {
    "addr:full":"3801 Deadwood Ave N Rapid City SD 57702",
    "addr:housenumber":"3801",
    "addr:postcode":"57702",
    "addr:street":"Deadwood Ave N",
    "iso:country":"US",
    "sg:address":"3801 Deadwood Ave N",
    "sg:city":"Rapid City",
    "sg:classifiers":[
        {
            "category":"Wholesale",
            "subcategory":"Machinery & Supplies",
            "type":"Manufacturing & Wholesale Goods"
        }
    ],
    "sg:phone":"+1 605 348 7438",
    "sg:postcode":"57702",
    "sg:province":"SD",
    "sg:tags":[
        "contractor"
    ],
    "sg:website":"www.dieselmachinery.com",
    "wof:name":"DMI Diesel Machinery Inc",
    "wof:placetype":"venue"
},
  "geometry": {"coordinates":[-103.27206200000001,44.135948],"type":"Point"}
}