{
  "type": "Feature",
  "properties": {
    "addr:full":"5312 Sheridan Lake Rd Rapid City SD 57702",
    "addr:housenumber":"5312",
    "addr:postcode":"57702",
    "addr:street":"Sheridan Lake Rd",
    "iso:country":"US",
    "sg:address":"5312 Sheridan Lake Rd",
    "sg:city":"Rapid City",
    "sg:classifiers":[
        {
            "category":"Restaurant",
            "type":"Food & Drink"
        }
    ],
    "sg:phone":"+1 605 721 6450",
    "sg:postcode":"57702",
    "sg:province":"SD",
    "wof:name":"My Girlfriend's Kitchen",
    "wof:placetype":"venue"
},
  "geometry": {"coordinates":[-103.272125,44.034144],"type":"Point"}
}