{
  "type": "Feature",
  "properties": {
    "iso:country":"US",
    "sg:address":"509 Pine St",
    "sg:city":"Yankton",
    "sg:classifiers":[
        {
            "category":"Recreation",
            "type":"Entertainment"
        }
    ],
    "sg:phone":"+1 605 665 7470",
    "sg:postcode":"57078",
    "sg:province":"SD",
    "sg:tags":[
        "historical"
    ],
    "wof:name":"Cramer Kenyon Home",
    "wof:placetype":"venue"
},
  "geometry": {"coordinates":[-97.389051,42.873606],"type":"Point"}
}