{
  "type": "Feature",
  "properties": {
    "addr:full":"2300 W 46th St Sioux Falls SD 57105",
    "addr:housenumber":"2300",
    "addr:postcode":"57105",
    "addr:street":"W 46Th St",
    "iso:country":"US",
    "sg:address":"2300 W 46th St",
    "sg:city":"Sioux Falls",
    "sg:classifiers":[
        {
            "category":"Social Services",
            "type":"Services"
        }
    ],
    "sg:phone":"+1 605 333 3317",
    "sg:postcode":"57105",
    "sg:province":"SD",
    "sg:tags":[
        "organization",
        "welfare"
    ],
    "wof:name":"Workers On Wheels-Senior Chore",
    "wof:placetype":"venue"
},
  "geometry": {"coordinates":[-96.75241699999999,43.510642],"type":"Point"}
}