{
  "type": "Feature",
  "properties": {
    "iso:country":"US",
    "sg:address":"402 1st St S",
    "sg:city":"Brandt",
    "sg:classifiers":[
        {
            "category":"Insurance",
            "subcategory":"Insurance Agent",
            "type":"Services"
        }
    ],
    "sg:phone":"+1 605 876 2941",
    "sg:postcode":"57219",
    "sg:province":"SD",
    "wof:name":"Dakota Farm Mutual Insur Co",
    "wof:placetype":"venue"
},
  "geometry": {"coordinates":[-97.75302,45.34369],"type":"Point"}
}