{
  "type": "Feature",
  "properties": {
    "iso:country":"US",
    "sg:address":"22646 434th Ave",
    "sg:city":"Howard",
    "sg:classifiers":[
        {
            "category":"Farming",
            "subcategory":"Farm",
            "type":"Manufacturing & Wholesale Goods"
        }
    ],
    "sg:phone":"+1 605 772 5349",
    "sg:postcode":"57349",
    "sg:province":"SD",
    "sg:tags":[
        "crop",
        "general"
    ],
    "wof:name":"Wunder John",
    "wof:placetype":"venue"
},
  "geometry": {"coordinates":[-97.530601,44.102848],"type":"Point"}
}