{
  "type": "Feature",
  "properties": {
    "addr:full":"551 Main St Hoven SD 57450",
    "addr:housenumber":"551",
    "addr:postcode":"57450",
    "addr:street":"Main St",
    "iso:country":"US",
    "sg:address":"551 Main St",
    "sg:city":"Hoven",
    "sg:classifiers":[
        {
            "category":"Education",
            "subcategory":"School",
            "type":"Public Place"
        }
    ],
    "sg:phone":"+1 605 948 2509",
    "sg:postcode":"57450",
    "sg:province":"SD",
    "wof:name":"Hoven Elementary School",
    "wof:placetype":"venue"
},
  "geometry": {"coordinates":[-99.77724000000001,45.239428],"type":"Point"}
}