{
  "type": "Feature",
  "properties": {
    "iso:country":"US",
    "sg:address":"824 32nd Ave",
    "sg:city":"Brookings",
    "sg:classifiers":[
        {
            "category":"Real Estate",
            "subcategory":"Real Estate Operator",
            "type":"Services"
        }
    ],
    "sg:phone":"+1 605 692 7539",
    "sg:postcode":"57006",
    "sg:province":"SD",
    "wof:name":"Brookings Area Multiplex",
    "wof:placetype":"venue"
},
  "geometry": {"coordinates":[-96.751628,44.314605],"type":"Point"}
}