{
  "type": "Feature",
  "properties": {
    "iso:country":"US",
    "sg:address":"610 12th St S",
    "sg:city":"Brookings",
    "sg:classifiers":[
        {
            "category":"Sports & Exercise",
            "subcategory":"Gym",
            "type":"Entertainment"
        }
    ],
    "sg:phone":"+1 605 692 2469",
    "sg:postcode":"57006",
    "sg:province":"SD",
    "sg:tags":[
        "club",
        "health",
        "studio",
        "gymnasium"
    ],
    "wof:name":"Curves",
    "wof:placetype":"venue"
},
  "geometry": {"coordinates":[-96.795683,44.292365],"type":"Point"}
}