{
  "type": "Feature",
  "properties": {
    "addr:full":"310 E Fairmont Blvd Rapid City SD 57701",
    "addr:housenumber":"310",
    "addr:postcode":"57701",
    "addr:street":"E Fairmont Blvd",
    "iso:country":"US",
    "sg:address":"310 E Fairmont Blvd",
    "sg:city":"Rapid City",
    "sg:classifiers":[
        {
            "category":"Food & Beverages",
            "subcategory":"Groceries & Convenience Stores",
            "type":"Retail Goods"
        }
    ],
    "sg:phone":"+1 605 343 0152",
    "sg:postcode":"57701",
    "sg:province":"SD",
    "sg:tags":[
        "station",
        "gasoline"
    ],
    "wof:name":"Circle S Plaza",
    "wof:placetype":"venue"
},
  "geometry": {"coordinates":[-103.21172,44.055098],"type":"Point"}
}