{
  "type": "Feature",
  "properties": {
    "addr:full":"1925 2nd Ave SE Watertown SD 57201",
    "addr:housenumber":"1925",
    "addr:postcode":"57201",
    "addr:street":"2Nd Ave Se",
    "iso:country":"US",
    "sg:address":"1925 2nd Ave SE",
    "sg:city":"Watertown",
    "sg:classifiers":[
        {
            "category":"Organizations",
            "subcategory":"Professional Association",
            "type":"Services"
        }
    ],
    "sg:phone":"+1 605 882 5706",
    "sg:postcode":"57201",
    "sg:province":"SD",
    "wof:name":"Skyview 3 Condominium Assn",
    "wof:placetype":"venue"
},
  "geometry": {"coordinates":[-97.08386,44.892766],"type":"Point"}
}