{
  "type": "Feature",
  "properties": {
    "iso:country":"US",
    "sg:address":"333 S Phillips Ave",
    "sg:city":"Sioux Falls",
    "sg:classifiers":[
        {
            "category":"Home & Garden",
            "subcategory":"Household Appliances",
            "type":"Retail Goods"
        }
    ],
    "sg:phone":"+1 605 332 3821",
    "sg:postcode":"57104",
    "sg:province":"SD",
    "sg:tags":[
        "repair"
    ],
    "sg:website":"www.fondersewing.com",
    "wof:name":"Fonder Sewing Machine Co",
    "wof:placetype":"venue"
},
  "geometry": {"coordinates":[-96.726882,43.543864],"type":"Point"}
}