{
  "type": "Feature",
  "properties": {
    "iso:country":"US",
    "sg:address":"507 S Main Ave",
    "sg:city":"Sioux Falls",
    "sg:classifiers":[
        {
            "category":"Retail",
            "subcategory":"Funeral Services",
            "type":"Services"
        }
    ],
    "sg:phone":"+1 605 336 2640",
    "sg:postcode":"57104",
    "sg:province":"SD",
    "wof:name":"Miller Funeral Home",
    "wof:placetype":"venue"
},
  "geometry": {"coordinates":[-96.728313,43.541504],"type":"Point"}
}