{
  "type": "Feature",
  "properties": {
    "iso:country":"US",
    "sg:address":"302 S 2nd St",
    "sg:city":"Aberdeen",
    "sg:classifiers":[
        {
            "category":"Building & Trades",
            "subcategory":"Construction",
            "type":"Services"
        }
    ],
    "sg:phone":"+1 605 225 4242",
    "sg:postcode":"57401",
    "sg:province":"SD",
    "sg:tags":[
        "tile",
        "dealer"
    ],
    "wof:name":"Finishing Touch Design Studio",
    "wof:placetype":"venue"
},
  "geometry": {"coordinates":[-98.49095,45.462111],"type":"Point"}
}