{
  "type": "Feature",
  "properties": {
    "iso:country":"US",
    "sg:address":"136 S Main St",
    "sg:city":"Chamberlain",
    "sg:classifiers":[
        {
            "category":"Sports & Exercise",
            "subcategory":"Gym",
            "type":"Entertainment"
        }
    ],
    "sg:phone":"+1 605 234 3000",
    "sg:postcode":"57325",
    "sg:province":"SD",
    "sg:tags":[
        "club",
        "health",
        "studio",
        "gymnasium"
    ],
    "wof:name":"Curves For Women",
    "wof:placetype":"venue"
},
  "geometry": {"coordinates":[-99.330683,43.810253],"type":"Point"}
}