{
  "type": "Feature",
  "properties": {
    "iso:country":"US",
    "sg:address":"47550 233A St",
    "sg:city":"Egan",
    "sg:classifiers":[
        {
            "category":"Building & Trades",
            "subcategory":"Construction",
            "type":"Services"
        },
        {
            "category":"Military Area",
            "subcategory":"Armory",
            "type":"Public Place"
        }
    ],
    "sg:phone":"+1 605 997 3642",
    "sg:postcode":"57024",
    "sg:province":"SD",
    "sg:tags":[
        "repair",
        "fence-sales",
        "fence",
        "contractor"
    ],
    "wof:name":"Eastern Dakota Specialties",
    "wof:placetype":"venue"
},
  "geometry": {"coordinates":[-96.667343,44.00044],"type":"Point"}
}