{
  "type": "Feature",
  "properties": {
    "iso:country":"US",
    "sg:address":"105 S 5th St",
    "sg:city":"Menno",
    "sg:classifiers":[
        {
            "category":"Banks & Credit Unions",
            "subcategory":"Bank",
            "type":"Services"
        }
    ],
    "sg:phone":"+1 605 387 5111",
    "sg:postcode":"57045",
    "sg:province":"SD",
    "wof:name":"Menno State Bank",
    "wof:placetype":"venue"
},
  "geometry": {"coordinates":[-97.578124,43.240849],"type":"Point"}
}