{
  "type": "Feature",
  "properties": {
    "iso:country":"US",
    "sg:address":"758 W Park St",
    "sg:city":"Winner",
    "sg:classifiers":[
        {
            "category":"Recreation",
            "type":"Entertainment"
        }
    ],
    "sg:phone":"+1 605 842 0369",
    "sg:postcode":"57580",
    "sg:province":"SD",
    "sg:tags":[
        "club",
        "membership"
    ],
    "wof:name":"Rosebud Arrow Rod & Gun Inc",
    "wof:placetype":"venue"
},
  "geometry": {"coordinates":[-99.86826,43.371241],"type":"Point"}
}