{
  "type": "Feature",
  "properties": {
    "iso:country":"US",
    "sg:address":"3405 Hallmark Ct",
    "sg:city":"Rapid City",
    "sg:classifiers":[
        {
            "category":"Wholesale",
            "subcategory":"Durable Goods & Equipment",
            "type":"Manufacturing & Wholesale Goods"
        }
    ],
    "sg:phone":"+1 605 348 2830",
    "sg:postcode":"57702",
    "sg:province":"SD",
    "sg:tags":[
        "representative",
        "manufacturer"
    ],
    "wof:name":"Benchcraft",
    "wof:placetype":"venue"
},
  "geometry": {"coordinates":[-103.278152,44.052457],"type":"Point"}
}