{
  "type": "Feature",
  "properties": {
    "addr:full":"2921 Industrial Ave Aberdeen SD 57401",
    "addr:housenumber":"2921",
    "addr:postcode":"57401",
    "addr:street":"Industrial Ave",
    "iso:country":"US",
    "sg:address":"2921 Industrial Ave",
    "sg:city":"Aberdeen",
    "sg:classifiers":[
        {
            "category":"Freight",
            "type":"Transportation"
        }
    ],
    "sg:phone":"+1 605 225 8110",
    "sg:postcode":"57401",
    "sg:province":"SD",
    "sg:tags":[
        "terminal",
        "truck",
        "facility"
    ],
    "wof:name":"Lewis Transportation",
    "wof:placetype":"venue"
},
  "geometry": {"coordinates":[-98.44338399999999,45.469337],"type":"Point"}
}