{
  "type": "Feature",
  "properties": {
    "iso:country":"US",
    "sg:address":"204 N Sycamore Ave",
    "sg:city":"Sioux Falls",
    "sg:classifiers":[
        {
            "category":"Retail",
            "subcategory":"Repair Shop",
            "type":"Services"
        }
    ],
    "sg:phone":"+1 605 334 5491",
    "sg:postcode":"57110",
    "sg:province":"SD",
    "sg:tags":[
        "ironwork"
    ],
    "wof:name":"Weld-It Shop",
    "wof:placetype":"venue"
},
  "geometry": {"coordinates":[-96.67144999999999,43.549232],"type":"Point"}
}