{
  "type": "Feature",
  "properties": {
    "iso:country":"US",
    "sg:address":"40974 298th St",
    "sg:city":"Avon",
    "sg:phone":"+1 605 286 3549",
    "sg:postcode":"57315",
    "sg:province":"SD",
    "sg:tags":[
        "farm",
        "corn"
    ],
    "wof:name":"Oscar Becvar",
    "wof:placetype":"venue"
},
  "geometry": {"coordinates":[-98.009416,43.068353],"type":"Point"}
}