{
  "type": "Feature",
  "properties": {
    "iso:country":"US",
    "sg:address":"40879 305th St",
    "sg:city":"Avon",
    "sg:classifiers":[
        {
            "category":"Farming",
            "subcategory":"Dairy Farm",
            "type":"Manufacturing & Wholesale Goods"
        }
    ],
    "sg:phone":"+1 605 286 3404",
    "sg:postcode":"57315",
    "sg:province":"SD",
    "sg:tags":[
        "field",
        "corn",
        "soybean",
        "crop"
    ],
    "wof:name":"D Namminga",
    "wof:placetype":"venue"
},
  "geometry": {"coordinates":[-98.01523,42.966643],"type":"Point"}
}