{
  "type": "Feature",
  "properties": {
    "iso:country":"US",
    "sg:address":"2310 E 10th St",
    "sg:city":"Sioux Falls",
    "sg:classifiers":[
        {
            "category":"Food & Beverages",
            "subcategory":"Bakery",
            "type":"Retail Goods"
        }
    ],
    "sg:phone":"+1 605 336 3614",
    "sg:postcode":"57103",
    "sg:province":"SD",
    "wof:name":"Brendas Pastry Shop",
    "wof:placetype":"venue"
},
  "geometry": {"coordinates":[-96.696521,43.546752],"type":"Point"}
}