{
  "type": "Feature",
  "properties": {
    "iso:country":"US",
    "sg:address":"102 S Main St",
    "sg:city":"Chamberlain",
    "sg:classifiers":[
        {
            "category":"Personal",
            "subcategory":"Beauty Salon",
            "type":"Services"
        }
    ],
    "sg:phone":"+1 605 734 6884",
    "sg:postcode":"57325",
    "sg:province":"SD",
    "sg:tags":[
        "shop"
    ],
    "wof:name":"Hair Expressions Salon",
    "wof:placetype":"venue"
},
  "geometry": {"coordinates":[-99.330348,43.810941],"type":"Point"}
}