{
  "type": "Feature",
  "properties": {
    "iso:country":"US",
    "sg:address":"23045 Mystic Rd",
    "sg:city":"Hill City",
    "sg:classifiers":[
        {
            "category":"Organizations",
            "subcategory":"Membership Organization",
            "type":"Services"
        }
    ],
    "sg:phone":"+1 605 574 4268",
    "sg:postcode":"57745",
    "sg:province":"SD",
    "sg:tags":[
        "building",
        "maintenance"
    ],
    "wof:name":"Mystic Preservation Alliance",
    "wof:placetype":"venue"
},
  "geometry": {"coordinates":[-103.656925,44.062229],"type":"Point"}
}