{
  "type": "Feature",
  "properties": {
    "iso:country":"US",
    "sg:address":"86 Centennial Dr",
    "sg:city":"Custer",
    "sg:classifiers":[
        {
            "category":"Restaurant",
            "type":"Food & Drink"
        }
    ],
    "sg:phone":"+1 605 673 3999",
    "sg:postcode":"57730",
    "sg:province":"SD",
    "sg:tags":[
        "shop",
        "coffee"
    ],
    "wof:name":"Espresso & More",
    "wof:placetype":"venue"
},
  "geometry": {"coordinates":[-103.609045,43.762771],"type":"Point"}
}