{
  "type": "Feature",
  "properties": {
    "addr:full":"1719 W Main St Rapid City SD 57702",
    "addr:housenumber":"1719",
    "addr:postcode":"57702",
    "addr:street":"W Main St",
    "iso:country":"US",
    "sg:address":"1719 W Main St",
    "sg:city":"Rapid City",
    "sg:classifiers":[
        {
            "category":"Banks & Credit Unions",
            "subcategory":"Investment Brokerage",
            "type":"Services"
        }
    ],
    "sg:phone":"+1 605 342 6636",
    "sg:postcode":"57702",
    "sg:province":"SD",
    "sg:tags":[
        "advisory",
        "consulting",
        "management",
        "financial"
    ],
    "wof:name":"Rushmore Financial Management",
    "wof:placetype":"venue"
},
  "geometry": {"coordinates":[-103.246167,44.081746],"type":"Point"}
}