{
  "type": "Feature",
  "properties": {
    "iso:country":"US",
    "sg:address":"320 Washington Ave N",
    "sg:city":"Madison",
    "sg:classifiers":[
        {
            "category":"Shopping",
            "subcategory":"Florist",
            "type":"Retail Goods"
        }
    ],
    "sg:phone":"+1 605 256 4534",
    "sg:postcode":"57042",
    "sg:province":"SD",
    "wof:name":"Sample Our Flowers",
    "wof:placetype":"venue"
},
  "geometry": {"coordinates":[-97.109652,44.007702],"type":"Point"}
}