{
  "type": "Feature",
  "properties": {
    "addr:full":"3315 W Rapid St Rapid City SD 57702",
    "addr:housenumber":"3315",
    "addr:postcode":"57702",
    "addr:street":"W Rapid St",
    "iso:country":"US",
    "sg:address":"3315 W Rapid St",
    "sg:city":"Rapid City",
    "sg:classifiers":[
        {
            "category":"Social Services",
            "type":"Services"
        }
    ],
    "sg:phone":"+1 605 341 1363",
    "sg:postcode":"57702",
    "sg:province":"SD",
    "sg:tags":[
        "mission"
    ],
    "wof:name":"LDS Missionaries",
    "wof:placetype":"venue"
},
  "geometry": {"coordinates":[-103.272886,44.083028],"type":"Point"}
}