{
  "type": "Feature",
  "properties": {
    "addr:full":"8534 Dunsmore Rd Rapid City SD 57702",
    "addr:housenumber":"8534",
    "addr:postcode":"57702",
    "addr:street":"Dunsmore Rd",
    "iso:country":"US",
    "sg:address":"8534 Dunsmore Rd",
    "sg:city":"Rapid City",
    "sg:classifiers":[
        {
            "category":"Farming",
            "subcategory":"Nursery",
            "type":"Manufacturing & Wholesale Goods"
        }
    ],
    "sg:phone":"+1 605 342 6220",
    "sg:postcode":"57702",
    "sg:province":"SD",
    "sg:tags":[
        "turf"
    ],
    "wof:name":"Black Hills Hydro-Turf/Envrmnt",
    "wof:placetype":"venue"
},
  "geometry": {"coordinates":[-103.297406,44.002206],"type":"Point"}
}