{
  "type": "Feature",
  "properties": {
    "iso:country":"US",
    "sg:address":"2700 W 7th St",
    "sg:city":"Sioux Falls",
    "sg:classifiers":[
        {
            "category":"Shopping",
            "subcategory":"Shoes",
            "type":"Retail Goods"
        }
    ],
    "sg:phone":"+1 605 338 0180",
    "sg:postcode":"57104",
    "sg:province":"SD",
    "wof:name":"Dakota Z Coil",
    "wof:placetype":"venue"
},
  "geometry": {"coordinates":[-96.763632,43.550643],"type":"Point"}
}