{
  "type": "Feature",
  "properties": {
    "iso:country":"US",
    "sg:address":"31398 457th Ave",
    "sg:city":"Meckling",
    "sg:classifiers":[
        {
            "category":"Freight",
            "type":"Transportation"
        }
    ],
    "sg:phone":"+1 605 624 8248",
    "sg:postcode":"57069",
    "sg:province":"SD",
    "sg:tags":[
        "operator",
        "local",
        "trucking"
    ],
    "wof:name":"Myron Trucking",
    "wof:placetype":"venue"
},
  "geometry": {"coordinates":[-97.069042,42.842409],"type":"Point"}
}