{
  "type": "Feature",
  "properties": {
    "addr:full":"1400 E 39th St N Sioux Falls SD 57104",
    "addr:housenumber":"1400",
    "addr:postcode":"57104",
    "addr:street":"E 39Th St N",
    "iso:country":"US",
    "sg:address":"1400 E 39th St N",
    "sg:city":"Sioux Falls",
    "sg:classifiers":[
        {
            "category":"Wholesale",
            "subcategory":"Construction Materials",
            "type":"Manufacturing & Wholesale Goods"
        },
        {
            "category":"Home & Garden",
            "subcategory":"Building Materials",
            "type":"Retail Goods"
        }
    ],
    "sg:phone":"+1 605 357 9301",
    "sg:postcode":"57104",
    "sg:province":"SD",
    "sg:tags":[
        "insulation",
        "siding",
        "drywall",
        "contractor"
    ],
    "wof:name":"Dakota Wall Systems Inc",
    "wof:placetype":"venue"
},
  "geometry": {"coordinates":[-96.709819,43.583832],"type":"Point"}
}