{
  "type": "Feature",
  "properties": {
    "iso:country":"US",
    "sg:address":"400 W 10th St",
    "sg:city":"Sioux Falls",
    "sg:classifiers":[
        {
            "category":"Food & Beverages",
            "subcategory":"Groceries & Convenience Stores",
            "type":"Retail Goods"
        }
    ],
    "sg:phone":"+1 605 331 4711",
    "sg:postcode":"57104",
    "sg:province":"SD",
    "wof:name":"Munchies",
    "wof:placetype":"venue"
},
  "geometry": {"coordinates":[-96.732757,43.545997],"type":"Point"}
}