{
  "type": "Feature",
  "properties": {
    "iso:country":"US",
    "sg:address":"4500 S Technology Dr",
    "sg:city":"Sioux Falls",
    "sg:classifiers":[
        {
            "category":"Professional",
            "subcategory":"Accounting & Tax Preparation",
            "type":"Services"
        }
    ],
    "sg:phone":"+1 605 361 1200",
    "sg:postcode":"57106",
    "sg:province":"SD",
    "sg:tags":[
        "accountant"
    ],
    "sg:website":"www.siouxfallscpa.com",
    "wof:name":"Woltman Van Kerkerix & Stotz",
    "wof:placetype":"venue"
},
  "geometry": {"coordinates":[-96.775175,43.506245],"type":"Point"}
}