{
  "type": "Feature",
  "properties": {
    "iso:country":"US",
    "sg:address":"46893 265th St",
    "sg:city":"Sioux Falls",
    "sg:classifiers":[
        {
            "category":"Wholesale",
            "subcategory":"Farm Supplies",
            "type":"Manufacturing & Wholesale Goods"
        }
    ],
    "sg:phone":"+1 605 336 9300",
    "sg:postcode":"57106",
    "sg:province":"SD",
    "sg:tags":[
        "commission",
        "livestock"
    ],
    "wof:name":"Kramer Livestock Auction Co",
    "wof:placetype":"venue"
},
  "geometry": {"coordinates":[-96.83266399999999,43.543729],"type":"Point"}
}