{
  "type": "Feature",
  "properties": {
    "iso:country":"US",
    "sg:address":"1604 S Williams Ave",
    "sg:city":"Sioux Falls",
    "sg:classifiers":[
        {
            "category":"Professional",
            "subcategory":"Management & Consulting",
            "type":"Services"
        }
    ],
    "sg:phone":"+1 605 336 7421",
    "sg:postcode":"57105",
    "sg:province":"SD",
    "wof:name":"Great Plains Med Consulting",
    "wof:placetype":"venue"
},
  "geometry": {"coordinates":[-96.760023,43.529441],"type":"Point"}
}