{
  "type": "Feature",
  "properties": {
    "iso:country":"US",
    "sg:address":"2233 6th St",
    "sg:city":"Brookings",
    "sg:classifiers":[
        {
            "category":"Utilities",
            "subcategory":"Mobile Phone",
            "type":"Services"
        }
    ],
    "sg:phone":"+1 605 692 9344",
    "sg:postcode":"57006",
    "sg:province":"SD",
    "sg:tags":[
        "telephone",
        "cellular"
    ],
    "wof:name":"Trio Wireless",
    "wof:placetype":"venue"
},
  "geometry": {"coordinates":[-96.76292,44.311311],"type":"Point"}
}