{
  "type": "Feature",
  "properties": {
    "iso:country":"US",
    "sg:address":"2901 Broadway St",
    "sg:city":"Yankton",
    "sg:classifiers":[
        {
            "category":"Retail",
            "subcategory":"Auto Repair",
            "type":"Services"
        }
    ],
    "sg:phone":"+1 605 665 7680",
    "sg:postcode":"57078",
    "sg:province":"SD",
    "sg:tags":[
        "repairing",
        "automobile"
    ],
    "wof:name":"Master-Tech Auto Clinic Inc",
    "wof:placetype":"venue"
},
  "geometry": {"coordinates":[-97.397741,42.904013],"type":"Point"}
}