{
  "type": "Feature",
  "properties": {
    "addr:full":"26549 451st Ave Monroe SD 57047",
    "addr:housenumber":"26549",
    "addr:postcode":"57047",
    "addr:street":"451St Ave",
    "iso:country":"US",
    "sg:address":"26549 451st Ave",
    "sg:city":"Monroe",
    "sg:classifiers":[
        {
            "category":"Retail",
            "subcategory":"Auto Repair",
            "type":"Services"
        }
    ],
    "sg:phone":"+1 605 297 4295",
    "sg:postcode":"57047",
    "sg:province":"SD",
    "sg:tags":[
        "general"
    ],
    "wof:name":"Paul Davis Repair",
    "wof:placetype":"venue"
},
  "geometry": {"coordinates":[-97.189488,43.532864],"type":"Point"}
}