{
  "type": "Feature",
  "properties": {
    "iso:country":"US",
    "sg:address":"263 Kniest Ave",
    "sg:city":"Yankton",
    "sg:classifiers":[
        {
            "category":"Retail",
            "subcategory":"Repair Shop",
            "type":"Services"
        }
    ],
    "sg:phone":"+1 605 665 2276",
    "sg:postcode":"57078",
    "sg:province":"SD",
    "sg:tags":[
        "business"
    ],
    "wof:name":"Custom Upholstery By Diane",
    "wof:placetype":"venue"
},
  "geometry": {"coordinates":[-97.525038,42.871511],"type":"Point"}
}