{
  "type": "Feature",
  "properties": {
    "addr:full":"414 E 4th St Dell Rapids SD 57022",
    "addr:housenumber":"414",
    "addr:postcode":"57022",
    "addr:street":"E 4Th St",
    "iso:country":"US",
    "sg:address":"414 E 4th St",
    "sg:city":"Dell Rapids",
    "sg:classifiers":[
        {
            "category":"Manufacturing",
            "subcategory":"Printing",
            "type":"Manufacturing & Wholesale Goods"
        }
    ],
    "sg:phone":"+1 605 428 5441",
    "sg:postcode":"57022",
    "sg:province":"SD",
    "sg:tags":[
        "newspaper"
    ],
    "wof:name":"Dell Rapids Tribune",
    "wof:placetype":"venue"
},
  "geometry": {"coordinates":[-96.711823,43.82339],"type":"Point"}
}