{
  "type": "Feature",
  "properties": {
    "addr:full":"34190 145th St Roscoe SD 57471",
    "addr:housenumber":"34190",
    "addr:postcode":"57471",
    "addr:street":"145Th St",
    "iso:country":"US",
    "sg:address":"34190 145th St",
    "sg:city":"Roscoe",
    "sg:classifiers":[
        {
            "category":"Manufacturing",
            "subcategory":"Tools & Machinery",
            "type":"Manufacturing & Wholesale Goods"
        }
    ],
    "sg:phone":"+1 605 287 4535",
    "sg:postcode":"57471",
    "sg:province":"SD",
    "sg:tags":[
        "farm",
        "livestock",
        "mfg"
    ],
    "wof:name":"Mark Baer",
    "wof:placetype":"venue"
},
  "geometry": {"coordinates":[-99.347724,45.288841],"type":"Point"}
}