{
  "type": "Feature",
  "properties": {
    "iso:country":"US",
    "sg:address":"307 S Menlo Ave",
    "sg:city":"Sioux Falls",
    "sg:classifiers":[
        {
            "category":"Professional",
            "subcategory":"Management & Consulting",
            "type":"Services"
        }
    ],
    "sg:phone":"+1 605 331 2927",
    "sg:postcode":"57104",
    "sg:province":"SD",
    "sg:tags":[
        "association"
    ],
    "wof:name":"Management Service Partners",
    "wof:placetype":"venue"
},
  "geometry": {"coordinates":[-96.739676,43.544647],"type":"Point"}
}