{
  "type": "Feature",
  "properties": {
    "iso:country":"US",
    "sg:address":"47088 255th St",
    "sg:city":"Crooks",
    "sg:phone":"+1 605 543 5265",
    "sg:postcode":"57020",
    "sg:province":"SD",
    "sg:tags":[
        "farm",
        "corn",
        "soybean"
    ],
    "wof:name":"Swanson Farms Inc",
    "wof:placetype":"venue"
},
  "geometry": {"coordinates":[-96.792052,43.688765],"type":"Point"}
}