{
  "type": "Feature",
  "properties": {
    "iso:country":"US",
    "sg:address":"1415 22nd Ave S",
    "sg:city":"Brookings",
    "sg:classifiers":[
        {
            "category":"Sports & Exercise",
            "subcategory":"Golf",
            "type":"Entertainment"
        }
    ],
    "sg:phone":"+1 605 692 2212",
    "sg:postcode":"57006",
    "sg:province":"SD",
    "sg:tags":[
        "course",
        "public"
    ],
    "wof:name":"Edgebrook Golf Course",
    "wof:placetype":"venue"
},
  "geometry": {"coordinates":[-96.76827900000001,44.289454],"type":"Point"}
}