{
  "type": "Feature",
  "properties": {
    "iso:country":"US",
    "sg:address":"5108 Pierre St",
    "sg:city":"Rapid City",
    "sg:classifiers":[
        {
            "category":"Social Services",
            "subcategory":"Child Care",
            "type":"Services"
        }
    ],
    "sg:phone":"+1 605 721 8865",
    "sg:postcode":"57702",
    "sg:province":"SD",
    "sg:tags":[
        "day"
    ],
    "wof:name":"Wilson Aundrea Day Care",
    "wof:placetype":"venue"
},
  "geometry": {"coordinates":[-103.302427,44.089056],"type":"Point"}
}