{
  "type": "Feature",
  "properties": {
    "addr:full":"20531 453rd Ave Arlington SD 57212",
    "addr:housenumber":"20531",
    "addr:postcode":"57212",
    "addr:street":"453Rd Ave",
    "iso:country":"US",
    "sg:address":"20531 453rd Ave",
    "sg:city":"Arlington",
    "sg:classifiers":[
        {
            "category":"Manufacturing",
            "subcategory":"Signs",
            "type":"Manufacturing & Wholesale Goods"
        }
    ],
    "sg:phone":"+1 605 690 7446",
    "sg:postcode":"57212",
    "sg:province":"SD",
    "sg:tags":[
        "specialty",
        "mfg"
    ],
    "wof:name":"Custom Club & Repair",
    "wof:placetype":"venue"
},
  "geometry": {"coordinates":[-97.149255,44.406133],"type":"Point"}
}