{
  "type": "Feature",
  "properties": {
    "addr:full":"306 S Harrison St Gettysburg SD 57442",
    "addr:housenumber":"306",
    "addr:postcode":"57442",
    "addr:street":"S Harrison St",
    "iso:country":"US",
    "sg:address":"306 S Harrison St",
    "sg:city":"Gettysburg",
    "sg:classifiers":[
        {
            "category":"Real Estate",
            "subcategory":"Real Estate Operator",
            "type":"Services"
        }
    ],
    "sg:phone":"+1 605 765 9440",
    "sg:postcode":"57442",
    "sg:province":"SD",
    "sg:tags":[
        "farming"
    ],
    "wof:name":"Curtis J & Jeanne M Lagan",
    "wof:placetype":"venue"
},
  "geometry": {"coordinates":[-99.948398,45.009296],"type":"Point"}
}