{
  "type": "Feature",
  "properties": {
    "iso:country":"US",
    "sg:address":"45251 309th St",
    "sg:city":"Gayville",
    "sg:classifiers":[
        {
            "category":"Farming",
            "subcategory":"Livestock Farm",
            "type":"Manufacturing & Wholesale Goods"
        }
    ],
    "sg:phone":"+1 605 267 4130",
    "sg:postcode":"57031",
    "sg:province":"SD",
    "sg:tags":[
        "animal",
        "general"
    ],
    "wof:name":"Petrick Farms",
    "wof:placetype":"venue"
},
  "geometry": {"coordinates":[-97.146895,42.909387],"type":"Point"}
}