{
  "type": "Feature",
  "properties": {
    "iso:country":"US",
    "sg:address":"715 S Minnesota Ave",
    "sg:city":"Sioux Falls",
    "sg:classifiers":[
        {
            "category":"Government",
            "subcategory":"Office",
            "type":"Public Place"
        }
    ],
    "sg:phone":"+1 605 332 8896",
    "sg:postcode":"57104",
    "sg:province":"SD",
    "wof:name":"REPRESENTATIVE Tim Johnson",
    "wof:placetype":"venue"
},
  "geometry": {"coordinates":[-96.73134,43.541215],"type":"Point"}
}