{
  "type": "Feature",
  "properties": {
    "addr:full":"31842 295th St Colome SD 57528",
    "addr:housenumber":"31842",
    "addr:postcode":"57528",
    "addr:street":"295Th St",
    "iso:country":"US",
    "sg:address":"31842 295th St",
    "sg:city":"Colome",
    "sg:classifiers":[
        {
            "category":"Farming",
            "subcategory":"Livestock Farm",
            "type":"Manufacturing & Wholesale Goods"
        }
    ],
    "sg:phone":"+1 605 842 3410",
    "sg:postcode":"57528",
    "sg:province":"SD",
    "sg:tags":[
        "beef",
        "feedlot",
        "cattle"
    ],
    "wof:name":"Gary Woods",
    "wof:placetype":"venue"
},
  "geometry": {"coordinates":[-99.80432999999999,43.125664],"type":"Point"}
}