{
  "type": "Feature",
  "properties": {
    "iso:country":"US",
    "sg:address":"38392 132nd St",
    "sg:city":"Aberdeen",
    "sg:classifiers":[
        {
            "category":"Building & Trades",
            "subcategory":"Electrical",
            "type":"Services"
        }
    ],
    "sg:phone":"+1 605 226 1297",
    "sg:postcode":"57401",
    "sg:province":"SD",
    "sg:tags":[
        "electric",
        "contractor"
    ],
    "wof:name":"Electric Co Of South Dakota",
    "wof:placetype":"venue"
},
  "geometry": {"coordinates":[-98.557318,45.474404],"type":"Point"}
}