{
  "type": "Feature",
  "properties": {
    "addr:full":"119 W 6th St Gregory SD 57533",
    "addr:housenumber":"119",
    "addr:postcode":"57533",
    "addr:street":"W 6Th St",
    "iso:country":"US",
    "sg:address":"119 W 6th St",
    "sg:city":"Gregory",
    "sg:classifiers":[
        {
            "category":"Travel",
            "subcategory":"Travel Agent",
            "type":"Entertainment"
        }
    ],
    "sg:phone":"+1 605 835 9023",
    "sg:postcode":"57533",
    "sg:province":"SD",
    "sg:tags":[
        "agency",
        "bureau"
    ],
    "wof:name":"Travel Now of Gregory",
    "wof:placetype":"venue"
},
  "geometry": {"coordinates":[-99.432075,43.232132],"type":"Point"}
}