{
  "type": "Feature",
  "properties": {
    "iso:country":"US",
    "sg:address":"502 E 5th St",
    "sg:city":"Dell Rapids",
    "sg:classifiers":[
        {
            "category":"Local Transit",
            "type":"Transportation"
        }
    ],
    "sg:phone":"+1 605 428 6100",
    "sg:postcode":"57022",
    "sg:province":"SD",
    "sg:tags":[
        "passenger"
    ],
    "wof:name":"Ambulance Service",
    "wof:placetype":"venue"
},
  "geometry": {"coordinates":[-96.71019099999999,43.824358],"type":"Point"}
}