{
  "type": "Feature",
  "properties": {
    "iso:country":"US",
    "sg:address":"1130 Empire Mall",
    "sg:city":"Sioux Falls",
    "sg:classifiers":[
        {
            "category":"Home & Garden",
            "subcategory":"Furniture",
            "type":"Retail Goods"
        }
    ],
    "sg:phone":"+1 605 362 1593",
    "sg:postcode":"57106",
    "sg:province":"SD",
    "sg:tags":[
        "mattress"
    ],
    "sg:website":"www.selectcomfort.com",
    "wof:name":"Select Comfort Corp",
    "wof:placetype":"venue"
},
  "geometry": {"coordinates":[-96.77479599999999,43.514229],"type":"Point"}
}