{
  "type": "Feature",
  "properties": {
    "iso:country":"US",
    "sg:address":"41853 277th St",
    "sg:city":"Parkston",
    "sg:phone":"+1 605 928 7444",
    "sg:postcode":"57366",
    "sg:province":"SD",
    "sg:tags":[
        "farm",
        "corn"
    ],
    "wof:name":"Kenneth Leischner",
    "wof:placetype":"venue"
},
  "geometry": {"coordinates":[-97.832157,43.370563],"type":"Point"}
}