{
  "type": "Feature",
  "properties": {
    "addr:full":"825 Jackson Blvd Rapid City SD 57702",
    "addr:housenumber":"825",
    "addr:postcode":"57702",
    "addr:street":"Jackson Blvd",
    "iso:country":"US",
    "sg:address":"825 Jackson Blvd",
    "sg:city":"Rapid City",
    "sg:classifiers":[
        {
            "category":"Bars & Pubs",
            "type":"Food & Drink"
        }
    ],
    "sg:phone":"+1 605 348 1213",
    "sg:postcode":"57702",
    "sg:province":"SD",
    "sg:tags":[
        "grill",
        "bar"
    ],
    "wof:name":"Kellys Sports Lounge Inc",
    "wof:placetype":"venue"
},
  "geometry": {"coordinates":[-103.25062699999999,44.077293],"type":"Point"}
}