{
  "type": "Feature",
  "properties": {
    "iso:country":"US",
    "sg:address":"2208 W 41st St",
    "sg:city":"Sioux Falls",
    "sg:classifiers":[
        {
            "category":"Shopping",
            "subcategory":"Gifts & Souvenirs",
            "type":"Retail Goods"
        }
    ],
    "sg:phone":"+1 605 334 0662",
    "sg:postcode":"57105",
    "sg:province":"SD",
    "sg:tags":[
        "shop"
    ],
    "sg:website":"www.paintedprairieinc.com",
    "wof:name":"Painted Prairie Inc",
    "wof:placetype":"venue"
},
  "geometry": {"coordinates":[-96.753554,43.514921],"type":"Point"}
}