{
  "type": "Feature",
  "properties": {
    "addr:full":"4530 Wentworth Dr Rapid City SD 57702",
    "addr:housenumber":"4530",
    "addr:postcode":"57702",
    "addr:street":"Wentworth Dr",
    "iso:country":"US",
    "sg:address":"4530 Wentworth Dr",
    "sg:city":"Rapid City",
    "sg:classifiers":[
        {
            "category":"Building & Trades",
            "subcategory":"Plumbing",
            "type":"Services"
        }
    ],
    "sg:phone":"+1 605 342 9530",
    "sg:postcode":"57702",
    "sg:province":"SD",
    "sg:tags":[
        "contractor"
    ],
    "wof:name":"Noble Heating & AC",
    "wof:placetype":"venue"
},
  "geometry": {"coordinates":[-103.298175,44.084801],"type":"Point"}
}