{
  "type": "Feature",
  "properties": {
    "iso:country":"US",
    "sg:address":"2507 Fox Run Pkwy",
    "sg:city":"Yankton",
    "sg:classifiers":[
        {
            "category":"Health Services",
            "subcategory":"Chiropractor",
            "type":"Services"
        }
    ],
    "sg:phone":"+1 605 665 8073",
    "sg:postcode":"57078",
    "sg:province":"SD",
    "wof:name":"First Chiropractic Ctr",
    "wof:placetype":"venue"
},
  "geometry": {"coordinates":[-97.399976,42.90139],"type":"Point"}
}