{
  "type": "Feature",
  "properties": {
    "iso:country":"US",
    "sg:address":"2522 W 41st St",
    "sg:city":"Sioux Falls",
    "sg:classifiers":[
        {
            "category":"Arts & Performance",
            "subcategory":"Theater",
            "type":"Entertainment"
        }
    ],
    "sg:phone":"+1 605 332 7886",
    "sg:postcode":"57105",
    "sg:province":"SD",
    "sg:tags":[
        "entertainer"
    ],
    "sg:website":"www.yvettewilde.com",
    "wof:name":"Sexy-1 Professional Svc",
    "wof:placetype":"venue"
},
  "geometry": {"coordinates":[-96.757134,43.514916],"type":"Point"}
}