{
  "type": "Feature",
  "properties": {
    "iso:country":"US",
    "sg:address":"24939 421st Ave",
    "sg:city":"Alexandria",
    "sg:classifiers":[
        {
            "category":"Freight",
            "type":"Transportation"
        }
    ],
    "sg:phone":"+1 605 239 4868",
    "sg:postcode":"57311",
    "sg:province":"SD",
    "sg:tags":[
        "trucking"
    ],
    "wof:name":"Fitzpatrick Trucking",
    "wof:placetype":"venue"
},
  "geometry": {"coordinates":[-97.78953799999999,43.762161],"type":"Point"}
}