{
  "type": "Feature",
  "properties": {
    "iso:country":"US",
    "sg:address":"2101 W 41st St",
    "sg:city":"Sioux Falls",
    "sg:classifiers":[
        {
            "category":"Sports & Exercise",
            "subcategory":"Gym",
            "type":"Entertainment"
        }
    ],
    "sg:phone":"+1 605 274 6571",
    "sg:postcode":"57105",
    "sg:province":"SD",
    "sg:tags":[
        "club",
        "health",
        "studio",
        "gymnasium"
    ],
    "wof:name":"Curves For Women",
    "wof:placetype":"venue"
},
  "geometry": {"coordinates":[-96.75232800000001,43.514842],"type":"Point"}
}