{
  "type": "Feature",
  "properties": {
    "iso:country":"US",
    "sg:address":"2138 Baldwin St",
    "sg:city":"Sturgis",
    "sg:classifiers":[
        {
            "category":"Retail",
            "subcategory":"Repair Shop",
            "type":"Services"
        }
    ],
    "sg:phone":"+1 605 347 4478",
    "sg:postcode":"57785",
    "sg:province":"SD",
    "sg:tags":[
        "equipment"
    ],
    "wof:name":"Roses Sanitation",
    "wof:placetype":"venue"
},
  "geometry": {"coordinates":[-103.504818,44.402755],"type":"Point"}
}