{
  "type": "Feature",
  "properties": {
    "iso:country":"US",
    "sg:address":"42837 State Hwy 42",
    "sg:city":"Emery",
    "sg:classifiers":[
        {
            "category":"Professional",
            "subcategory":"Business Services",
            "type":"Services"
        }
    ],
    "sg:phone":"+1 605 321 9953",
    "sg:postcode":"57332",
    "sg:province":"SD",
    "wof:name":"Jeremiah Enterprises",
    "wof:placetype":"venue"
},
  "geometry": {"coordinates":[-97.646452,43.543233],"type":"Point"}
}