{
  "type": "Feature",
  "properties": {
    "iso:country":"US",
    "sg:address":"46304 Jeffrey St",
    "sg:city":"Hartford",
    "sg:classifiers":[
        {
            "category":"Professional",
            "type":"Services"
        }
    ],
    "sg:phone":"+1 605 528 4700",
    "sg:postcode":"57033",
    "sg:province":"SD",
    "sg:tags":[
        "establishment"
    ],
    "wof:name":"Mitchhart Mang Inc",
    "wof:placetype":"venue"
},
  "geometry": {"coordinates":[-96.949585,43.605737],"type":"Point"}
}