{
  "type": "Feature",
  "properties": {
    "addr:full":"850 Mountain View Rd Rapid City SD 57702",
    "addr:housenumber":"850",
    "addr:postcode":"57702",
    "addr:street":"Mountain View Rd",
    "iso:country":"US",
    "sg:address":"850 Mountain View Rd",
    "sg:city":"Rapid City",
    "sg:classifiers":[
        {
            "category":"Banks & Credit Unions",
            "subcategory":"Bank",
            "type":"Services"
        }
    ],
    "sg:phone":"+1 605 343 0891",
    "sg:postcode":"57702",
    "sg:province":"SD",
    "wof:name":"Black Hills Federal CU",
    "wof:placetype":"venue"
},
  "geometry": {"coordinates":[-103.251955,44.079831],"type":"Point"}
}