{
  "type": "Feature",
  "properties": {
    "iso:country":"US",
    "sg:address":"1217 Harmony Cir",
    "sg:city":"Spearfish",
    "sg:classifiers":[
        {
            "category":"Retail",
            "subcategory":"Repair Shop",
            "type":"Services"
        }
    ],
    "sg:phone":"+1 605 642 3385",
    "sg:postcode":"57783",
    "sg:province":"SD",
    "wof:name":"Spearfish Gunsmithing",
    "wof:placetype":"venue"
},
  "geometry": {"coordinates":[-103.877022,44.49551],"type":"Point"}
}