{
  "type": "Feature",
  "properties": {
    "addr:full":"400 Main St Armour SD 57313",
    "addr:housenumber":"400",
    "addr:postcode":"57313",
    "addr:street":"Main St",
    "iso:country":"US",
    "sg:address":"400 Main St",
    "sg:city":"Armour",
    "sg:classifiers":[
        {
            "category":"Utilities",
            "subcategory":"Electric",
            "type":"Services"
        }
    ],
    "sg:phone":"+1 605 724 2323",
    "sg:postcode":"57313",
    "sg:province":"SD",
    "sg:tags":[
        "company"
    ],
    "wof:name":"Douglas Electric Co-Op Inc",
    "wof:placetype":"venue"
},
  "geometry": {"coordinates":[-98.34660599999999,43.315678],"type":"Point"}
}