{
  "type": "Feature",
  "properties": {
    "addr:full":"4832 Mountain Springs Ct Rapid City SD 57702",
    "addr:housenumber":"4832",
    "addr:postcode":"57702",
    "addr:street":"Mountain Springs Ct",
    "iso:country":"US",
    "sg:address":"4832 Mountain Springs Ct",
    "sg:city":"Rapid City",
    "sg:classifiers":[
        {
            "category":"Shopping",
            "type":"Retail Goods"
        }
    ],
    "sg:phone":"+1 605 343 9642",
    "sg:postcode":"57702",
    "sg:province":"SD",
    "sg:tags":[
        "awning",
        "canopy"
    ],
    "wof:name":"Trm Exterior Cleaning Svc",
    "wof:placetype":"venue"
},
  "geometry": {"coordinates":[-103.300223,44.093921],"type":"Point"}
}