{
  "type": "Feature",
  "properties": {
    "iso:country":"US",
    "sg:address":"45620 213th St",
    "sg:city":"Arlington",
    "sg:phone":"+1 605 983 5702",
    "sg:postcode":"57212",
    "sg:province":"SD",
    "sg:tags":[
        "farm",
        "corn",
        "soybean"
    ],
    "wof:name":"Curt Larsen",
    "wof:placetype":"venue"
},
  "geometry": {"coordinates":[-97.071611,44.297004],"type":"Point"}
}