{
  "type": "Feature",
  "properties": {
    "iso:country":"US",
    "sg:address":"215 E 5th St",
    "sg:city":"Parker",
    "sg:classifiers":[
        {
            "category":"Home & Garden",
            "subcategory":"Garden Supply",
            "type":"Retail Goods"
        }
    ],
    "sg:phone":"+1 605 297 2068",
    "sg:postcode":"57053",
    "sg:province":"SD",
    "wof:name":"Cargill AG Horizons",
    "wof:placetype":"venue"
},
  "geometry": {"coordinates":[-97.134956,43.400172],"type":"Point"}
}