{
  "type": "Feature",
  "properties": {
    "addr:full":"1395 4th St NW Watertown SD 57201",
    "addr:housenumber":"1395",
    "addr:postcode":"57201",
    "addr:street":"4Th St Nw",
    "iso:country":"US",
    "sg:address":"1395 4th St NW",
    "sg:city":"Watertown",
    "sg:classifiers":[
        {
            "category":"Professional",
            "subcategory":"Business Services",
            "type":"Services"
        }
    ],
    "sg:phone":"+1 605 882 2374",
    "sg:postcode":"57201",
    "sg:province":"SD",
    "wof:name":"Roxy Wilfahrt",
    "wof:placetype":"venue"
},
  "geometry": {"coordinates":[-97.119409,44.918567],"type":"Point"}
}