{
  "type": "Feature",
  "properties": {
    "iso:country":"US",
    "sg:address":"1919 S Norton Ave",
    "sg:city":"Sioux Falls",
    "sg:classifiers":[
        {
            "category":"Real Estate",
            "subcategory":"Real Estate Operator",
            "type":"Services"
        }
    ],
    "sg:phone":"+1 605 332 1820",
    "sg:postcode":"57105",
    "sg:province":"SD",
    "sg:tags":[
        "property",
        "lessor"
    ],
    "wof:name":"Kathy Stelzer",
    "wof:placetype":"venue"
},
  "geometry": {"coordinates":[-96.735093,43.52748],"type":"Point"}
}