{
  "type": "Feature",
  "properties": {
    "addr:full":"305 Deadwood St Pierre SD 57532",
    "addr:housenumber":"305",
    "addr:postcode":"57532",
    "addr:street":"Deadwood",
    "iso:country":"US",
    "sg:address":"305 Deadwood St",
    "sg:city":"Pierre",
    "sg:classifiers":[
        {
            "category":"Government",
            "subcategory":"Fire Station",
            "type":"Public Place"
        }
    ],
    "sg:phone":"+1 605 000 1111",
    "sg:postcode":"57532",
    "sg:province":"SD",
    "sg:tags":[
        "department"
    ],
    "wof:name":"Fort Pierre Fire Dept",
    "wof:placetype":"venue"
},
  "geometry": {"coordinates":[-100.37348299999999,44.357211],"type":"Point"}
}