{
  "type": "Feature",
  "properties": {
    "iso:country":"US",
    "sg:address":"2465 W Chicago St",
    "sg:city":"Rapid City",
    "sg:classifiers":[
        {
            "category":"Professional",
            "subcategory":"Engineering",
            "type":"Services"
        }
    ],
    "sg:phone":"+1 605 343 0222",
    "sg:postcode":"57702",
    "sg:province":"SD",
    "sg:tags":[
        "engineer"
    ],
    "wof:name":"Bareis Engineering Inc",
    "wof:placetype":"venue"
},
  "geometry": {"coordinates":[-103.258652,44.08452],"type":"Point"}
}