{
  "type": "Feature",
  "properties": {
    "iso:country":"US",
    "sg:address":"214 E Center St",
    "sg:city":"Marion",
    "sg:classifiers":[
        {
            "category":"Retail",
            "subcategory":"Auto Repair",
            "type":"Services"
        }
    ],
    "sg:phone":"+1 605 648 3171",
    "sg:postcode":"57043",
    "sg:province":"SD",
    "sg:tags":[
        "muffler",
        "exhaust",
        "system"
    ],
    "wof:name":"B & B Radiator & Exhaust Rpr",
    "wof:placetype":"venue"
},
  "geometry": {"coordinates":[-97.259266,43.428571],"type":"Point"}
}