{
  "type": "Feature",
  "properties": {
    "addr:full":"13391 Woodcrest Ct Rapid City SD 57702",
    "addr:housenumber":"13391",
    "addr:postcode":"57702",
    "addr:street":"Woodcrest Ct",
    "iso:country":"US",
    "sg:address":"13391 Woodcrest Ct",
    "sg:city":"Rapid City",
    "sg:classifiers":[
        {
            "category":"Health Services",
            "subcategory":"Doctor",
            "type":"Services"
        }
    ],
    "sg:phone":"+1 605 348 3350",
    "sg:postcode":"57702",
    "sg:province":"SD",
    "sg:tags":[
        "medical"
    ],
    "wof:name":"Richard H Tucker Dr",
    "wof:placetype":"venue"
},
  "geometry": {"coordinates":[-103.372936,44.135696],"type":"Point"}
}