{
  "type": "Feature",
  "properties": {
    "iso:country":"US",
    "sg:address":"135 E Neosho St",
    "sg:city":"Iroquois",
    "sg:classifiers":[
        {
            "category":"Bars & Pubs",
            "type":"Food & Drink"
        }
    ],
    "sg:phone":"+1 605 546 2219",
    "sg:postcode":"57353",
    "sg:province":"SD",
    "wof:name":"Lazy R Bar",
    "wof:placetype":"venue"
},
  "geometry": {"coordinates":[-97.852669,44.369075],"type":"Point"}
}