{
  "type": "Feature",
  "properties": {
    "iso:country":"US",
    "sg:address":"31535 206th St",
    "sg:city":"Harrold",
    "sg:classifiers":[
        {
            "category":"Farming",
            "subcategory":"Farm",
            "type":"Manufacturing & Wholesale Goods"
        }
    ],
    "sg:phone":"+1 605 875 3368",
    "sg:postcode":"57536",
    "sg:province":"SD",
    "sg:tags":[
        "crop",
        "general"
    ],
    "wof:name":"Roger Burki",
    "wof:placetype":"venue"
},
  "geometry": {"coordinates":[-99.862141,44.396423],"type":"Point"}
}