{
  "type": "Feature",
  "properties": {
    "iso:country":"US",
    "sg:address":"1301 Turbine Dr",
    "sg:city":"Rapid City",
    "sg:classifiers":[
        {
            "category":"Manufacturing",
            "subcategory":"Metals",
            "type":"Manufacturing & Wholesale Goods"
        }
    ],
    "sg:phone":"+1 605 341 3006",
    "sg:postcode":"57703",
    "sg:province":"SD",
    "sg:tags":[
        "small",
        "sporting",
        "arms",
        "mfg"
    ],
    "sg:website":"www.hsprecision.com",
    "wof:name":"H-S Precision Inc",
    "wof:placetype":"venue"
},
  "geometry": {"coordinates":[-103.155372,44.071105],"type":"Point"}
}