{
  "type": "Feature",
  "properties": {
    "iso:country":"US",
    "sg:address":"504 S State St",
    "sg:city":"Aberdeen",
    "sg:classifiers":[
        {
            "category":"Shopping",
            "subcategory":"Used Merchandise",
            "type":"Retail Goods"
        }
    ],
    "sg:phone":"+1 605 225 3852",
    "sg:postcode":"57401",
    "sg:province":"SD",
    "sg:tags":[
        "book",
        "rare",
        "dealer"
    ],
    "wof:name":"Corner Book Shoppe",
    "wof:placetype":"venue"
},
  "geometry": {"coordinates":[-98.479347,45.460082],"type":"Point"}
}