{
  "type": "Feature",
  "properties": {
    "iso:country":"US",
    "sg:address":"38804 160th St",
    "sg:city":"Ashton",
    "sg:phone":"+1 605 472 2687",
    "sg:postcode":"57424",
    "sg:province":"SD",
    "sg:tags":[
        "farm",
        "wheat",
        "beef",
        "feedlot",
        "cattle"
    ],
    "wof:name":"Calvin Fortin",
    "wof:placetype":"venue"
},
  "geometry": {"coordinates":[-98.452625,45.07063],"type":"Point"}
}