{
  "type": "Feature",
  "properties": {
    "iso:country":"US",
    "sg:address":"2001 7th St",
    "sg:city":"Rapid City",
    "sg:classifiers":[
        {
            "category":"Shopping",
            "type":"Retail Goods"
        }
    ],
    "sg:phone":"+1 605 737 0248",
    "sg:postcode":"57701",
    "sg:province":"SD",
    "sg:tags":[
        "equipment",
        "care",
        "health",
        "home"
    ],
    "wof:name":"Breathe EZ Oxygen",
    "wof:placetype":"venue"
},
  "geometry": {"coordinates":[-103.23020099999999,44.0655],"type":"Point"}
}