{
  "type": "Feature",
  "properties": {
    "iso:country":"US",
    "sg:address":"515 S 8th Ave",
    "sg:city":"Sioux Falls",
    "sg:classifiers":[
        {
            "category":"Health Services",
            "subcategory":"Clinic",
            "type":"Services"
        }
    ],
    "sg:phone":"+1 605 332 2196",
    "sg:postcode":"57104",
    "sg:province":"SD",
    "sg:tags":[
        "home"
    ],
    "sg:website":"www.homecareservicessd.com",
    "wof:name":"Homecare Services-South Dakota",
    "wof:placetype":"venue"
},
  "geometry": {"coordinates":[-96.715001,43.541603],"type":"Point"}
}