{
  "type": "Feature",
  "properties": {
    "iso:country":"US",
    "sg:address":"107 Flynn Dr",
    "sg:city":"Milbank",
    "sg:classifiers":[
        {
            "category":"Shopping",
            "subcategory":"Computers & Home Electronics",
            "type":"Retail Goods"
        }
    ],
    "sg:phone":"+1 605 432 5753",
    "sg:postcode":"57252",
    "sg:province":"SD",
    "sg:tags":[
        "software"
    ],
    "wof:name":"Linkit Software",
    "wof:placetype":"venue"
},
  "geometry": {"coordinates":[-96.619943,45.22205],"type":"Point"}
}