{
  "type": "Feature",
  "properties": {
    "iso:country":"US",
    "sg:address":"19602 Lake Pl",
    "sg:city":"Pierre",
    "sg:classifiers":[
        {
            "category":"Restaurant",
            "type":"Food & Drink"
        }
    ],
    "sg:phone":"+1 605 224 9340",
    "sg:postcode":"57501",
    "sg:province":"SD",
    "sg:website":"www.lighthousepointe.com",
    "wof:name":"Lighthouse Pointe Restaurant",
    "wof:placetype":"venue"
},
  "geometry": {"coordinates":[-100.474434,44.546241],"type":"Point"}
}