{
  "type": "Feature",
  "properties": {
    "iso:country":"US",
    "sg:address":"3620 N Lewis Ave",
    "sg:city":"Sioux Falls",
    "sg:classifiers":[
        {
            "category":"Building & Trades",
            "subcategory":"Equipment Rental",
            "type":"Services"
        }
    ],
    "sg:phone":"+1 605 357 9510",
    "sg:postcode":"57104",
    "sg:province":"SD",
    "sg:tags":[
        "contractor"
    ],
    "wof:name":"RSC Equipment",
    "wof:placetype":"venue"
},
  "geometry": {"coordinates":[-96.701327,43.585281],"type":"Point"}
}