{
  "type": "Feature",
  "properties": {
    "iso:country":"US",
    "sg:address":"123 Ray Ann Ct",
    "sg:city":"Rapid City",
    "sg:classifiers":[
        {
            "category":"Retail",
            "subcategory":"Laundry & Dry Cleaning",
            "type":"Services"
        }
    ],
    "sg:phone":"+1 605 343 6893",
    "sg:postcode":"57702",
    "sg:province":"SD",
    "sg:tags":[
        "carpet",
        "furniture"
    ],
    "wof:name":"Menkens Carpet & Furniture Clg",
    "wof:placetype":"venue"
},
  "geometry": {"coordinates":[-103.301304,44.087197],"type":"Point"}
}