{
  "type": "Feature",
  "properties": {
    "addr:full":"5208 S Danberry Dr Sioux Falls SD 57106",
    "addr:housenumber":"5208",
    "addr:postcode":"57106",
    "addr:street":"S Danberry Dr",
    "iso:country":"US",
    "sg:address":"5208 S Danberry Dr",
    "sg:city":"Sioux Falls",
    "sg:classifiers":[
        {
            "category":"Building & Trades",
            "subcategory":"Construction",
            "type":"Services"
        }
    ],
    "sg:phone":"+1 605 361 1790",
    "sg:postcode":"57106",
    "sg:province":"SD",
    "sg:tags":[
        "general",
        "contractor"
    ],
    "wof:name":"Janssen & Janssen",
    "wof:placetype":"venue"
},
  "geometry": {"coordinates":[-96.798734,43.498844],"type":"Point"}
}