{
  "type": "Feature",
  "properties": {
    "addr:full":"726 Payton Ct Rapid City SD 57702",
    "addr:housenumber":"726",
    "addr:postcode":"57702",
    "addr:street":"Payton Ct",
    "iso:country":"US",
    "sg:address":"726 Payton Ct",
    "sg:city":"Rapid City",
    "sg:classifiers":[
        {
            "category":"Health Services",
            "subcategory":"Doctor",
            "type":"Services"
        }
    ],
    "sg:phone":"+1 605 343 1060",
    "sg:postcode":"57702",
    "sg:province":"SD",
    "sg:tags":[
        "dr"
    ],
    "wof:name":"Gerti J Janss",
    "wof:placetype":"venue"
},
  "geometry": {"coordinates":[-103.27588299999999,44.079771],"type":"Point"}
}