{
  "type": "Feature",
  "properties": {
    "addr:full":"920 14th St SE Watertown SD 57201",
    "addr:housenumber":"920",
    "addr:postcode":"57201",
    "addr:street":"14Th St Se",
    "iso:country":"US",
    "sg:address":"920 14th St SE",
    "sg:city":"Watertown",
    "sg:classifiers":[
        {
            "category":"Professional",
            "subcategory":"Business Services",
            "type":"Services"
        }
    ],
    "sg:phone":"+1 605 882 2243",
    "sg:postcode":"57201",
    "sg:province":"SD",
    "sg:tags":[
        "reservation",
        "motel",
        "hotel"
    ],
    "wof:name":"Travelers Inn",
    "wof:placetype":"venue"
},
  "geometry": {"coordinates":[-97.09285,44.889797],"type":"Point"}
}