{
  "type": "Feature",
  "properties": {
    "addr:full":"57 Sherman St Deadwood SD 57732",
    "addr:housenumber":"57",
    "addr:postcode":"57732",
    "addr:street":"Sherman St",
    "iso:country":"US",
    "sg:address":"57 Sherman St",
    "sg:city":"Deadwood",
    "sg:classifiers":[
        {
            "category":"Travel",
            "subcategory":"Hotels & Motels",
            "type":"Entertainment"
        }
    ],
    "sg:phone":"+1 605 343 8126",
    "sg:postcode":"57732",
    "sg:province":"SD",
    "wof:name":"Butch Cassidy & The Sundance",
    "wof:placetype":"venue"
},
  "geometry": {"coordinates":[-103.72885599999999,44.376396],"type":"Point"}
}