{
  "type": "Feature",
  "properties": {
    "addr:full":"621 6th St Rapid City SD 57701",
    "addr:housenumber":"621",
    "addr:postcode":"57701",
    "addr:street":"6Th St",
    "iso:country":"US",
    "sg:address":"621 6th St",
    "sg:city":"Rapid City",
    "sg:classifiers":[
        {
            "category":"Personal",
            "type":"Services"
        }
    ],
    "sg:phone":"+1 605 348 4550",
    "sg:postcode":"57701",
    "sg:province":"SD",
    "sg:tags":[
        "credit",
        "debt",
        "counseling"
    ],
    "sg:website":"www.creditwhencreditisdue.com",
    "wof:name":"Consumer Credit Counseling Svc",
    "wof:placetype":"venue"
},
  "geometry": {"coordinates":[-103.22763,44.079178],"type":"Point"}
}