{
  "type": "Feature",
  "properties": {
    "iso:country":"US",
    "sg:address":"201 N Hooker Ave",
    "sg:city":"White",
    "sg:classifiers":[
        {
            "category":"Retail",
            "subcategory":"Repair Shop",
            "type":"Services"
        }
    ],
    "sg:phone":"+1 605 629 6861",
    "sg:postcode":"57276",
    "sg:province":"SD",
    "sg:tags":[
        "plumbing",
        "drain",
        "cleaning",
        "sewer"
    ],
    "wof:name":"Drains Unlimited",
    "wof:placetype":"venue"
},
  "geometry": {"coordinates":[-96.646182,44.436786],"type":"Point"}
}