{
  "type": "Feature",
  "properties": {
    "iso:country":"US",
    "sg:address":"6729 W 41st St",
    "sg:city":"Sioux Falls",
    "sg:classifiers":[
        {
            "category":"Restaurant",
            "type":"Food & Drink"
        }
    ],
    "sg:menulink":"http://www.allmenus.com/sd/sioux-falls/96413-taco-johns/menu/",
    "sg:phone":"+1 605 361 9920",
    "sg:postcode":"57106",
    "sg:province":"SD",
    "sg:tags":[
        "american",
        "mexican"
    ],
    "wof:name":"Taco John's",
    "wof:placetype":"venue"
},
  "geometry": {"coordinates":[-96.811196,43.514823],"type":"Point"}
}