{
  "type": "Feature",
  "properties": {
    "iso:country":"US",
    "sg:address":"4404 S Yellowstone Ln",
    "sg:city":"Sioux Falls",
    "sg:classifiers":[
        {
            "category":"Real Estate",
            "subcategory":"Real Estate Agent",
            "type":"Services"
        }
    ],
    "sg:phone":"+1 605 334 8155",
    "sg:postcode":"57105",
    "sg:province":"SD",
    "wof:name":"Savings Real Estate/Appraisal",
    "wof:placetype":"venue"
},
  "geometry": {"coordinates":[-96.738148,43.500365],"type":"Point"}
}