{
  "type": "Feature",
  "properties": {
    "iso:country":"US",
    "sg:address":"47154 258th St",
    "sg:city":"Sioux Falls",
    "sg:classifiers":[
        {
            "category":"Real Estate",
            "subcategory":"Real Estate Operator",
            "type":"Services"
        }
    ],
    "sg:phone":"+1 605 543 5557",
    "sg:postcode":"57107",
    "sg:province":"SD",
    "sg:tags":[
        "property",
        "lessor"
    ],
    "wof:name":"Clayton Dawson",
    "wof:placetype":"venue"
},
  "geometry": {"coordinates":[-96.779242,43.645382],"type":"Point"}
}