{
  "type": "Feature",
  "properties": {
    "iso:country":"US",
    "sg:address":"3209 S Louise Ave",
    "sg:city":"Sioux Falls",
    "sg:classifiers":[
        {
            "category":"Personal",
            "subcategory":"Beauty Salon",
            "type":"Services"
        }
    ],
    "sg:phone":"+1 605 362 8368",
    "sg:postcode":"57106",
    "sg:province":"SD",
    "sg:website":"www.smartstyle.com",
    "wof:name":"Smart Style Family Hair Salon",
    "wof:placetype":"venue"
},
  "geometry": {"coordinates":[-96.77109799999999,43.518189],"type":"Point"}
}