{
  "type": "Feature",
  "properties": {
    "iso:country":"US",
    "sg:address":"13230 393rd Ave",
    "sg:city":"Bath",
    "sg:classifiers":[
        {
            "category":"Farming",
            "subcategory":"Dairy Farm",
            "type":"Manufacturing & Wholesale Goods"
        }
    ],
    "sg:phone":"+1 605 229 1365",
    "sg:postcode":"57427",
    "sg:province":"SD",
    "wof:name":"John Weigel",
    "wof:placetype":"venue"
},
  "geometry": {"coordinates":[-98.371626,45.468655],"type":"Point"}
}