{
  "type": "Feature",
  "properties": {
    "addr:full":"301 E Kemp Ave Watertown SD 57201",
    "addr:housenumber":"301",
    "addr:postcode":"57201",
    "addr:street":"E Kemp Ave",
    "iso:country":"US",
    "sg:address":"301 E Kemp Ave",
    "sg:city":"Watertown",
    "sg:classifiers":[
        {
            "category":"Organizations",
            "subcategory":"Professional Association",
            "type":"Services"
        },
        {
            "category":"Social Services",
            "type":"Services"
        }
    ],
    "sg:phone":"+1 605 886 7063",
    "sg:postcode":"57201",
    "sg:province":"SD",
    "wof:name":"Senior Citizens Center",
    "wof:placetype":"venue"
},
  "geometry": {"coordinates":[-97.10963,44.899474],"type":"Point"}
}