{
  "type": "Feature",
  "properties": {
    "iso:country":"US",
    "sg:address":"519 S Arch St",
    "sg:city":"Aberdeen",
    "sg:classifiers":[
        {
            "category":"Organizations",
            "subcategory":"Non-profit Organization",
            "type":"Services"
        }
    ],
    "sg:phone":"+1 605 225 1292",
    "sg:postcode":"57401",
    "sg:province":"SD",
    "sg:tags":[
        "information",
        "alcoholism",
        "treatment"
    ],
    "wof:name":"Alcoholics Anonymous",
    "wof:placetype":"venue"
},
  "geometry": {"coordinates":[-98.480682,45.459917],"type":"Point"}
}