{
  "type": "Feature",
  "properties": {
    "addr:full":"13579 387th Ave Aberdeen SD 57401",
    "addr:housenumber":"13579",
    "addr:postcode":"57401",
    "addr:street":"387Th Ave",
    "iso:country":"US",
    "sg:address":"13579 387th Ave",
    "sg:city":"Aberdeen",
    "sg:classifiers":[
        {
            "category":"Professional",
            "subcategory":"Business Services",
            "type":"Services"
        },
        {
            "category":"Wholesale",
            "subcategory":"Non-durable Goods",
            "type":"Manufacturing & Wholesale Goods"
        }
    ],
    "sg:phone":"+1 605 226 1213",
    "sg:postcode":"57401",
    "sg:province":"SD",
    "sg:tags":[
        "fund",
        "raising",
        "merchandise"
    ],
    "wof:name":"Red Wheel Fundraising Inc",
    "wof:placetype":"venue"
},
  "geometry": {"coordinates":[-98.49536999999999,45.401523],"type":"Point"}
}