{
  "type": "Feature",
  "properties": {
    "addr:full":"1823 Sheridan Lake Rd Rapid City SD 57702",
    "addr:housenumber":"1823",
    "addr:postcode":"57702",
    "addr:street":"Sheridan Lake Rd",
    "iso:country":"US",
    "sg:address":"1823 Sheridan Lake Rd",
    "sg:city":"Rapid City",
    "sg:classifiers":[
        {
            "category":"Organizations",
            "subcategory":"Religious Organization",
            "type":"Services"
        }
    ],
    "sg:phone":"+1 605 342 3873",
    "sg:postcode":"57702",
    "sg:province":"SD",
    "wof:name":"Strathavon Wesleyan Church",
    "wof:placetype":"venue"
},
  "geometry": {"coordinates":[-103.262145,44.067689],"type":"Point"}
}