{
  "type": "Feature",
  "properties": {
    "iso:country":"US",
    "sg:address":"758 Mellette Ave SW",
    "sg:city":"Huron",
    "sg:classifiers":[
        {
            "category":"Freight",
            "type":"Transportation"
        }
    ],
    "sg:phone":"+1 605 352 3435",
    "sg:postcode":"57350",
    "sg:province":"SD",
    "sg:tags":[
        "trucking"
    ],
    "wof:name":"Seaman Trucking",
    "wof:placetype":"venue"
},
  "geometry": {"coordinates":[-98.23562,44.357838],"type":"Point"}
}