{
  "type": "Feature",
  "properties": {
    "addr:full":"4520 Wentworth Dr Rapid City SD 57702",
    "addr:housenumber":"4520",
    "addr:postcode":"57702",
    "addr:street":"Wentworth Dr",
    "iso:country":"US",
    "sg:address":"4520 Wentworth Dr",
    "sg:city":"Rapid City",
    "sg:classifiers":[
        {
            "category":"Travel",
            "subcategory":"Travel Agent",
            "type":"Entertainment"
        }
    ],
    "sg:phone":"+1 605 342 7691",
    "sg:postcode":"57702",
    "sg:province":"SD",
    "sg:tags":[
        "tours",
        "promoter"
    ],
    "wof:name":"Affordable Adventures",
    "wof:placetype":"venue"
},
  "geometry": {"coordinates":[-103.29372100000001,44.082353],"type":"Point"}
}