{
  "type": "Feature",
  "properties": {
    "iso:country":"US",
    "sg:address":"952 Empire Mall",
    "sg:city":"Sioux Falls",
    "sg:classifiers":[
        {
            "category":"Shopping",
            "subcategory":"Optical Goods",
            "type":"Retail Goods"
        }
    ],
    "sg:phone":"+1 605 361 4398",
    "sg:postcode":"57106",
    "sg:province":"SD",
    "wof:name":"Vision World",
    "wof:placetype":"venue"
},
  "geometry": {"coordinates":[-96.77479599999999,43.514223],"type":"Point"}
}