{
  "type": "Feature",
  "properties": {
    "iso:country":"US",
    "sg:address":"1777 Zinnia",
    "sg:city":"Rapid City",
    "sg:classifiers":[
        {
            "category":"Organizations",
            "subcategory":"Religious Organization",
            "type":"Services"
        }
    ],
    "sg:phone":"+1 605 393 2246",
    "sg:postcode":"57703",
    "sg:province":"SD",
    "sg:tags":[
        "church"
    ],
    "wof:name":"Rapid Valley Faith Baptist Chr",
    "wof:placetype":"venue"
},
  "geometry": {"coordinates":[-103.148726,44.069285],"type":"Point"}
}