{
  "type": "Feature",
  "properties": {
    "iso:country":"US",
    "sg:address":"323 Main Ave",
    "sg:city":"Sinai",
    "sg:classifiers":[
        {
            "category":"Freight",
            "type":"Transportation"
        }
    ],
    "sg:phone":"+1 605 826 4321",
    "sg:postcode":"57061",
    "sg:province":"SD",
    "sg:tags":[
        "grain",
        "elevator"
    ],
    "wof:name":"Sinai Cooperative Elevator Co",
    "wof:placetype":"venue"
},
  "geometry": {"coordinates":[-97.040581,44.244447],"type":"Point"}
}