{
  "type": "Feature",
  "properties": {
    "addr:full":"4205 Range View Ct Rapid City SD 57701",
    "addr:housenumber":"4205",
    "addr:postcode":"57701",
    "addr:street":"Range View Ct",
    "iso:country":"US",
    "sg:address":"4205 Range View Ct",
    "sg:city":"Rapid City",
    "sg:classifiers":[
        {
            "category":"Building & Trades",
            "subcategory":"Construction",
            "type":"Services"
        }
    ],
    "sg:phone":"+1 605 342 2002",
    "sg:postcode":"57701",
    "sg:province":"SD",
    "sg:tags":[
        "carpentry",
        "contractor"
    ],
    "wof:name":"Sage Woodworking",
    "wof:placetype":"venue"
},
  "geometry": {"coordinates":[-103.19675100000001,44.042701],"type":"Point"}
}