{
  "type": "Feature",
  "properties": {
    "iso:country":"US",
    "sg:address":"601 9th Ave SW",
    "sg:city":"Aberdeen",
    "sg:classifiers":[
        {
            "category":"Manufacturing",
            "subcategory":"Glass & Minerals",
            "type":"Manufacturing & Wholesale Goods"
        }
    ],
    "sg:phone":"+1 605 225 8081",
    "sg:postcode":"57401",
    "sg:province":"SD",
    "sg:tags":[
        "a",
        "plant",
        "asphalt",
        "mix",
        "as",
        "concrete",
        "sand",
        "ready",
        "gravel"
    ],
    "wof:name":"Jensen Rock & Sand Inc",
    "wof:placetype":"venue"
},
  "geometry": {"coordinates":[-98.495505,45.456059],"type":"Point"}
}