{
  "type": "Feature",
  "properties": {
    "iso:country":"US",
    "sg:address":"259 Dakota Ave S",
    "sg:city":"Huron",
    "sg:classifiers":[
        {
            "category":"Shopping",
            "subcategory":"Hobbies, Toys, & Games",
            "type":"Retail Goods"
        }
    ],
    "sg:phone":"+1 605 352 9572",
    "sg:postcode":"57350",
    "sg:province":"SD",
    "sg:tags":[
        "arts",
        "craft"
    ],
    "wof:name":"Ben Franklins Crafts",
    "wof:placetype":"venue"
},
  "geometry": {"coordinates":[-98.214209,44.36374],"type":"Point"}
}