{
  "type": "Feature",
  "properties": {
    "iso:country":"US",
    "sg:address":"816 S Suburban Dr",
    "sg:city":"Sioux Falls",
    "sg:classifiers":[
        {
            "category":"Shopping",
            "subcategory":"Stationery & Office Supplies",
            "type":"Retail Goods"
        }
    ],
    "sg:phone":"+1 605 373 0710",
    "sg:postcode":"57110",
    "sg:province":"SD",
    "sg:tags":[
        "album",
        "scrapbook"
    ],
    "wof:name":"Creative Memories",
    "wof:placetype":"venue"
},
  "geometry": {"coordinates":[-96.670034,43.540076],"type":"Point"}
}