{
  "type": "Feature",
  "properties": {
    "iso:country":"US",
    "sg:address":"31790 277th St",
    "sg:city":"Winner",
    "sg:classifiers":[
        {
            "category":"Building & Trades",
            "subcategory":"Construction",
            "type":"Services"
        }
    ],
    "sg:phone":"+1 605 842 2838",
    "sg:postcode":"57580",
    "sg:province":"SD",
    "sg:tags":[
        "general",
        "contractor"
    ],
    "wof:name":"Ron Ernest & Sons Construction",
    "wof:placetype":"venue"
},
  "geometry": {"coordinates":[-99.814448,43.38638],"type":"Point"}
}