{
  "type": "Feature",
  "properties": {
    "iso:country":"US",
    "sg:address":"3460 Sturgis Rd",
    "sg:city":"Rapid City",
    "sg:classifiers":[
        {
            "category":"Food & Beverages",
            "subcategory":"Liquor & Beverages",
            "type":"Retail Goods"
        }
    ],
    "sg:phone":"+1 605 343 0548",
    "sg:postcode":"57702",
    "sg:province":"SD",
    "wof:name":"R C Liquor",
    "wof:placetype":"venue"
},
  "geometry": {"coordinates":[-103.278062,44.085131],"type":"Point"}
}