{
  "type": "Feature",
  "properties": {
    "iso:country":"US",
    "sg:address":"221 Main Ave N",
    "sg:city":"Wagner",
    "sg:classifiers":[
        {
            "category":"Shopping",
            "subcategory":"Clothing, Apparel, & Fashions",
            "type":"Retail Goods"
        }
    ],
    "sg:phone":"+1 605 384 5633",
    "sg:postcode":"57380",
    "sg:province":"SD",
    "sg:tags":[
        "furnishing"
    ],
    "wof:name":"Jane's Country",
    "wof:placetype":"venue"
},
  "geometry": {"coordinates":[-98.293579,43.083434],"type":"Point"}
}