{
  "type": "Feature",
  "properties": {
    "addr:full":"329 S Chicago Ave Sioux Falls SD 57103",
    "addr:housenumber":"329",
    "addr:postcode":"57103",
    "addr:street":"S Chicago Ave",
    "iso:country":"US",
    "sg:address":"329 S Chicago Ave",
    "sg:city":"Sioux Falls",
    "sg:classifiers":[
        {
            "category":"Retail",
            "subcategory":"Repair Shop",
            "type":"Services"
        }
    ],
    "sg:phone":"+1 605 334 0490",
    "sg:postcode":"57103",
    "sg:province":"SD",
    "wof:name":"Warren Sharpening Service",
    "wof:placetype":"venue"
},
  "geometry": {"coordinates":[-96.700215,43.545105],"type":"Point"}
}