{
  "type": "Feature",
  "properties": {
    "iso:country":"US",
    "sg:address":"515 City Springs Ln",
    "sg:city":"Rapid City",
    "sg:classifiers":[
        {
            "category":"Home & Garden",
            "subcategory":"Building Materials",
            "type":"Retail Goods"
        }
    ],
    "sg:phone":"+1 605 343 1689",
    "sg:postcode":"57702",
    "sg:province":"SD",
    "wof:name":"Panscharosa Stained GL Works",
    "wof:placetype":"venue"
},
  "geometry": {"coordinates":[-103.29541,44.089155],"type":"Point"}
}