{
  "type": "Feature",
  "properties": {
    "addr:full":"1800 W 50th St Sioux Falls SD 57105",
    "addr:housenumber":"1800",
    "addr:postcode":"57105",
    "addr:street":"W 50Th St",
    "iso:country":"US",
    "sg:address":"1800 W 50th St",
    "sg:city":"Sioux Falls",
    "sg:classifiers":[
        {
            "category":"Wholesale",
            "subcategory":"Non-durable Goods",
            "type":"Manufacturing & Wholesale Goods"
        }
    ],
    "sg:phone":"+1 605 332 2550",
    "sg:postcode":"57105",
    "sg:province":"SD",
    "sg:tags":[
        "engineering",
        "architectural",
        "supply"
    ],
    "wof:name":"Cadd/Engineering Supply Inc",
    "wof:placetype":"venue"
},
  "geometry": {"coordinates":[-96.74687,43.507452],"type":"Point"}
}