{
  "type": "Feature",
  "properties": {
    "iso:country":"US",
    "sg:address":"35415 State Hwy 26",
    "sg:city":"Orient",
    "sg:classifiers":[
        {
            "category":"Bars & Pubs",
            "type":"Food & Drink"
        }
    ],
    "sg:phone":"+1 605 392 2515",
    "sg:postcode":"57467",
    "sg:province":"SD",
    "sg:tags":[
        "tavern"
    ],
    "wof:name":"Ponderosa Bar & Cafe",
    "wof:placetype":"venue"
},
  "geometry": {"coordinates":[-99.10686800000001,44.779592],"type":"Point"}
}