{
  "type": "Feature",
  "properties": {
    "iso:country":"US",
    "sg:address":"309 Veterans Ave",
    "sg:city":"Sisseton",
    "sg:classifiers":[
        {
            "category":"Personal",
            "subcategory":"Beauty Salon",
            "type":"Services"
        }
    ],
    "sg:phone":"+1 605 698 4310",
    "sg:postcode":"57262",
    "sg:province":"SD",
    "sg:tags":[
        "shop"
    ],
    "wof:name":"Reflections",
    "wof:placetype":"venue"
},
  "geometry": {"coordinates":[-97.049583,45.663665],"type":"Point"}
}