{
  "type": "Feature",
  "properties": {
    "iso:country":"US",
    "sg:address":"514 N Weber St",
    "sg:city":"Aberdeen",
    "sg:classifiers":[
        {
            "category":"Building & Trades",
            "subcategory":"Construction",
            "type":"Services"
        }
    ],
    "sg:phone":"+1 605 225 5114",
    "sg:postcode":"57401",
    "sg:province":"SD",
    "sg:tags":[
        "house"
    ],
    "wof:name":"Crompton Construction",
    "wof:placetype":"venue"
},
  "geometry": {"coordinates":[-98.46695,45.471626],"type":"Point"}
}