{
  "type": "Feature",
  "properties": {
    "iso:country":"US",
    "sg:address":"14698 State Hwy 15",
    "sg:city":"Milbank",
    "sg:classifiers":[
        {
            "category":"Farming",
            "subcategory":"Farm",
            "type":"Manufacturing & Wholesale Goods"
        },
        {
            "category":"Farming",
            "subcategory":"Farm & Veterinary Services",
            "type":"Manufacturing & Wholesale Goods"
        }
    ],
    "sg:phone":"+1 605 432 6030",
    "sg:postcode":"57252",
    "sg:province":"SD",
    "sg:tags":[
        "hog",
        "raise",
        "crop",
        "general",
        "seed",
        "grain",
        "cleaning"
    ],
    "wof:name":"Stengel Seed & Grain Co",
    "wof:placetype":"venue"
},
  "geometry": {"coordinates":[-96.63738,45.254177],"type":"Point"}
}