{
  "type": "Feature",
  "properties": {
    "addr:full":"1120 9th Ave SE Watertown SD 57201",
    "addr:housenumber":"1120",
    "addr:postcode":"57201",
    "addr:street":"9Th Ave Se",
    "iso:country":"US",
    "sg:address":"1120 9th Ave SE",
    "sg:city":"Watertown",
    "sg:classifiers":[
        {
            "category":"Banks & Credit Unions",
            "subcategory":"Bank",
            "type":"Services"
        }
    ],
    "sg:phone":"+1 605 882 8320",
    "sg:postcode":"57201",
    "sg:province":"SD",
    "wof:name":"First American Bank & Trust",
    "wof:placetype":"venue"
},
  "geometry": {"coordinates":[-97.09967399999999,44.889984],"type":"Point"}
}