{
  "type": "Feature",
  "properties": {
    "addr:full":"412 E Elm St Brandon SD 57005",
    "addr:housenumber":"412",
    "addr:postcode":"57005",
    "addr:street":"E Elm St",
    "iso:country":"US",
    "sg:address":"412 E Elm St",
    "sg:city":"Brandon",
    "sg:classifiers":[
        {
            "category":"Museum",
            "type":"Entertainment"
        }
    ],
    "sg:phone":"+1 605 582 5841",
    "sg:postcode":"57005",
    "sg:province":"SD",
    "wof:name":"Brandon Area Museum",
    "wof:placetype":"venue"
},
  "geometry": {"coordinates":[-96.586065,43.591662],"type":"Point"}
}