{
  "type": "Feature",
  "properties": {
    "iso:country":"US",
    "sg:address":"2908 E 26th St",
    "sg:city":"Sioux Falls",
    "sg:classifiers":[
        {
            "category":"Health Services",
            "subcategory":"Clinic",
            "type":"Services"
        }
    ],
    "sg:phone":"+1 605 335 3373",
    "sg:postcode":"57103",
    "sg:province":"SD",
    "sg:tags":[
        "home"
    ],
    "wof:name":"State Home Care Svc",
    "wof:placetype":"venue"
},
  "geometry": {"coordinates":[-96.687613,43.529367],"type":"Point"}
}