{
  "type": "Feature",
  "properties": {
    "iso:country":"US",
    "sg:address":"3900 S Southeastern Ave",
    "sg:city":"Sioux Falls",
    "sg:classifiers":[
        {
            "category":"Freight",
            "type":"Transportation"
        }
    ],
    "sg:phone":"+1 605 339 8844",
    "sg:postcode":"57103",
    "sg:province":"SD",
    "sg:tags":[
        "trucking"
    ],
    "wof:name":"Hatley Trucking",
    "wof:placetype":"venue"
},
  "geometry": {"coordinates":[-96.689266,43.509303],"type":"Point"}
}