{
  "type": "Feature",
  "properties": {
    "iso:country":"US",
    "sg:address":"1421 16th Ave SE",
    "sg:city":"Aberdeen",
    "sg:classifiers":[
        {
            "category":"Real Estate",
            "subcategory":"Real Estate Agent",
            "type":"Services"
        }
    ],
    "sg:phone":"+1 605 225 1949",
    "sg:postcode":"57401",
    "sg:province":"SD",
    "wof:name":"Jim Payne & Associates",
    "wof:placetype":"venue"
},
  "geometry": {"coordinates":[-98.466889,45.448812],"type":"Point"}
}