{
  "type": "Feature",
  "properties": {
    "addr:full":"1421 16th Ave SE Aberdeen SD 57401",
    "addr:housenumber":"1421",
    "addr:postcode":"57401",
    "addr:street":"16Th Ave Se",
    "iso:country":"US",
    "sg:address":"1421 16th Ave SE",
    "sg:city":"Aberdeen",
    "sg:classifiers":[
        {
            "category":"Real Estate",
            "subcategory":"Real Estate Agent",
            "type":"Services"
        }
    ],
    "sg:phone":"+1 605 225 1949",
    "sg:postcode":"57401",
    "sg:province":"SD",
    "wof:name":"Jim Payne & Associates",
    "wof:placetype":"venue"
},
  "geometry": {"coordinates":[-98.46688899999999,45.448812],"type":"Point"}
}