{
  "type": "Feature",
  "properties": {
    "addr:full":"440 Mount Rushmore Rd Rapid City SD 57701",
    "addr:housenumber":"440",
    "addr:postcode":"57701",
    "addr:street":"Mount Rushmore Rd",
    "iso:country":"US",
    "sg:address":"440 Mount Rushmore Rd",
    "sg:city":"Rapid City",
    "sg:classifiers":[
        {
            "category":"Professional",
            "subcategory":"Lawyer & Legal Services",
            "type":"Services"
        }
    ],
    "sg:phone":"+1 605 342 1078",
    "sg:postcode":"57701",
    "sg:province":"SD",
    "sg:tags":[
        "attorney"
    ],
    "sg:website":"www.gundersonpalmer.com",
    "wof:name":"Gunderson Palmer Goodsell",
    "wof:placetype":"venue"
},
  "geometry": {"coordinates":[-103.230519,44.082071],"type":"Point"}
}