{
  "type": "Feature",
  "properties": {
    "iso:country":"US",
    "sg:address":"4461 Cliff Dr",
    "sg:city":"Rapid City",
    "sg:classifiers":[
        {
            "category":"Organizations",
            "subcategory":"Religious Organization",
            "type":"Services"
        }
    ],
    "sg:phone":"+1 605 348 1669",
    "sg:postcode":"57702",
    "sg:province":"SD",
    "sg:tags":[
        "church"
    ],
    "sg:website":"www.mormon.org",
    "wof:name":"Church Of Jesus Christ Of Lds",
    "wof:placetype":"venue"
},
  "geometry": {"coordinates":[-103.289413,44.056059],"type":"Point"}
}