{
  "type": "Feature",
  "properties": {
    "addr:full":"120 S Kimball St Mitchell SD 57301",
    "addr:housenumber":"120",
    "addr:postcode":"57301",
    "addr:street":"S Kimball St",
    "iso:country":"US",
    "sg:address":"120 S Kimball St",
    "sg:city":"Mitchell",
    "sg:classifiers":[
        {
            "category":"Manufacturing",
            "subcategory":"Food",
            "type":"Manufacturing & Wholesale Goods"
        }
    ],
    "sg:phone":"+1 605 996 5633",
    "sg:postcode":"57301",
    "sg:province":"SD",
    "sg:tags":[
        "bottler"
    ],
    "wof:name":"Coca-Cola Bottling Co",
    "wof:placetype":"venue"
},
  "geometry": {"coordinates":[-98.022558,43.709268],"type":"Point"}
}