{
  "type": "Feature",
  "properties": {
    "iso:country":"US",
    "sg:address":"3109 W 41st St",
    "sg:city":"Sioux Falls",
    "sg:classifiers":[
        {
            "category":"Wholesale",
            "subcategory":"Medical Equipment & Supplies",
            "type":"Manufacturing & Wholesale Goods"
        },
        {
            "category":"Manufacturing",
            "subcategory":"Tools & Machinery",
            "type":"Manufacturing & Wholesale Goods"
        }
    ],
    "sg:phone":"+1 605 373 0264",
    "sg:postcode":"57105",
    "sg:province":"SD",
    "sg:tags":[
        "lens",
        "optical",
        "mfg"
    ],
    "wof:name":"Twin City Optical Co",
    "wof:placetype":"venue"
},
  "geometry": {"coordinates":[-96.761101,43.514824],"type":"Point"}
}