{
  "type": "Feature",
  "properties": {
    "iso:country":"US",
    "sg:address":"241 State Hwy 44",
    "sg:city":"Chancellor",
    "sg:classifiers":[
        {
            "category":"Retail",
            "subcategory":"Auto Repair",
            "type":"Services"
        }
    ],
    "sg:phone":"+1 605 647 5938",
    "sg:postcode":"57015",
    "sg:province":"SD",
    "sg:tags":[
        "repairing",
        "automobile"
    ],
    "wof:name":"Hostetler Repair LLC",
    "wof:placetype":"venue"
},
  "geometry": {"coordinates":[-96.98648799999999,43.37339],"type":"Point"}
}