{
  "type": "Feature",
  "properties": {
    "addr:full":"810 Kingswood Dr Rapid City SD 57702",
    "addr:housenumber":"810",
    "addr:postcode":"57702",
    "addr:street":"Kingswood Dr",
    "iso:country":"US",
    "sg:address":"810 Kingswood Dr",
    "sg:city":"Rapid City",
    "sg:classifiers":[
        {
            "category":"Building & Trades",
            "subcategory":"Landscaping Services",
            "type":"Services"
        }
    ],
    "sg:phone":"+1 605 343 3045",
    "sg:postcode":"57702",
    "sg:province":"SD",
    "sg:tags":[
        "tree"
    ],
    "wof:name":"Troy's Tree Stump Removal Svc",
    "wof:placetype":"venue"
},
  "geometry": {"coordinates":[-103.293374,44.09588],"type":"Point"}
}