{
  "type": "Feature",
  "properties": {
    "iso:country":"US",
    "sg:address":"111 S Main St",
    "sg:city":"Chamberlain",
    "sg:classifiers":[
        {
            "category":"Shopping",
            "subcategory":"Used Merchandise",
            "type":"Retail Goods"
        }
    ],
    "sg:phone":"+1 605 234 4159",
    "sg:postcode":"57325",
    "sg:province":"SD",
    "sg:tags":[
        "shop",
        "thrift"
    ],
    "wof:name":"St Joseph's Indian School Thri",
    "wof:placetype":"venue"
},
  "geometry": {"coordinates":[-99.330292,43.810714],"type":"Point"}
}