{
  "type": "Feature",
  "properties": {
    "addr:full":"159 N Ottowa St Iroquois SD 57353",
    "addr:housenumber":"159",
    "addr:postcode":"57353",
    "addr:street":"N Ottowa St",
    "iso:country":"US",
    "sg:address":"159 N Ottowa St",
    "sg:city":"Iroquois",
    "sg:classifiers":[
        {
            "category":"Freight",
            "type":"Transportation"
        }
    ],
    "sg:phone":"+1 605 546 2351",
    "sg:postcode":"57353",
    "sg:province":"SD",
    "sg:tags":[
        "frozen",
        "food",
        "locker",
        "plant"
    ],
    "wof:name":"Country Butcher Shop",
    "wof:placetype":"venue"
},
  "geometry": {"coordinates":[-97.849287,44.36968],"type":"Point"}
}