{
  "type": "Feature",
  "properties": {
    "iso:country":"US",
    "sg:address":"2223 Jackson Blvd",
    "sg:city":"Rapid City",
    "sg:classifiers":[
        {
            "category":"Autos & Motor Vehicles",
            "subcategory":"Fuel & Gas Station",
            "type":"Retail Goods"
        }
    ],
    "sg:phone":"+1 605 342 1876",
    "sg:postcode":"57702",
    "sg:province":"SD",
    "sg:tags":[
        "oil"
    ],
    "wof:name":"Doug's Sinclair",
    "wof:placetype":"venue"
},
  "geometry": {"coordinates":[-103.25999,44.070809],"type":"Point"}
}