{
  "type": "Feature",
  "properties": {
    "addr:full":"25450 436th Ave Salem SD 57058",
    "addr:housenumber":"25450",
    "addr:postcode":"57058",
    "addr:street":"436Th Ave",
    "iso:country":"US",
    "sg:address":"25450 436th Ave",
    "sg:city":"Salem",
    "sg:phone":"+1 605 425 2157",
    "sg:postcode":"57058",
    "sg:province":"SD",
    "sg:tags":[
        "farm",
        "grain",
        "cash"
    ],
    "wof:name":"Kurth Bedeane",
    "wof:placetype":"venue"
},
  "geometry": {"coordinates":[-97.48868400000001,43.691077],"type":"Point"}
}