{
  "type": "Feature",
  "properties": {
    "addr:full":"680 N Lacrosse St Rapid City SD 57701",
    "addr:housenumber":"680",
    "addr:postcode":"57701",
    "addr:street":"N Lacrosse St",
    "iso:country":"US",
    "sg:address":"680 N Lacrosse St",
    "sg:city":"Rapid City",
    "sg:classifiers":[
        {
            "category":"Utilities",
            "subcategory":"Mobile Phone",
            "type":"Services"
        }
    ],
    "sg:phone":"+1 605 343 3806",
    "sg:postcode":"57701",
    "sg:province":"SD",
    "sg:tags":[
        "telephone",
        "cellular"
    ],
    "wof:name":"Accessory Phone Ctr/Wirefree",
    "wof:placetype":"venue"
},
  "geometry": {"coordinates":[-103.201785,44.089521],"type":"Point"}
}