{
  "type": "Feature",
  "properties": {
    "addr:full":"44578 302nd St Volin SD 57072",
    "addr:housenumber":"44578",
    "addr:postcode":"57072",
    "addr:street":"302Nd St",
    "iso:country":"US",
    "sg:address":"44578 302nd St",
    "sg:city":"Volin",
    "sg:phone":"+1 605 263 3811",
    "sg:postcode":"57072",
    "sg:province":"SD",
    "sg:tags":[
        "farm",
        "grain",
        "cash"
    ],
    "wof:name":"Alan Morman",
    "wof:placetype":"venue"
},
  "geometry": {"coordinates":[-97.28558700000001,43.01049],"type":"Point"}
}