{
  "type": "Feature",
  "properties": {
    "addr:full":"43188 US Hwy 14 De Smet SD 57231",
    "addr:postcode":"43188;57231",
    "addr:street":"Us Hwy 14 De Smet",
    "iso:country":"US",
    "sg:address":"43188 US Hwy 14",
    "sg:city":"De Smet",
    "sg:classifiers":[
        {
            "category":"Autos & Motor Vehicles",
            "subcategory":"Automobile Sales",
            "type":"Retail Goods"
        }
    ],
    "sg:phone":"+1 605 854 9959",
    "sg:postcode":"57231",
    "sg:province":"SD",
    "sg:tags":[
        "car",
        "dealer"
    ],
    "wof:name":"Covered Wagon",
    "wof:placetype":"venue"
},
  "geometry": {"coordinates":[-97.584847,44.383216],"type":"Point"}
}