{
  "type": "Feature",
  "properties": {
    "addr:full":"38404 129th St Aberdeen SD 57401",
    "addr:housenumber":"38404",
    "addr:postcode":"57401",
    "addr:street":"129Th St",
    "iso:country":"US",
    "sg:address":"38404 129th St",
    "sg:city":"Aberdeen",
    "sg:classifiers":[
        {
            "category":"Autos & Motor Vehicles",
            "subcategory":"Automobile Sales",
            "type":"Retail Goods"
        }
    ],
    "sg:phone":"+1 605 229 5353",
    "sg:postcode":"57401",
    "sg:province":"SD",
    "sg:tags":[
        "sport",
        "trailer",
        "utility"
    ],
    "wof:name":"Bitz Equipment & Trailer Sales",
    "wof:placetype":"venue"
},
  "geometry": {"coordinates":[-98.536383,45.517655],"type":"Point"}
}