{
  "type": "Feature",
  "properties": {
    "iso:country":"US",
    "sg:address":"1734 6th St",
    "sg:city":"Brookings",
    "sg:classifiers":[
        {
            "category":"Shopping",
            "subcategory":"Florist",
            "type":"Retail Goods"
        }
    ],
    "sg:phone":"+1 605 697 1734",
    "sg:postcode":"57006",
    "sg:province":"SD",
    "wof:name":"Bloomingvilla",
    "wof:placetype":"venue"
},
  "geometry": {"coordinates":[-96.77619300000001,44.311311],"type":"Point"}
}