{
  "type": "Feature",
  "properties": {
    "addr:full":"1908 Broadway St Yankton SD 57078",
    "addr:housenumber":"1908",
    "addr:postcode":"57078",
    "addr:street":"Broadway St",
    "iso:country":"US",
    "sg:address":"1908 Broadway St",
    "sg:city":"Yankton",
    "sg:classifiers":[
        {
            "category":"Wholesale",
            "subcategory":"Electrical",
            "type":"Manufacturing & Wholesale Goods"
        }
    ],
    "sg:phone":"+1 605 665 1134",
    "sg:postcode":"57078",
    "sg:province":"SD",
    "sg:tags":[
        "communication",
        "radio",
        "system"
    ],
    "wof:name":"Tom's Two Way Radio Clinic",
    "wof:placetype":"venue"
},
  "geometry": {"coordinates":[-97.396637,42.888739],"type":"Point"}
}