{
  "type": "Feature",
  "properties": {
    "iso:country":"US",
    "sg:address":"15941 486th Ave",
    "sg:city":"Revillo",
    "sg:phone":"+1 605 623 4484",
    "sg:postcode":"57259",
    "sg:province":"SD",
    "sg:tags":[
        "corn",
        "soybean",
        "farmer"
    ],
    "wof:name":"Greg Wollschlager",
    "wof:placetype":"venue"
},
  "geometry": {"coordinates":[-96.4768,45.073993],"type":"Point"}
}