{
  "type": "Feature",
  "properties": {
    "iso:country":"US",
    "sg:address":"1089 Rand Rd",
    "sg:city":"Rapid City",
    "sg:classifiers":[
        {
            "category":"Building & Trades",
            "subcategory":"Construction",
            "type":"Services"
        },
        {
            "category":"Home & Garden",
            "subcategory":"Furniture",
            "type":"Retail Goods"
        }
    ],
    "sg:phone":"+1 605 343 8779",
    "sg:postcode":"57702",
    "sg:province":"SD",
    "sg:tags":[
        "cabinet",
        "carpentry",
        "contractor"
    ],
    "wof:name":"Prang's Custom Woodwork",
    "wof:placetype":"venue"
},
  "geometry": {"coordinates":[-103.2621,44.094879],"type":"Point"}
}