{
  "type": "Feature",
  "properties": {
    "iso:country":"US",
    "sg:address":"700 W Community Dr",
    "sg:city":"Flandreau",
    "sg:classifiers":[
        {
            "category":"Education",
            "subcategory":"School",
            "type":"Public Place"
        }
    ],
    "sg:phone":"+1 605 997 2705",
    "sg:postcode":"57028",
    "sg:province":"SD",
    "wof:name":"Flandreau Middle School",
    "wof:placetype":"venue"
},
  "geometry": {"coordinates":[-96.605916,44.051246],"type":"Point"}
}