{
  "type": "Feature",
  "properties": {
    "iso:country":"US",
    "sg:address":"8074 5th St",
    "sg:city":"Bowdle",
    "sg:classifiers":[
        {
            "category":"Organizations",
            "subcategory":"Religious Organization",
            "type":"Services"
        }
    ],
    "sg:phone":"+1 605 285 6379",
    "sg:postcode":"57428",
    "sg:province":"SD",
    "sg:tags":[
        "church"
    ],
    "sg:website":"www.clclutheran.org",
    "wof:name":"Redeemer Lutheran Church",
    "wof:placetype":"venue"
},
  "geometry": {"coordinates":[-99.662328,45.44854],"type":"Point"}
}