{
  "type": "Feature",
  "properties": {
    "iso:country":"US",
    "sg:address":"205 Wallace Ave S",
    "sg:city":"Wessington Spgs",
    "sg:classifiers":[
        {
            "category":"Government",
            "subcategory":"Police Station",
            "type":"Public Place"
        }
    ],
    "sg:phone":"+1 605 539 1311",
    "sg:postcode":"57382",
    "sg:province":"SD",
    "sg:tags":[
        "sheriff"
    ],
    "wof:name":"Jerauld County Sheriff",
    "wof:placetype":"venue"
},
  "geometry": {"coordinates":[-98.56954,44.078332],"type":"Point"}
}