{
  "type": "Feature",
  "properties": {
    "iso:country":"US",
    "sg:address":"2405 S Royal Ct",
    "sg:city":"Sioux Falls",
    "sg:classifiers":[
        {
            "category":"Building & Trades",
            "subcategory":"Construction",
            "type":"Services"
        }
    ],
    "sg:phone":"+1 605 333 0060",
    "sg:postcode":"57106",
    "sg:province":"SD",
    "sg:tags":[
        "carpentry",
        "contractor"
    ],
    "sg:website":"www.kitchensolvers.com",
    "wof:name":"Kitchen Solvers",
    "wof:placetype":"venue"
},
  "geometry": {"coordinates":[-96.796545,43.522559],"type":"Point"}
}