{
  "type": "Feature",
  "properties": {
    "iso:country":"US",
    "sg:address":"411 Walnut St",
    "sg:city":"Piedmont",
    "sg:classifiers":[
        {
            "category":"Organizations",
            "subcategory":"Religious Organization",
            "type":"Services"
        }
    ],
    "sg:phone":"+1 605 787 4086",
    "sg:postcode":"57769",
    "sg:province":"SD",
    "wof:name":"Grace United Methodist Church",
    "wof:placetype":"venue"
},
  "geometry": {"coordinates":[-103.392315,44.231336],"type":"Point"}
}