{
  "type": "Feature",
  "properties": {
    "iso:country":"US",
    "sg:address":"626 S Mc Coy St",
    "sg:city":"Aberdeen",
    "sg:classifiers":[
        {
            "category":"Retail",
            "subcategory":"Repair Shop",
            "type":"Services"
        },
        {
            "category":"Shopping",
            "subcategory":"Bicycles & Sporting Goods",
            "type":"Retail Goods"
        }
    ],
    "sg:phone":"+1 605 225 5596",
    "sg:postcode":"57401",
    "sg:province":"SD",
    "sg:tags":[
        "taxidermist"
    ],
    "wof:name":"Roger's Taxidermy Studio",
    "wof:placetype":"venue"
},
  "geometry": {"coordinates":[-98.461772,45.458742],"type":"Point"}
}