{
  "type": "Feature",
  "properties": {
    "addr:full":"44056 298th St Irene SD 57037",
    "addr:housenumber":"44056",
    "addr:postcode":"57037",
    "addr:street":"298Th St",
    "iso:country":"US",
    "sg:address":"44056 298th St",
    "sg:city":"Irene",
    "sg:phone":"+1 605 263 3778",
    "sg:postcode":"57037",
    "sg:province":"SD",
    "sg:tags":[
        "beef",
        "farm",
        "corn",
        "soybean",
        "cattle",
        "feedlot"
    ],
    "wof:name":"James Sees",
    "wof:placetype":"venue"
},
  "geometry": {"coordinates":[-97.397621,43.068149],"type":"Point"}
}