{
  "type": "Feature",
  "properties": {
    "iso:country":"US",
    "sg:address":"525 Belair Dr",
    "sg:city":"Custer",
    "sg:classifiers":[
        {
            "category":"Professional",
            "subcategory":"Management & Consulting",
            "type":"Services"
        }
    ],
    "sg:phone":"+1 605 673 3601",
    "sg:postcode":"57730",
    "sg:province":"SD",
    "sg:tags":[
        "environmental"
    ],
    "wof:name":"Sandvig Consulting",
    "wof:placetype":"venue"
},
  "geometry": {"coordinates":[-103.610595,43.770839],"type":"Point"}
}