{
  "type": "Feature",
  "properties": {
    "addr:full":"707 Baltimore Ave Hot Springs SD 57747",
    "addr:housenumber":"707",
    "addr:postcode":"57747",
    "addr:street":"Baltimore Ave",
    "iso:country":"US",
    "sg:address":"707 Baltimore Ave",
    "sg:city":"Hot Springs",
    "sg:classifiers":[
        {
            "category":"Building & Trades",
            "subcategory":"Plumbing",
            "type":"Services"
        }
    ],
    "sg:phone":"+1 605 745 7774",
    "sg:postcode":"57747",
    "sg:province":"SD",
    "sg:tags":[
        "conditioning",
        "air",
        "system",
        "contractor"
    ],
    "wof:name":"Flint Electric Heating & AC",
    "wof:placetype":"venue"
},
  "geometry": {"coordinates":[-103.47367,43.429115],"type":"Point"}
}