{
  "type": "Feature",
  "properties": {
    "iso:country":"US",
    "sg:address":"43833 238th St",
    "sg:city":"Howard",
    "sg:classifiers":[
        {
            "category":"Farming",
            "subcategory":"Livestock Farm",
            "type":"Manufacturing & Wholesale Goods"
        }
    ],
    "sg:phone":"+1 605 772 5703",
    "sg:postcode":"57349",
    "sg:province":"SD",
    "sg:tags":[
        "beef",
        "feedlot",
        "cattle"
    ],
    "wof:name":"Powell Orrin",
    "wof:placetype":"venue"
},
  "geometry": {"coordinates":[-97.442553,43.93556],"type":"Point"}
}