{
  "type": "Feature",
  "properties": {
    "iso:country":"US",
    "sg:address":"27535 460th Ave",
    "sg:city":"Chancellor",
    "sg:classifiers":[
        {
            "category":"Retail",
            "subcategory":"Repair Shop",
            "type":"Services"
        }
    ],
    "sg:phone":"+1 605 647 5766",
    "sg:postcode":"57015",
    "sg:province":"SD",
    "wof:name":"Sasker Repair",
    "wof:placetype":"venue"
},
  "geometry": {"coordinates":[-97.004077,43.397321],"type":"Point"}
}