{
  "type": "Feature",
  "properties": {
    "addr:full":"5300 W 12th St Sioux Falls SD 57107",
    "addr:housenumber":"5300",
    "addr:postcode":"57107",
    "addr:street":"W 12Th St",
    "iso:country":"US",
    "sg:address":"5300 W 12th St",
    "sg:city":"Sioux Falls",
    "sg:classifiers":[
        {
            "category":"Wholesale",
            "subcategory":"Petroleum",
            "type":"Manufacturing & Wholesale Goods"
        }
    ],
    "sg:phone":"+1 605 338 3521",
    "sg:postcode":"57107",
    "sg:province":"SD",
    "sg:tags":[
        "pipe",
        "line",
        "company"
    ],
    "wof:name":"Magellan Pipe Line Co",
    "wof:placetype":"venue"
},
  "geometry": {"coordinates":[-96.79340000000001,43.5439],"type":"Point"}
}