{
  "type": "Feature",
  "properties": {
    "addr:full":"11818 425th Ave Langford SD 57454",
    "addr:housenumber":"11818",
    "addr:postcode":"57454",
    "addr:street":"425Th Ave",
    "iso:country":"US",
    "sg:address":"11818 425th Ave",
    "sg:city":"Langford",
    "sg:phone":"+1 605 493 6692",
    "sg:postcode":"57454",
    "sg:province":"SD",
    "sg:tags":[
        "farm",
        "wheat"
    ],
    "wof:name":"Bernice Planteen",
    "wof:placetype":"venue"
},
  "geometry": {"coordinates":[-97.71059,45.645972],"type":"Point"}
}