{
  "type": "Feature",
  "properties": {
    "iso:country":"US",
    "sg:address":"11 S Maple",
    "sg:city":"Watertown",
    "sg:classifiers":[
        {
            "category":"Travel",
            "subcategory":"Travel Agent",
            "type":"Entertainment"
        }
    ],
    "sg:phone":"+1 605 886 6220",
    "sg:postcode":"57201",
    "sg:province":"SD",
    "sg:tags":[
        "agency"
    ],
    "wof:name":"Watertowns First Choice Travel",
    "wof:placetype":"venue"
},
  "geometry": {"coordinates":[-97.112982,44.900019],"type":"Point"}
}