{
  "type": "Feature",
  "properties": {
    "iso:country":"US",
    "sg:address":"21881 449th Ave",
    "sg:city":"Oldham",
    "sg:classifiers":[
        {
            "category":"Retail",
            "subcategory":"Repair Shop",
            "type":"Services"
        }
    ],
    "sg:phone":"+1 605 482 8404",
    "sg:postcode":"57051",
    "sg:province":"SD",
    "wof:name":"Schneiders Tractor Repair",
    "wof:placetype":"venue"
},
  "geometry": {"coordinates":[-97.230295,44.210405],"type":"Point"}
}