{
  "type": "Feature",
  "properties": {
    "addr:full":"12724 Old Hill City Rd Hill City SD 57745",
    "addr:housenumber":"12724",
    "addr:postcode":"57745",
    "addr:street":"City Rd",
    "iso:country":"US",
    "sg:address":"12724 Old Hill City Rd",
    "sg:city":"Hill City",
    "sg:classifiers":[
        {
            "category":"Building & Trades",
            "subcategory":"Plumbing",
            "type":"Services"
        }
    ],
    "sg:phone":"+1 605 348 9754",
    "sg:postcode":"57745",
    "sg:province":"SD",
    "sg:tags":[
        "plumbing",
        "contractor"
    ],
    "wof:name":"Hills Plumbing & Heating",
    "wof:placetype":"venue"
},
  "geometry": {"coordinates":[-103.514242,43.920842],"type":"Point"}
}