{
  "type": "Feature",
  "properties": {
    "iso:country":"US",
    "sg:address":"112 2nd St",
    "sg:city":"Wagner",
    "sg:classifiers":[
        {
            "category":"Professional",
            "subcategory":"Lawyer & Legal Services",
            "type":"Services"
        }
    ],
    "sg:phone":"+1 605 384 5970",
    "sg:postcode":"57380",
    "sg:province":"SD",
    "sg:tags":[
        "attorney"
    ],
    "wof:name":"Bruce Anderson",
    "wof:placetype":"venue"
},
  "geometry": {"coordinates":[-98.29351200000001,43.079864],"type":"Point"}
}