{
  "type": "Feature",
  "properties": {
    "iso:country":"US",
    "sg:address":"47449 276th St",
    "sg:city":"Worthing",
    "sg:classifiers":[
        {
            "category":"Real Estate",
            "subcategory":"Real Estate Operator",
            "type":"Services"
        }
    ],
    "sg:phone":"+1 605 743 2101",
    "sg:postcode":"57077",
    "sg:province":"SD",
    "sg:tags":[
        "property",
        "lessor"
    ],
    "wof:name":"Leslie Schuer",
    "wof:placetype":"venue"
},
  "geometry": {"coordinates":[-96.717485,43.388078],"type":"Point"}
}