{
  "type": "Feature",
  "properties": {
    "addr:full":"719 N Main St Aberdeen SD 57401",
    "addr:housenumber":"719",
    "addr:postcode":"57401",
    "addr:street":"N Main St",
    "iso:country":"US",
    "sg:address":"719 N Main St",
    "sg:city":"Aberdeen",
    "sg:classifiers":[
        {
            "category":"Autos & Motor Vehicles",
            "subcategory":"Fuel & Gas Station",
            "type":"Retail Goods"
        }
    ],
    "sg:phone":"+1 605 225 2455",
    "sg:postcode":"57401",
    "sg:province":"SD",
    "sg:tags":[
        "gasoline",
        "grocery",
        "station",
        "eating"
    ],
    "wof:name":"Scottys Drive Inn",
    "wof:placetype":"venue"
},
  "geometry": {"coordinates":[-98.48818900000001,45.473602],"type":"Point"}
}