{
  "type": "Feature",
  "properties": {
    "addr:full":"523 E Capitol Ave Pierre SD 57501",
    "addr:housenumber":"523",
    "addr:postcode":"57501",
    "addr:street":"E Capitol Ave",
    "iso:country":"US",
    "sg:address":"523 E Capitol Ave",
    "sg:city":"Pierre",
    "sg:classifiers":[
        {
            "category":"Government",
            "subcategory":"Office",
            "type":"Public Place"
        }
    ],
    "sg:phone":"+1 605 773 3405",
    "sg:postcode":"57501",
    "sg:province":"SD",
    "wof:name":"Purchasing and Printing",
    "wof:placetype":"venue"
},
  "geometry": {"coordinates":[-100.346728,44.36583],"type":"Point"}
}