{
  "type": "Feature",
  "properties": {
    "iso:country":"US",
    "sg:address":"1500 W 22nd St",
    "sg:city":"Sioux Falls",
    "sg:classifiers":[
        {
            "category":"Health Services",
            "subcategory":"Doctor",
            "type":"Services"
        }
    ],
    "sg:phone":"+1 605 328 4600",
    "sg:postcode":"57105",
    "sg:province":"SD",
    "sg:tags":[
        "physician",
        "surgeon"
    ],
    "wof:name":"SVC Maternal Fetal Medicine",
    "wof:placetype":"venue"
},
  "geometry": {"coordinates":[-96.745003,43.533044],"type":"Point"}
}