{
  "type": "Feature",
  "properties": {
    "addr:full":"505 W Sweetbriar Pl Sioux Falls SD 57108",
    "addr:housenumber":"505",
    "addr:postcode":"57108",
    "addr:street":"W Sweetbriar Pl",
    "iso:country":"US",
    "sg:address":"505 W Sweetbriar Pl",
    "sg:city":"Sioux Falls",
    "sg:classifiers":[
        {
            "category":"Real Estate",
            "subcategory":"Real Estate Operator",
            "type":"Services"
        }
    ],
    "sg:phone":"+1 605 332 8492",
    "sg:postcode":"57108",
    "sg:province":"SD",
    "sg:tags":[
        "building",
        "nonresidential"
    ],
    "wof:name":"Sorrell Properties LLC",
    "wof:placetype":"venue"
},
  "geometry": {"coordinates":[-96.73010600000001,43.498204],"type":"Point"}
}