{
  "type": "Feature",
  "properties": {
    "iso:country":"US",
    "sg:address":"38846 124th St",
    "sg:city":"Aberdeen",
    "sg:classifiers":[
        {
            "category":"Building & Trades",
            "subcategory":"Construction",
            "type":"Services"
        }
    ],
    "sg:phone":"+1 605 225 7203",
    "sg:postcode":"57401",
    "sg:province":"SD",
    "sg:tags":[
        "nonresidential"
    ],
    "wof:name":"Trins Construction Inc",
    "wof:placetype":"venue"
},
  "geometry": {"coordinates":[-98.46716000000001,45.589727],"type":"Point"}
}