{
  "type": "Feature",
  "properties": {
    "iso:country":"US",
    "sg:address":"4320 S Louise Ave",
    "sg:city":"Sioux Falls",
    "sg:classifiers":[
        {
            "category":"Professional",
            "subcategory":"Employment Agencies",
            "type":"Services"
        }
    ],
    "sg:phone":"+1 605 271 5627",
    "sg:postcode":"57106",
    "sg:province":"SD",
    "sg:tags":[
        "opportunity"
    ],
    "wof:name":"Employment Edge",
    "wof:placetype":"venue"
},
  "geometry": {"coordinates":[-96.770949,43.506854],"type":"Point"}
}