{
  "type": "Feature",
  "properties": {
    "iso:country":"US",
    "sg:address":"5 S Broadway St",
    "sg:city":"Columbia",
    "sg:classifiers":[
        {
            "category":"Government",
            "subcategory":"Post Office",
            "type":"Public Place"
        }
    ],
    "sg:phone":"+1 605 396 2664",
    "sg:postcode":"57433",
    "sg:province":"SD",
    "sg:tags":[
        "postal",
        "us"
    ],
    "wof:name":"US Post Office",
    "wof:placetype":"venue"
},
  "geometry": {"coordinates":[-98.311207,45.610753],"type":"Point"}
}