{
  "type": "Feature",
  "properties": {
    "addr:full":"275 Lincoln Ave SW Huron SD 57350",
    "addr:housenumber":"275",
    "addr:postcode":"57350",
    "addr:street":"Lincoln Ave Sw",
    "iso:country":"US",
    "sg:address":"275 Lincoln Ave SW",
    "sg:city":"Huron",
    "sg:classifiers":[
        {
            "category":"Food & Beverages",
            "subcategory":"Groceries & Convenience Stores",
            "type":"Retail Goods"
        }
    ],
    "sg:phone":"+1 605 352 5086",
    "sg:postcode":"57350",
    "sg:province":"SD",
    "wof:name":"D & S Mini-Mart",
    "wof:placetype":"venue"
},
  "geometry": {"coordinates":[-98.23447400000001,44.363625],"type":"Point"}
}