{
  "type": "Feature",
  "properties": {
    "iso:country":"US",
    "sg:address":"505 3rd St",
    "sg:city":"Garretson",
    "sg:classifiers":[
        {
            "category":"Utilities",
            "subcategory":"Fuel Oil & Lpg",
            "type":"Services"
        }
    ],
    "sg:phone":"+1 605 594 3495",
    "sg:postcode":"57030",
    "sg:province":"SD",
    "sg:tags":[
        "liquefied",
        "gas",
        "petroleum"
    ],
    "wof:name":"Ferrellgas L P",
    "wof:placetype":"venue"
},
  "geometry": {"coordinates":[-96.502774,43.716031],"type":"Point"}
}