{
  "type": "Feature",
  "properties": {
    "iso:country":"US",
    "sg:address":"615 E 8th St",
    "sg:city":"Sioux Falls",
    "sg:phone":"+1 605 336 3337",
    "sg:postcode":"57103",
    "sg:province":"SD",
    "sg:tags":[
        "oil"
    ],
    "wof:name":"Midwest Oil Co",
    "wof:placetype":"venue"
},
  "geometry": {"coordinates":[-96.718627,43.548558],"type":"Point"}
}