{
  "type": "Feature",
  "properties": {
    "iso:country":"US",
    "sg:address":"12202 Aviation Way",
    "sg:city":"Custer",
    "sg:classifiers":[
        {
            "category":"Government",
            "subcategory":"Office",
            "type":"Public Place"
        }
    ],
    "sg:phone":"+1 605 673 4892",
    "sg:postcode":"57730",
    "sg:province":"SD",
    "sg:tags":[
        "federal",
        "program"
    ],
    "sg:website":"www.usda.gov",
    "wof:name":"US Agricultural Dept",
    "wof:placetype":"venue"
},
  "geometry": {"coordinates":[-103.610205,43.731128],"type":"Point"}
}