{
  "type": "Feature",
  "properties": {
    "iso:country":"US",
    "sg:address":"1609 S Rustin St",
    "sg:city":"Sioux City",
    "sg:phone":"+1 712 276 4402",
    "sg:postcode":"51106",
    "sg:province":"SD",
    "sg:tags":[
        "farm",
        "corn"
    ],
    "wof:name":"Duane Conkey",
    "wof:placetype":"venue"
},
  "geometry": {"coordinates":[-96.371662,42.473744],"type":"Point"}
}