{
  "type": "Feature",
  "properties": {
    "iso:country":"US",
    "sg:address":"1020 S Rainbow Rd",
    "sg:city":"Spearfish",
    "sg:classifiers":[
        {
            "category":"Professional",
            "subcategory":"Accounting & Tax Preparation",
            "type":"Services"
        }
    ],
    "sg:phone":"+1 605 644 1012",
    "sg:postcode":"57783",
    "sg:province":"SD",
    "wof:name":"Letters Ledgers",
    "wof:placetype":"venue"
},
  "geometry": {"coordinates":[-103.769746,44.462586],"type":"Point"}
}