{
  "type": "Feature",
  "properties": {
    "iso:country":"US",
    "sg:address":"620 W 18th St",
    "sg:city":"Sioux Falls",
    "sg:classifiers":[
        {
            "category":"Social Services",
            "type":"Services"
        }
    ],
    "sg:phone":"+1 605 731 2000",
    "sg:postcode":"57104",
    "sg:province":"SD",
    "wof:name":"Lutheran Social Services",
    "wof:placetype":"venue"
},
  "geometry": {"coordinates":[-96.734801,43.53676],"type":"Point"}
}