{
  "type": "Feature",
  "properties": {
    "iso:country":"US",
    "sg:address":"31377 454th Ave",
    "sg:city":"Meckling",
    "sg:classifiers":[
        {
            "category":"Farming",
            "subcategory":"Farm",
            "type":"Manufacturing & Wholesale Goods"
        }
    ],
    "sg:phone":"+1 605 624 6797",
    "sg:postcode":"57069",
    "sg:province":"SD",
    "sg:tags":[
        "crop",
        "general"
    ],
    "wof:name":"Three W J Farms",
    "wof:placetype":"venue"
},
  "geometry": {"coordinates":[-97.121858,42.840133],"type":"Point"}
}