{
  "type": "Feature",
  "properties": {
    "iso:country":"US",
    "sg:address":"13218 331st Ave",
    "sg:city":"Bowdle",
    "sg:classifiers":[
        {
            "category":"Farming",
            "subcategory":"Farm",
            "type":"Manufacturing & Wholesale Goods"
        }
    ],
    "sg:phone":"+1 605 285 6337",
    "sg:postcode":"57428",
    "sg:province":"SD",
    "sg:tags":[
        "crop",
        "general"
    ],
    "wof:name":"Oscar & Judith Huber",
    "wof:placetype":"venue"
},
  "geometry": {"coordinates":[-99.543752,45.475589],"type":"Point"}
}