{
  "type": "Feature",
  "properties": {
    "addr:full":"122 N Main St Aberdeen SD 57401",
    "addr:housenumber":"122",
    "addr:postcode":"57401",
    "addr:street":"N Main St",
    "iso:country":"US",
    "sg:address":"122 N Main St",
    "sg:city":"Aberdeen",
    "sg:classifiers":[
        {
            "category":"Shopping",
            "subcategory":"Florist",
            "type":"Retail Goods"
        }
    ],
    "sg:phone":"+1 605 229 0000",
    "sg:postcode":"57401",
    "sg:province":"SD",
    "sg:tags":[
        "floral",
        "shop"
    ],
    "wof:name":"Annette's Floral Boutique",
    "wof:placetype":"venue"
},
  "geometry": {"coordinates":[-98.488045,45.467477],"type":"Point"}
}