{
  "type": "Feature",
  "properties": {
    "addr:full":"357 Main St Hill City SD 57745",
    "addr:housenumber":"357",
    "addr:postcode":"57745",
    "addr:street":"Main St",
    "iso:country":"US",
    "sg:address":"357 Main St",
    "sg:city":"Hill City",
    "sg:classifiers":[
        {
            "category":"Restaurant",
            "type":"Food & Drink"
        }
    ],
    "sg:phone":"+1 605 574 2423",
    "sg:postcode":"57745",
    "sg:province":"SD",
    "sg:tags":[
        "parlor",
        "ice",
        "cream"
    ],
    "wof:name":"Pauline's Ice Cream Parlor",
    "wof:placetype":"venue"
},
  "geometry": {"coordinates":[-103.575587,43.931655],"type":"Point"}
}