{
  "type": "Feature",
  "properties": {
    "iso:country":"US",
    "sg:address":"46710 262nd St",
    "sg:city":"Sioux Falls",
    "sg:phone":"+1 605 332 3598",
    "sg:postcode":"57107",
    "sg:province":"SD",
    "sg:tags":[
        "farm",
        "corn",
        "soybean"
    ],
    "wof:name":"Mabel Bowden",
    "wof:placetype":"venue"
},
  "geometry": {"coordinates":[-96.865026,43.587096],"type":"Point"}
}