{
  "type": "Feature",
  "properties": {
    "iso:country":"US",
    "sg:address":"312 4th St W",
    "sg:city":"Clear Lake",
    "sg:classifiers":[
        {
            "category":"Utilities",
            "subcategory":"Telephone",
            "type":"Services"
        }
    ],
    "sg:phone":"+1 605 874 2181",
    "sg:postcode":"57226",
    "sg:province":"SD",
    "sg:tags":[
        "company"
    ],
    "sg:website":"www.itc-web.com",
    "wof:name":"Interstate Telecommunication",
    "wof:placetype":"venue"
},
  "geometry": {"coordinates":[-96.683158,44.755682],"type":"Point"}
}