{
  "type": "Feature",
  "properties": {
    "addr:full":"1000 S Stoakes Ave Sioux Falls SD 57110",
    "addr:housenumber":"1000",
    "addr:postcode":"57110",
    "addr:street":"S Stoakes Ave",
    "iso:country":"US",
    "sg:address":"1000 S Stoakes Ave",
    "sg:city":"Sioux Falls",
    "sg:classifiers":[
        {
            "category":"Retail",
            "subcategory":"Auto Repair",
            "type":"Services"
        }
    ],
    "sg:phone":"+1 605 331 6003",
    "sg:postcode":"57110",
    "sg:province":"SD",
    "sg:tags":[
        "shop",
        "automobile",
        "machine",
        "general"
    ],
    "wof:name":"Automotive Machine and Repair",
    "wof:placetype":"venue"
},
  "geometry": {"coordinates":[-96.637957,43.537376],"type":"Point"}
}