{
  "type": "Feature",
  "properties": {
    "iso:country":"US",
    "sg:address":"289 Dakota Ave S",
    "sg:city":"Huron",
    "sg:classifiers":[
        {
            "category":"Manufacturing",
            "subcategory":"Printing",
            "type":"Manufacturing & Wholesale Goods"
        }
    ],
    "sg:phone":"+1 605 352 8801",
    "sg:postcode":"57350",
    "sg:province":"SD",
    "sg:tags":[
        "screen"
    ],
    "wof:name":"Prints-R-Us",
    "wof:placetype":"venue"
},
  "geometry": {"coordinates":[-98.214207,44.363367],"type":"Point"}
}