{
  "type": "Feature",
  "properties": {
    "iso:country":"US",
    "sg:address":"5511 W 12th St",
    "sg:city":"Sioux Falls",
    "sg:classifiers":[
        {
            "category":"Retail",
            "subcategory":"Auto Repair",
            "type":"Services"
        }
    ],
    "sg:phone":"+1 605 271 1550",
    "sg:postcode":"57106",
    "sg:province":"SD",
    "sg:tags":[
        "glass",
        "coating",
        "tinting"
    ],
    "wof:name":"Gray Shady's Tint Co",
    "wof:placetype":"venue"
},
  "geometry": {"coordinates":[-96.790914,43.543903],"type":"Point"}
}