{
  "type": "Feature",
  "properties": {
    "iso:country":"US",
    "sg:address":"244 N Main St",
    "sg:city":"Salem",
    "sg:classifiers":[
        {
            "category":"Home & Garden",
            "subcategory":"Hardware",
            "type":"Retail Goods"
        }
    ],
    "sg:phone":"+1 605 425 3123",
    "sg:postcode":"57058",
    "sg:province":"SD",
    "wof:name":"Zapp Hardware",
    "wof:placetype":"venue"
},
  "geometry": {"coordinates":[-97.387422,43.725968],"type":"Point"}
}