{
  "type": "Feature",
  "properties": {
    "iso:country":"US",
    "sg:address":"46038 190th St",
    "sg:city":"Castlewood",
    "sg:classifiers":[
        {
            "category":"Farming",
            "subcategory":"Livestock Farm",
            "type":"Manufacturing & Wholesale Goods"
        }
    ],
    "sg:phone":"+1 605 873 2865",
    "sg:postcode":"57223",
    "sg:province":"SD",
    "sg:tags":[
        "animal",
        "crop",
        "general"
    ],
    "wof:name":"Lyle R Poppen",
    "wof:placetype":"venue"
},
  "geometry": {"coordinates":[-96.994192,44.630428],"type":"Point"}
}