{
  "type": "Feature",
  "properties": {
    "iso:country":"US",
    "sg:address":"101 Industrial Dr",
    "sg:city":"Volga",
    "sg:classifiers":[
        {
            "category":"Freight",
            "type":"Transportation"
        }
    ],
    "sg:phone":"+1 605 627 9907",
    "sg:postcode":"57032",
    "sg:province":"SD",
    "sg:tags":[
        "trucking"
    ],
    "sg:website":"www.landoflakes.com",
    "wof:name":"Northwest Food Prods Trnsprtn",
    "wof:placetype":"venue"
},
  "geometry": {"coordinates":[-96.70424,43.441698],"type":"Point"}
}