{
  "type": "Feature",
  "properties": {
    "addr:full":"129 N Main Ave Colman SD 57017",
    "addr:housenumber":"129",
    "addr:postcode":"57017",
    "addr:street":"N Main Ave",
    "iso:country":"US",
    "sg:address":"129 N Main Ave",
    "sg:city":"Colman",
    "sg:classifiers":[
        {
            "category":"Government",
            "subcategory":"Post Office",
            "type":"Public Place"
        }
    ],
    "sg:phone":"+1 605 534 3521",
    "sg:postcode":"57017",
    "sg:province":"SD",
    "wof:name":"US Post Office",
    "wof:placetype":"venue"
},
  "geometry": {"coordinates":[-96.81407,43.983686],"type":"Point"}
}