{
  "type": "Feature",
  "properties": {
    "iso:country":"US",
    "sg:address":"23625 Tigerville Rd",
    "sg:city":"Hill City",
    "sg:classifiers":[
        {
            "category":"Building & Trades",
            "subcategory":"Landscaping Services",
            "type":"Services"
        }
    ],
    "sg:phone":"+1 605 574 4287",
    "sg:postcode":"57745",
    "sg:province":"SD",
    "sg:tags":[
        "lawn",
        "maintenance",
        "grounds"
    ],
    "wof:name":"Prochem Vegitation Mgmt",
    "wof:placetype":"venue"
},
  "geometry": {"coordinates":[-103.643387,43.981857],"type":"Point"}
}