{
  "type": "Feature",
  "properties": {
    "iso:country":"US",
    "sg:address":"18418 390th Ave",
    "sg:city":"Hitchcock",
    "sg:classifiers":[
        {
            "category":"Farming",
            "subcategory":"Dairy Farm",
            "type":"Manufacturing & Wholesale Goods"
        }
    ],
    "sg:phone":"+1 605 266 2858",
    "sg:postcode":"57348",
    "sg:province":"SD",
    "wof:name":"Makin Milk Dairy",
    "wof:placetype":"venue"
},
  "geometry": {"coordinates":[-98.422542,44.711995],"type":"Point"}
}