{
  "type": "Feature",
  "properties": {
    "iso:country":"US",
    "sg:address":"101 W Holly Blvd",
    "sg:city":"Brandon",
    "sg:classifiers":[
        {
            "category":"Autos & Motor Vehicles",
            "subcategory":"Fuel & Gas Station",
            "type":"Retail Goods"
        },
        {
            "category":"Restaurant",
            "type":"Food & Drink"
        },
        {
            "category":"Food & Beverages",
            "subcategory":"Groceries & Convenience Stores",
            "type":"Retail Goods"
        }
    ],
    "sg:phone":"+1 605 582 6678",
    "sg:postcode":"57005",
    "sg:province":"SD",
    "sg:tags":[
        "pizza"
    ],
    "sg:website":"http://caseys.com",
    "wof:name":"Casey's General Store",
    "wof:placetype":"venue"
},
  "geometry": {"coordinates":[-96.591888,43.594662],"type":"Point"}
}