{
  "type": "Feature",
  "properties": {
    "iso:country":"US",
    "sg:address":"4610 S Technopolis Dr",
    "sg:city":"Sioux Falls",
    "sg:classifiers":[
        {
            "category":"Professional",
            "subcategory":"Computer Services",
            "type":"Services"
        }
    ],
    "sg:phone":"+1 605 361 2119",
    "sg:postcode":"57106",
    "sg:province":"SD",
    "sg:tags":[
        "internet"
    ],
    "wof:name":"Amerion",
    "wof:placetype":"venue"
},
  "geometry": {"coordinates":[-96.774638,43.501899],"type":"Point"}
}