{
  "type": "Feature",
  "properties": {
    "iso:country":"US",
    "sg:address":"45774 314th St",
    "sg:city":"Meckling",
    "sg:phone":"+1 605 624 3786",
    "sg:postcode":"57069",
    "sg:province":"SD",
    "sg:tags":[
        "farm",
        "field",
        "corn",
        "soybean",
        "crop"
    ],
    "wof:name":"Warren Olson",
    "wof:placetype":"venue"
},
  "geometry": {"coordinates":[-97.04292700000001,42.837273],"type":"Point"}
}