{
  "type": "Feature",
  "properties": {
    "addr:full":"27948 455th Ave Parker SD 57053",
    "addr:housenumber":"27948",
    "addr:postcode":"57053",
    "addr:street":"455Th Ave",
    "iso:country":"US",
    "sg:address":"27948 455th Ave",
    "sg:city":"Parker",
    "sg:classifiers":[
        {
            "category":"Organizations",
            "subcategory":"Religious Organization",
            "type":"Services"
        }
    ],
    "sg:phone":"+1 605 368 2258",
    "sg:postcode":"57053",
    "sg:province":"SD",
    "sg:tags":[
        "church"
    ],
    "wof:name":"Grace Baptist Church",
    "wof:placetype":"venue"
},
  "geometry": {"coordinates":[-97.103842,43.336858],"type":"Point"}
}