{
  "type": "Feature",
  "properties": {
    "addr:full":"1100 S Euclid Ave Sioux Falls SD 57105",
    "addr:housenumber":"1100",
    "addr:postcode":"57105",
    "addr:street":"S Euclid Ave",
    "iso:country":"US",
    "sg:address":"1100 S Euclid Ave",
    "sg:city":"Sioux Falls",
    "sg:classifiers":[
        {
            "category":"Government",
            "subcategory":"Office",
            "type":"Public Place"
        }
    ],
    "sg:phone":"+1 605 336 6711",
    "sg:postcode":"57105",
    "sg:province":"SD",
    "sg:tags":[
        "village"
    ],
    "wof:name":"Hartford Ambulance",
    "wof:placetype":"venue"
},
  "geometry": {"coordinates":[-96.742368,43.535874],"type":"Point"}
}