{
  "type": "Feature",
  "properties": {
    "iso:country":"US",
    "sg:address":"311 Main St",
    "sg:city":"Platte",
    "sg:classifiers":[
        {
            "category":"Restaurant",
            "type":"Food & Drink"
        }
    ],
    "sg:phone":"+1 605 337 2580",
    "sg:postcode":"57369",
    "sg:province":"SD",
    "wof:name":"Barrister",
    "wof:placetype":"venue"
},
  "geometry": {"coordinates":[-98.84468200000001,43.38807],"type":"Point"}
}