{
  "type": "Feature",
  "properties": {
    "iso:country":"US",
    "sg:address":"410 N Henry St",
    "sg:city":"Tripp",
    "sg:classifiers":[
        {
            "category":"Bars & Pubs",
            "type":"Food & Drink"
        }
    ],
    "sg:phone":"+1 605 935 6862",
    "sg:postcode":"57376",
    "sg:province":"SD",
    "sg:tags":[
        "drinking"
    ],
    "wof:name":"Idle Hour Theatre Co Inc",
    "wof:placetype":"venue"
},
  "geometry": {"coordinates":[-97.967787,43.228522],"type":"Point"}
}