{
  "type": "Feature",
  "properties": {
    "iso:country":"US",
    "sg:address":"8601 E Saddle Creek Rd",
    "sg:city":"Sioux Falls",
    "sg:classifiers":[
        {
            "category":"Professional",
            "subcategory":"Engineering",
            "type":"Services"
        }
    ],
    "sg:phone":"+1 605 582 3149",
    "sg:postcode":"57110",
    "sg:province":"SD",
    "sg:tags":[
        "engineer"
    ],
    "wof:name":"Stangohr & Stangohr",
    "wof:placetype":"venue"
},
  "geometry": {"coordinates":[-96.619057,43.562419],"type":"Point"}
}