{
  "type": "Feature",
  "properties": {
    "addr:full":"304 E 31st St Sioux Falls SD 57105",
    "addr:housenumber":"304",
    "addr:postcode":"57105",
    "addr:street":"E 31St St",
    "iso:country":"US",
    "sg:address":"304 E 31st St",
    "sg:city":"Sioux Falls",
    "sg:classifiers":[
        {
            "category":"Professional",
            "subcategory":"Computer Services",
            "type":"Services"
        }
    ],
    "sg:phone":"+1 605 335 8706",
    "sg:postcode":"57105",
    "sg:province":"SD",
    "sg:tags":[
        "programing",
        "custom"
    ],
    "wof:name":"Fitzgrald Solutionsd Group Inc",
    "wof:placetype":"venue"
},
  "geometry": {"coordinates":[-96.722431,43.524444],"type":"Point"}
}