{
  "type": "Feature",
  "properties": {
    "iso:country":"US",
    "sg:address":"1305 W 18th St",
    "sg:city":"Sioux Falls",
    "sg:classifiers":[
        {
            "category":"Health Services",
            "subcategory":"Doctor",
            "type":"Services"
        }
    ],
    "sg:phone":"+1 605 333 6543",
    "sg:postcode":"57105",
    "sg:province":"SD",
    "sg:tags":[
        "physician",
        "surgeon"
    ],
    "wof:name":"Same Day Surgery",
    "wof:placetype":"venue"
},
  "geometry": {"coordinates":[-96.744949,43.536605],"type":"Point"}
}