{
  "type": "Feature",
  "properties": {
    "addr:full":"15083 Bixby Rd Bison SD 57620",
    "addr:housenumber":"15083",
    "addr:postcode":"57620",
    "addr:street":"Bixby Rd",
    "iso:country":"US",
    "sg:address":"15083 Bixby Rd",
    "sg:city":"Bison",
    "sg:classifiers":[
        {
            "category":"Farming",
            "subcategory":"Livestock Farm",
            "type":"Manufacturing & Wholesale Goods"
        }
    ],
    "sg:phone":"+1 605 244 7410",
    "sg:postcode":"57620",
    "sg:province":"SD",
    "sg:tags":[
        "beef",
        "feedlot",
        "cattle"
    ],
    "wof:name":"Mike Fisher Jr",
    "wof:placetype":"venue"
},
  "geometry": {"coordinates":[-102.570097,45.291558],"type":"Point"}
}