{
  "type": "Feature",
  "properties": {
    "iso:country":"US",
    "sg:address":"6009 W 41st St",
    "sg:city":"Sioux Falls",
    "sg:classifiers":[
        {
            "category":"Real Estate",
            "subcategory":"Real Estate Agent",
            "type":"Services"
        }
    ],
    "sg:phone":"+1 605 361 2960",
    "sg:postcode":"57106",
    "sg:province":"SD",
    "wof:name":"M Realty",
    "wof:placetype":"venue"
},
  "geometry": {"coordinates":[-96.802428,43.514812],"type":"Point"}
}