{
  "type": "Feature",
  "properties": {
    "iso:country":"US",
    "sg:address":"1400 Main St",
    "sg:city":"Webster",
    "sg:classifiers":[
        {
            "category":"Retail",
            "subcategory":"Auto Rental",
            "type":"Services"
        }
    ],
    "sg:phone":"+1 605 345 3013",
    "sg:postcode":"57274",
    "sg:province":"SD",
    "sg:tags":[
        "truck"
    ],
    "wof:name":"Freddies Auto Parts",
    "wof:placetype":"venue"
},
  "geometry": {"coordinates":[-97.519977,45.340072],"type":"Point"}
}