{
  "type": "Feature",
  "properties": {
    "addr:full":"305 Maple St W Sisseton SD 57262",
    "addr:housenumber":"305",
    "addr:postcode":"57262",
    "addr:street":"Maple St W",
    "iso:country":"US",
    "sg:address":"305 Maple St W",
    "sg:city":"Sisseton",
    "sg:classifiers":[
        {
            "category":"Education",
            "subcategory":"Library",
            "type":"Public Place"
        }
    ],
    "sg:phone":"+1 605 698 7391",
    "sg:postcode":"57262",
    "sg:province":"SD",
    "wof:name":"Sisseton Library",
    "wof:placetype":"venue"
},
  "geometry": {"coordinates":[-97.05482600000001,45.663775],"type":"Point"}
}