{
  "type": "Feature",
  "properties": {
    "iso:country":"US",
    "sg:address":"209 E Pleasant Dr",
    "sg:city":"Pierre",
    "sg:classifiers":[
        {
            "category":"Home & Garden",
            "subcategory":"Household Appliances",
            "type":"Retail Goods"
        }
    ],
    "sg:phone":"+1 605 945 4324",
    "sg:postcode":"57501",
    "sg:province":"SD",
    "sg:tags":[
        "cleaners",
        "vacuum"
    ],
    "wof:name":"Rocky Mountain Air -S Dk",
    "wof:placetype":"venue"
},
  "geometry": {"coordinates":[-100.351626,44.367443],"type":"Point"}
}