{
  "type": "Feature",
  "properties": {
    "iso:country":"US",
    "sg:address":"29885 310th Ave",
    "sg:city":"Winner",
    "sg:classifiers":[
        {
            "category":"Retail",
            "subcategory":"Repair Shop",
            "type":"Services"
        }
    ],
    "sg:phone":"+1 605 557 3282",
    "sg:postcode":"57580",
    "sg:province":"SD",
    "sg:tags":[
        "related"
    ],
    "wof:name":"A & A Repair Aaron Davis",
    "wof:placetype":"venue"
},
  "geometry": {"coordinates":[-99.968797,43.069747],"type":"Point"}
}