{
  "type": "Feature",
  "properties": {
    "iso:country":"US",
    "sg:address":"26150 451st Ave",
    "sg:city":"Canistota",
    "sg:classifiers":[
        {
            "category":"Wholesale",
            "subcategory":"Machinery & Supplies",
            "type":"Manufacturing & Wholesale Goods"
        }
    ],
    "sg:phone":"+1 605 296 3612",
    "sg:postcode":"57012",
    "sg:province":"SD",
    "sg:tags":[
        "farm",
        "equipment"
    ],
    "wof:name":"Koehn Implement",
    "wof:placetype":"venue"
},
  "geometry": {"coordinates":[-97.188433,43.594296],"type":"Point"}
}