{
  "type": "Feature",
  "properties": {
    "iso:country":"US",
    "sg:address":"2919 Jolly Ln",
    "sg:city":"Rapid City",
    "sg:classifiers":[
        {
            "category":"Personal",
            "subcategory":"Beauty Salon",
            "type":"Services"
        }
    ],
    "sg:phone":"+1 605 393 2396",
    "sg:postcode":"57703",
    "sg:province":"SD",
    "sg:tags":[
        "treatment",
        "skin"
    ],
    "wof:name":"XOXO Skin Care",
    "wof:placetype":"venue"
},
  "geometry": {"coordinates":[-103.151477,44.057749],"type":"Point"}
}