{
  "type": "Feature",
  "properties": {
    "addr:full":"508 Main St Platte SD 57369",
    "addr:housenumber":"508",
    "addr:postcode":"57369",
    "addr:street":"Main St",
    "iso:country":"US",
    "sg:address":"508 Main St",
    "sg:city":"Platte",
    "sg:classifiers":[
        {
            "category":"Social Services",
            "type":"Services"
        }
    ],
    "sg:phone":"+1 605 337 2265",
    "sg:postcode":"57369",
    "sg:province":"SD",
    "sg:tags":[
        "senior",
        "citizen"
    ],
    "wof:name":"Senior Citizen Ctr",
    "wof:placetype":"venue"
},
  "geometry": {"coordinates":[-98.84482199999999,43.386088],"type":"Point"}
}