{
  "type": "Feature",
  "properties": {
    "iso:country":"US",
    "sg:address":"131 N Main St",
    "sg:city":"Forestburg",
    "sg:classifiers":[
        {
            "category":"Bars & Pubs",
            "type":"Food & Drink"
        }
    ],
    "sg:phone":"+1 605 495 4141",
    "sg:postcode":"57314",
    "sg:province":"SD",
    "wof:name":"John Doren",
    "wof:placetype":"venue"
},
  "geometry": {"coordinates":[-97.921425,44.007691],"type":"Point"}
}