{
  "type": "Feature",
  "properties": {
    "addr:full":"170 S Main St Parker SD 57053",
    "addr:housenumber":"170",
    "addr:postcode":"57053",
    "addr:street":"S Main St",
    "iso:country":"US",
    "sg:address":"170 S Main St",
    "sg:city":"Parker",
    "sg:classifiers":[
        {
            "category":"Professional",
            "subcategory":"Research",
            "type":"Services"
        }
    ],
    "sg:phone":"+1 605 297 4305",
    "sg:postcode":"57053",
    "sg:province":"SD",
    "sg:tags":[
        "economic",
        "analysis"
    ],
    "wof:name":"Parker Development Corp",
    "wof:placetype":"venue"
},
  "geometry": {"coordinates":[-97.136591,43.395968],"type":"Point"}
}