{
  "type": "Feature",
  "properties": {
    "iso:country":"US",
    "sg:address":"713 9th Ave SE",
    "sg:city":"Watertown",
    "sg:classifiers":[
        {
            "category":"Shopping",
            "type":"Retail Goods"
        }
    ],
    "sg:phone":"+1 605 886 6686",
    "sg:postcode":"57201",
    "sg:province":"SD",
    "sg:tags":[
        "communication",
        "radiotelephone",
        "merchandise"
    ],
    "wof:name":"Cell Phone Superstore",
    "wof:placetype":"venue"
},
  "geometry": {"coordinates":[-97.106517,44.890156],"type":"Point"}
}