{
  "type": "Feature",
  "properties": {
    "iso:country":"US",
    "sg:address":"410 2nd Ave SE",
    "sg:city":"Clark",
    "sg:classifiers":[
        {
            "category":"Organizations",
            "subcategory":"Religious Organization",
            "type":"Services"
        }
    ],
    "sg:phone":"+1 605 532 3762",
    "sg:postcode":"57225",
    "sg:province":"SD",
    "sg:tags":[
        "church"
    ],
    "wof:name":"Plymouth Congregational Church",
    "wof:placetype":"venue"
},
  "geometry": {"coordinates":[-97.730456,44.875908],"type":"Point"}
}