{
  "type": "Feature",
  "properties": {
    "iso:country":"US",
    "sg:address":"15 W Main St",
    "sg:city":"Vermillion",
    "sg:classifiers":[
        {
            "category":"Shopping",
            "subcategory":"Jewelry",
            "type":"Retail Goods"
        }
    ],
    "sg:phone":"+1 605 624 3811",
    "sg:postcode":"57069",
    "sg:province":"SD",
    "sg:tags":[
        "jeweler"
    ],
    "wof:name":"Dallas Jewelry",
    "wof:placetype":"venue"
},
  "geometry": {"coordinates":[-96.932272,42.779477],"type":"Point"}
}