{
  "type": "Feature",
  "properties": {
    "iso:country":"US",
    "sg:address":"40962 218th St",
    "sg:city":"Cavour",
    "sg:phone":"+1 605 599 2946",
    "sg:postcode":"57324",
    "sg:province":"SD",
    "sg:tags":[
        "farm",
        "field",
        "crop"
    ],
    "wof:name":"Carl Matter",
    "wof:placetype":"venue"
},
  "geometry": {"coordinates":[-98.02081,44.224077],"type":"Point"}
}