{
  "type": "Feature",
  "properties": {
    "addr:full":"1004 6th St Florence SD 57235",
    "addr:housenumber":"1004",
    "addr:postcode":"57235",
    "addr:street":"6Th St",
    "iso:country":"US",
    "sg:address":"1004 6th St",
    "sg:city":"Florence",
    "sg:classifiers":[
        {
            "category":"Social Services",
            "subcategory":"Adult Care",
            "type":"Services"
        },
        {
            "category":"Banks & Credit Unions",
            "subcategory":"Bank",
            "type":"Services"
        }
    ],
    "sg:phone":"+1 605 758 2050",
    "sg:postcode":"57235",
    "sg:province":"SD",
    "sg:tags":[
        "home",
        "broker",
        "mortgage",
        "residential"
    ],
    "wof:name":"Country View Assisted Living",
    "wof:placetype":"venue"
},
  "geometry": {"coordinates":[-97.33098099999999,45.059063],"type":"Point"}
}