{
  "type": "Feature",
  "properties": {
    "addr:full":"3209 S Louise Ave Sioux Falls SD 57106",
    "addr:housenumber":"3209",
    "addr:postcode":"57106",
    "addr:street":"S Louise Ave",
    "iso:country":"US",
    "sg:address":"3209 S Louise Ave",
    "sg:city":"Sioux Falls",
    "sg:classifiers":[
        {
            "category":"Retail",
            "subcategory":"Portrait Studio",
            "type":"Services"
        }
    ],
    "sg:phone":"+1 605 362 8742",
    "sg:postcode":"57106",
    "sg:province":"SD",
    "sg:tags":[
        "photo"
    ],
    "wof:name":"PCA International LLC",
    "wof:placetype":"venue"
},
  "geometry": {"coordinates":[-96.77109799999999,43.518189],"type":"Point"}
}