{
  "type": "Feature",
  "properties": {
    "iso:country":"US",
    "sg:address":"2400 S Bahnson Ave",
    "sg:city":"Sioux Falls",
    "sg:classifiers":[
        {
            "category":"Education",
            "subcategory":"School",
            "type":"Public Place"
        }
    ],
    "sg:phone":"+1 605 371 4120",
    "sg:postcode":"57103",
    "sg:province":"SD",
    "sg:website":"www.sf.k12.sd.us",
    "wof:name":"Harvey Dunn Elementary School",
    "wof:placetype":"venue"
},
  "geometry": {"coordinates":[-96.681367,43.522473],"type":"Point"}
}