{
  "type": "Feature",
  "properties": {
    "iso:country":"US",
    "sg:address":"918 8th Ave NE",
    "sg:city":"Aberdeen",
    "sg:classifiers":[
        {
            "category":"Manufacturing",
            "subcategory":"Retail Goods",
            "type":"Manufacturing & Wholesale Goods"
        }
    ],
    "sg:phone":"+1 605 225 5489",
    "sg:postcode":"57401",
    "sg:province":"SD",
    "sg:tags":[
        "rubber",
        "stamp",
        "same",
        "mfg"
    ],
    "wof:name":"Midwest Rubber Stamp Co",
    "wof:placetype":"venue"
},
  "geometry": {"coordinates":[-98.473348,45.473647],"type":"Point"}
}