{
  "type": "Feature",
  "properties": {
    "iso:country":"US",
    "sg:address":"1270 Territorial Rd",
    "sg:city":"Madison",
    "sg:classifiers":[
        {
            "category":"Building & Trades",
            "subcategory":"Plumbing",
            "type":"Services"
        }
    ],
    "sg:phone":"+1 605 256 6284",
    "sg:postcode":"57042",
    "sg:province":"SD",
    "sg:tags":[
        "contractor"
    ],
    "wof:name":"Andys Plumbing & Heating Inc",
    "wof:placetype":"venue"
},
  "geometry": {"coordinates":[-97.17025099999999,44.001649],"type":"Point"}
}