{
  "type": "Feature",
  "properties": {
    "iso:country":"US",
    "sg:address":"27261 470th Ave",
    "sg:city":"Tea",
    "sg:phone":"+1 605 368 2421",
    "sg:postcode":"57064",
    "sg:province":"SD",
    "sg:tags":[
        "farm",
        "corn",
        "soybean"
    ],
    "wof:name":"Gordon Bergjord",
    "wof:placetype":"venue"
},
  "geometry": {"coordinates":[-96.806349,43.43754],"type":"Point"}
}