{
  "type": "Feature",
  "properties": {
    "addr:full":"110 E Main St Vermillion SD 57069",
    "addr:housenumber":"110",
    "addr:postcode":"57069",
    "addr:street":"E Main St",
    "iso:country":"US",
    "sg:address":"110 E Main St",
    "sg:city":"Vermillion",
    "sg:classifiers":[
        {
            "category":"Health Services",
            "subcategory":"Hospital",
            "type":"Services"
        }
    ],
    "sg:phone":"+1 605 624 9307",
    "sg:postcode":"57069",
    "sg:province":"SD",
    "sg:tags":[
        "mental"
    ],
    "wof:name":"Psychological Services",
    "wof:placetype":"venue"
},
  "geometry": {"coordinates":[-96.930471,42.779484],"type":"Point"}
}