{
  "type": "Feature",
  "properties": {
    "iso:country":"US",
    "sg:address":"842 Lincoln St",
    "sg:city":"Burke",
    "sg:classifiers":[
        {
            "category":"Organizations",
            "subcategory":"Religious Organization",
            "type":"Services"
        }
    ],
    "sg:phone":"+1 605 775 2592",
    "sg:postcode":"57523",
    "sg:province":"SD",
    "sg:tags":[
        "church"
    ],
    "wof:name":"Union Baptist Church",
    "wof:placetype":"venue"
},
  "geometry": {"coordinates":[-99.289329,43.181948],"type":"Point"}
}