{
  "type": "Feature",
  "properties": {
    "iso:country":"US",
    "sg:address":"601 4th St S",
    "sg:city":"Brookings",
    "sg:classifiers":[
        {
            "category":"Professional",
            "subcategory":"Lawyer & Legal Services",
            "type":"Services"
        }
    ],
    "sg:phone":"+1 605 692 2883",
    "sg:postcode":"57006",
    "sg:province":"SD",
    "sg:tags":[
        "attorney"
    ],
    "wof:name":"Wieczorek Law Offices",
    "wof:placetype":"venue"
},
  "geometry": {"coordinates":[-96.795273,44.302004],"type":"Point"}
}