{
  "type": "Feature",
  "properties": {
    "iso:country":"US",
    "sg:address":"16460 437th Ave",
    "sg:city":"Henry",
    "sg:classifiers":[
        {
            "category":"Farming",
            "subcategory":"Livestock Farm",
            "type":"Manufacturing & Wholesale Goods"
        }
    ],
    "sg:phone":"+1 605 758 2236",
    "sg:postcode":"57243",
    "sg:province":"SD",
    "sg:tags":[
        "feedlot",
        "grain",
        "cash",
        "beef",
        "cattle"
    ],
    "wof:name":"Wayne Blashill",
    "wof:placetype":"venue"
},
  "geometry": {"coordinates":[-97.473552,44.998226],"type":"Point"}
}