{
  "type": "Feature",
  "properties": {
    "iso:country":"US",
    "sg:address":"2003 Red Dale Dr",
    "sg:city":"Rapid City",
    "sg:classifiers":[
        {
            "category":"Wholesale",
            "subcategory":"Machinery & Supplies",
            "type":"Manufacturing & Wholesale Goods"
        }
    ],
    "sg:phone":"+1 605 391 8119",
    "sg:postcode":"57702",
    "sg:province":"SD",
    "sg:tags":[
        "equipment"
    ],
    "wof:name":"K/Wt Distributing",
    "wof:placetype":"venue"
},
  "geometry": {"coordinates":[-103.288263,44.064882],"type":"Point"}
}