{
  "type": "Feature",
  "properties": {
    "addr:full":"510 N Cambell St Rapid City SD 57701",
    "addr:housenumber":"510",
    "addr:postcode":"57701",
    "addr:street":"N Cambell St",
    "iso:country":"US",
    "sg:address":"510 N Cambell St",
    "sg:city":"Rapid City",
    "sg:classifiers":[
        {
            "category":"Government",
            "subcategory":"Office",
            "type":"Public Place"
        }
    ],
    "sg:phone":"+1 605 394 2434",
    "sg:postcode":"57701",
    "sg:province":"SD",
    "sg:tags":[
        "state",
        "resource"
    ],
    "wof:name":"Social Service Dept",
    "wof:placetype":"venue"
},
  "geometry": {"coordinates":[-103.191607,44.086114],"type":"Point"}
}