{
  "type": "Feature",
  "properties": {
    "addr:full":"511 W Cedar St Beresford SD 57004",
    "addr:housenumber":"511",
    "addr:postcode":"57004",
    "addr:street":"W Cedar St",
    "iso:country":"US",
    "sg:address":"511 W Cedar St",
    "sg:city":"Beresford",
    "sg:classifiers":[
        {
            "category":"Farming",
            "subcategory":"Farm",
            "type":"Manufacturing & Wholesale Goods"
        }
    ],
    "sg:phone":"+1 605 763 2669",
    "sg:postcode":"57004",
    "sg:province":"SD",
    "sg:tags":[
        "crop",
        "general"
    ],
    "wof:name":"Jeff Norling",
    "wof:placetype":"venue"
},
  "geometry": {"coordinates":[-96.780681,43.083598],"type":"Point"}
}