{
  "type": "Feature",
  "properties": {
    "iso:country":"US",
    "sg:address":"406 S Lyndale Ave",
    "sg:city":"Sioux Falls",
    "sg:classifiers":[
        {
            "category":"Real Estate",
            "subcategory":"Architect",
            "type":"Services"
        },
        {
            "category":"Building & Trades",
            "subcategory":"Construction",
            "type":"Services"
        }
    ],
    "sg:phone":"+1 605 335 1751",
    "sg:postcode":"57104",
    "sg:province":"SD",
    "sg:tags":[
        "concrete",
        "work"
    ],
    "wof:name":"Backhaus Construction Inc",
    "wof:placetype":"venue"
},
  "geometry": {"coordinates":[-96.753524,43.542255],"type":"Point"}
}