{
  "type": "Feature",
  "properties": {
    "iso:country":"US",
    "sg:address":"6700 W 9th St",
    "sg:city":"Sioux Falls",
    "sg:classifiers":[
        {
            "category":"Freight",
            "type":"Transportation"
        }
    ],
    "sg:phone":"+1 605 334 9543",
    "sg:postcode":"57107",
    "sg:province":"SD",
    "sg:tags":[
        "operator",
        "local",
        "trucking"
    ],
    "wof:name":"Hanisch Milk Hauling Inc",
    "wof:placetype":"venue"
},
  "geometry": {"coordinates":[-96.81061099999999,43.547453],"type":"Point"}
}