{
  "type": "Feature",
  "properties": {
    "iso:country":"US",
    "sg:address":"46754 271st St",
    "sg:city":"Tea",
    "sg:classifiers":[
        {
            "category":"Real Estate",
            "subcategory":"Real Estate Operator",
            "type":"Services"
        }
    ],
    "sg:phone":"+1 605 368 2410",
    "sg:postcode":"57064",
    "sg:province":"SD",
    "sg:tags":[
        "property",
        "lessor"
    ],
    "wof:name":"Lee Hofer",
    "wof:placetype":"venue"
},
  "geometry": {"coordinates":[-96.854585,43.461104],"type":"Point"}
}