{
  "type": "Feature",
  "properties": {
    "iso:country":"US",
    "sg:address":"27121 469th Ave",
    "sg:city":"Tea",
    "sg:classifiers":[
        {
            "category":"Wholesale",
            "subcategory":"Construction Materials",
            "type":"Manufacturing & Wholesale Goods"
        }
    ],
    "sg:phone":"+1 605 498 8004",
    "sg:postcode":"57064",
    "sg:province":"SD",
    "sg:tags":[
        "building"
    ],
    "sg:website":"www.gruen-wald.com",
    "wof:name":"Gruen-Wald Engineered Laminate",
    "wof:placetype":"venue"
},
  "geometry": {"coordinates":[-96.826359,43.458265],"type":"Point"}
}