{
  "type": "Feature",
  "properties": {
    "addr:full":"50 7th St SE Huron SD 57350",
    "addr:housenumber":"50",
    "addr:postcode":"57350",
    "addr:street":"7Th St Se",
    "iso:country":"US",
    "sg:address":"50 7th St SE",
    "sg:city":"Huron",
    "sg:classifiers":[
        {
            "category":"Health Services",
            "subcategory":"Nursing And Care Facility",
            "type":"Services"
        }
    ],
    "sg:phone":"+1 605 352 8533",
    "sg:postcode":"57350",
    "sg:province":"SD",
    "sg:tags":[
        "home",
        "convalescent"
    ],
    "wof:name":"Violet Tschetter Memorial Home",
    "wof:placetype":"venue"
},
  "geometry": {"coordinates":[-98.213285,44.358459],"type":"Point"}
}