{
  "type": "Feature",
  "properties": {
    "iso:country":"US",
    "sg:address":"405 Humphrey Dr",
    "sg:city":"Doland",
    "sg:classifiers":[
        {
            "category":"Education",
            "subcategory":"School",
            "type":"Public Place"
        }
    ],
    "sg:phone":"+1 605 635 6241",
    "sg:postcode":"57436",
    "sg:province":"SD",
    "wof:name":"Doland Schools",
    "wof:placetype":"venue"
},
  "geometry": {"coordinates":[-98.101708,44.8981],"type":"Point"}
}