{
  "type": "Feature",
  "properties": {
    "iso:country":"US",
    "sg:address":"123 W 3rd St",
    "sg:city":"Miller",
    "sg:classifiers":[
        {
            "category":"Sports & Exercise",
            "subcategory":"Bowling",
            "type":"Entertainment"
        }
    ],
    "sg:phone":"+1 605 853 3721",
    "sg:postcode":"57362",
    "sg:province":"SD",
    "sg:tags":[
        "center"
    ],
    "wof:name":"Coral Lanes",
    "wof:placetype":"venue"
},
  "geometry": {"coordinates":[-98.989975,44.518348],"type":"Point"}
}