{
  "type": "Feature",
  "properties": {
    "addr:full":"1420 E 4th Ave Mitchell SD 57301",
    "addr:housenumber":"1420",
    "addr:postcode":"57301",
    "addr:street":"E 4Th Ave",
    "iso:country":"US",
    "sg:address":"1420 E 4th Ave",
    "sg:city":"Mitchell",
    "sg:classifiers":[
        {
            "category":"Organizations",
            "subcategory":"Religious Organization",
            "type":"Services"
        }
    ],
    "sg:phone":"+1 605 996 1935",
    "sg:postcode":"57301",
    "sg:province":"SD",
    "sg:tags":[
        "monastery",
        "convent"
    ],
    "wof:name":"Presentation Sisters",
    "wof:placetype":"venue"
},
  "geometry": {"coordinates":[-98.005725,43.712795],"type":"Point"}
}