{
  "type": "Feature",
  "properties": {
    "addr:full":"505 W 4th St Dell Rapids SD 57022",
    "addr:housenumber":"505",
    "addr:postcode":"57022",
    "addr:street":"W 4Th St",
    "iso:country":"US",
    "sg:address":"505 W 4th St",
    "sg:city":"Dell Rapids",
    "sg:classifiers":[
        {
            "category":"Real Estate",
            "subcategory":"Real Estate Agent",
            "type":"Services"
        }
    ],
    "sg:phone":"+1 605 428 3909",
    "sg:postcode":"57022",
    "sg:province":"SD",
    "wof:name":"Landmark Realty",
    "wof:placetype":"venue"
},
  "geometry": {"coordinates":[-96.727009,43.823443],"type":"Point"}
}