{
  "type": "Feature",
  "properties": {
    "iso:country":"US",
    "sg:address":"3447 Sturgis Rd",
    "sg:city":"Rapid City",
    "sg:classifiers":[
        {
            "category":"Manufacturing",
            "subcategory":"Jewelry",
            "type":"Manufacturing & Wholesale Goods"
        }
    ],
    "sg:phone":"+1 605 348 8108",
    "sg:postcode":"57702",
    "sg:province":"SD",
    "sg:tags":[
        "mfg"
    ],
    "wof:name":"Black Hills Gold & Silver",
    "wof:placetype":"venue"
},
  "geometry": {"coordinates":[-103.278414,44.085312],"type":"Point"}
}