{
  "type": "Feature",
  "properties": {
    "iso:country":"US",
    "sg:address":"2301 Broadway St",
    "sg:city":"Yankton",
    "sg:classifiers":[
        {
            "category":"Restaurant",
            "type":"Food & Drink"
        }
    ],
    "sg:phone":"+1 605 665 6200",
    "sg:postcode":"57078",
    "sg:province":"SD",
    "wof:name":"Mc Donald's",
    "wof:placetype":"venue"
},
  "geometry": {"coordinates":[-97.397536,42.897931],"type":"Point"}
}