{
  "type": "Feature",
  "properties": {
    "iso:country":"US",
    "sg:address":"27334 356th Ave",
    "sg:city":"Platte",
    "sg:phone":"+1 605 337 3682",
    "sg:postcode":"57369",
    "sg:province":"SD",
    "sg:tags":[
        "farm",
        "corn",
        "beef",
        "feedlot",
        "cattle"
    ],
    "wof:name":"L Qualm & Sons Inc",
    "wof:placetype":"venue"
},
  "geometry": {"coordinates":[-99.062522,43.422093],"type":"Point"}
}