{
  "type": "Feature",
  "properties": {
    "iso:country":"US",
    "sg:address":"14545 400th Ave",
    "sg:city":"Stratford",
    "sg:classifiers":[
        {
            "category":"Retail",
            "subcategory":"Repair Shop",
            "type":"Services"
        }
    ],
    "sg:phone":"+1 605 395 6451",
    "sg:postcode":"57474",
    "sg:province":"SD",
    "wof:name":"Taxidermy Man",
    "wof:placetype":"venue"
},
  "geometry": {"coordinates":[-98.227749,45.27793],"type":"Point"}
}