{
  "type": "Feature",
  "properties": {
    "iso:country":"US",
    "sg:address":"720 6th Ave SW",
    "sg:city":"Aberdeen",
    "sg:classifiers":[
        {
            "category":"Retail",
            "subcategory":"Car Wash",
            "type":"Services"
        }
    ],
    "sg:phone":"+1 605 225 6898",
    "sg:postcode":"57401",
    "sg:province":"SD",
    "sg:tags":[
        "polishing",
        "washing"
    ],
    "wof:name":"Suds & Cars",
    "wof:placetype":"venue"
},
  "geometry": {"coordinates":[-98.49930000000001,45.459509],"type":"Point"}
}