{
  "type": "Feature",
  "properties": {
    "iso:country":"US",
    "sg:address":"28870 394th Ave",
    "sg:city":"Armour",
    "sg:phone":"+1 605 384 5130",
    "sg:postcode":"57313",
    "sg:province":"SD",
    "sg:tags":[
        "farm",
        "grain",
        "cash",
        "soybean"
    ],
    "wof:name":"Mark Wiechmann",
    "wof:placetype":"venue"
},
  "geometry": {"coordinates":[-98.307419,43.202171],"type":"Point"}
}