{
  "type": "Feature",
  "properties": {
    "addr:full":"645 Century Rd Rapid City SD 57701",
    "addr:housenumber":"645",
    "addr:postcode":"57701",
    "addr:street":"Century Rd",
    "iso:country":"US",
    "sg:address":"645 Century Rd",
    "sg:city":"Rapid City",
    "sg:classifiers":[
        {
            "category":"Retail",
            "subcategory":"Auto Repair",
            "type":"Services"
        }
    ],
    "sg:phone":"+1 605 342 7800",
    "sg:postcode":"57701",
    "sg:province":"SD",
    "sg:tags":[
        "transmission"
    ],
    "sg:website":"www.aamco.com",
    "wof:name":"AAMCO Transmissions",
    "wof:placetype":"venue"
},
  "geometry": {"coordinates":[-103.188855,44.09484],"type":"Point"}
}