{
  "type": "Feature",
  "properties": {
    "addr:full":"1501 N Main St Mitchell SD 57301",
    "addr:housenumber":"1501",
    "addr:postcode":"57301",
    "addr:street":"N Main St",
    "iso:country":"US",
    "sg:address":"1501 N Main St",
    "sg:city":"Mitchell",
    "sg:classifiers":[
        {
            "category":"Health Services",
            "subcategory":"Chiropractor",
            "type":"Services"
        }
    ],
    "sg:phone":"+1 605 996 4202",
    "sg:postcode":"57301",
    "sg:province":"SD",
    "wof:name":"South Dakota Chiropractor",
    "wof:placetype":"venue"
},
  "geometry": {"coordinates":[-98.02580500000001,43.725736],"type":"Point"}
}