{
  "type": "Feature",
  "properties": {
    "addr:full":"320 W Main St Wessington Spgs SD 57382",
    "addr:housenumber":"320",
    "addr:postcode":"57382",
    "addr:street":"W Main St",
    "iso:country":"US",
    "sg:address":"320 W Main St",
    "sg:city":"Wessington Spgs",
    "sg:classifiers":[
        {
            "category":"Travel",
            "subcategory":"Hotels & Motels",
            "type":"Entertainment"
        }
    ],
    "sg:phone":"+1 605 539 1440",
    "sg:postcode":"57382",
    "sg:province":"SD",
    "wof:name":"Traveler's Motel",
    "wof:placetype":"venue"
},
  "geometry": {"coordinates":[-98.574979,44.07943],"type":"Point"}
}