{
  "type": "Feature",
  "properties": {
    "iso:country":"US",
    "sg:address":"202 Kasan Ave",
    "sg:city":"Volga",
    "sg:classifiers":[
        {
            "category":"Utilities",
            "subcategory":"Water",
            "type":"Services"
        }
    ],
    "sg:phone":"+1 605 627 9421",
    "sg:postcode":"57071",
    "sg:province":"SD",
    "sg:tags":[
        "company",
        "sewage"
    ],
    "wof:name":"City Of Volga Municipal Utilit",
    "wof:placetype":"venue"
},
  "geometry": {"coordinates":[-96.926632,44.323643],"type":"Point"}
}