{
  "type": "Feature",
  "properties": {
    "iso:country":"US",
    "sg:address":"2204 Hwy 12 W",
    "sg:city":"Aberdeen",
    "sg:classifiers":[
        {
            "category":"Building & Trades",
            "subcategory":"Construction",
            "type":"Services"
        }
    ],
    "sg:phone":"+1 605 225 3814",
    "sg:postcode":"57401",
    "sg:province":"SD",
    "sg:tags":[
        "excavating",
        "contractor"
    ],
    "sg:website":"www.lientransportation.com",
    "wof:name":"Lien Transportation Co",
    "wof:placetype":"venue"
},
  "geometry": {"coordinates":[-98.523465,45.459071],"type":"Point"}
}