{
  "type": "Feature",
  "properties": {
    "iso:country":"US",
    "sg:address":"119 S Central Ave",
    "sg:city":"Pierre",
    "sg:classifiers":[
        {
            "category":"Organizations",
            "subcategory":"Membership Organization",
            "type":"Services"
        }
    ],
    "sg:phone":"+1 605 224 5552",
    "sg:postcode":"57501",
    "sg:province":"SD",
    "wof:name":"Knights of York Cross of",
    "wof:placetype":"venue"
},
  "geometry": {"coordinates":[-100.354275,44.370309],"type":"Point"}
}