{
  "type": "Feature",
  "properties": {
    "iso:country":"US",
    "sg:address":"1014 22nd Ave S",
    "sg:city":"Brookings",
    "sg:classifiers":[
        {
            "category":"Real Estate",
            "subcategory":"Real Estate Operator",
            "type":"Services"
        }
    ],
    "sg:phone":"+1 605 693 3203",
    "sg:postcode":"57006",
    "sg:province":"SD",
    "sg:tags":[
        "apartment"
    ],
    "wof:name":"Countryside Estates",
    "wof:placetype":"venue"
},
  "geometry": {"coordinates":[-96.768404,44.294375],"type":"Point"}
}