{
  "type": "Feature",
  "properties": {
    "iso:country":"US",
    "sg:address":"402 Grand Ave",
    "sg:city":"Lead",
    "sg:classifiers":[
        {
            "category":"Real Estate",
            "subcategory":"Surveying",
            "type":"Services"
        }
    ],
    "sg:phone":"+1 605 580 0386",
    "sg:postcode":"57754",
    "sg:province":"SD",
    "sg:tags":[
        "surveyor",
        "land"
    ],
    "wof:name":"Azimuth Surveying and Mapping",
    "wof:placetype":"venue"
},
  "geometry": {"coordinates":[-103.769417,44.347497],"type":"Point"}
}