{
  "type": "Feature",
  "properties": {
    "iso:country":"US",
    "sg:address":"235 W 10th St",
    "sg:city":"Sioux Falls",
    "sg:classifiers":[
        {
            "category":"Government",
            "subcategory":"Office",
            "type":"Public Place"
        }
    ],
    "sg:phone":"+1 605 367 8070",
    "sg:postcode":"57104",
    "sg:province":"SD",
    "sg:tags":[
        "village"
    ],
    "wof:name":"Sioux Falls City Council Ofc",
    "wof:placetype":"venue"
},
  "geometry": {"coordinates":[-96.7294,43.545922],"type":"Point"}
}