{
  "type": "Feature",
  "properties": {
    "addr:full":"505 Haynes St Mt Vernon SD 57363",
    "addr:housenumber":"505",
    "addr:postcode":"57363",
    "addr:street":"Haynes St",
    "iso:country":"US",
    "sg:address":"505 Haynes St",
    "sg:city":"Mt Vernon",
    "sg:classifiers":[
        {
            "category":"Banks & Credit Unions",
            "subcategory":"Bank",
            "type":"Services"
        }
    ],
    "sg:phone":"+1 605 236 5200",
    "sg:postcode":"57363",
    "sg:province":"SD",
    "sg:tags":[
        "loan",
        "real estate"
    ],
    "wof:name":"Midwest Mortgage & More",
    "wof:placetype":"venue"
},
  "geometry": {"coordinates":[-98.255914,43.715632],"type":"Point"}
}