{
  "type": "Feature",
  "properties": {
    "iso:country":"US",
    "sg:address":"47845 271st St",
    "sg:city":"Harrisburg",
    "sg:phone":"+1 605 743 2240",
    "sg:postcode":"57032",
    "sg:province":"SD",
    "sg:tags":[
        "farm",
        "field",
        "crop"
    ],
    "wof:name":"Lyle Stoterau",
    "wof:placetype":"venue"
},
  "geometry": {"coordinates":[-96.63511699999999,43.460368],"type":"Point"}
}