{
  "type": "Feature",
  "properties": {
    "iso:country":"US",
    "sg:address":"3420 S Hwy 79",
    "sg:city":"Rapid City",
    "sg:classifiers":[
        {
            "category":"Freight",
            "type":"Transportation"
        }
    ],
    "sg:phone":"+1 605 343 3147",
    "sg:postcode":"57701",
    "sg:province":"SD",
    "sg:tags":[
        "mover"
    ],
    "wof:name":"Hanson-Maves Co",
    "wof:placetype":"venue"
},
  "geometry": {"coordinates":[-103.19168000000001,44.051004],"type":"Point"}
}