{
  "type": "Feature",
  "properties": {
    "addr:full":"16 S Broadway Watertown SD 57201",
    "addr:housenumber":"16",
    "addr:postcode":"57201",
    "addr:street":"S Broadway",
    "iso:country":"US",
    "sg:address":"16 S Broadway",
    "sg:city":"Watertown",
    "sg:classifiers":[
        {
            "category":"Shopping",
            "subcategory":"Hobbies, Toys, & Games",
            "type":"Retail Goods"
        }
    ],
    "sg:phone":"+1 605 886 3791",
    "sg:postcode":"57201",
    "sg:province":"SD",
    "sg:tags":[
        "darts",
        "boards",
        "dart"
    ],
    "wof:name":"Dart Shop",
    "wof:placetype":"venue"
},
  "geometry": {"coordinates":[-97.11453,44.900273],"type":"Point"}
}