{
  "type": "Feature",
  "properties": {
    "addr:full":"1520 N Garfield Ave Pierre SD 57501",
    "addr:housenumber":"1520",
    "addr:postcode":"57501",
    "addr:street":"N Garfield Ave",
    "iso:country":"US",
    "sg:address":"1520 N Garfield Ave",
    "sg:city":"Pierre",
    "sg:classifiers":[
        {
            "category":"Wholesale",
            "subcategory":"Electrical",
            "type":"Manufacturing & Wholesale Goods"
        }
    ],
    "sg:phone":"+1 605 224 1676",
    "sg:postcode":"57501",
    "sg:province":"SD",
    "sg:tags":[
        "communication",
        "radio",
        "system"
    ],
    "wof:name":"Communications Center Inc",
    "wof:placetype":"venue"
},
  "geometry": {"coordinates":[-100.314538,44.381811],"type":"Point"}
}