{
  "type": "Feature",
  "properties": {
    "addr:full":"10868 92nd St SE Oakes SD 58474",
    "addr:housenumber":"10868",
    "addr:postcode":"58474",
    "addr:street":"92Nd St Se",
    "iso:country":"US",
    "sg:address":"10868 92nd St SE",
    "sg:city":"Oakes",
    "sg:phone":"+1 701 742 2759",
    "sg:postcode":"58474",
    "sg:province":"SD",
    "sg:tags":[
        "irish",
        "wheat",
        "potato",
        "farm",
        "corn",
        "soybean"
    ],
    "wof:name":"Wayne Rehovsky",
    "wof:placetype":"venue"
},
  "geometry": {"coordinates":[-98.13178499999999,46.080971],"type":"Point"}
}