{
  "type": "Feature",
  "properties": {
    "addr:full":"43822 280th St Freeman SD 57029",
    "addr:housenumber":"43822",
    "addr:postcode":"57029",
    "addr:street":"280Th St",
    "iso:country":"US",
    "sg:address":"43822 280th St",
    "sg:city":"Freeman",
    "sg:classifiers":[
        {
            "category":"Sports & Exercise",
            "subcategory":"Golf",
            "type":"Entertainment"
        }
    ],
    "sg:phone":"+1 605 925 4155",
    "sg:postcode":"57029",
    "sg:province":"SD",
    "sg:tags":[
        "course"
    ],
    "wof:name":"Valley View Golf Course Mntnc",
    "wof:placetype":"venue"
},
  "geometry": {"coordinates":[-97.379684,43.328407],"type":"Point"}
}