{
  "type": "Feature",
  "properties": {
    "iso:country":"US",
    "sg:address":"340 S Phillips Ave",
    "sg:city":"Sioux Falls",
    "sg:classifiers":[
        {
            "category":"Professional",
            "subcategory":"Engineering",
            "type":"Services"
        }
    ],
    "sg:phone":"+1 605 335 3720",
    "sg:postcode":"57104",
    "sg:province":"SD",
    "sg:tags":[
        "engineer"
    ],
    "sg:website":"www.aceinet.com",
    "wof:name":"Associated Consulting Engnrng",
    "wof:placetype":"venue"
},
  "geometry": {"coordinates":[-96.72673,43.543962],"type":"Point"}
}