{
  "type": "Feature",
  "properties": {
    "iso:country":"US",
    "sg:address":"32850 194th St",
    "sg:city":"Holabird",
    "sg:phone":"+1 605 852 2051",
    "sg:postcode":"57540",
    "sg:province":"SD",
    "sg:tags":[
        "farm",
        "corn",
        "wheat"
    ],
    "wof:name":"Edward Nemec",
    "wof:placetype":"venue"
},
  "geometry": {"coordinates":[-99.592343,44.576969],"type":"Point"}
}