{
  "type": "Feature",
  "properties": {
    "iso:country":"US",
    "sg:address":"47794 Julie Rd",
    "sg:city":"Sioux Falls",
    "sg:classifiers":[
        {
            "category":"Restaurant",
            "type":"Food & Drink"
        }
    ],
    "sg:phone":"+1 605 743 5368",
    "sg:postcode":"57108",
    "sg:province":"SD",
    "sg:tags":[
        "eating"
    ],
    "wof:name":"Big Denny Catering",
    "wof:placetype":"venue"
},
  "geometry": {"coordinates":[-96.649583,43.479353],"type":"Point"}
}