{
  "type": "Feature",
  "properties": {
    "iso:country":"US",
    "sg:address":"1211 3rd St",
    "sg:city":"Brookings",
    "sg:classifiers":[
        {
            "category":"Shopping",
            "subcategory":"Used Merchandise",
            "type":"Retail Goods"
        }
    ],
    "sg:phone":"+1 605 692 2497",
    "sg:postcode":"57006",
    "sg:province":"SD",
    "wof:name":"Selkens Good Oldays Antiques",
    "wof:placetype":"venue"
},
  "geometry": {"coordinates":[-96.785096,44.307937],"type":"Point"}
}