{
  "type": "Feature",
  "properties": {
    "addr:full":"802 8th St Eureka SD 57437",
    "addr:housenumber":"802",
    "addr:postcode":"57437",
    "addr:street":"8Th St",
    "iso:country":"US",
    "sg:address":"802 8th St",
    "sg:city":"Eureka",
    "sg:classifiers":[
        {
            "category":"Organizations",
            "subcategory":"Religious Organization",
            "type":"Services"
        }
    ],
    "sg:phone":"+1 605 284 2449",
    "sg:postcode":"57437",
    "sg:province":"SD",
    "sg:tags":[
        "church"
    ],
    "wof:name":"Baptist Church",
    "wof:placetype":"venue"
},
  "geometry": {"coordinates":[-99.62120299999999,45.768502],"type":"Point"}
}