{
  "type": "Feature",
  "properties": {
    "iso:country":"US",
    "sg:address":"18358 378th Ave",
    "sg:city":"Tulare",
    "sg:classifiers":[
        {
            "category":"Farming",
            "subcategory":"Farm",
            "type":"Manufacturing & Wholesale Goods"
        }
    ],
    "sg:phone":"+1 605 596 4349",
    "sg:postcode":"57476",
    "sg:province":"SD",
    "sg:tags":[
        "crop",
        "general"
    ],
    "wof:name":"Warren A Lewis",
    "wof:placetype":"venue"
},
  "geometry": {"coordinates":[-98.62531199999999,44.726325],"type":"Point"}
}