{
  "type": "Feature",
  "properties": {
    "iso:country":"US",
    "sg:address":"41409 101st St",
    "sg:city":"Britton",
    "sg:classifiers":[
        {
            "category":"Real Estate",
            "subcategory":"Real Estate Operator",
            "type":"Services"
        }
    ],
    "sg:phone":"+1 605 448 2657",
    "sg:postcode":"57430",
    "sg:province":"SD",
    "sg:tags":[
        "property",
        "lessor"
    ],
    "wof:name":"Cyril Hastings",
    "wof:placetype":"venue"
},
  "geometry": {"coordinates":[-97.913489,45.921774],"type":"Point"}
}