{
  "type": "Feature",
  "properties": {
    "iso:country":"US",
    "sg:address":"2901 State Hwy 50",
    "sg:city":"Yankton",
    "sg:classifiers":[
        {
            "category":"Home & Garden",
            "subcategory":"Mobile Homes",
            "type":"Retail Goods"
        }
    ],
    "sg:phone":"+1 605 665 8998",
    "sg:postcode":"57078",
    "sg:province":"SD",
    "sg:tags":[
        "house",
        "construction"
    ],
    "wof:name":"Country View Homes",
    "wof:placetype":"venue"
},
  "geometry": {"coordinates":[-97.397741,42.904013],"type":"Point"}
}