{
  "type": "Feature",
  "properties": {
    "addr:full":"337 8th St Brookings SD 57006",
    "addr:housenumber":"337",
    "addr:postcode":"57006",
    "addr:street":"8Th St",
    "iso:country":"US",
    "sg:address":"337 8th St",
    "sg:city":"Brookings",
    "sg:classifiers":[
        {
            "category":"Organizations",
            "subcategory":"Religious Organization",
            "type":"Services"
        }
    ],
    "sg:phone":"+1 605 692 6251",
    "sg:postcode":"57006",
    "sg:province":"SD",
    "sg:tags":[
        "church"
    ],
    "sg:website":"www.firstlutheranbrookings.org",
    "wof:name":"First Lutheran Church",
    "wof:placetype":"venue"
},
  "geometry": {"coordinates":[-96.799944,44.31437],"type":"Point"}
}