{
  "type": "Feature",
  "properties": {
    "addr:full":"703 Main St Webster SD 57274",
    "addr:housenumber":"703",
    "addr:postcode":"57274",
    "addr:street":"Main St",
    "iso:country":"US",
    "sg:address":"703 Main St",
    "sg:city":"Webster",
    "sg:classifiers":[
        {
            "category":"Real Estate",
            "subcategory":"Real Estate Services",
            "type":"Services"
        }
    ],
    "sg:phone":"+1 605 345 3891",
    "sg:postcode":"57274",
    "sg:province":"SD",
    "wof:name":"Grue Abstract Co",
    "wof:placetype":"venue"
},
  "geometry": {"coordinates":[-97.520195,45.333183],"type":"Point"}
}