{
  "type": "Feature",
  "properties": {
    "addr:full":"210 E Grand Xing Mobridge SD 57601",
    "addr:housenumber":"210",
    "addr:postcode":"57601",
    "addr:street":"E Grand Xing",
    "iso:country":"US",
    "sg:address":"210 E Grand Xing",
    "sg:city":"Mobridge",
    "sg:classifiers":[
        {
            "category":"Professional",
            "subcategory":"Accounting & Tax Preparation",
            "type":"Services"
        }
    ],
    "sg:phone":"+1 605 845 3658",
    "sg:postcode":"57601",
    "sg:province":"SD",
    "sg:tags":[
        "accountant"
    ],
    "wof:name":"Kohlman Bierschbach & Anderson",
    "wof:placetype":"venue"
},
  "geometry": {"coordinates":[-100.432373,45.537457],"type":"Point"}
}