{
  "type": "Feature",
  "properties": {
    "iso:country":"US",
    "sg:address":"1008 Howard St",
    "sg:city":"Rapid City",
    "sg:classifiers":[
        {
            "category":"Real Estate",
            "subcategory":"Developer",
            "type":"Services"
        },
        {
            "category":"Travel",
            "subcategory":"Campground",
            "type":"Entertainment"
        }
    ],
    "sg:phone":"+1 605 343 6861",
    "sg:postcode":"57701",
    "sg:province":"SD",
    "sg:tags":[
        "mobile",
        "home",
        "laundromat",
        "court"
    ],
    "wof:name":"Wheel Estates",
    "wof:placetype":"venue"
},
  "geometry": {"coordinates":[-103.230137,44.106796],"type":"Point"}
}