{
  "type": "Feature",
  "properties": {
    "iso:country":"US",
    "sg:address":"502 E North St",
    "sg:city":"Humboldt",
    "sg:classifiers":[
        {
            "category":"Wholesale",
            "subcategory":"Machinery & Supplies",
            "type":"Manufacturing & Wholesale Goods"
        }
    ],
    "sg:phone":"+1 605 363 5041",
    "sg:postcode":"57035",
    "sg:province":"SD",
    "sg:tags":[
        "equipment",
        "establishment"
    ],
    "wof:name":"Sidels Taxidermy",
    "wof:placetype":"venue"
},
  "geometry": {"coordinates":[-97.06889,43.647165],"type":"Point"}
}