{
  "type": "Feature",
  "properties": {
    "addr:full":"315 Seaton Cir Spearfish SD 57783",
    "addr:housenumber":"315",
    "addr:postcode":"57783",
    "addr:street":"Seaton Cir",
    "iso:country":"US",
    "sg:address":"315 Seaton Cir",
    "sg:city":"Spearfish",
    "sg:classifiers":[
        {
            "category":"Manufacturing",
            "subcategory":"Printing",
            "type":"Manufacturing & Wholesale Goods"
        }
    ],
    "sg:phone":"+1 605 642 2761",
    "sg:postcode":"57783",
    "sg:province":"SD",
    "sg:tags":[
        "newspaper"
    ],
    "wof:name":"Black Hills Pioneer & Weekly",
    "wof:placetype":"venue"
},
  "geometry": {"coordinates":[-103.807902,44.482926],"type":"Point"}
}