{
  "type": "Feature",
  "properties": {
    "iso:country":"US",
    "sg:address":"34 N 8th St",
    "sg:city":"Custer",
    "sg:classifiers":[
        {
            "category":"Organizations",
            "subcategory":"Religious Organization",
            "type":"Services"
        }
    ],
    "sg:phone":"+1 605 673 3926",
    "sg:postcode":"57730",
    "sg:province":"SD",
    "sg:tags":[
        "church"
    ],
    "wof:name":"Living Outreach Church Office",
    "wof:placetype":"venue"
},
  "geometry": {"coordinates":[-103.596245,43.768634],"type":"Point"}
}