{
  "type": "Feature",
  "properties": {
    "addr:full":"308 S Main St Aberdeen SD 57401",
    "addr:housenumber":"308",
    "addr:postcode":"57401",
    "addr:street":"S Main St",
    "iso:country":"US",
    "sg:address":"308 S Main St",
    "sg:city":"Aberdeen",
    "sg:classifiers":[
        {
            "category":"Banks & Credit Unions",
            "subcategory":"Investment Brokerage",
            "type":"Services"
        }
    ],
    "sg:phone":"+1 605 225 0104",
    "sg:postcode":"57401",
    "sg:province":"SD",
    "sg:tags":[
        "security"
    ],
    "wof:name":"Investment Center",
    "wof:placetype":"venue"
},
  "geometry": {"coordinates":[-98.48811000000001,45.462045],"type":"Point"}
}