{
  "type": "Feature",
  "properties": {
    "iso:country":"US",
    "sg:address":"1310 Main Ave S",
    "sg:city":"Brookings",
    "sg:classifiers":[
        {
            "category":"Building & Trades",
            "subcategory":"Equipment Rental",
            "type":"Services"
        }
    ],
    "sg:phone":"+1 605 692 7275",
    "sg:postcode":"57006",
    "sg:province":"SD",
    "sg:tags":[
        "disabled",
        "person",
        "supply"
    ],
    "wof:name":"Dakotalink",
    "wof:placetype":"venue"
},
  "geometry": {"coordinates":[-96.79878600000001,44.291152],"type":"Point"}
}