{
  "type": "Feature",
  "properties": {
    "addr:full":"209 E 2nd St Alcester SD 57001",
    "addr:housenumber":"209",
    "addr:postcode":"57001",
    "addr:street":"E 2Nd St",
    "iso:country":"US",
    "sg:address":"209 E 2nd St",
    "sg:city":"Alcester",
    "sg:classifiers":[
        {
            "category":"Professional",
            "type":"Services"
        }
    ],
    "sg:phone":"+1 605 934 2098",
    "sg:postcode":"57001",
    "sg:province":"SD",
    "sg:tags":[
        "establishment"
    ],
    "wof:name":"Com Plecks Inc",
    "wof:placetype":"venue"
},
  "geometry": {"coordinates":[-96.629428,43.021529],"type":"Point"}
}