{
  "type": "Feature",
  "properties": {
    "iso:country":"US",
    "sg:address":"3401 W 49th St",
    "sg:city":"Sioux Falls",
    "sg:classifiers":[
        {
            "category":"Health Services",
            "subcategory":"Doctor",
            "type":"Services"
        }
    ],
    "sg:phone":"+1 605 333 1850",
    "sg:postcode":"57106",
    "sg:province":"SD",
    "sg:tags":[
        "medical"
    ],
    "wof:name":"Family Practice Physicians S",
    "wof:placetype":"venue"
},
  "geometry": {"coordinates":[-96.767467,43.507605],"type":"Point"}
}