{
  "type": "Feature",
  "properties": {
    "addr:full":"41717 303rd St Tyndall SD 57066",
    "addr:housenumber":"41717",
    "addr:postcode":"57066",
    "addr:street":"303Rd St",
    "iso:country":"US",
    "sg:address":"41717 303rd St",
    "sg:city":"Tyndall",
    "sg:classifiers":[
        {
            "category":"Personal",
            "subcategory":"Beauty Salon",
            "type":"Services"
        }
    ],
    "sg:phone":"+1 605 589 4040",
    "sg:postcode":"57066",
    "sg:province":"SD",
    "wof:name":"House Of Hair",
    "wof:placetype":"venue"
},
  "geometry": {"coordinates":[-97.844598,42.995729],"type":"Point"}
}