{
  "type": "Feature",
  "properties": {
    "iso:country":"US",
    "sg:address":"45713 302nd St",
    "sg:city":"Wakonda",
    "sg:phone":"+1 605 267 2531",
    "sg:postcode":"57073",
    "sg:province":"SD",
    "sg:tags":[
        "farm",
        "corn",
        "soybean"
    ],
    "wof:name":"Paul Jensen Paul",
    "wof:placetype":"venue"
},
  "geometry": {"coordinates":[-97.058588,43.01145],"type":"Point"}
}