{
  "type": "Feature",
  "properties": {
    "iso:country":"US",
    "sg:address":"1508 W Cedar St",
    "sg:city":"Beresford",
    "sg:classifiers":[
        {
            "category":"Government",
            "subcategory":"Office",
            "type":"Public Place"
        }
    ],
    "sg:phone":"+1 605 763 5095",
    "sg:postcode":"57004",
    "sg:province":"SD",
    "sg:tags":[
        "state",
        "program"
    ],
    "wof:name":"Transportation Dept",
    "wof:placetype":"venue"
},
  "geometry": {"coordinates":[-96.801688,43.083679],"type":"Point"}
}