{
  "type": "Feature",
  "properties": {
    "iso:country":"US",
    "sg:address":"1527 NW 2nd St",
    "sg:city":"Madison",
    "sg:classifiers":[
        {
            "category":"Insurance",
            "subcategory":"Insurance Agent",
            "type":"Services"
        }
    ],
    "sg:phone":"+1 605 256 4609",
    "sg:postcode":"57042",
    "sg:province":"SD",
    "wof:name":"Thrivent Financial-Lutherans",
    "wof:placetype":"venue"
},
  "geometry": {"coordinates":[-97.13785,44.00738],"type":"Point"}
}