{
  "type": "Feature",
  "properties": {
    "addr:full":"634 Old Hill City Rd Keystone SD 57751",
    "addr:housenumber":"634",
    "addr:postcode":"57751",
    "addr:street":"City Rd",
    "iso:country":"US",
    "sg:address":"634 Old Hill City Rd",
    "sg:city":"Keystone",
    "sg:classifiers":[
        {
            "category":"Travel",
            "subcategory":"Campground",
            "type":"Entertainment"
        }
    ],
    "sg:phone":"+1 605 666 4557",
    "sg:postcode":"57751",
    "sg:province":"SD",
    "wof:name":"Battle Creek Campgrounds",
    "wof:placetype":"venue"
},
  "geometry": {"coordinates":[-103.44372799999999,43.897464],"type":"Point"}
}