{
  "type": "Feature",
  "properties": {
    "iso:country":"US",
    "sg:address":"634 Old Hill City Rd",
    "sg:city":"Keystone",
    "sg:classifiers":[
        {
            "category":"Travel",
            "subcategory":"Campground",
            "type":"Entertainment"
        }
    ],
    "sg:phone":"+1 605 666 4557",
    "sg:postcode":"57751",
    "sg:province":"SD",
    "wof:name":"Battle Creek Campgrounds",
    "wof:placetype":"venue"
},
  "geometry": {"coordinates":[-103.443728,43.897464],"type":"Point"}
}