{
  "type": "Feature",
  "properties": {
    "addr:full":"2400 W Main St Rapid City SD 57702",
    "addr:housenumber":"2400",
    "addr:postcode":"57702",
    "addr:street":"W Main St",
    "iso:country":"US",
    "sg:address":"2400 W Main St",
    "sg:city":"Rapid City",
    "sg:classifiers":[
        {
            "category":"Personal",
            "subcategory":"Tattoo Parlor",
            "type":"Services"
        }
    ],
    "sg:phone":"+1 605 718 7817",
    "sg:postcode":"57702",
    "sg:province":"SD",
    "sg:tags":[
        "tattooing"
    ],
    "wof:name":"Biomek Tattoo & Piercing",
    "wof:placetype":"venue"
},
  "geometry": {"coordinates":[-103.25891,44.082166],"type":"Point"}
}