{
  "type": "Feature",
  "properties": {
    "iso:country":"US",
    "sg:address":"1000 N Main St",
    "sg:city":"Mitchell",
    "sg:classifiers":[
        {
            "category":"Autos & Motor Vehicles",
            "subcategory":"Motorcycle Sales",
            "type":"Retail Goods"
        }
    ],
    "sg:phone":"+1 605 990 5337",
    "sg:postcode":"57301",
    "sg:province":"SD",
    "sg:tags":[
        "scooter"
    ],
    "wof:name":"Lee's Power Sports Inc",
    "wof:placetype":"venue"
},
  "geometry": {"coordinates":[-98.025695,43.719741],"type":"Point"}
}