{
  "type": "Feature",
  "properties": {
    "iso:country":"US",
    "sg:address":"47874 Atterbury Ct",
    "sg:city":"Harrisburg",
    "sg:classifiers":[
        {
            "category":"Communications",
            "subcategory":"Film & Video Production",
            "type":"Services"
        }
    ],
    "sg:phone":"+1 605 743 5240",
    "sg:postcode":"57032",
    "sg:province":"SD",
    "sg:tags":[
        "duplication"
    ],
    "wof:name":"Maloney Memories",
    "wof:placetype":"venue"
},
  "geometry": {"coordinates":[-96.635028,43.461566],"type":"Point"}
}