{
  "type": "Feature",
  "properties": {
    "iso:country":"US",
    "sg:address":"40919 293rd St",
    "sg:city":"Tripp",
    "sg:classifiers":[
        {
            "category":"Farming",
            "subcategory":"Livestock Farm",
            "type":"Manufacturing & Wholesale Goods"
        }
    ],
    "sg:phone":"+1 605 935 6586",
    "sg:postcode":"57376",
    "sg:province":"SD",
    "sg:tags":[
        "beef",
        "feedlot",
        "cattle"
    ],
    "wof:name":"Dewald Arlo",
    "wof:placetype":"venue"
},
  "geometry": {"coordinates":[-97.992304,43.139753],"type":"Point"}
}