{
  "type": "Feature",
  "properties": {
    "iso:country":"US",
    "sg:address":"214 Capital St",
    "sg:city":"Yankton",
    "sg:classifiers":[
        {
            "category":"Home & Garden",
            "subcategory":"Household Appliances",
            "type":"Retail Goods"
        }
    ],
    "sg:phone":"+1 605 665 8052",
    "sg:postcode":"57078",
    "sg:province":"SD",
    "sg:tags":[
        "cleaners",
        "vacuum"
    ],
    "wof:name":"Jones Distributing",
    "wof:placetype":"venue"
},
  "geometry": {"coordinates":[-97.390456,42.869065],"type":"Point"}
}