{
  "type": "Feature",
  "properties": {
    "iso:country":"US",
    "sg:address":"728 34th Ave",
    "sg:city":"Brookings",
    "sg:classifiers":[
        {
            "category":"Autos & Motor Vehicles",
            "subcategory":"Automobile Sales",
            "type":"Retail Goods"
        }
    ],
    "sg:phone":"+1 605 695 2036",
    "sg:postcode":"57006",
    "sg:province":"SD",
    "sg:tags":[
        "car",
        "dealer"
    ],
    "wof:name":"Rusty's Auto",
    "wof:placetype":"venue"
},
  "geometry": {"coordinates":[-96.74835299999999,44.312637],"type":"Point"}
}