{
  "type": "Feature",
  "properties": {
    "iso:country":"US",
    "sg:address":"2323 Jennings Ave",
    "sg:city":"Hot Springs",
    "sg:classifiers":[
        {
            "category":"Organizations",
            "subcategory":"Religious Organization",
            "type":"Services"
        }
    ],
    "sg:phone":"+1 605 745 3378",
    "sg:postcode":"57747",
    "sg:province":"SD",
    "sg:tags":[
        "church"
    ],
    "wof:name":"Grace Lutheran Church",
    "wof:placetype":"venue"
},
  "geometry": {"coordinates":[-103.492948,43.431053],"type":"Point"}
}