{
  "type": "Feature",
  "properties": {
    "addr:full":"2001 9th Ave SW Watertown SD 57201",
    "addr:housenumber":"2001",
    "addr:postcode":"57201",
    "addr:street":"9Th Ave Sw",
    "iso:country":"US",
    "sg:address":"2001 9th Ave SW",
    "sg:city":"Watertown",
    "sg:classifiers":[
        {
            "category":"Government",
            "subcategory":"Office",
            "type":"Public Place"
        }
    ],
    "sg:phone":"+1 605 882 5022",
    "sg:postcode":"57201",
    "sg:province":"SD",
    "sg:tags":[
        "state",
        "resource"
    ],
    "wof:name":"Child Support Enforcement",
    "wof:placetype":"venue"
},
  "geometry": {"coordinates":[-97.142892,44.890142],"type":"Point"}
}