{
  "type": "Feature",
  "properties": {
    "iso:country":"US",
    "sg:address":"410 3rd St",
    "sg:city":"Hecla",
    "sg:classifiers":[
        {
            "category":"Travel",
            "subcategory":"Hotels & Motels",
            "type":"Entertainment"
        }
    ],
    "sg:phone":"+1 605 994 2460",
    "sg:postcode":"57446",
    "sg:province":"SD",
    "wof:name":"Sand Lake Hotel",
    "wof:placetype":"venue"
},
  "geometry": {"coordinates":[-98.152629,45.882387],"type":"Point"}
}