{
  "type": "Feature",
  "properties": {
    "iso:country":"US",
    "sg:address":"5808 W Karen Dr",
    "sg:city":"Sioux Falls",
    "sg:classifiers":[
        {
            "category":"Professional",
            "subcategory":"Computer Services",
            "type":"Services"
        }
    ],
    "sg:phone":"+1 605 361 6398",
    "sg:postcode":"57106",
    "sg:province":"SD",
    "sg:tags":[
        "related"
    ],
    "wof:name":"Quanet Solutions Inc",
    "wof:placetype":"venue"
},
  "geometry": {"coordinates":[-96.799633,43.522763],"type":"Point"}
}