{
  "type": "Feature",
  "properties": {
    "iso:country":"US",
    "sg:address":"825 3rd St SW",
    "sg:city":"Watertown",
    "sg:classifiers":[
        {
            "category":"Recreation",
            "subcategory":"Amusement Park",
            "type":"Entertainment"
        }
    ],
    "sg:phone":"+1 605 882 6959",
    "sg:postcode":"57201",
    "sg:province":"SD",
    "sg:website":"www.thunderroad.info",
    "wof:name":"Thunder Road Go Karts & Mini",
    "wof:placetype":"venue"
},
  "geometry": {"coordinates":[-97.12317899999999,44.891709],"type":"Point"}
}