{
  "type": "Feature",
  "properties": {
    "addr:full":"628 Main Ave Brookings SD 57006",
    "addr:housenumber":"628",
    "addr:postcode":"57006",
    "addr:street":"Main Ave",
    "iso:country":"US",
    "sg:address":"628 Main Ave",
    "sg:city":"Brookings",
    "sg:classifiers":[
        {
            "category":"Health Services",
            "subcategory":"Doctor",
            "type":"Services"
        }
    ],
    "sg:phone":"+1 605 692 8189",
    "sg:postcode":"57006",
    "sg:province":"SD",
    "sg:tags":[
        "medical"
    ],
    "wof:name":"Urology Specialists Chartered",
    "wof:placetype":"venue"
},
  "geometry": {"coordinates":[-96.79853,44.312509],"type":"Point"}
}