{
  "type": "Feature",
  "properties": {
    "iso:country":"US",
    "sg:address":"4612 N Hillcrest Ave",
    "sg:city":"Sioux Falls",
    "sg:classifiers":[
        {
            "category":"Freight",
            "type":"Transportation"
        }
    ],
    "sg:phone":"+1 605 339 1749",
    "sg:postcode":"57104",
    "sg:province":"SD",
    "sg:tags":[
        "trucking"
    ],
    "wof:name":"De Marteleare Trucking",
    "wof:placetype":"venue"
},
  "geometry": {"coordinates":[-96.703948,43.596525],"type":"Point"}
}