{
  "type": "Feature",
  "properties": {
    "addr:full":"111 E Washita St Iroquois SD 57353",
    "addr:housenumber":"111",
    "addr:postcode":"57353",
    "addr:street":"E Washita St",
    "iso:country":"US",
    "sg:address":"111 E Washita St",
    "sg:city":"Iroquois",
    "sg:classifiers":[
        {
            "category":"Education",
            "subcategory":"School",
            "type":"Public Place"
        }
    ],
    "sg:phone":"+1 605 546 2210",
    "sg:postcode":"57353",
    "sg:province":"SD",
    "wof:name":"Pearl Creek Colony Elementary",
    "wof:placetype":"venue"
},
  "geometry": {"coordinates":[-97.85303500000001,44.366944],"type":"Point"}
}