{
  "type": "Feature",
  "properties": {
    "addr:full":"5955 S Hwy 16 Rapid City SD 57701",
    "addr:housenumber":"5955",
    "addr:postcode":"57701",
    "addr:street":"S Hwy 16",
    "iso:country":"US",
    "sg:address":"5955 S Hwy 16",
    "sg:city":"Rapid City",
    "sg:classifiers":[
        {
            "category":"Home & Garden",
            "subcategory":"Furniture",
            "type":"Retail Goods"
        }
    ],
    "sg:phone":"+1 605 718 9900",
    "sg:postcode":"57701",
    "sg:province":"SD",
    "wof:name":"Bella Patina",
    "wof:placetype":"venue"
},
  "geometry": {"coordinates":[-103.248891,44.024144],"type":"Point"}
}