{
  "type": "Feature",
  "properties": {
    "addr:full":"28103 318th Ave Winner SD 57580",
    "addr:housenumber":"28103",
    "addr:postcode":"57580",
    "addr:street":"318Th Ave",
    "iso:country":"US",
    "sg:address":"28103 318th Ave",
    "sg:city":"Winner",
    "sg:phone":"+1 605 842 1682",
    "sg:postcode":"57580",
    "sg:province":"SD",
    "sg:tags":[
        "wheat",
        "beef",
        "farm",
        "corn",
        "cash",
        "grain",
        "cattle"
    ],
    "wof:name":"Watzel Farms",
    "wof:placetype":"venue"
},
  "geometry": {"coordinates":[-99.810855,43.328726],"type":"Point"}
}