{
  "type": "Feature",
  "properties": {
    "iso:country":"US",
    "sg:address":"23825 S Rockerville Rd",
    "sg:city":"Rapid City",
    "sg:classifiers":[
        {
            "category":"Building & Trades",
            "subcategory":"Construction",
            "type":"Services"
        }
    ],
    "sg:phone":"+1 605 399 0831",
    "sg:postcode":"57702",
    "sg:province":"SD",
    "sg:tags":[
        "excavation",
        "contractor"
    ],
    "wof:name":"Munyan Excavating LLC",
    "wof:placetype":"venue"
},
  "geometry": {"coordinates":[-103.358024,43.949787],"type":"Point"}
}