{
  "type": "Feature",
  "properties": {
    "iso:country":"US",
    "sg:address":"4700 E 6th St",
    "sg:city":"Sioux Falls",
    "sg:classifiers":[
        {
            "category":"Personal",
            "subcategory":"Beauty Salon",
            "type":"Services"
        }
    ],
    "sg:phone":"+1 605 275 0081",
    "sg:postcode":"57110",
    "sg:province":"SD",
    "sg:tags":[
        "shop"
    ],
    "wof:name":"Makes Room For Them Ernestine",
    "wof:placetype":"venue"
},
  "geometry": {"coordinates":[-96.667137,43.551213],"type":"Point"}
}