{
  "type": "Feature",
  "properties": {
    "addr:full":"1500 E Havens St Mitchell SD 57301",
    "addr:housenumber":"1500",
    "addr:postcode":"57301",
    "addr:street":"E Havens St",
    "iso:country":"US",
    "sg:address":"1500 E Havens St",
    "sg:city":"Mitchell",
    "sg:classifiers":[
        {
            "category":"Personal",
            "type":"Services"
        }
    ],
    "sg:phone":"+1 605 996 8779",
    "sg:postcode":"57301",
    "sg:province":"SD",
    "sg:tags":[
        "locker"
    ],
    "wof:name":"Shorty's Locker",
    "wof:placetype":"venue"
},
  "geometry": {"coordinates":[-97.994513,43.702281],"type":"Point"}
}