{
  "type": "Feature",
  "properties": {
    "addr:full":"323 4th Ave E Mobridge SD 57601",
    "addr:housenumber":"323",
    "addr:postcode":"57601",
    "addr:street":"4Th Ave E Mobridge",
    "iso:country":"US",
    "sg:address":"323 4th Ave E",
    "sg:city":"Mobridge",
    "sg:classifiers":[
        {
            "category":"Organizations",
            "subcategory":"Religious Organization",
            "type":"Services"
        }
    ],
    "sg:phone":"+1 605 845 3214",
    "sg:postcode":"57601",
    "sg:province":"SD",
    "wof:name":"Church of God",
    "wof:placetype":"venue"
},
  "geometry": {"coordinates":[-100.428175,45.536161],"type":"Point"}
}