{
  "type": "Feature",
  "properties": {
    "iso:country":"US",
    "sg:address":"121 Monroe St",
    "sg:city":"Winner",
    "sg:classifiers":[
        {
            "category":"Home & Garden",
            "subcategory":"Hardware",
            "type":"Retail Goods"
        }
    ],
    "sg:phone":"+1 605 842 3623",
    "sg:postcode":"57580",
    "sg:province":"SD",
    "wof:name":"Outlaw's Ace Hardware",
    "wof:placetype":"venue"
},
  "geometry": {"coordinates":[-99.85847099999999,43.377444],"type":"Point"}
}