{
  "type": "Feature",
  "properties": {
    "iso:country":"US",
    "sg:address":"525 US Hwy 281",
    "sg:city":"Corsica",
    "sg:classifiers":[
        {
            "category":"Wholesale",
            "subcategory":"Machinery & Supplies",
            "type":"Manufacturing & Wholesale Goods"
        }
    ],
    "sg:phone":"+1 605 946 5444",
    "sg:postcode":"57328",
    "sg:province":"SD",
    "sg:tags":[
        "farm",
        "repair",
        "implement"
    ],
    "wof:name":"Platte Parts Store",
    "wof:placetype":"venue"
},
  "geometry": {"coordinates":[-98.410102,43.420385],"type":"Point"}
}