{
  "type": "Feature",
  "properties": {
    "addr:full":"36690 119th St Westport SD 57481",
    "addr:housenumber":"36690",
    "addr:postcode":"57481",
    "addr:street":"119Th St",
    "iso:country":"US",
    "sg:address":"36690 119th St",
    "sg:city":"Westport",
    "sg:classifiers":[
        {
            "category":"Real Estate",
            "subcategory":"Real Estate Operator",
            "type":"Services"
        }
    ],
    "sg:phone":"+1 605 439 3417",
    "sg:postcode":"57481",
    "sg:province":"SD",
    "sg:tags":[
        "property",
        "lessor"
    ],
    "wof:name":"Elizabeth Maroney",
    "wof:placetype":"venue"
},
  "geometry": {"coordinates":[-98.90710300000001,45.664825],"type":"Point"}
}