{
  "type": "Feature",
  "properties": {
    "addr:full":"904 9th Ave SE Watertown SD 57201",
    "addr:housenumber":"904",
    "addr:postcode":"57201",
    "addr:street":"9Th Ave Se",
    "iso:country":"US",
    "sg:address":"904 9th Ave SE",
    "sg:city":"Watertown",
    "sg:classifiers":[
        {
            "category":"Retail",
            "subcategory":"Auto Repair",
            "type":"Services"
        }
    ],
    "sg:phone":"+1 605 882 3400",
    "sg:postcode":"57201",
    "sg:province":"SD",
    "sg:tags":[
        "automotive"
    ],
    "wof:name":"Valvoline Instant Oil Change",
    "wof:placetype":"venue"
},
  "geometry": {"coordinates":[-97.10349100000001,44.890005],"type":"Point"}
}