{
  "type": "Feature",
  "properties": {
    "addr:full":"48 Highland Ave Deadwood SD 57732",
    "addr:housenumber":"48",
    "addr:postcode":"57732",
    "addr:street":"Highland Ave",
    "iso:country":"US",
    "sg:address":"48 Highland Ave",
    "sg:city":"Deadwood",
    "sg:classifiers":[
        {
            "category":"Building & Trades",
            "subcategory":"Construction",
            "type":"Services"
        }
    ],
    "sg:phone":"+1 605 578 2482",
    "sg:postcode":"57732",
    "sg:province":"SD",
    "sg:tags":[
        "house"
    ],
    "wof:name":"D B Logging",
    "wof:placetype":"venue"
},
  "geometry": {"coordinates":[-103.725863,44.382998],"type":"Point"}
}