{
  "type": "Feature",
  "properties": {
    "iso:country":"US",
    "sg:address":"819 4th Ave NW",
    "sg:city":"Watertown",
    "sg:classifiers":[
        {
            "category":"Professional",
            "subcategory":"Advertising",
            "type":"Services"
        }
    ],
    "sg:phone":"+1 605 753 5950",
    "sg:postcode":"57201",
    "sg:province":"SD",
    "wof:name":"FARMERSCLASSIFIED.COM",
    "wof:placetype":"venue"
},
  "geometry": {"coordinates":[-97.130092,44.905853],"type":"Point"}
}