{
  "type": "Feature",
  "properties": {
    "addr:full":"6400 E Fawn Cir Sioux Falls SD 57110",
    "addr:housenumber":"6400",
    "addr:postcode":"57110",
    "addr:street":"E Fawn Cir",
    "iso:country":"US",
    "sg:address":"6400 E Fawn Cir",
    "sg:city":"Sioux Falls",
    "sg:classifiers":[
        {
            "category":"Freight",
            "type":"Transportation"
        }
    ],
    "sg:phone":"+1 605 275 6560",
    "sg:postcode":"57110",
    "sg:province":"SD",
    "sg:tags":[
        "broker",
        "trucking"
    ],
    "wof:name":"Bison Transportation Inc",
    "wof:placetype":"venue"
},
  "geometry": {"coordinates":[-96.64444899999999,43.539432],"type":"Point"}
}