{
  "type": "Feature",
  "properties": {
    "iso:country":"US",
    "sg:address":"2101 W 41st St",
    "sg:city":"Sioux Falls",
    "sg:classifiers":[
        {
            "category":"Insurance",
            "subcategory":"Insurance Agent",
            "type":"Services"
        }
    ],
    "sg:phone":"+1 605 338 8123",
    "sg:postcode":"57105",
    "sg:province":"SD",
    "wof:name":"American Family Insurance",
    "wof:placetype":"venue"
},
  "geometry": {"coordinates":[-96.75232800000001,43.514842],"type":"Point"}
}