{
  "type": "Feature",
  "properties": {
    "iso:country":"US",
    "sg:address":"217 S Main St",
    "sg:city":"Howard",
    "sg:classifiers":[
        {
            "category":"Banks & Credit Unions",
            "subcategory":"Bank",
            "type":"Services"
        }
    ],
    "sg:phone":"+1 605 772 4561",
    "sg:postcode":"57349",
    "sg:province":"SD",
    "wof:name":"Miner County Bank",
    "wof:placetype":"venue"
},
  "geometry": {"coordinates":[-97.52692500000001,44.009771],"type":"Point"}
}