{
  "type": "Feature",
  "properties": {
    "iso:country":"US",
    "sg:address":"805 Broadway Ave",
    "sg:city":"Valley Springs",
    "sg:classifiers":[
        {
            "category":"Arts & Performance",
            "subcategory":"Theater",
            "type":"Entertainment"
        }
    ],
    "sg:phone":"+1 605 757 7191",
    "sg:postcode":"57068",
    "sg:province":"SD",
    "sg:tags":[
        "karaoke"
    ],
    "wof:name":"Mystic Music Entertainment",
    "wof:placetype":"venue"
},
  "geometry": {"coordinates":[-96.462258,43.582548],"type":"Point"}
}