{
  "type": "Feature",
  "properties": {
    "iso:country":"US",
    "sg:address":"3225 W Rapid St",
    "sg:city":"Rapid City",
    "sg:classifiers":[
        {
            "category":"Wholesale",
            "subcategory":"Medical Equipment & Supplies",
            "type":"Manufacturing & Wholesale Goods"
        },
        {
            "category":"Shopping",
            "subcategory":"Stationery & Office Supplies",
            "type":"Retail Goods"
        }
    ],
    "sg:phone":"+1 605 348 8068",
    "sg:postcode":"57702",
    "sg:province":"SD",
    "wof:name":"Lakota Enterprises Inc",
    "wof:placetype":"venue"
},
  "geometry": {"coordinates":[-103.272117,44.083106],"type":"Point"}
}