{
  "type": "Feature",
  "properties": {
    "addr:full":"1000 S Burr St Mitchell SD 57301",
    "addr:housenumber":"1000",
    "addr:postcode":"57301",
    "addr:street":"S Burr St",
    "iso:country":"US",
    "sg:address":"1000 S Burr St",
    "sg:city":"Mitchell",
    "sg:classifiers":[
        {
            "category":"Ice Cream",
            "type":"Food & Drink"
        }
    ],
    "sg:menulink":"http://www.allmenus.com/sd/mitchell/192444-dairy-queen/menu/",
    "sg:phone":"+1 605 996 9632",
    "sg:postcode":"57301",
    "sg:province":"SD",
    "sg:tags":[
        "burger",
        "american"
    ],
    "wof:name":"Dairy Queen",
    "wof:placetype":"venue"
},
  "geometry": {"coordinates":[-98.018382,43.70119],"type":"Point"}
}