{
  "type": "Feature",
  "properties": {
    "addr:full":"401 S Glendale Ave Sioux Falls SD 57104",
    "addr:housenumber":"401",
    "addr:postcode":"57104",
    "addr:street":"S Glendale Ave",
    "iso:country":"US",
    "sg:address":"401 S Glendale Ave",
    "sg:city":"Sioux Falls",
    "sg:classifiers":[
        {
            "category":"Organizations",
            "subcategory":"Religious Organization",
            "type":"Services"
        }
    ],
    "sg:phone":"+1 605 275 4646",
    "sg:postcode":"57104",
    "sg:province":"SD",
    "sg:tags":[
        "church"
    ],
    "wof:name":"Mercy Church",
    "wof:placetype":"venue"
},
  "geometry": {"coordinates":[-96.74745799999999,43.543012],"type":"Point"}
}