{
  "type": "Feature",
  "properties": {
    "iso:country":"US",
    "sg:address":"116 E 2nd St",
    "sg:city":"Alcester",
    "sg:classifiers":[
        {
            "category":"Retail",
            "subcategory":"Repair Shop",
            "type":"Services"
        }
    ],
    "sg:phone":"+1 605 934 2999",
    "sg:postcode":"57001",
    "sg:province":"SD",
    "sg:tags":[
        "related"
    ],
    "wof:name":"Maximum Performance Repair",
    "wof:placetype":"venue"
},
  "geometry": {"coordinates":[-96.630732,43.02168],"type":"Point"}
}