{
  "type": "Feature",
  "properties": {
    "addr:full":"530 Main St Winfred SD 57036",
    "addr:housenumber":"530",
    "addr:postcode":"57036",
    "addr:street":"Main St",
    "iso:country":"US",
    "sg:address":"530 Main St",
    "sg:city":"Winfred",
    "sg:classifiers":[
        {
            "category":"Farming",
            "subcategory":"Livestock Farm",
            "type":"Manufacturing & Wholesale Goods"
        }
    ],
    "sg:phone":"+1 605 485 2221",
    "sg:postcode":"57036",
    "sg:province":"SD",
    "sg:tags":[
        "beekeeper"
    ],
    "wof:name":"A H Meyer & Sons Inc",
    "wof:placetype":"venue"
},
  "geometry": {"coordinates":[-97.08790500000001,43.281582],"type":"Point"}
}