{
  "type": "Feature",
  "properties": {
    "addr:full":"133 S Main Ave Sioux Falls SD 57104",
    "addr:housenumber":"133",
    "addr:postcode":"57104",
    "addr:street":"S Main Ave",
    "iso:country":"US",
    "sg:address":"133 S Main Ave",
    "sg:city":"Sioux Falls",
    "sg:classifiers":[
        {
            "category":"Banks & Credit Unions",
            "subcategory":"Bank",
            "type":"Services"
        }
    ],
    "sg:phone":"+1 605 988 0298",
    "sg:postcode":"57104",
    "sg:province":"SD",
    "sg:website":"www.firstambanktrust.com",
    "wof:name":"First American Bank & Trust",
    "wof:placetype":"venue"
},
  "geometry": {"coordinates":[-96.72836100000001,43.54642],"type":"Point"}
}