{
  "type": "Feature",
  "properties": {
    "iso:country":"US",
    "sg:address":"2120 Mount Rushmore Rd",
    "sg:city":"Rapid City",
    "sg:classifiers":[
        {
            "category":"Banks & Credit Unions",
            "subcategory":"Bank",
            "type":"Services"
        }
    ],
    "sg:phone":"+1 605 342 8436",
    "sg:postcode":"57701",
    "sg:province":"SD",
    "wof:name":"Security First Bank",
    "wof:placetype":"venue"
},
  "geometry": {"coordinates":[-103.232308,44.064616],"type":"Point"}
}