{
  "type": "Feature",
  "properties": {
    "iso:country":"US",
    "sg:address":"20641 State Hwy 45",
    "sg:city":"Miller",
    "sg:classifiers":[
        {
            "category":"Farming",
            "subcategory":"Livestock Farm",
            "type":"Manufacturing & Wholesale Goods"
        }
    ],
    "sg:phone":"+1 605 853 3910",
    "sg:postcode":"57362",
    "sg:province":"SD",
    "sg:tags":[
        "beef",
        "feedlot",
        "cattle"
    ],
    "wof:name":"Gary Yearous",
    "wof:placetype":"venue"
},
  "geometry": {"coordinates":[-98.98350499999999,44.393929],"type":"Point"}
}