{
  "type": "Feature",
  "properties": {
    "iso:country":"US",
    "sg:address":"324 E Main St",
    "sg:city":"White",
    "sg:classifiers":[
        {
            "category":"Professional",
            "subcategory":"Business Services",
            "type":"Services"
        }
    ],
    "sg:phone":"+1 605 629 2018",
    "sg:postcode":"57276",
    "sg:province":"SD",
    "sg:tags":[
        "auctioneer"
    ],
    "wof:name":"Jurrens Auctions",
    "wof:placetype":"venue"
},
  "geometry": {"coordinates":[-96.643092,44.43459],"type":"Point"}
}