{
  "type": "Feature",
  "properties": {
    "iso:country":"US",
    "sg:address":"25152 Big Sioux Rd",
    "sg:city":"Baltic",
    "sg:phone":"+1 605 529 5787",
    "sg:postcode":"57003",
    "sg:province":"SD",
    "sg:tags":[
        "farm",
        "corn",
        "soybean"
    ],
    "wof:name":"Greg Lostroh",
    "wof:placetype":"venue"
},
  "geometry": {"coordinates":[-96.761262,43.733061],"type":"Point"}
}