{
  "type": "Feature",
  "properties": {
    "iso:country":"US",
    "sg:address":"1729 S Cliff Ave",
    "sg:city":"Sioux Falls",
    "sg:classifiers":[
        {
            "category":"Health Services",
            "subcategory":"Doctor",
            "type":"Services"
        }
    ],
    "sg:phone":"+1 605 339 1369",
    "sg:postcode":"57105",
    "sg:province":"SD",
    "sg:tags":[
        "dentist"
    ],
    "sg:website":"www.graberfamilydentistry.com",
    "wof:name":"Graber Family Dentistry Inc",
    "wof:placetype":"venue"
},
  "geometry": {"coordinates":[-96.71136799999999,43.529832],"type":"Point"}
}