{
  "type": "Feature",
  "properties": {
    "iso:country":"US",
    "sg:address":"196 S Harmon Dr",
    "sg:city":"Mitchell",
    "sg:classifiers":[
        {
            "category":"Professional",
            "type":"Services"
        }
    ],
    "sg:phone":"+1 605 996 1081",
    "sg:postcode":"57301",
    "sg:province":"SD",
    "wof:name":"Ideavations LLC",
    "wof:placetype":"venue"
},
  "geometry": {"coordinates":[-98.041914,43.750341],"type":"Point"}
}