{
  "type": "Feature",
  "properties": {
    "addr:full":"420 Mount Rushmore Rd Custer SD 57730",
    "addr:housenumber":"420",
    "addr:postcode":"57730",
    "addr:street":"Mount Rushmore Rd",
    "iso:country":"US",
    "sg:address":"420 Mount Rushmore Rd",
    "sg:city":"Custer",
    "sg:classifiers":[
        {
            "category":"Government",
            "subcategory":"Office",
            "type":"Public Place"
        }
    ],
    "sg:phone":"+1 605 673 8170",
    "sg:postcode":"57730",
    "sg:province":"SD",
    "wof:name":"Custer County Equalization Dir",
    "wof:placetype":"venue"
},
  "geometry": {"coordinates":[-103.600515,43.766085],"type":"Point"}
}