{
  "type": "Feature",
  "properties": {
    "addr:full":"29490 State Hwy 34 Pierre SD 57501",
    "addr:housenumber":"29490",
    "addr:postcode":"57501",
    "addr:street":"State Hwy 34",
    "iso:country":"US",
    "sg:address":"29490 State Hwy 34",
    "sg:city":"Pierre",
    "sg:classifiers":[
        {
            "category":"Freight",
            "type":"Transportation"
        }
    ],
    "sg:phone":"+1 605 224 4682",
    "sg:postcode":"57501",
    "sg:province":"SD",
    "sg:tags":[
        "special"
    ],
    "wof:name":"Capital Welding and Machine",
    "wof:placetype":"venue"
},
  "geometry": {"coordinates":[-100.257046,44.345932],"type":"Point"}
}