{
  "type": "Feature",
  "properties": {
    "iso:country":"US",
    "sg:address":"41123 198th St",
    "sg:city":"Yale",
    "sg:classifiers":[
        {
            "category":"Farming",
            "subcategory":"Farm",
            "type":"Manufacturing & Wholesale Goods"
        }
    ],
    "sg:phone":"+1 605 352 7756",
    "sg:postcode":"57386",
    "sg:province":"SD",
    "sg:tags":[
        "crop",
        "general"
    ],
    "wof:name":"Hofer Farms Ltd Family Partnr",
    "wof:placetype":"venue"
},
  "geometry": {"coordinates":[-97.98717000000001,44.513832],"type":"Point"}
}