{
  "type": "Feature",
  "properties": {
    "iso:country":"US",
    "sg:address":"308 Julius St",
    "sg:city":"Lead",
    "sg:classifiers":[
        {
            "category":"Professional",
            "subcategory":"Employment Agencies",
            "type":"Services"
        }
    ],
    "sg:phone":"+1 605 584 1361",
    "sg:postcode":"57754",
    "sg:province":"SD",
    "sg:tags":[
        "co",
        "fraternal"
    ],
    "wof:name":"South Dakota Career Ctr",
    "wof:placetype":"venue"
},
  "geometry": {"coordinates":[-103.767909,44.351359],"type":"Point"}
}