{
  "type": "Feature",
  "properties": {
    "iso:country":"US",
    "sg:address":"320 Main Ave",
    "sg:city":"Brandon",
    "sg:classifiers":[
        {
            "category":"Building & Trades",
            "subcategory":"Construction",
            "type":"Services"
        }
    ],
    "sg:phone":"+1 605 582 3232",
    "sg:postcode":"57005",
    "sg:province":"SD",
    "sg:tags":[
        "contractor"
    ],
    "wof:name":"Fire Dept Building",
    "wof:placetype":"venue"
},
  "geometry": {"coordinates":[-96.587694,43.591363],"type":"Point"}
}