{
  "type": "Feature",
  "properties": {
    "iso:country":"US",
    "sg:address":"29463 321st Ave",
    "sg:city":"Colome",
    "sg:classifiers":[
        {
            "category":"Farming",
            "subcategory":"Livestock Farm",
            "type":"Manufacturing & Wholesale Goods"
        }
    ],
    "sg:phone":"+1 605 842 3446",
    "sg:postcode":"57528",
    "sg:province":"SD",
    "sg:tags":[
        "beef",
        "feedlot",
        "cattle"
    ],
    "wof:name":"Larry Bertram Farm",
    "wof:placetype":"venue"
},
  "geometry": {"coordinates":[-99.751166,43.13088],"type":"Point"}
}