{
  "type": "Feature",
  "properties": {
    "iso:country":"US",
    "sg:address":"626 6th St",
    "sg:city":"Rapid City",
    "sg:classifiers":[
        {
            "category":"Home & Garden",
            "subcategory":"Building Materials",
            "type":"Retail Goods"
        }
    ],
    "sg:phone":"+1 605 342 1309",
    "sg:postcode":"57701",
    "sg:province":"SD",
    "sg:tags":[
        "paint",
        "floor",
        "covering"
    ],
    "wof:name":"Roger Frye's Paint & Supply",
    "wof:placetype":"venue"
},
  "geometry": {"coordinates":[-103.227469,44.079212],"type":"Point"}
}