{
  "type": "Feature",
  "properties": {
    "iso:country":"US",
    "sg:address":"4100 W Shirley Pl",
    "sg:city":"Sioux Falls",
    "sg:classifiers":[
        {
            "category":"Travel",
            "subcategory":"Hotels & Motels",
            "type":"Entertainment"
        }
    ],
    "sg:phone":"+1 605 361 3118",
    "sg:postcode":"57106",
    "sg:province":"SD",
    "sg:tags":[
        "operation"
    ],
    "wof:name":"Best Western",
    "wof:placetype":"venue"
},
  "geometry": {"coordinates":[-96.775324,43.515933],"type":"Point"}
}