{
  "type": "Feature",
  "properties": {
    "iso:country":"US",
    "sg:address":"1714 West Blvd",
    "sg:city":"Rapid City",
    "sg:classifiers":[
        {
            "category":"Manufacturing",
            "subcategory":"Tools & Machinery",
            "type":"Manufacturing & Wholesale Goods"
        }
    ],
    "sg:phone":"+1 605 718 0240",
    "sg:postcode":"57701",
    "sg:province":"SD",
    "sg:tags":[
        "distributor",
        "equipment",
        "highway"
    ],
    "wof:name":"Road Groom of Dakotas",
    "wof:placetype":"venue"
},
  "geometry": {"coordinates":[-103.236153,44.068667],"type":"Point"}
}