{
  "type": "Feature",
  "properties": {
    "iso:country":"US",
    "sg:address":"2710 W 12th St",
    "sg:city":"Sioux Falls",
    "sg:classifiers":[
        {
            "category":"Health Services",
            "subcategory":"Clinic",
            "type":"Services"
        }
    ],
    "sg:phone":"+1 605 328 5900",
    "sg:postcode":"57104",
    "sg:province":"SD",
    "sg:tags":[
        "home",
        "care"
    ],
    "wof:name":"Visiting Nurse Association",
    "wof:placetype":"venue"
},
  "geometry": {"coordinates":[-96.765691,43.544004],"type":"Point"}
}