{
  "type": "Feature",
  "properties": {
    "iso:country":"US",
    "sg:address":"31539 468th Ave",
    "sg:city":"Burbank",
    "sg:phone":"+1 605 624 3637",
    "sg:postcode":"57010",
    "sg:province":"SD",
    "sg:tags":[
        "farm",
        "corn",
        "soybean"
    ],
    "wof:name":"Lyman Mollet",
    "wof:placetype":"venue"
},
  "geometry": {"coordinates":[-96.84572199999999,42.816874],"type":"Point"}
}