{
  "type": "Feature",
  "properties": {
    "addr:full":"111 2nd Ave Wall SD 57790",
    "addr:housenumber":"111",
    "addr:postcode":"57790",
    "addr:street":"2Nd Ave",
    "iso:country":"US",
    "sg:address":"111 2nd Ave",
    "sg:city":"Wall",
    "sg:classifiers":[
        {
            "category":"Wholesale",
            "subcategory":"Farm Supplies",
            "type":"Manufacturing & Wholesale Goods"
        }
    ],
    "sg:phone":"+1 605 279 2255",
    "sg:postcode":"57790",
    "sg:province":"SD",
    "sg:tags":[
        "fertilizer"
    ],
    "wof:name":"Johnson's Ranchers Supply Inc",
    "wof:placetype":"venue"
},
  "geometry": {"coordinates":[-102.24061500000001,43.996453],"type":"Point"}
}