{
  "type": "Feature",
  "properties": {
    "iso:country":"US",
    "sg:address":"19738 378th Ave",
    "sg:city":"Wessington",
    "sg:classifiers":[
        {
            "category":"Farming",
            "subcategory":"Farm",
            "type":"Manufacturing & Wholesale Goods"
        }
    ],
    "sg:phone":"+1 605 458 2529",
    "sg:postcode":"57381",
    "sg:province":"SD",
    "sg:tags":[
        "grain",
        "cash"
    ],
    "wof:name":"Zerfoss Hopkins Farm",
    "wof:placetype":"venue"
},
  "geometry": {"coordinates":[-98.620238,44.524514],"type":"Point"}
}