{
  "type": "Feature",
  "properties": {
    "iso:country":"US",
    "sg:address":"2693 Commerce Rd",
    "sg:city":"Rapid City",
    "sg:classifiers":[
        {
            "category":"Home & Garden",
            "subcategory":"Building Materials",
            "type":"Retail Goods"
        }
    ],
    "sg:phone":"+1 605 718 8868",
    "sg:postcode":"57702",
    "sg:province":"SD",
    "wof:name":"Denver Grounting",
    "wof:placetype":"venue"
},
  "geometry": {"coordinates":[-103.263751,44.096607],"type":"Point"}
}