{
  "type": "Feature",
  "properties": {
    "iso:country":"US",
    "sg:address":"510 Main Ave S",
    "sg:city":"Brookings",
    "sg:classifiers":[
        {
            "category":"Social Services",
            "type":"Services"
        }
    ],
    "sg:phone":"+1 605 690 4425",
    "sg:postcode":"57006",
    "sg:province":"SD",
    "sg:tags":[
        "counseling"
    ],
    "wof:name":"Dakota Prairie Counseling",
    "wof:placetype":"venue"
},
  "geometry": {"coordinates":[-96.798699,44.300692],"type":"Point"}
}