{
  "type": "Feature",
  "properties": {
    "addr:full":"23101 157th Ave New Underwood SD 57761",
    "addr:housenumber":"23101",
    "addr:postcode":"57761",
    "addr:street":"157Th Ave",
    "iso:country":"US",
    "sg:address":"23101 157th Ave",
    "sg:city":"New Underwood",
    "sg:classifiers":[
        {
            "category":"Farming",
            "subcategory":"Livestock Farm",
            "type":"Manufacturing & Wholesale Goods"
        }
    ],
    "sg:phone":"+1 605 393 2343",
    "sg:postcode":"57761",
    "sg:province":"SD",
    "sg:tags":[
        "beef",
        "feedlot",
        "cattle"
    ],
    "wof:name":"Vern Powell",
    "wof:placetype":"venue"
},
  "geometry": {"coordinates":[-102.909834,44.050323],"type":"Point"}
}