{
  "type": "Feature",
  "properties": {
    "addr:full":"3200 1st Ave Spearfish SD 57783",
    "addr:housenumber":"3200",
    "addr:postcode":"57783",
    "addr:street":"1St Ave",
    "iso:country":"US",
    "sg:address":"3200 1st Ave",
    "sg:city":"Spearfish",
    "sg:classifiers":[
        {
            "category":"Manufacturing",
            "subcategory":"Glass & Minerals",
            "type":"Manufacturing & Wholesale Goods"
        }
    ],
    "sg:phone":"+1 605 642 3845",
    "sg:postcode":"57783",
    "sg:province":"SD",
    "sg:tags":[
        "ready",
        "concrete",
        "mfg"
    ],
    "wof:name":"Croell Redi-Mix Inc",
    "wof:placetype":"venue"
},
  "geometry": {"coordinates":[-103.800899,44.48045],"type":"Point"}
}