{
  "type": "Feature",
  "properties": {
    "iso:country":"US",
    "sg:address":"308 4th St",
    "sg:city":"Brookings",
    "sg:classifiers":[
        {
            "category":"Recreation",
            "type":"Entertainment"
        }
    ],
    "sg:phone":"+1 605 692 1554",
    "sg:postcode":"57006",
    "sg:province":"SD",
    "sg:tags":[
        "historical"
    ],
    "wof:name":"Downtown Brookings Inc",
    "wof:placetype":"venue"
},
  "geometry": {"coordinates":[-96.80022,44.309027],"type":"Point"}
}