{
  "type": "Feature",
  "properties": {
    "iso:country":"US",
    "sg:address":"16761 355th Ave",
    "sg:city":"Faulkton",
    "sg:classifiers":[
        {
            "category":"Farming",
            "subcategory":"Livestock Farm",
            "type":"Manufacturing & Wholesale Goods"
        }
    ],
    "sg:phone":"+1 605 392 2443",
    "sg:postcode":"57438",
    "sg:province":"SD",
    "sg:tags":[
        "beef",
        "feedlot",
        "cattle"
    ],
    "wof:name":"Craig Huss Farm",
    "wof:placetype":"venue"
},
  "geometry": {"coordinates":[-99.08349699999999,44.960892],"type":"Point"}
}