{
  "type": "Feature",
  "properties": {
    "iso:country":"US",
    "sg:address":"717 S Main St",
    "sg:city":"Aberdeen",
    "sg:classifiers":[
        {
            "category":"Retail",
            "subcategory":"Portrait Studio",
            "type":"Services"
        }
    ],
    "sg:phone":"+1 605 225 5344",
    "sg:postcode":"57401",
    "sg:province":"SD",
    "sg:tags":[
        "photographer"
    ],
    "wof:name":"Hardin's Photography",
    "wof:placetype":"venue"
},
  "geometry": {"coordinates":[-98.487966,45.457906],"type":"Point"}
}