{
  "type": "Feature",
  "properties": {
    "addr:full":"828 8th St S Brookings SD 57006",
    "addr:housenumber":"828",
    "addr:postcode":"57006",
    "addr:street":"8Th St S",
    "iso:country":"US",
    "sg:address":"828 8th St S",
    "sg:city":"Brookings",
    "sg:classifiers":[
        {
            "category":"Organizations",
            "subcategory":"Religious Organization",
            "type":"Services"
        }
    ],
    "sg:phone":"+1 605 697 2882",
    "sg:postcode":"57006",
    "sg:province":"SD",
    "wof:name":"United Church Of Christ",
    "wof:placetype":"venue"
},
  "geometry": {"coordinates":[-96.791054,44.296963],"type":"Point"}
}