{
  "type": "Feature",
  "properties": {
    "iso:country":"US",
    "sg:address":"503 6th St",
    "sg:city":"Brookings",
    "sg:classifiers":[
        {
            "category":"Food & Beverages",
            "subcategory":"Groceries & Convenience Stores",
            "type":"Retail Goods"
        }
    ],
    "sg:phone":"+1 605 692 5499",
    "sg:postcode":"57006",
    "sg:province":"SD",
    "sg:tags":[
        "station",
        "gasoline"
    ],
    "wof:name":"Ampride",
    "wof:placetype":"venue"
},
  "geometry": {"coordinates":[-96.796875,44.311565],"type":"Point"}
}