{
  "type": "Feature",
  "properties": {
    "iso:country":"US",
    "sg:address":"2032 S Grange Ave",
    "sg:city":"Sioux Falls",
    "sg:classifiers":[
        {
            "category":"Professional",
            "subcategory":"Research",
            "type":"Services"
        }
    ],
    "sg:phone":"+1 605 336 5493",
    "sg:postcode":"57105",
    "sg:province":"SD",
    "sg:tags":[
        "commercial",
        "physical"
    ],
    "wof:name":"Archelogy Lab Agustana College",
    "wof:placetype":"venue"
},
  "geometry": {"coordinates":[-96.741169,43.526394],"type":"Point"}
}