{
  "type": "Feature",
  "properties": {
    "addr:full":"25715 403rd Ave Mitchell SD 57301",
    "addr:housenumber":"25715",
    "addr:postcode":"57301",
    "addr:street":"403Rd Ave",
    "iso:country":"US",
    "sg:address":"25715 403rd Ave",
    "sg:city":"Mitchell",
    "sg:classifiers":[
        {
            "category":"Organizations",
            "subcategory":"Religious Organization",
            "type":"Services"
        }
    ],
    "sg:phone":"+1 605 337 3211",
    "sg:postcode":"57301",
    "sg:province":"SD",
    "sg:tags":[
        "church"
    ],
    "wof:name":"Mitchell Sda Church",
    "wof:placetype":"venue"
},
  "geometry": {"coordinates":[-98.146253,43.656194],"type":"Point"}
}