{
  "type": "Feature",
  "properties": {
    "iso:country":"US",
    "sg:address":"551 N 3rd Ave",
    "sg:city":"Canistota",
    "sg:classifiers":[
        {
            "category":"Manufacturing",
            "subcategory":"Electronics",
            "type":"Manufacturing & Wholesale Goods"
        }
    ],
    "sg:phone":"+1 605 296 3471",
    "sg:postcode":"57012",
    "sg:province":"SD",
    "sg:tags":[
        "equipment",
        "electronic",
        "supply"
    ],
    "sg:website":"www.dynage.com",
    "wof:name":"Oakleaf Inc",
    "wof:placetype":"venue"
},
  "geometry": {"coordinates":[-97.292783,43.598497],"type":"Point"}
}