{
  "type": "Feature",
  "properties": {
    "iso:country":"US",
    "sg:address":"2023 Crystal Ave",
    "sg:city":"Aberdeen",
    "sg:classifiers":[
        {
            "category":"Social Services",
            "subcategory":"Child Care",
            "type":"Services"
        }
    ],
    "sg:phone":"+1 605 229 2567",
    "sg:postcode":"57401",
    "sg:province":"SD",
    "sg:tags":[
        "day"
    ],
    "wof:name":"Discovery Land Day Care",
    "wof:placetype":"venue"
},
  "geometry": {"coordinates":[-98.515943,45.430547],"type":"Point"}
}