{
  "type": "Feature",
  "properties": {
    "iso:country":"US",
    "sg:address":"21181 460th Ave",
    "sg:city":"Volga",
    "sg:classifiers":[
        {
            "category":"Autos & Motor Vehicles",
            "subcategory":"Automobile Sales",
            "type":"Retail Goods"
        }
    ],
    "sg:phone":"+1 605 826 4204",
    "sg:postcode":"57071",
    "sg:province":"SD",
    "sg:tags":[
        "car",
        "dealer"
    ],
    "wof:name":"Shorty's Country Auto Sales",
    "wof:placetype":"venue"
},
  "geometry": {"coordinates":[-97.00762,44.313306],"type":"Point"}
}