{
  "type": "Feature",
  "properties": {
    "iso:country":"US",
    "sg:address":"1659 Dakota Ave S",
    "sg:city":"Huron",
    "sg:classifiers":[
        {
            "category":"Autos & Motor Vehicles",
            "subcategory":"Auto Supplies",
            "type":"Retail Goods"
        }
    ],
    "sg:phone":"+1 605 352 4980",
    "sg:postcode":"57350",
    "sg:province":"SD",
    "sg:tags":[
        "automobile",
        "parts"
    ],
    "wof:name":"Advance Auto Parts Inc",
    "wof:placetype":"venue"
},
  "geometry": {"coordinates":[-98.214164,44.347077],"type":"Point"}
}