{
  "type": "Feature",
  "properties": {
    "iso:country":"US",
    "sg:address":"708 8th St",
    "sg:city":"Armour",
    "sg:classifiers":[
        {
            "category":"Government",
            "subcategory":"Office",
            "type":"Public Place"
        }
    ],
    "sg:phone":"+1 605 724 2758",
    "sg:postcode":"57313",
    "sg:province":"SD",
    "sg:tags":[
        "county",
        "program",
        "health"
    ],
    "wof:name":"Douglas County Health Nurse",
    "wof:placetype":"venue"
},
  "geometry": {"coordinates":[-98.346369,43.324914],"type":"Point"}
}