{
  "type": "Feature",
  "properties": {
    "addr:full":"5224 S Sweetbriar Ct Sioux Falls SD 57108",
    "addr:housenumber":"5224",
    "addr:postcode":"57108",
    "addr:street":"S Sweetbriar Ct",
    "iso:country":"US",
    "sg:address":"5224 S Sweetbriar Ct",
    "sg:city":"Sioux Falls",
    "sg:classifiers":[
        {
            "category":"Health Services",
            "subcategory":"Doctor",
            "type":"Services"
        }
    ],
    "sg:phone":"+1 605 335 9591",
    "sg:postcode":"57108",
    "sg:province":"SD",
    "sg:tags":[
        "medical"
    ],
    "wof:name":"Thompson Clinic",
    "wof:placetype":"venue"
},
  "geometry": {"coordinates":[-96.729636,43.496624],"type":"Point"}
}