{
  "type": "Feature",
  "properties": {
    "iso:country":"US",
    "sg:address":"1801 E Spruce St",
    "sg:city":"Mitchell",
    "sg:classifiers":[
        {
            "category":"Wholesale",
            "subcategory":"Farm Supplies",
            "type":"Manufacturing & Wholesale Goods"
        }
    ],
    "sg:phone":"+1 605 996 6543",
    "sg:postcode":"57301",
    "sg:province":"SD",
    "sg:tags":[
        "livestock"
    ],
    "wof:name":"Mitchell Livestock Auction Co",
    "wof:placetype":"venue"
},
  "geometry": {"coordinates":[-97.99963,43.687615],"type":"Point"}
}