{
  "type": "Feature",
  "properties": {
    "iso:country":"US",
    "sg:address":"1313 Ferdig St",
    "sg:city":"Yankton",
    "sg:classifiers":[
        {
            "category":"Recreation",
            "subcategory":"Marina",
            "type":"Entertainment"
        }
    ],
    "sg:phone":"+1 605 665 7848",
    "sg:postcode":"57078",
    "sg:province":"SD",
    "sg:tags":[
        "repairing",
        "boat"
    ],
    "wof:name":"Larsen Marine",
    "wof:placetype":"venue"
},
  "geometry": {"coordinates":[-97.37242500000001,42.883354],"type":"Point"}
}