{
  "type": "Feature",
  "properties": {
    "iso:country":"US",
    "sg:address":"18657 295th Ave",
    "sg:city":"Onida",
    "sg:classifiers":[
        {
            "category":"Farming",
            "subcategory":"Livestock Farm",
            "type":"Manufacturing & Wholesale Goods"
        }
    ],
    "sg:phone":"+1 605 264 5352",
    "sg:postcode":"57564",
    "sg:province":"SD",
    "sg:tags":[
        "beef",
        "feedlot",
        "cattle"
    ],
    "wof:name":"Delbert L Fast",
    "wof:placetype":"venue"
},
  "geometry": {"coordinates":[-100.243397,44.684402],"type":"Point"}
}