{
  "type": "Feature",
  "properties": {
    "iso:country":"US",
    "sg:address":"2613 W 29th St",
    "sg:city":"Sioux Falls",
    "sg:classifiers":[
        {
            "category":"Professional",
            "subcategory":"Management & Consulting",
            "type":"Services"
        }
    ],
    "sg:phone":"+1 605 338 5551",
    "sg:postcode":"57105",
    "sg:province":"SD",
    "sg:website":"www.fyi-dakota.com",
    "wof:name":"For Your Information",
    "wof:placetype":"venue"
},
  "geometry": {"coordinates":[-96.759353,43.526267],"type":"Point"}
}