{
  "type": "Feature",
  "properties": {
    "addr:full":"15524 485th Ave Milbank SD 57252",
    "addr:housenumber":"15524",
    "addr:postcode":"57252",
    "addr:street":"485Th Ave",
    "iso:country":"US",
    "sg:address":"15524 485th Ave",
    "sg:city":"Milbank",
    "sg:classifiers":[
        {
            "category":"Farming",
            "subcategory":"Dairy Farm",
            "type":"Manufacturing & Wholesale Goods"
        }
    ],
    "sg:phone":"+1 605 432 4459",
    "sg:postcode":"57252",
    "sg:province":"SD",
    "wof:name":"Sunny Pine Farm",
    "wof:placetype":"venue"
},
  "geometry": {"coordinates":[-96.497821,45.133118],"type":"Point"}
}