{
  "type": "Feature",
  "properties": {
    "iso:country":"US",
    "sg:address":"264 Kansas Ave SE",
    "sg:city":"Huron",
    "sg:classifiers":[
        {
            "category":"Shopping",
            "type":"Retail Goods"
        }
    ],
    "sg:phone":"+1 605 352 3949",
    "sg:postcode":"57350",
    "sg:province":"SD",
    "sg:tags":[
        "hearing",
        "equipment",
        "supply",
        "merchandise",
        "impaired"
    ],
    "wof:name":"Palmer Hearing Aid Service",
    "wof:placetype":"venue"
},
  "geometry": {"coordinates":[-98.212369,44.363672],"type":"Point"}
}