{
  "type": "Feature",
  "properties": {
    "iso:country":"US",
    "sg:address":"1301 S Duluth Ave",
    "sg:city":"Sioux Falls",
    "sg:classifiers":[
        {
            "category":"Shopping",
            "subcategory":"Used Merchandise",
            "type":"Retail Goods"
        }
    ],
    "sg:phone":"+1 605 332 9662",
    "sg:postcode":"57105",
    "sg:province":"SD",
    "sg:tags":[
        "antique",
        "repair"
    ],
    "wof:name":"Kolbe's Antiques Books Clocks",
    "wof:placetype":"venue"
},
  "geometry": {"coordinates":[-96.733785,43.533044],"type":"Point"}
}