{
  "type": "Feature",
  "properties": {
    "iso:country":"US",
    "sg:address":"113 W Lawler Ave",
    "sg:city":"Chamberlain",
    "sg:classifiers":[
        {
            "category":"Health Services",
            "subcategory":"Chiropractor",
            "type":"Services"
        }
    ],
    "sg:phone":"+1 605 734 6968",
    "sg:postcode":"57325",
    "sg:province":"SD",
    "wof:name":"Chamberlain Chiropractic",
    "wof:placetype":"venue"
},
  "geometry": {"coordinates":[-99.331322,43.811271],"type":"Point"}
}