{
  "type": "Feature",
  "properties": {
    "iso:country":"US",
    "sg:address":"3532 Custer Ave SE",
    "sg:city":"Huron",
    "sg:classifiers":[
        {
            "category":"Organizations",
            "subcategory":"Non-profit Organization",
            "type":"Services"
        }
    ],
    "sg:phone":"+1 605 352 9098",
    "sg:postcode":"57350",
    "sg:province":"SD",
    "sg:tags":[
        "social"
    ],
    "wof:name":"Our Home Inc",
    "wof:placetype":"venue"
},
  "geometry": {"coordinates":[-98.17446700000001,44.326739],"type":"Point"}
}