{
  "type": "Feature",
  "properties": {
    "iso:country":"US",
    "sg:address":"3301 Grandview Dr",
    "sg:city":"Rapid City",
    "sg:classifiers":[
        {
            "category":"Education",
            "subcategory":"School",
            "type":"Public Place"
        }
    ],
    "sg:phone":"+1 605 394 1829",
    "sg:postcode":"57701",
    "sg:province":"SD",
    "sg:tags":[
        "executive"
    ],
    "sg:website":"www.grandview.com",
    "wof:name":"Grandview Elementary School",
    "wof:placetype":"venue"
},
  "geometry": {"coordinates":[-103.216438,44.052271],"type":"Point"}
}