{
  "type": "Feature",
  "properties": {
    "iso:country":"US",
    "sg:address":"11750 389th Ave",
    "sg:city":"Westport",
    "sg:phone":"+1 605 329 2714",
    "sg:postcode":"57481",
    "sg:province":"SD",
    "sg:tags":[
        "farm",
        "soybean"
    ],
    "wof:name":"Engelhart Darrin",
    "wof:placetype":"venue"
},
  "geometry": {"coordinates":[-98.455578,45.680812],"type":"Point"}
}