{
  "type": "Feature",
  "properties": {
    "addr:full":"23884 US Hwy 385 Hill City SD 57745",
    "addr:postcode":"23884;57745",
    "addr:street":"Us Hwy 385",
    "iso:country":"US",
    "sg:address":"23884 US Hwy 385",
    "sg:city":"Hill City",
    "sg:classifiers":[
        {
            "category":"Travel",
            "subcategory":"Hotels & Motels",
            "type":"Entertainment"
        }
    ],
    "sg:phone":"+1 605 574 2347",
    "sg:postcode":"57745",
    "sg:province":"SD",
    "sg:tags":[
        "operation"
    ],
    "wof:name":"Lode Stone Motel",
    "wof:placetype":"venue"
},
  "geometry": {"coordinates":[-103.525572,43.9462],"type":"Point"}
}