{
  "type": "Feature",
  "properties": {
    "iso:country":"US",
    "sg:address":"42855 287th St",
    "sg:city":"Menno",
    "sg:classifiers":[
        {
            "category":"Farming",
            "subcategory":"Farm",
            "type":"Manufacturing & Wholesale Goods"
        }
    ],
    "sg:phone":"+1 605 387 5448",
    "sg:postcode":"57045",
    "sg:province":"SD",
    "sg:tags":[
        "crop",
        "general"
    ],
    "wof:name":"Brian D Herboldt",
    "wof:placetype":"venue"
},
  "geometry": {"coordinates":[-97.62716500000001,43.226494],"type":"Point"}
}