{
  "type": "Feature",
  "properties": {
    "iso:country":"US",
    "sg:address":"1852 Lombardy Dr",
    "sg:city":"Rapid City",
    "sg:classifiers":[
        {
            "category":"Freight",
            "type":"Transportation"
        }
    ],
    "sg:phone":"+1 605 341 3042",
    "sg:postcode":"57703",
    "sg:province":"SD",
    "sg:tags":[
        "commercial",
        "storage"
    ],
    "wof:name":"Sto-N-Go Storage Units",
    "wof:placetype":"venue"
},
  "geometry": {"coordinates":[-103.18487,44.063015],"type":"Point"}
}