{
  "type": "Feature",
  "properties": {
    "addr:full":"18917 446th Ave Hayti SD 57241",
    "addr:housenumber":"18917",
    "addr:postcode":"57241",
    "addr:street":"446Th Ave",
    "iso:country":"US",
    "sg:address":"18917 446th Ave",
    "sg:city":"Hayti",
    "sg:phone":"+1 605 783 3809",
    "sg:postcode":"57241",
    "sg:province":"SD",
    "sg:tags":[
        "farm",
        "corn",
        "soybean"
    ],
    "wof:name":"Rick Wadsworth",
    "wof:placetype":"venue"
},
  "geometry": {"coordinates":[-97.289435,44.642747],"type":"Point"}
}