{
  "type": "Feature",
  "properties": {
    "iso:country":"US",
    "sg:address":"30679 457th Ave",
    "sg:city":"Wakonda",
    "sg:phone":"+1 605 267 2412",
    "sg:postcode":"57073",
    "sg:province":"SD",
    "sg:tags":[
        "farm",
        "corn",
        "soybean"
    ],
    "wof:name":"Gordon Jensen",
    "wof:placetype":"venue"
},
  "geometry": {"coordinates":[-97.062331,42.942],"type":"Point"}
}