{
  "type": "Feature",
  "properties": {
    "iso:country":"US",
    "sg:address":"2609 S Holly Ave",
    "sg:city":"Sioux Falls",
    "sg:classifiers":[
        {
            "category":"Organizations",
            "subcategory":"Religious Organization",
            "type":"Services"
        }
    ],
    "sg:phone":"+1 605 334 5248",
    "sg:postcode":"57105",
    "sg:province":"SD",
    "sg:tags":[
        "church"
    ],
    "wof:name":"Se District United Methodist",
    "wof:placetype":"venue"
},
  "geometry": {"coordinates":[-96.754944,43.520904],"type":"Point"}
}