{
  "type": "Feature",
  "properties": {
    "addr:full":"4525 N Haines Ave Rapid City SD 57701",
    "addr:housenumber":"4525",
    "addr:postcode":"57701",
    "addr:street":"N Haines Ave",
    "iso:country":"US",
    "sg:address":"4525 N Haines Ave",
    "sg:city":"Rapid City",
    "sg:classifiers":[
        {
            "category":"Food & Beverages",
            "subcategory":"Groceries & Convenience Stores",
            "type":"Retail Goods"
        }
    ],
    "sg:phone":"+1 605 342 5506",
    "sg:postcode":"57701",
    "sg:province":"SD",
    "wof:name":"Hendersons Ranch",
    "wof:placetype":"venue"
},
  "geometry": {"coordinates":[-103.223107,44.129213],"type":"Point"}
}