{
  "type": "Feature",
  "properties": {
    "addr:full":"337 Main St Hill City SD 57745",
    "addr:housenumber":"337",
    "addr:postcode":"57745",
    "addr:street":"Main St",
    "iso:country":"US",
    "sg:address":"337 Main St",
    "sg:city":"Hill City",
    "sg:classifiers":[
        {
            "category":"Shopping",
            "subcategory":"Gifts & Souvenirs",
            "type":"Retail Goods"
        }
    ],
    "sg:phone":"+1 605 574 9079",
    "sg:postcode":"57745",
    "sg:province":"SD",
    "sg:tags":[
        "shop"
    ],
    "wof:name":"Double D Gifts",
    "wof:placetype":"venue"
},
  "geometry": {"coordinates":[-103.57553299999999,43.931986],"type":"Point"}
}