{
  "type": "Feature",
  "properties": {
    "iso:country":"US",
    "sg:address":"900 E Benson Rd",
    "sg:city":"Sioux Falls",
    "sg:classifiers":[
        {
            "category":"Freight",
            "type":"Transportation"
        }
    ],
    "sg:phone":"+1 605 339 3999",
    "sg:postcode":"57104",
    "sg:province":"SD",
    "sg:tags":[
        "delivery"
    ],
    "wof:name":"Beaverex Services Inc",
    "wof:placetype":"venue"
},
  "geometry": {"coordinates":[-96.71468299999999,43.587457],"type":"Point"}
}