{
  "type": "Feature",
  "properties": {
    "addr:full":"1104 Crow Peak Ln Spearfish SD 57783",
    "addr:housenumber":"1104",
    "addr:postcode":"57783",
    "addr:street":"Crow Peak Ln",
    "iso:country":"US",
    "sg:address":"1104 Crow Peak Ln",
    "sg:city":"Spearfish",
    "sg:classifiers":[
        {
            "category":"Insurance",
            "subcategory":"Insurance Agent",
            "type":"Services"
        }
    ],
    "sg:phone":"+1 605 642 9644",
    "sg:postcode":"57783",
    "sg:province":"SD",
    "wof:name":"Horace Mann Insurance Co",
    "wof:placetype":"venue"
},
  "geometry": {"coordinates":[-103.793396,44.462965],"type":"Point"}
}