{
  "type": "Feature",
  "properties": {
    "iso:country":"US",
    "sg:address":"3605 W Tickman St",
    "sg:city":"Sioux Falls",
    "sg:classifiers":[
        {
            "category":"Building & Trades",
            "subcategory":"Plumbing",
            "type":"Services"
        }
    ],
    "sg:phone":"+1 605 334 3444",
    "sg:postcode":"57107",
    "sg:province":"SD",
    "sg:tags":[
        "plumbing",
        "contractor"
    ],
    "wof:name":"Bioway America Air Tech",
    "wof:placetype":"venue"
},
  "geometry": {"coordinates":[-96.771727,43.582613],"type":"Point"}
}