{
  "type": "Feature",
  "properties": {
    "iso:country":"US",
    "sg:address":"500 S A Ave",
    "sg:city":"New Underwood",
    "sg:classifiers":[
        {
            "category":"Recreation",
            "type":"Entertainment"
        }
    ],
    "sg:phone":"+1 605 754 9908",
    "sg:postcode":"57761",
    "sg:province":"SD",
    "sg:tags":[
        "hall",
        "auditorium"
    ],
    "wof:name":"New Underwood Community Ctr",
    "wof:placetype":"venue"
},
  "geometry": {"coordinates":[-102.83637,44.091182],"type":"Point"}
}