{
  "type": "Feature",
  "properties": {
    "iso:country":"US",
    "sg:address":"2101 Rand Rd",
    "sg:city":"Rapid City",
    "sg:classifiers":[
        {
            "category":"Wholesale",
            "subcategory":"Groceries",
            "type":"Manufacturing & Wholesale Goods"
        }
    ],
    "sg:phone":"+1 605 342 2230",
    "sg:postcode":"57702",
    "sg:province":"SD",
    "sg:tags":[
        "food",
        "product"
    ],
    "sg:website":"www.fritolay.com",
    "wof:name":"Frito-Lay Inc",
    "wof:placetype":"venue"
},
  "geometry": {"coordinates":[-103.26329800000001,44.101905],"type":"Point"}
}