{
  "type": "Feature",
  "properties": {
    "addr:full":"25 Kirk Rd Deadwood SD 57732",
    "addr:housenumber":"25",
    "addr:postcode":"57732",
    "addr:street":"Kirk Rd",
    "iso:country":"US",
    "sg:address":"25 Kirk Rd",
    "sg:city":"Deadwood",
    "sg:classifiers":[
        {
            "category":"Real Estate",
            "subcategory":"Surveying",
            "type":"Services"
        }
    ],
    "sg:phone":"+1 605 578 1637",
    "sg:postcode":"57732",
    "sg:province":"SD",
    "sg:tags":[
        "surveyor"
    ],
    "wof:name":"Arleth & Assoc",
    "wof:placetype":"venue"
},
  "geometry": {"coordinates":[-103.74367100000001,44.351457],"type":"Point"}
}