{
  "type": "Feature",
  "properties": {
    "iso:country":"US",
    "sg:address":"26555 465th Ave",
    "sg:city":"Hartford",
    "sg:classifiers":[
        {
            "category":"Shopping",
            "subcategory":"Bicycles & Sporting Goods",
            "type":"Retail Goods"
        }
    ],
    "sg:phone":"+1 605 526 4353",
    "sg:postcode":"57033",
    "sg:province":"SD",
    "wof:name":"Custom Golf Works",
    "wof:placetype":"venue"
},
  "geometry": {"coordinates":[-96.910475,43.537915],"type":"Point"}
}