{
  "type": "Feature",
  "properties": {
    "addr:full":"1230 N 5th St Spearfish SD 57783",
    "addr:housenumber":"1230",
    "addr:postcode":"57783",
    "addr:street":"N 5Th St",
    "iso:country":"US",
    "sg:address":"1230 N 5th St",
    "sg:city":"Spearfish",
    "sg:classifiers":[
        {
            "category":"Real Estate",
            "subcategory":"Real Estate Agent",
            "type":"Services"
        }
    ],
    "sg:phone":"+1 605 642 5723",
    "sg:postcode":"57783",
    "sg:province":"SD",
    "wof:name":"Johnson/Joy Real Estate",
    "wof:placetype":"venue"
},
  "geometry": {"coordinates":[-103.862116,44.495948],"type":"Point"}
}