{
  "type": "Feature",
  "properties": {
    "iso:country":"US",
    "sg:address":"2250 Park Ave",
    "sg:city":"Sturgis",
    "sg:classifiers":[
        {
            "category":"Food & Beverages",
            "subcategory":"Meat & Fish",
            "type":"Retail Goods"
        }
    ],
    "sg:phone":"+1 605 347 2626",
    "sg:postcode":"57785",
    "sg:province":"SD",
    "wof:name":"GNG Enterprises Incop",
    "wof:placetype":"venue"
},
  "geometry": {"coordinates":[-103.52735800000001,44.417865],"type":"Point"}
}