{
  "type": "Feature",
  "properties": {
    "iso:country":"US",
    "sg:address":"214 11th St",
    "sg:city":"Ipswich",
    "sg:classifiers":[
        {
            "category":"Retail",
            "subcategory":"Auto Repair",
            "type":"Services"
        }
    ],
    "sg:phone":"+1 605 426 6831",
    "sg:postcode":"57451",
    "sg:province":"SD",
    "sg:tags":[
        "body"
    ],
    "wof:name":"Heiers Body & Repair Shop",
    "wof:placetype":"venue"
},
  "geometry": {"coordinates":[-99.038904,45.446218],"type":"Point"}
}