{
  "type": "Feature",
  "properties": {
    "iso:country":"US",
    "sg:address":"35968 133rd St",
    "sg:city":"Ipswich",
    "sg:classifiers":[
        {
            "category":"Professional",
            "type":"Services"
        }
    ],
    "sg:phone":"+1 605 426 6110",
    "sg:postcode":"57451",
    "sg:province":"SD",
    "wof:name":"Wesley G Stern",
    "wof:placetype":"venue"
},
  "geometry": {"coordinates":[-99.006498,45.46237],"type":"Point"}
}