{
  "type": "Feature",
  "properties": {
    "iso:country":"US",
    "sg:address":"713 E Main St",
    "sg:city":"Parkston",
    "sg:classifiers":[
        {
            "category":"Shopping",
            "subcategory":"Florist",
            "type":"Retail Goods"
        }
    ],
    "sg:phone":"+1 605 928 3800",
    "sg:postcode":"57366",
    "sg:province":"SD",
    "wof:name":"M S Bumblebees Flowers & Gifts",
    "wof:placetype":"venue"
},
  "geometry": {"coordinates":[-97.976559,43.39482],"type":"Point"}
}