{
  "type": "Feature",
  "properties": {
    "iso:country":"US",
    "sg:address":"300 State Hwy 44",
    "sg:city":"Chancellor",
    "sg:classifiers":[
        {
            "category":"Food & Beverages",
            "subcategory":"Groceries & Convenience Stores",
            "type":"Retail Goods"
        }
    ],
    "sg:phone":"+1 605 647 2700",
    "sg:postcode":"57015",
    "sg:province":"SD",
    "sg:website":"www.countrypride.com",
    "wof:name":"Ampride",
    "wof:placetype":"venue"
},
  "geometry": {"coordinates":[-96.988451,43.373667],"type":"Point"}
}