{
  "type": "Feature",
  "properties": {
    "addr:full":"207 S Monroe Ave New Underwood SD 57761",
    "addr:housenumber":"207",
    "addr:postcode":"57761",
    "addr:street":"S Monroe Ave",
    "iso:country":"US",
    "sg:address":"207 S Monroe Ave",
    "sg:city":"New Underwood",
    "sg:classifiers":[
        {
            "category":"Organizations",
            "subcategory":"Religious Organization",
            "type":"Services"
        }
    ],
    "sg:phone":"+1 605 754 6446",
    "sg:postcode":"57761",
    "sg:province":"SD",
    "sg:tags":[
        "church"
    ],
    "wof:name":"St John's Catholic Rectory",
    "wof:placetype":"venue"
},
  "geometry": {"coordinates":[-102.83073899999999,44.09515],"type":"Point"}
}