{
  "type": "Feature",
  "properties": {
    "addr:full":"129 N Main Ave Hartford SD 57033",
    "addr:housenumber":"129",
    "addr:postcode":"57033",
    "addr:street":"N Main Ave",
    "iso:country":"US",
    "sg:address":"129 N Main Ave",
    "sg:city":"Hartford",
    "sg:classifiers":[
        {
            "category":"Health Services",
            "subcategory":"Health Practitioner",
            "type":"Services"
        }
    ],
    "sg:phone":"+1 605 528 7471",
    "sg:postcode":"57033",
    "sg:province":"SD",
    "wof:name":"Royal Trtmnt Thrpeutic Massage",
    "wof:placetype":"venue"
},
  "geometry": {"coordinates":[-96.945745,43.622725],"type":"Point"}
}