{
  "type": "Feature",
  "properties": {
    "iso:country":"US",
    "sg:address":"411 N 4th St",
    "sg:city":"Beresford",
    "sg:classifiers":[
        {
            "category":"Real Estate",
            "subcategory":"Real Estate Operator",
            "type":"Services"
        }
    ],
    "sg:phone":"+1 605 763 5411",
    "sg:postcode":"57004",
    "sg:province":"SD",
    "sg:tags":[
        "property",
        "lessor"
    ],
    "wof:name":"Johnson Willma",
    "wof:placetype":"venue"
},
  "geometry": {"coordinates":[-96.77568599999999,43.084596],"type":"Point"}
}