{
  "type": "Feature",
  "properties": {
    "iso:country":"US",
    "sg:address":"101 E Main St",
    "sg:city":"Canistota",
    "sg:classifiers":[
        {
            "category":"Travel",
            "subcategory":"Hotels & Motels",
            "type":"Entertainment"
        }
    ],
    "sg:phone":"+1 605 296 3555",
    "sg:postcode":"57012",
    "sg:province":"SD",
    "wof:name":"Cameron Inn",
    "wof:placetype":"venue"
},
  "geometry": {"coordinates":[-97.285108,43.598029],"type":"Point"}
}