{
  "type": "Feature",
  "properties": {
    "iso:country":"US",
    "sg:address":"43639 277th St",
    "sg:city":"Freeman",
    "sg:phone":"+1 605 925 7952",
    "sg:postcode":"57029",
    "sg:province":"SD",
    "sg:tags":[
        "farm",
        "corn",
        "soybean"
    ],
    "wof:name":"Greg Kleinsasser",
    "wof:placetype":"venue"
},
  "geometry": {"coordinates":[-97.476041,43.37152],"type":"Point"}
}