{
  "type": "Feature",
  "properties": {
    "iso:country":"US",
    "sg:address":"24 5th St SE",
    "sg:city":"Watertown",
    "sg:classifiers":[
        {
            "category":"Restaurant",
            "type":"Food & Drink"
        }
    ],
    "sg:phone":"+1 605 886 6098",
    "sg:postcode":"57201",
    "sg:province":"SD",
    "wof:name":"Burger Time",
    "wof:placetype":"venue"
},
  "geometry": {"coordinates":[-97.106496,44.898571],"type":"Point"}
}