{
  "type": "Feature",
  "properties": {
    "iso:country":"US",
    "sg:address":"3800 W Technology Cir",
    "sg:city":"Sioux Falls",
    "sg:classifiers":[
        {
            "category":"Professional",
            "subcategory":"Research",
            "type":"Services"
        }
    ],
    "sg:phone":"+1 605 361 5728",
    "sg:postcode":"57106",
    "sg:province":"SD",
    "sg:tags":[
        "ergonomics"
    ],
    "wof:name":"Human Engineering Solutions",
    "wof:placetype":"venue"
},
  "geometry": {"coordinates":[-96.772381,43.505185],"type":"Point"}
}