{
  "type": "Feature",
  "properties": {
    "addr:full":"606 Mount Rushmore Rd Custer SD 57730",
    "addr:housenumber":"606",
    "addr:postcode":"57730",
    "addr:street":"Mount Rushmore Rd",
    "iso:country":"US",
    "sg:address":"606 Mount Rushmore Rd",
    "sg:city":"Custer",
    "sg:classifiers":[
        {
            "category":"Shopping",
            "subcategory":"Used Merchandise",
            "type":"Retail Goods"
        }
    ],
    "sg:phone":"+1 605 673 3293",
    "sg:postcode":"57730",
    "sg:province":"SD",
    "wof:name":"Re Uzit Shop",
    "wof:placetype":"venue"
},
  "geometry": {"coordinates":[-103.597937,43.766788],"type":"Point"}
}