{
  "type": "Feature",
  "properties": {
    "addr:full":"39478 234th St Woonsocket SD 57385",
    "addr:housenumber":"39478",
    "addr:postcode":"57385",
    "addr:street":"234Th St",
    "iso:country":"US",
    "sg:address":"39478 234th St",
    "sg:city":"Woonsocket",
    "sg:phone":"+1 605 796 4191",
    "sg:postcode":"57385",
    "sg:province":"SD",
    "sg:tags":[
        "farm",
        "corn"
    ],
    "wof:name":"Swenson Bros Farm",
    "wof:placetype":"venue"
},
  "geometry": {"coordinates":[-98.328317,43.995942],"type":"Point"}
}