{
  "type": "Feature",
  "properties": {
    "iso:country":"US",
    "sg:address":"754 22nd Ave S",
    "sg:city":"Brookings",
    "sg:classifiers":[
        {
            "category":"Professional",
            "subcategory":"Computer Services",
            "type":"Services"
        }
    ],
    "sg:phone":"+1 605 696 5500",
    "sg:postcode":"57006",
    "sg:province":"SD",
    "sg:tags":[
        "consultant",
        "designer",
        "datum",
        "system"
    ],
    "sg:website":"www.fairisaac.com",
    "wof:name":"Fair Isaac",
    "wof:placetype":"venue"
},
  "geometry": {"coordinates":[-96.768375,44.297433],"type":"Point"}
}