{
  "type": "Feature",
  "properties": {
    "addr:full":"1141 Deadwood Ave N Rapid City SD 57702",
    "addr:housenumber":"1141",
    "addr:postcode":"57702",
    "addr:street":"Deadwood Ave N",
    "iso:country":"US",
    "sg:address":"1141 Deadwood Ave N",
    "sg:city":"Rapid City",
    "sg:classifiers":[
        {
            "category":"Manufacturing",
            "subcategory":"Furniture",
            "type":"Manufacturing & Wholesale Goods"
        }
    ],
    "sg:phone":"+1 605 343 7457",
    "sg:postcode":"57702",
    "sg:province":"SD",
    "wof:name":"Stratman Studio & Design",
    "wof:placetype":"venue"
},
  "geometry": {"coordinates":[-103.271899,44.141783],"type":"Point"}
}