{
  "type": "Feature",
  "properties": {
    "iso:country":"US",
    "sg:address":"300 US Hwy 12",
    "sg:city":"Webster",
    "sg:classifiers":[
        {
            "category":"Autos & Motor Vehicles",
            "subcategory":"Auto Supplies",
            "type":"Retail Goods"
        }
    ],
    "sg:phone":"+1 605 345 3303",
    "sg:postcode":"57274",
    "sg:province":"SD",
    "wof:name":"Hedahls Auto Parts",
    "wof:placetype":"venue"
},
  "geometry": {"coordinates":[-97.51603,45.340989],"type":"Point"}
}