{
  "type": "Feature",
  "properties": {
    "iso:country":"US",
    "sg:address":"824 Fairview St",
    "sg:city":"Rapid City",
    "sg:classifiers":[
        {
            "category":"Social Services",
            "subcategory":"Adult Care",
            "type":"Services"
        }
    ],
    "sg:phone":"+1 605 342 1790",
    "sg:postcode":"57701",
    "sg:province":"SD",
    "sg:tags":[
        "home",
        "residential"
    ],
    "wof:name":"Norton Guest Home",
    "wof:placetype":"venue"
},
  "geometry": {"coordinates":[-103.23378200000001,44.073829],"type":"Point"}
}