{
  "type": "Feature",
  "properties": {
    "iso:country":"US",
    "sg:address":"23932 403rd Ave",
    "sg:city":"Letcher",
    "sg:classifiers":[
        {
            "category":"Retail",
            "subcategory":"Animal Services",
            "type":"Services"
        }
    ],
    "sg:phone":"+1 605 248 2667",
    "sg:postcode":"57359",
    "sg:province":"SD",
    "wof:name":"Golden Field Kennels",
    "wof:placetype":"venue"
},
  "geometry": {"coordinates":[-98.151461,43.919776],"type":"Point"}
}