{
  "type": "Feature",
  "properties": {
    "iso:country":"US",
    "sg:address":"120 S Sunset Dr",
    "sg:city":"Ipswich",
    "sg:classifiers":[
        {
            "category":"Professional",
            "subcategory":"Advertising",
            "type":"Services"
        }
    ],
    "sg:phone":"+1 605 225 1702",
    "sg:postcode":"57451",
    "sg:province":"SD",
    "sg:tags":[
        "promotion"
    ],
    "wof:name":"Angling Enterprises",
    "wof:placetype":"venue"
},
  "geometry": {"coordinates":[-98.734328,45.460687],"type":"Point"}
}