{
  "type": "Feature",
  "properties": {
    "addr:full":"400 E 60th St Sioux Falls SD 57104",
    "addr:housenumber":"400",
    "addr:postcode":"57104",
    "addr:street":"E 60Th St",
    "iso:country":"US",
    "sg:address":"400 E 60th St",
    "sg:city":"Sioux Falls",
    "sg:classifiers":[
        {
            "category":"Retail",
            "subcategory":"Auto Repair",
            "type":"Services"
        }
    ],
    "sg:phone":"+1 605 339 3216",
    "sg:postcode":"57104",
    "sg:province":"SD",
    "sg:tags":[
        "repairing",
        "tire"
    ],
    "wof:name":"Graham Tire Co-Commercial Tire",
    "wof:placetype":"venue"
},
  "geometry": {"coordinates":[-96.71809399999999,43.602005],"type":"Point"}
}