{
  "type": "Feature",
  "properties": {
    "addr:full":"45339 300th St Wakonda SD 57073",
    "addr:housenumber":"45339",
    "addr:postcode":"57073",
    "addr:street":"300Th St",
    "iso:country":"US",
    "sg:address":"45339 300th St",
    "sg:city":"Wakonda",
    "sg:classifiers":[
        {
            "category":"Farming",
            "subcategory":"Farm",
            "type":"Manufacturing & Wholesale Goods"
        }
    ],
    "sg:phone":"+1 605 267 2605",
    "sg:postcode":"57073",
    "sg:province":"SD",
    "sg:tags":[
        "crop",
        "general"
    ],
    "wof:name":"Dennis Ganschow",
    "wof:placetype":"venue"
},
  "geometry": {"coordinates":[-97.134023,43.038722],"type":"Point"}
}