{
  "type": "Feature",
  "properties": {
    "iso:country":"US",
    "sg:address":"603 Dakota St",
    "sg:city":"Milbank",
    "sg:classifiers":[
        {
            "category":"Professional",
            "subcategory":"Management & Consulting",
            "type":"Services"
        }
    ],
    "sg:phone":"+1 605 432 6621",
    "sg:postcode":"57248",
    "sg:province":"SD",
    "sg:tags":[
        "consultant",
        "business"
    ],
    "wof:name":"E R Staff Inc",
    "wof:placetype":"venue"
},
  "geometry": {"coordinates":[-97.210845,44.582113],"type":"Point"}
}