{
  "type": "Feature",
  "properties": {
    "iso:country":"US",
    "sg:address":"11578 310th Ave",
    "sg:city":"Mound City",
    "sg:classifiers":[
        {
            "category":"Personal",
            "subcategory":"Beauty Salon",
            "type":"Services"
        }
    ],
    "sg:phone":"+1 605 955 3304",
    "sg:postcode":"57646",
    "sg:province":"SD",
    "wof:name":"Sheila's Hair Studio",
    "wof:placetype":"venue"
},
  "geometry": {"coordinates":[-99.986067,45.71074],"type":"Point"}
}