{
  "type": "Feature",
  "properties": {
    "iso:country":"US",
    "sg:address":"423 E 4th St",
    "sg:city":"Dell Rapids",
    "sg:classifiers":[
        {
            "category":"Banks & Credit Unions",
            "subcategory":"Bank",
            "type":"Services"
        }
    ],
    "sg:phone":"+1 605 428 3684",
    "sg:postcode":"57022",
    "sg:province":"SD",
    "sg:tags":[
        "loan",
        "real estate"
    ],
    "wof:name":"Odyssey Mortgage",
    "wof:placetype":"venue"
},
  "geometry": {"coordinates":[-96.711722,43.823238],"type":"Point"}
}