{
  "type": "Feature",
  "properties": {
    "addr:full":"305 N Wood Ave Philip SD 57567",
    "addr:housenumber":"305",
    "addr:postcode":"57567",
    "addr:street":"N Wood Ave",
    "iso:country":"US",
    "sg:address":"305 N Wood Ave",
    "sg:city":"Philip",
    "sg:classifiers":[
        {
            "category":"Personal",
            "subcategory":"Beauty Salon",
            "type":"Services"
        }
    ],
    "sg:phone":"+1 605 859 2900",
    "sg:postcode":"57567",
    "sg:province":"SD",
    "wof:name":"Patina Finish Co",
    "wof:placetype":"venue"
},
  "geometry": {"coordinates":[-101.66270799999999,44.041417],"type":"Point"}
}