{
  "type": "Feature",
  "properties": {
    "iso:country":"US",
    "sg:address":"90 N Harmon Dr",
    "sg:city":"Mitchell",
    "sg:classifiers":[
        {
            "category":"Home & Garden",
            "subcategory":"Home Furnishings",
            "type":"Retail Goods"
        }
    ],
    "sg:phone":"+1 605 995 2099",
    "sg:postcode":"57301",
    "sg:province":"SD",
    "sg:tags":[
        "bathroom",
        "fixture",
        "accessory"
    ],
    "wof:name":"Pottery Depot",
    "wof:placetype":"venue"
},
  "geometry": {"coordinates":[-98.026416,43.745962],"type":"Point"}
}