{
  "type": "Feature",
  "properties": {
    "iso:country":"US",
    "sg:address":"22625 473rd Ave",
    "sg:city":"Flandreau",
    "sg:phone":"+1 605 997 3653",
    "sg:postcode":"57006",
    "sg:province":"SD",
    "sg:tags":[
        "farm",
        "field",
        "crop"
    ],
    "wof:name":"Larry Hobbie",
    "wof:placetype":"venue"
},
  "geometry": {"coordinates":[-96.74664799999999,44.196847],"type":"Point"}
}