{
  "type": "Feature",
  "properties": {
    "iso:country":"US",
    "sg:address":"43856 272nd St",
    "sg:city":"Bridgewater",
    "sg:classifiers":[
        {
            "category":"Farming",
            "subcategory":"Dairy Farm",
            "type":"Manufacturing & Wholesale Goods"
        }
    ],
    "sg:phone":"+1 605 648 3160",
    "sg:postcode":"57319",
    "sg:province":"SD",
    "wof:name":"Hofer Farms",
    "wof:placetype":"venue"
},
  "geometry": {"coordinates":[-97.43450199999999,43.444123],"type":"Point"}
}