{
  "type": "Feature",
  "properties": {
    "iso:country":"US",
    "sg:address":"1223 4th Ave SW",
    "sg:city":"Aberdeen",
    "sg:classifiers":[
        {
            "category":"Organizations",
            "subcategory":"Religious Organization",
            "type":"Services"
        }
    ],
    "sg:phone":"+1 605 226 3279",
    "sg:postcode":"57401",
    "sg:province":"SD",
    "wof:name":"Old Apostolic Church",
    "wof:placetype":"venue"
},
  "geometry": {"coordinates":[-98.506705,45.461125],"type":"Point"}
}