{
  "type": "Feature",
  "properties": {
    "iso:country":"US",
    "sg:address":"2127 S Minnesota Ave",
    "sg:city":"Sioux Falls",
    "sg:classifiers":[
        {
            "category":"Health Services",
            "subcategory":"Podiatrist",
            "type":"Services"
        },
        {
            "category":"Health Services",
            "subcategory":"Doctor",
            "type":"Services"
        }
    ],
    "sg:phone":"+1 605 332 2661",
    "sg:postcode":"57105",
    "sg:province":"SD",
    "wof:name":"Sioux Falls Foot Surgeons",
    "wof:placetype":"venue"
},
  "geometry": {"coordinates":[-96.731352,43.525108],"type":"Point"}
}