{
  "type": "Feature",
  "properties": {
    "iso:country":"US",
    "sg:address":"511 Main Ave",
    "sg:city":"Sisseton",
    "sg:classifiers":[
        {
            "category":"Government",
            "subcategory":"Office",
            "type":"Public Place"
        }
    ],
    "sg:phone":"+1 605 698 7604",
    "sg:postcode":"57262",
    "sg:province":"SD",
    "wof:name":"Sioux JOM Office",
    "wof:placetype":"venue"
},
  "geometry": {"coordinates":[-97.050921,45.665418],"type":"Point"}
}