{
  "type": "Feature",
  "properties": {
    "iso:country":"US",
    "sg:address":"124 E Dakota Ave",
    "sg:city":"Pierre",
    "sg:classifiers":[
        {
            "category":"Professional",
            "subcategory":"Employment Agencies",
            "type":"Services"
        }
    ],
    "sg:phone":"+1 605 773 4755",
    "sg:postcode":"57501",
    "sg:province":"SD",
    "sg:tags":[
        "co",
        "fraternal"
    ],
    "sg:website":"www.therightturn.homestead.com",
    "wof:name":"Right Turn",
    "wof:placetype":"venue"
},
  "geometry": {"coordinates":[-100.35472900000001,44.36551],"type":"Point"}
}