{
  "type": "Feature",
  "properties": {
    "iso:country":"US",
    "sg:address":"14 S Illinois St",
    "sg:city":"Aberdeen",
    "sg:classifiers":[
        {
            "category":"Professional",
            "type":"Services"
        }
    ],
    "sg:phone":"+1 605 226 1528",
    "sg:postcode":"57401",
    "sg:province":"SD",
    "wof:name":"Mel Harrell",
    "wof:placetype":"venue"
},
  "geometry": {"coordinates":[-98.450291,45.465037],"type":"Point"}
}