{
  "type": "Feature",
  "properties": {
    "addr:full":"909 Douglas Ave Yankton SD 57078",
    "addr:housenumber":"909",
    "addr:postcode":"57078",
    "addr:street":"Douglas Ave",
    "iso:country":"US",
    "sg:address":"909 Douglas Ave",
    "sg:city":"Yankton",
    "sg:classifiers":[
        {
            "category":"Retail",
            "subcategory":"Portrait Studio",
            "type":"Services"
        }
    ],
    "sg:phone":"+1 605 655 5984",
    "sg:postcode":"57078",
    "sg:province":"SD",
    "sg:tags":[
        "photo"
    ],
    "wof:name":"Personal Touch Photography",
    "wof:placetype":"venue"
},
  "geometry": {"coordinates":[-97.39198500000001,42.878863],"type":"Point"}
}