{
  "type": "Feature",
  "properties": {
    "addr:full":"1003 5th Ave W Lemmon SD 57638",
    "addr:housenumber":"1003",
    "addr:postcode":"57638",
    "addr:street":"5Th Ave W Lemmon",
    "iso:country":"US",
    "sg:address":"1003 5th Ave W",
    "sg:city":"Lemmon",
    "sg:classifiers":[
        {
            "category":"Health Services",
            "subcategory":"Clinic",
            "type":"Services"
        }
    ],
    "sg:phone":"+1 605 374 7296",
    "sg:postcode":"57638",
    "sg:province":"SD",
    "sg:tags":[
        "holistic",
        "practitioner"
    ],
    "wof:name":"Natural Alternatives",
    "wof:placetype":"venue"
},
  "geometry": {"coordinates":[-102.16657600000001,45.934947],"type":"Point"}
}