{
  "type": "Feature",
  "properties": {
    "iso:country":"US",
    "sg:address":"1109 N Main St",
    "sg:city":"Mitchell",
    "sg:classifiers":[
        {
            "category":"Restaurant",
            "type":"Food & Drink"
        }
    ],
    "sg:phone":"+1 605 996 2300",
    "sg:postcode":"57301",
    "sg:province":"SD",
    "sg:tags":[
        "eating",
        "pizza"
    ],
    "sg:website":"www.godfathers.com",
    "wof:name":"Godfather's Pizza",
    "wof:placetype":"venue"
},
  "geometry": {"coordinates":[-98.025778,43.720672],"type":"Point"}
}