{
  "type": "Feature",
  "properties": {
    "iso:country":"US",
    "sg:address":"45067 284th St",
    "sg:city":"Hurley",
    "sg:classifiers":[
        {
            "category":"Farming",
            "subcategory":"Livestock Farm",
            "type":"Manufacturing & Wholesale Goods"
        }
    ],
    "sg:phone":"+1 605 238 5885",
    "sg:postcode":"57036",
    "sg:province":"SD",
    "sg:tags":[
        "hog",
        "or",
        "feedlot"
    ],
    "wof:name":"Benson Hog Farm",
    "wof:placetype":"venue"
},
  "geometry": {"coordinates":[-97.187295,43.271029],"type":"Point"}
}