{
  "type": "Feature",
  "properties": {
    "iso:country":"US",
    "sg:address":"2332 W Main St",
    "sg:city":"Rapid City",
    "sg:classifiers":[
        {
            "category":"Food & Beverages",
            "subcategory":"Fruits & Vegetables",
            "type":"Retail Goods"
        }
    ],
    "sg:phone":"+1 605 341 3711",
    "sg:postcode":"57702",
    "sg:province":"SD",
    "sg:tags":[
        "juice"
    ],
    "wof:name":"Junga Juice",
    "wof:placetype":"venue"
},
  "geometry": {"coordinates":[-103.257034,44.081987],"type":"Point"}
}