{
  "type": "Feature",
  "properties": {
    "addr:full":"11 E Kidder St Vermillion SD 57069",
    "addr:housenumber":"11",
    "addr:postcode":"57069",
    "addr:street":"E Kidder St",
    "iso:country":"US",
    "sg:address":"11 E Kidder St",
    "sg:city":"Vermillion",
    "sg:classifiers":[
        {
            "category":"Health Services",
            "subcategory":"Chiropractor",
            "type":"Services"
        }
    ],
    "sg:phone":"+1 605 624 8822",
    "sg:postcode":"57069",
    "sg:province":"SD",
    "wof:name":"F P Kroon DC",
    "wof:placetype":"venue"
},
  "geometry": {"coordinates":[-96.932253,42.778268],"type":"Point"}
}