{
  "type": "Feature",
  "properties": {
    "addr:full":"3116 Sunnyview Dr Brookings SD 57006",
    "addr:housenumber":"3116",
    "addr:postcode":"57006",
    "addr:street":"Sunnyview Dr",
    "iso:country":"US",
    "sg:address":"3116 Sunnyview Dr",
    "sg:city":"Brookings",
    "sg:classifiers":[
        {
            "category":"Building & Trades",
            "subcategory":"Plumbing",
            "type":"Services"
        }
    ],
    "sg:phone":"+1 605 693 3227",
    "sg:postcode":"57006",
    "sg:province":"SD",
    "sg:tags":[
        "contractor",
        "management",
        "consult"
    ],
    "wof:name":"Guaranteed Pricing Systems",
    "wof:placetype":"venue"
},
  "geometry": {"coordinates":[-96.785427,44.344582],"type":"Point"}
}