{
  "type": "Feature",
  "properties": {
    "iso:country":"US",
    "sg:address":"2000 E 54th St",
    "sg:city":"Sioux Falls",
    "sg:classifiers":[
        {
            "category":"Manufacturing",
            "subcategory":"Tools & Machinery",
            "type":"Manufacturing & Wholesale Goods"
        }
    ],
    "sg:phone":"+1 605 373 1160",
    "sg:postcode":"57103",
    "sg:province":"SD",
    "sg:tags":[
        "die",
        "maker"
    ],
    "sg:website":"www.midwestprecision-sd.com",
    "wof:name":"Midwest Precision Tool & Die",
    "wof:placetype":"venue"
},
  "geometry": {"coordinates":[-96.70028000000001,43.502821],"type":"Point"}
}