{
  "type": "Feature",
  "properties": {
    "iso:country":"US",
    "sg:address":"503 N Main St",
    "sg:city":"Morristown",
    "sg:classifiers":[
        {
            "category":"Organizations",
            "subcategory":"Religious Organization",
            "type":"Services"
        }
    ],
    "sg:phone":"+1 605 524 3238",
    "sg:postcode":"57626",
    "sg:province":"SD",
    "sg:tags":[
        "church"
    ],
    "wof:name":"Christ Lutheran Church",
    "wof:placetype":"venue"
},
  "geometry": {"coordinates":[-102.038347,45.029596],"type":"Point"}
}