{
  "type": "Feature",
  "properties": {
    "addr:full":"35250 191st St Miller SD 57362",
    "addr:housenumber":"35250",
    "addr:postcode":"57362",
    "addr:street":"191St St",
    "iso:country":"US",
    "sg:address":"35250 191st St",
    "sg:city":"Miller",
    "sg:classifiers":[
        {
            "category":"Government",
            "subcategory":"Office",
            "type":"Public Place"
        }
    ],
    "sg:phone":"+1 605 853 2533",
    "sg:postcode":"57362",
    "sg:province":"SD",
    "sg:tags":[
        "recreation",
        "area"
    ],
    "wof:name":"Lake Louise Recreation Area",
    "wof:placetype":"venue"
},
  "geometry": {"coordinates":[-99.14061100000001,44.619998],"type":"Point"}
}