{
  "type": "Feature",
  "properties": {
    "iso:country":"US",
    "sg:address":"113 E Dakota Ave",
    "sg:city":"Pierre",
    "sg:classifiers":[
        {
            "category":"Retail",
            "subcategory":"Repair Shop",
            "type":"Services"
        }
    ],
    "sg:phone":"+1 605 224 0206",
    "sg:postcode":"57501",
    "sg:province":"SD",
    "wof:name":"A A A Locksmith Service",
    "wof:placetype":"venue"
},
  "geometry": {"coordinates":[-100.354939,44.365486],"type":"Point"}
}