{
  "type": "Feature",
  "properties": {
    "addr:full":"31375 137th St Java SD 57452",
    "addr:housenumber":"31375",
    "addr:postcode":"57452",
    "addr:street":"137Th St",
    "iso:country":"US",
    "sg:address":"31375 137th St",
    "sg:city":"Java",
    "sg:phone":"+1 605 649 6341",
    "sg:postcode":"57452",
    "sg:province":"SD",
    "sg:tags":[
        "farm",
        "corn",
        "grain",
        "cash"
    ],
    "wof:name":"Lanny Stiklestad",
    "wof:placetype":"venue"
},
  "geometry": {"coordinates":[-99.92766399999999,45.404719],"type":"Point"}
}