{
  "type": "Feature",
  "properties": {
    "addr:full":"39149 269th St Corsica SD 57328",
    "addr:housenumber":"39149",
    "addr:postcode":"57328",
    "addr:street":"269Th St",
    "iso:country":"US",
    "sg:address":"39149 269th St",
    "sg:city":"Corsica",
    "sg:classifiers":[
        {
            "category":"Farming",
            "subcategory":"Livestock Farm",
            "type":"Manufacturing & Wholesale Goods"
        }
    ],
    "sg:phone":"+1 605 946 5401",
    "sg:postcode":"57328",
    "sg:province":"SD",
    "sg:tags":[
        "beef",
        "feedlot",
        "cattle"
    ],
    "wof:name":"Donnie Muilenburg",
    "wof:placetype":"venue"
},
  "geometry": {"coordinates":[-98.352132,43.485151],"type":"Point"}
}