{
  "type": "Feature",
  "properties": {
    "iso:country":"US",
    "sg:address":"9053 124th Ave SE",
    "sg:city":"Cogswell",
    "sg:phone":"+1 701 724 3441",
    "sg:postcode":"58017",
    "sg:province":"SD",
    "sg:tags":[
        "farm",
        "corn",
        "soybean"
    ],
    "wof:name":"Hayen Farms",
    "wof:placetype":"venue"
},
  "geometry": {"coordinates":[-97.799268,46.1023],"type":"Point"}
}