{
  "type": "Feature",
  "properties": {
    "addr:full":"412 E 4th St Dell Rapids SD 57022",
    "addr:housenumber":"412",
    "addr:postcode":"57022",
    "addr:street":"E 4Th St",
    "iso:country":"US",
    "sg:address":"412 E 4th St",
    "sg:city":"Dell Rapids",
    "sg:classifiers":[
        {
            "category":"Manufacturing",
            "subcategory":"Toys & Sporting Goods",
            "type":"Manufacturing & Wholesale Goods"
        }
    ],
    "sg:phone":"+1 605 428 3105",
    "sg:postcode":"57022",
    "sg:province":"SD",
    "sg:tags":[
        "mfg"
    ],
    "wof:name":"Laughing Hugs",
    "wof:placetype":"venue"
},
  "geometry": {"coordinates":[-96.711849,43.82339],"type":"Point"}
}