{
  "type": "Feature",
  "properties": {
    "addr:full":"200 N Main St Winner SD 57580",
    "addr:housenumber":"200",
    "addr:postcode":"57580",
    "addr:street":"N Main St",
    "iso:country":"US",
    "sg:address":"200 N Main St",
    "sg:city":"Winner",
    "sg:classifiers":[
        {
            "category":"Wholesale",
            "subcategory":"Farm Supplies",
            "type":"Manufacturing & Wholesale Goods"
        }
    ],
    "sg:phone":"+1 605 842 2721",
    "sg:postcode":"57580",
    "sg:province":"SD",
    "sg:tags":[
        "grain"
    ],
    "wof:name":"Country Pride Coop",
    "wof:placetype":"venue"
},
  "geometry": {"coordinates":[-99.85683400000001,43.379486],"type":"Point"}
}