{
  "type": "Feature",
  "properties": {
    "iso:country":"US",
    "sg:address":"4110 Brookside Dr",
    "sg:city":"Rapid City",
    "sg:classifiers":[
        {
            "category":"Real Estate",
            "subcategory":"Real Estate Agent",
            "type":"Services"
        }
    ],
    "sg:phone":"+1 605 343 3410",
    "sg:postcode":"57702",
    "sg:province":"SD",
    "wof:name":"Ray Anderson Real Estate",
    "wof:placetype":"venue"
},
  "geometry": {"coordinates":[-103.28675800000001,44.080133],"type":"Point"}
}