{
  "type": "Feature",
  "properties": {
    "addr:full":"27163 469th Ave Tea SD 57064",
    "addr:housenumber":"27163",
    "addr:postcode":"57064",
    "addr:street":"469Th Ave",
    "iso:country":"US",
    "sg:address":"27163 469th Ave",
    "sg:city":"Tea",
    "sg:classifiers":[
        {
            "category":"Home & Garden",
            "subcategory":"Hardware",
            "type":"Retail Goods"
        }
    ],
    "sg:phone":"+1 605 213 2000",
    "sg:postcode":"57064",
    "sg:province":"SD",
    "wof:name":"True Value Hardware",
    "wof:placetype":"venue"
},
  "geometry": {"coordinates":[-96.82627599999999,43.452576],"type":"Point"}
}