{
  "type": "Feature",
  "properties": {
    "addr:full":"2471 Pine Ridge Ln Sturgis SD 57785",
    "addr:housenumber":"2471",
    "addr:postcode":"57785",
    "addr:street":"Pine Ridge Ln",
    "iso:country":"US",
    "sg:address":"2471 Pine Ridge Ln",
    "sg:city":"Sturgis",
    "sg:classifiers":[
        {
            "category":"Building & Trades",
            "subcategory":"Plumbing",
            "type":"Services"
        }
    ],
    "sg:phone":"+1 605 347 2234",
    "sg:postcode":"57785",
    "sg:province":"SD",
    "sg:tags":[
        "system",
        "contractor",
        "heating",
        "refrigeration",
        "conditioning",
        "air"
    ],
    "wof:name":"Chuck's Refrigeration",
    "wof:placetype":"venue"
},
  "geometry": {"coordinates":[-103.531543,44.423269],"type":"Point"}
}