{
  "type": "Feature",
  "properties": {
    "addr:full":"8220 Elk Creek Rd Piedmont SD 57769",
    "addr:housenumber":"8220",
    "addr:postcode":"57769",
    "addr:street":"Elk Creek Rd",
    "iso:country":"US",
    "sg:address":"8220 Elk Creek Rd",
    "sg:city":"Piedmont",
    "sg:classifiers":[
        {
            "category":"Travel",
            "subcategory":"Campground",
            "type":"Entertainment"
        }
    ],
    "sg:phone":"+1 605 787 9400",
    "sg:postcode":"57769",
    "sg:province":"SD",
    "sg:tags":[
        "trailer"
    ],
    "wof:name":"Deerview Rv Camp",
    "wof:placetype":"venue"
},
  "geometry": {"coordinates":[-103.373563,44.22403],"type":"Point"}
}