{
  "type": "Feature",
  "properties": {
    "addr:full":"9 Court St Vermillion SD 57069",
    "addr:housenumber":"9",
    "addr:postcode":"57069",
    "addr:street":"Court St",
    "iso:country":"US",
    "sg:address":"9 Court St",
    "sg:city":"Vermillion",
    "sg:classifiers":[
        {
            "category":"Home & Garden",
            "subcategory":"Hardware",
            "type":"Retail Goods"
        }
    ],
    "sg:phone":"+1 605 624 6725",
    "sg:postcode":"57069",
    "sg:province":"SD",
    "wof:name":"Coast To Coast",
    "wof:placetype":"venue"
},
  "geometry": {"coordinates":[-96.932457,42.779315],"type":"Point"}
}