{
  "type": "Feature",
  "properties": {
    "iso:country":"US",
    "sg:address":"505 Kerrydon Dr",
    "sg:city":"Milbank",
    "sg:classifiers":[
        {
            "category":"Freight",
            "type":"Transportation"
        }
    ],
    "sg:phone":"+1 605 432 9545",
    "sg:postcode":"57252",
    "sg:province":"SD",
    "sg:tags":[
        "arrangement"
    ],
    "wof:name":"R E Lean Inc",
    "wof:placetype":"venue"
},
  "geometry": {"coordinates":[-96.63035000000001,45.211631],"type":"Point"}
}