{
  "type": "Feature",
  "properties": {
    "iso:country":"US",
    "sg:address":"13280 392nd Ave",
    "sg:city":"Aberdeen",
    "sg:classifiers":[
        {
            "category":"Freight",
            "type":"Transportation"
        }
    ],
    "sg:phone":"+1 605 725 6860",
    "sg:postcode":"57401",
    "sg:province":"SD",
    "sg:tags":[
        "operator",
        "trucking"
    ],
    "wof:name":"Scott Ogden",
    "wof:placetype":"venue"
},
  "geometry": {"coordinates":[-98.392185,45.461349],"type":"Point"}
}