{
  "type": "Feature",
  "properties": {
    "iso:country":"US",
    "sg:address":"405 W Milbank Ave",
    "sg:city":"Milbank",
    "sg:classifiers":[
        {
            "category":"Railroad",
            "type":"Transportation"
        }
    ],
    "sg:phone":"+1 605 432 6912",
    "sg:postcode":"57252",
    "sg:province":"SD",
    "sg:tags":[
        "line",
        "operation",
        "hauling"
    ],
    "wof:name":"Sisseton Milbank Railroad Inc",
    "wof:placetype":"venue"
},
  "geometry": {"coordinates":[-96.643595,45.222659],"type":"Point"}
}