{
  "type": "Feature",
  "properties": {
    "addr:full":"108 S 2nd St Aberdeen SD 57401",
    "addr:housenumber":"108",
    "addr:postcode":"57401",
    "addr:street":"S 2Nd St",
    "iso:country":"US",
    "sg:address":"108 S 2nd St",
    "sg:city":"Aberdeen",
    "sg:classifiers":[
        {
            "category":"Building & Trades",
            "subcategory":"Cleaning & Sanitation",
            "type":"Services"
        }
    ],
    "sg:phone":"+1 605 225 8847",
    "sg:postcode":"57401",
    "sg:province":"SD",
    "sg:tags":[
        "janitor"
    ],
    "wof:name":"J & R Janitorial Svc",
    "wof:placetype":"venue"
},
  "geometry": {"coordinates":[-98.49095199999999,45.46403],"type":"Point"}
}