{
  "type": "Feature",
  "properties": {
    "iso:country":"US",
    "sg:address":"2708 S Alpine Ave",
    "sg:city":"Sioux Falls",
    "sg:classifiers":[
        {
            "category":"Manufacturing",
            "subcategory":"Tools & Machinery",
            "type":"Manufacturing & Wholesale Goods"
        }
    ],
    "sg:phone":"+1 605 334 0397",
    "sg:postcode":"57110",
    "sg:province":"SD",
    "sg:tags":[
        "equipment",
        "handling",
        "grain"
    ],
    "wof:name":"Knutson Sales",
    "wof:placetype":"venue"
},
  "geometry": {"coordinates":[-96.664698,43.519731],"type":"Point"}
}