{
  "type": "Feature",
  "properties": {
    "addr:full":"1408 N Pikes Peak Cir Sioux Falls SD 57110",
    "addr:housenumber":"1408",
    "addr:postcode":"57110",
    "addr:street":"N Pikes Peak Cir",
    "iso:country":"US",
    "sg:address":"1408 N Pikes Peak Cir",
    "sg:city":"Sioux Falls",
    "sg:classifiers":[
        {
            "category":"Real Estate",
            "subcategory":"Real Estate Agent",
            "type":"Services"
        }
    ],
    "sg:phone":"+1 605 339 4475",
    "sg:postcode":"57110",
    "sg:province":"SD",
    "sg:tags":[
        "residential"
    ],
    "wof:name":"Crannycos",
    "wof:placetype":"venue"
},
  "geometry": {"coordinates":[-96.668801,43.559953],"type":"Point"}
}