{
  "type": "Feature",
  "properties": {
    "iso:country":"US",
    "sg:address":"1902 24th Ave NW",
    "sg:city":"Aberdeen",
    "sg:classifiers":[
        {
            "category":"Recreation",
            "subcategory":"Amusement Park",
            "type":"Entertainment"
        }
    ],
    "sg:phone":"+1 605 225 8541",
    "sg:postcode":"57401",
    "sg:province":"SD",
    "wof:name":"Wylie Thunder Road Go-Karts",
    "wof:placetype":"venue"
},
  "geometry": {"coordinates":[-98.522378,45.488602],"type":"Point"}
}