{
  "type": "Feature",
  "properties": {
    "addr:full":"1000 S Edward Dr Sioux Falls SD 57103",
    "addr:housenumber":"1000",
    "addr:postcode":"57103",
    "addr:street":"S Edward Dr",
    "iso:country":"US",
    "sg:address":"1000 S Edward Dr",
    "sg:city":"Sioux Falls",
    "sg:classifiers":[
        {
            "category":"Education",
            "subcategory":"School",
            "type":"Public Place"
        }
    ],
    "sg:phone":"+1 605 367 6150",
    "sg:postcode":"57103",
    "sg:province":"SD",
    "wof:name":"Cleveland Elementary School",
    "wof:placetype":"venue"
},
  "geometry": {"coordinates":[-96.684275,43.537969],"type":"Point"}
}