{
  "type": "Feature",
  "properties": {
    "iso:country":"US",
    "sg:address":"21 2nd Ave NW",
    "sg:city":"Aberdeen",
    "sg:classifiers":[
        {
            "category":"Retail",
            "subcategory":"Repair Shop",
            "type":"Services"
        }
    ],
    "sg:phone":"+1 605 225 8010",
    "sg:postcode":"57401",
    "sg:province":"SD",
    "sg:tags":[
        "repairing",
        "lawn",
        "mower"
    ],
    "wof:name":"Nelson Sales & Svc",
    "wof:placetype":"venue"
},
  "geometry": {"coordinates":[-98.489151,45.467654],"type":"Point"}
}