{
  "type": "Feature",
  "properties": {
    "addr:full":"37163 242nd St White Lake SD 57383",
    "addr:housenumber":"37163",
    "addr:postcode":"57383",
    "addr:street":"242Nd St",
    "iso:country":"US",
    "sg:address":"37163 242nd St",
    "sg:city":"White Lake",
    "sg:classifiers":[
        {
            "category":"Farming",
            "subcategory":"Farm",
            "type":"Manufacturing & Wholesale Goods"
        }
    ],
    "sg:phone":"+1 605 249 2537",
    "sg:postcode":"57383",
    "sg:province":"SD",
    "sg:tags":[
        "crop",
        "general"
    ],
    "wof:name":"Ronald Gillen",
    "wof:placetype":"venue"
},
  "geometry": {"coordinates":[-98.756867,43.877629],"type":"Point"}
}