{
  "type": "Feature",
  "properties": {
    "iso:country":"US",
    "sg:address":"600 Main Ave",
    "sg:city":"Toronto",
    "sg:classifiers":[
        {
            "category":"Food & Beverages",
            "subcategory":"Groceries & Convenience Stores",
            "type":"Retail Goods"
        }
    ],
    "sg:phone":"+1 605 794 2511",
    "sg:postcode":"57237",
    "sg:province":"SD",
    "wof:name":"Doc's Quick Stop",
    "wof:placetype":"venue"
},
  "geometry": {"coordinates":[-96.46066500000001,44.79054],"type":"Point"}
}