{
  "type": "Feature",
  "properties": {
    "iso:country":"US",
    "sg:address":"46214 277th St",
    "sg:city":"Chancellor",
    "sg:classifiers":[
        {
            "category":"Farming",
            "subcategory":"Farm",
            "type":"Manufacturing & Wholesale Goods"
        }
    ],
    "sg:phone":"+1 605 647 2129",
    "sg:postcode":"57015",
    "sg:province":"SD",
    "sg:tags":[
        "crop",
        "general"
    ],
    "wof:name":"Frank Haan",
    "wof:placetype":"venue"
},
  "geometry": {"coordinates":[-96.947149,43.374072],"type":"Point"}
}