{
  "type": "Feature",
  "properties": {
    "iso:country":"US",
    "sg:address":"3107 Flint Dr",
    "sg:city":"Rapid City",
    "sg:classifiers":[
        {
            "category":"Travel",
            "subcategory":"Travel Agent",
            "type":"Entertainment"
        }
    ],
    "sg:phone":"+1 605 399 1463",
    "sg:postcode":"57702",
    "sg:province":"SD",
    "sg:tags":[
        "operator",
        "shop",
        "tour",
        "gift"
    ],
    "wof:name":"Rushmore Tramway",
    "wof:placetype":"venue"
},
  "geometry": {"coordinates":[-103.264392,44.053684],"type":"Point"}
}