{
  "type": "Feature",
  "properties": {
    "iso:country":"US",
    "sg:address":"1120 E Sioux Ave",
    "sg:city":"Pierre",
    "sg:classifiers":[
        {
            "category":"Recreation",
            "subcategory":"Arcade",
            "type":"Entertainment"
        },
        {
            "category":"Travel",
            "subcategory":"Hotels & Motels",
            "type":"Entertainment"
        }
    ],
    "sg:phone":"+1 605 224 7529",
    "sg:postcode":"57501",
    "sg:province":"SD",
    "sg:tags":[
        "operation",
        "casino"
    ],
    "wof:name":"Double Play Casino and Sports",
    "wof:placetype":"venue"
},
  "geometry": {"coordinates":[-100.33737499999999,44.360379],"type":"Point"}
}