{
  "type": "Feature",
  "properties": {
    "addr:full":"1520 42nd St Brookings SD 57006",
    "addr:housenumber":"1520",
    "addr:postcode":"57006",
    "addr:street":"42Nd St",
    "iso:country":"US",
    "sg:address":"1520 42nd St",
    "sg:city":"Brookings",
    "sg:classifiers":[
        {
            "category":"Shopping",
            "subcategory":"Bicycles & Sporting Goods",
            "type":"Retail Goods"
        }
    ],
    "sg:phone":"+1 605 693 3019",
    "sg:postcode":"57006",
    "sg:province":"SD",
    "wof:name":"L & R Supply",
    "wof:placetype":"venue"
},
  "geometry": {"coordinates":[-96.77722199999999,44.354892],"type":"Point"}
}