{
  "type": "Feature",
  "properties": {
    "addr:full":"715 W Willow St Groton SD 57445",
    "addr:housenumber":"715",
    "addr:postcode":"57445",
    "addr:street":"W Willow St",
    "iso:country":"US",
    "sg:address":"715 W Willow St",
    "sg:city":"Groton",
    "sg:classifiers":[
        {
            "category":"Farming",
            "subcategory":"Livestock Farm",
            "type":"Manufacturing & Wholesale Goods"
        }
    ],
    "sg:phone":"+1 605 397 8617",
    "sg:postcode":"57445",
    "sg:province":"SD",
    "sg:tags":[
        "feedlot",
        "grain",
        "cash",
        "beef",
        "cattle"
    ],
    "wof:name":"Harvey Fleihs Jr",
    "wof:placetype":"venue"
},
  "geometry": {"coordinates":[-98.124022,45.428822],"type":"Point"}
}