{
  "type": "Feature",
  "properties": {
    "iso:country":"US",
    "sg:address":"30649 413th Ave",
    "sg:city":"Tyndall",
    "sg:classifiers":[
        {
            "category":"Government",
            "subcategory":"Office",
            "type":"Public Place"
        }
    ],
    "sg:phone":"+1 605 589 3698",
    "sg:postcode":"57066",
    "sg:province":"SD",
    "sg:tags":[
        "village"
    ],
    "wof:name":"Well Site",
    "wof:placetype":"venue"
},
  "geometry": {"coordinates":[-97.93131099999999,42.944238],"type":"Point"}
}