{
  "type": "Feature",
  "properties": {
    "iso:country":"US",
    "sg:address":"602 E 5th St",
    "sg:city":"Miller",
    "sg:classifiers":[
        {
            "category":"Social Services",
            "subcategory":"Child Care",
            "type":"Services"
        }
    ],
    "sg:phone":"+1 605 853 3880",
    "sg:postcode":"57362",
    "sg:province":"SD",
    "sg:tags":[
        "day"
    ],
    "wof:name":"Hand In Hand Day Care Inc",
    "wof:placetype":"venue"
},
  "geometry": {"coordinates":[-98.980804,44.520546],"type":"Point"}
}