{
  "type": "Feature",
  "properties": {
    "iso:country":"US",
    "sg:address":"1304 Oregon St",
    "sg:city":"Rapid City",
    "sg:classifiers":[
        {
            "category":"Building & Trades",
            "subcategory":"Electrical",
            "type":"Services"
        }
    ],
    "sg:phone":"+1 605 348 2335",
    "sg:postcode":"57701",
    "sg:province":"SD",
    "sg:tags":[
        "electrical",
        "contractor"
    ],
    "wof:name":"Micks Electric Inc",
    "wof:placetype":"venue"
},
  "geometry": {"coordinates":[-103.196264,44.051898],"type":"Point"}
}