{
  "type": "Feature",
  "properties": {
    "iso:country":"US",
    "sg:address":"134 Sherman St",
    "sg:city":"Deadwood",
    "sg:classifiers":[
        {
            "category":"Real Estate",
            "subcategory":"Real Estate Agent",
            "type":"Services"
        }
    ],
    "sg:phone":"+1 605 722 1543",
    "sg:postcode":"57732",
    "sg:province":"SD",
    "wof:name":"Keene Team Realtors",
    "wof:placetype":"venue"
},
  "geometry": {"coordinates":[-103.72887900000001,44.374601],"type":"Point"}
}