{
  "type": "Feature",
  "properties": {
    "addr:full":"21811 369th Ave Wessington SD 57381",
    "addr:housenumber":"21811",
    "addr:postcode":"57381",
    "addr:street":"369Th Ave",
    "iso:country":"US",
    "sg:address":"21811 369th Ave",
    "sg:city":"Wessington",
    "sg:classifiers":[
        {
            "category":"Farming",
            "subcategory":"Farm",
            "type":"Manufacturing & Wholesale Goods"
        }
    ],
    "sg:phone":"+1 605 539 9608",
    "sg:postcode":"57381",
    "sg:province":"SD",
    "sg:tags":[
        "crop",
        "general"
    ],
    "wof:name":"Tom Koth",
    "wof:placetype":"venue"
},
  "geometry": {"coordinates":[-98.801545,44.224081],"type":"Point"}
}