{
  "type": "Feature",
  "properties": {
    "iso:country":"US",
    "sg:address":"2405 6th St",
    "sg:city":"Brookings",
    "sg:classifiers":[
        {
            "category":"Autos & Motor Vehicles",
            "subcategory":"Automobile Sales",
            "type":"Retail Goods"
        }
    ],
    "sg:phone":"+1 605 692 8811",
    "sg:postcode":"57006",
    "sg:province":"SD",
    "sg:tags":[
        "used"
    ],
    "wof:name":"West Side Wheels",
    "wof:placetype":"venue"
},
  "geometry": {"coordinates":[-96.764546,44.311652],"type":"Point"}
}