{
  "type": "Feature",
  "properties": {
    "iso:country":"US",
    "sg:address":"119 E Chicago St",
    "sg:city":"Tabor",
    "sg:classifiers":[
        {
            "category":"Utilities",
            "subcategory":"Telephone",
            "type":"Services"
        }
    ],
    "sg:phone":"+1 605 463 2672",
    "sg:postcode":"57063",
    "sg:province":"SD",
    "sg:tags":[
        "company"
    ],
    "wof:name":"Fort Randall Telephone Co",
    "wof:placetype":"venue"
},
  "geometry": {"coordinates":[-97.658671,42.948417],"type":"Point"}
}