{
  "type": "Feature",
  "properties": {
    "iso:country":"US",
    "sg:address":"5929 S Mogen Ave",
    "sg:city":"Sioux Falls",
    "sg:classifiers":[
        {
            "category":"Banks & Credit Unions",
            "subcategory":"Bank",
            "type":"Services"
        }
    ],
    "sg:phone":"+1 605 988 5100",
    "sg:postcode":"57108",
    "sg:province":"SD",
    "sg:tags":[
        "national",
        "commercial"
    ],
    "wof:name":"1st Financial Bank USA",
    "wof:placetype":"venue"
},
  "geometry": {"coordinates":[-96.77,43.489955],"type":"Point"}
}