{
  "type": "Feature",
  "properties": {
    "iso:country":"US",
    "sg:address":"1012 W 41st St",
    "sg:city":"Sioux Falls",
    "sg:classifiers":[
        {
            "category":"Travel",
            "subcategory":"Travel Agent",
            "type":"Entertainment"
        }
    ],
    "sg:phone":"+1 605 335 6968",
    "sg:postcode":"57105",
    "sg:province":"SD",
    "sg:tags":[
        "agency",
        "bureau"
    ],
    "sg:website":"www.carlsonwagonlit.com",
    "wof:name":"Carlson Wavonlit Travel",
    "wof:placetype":"venue"
},
  "geometry": {"coordinates":[-96.738578,43.514932],"type":"Point"}
}