{
  "type": "Feature",
  "properties": {
    "iso:country":"US",
    "sg:address":"420 Co Rd 6",
    "sg:city":"Conde",
    "sg:classifiers":[
        {
            "category":"Freight",
            "type":"Transportation"
        }
    ],
    "sg:phone":"+1 605 382 5643",
    "sg:postcode":"57434",
    "sg:province":"SD",
    "sg:tags":[
        "operator",
        "local",
        "trucking"
    ],
    "wof:name":"Larry Hearnen",
    "wof:placetype":"venue"
},
  "geometry": {"coordinates":[-98.102148,45.154166],"type":"Point"}
}