{
  "type": "Feature",
  "properties": {
    "iso:country":"US",
    "sg:address":"413 E 4th St",
    "sg:city":"Dell Rapids",
    "sg:classifiers":[
        {
            "category":"Food & Beverages",
            "subcategory":"Bakery",
            "type":"Retail Goods"
        }
    ],
    "sg:phone":"+1 605 428 5000",
    "sg:postcode":"57022",
    "sg:province":"SD",
    "wof:name":"Pastries Holland House",
    "wof:placetype":"venue"
},
  "geometry": {"coordinates":[-96.711851,43.82324],"type":"Point"}
}