{
  "type": "Feature",
  "properties": {
    "addr:full":"39756 124th St Columbia SD 57433",
    "addr:housenumber":"39756",
    "addr:postcode":"57433",
    "addr:street":"124Th St",
    "iso:country":"US",
    "sg:address":"39756 124th St",
    "sg:city":"Columbia",
    "sg:classifiers":[
        {
            "category":"Farming",
            "subcategory":"Farm",
            "type":"Manufacturing & Wholesale Goods"
        }
    ],
    "sg:phone":"+1 605 396 2346",
    "sg:postcode":"57433",
    "sg:province":"SD",
    "sg:tags":[
        "crop",
        "general"
    ],
    "wof:name":"C Larson Trucking",
    "wof:placetype":"venue"
},
  "geometry": {"coordinates":[-98.268169,45.588851],"type":"Point"}
}