{
  "type": "Feature",
  "properties": {
    "iso:country":"US",
    "sg:address":"618 Main St",
    "sg:city":"Gregory",
    "sg:classifiers":[
        {
            "category":"Insurance",
            "subcategory":"Insurance Agent",
            "type":"Services"
        }
    ],
    "sg:phone":"+1 605 835 8965",
    "sg:postcode":"57533",
    "sg:province":"SD",
    "wof:name":"Tom Eliason",
    "wof:placetype":"venue"
},
  "geometry": {"coordinates":[-99.43082200000001,43.233329],"type":"Point"}
}