{
  "type": "Feature",
  "properties": {
    "iso:country":"US",
    "sg:address":"265 E Main St",
    "sg:city":"Corsica",
    "sg:classifiers":[
        {
            "category":"Health Services",
            "subcategory":"Doctor",
            "type":"Services"
        }
    ],
    "sg:phone":"+1 605 946 5411",
    "sg:postcode":"57328",
    "sg:province":"SD",
    "sg:tags":[
        "clinic"
    ],
    "sg:website":"www.averacorsicaclinic.org",
    "wof:name":"Avera Corsica Medical Clinic",
    "wof:placetype":"venue"
},
  "geometry": {"coordinates":[-98.407308,43.423633],"type":"Point"}
}