{
  "type": "Feature",
  "properties": {
    "iso:country":"US",
    "sg:address":"316 Capital St",
    "sg:city":"Yankton",
    "sg:classifiers":[
        {
            "category":"Autos & Motor Vehicles",
            "subcategory":"Automobile Sales",
            "type":"Retail Goods"
        }
    ],
    "sg:phone":"+1 605 665 3765",
    "sg:postcode":"57078",
    "sg:province":"SD",
    "sg:tags":[
        "car",
        "dealer"
    ],
    "sg:website":"www.robinsonmotors.net",
    "wof:name":"Robinson Motors",
    "wof:placetype":"venue"
},
  "geometry": {"coordinates":[-97.390423,42.870833],"type":"Point"}
}