{
  "type": "Feature",
  "properties": {
    "iso:country":"US",
    "sg:address":"300 S Courtland St",
    "sg:city":"Chamberlain",
    "sg:classifiers":[
        {
            "category":"Government",
            "subcategory":"Office",
            "type":"Public Place"
        }
    ],
    "sg:phone":"+1 605 734 4580",
    "sg:postcode":"57325",
    "sg:province":"SD",
    "sg:tags":[
        "county"
    ],
    "wof:name":"Brule County Clerk Of Courts",
    "wof:placetype":"venue"
},
  "geometry": {"coordinates":[-99.333543,43.808163],"type":"Point"}
}