{
  "type": "Feature",
  "properties": {
    "iso:country":"US",
    "sg:address":"4010 State Hwy 34",
    "sg:city":"Pierre",
    "sg:classifiers":[
        {
            "category":"Utilities",
            "subcategory":"Refuse",
            "type":"Services"
        }
    ],
    "sg:phone":"+1 605 224 4804",
    "sg:postcode":"57501",
    "sg:province":"SD",
    "sg:tags":[
        "dumps",
        "disposal",
        "waste"
    ],
    "wof:name":"Envirotech Waste Svc Inc",
    "wof:placetype":"venue"
},
  "geometry": {"coordinates":[-100.29131,44.352492],"type":"Point"}
}