{
  "type": "Feature",
  "properties": {
    "addr:full":"7 E Main St Vermillion SD 57069",
    "addr:housenumber":"7",
    "addr:postcode":"57069",
    "addr:street":"E Main St",
    "iso:country":"US",
    "sg:address":"7 E Main St",
    "sg:city":"Vermillion",
    "sg:classifiers":[
        {
            "category":"Health Services",
            "subcategory":"Optometrist",
            "type":"Services"
        }
    ],
    "sg:phone":"+1 605 624 4291",
    "sg:postcode":"57069",
    "sg:province":"SD",
    "wof:name":"Vermillion Vision Clinic",
    "wof:placetype":"venue"
},
  "geometry": {"coordinates":[-96.931989,42.779327],"type":"Point"}
}