{
  "type": "Feature",
  "properties": {
    "iso:country":"US",
    "sg:address":"10639 398th Ave",
    "sg:city":"Hecla",
    "sg:phone":"+1 605 994 2014",
    "sg:postcode":"57446",
    "sg:province":"SD",
    "sg:tags":[
        "farm",
        "corn",
        "wheat",
        "soybean"
    ],
    "wof:name":"Lyle Wampler",
    "wof:placetype":"venue"
},
  "geometry": {"coordinates":[-98.269507,45.84411],"type":"Point"}
}