{
  "type": "Feature",
  "properties": {
    "iso:country":"US",
    "sg:address":"196 E 6th St",
    "sg:city":"Sioux Falls",
    "sg:classifiers":[
        {
            "category":"Organizations",
            "subcategory":"Religious Organization",
            "type":"Services"
        }
    ],
    "sg:phone":"+1 605 274 6415",
    "sg:postcode":"57104",
    "sg:province":"SD",
    "sg:website":"www.thecrossing-sf.com",
    "wof:name":"Crossing",
    "wof:placetype":"venue"
},
  "geometry": {"coordinates":[-96.72551,43.551291],"type":"Point"}
}