{
  "type": "Feature",
  "properties": {
    "iso:country":"US",
    "sg:address":"103 S Hill St",
    "sg:city":"Bryant",
    "sg:classifiers":[
        {
            "category":"Autos & Motor Vehicles",
            "subcategory":"Fuel & Gas Station",
            "type":"Retail Goods"
        }
    ],
    "sg:phone":"+1 605 628 2025",
    "sg:postcode":"57221",
    "sg:province":"SD",
    "sg:tags":[
        "oil"
    ],
    "wof:name":"Barton's Service",
    "wof:placetype":"venue"
},
  "geometry": {"coordinates":[-97.467264,44.590491],"type":"Point"}
}