{
  "type": "Feature",
  "properties": {
    "addr:full":"21236 429th Ave De Smet SD 57231",
    "addr:housenumber":"21236",
    "addr:postcode":"57231",
    "addr:street":"429Th Ave De",
    "iso:country":"US",
    "sg:address":"21236 429th Ave",
    "sg:city":"De Smet",
    "sg:classifiers":[
        {
            "category":"Farming",
            "subcategory":"Livestock Farm",
            "type":"Manufacturing & Wholesale Goods"
        }
    ],
    "sg:phone":"+1 605 854 3424",
    "sg:postcode":"57231",
    "sg:province":"SD",
    "sg:tags":[
        "beef",
        "feedlot",
        "cattle"
    ],
    "wof:name":"William Driscoll",
    "wof:placetype":"venue"
},
  "geometry": {"coordinates":[-97.63216799999999,44.30561],"type":"Point"}
}