{
  "type": "Feature",
  "properties": {
    "addr:full":"800 S 14th St Hot Springs SD 57747",
    "addr:housenumber":"800",
    "addr:postcode":"57747",
    "addr:street":"S 14Th St",
    "iso:country":"US",
    "sg:address":"800 S 14th St",
    "sg:city":"Hot Springs",
    "sg:classifiers":[
        {
            "category":"Retail",
            "subcategory":"Car Wash",
            "type":"Services"
        }
    ],
    "sg:phone":"+1 605 745 6065",
    "sg:postcode":"57747",
    "sg:province":"SD",
    "sg:tags":[
        "polishing",
        "washing"
    ],
    "wof:name":"Westside Car Wash",
    "wof:placetype":"venue"
},
  "geometry": {"coordinates":[-103.47604800000001,43.421363],"type":"Point"}
}