{
  "type": "Feature",
  "properties": {
    "iso:country":"US",
    "sg:address":"4312 Circle Dr",
    "sg:city":"Rapid City",
    "sg:classifiers":[
        {
            "category":"Recreation",
            "type":"Entertainment"
        }
    ],
    "sg:phone":"+1 605 388 0888",
    "sg:postcode":"57702",
    "sg:province":"SD",
    "sg:tags":[
        "tours",
        "sightseeing"
    ],
    "sg:website":"www.attractiontours.com",
    "wof:name":"Attraction Tours-The Black Hls",
    "wof:placetype":"venue"
},
  "geometry": {"coordinates":[-103.292113,44.081635],"type":"Point"}
}