{
  "type": "Feature",
  "properties": {
    "iso:country":"US",
    "sg:address":"3205 S Shirley Ave",
    "sg:city":"Sioux Falls",
    "sg:classifiers":[
        {
            "category":"Shopping",
            "subcategory":"Discount & Variety Stores",
            "type":"Retail Goods"
        }
    ],
    "sg:phone":"+1 605 361 5121",
    "sg:postcode":"57106",
    "sg:province":"SD",
    "wof:name":"Dollar Discount",
    "wof:placetype":"venue"
},
  "geometry": {"coordinates":[-96.77648,43.52247],"type":"Point"}
}