{
  "type": "Feature",
  "properties": {
    "iso:country":"US",
    "sg:address":"40473 221st St",
    "sg:city":"Artesian",
    "sg:classifiers":[
        {
            "category":"Professional",
            "type":"Services"
        }
    ],
    "sg:phone":"+1 605 495 4241",
    "sg:postcode":"57314",
    "sg:province":"SD",
    "wof:name":"Earl Hinricher",
    "wof:placetype":"venue"
},
  "geometry": {"coordinates":[-98.129567,44.184249],"type":"Point"}
}