{
  "type": "Feature",
  "properties": {
    "addr:full":"343 S Chicago St Hot Springs SD 57747",
    "addr:housenumber":"343",
    "addr:postcode":"57747",
    "addr:street":"S Chicago St",
    "iso:country":"US",
    "sg:address":"343 S Chicago St",
    "sg:city":"Hot Springs",
    "sg:classifiers":[
        {
            "category":"Banks & Credit Unions",
            "subcategory":"Bank",
            "type":"Services"
        }
    ],
    "sg:phone":"+1 605 745 6060",
    "sg:postcode":"57747",
    "sg:province":"SD",
    "wof:name":"First Western Bank-Hot Springs",
    "wof:placetype":"venue"
},
  "geometry": {"coordinates":[-103.47310299999999,43.428443],"type":"Point"}
}