{
  "type": "Feature",
  "properties": {
    "iso:country":"US",
    "sg:address":"2340 1st Ave S",
    "sg:city":"Sturgis",
    "sg:classifiers":[
        {
            "category":"Real Estate",
            "subcategory":"Real Estate Operator",
            "type":"Services"
        }
    ],
    "sg:phone":"+1 605 347 9017",
    "sg:postcode":"57785",
    "sg:province":"SD",
    "sg:tags":[
        "building",
        "apartment"
    ],
    "wof:name":"Heritage Acres Inc",
    "wof:placetype":"venue"
},
  "geometry": {"coordinates":[-103.512907,44.391068],"type":"Point"}
}