{
  "type": "Feature",
  "properties": {
    "iso:country":"US",
    "sg:address":"1400 Sherman St",
    "sg:city":"Sturgis",
    "sg:classifiers":[
        {
            "category":"Government",
            "subcategory":"Office",
            "type":"Public Place"
        }
    ],
    "sg:phone":"+1 605 347 8540",
    "sg:postcode":"57785",
    "sg:province":"SD",
    "sg:tags":[
        "state"
    ],
    "wof:name":"Game Fish & Parks Dept",
    "wof:placetype":"venue"
},
  "geometry": {"coordinates":[-103.516992,44.413522],"type":"Point"}
}