{
  "type": "Feature",
  "properties": {
    "addr:full":"15120 455th Ave Summit SD 57266",
    "addr:housenumber":"15120",
    "addr:postcode":"57266",
    "addr:street":"455Th Ave",
    "iso:country":"US",
    "sg:address":"15120 455th Ave",
    "sg:city":"Summit",
    "sg:phone":"+1 605 398 6207",
    "sg:postcode":"57266",
    "sg:province":"SD",
    "sg:tags":[
        "farm",
        "cash",
        "trucking",
        "grain",
        "operator",
        "local"
    ],
    "wof:name":"Lau Trucking",
    "wof:placetype":"venue"
},
  "geometry": {"coordinates":[-97.102802,45.192239],"type":"Point"}
}