{
  "type": "Feature",
  "properties": {
    "iso:country":"US",
    "sg:address":"37885 275th St",
    "sg:city":"Corsica",
    "sg:phone":"+1 605 243 2399",
    "sg:postcode":"57328",
    "sg:province":"SD",
    "sg:tags":[
        "farm",
        "field",
        "crop"
    ],
    "wof:name":"Cornie J Blom",
    "wof:placetype":"venue"
},
  "geometry": {"coordinates":[-98.61760099999999,43.398771],"type":"Point"}
}