{
  "type": "Feature",
  "properties": {
    "iso:country":"US",
    "sg:address":"113 N Splitrock Blvd",
    "sg:city":"Brandon",
    "sg:classifiers":[
        {
            "category":"Sports & Exercise",
            "subcategory":"Gym",
            "type":"Entertainment"
        }
    ],
    "sg:phone":"+1 605 582 7001",
    "sg:postcode":"57005",
    "sg:province":"SD",
    "sg:tags":[
        "club",
        "health",
        "studio",
        "gymnasium"
    ],
    "wof:name":"Brandon Community Fitness Ctr",
    "wof:placetype":"venue"
},
  "geometry": {"coordinates":[-96.572416,43.596416],"type":"Point"}
}