{
  "type": "Feature",
  "properties": {
    "addr:full":"2480 Dyess Ave Rapid City SD 57701",
    "addr:postcode":"2480;57701",
    "addr:street":"Dyess Ave",
    "iso:country":"US",
    "sg:address":"2480 Dyess Ave",
    "sg:city":"Rapid City",
    "sg:classifiers":[
        {
            "category":"Manufacturing",
            "subcategory":"Glass & Minerals",
            "type":"Manufacturing & Wholesale Goods"
        }
    ],
    "sg:phone":"+1 605 394 0291",
    "sg:postcode":"57701",
    "sg:province":"SD",
    "sg:tags":[
        "ready",
        "mix",
        "mfg",
        "concrete"
    ],
    "wof:name":"Croell Redi-Mix Inc",
    "wof:placetype":"venue"
},
  "geometry": {"coordinates":[-103.17143,44.108695],"type":"Point"}
}