{
  "type": "Feature",
  "properties": {
    "addr:full":"1115 5th St Sturgis SD 57785",
    "addr:housenumber":"1115",
    "addr:postcode":"57785",
    "addr:street":"5Th St",
    "iso:country":"US",
    "sg:address":"1115 5th St",
    "sg:city":"Sturgis",
    "sg:classifiers":[
        {
            "category":"Building & Trades",
            "subcategory":"Construction",
            "type":"Services"
        }
    ],
    "sg:phone":"+1 605 347 3802",
    "sg:postcode":"57785",
    "sg:province":"SD",
    "sg:tags":[
        "excavation",
        "grading",
        "contractor"
    ],
    "wof:name":"Short Construction Inc",
    "wof:placetype":"venue"
},
  "geometry": {"coordinates":[-103.517082,44.413017],"type":"Point"}
}