{
  "type": "Feature",
  "properties": {
    "iso:country":"US",
    "sg:address":"614 E Main St",
    "sg:city":"Vermillion",
    "sg:classifiers":[
        {
            "category":"Organizations",
            "subcategory":"Religious Organization",
            "type":"Services"
        }
    ],
    "sg:phone":"+1 605 624 9316",
    "sg:postcode":"57069",
    "sg:province":"SD",
    "sg:tags":[
        "church"
    ],
    "wof:name":"Grace Baptist Chr Pastor's Res",
    "wof:placetype":"venue"
},
  "geometry": {"coordinates":[-96.922686,42.779493],"type":"Point"}
}