{
  "type": "Feature",
  "properties": {
    "iso:country":"US",
    "sg:address":"918 Van Buren St",
    "sg:city":"Rapid City",
    "sg:classifiers":[
        {
            "category":"Building & Trades",
            "subcategory":"Construction",
            "type":"Services"
        }
    ],
    "sg:phone":"+1 605 342 1262",
    "sg:postcode":"57701",
    "sg:province":"SD",
    "sg:tags":[
        "painter"
    ],
    "wof:name":"Weiland Painting Svc",
    "wof:placetype":"venue"
},
  "geometry": {"coordinates":[-103.229229,44.093091],"type":"Point"}
}