{
  "type": "Feature",
  "properties": {
    "addr:full":"1730 S Minnesota Ave Sioux Falls SD 57105",
    "addr:housenumber":"1730",
    "addr:postcode":"57105",
    "addr:street":"S Minnesota Ave",
    "iso:country":"US",
    "sg:address":"1730 S Minnesota Ave",
    "sg:city":"Sioux Falls",
    "sg:classifiers":[
        {
            "category":"Professional",
            "subcategory":"Accounting & Tax Preparation",
            "type":"Services"
        }
    ],
    "sg:phone":"+1 605 339 0872",
    "sg:postcode":"57105",
    "sg:province":"SD",
    "sg:tags":[
        "return",
        "filing"
    ],
    "wof:name":"H & R Block Tax Svc",
    "wof:placetype":"venue"
},
  "geometry": {"coordinates":[-96.731216,43.52969],"type":"Point"}
}