{
  "type": "Feature",
  "properties": {
    "addr:full":"23558 472nd Ave Colman SD 57004",
    "addr:housenumber":"23558",
    "addr:postcode":"57004",
    "addr:street":"472Nd Ave",
    "iso:country":"US",
    "sg:address":"23558 472nd Ave",
    "sg:city":"Colman",
    "sg:phone":"+1 605 534 3748",
    "sg:postcode":"57004",
    "sg:province":"SD",
    "sg:tags":[
        "farm",
        "corn",
        "soybean"
    ],
    "wof:name":"Brad Hemmer",
    "wof:placetype":"venue"
},
  "geometry": {"coordinates":[-96.76608400000001,42.921891],"type":"Point"}
}