{
  "type": "Feature",
  "properties": {
    "addr:full":"2305 Mount Rushmore Rd Rapid City SD 57701",
    "addr:housenumber":"2305",
    "addr:postcode":"57701",
    "addr:street":"Mount Rushmore Rd",
    "iso:country":"US",
    "sg:address":"2305 Mount Rushmore Rd",
    "sg:city":"Rapid City",
    "sg:classifiers":[
        {
            "category":"Bakery",
            "type":"Food & Drink"
        }
    ],
    "sg:menulink":"http://www.allmenus.com/sd/rapid-city/102253-perkins-restaurant--bakery/menu/",
    "sg:phone":"+1 605 341 5225",
    "sg:postcode":"57701",
    "sg:province":"SD",
    "sg:tags":[
        "sandwich",
        "salad",
        "soup",
        "american",
        "pastry",
        "wrap"
    ],
    "wof:name":"Perkins Restaurant & Bakery",
    "wof:placetype":"venue"
},
  "geometry": {"coordinates":[-103.23239,44.063245],"type":"Point"}
}