{
  "type": "Feature",
  "properties": {
    "addr:full":"1323 9th Ave SW Aberdeen SD 57401",
    "addr:housenumber":"1323",
    "addr:postcode":"57401",
    "addr:street":"9Th Ave Sw",
    "iso:country":"US",
    "sg:address":"1323 9th Ave SW",
    "sg:city":"Aberdeen",
    "sg:classifiers":[
        {
            "category":"Freight",
            "type":"Transportation"
        }
    ],
    "sg:phone":"+1 605 225 9216",
    "sg:postcode":"57401",
    "sg:province":"SD",
    "sg:tags":[
        "operator",
        "business",
        "trucking"
    ],
    "wof:name":"L&K Mobile Home Moving",
    "wof:placetype":"venue"
},
  "geometry": {"coordinates":[-98.508127,45.456052],"type":"Point"}
}