{
  "type": "Feature",
  "properties": {
    "iso:country":"US",
    "sg:address":"13029 Old Hill City Rd",
    "sg:city":"Keystone",
    "sg:classifiers":[
        {
            "category":"Social Services",
            "type":"Services"
        }
    ],
    "sg:phone":"+1 605 348 7054",
    "sg:postcode":"57751",
    "sg:province":"SD",
    "wof:name":"New Hope Counseling",
    "wof:placetype":"venue"
},
  "geometry": {"coordinates":[-103.45645399999999,43.903453],"type":"Point"}
}