{
  "type": "Feature",
  "properties": {
    "addr:full":"330 2nd St Harrison SD 57344",
    "addr:housenumber":"330",
    "addr:postcode":"57344",
    "addr:street":"2Nd St",
    "iso:country":"US",
    "sg:address":"330 2nd St",
    "sg:city":"Harrison",
    "sg:classifiers":[
        {
            "category":"Farming",
            "subcategory":"Livestock Farm",
            "type":"Manufacturing & Wholesale Goods"
        }
    ],
    "sg:phone":"+1 605 946 5562",
    "sg:postcode":"57344",
    "sg:province":"SD",
    "sg:tags":[
        "animal",
        "general"
    ],
    "wof:name":"Cornelius Vanderwal",
    "wof:placetype":"venue"
},
  "geometry": {"coordinates":[-98.524018,43.434256],"type":"Point"}
}