{
  "type": "Feature",
  "properties": {
    "iso:country":"US",
    "sg:address":"9597 125th Ave SE",
    "sg:city":"Cogswell",
    "sg:phone":"+1 701 724 3921",
    "sg:postcode":"58017",
    "sg:province":"SD",
    "sg:tags":[
        "farm",
        "grain",
        "cash"
    ],
    "wof:name":"Bosse Brothers",
    "wof:placetype":"venue"
},
  "geometry": {"coordinates":[-97.778544,46.023384],"type":"Point"}
}