{
  "type": "Feature",
  "properties": {
    "addr:full":"101 E Kemp Ave Watertown SD 57201",
    "addr:housenumber":"101",
    "addr:postcode":"57201",
    "addr:street":"E Kemp Ave",
    "iso:country":"US",
    "sg:address":"101 E Kemp Ave",
    "sg:city":"Watertown",
    "sg:classifiers":[
        {
            "category":"Personal",
            "subcategory":"Tattoo Parlor",
            "type":"Services"
        }
    ],
    "sg:phone":"+1 605 753 8282",
    "sg:postcode":"57201",
    "sg:province":"SD",
    "sg:tags":[
        "tattooing"
    ],
    "wof:name":"Stick It To You Tatoos",
    "wof:placetype":"venue"
},
  "geometry": {"coordinates":[-97.11287799999999,44.900115],"type":"Point"}
}