{
  "type": "Feature",
  "properties": {
    "addr:full":"41161 115th St Claremont SD 57432",
    "addr:housenumber":"41161",
    "addr:postcode":"57432",
    "addr:street":"115Th St",
    "iso:country":"US",
    "sg:address":"41161 115th St",
    "sg:city":"Claremont",
    "sg:classifiers":[
        {
            "category":"Farming",
            "subcategory":"Dairy Farm",
            "type":"Manufacturing & Wholesale Goods"
        }
    ],
    "sg:phone":"+1 605 448 5507",
    "sg:postcode":"57432",
    "sg:province":"SD",
    "wof:name":"Frey View Dairy Farm Inc",
    "wof:placetype":"venue"
},
  "geometry": {"coordinates":[-97.98997,45.718998],"type":"Point"}
}