{
  "type": "Feature",
  "properties": {
    "iso:country":"US",
    "sg:address":"17 Stone Dr",
    "sg:city":"Wall",
    "sg:classifiers":[
        {
            "category":"Recreation",
            "type":"Entertainment"
        }
    ],
    "sg:phone":"+1 605 279 2346",
    "sg:postcode":"57790",
    "sg:province":"SD",
    "wof:name":"Rodeo Services Entry Line LLC",
    "wof:placetype":"venue"
},
  "geometry": {"coordinates":[-102.248823,43.982499],"type":"Point"}
}