{
  "type": "Feature",
  "properties": {
    "addr:full":"30159 State Hwy 11 Alcester SD 57001",
    "addr:housenumber":"30159",
    "addr:postcode":"57001",
    "addr:street":"State Hwy 11",
    "iso:country":"US",
    "sg:address":"30159 State Hwy 11",
    "sg:city":"Alcester",
    "sg:classifiers":[
        {
            "category":"Restaurant",
            "type":"Food & Drink"
        }
    ],
    "sg:phone":"+1 605 934 2309",
    "sg:postcode":"57001",
    "sg:province":"SD",
    "sg:tags":[
        "eating"
    ],
    "wof:name":"Olde Towne Bistro",
    "wof:placetype":"venue"
},
  "geometry": {"coordinates":[-96.628187,43.019424],"type":"Point"}
}