{
  "type": "Feature",
  "properties": {
    "iso:country":"US",
    "sg:address":"111 N 3rd St",
    "sg:city":"Beresford",
    "sg:classifiers":[
        {
            "category":"Manufacturing",
            "subcategory":"Printing",
            "type":"Manufacturing & Wholesale Goods"
        }
    ],
    "sg:phone":"+1 605 763 2006",
    "sg:postcode":"57004",
    "sg:province":"SD",
    "sg:tags":[
        "newspaper"
    ],
    "wof:name":"Beresford Republic",
    "wof:placetype":"venue"
},
  "geometry": {"coordinates":[-96.774208,43.084668],"type":"Point"}
}