{
  "type": "Feature",
  "properties": {
    "addr:full":"27067 468th Ave Tea SD 57064",
    "addr:housenumber":"27067",
    "addr:postcode":"57064",
    "addr:street":"468Th Ave",
    "iso:country":"US",
    "sg:address":"27067 468th Ave",
    "sg:city":"Tea",
    "sg:classifiers":[
        {
            "category":"Professional",
            "subcategory":"Advertising",
            "type":"Services"
        }
    ],
    "sg:phone":"+1 605 368 9794",
    "sg:postcode":"57064",
    "sg:province":"SD",
    "sg:tags":[
        "agency"
    ],
    "wof:name":"Garner Advertising Inc",
    "wof:placetype":"venue"
},
  "geometry": {"coordinates":[-96.84622299999999,43.466018],"type":"Point"}
}