{
  "type": "Feature",
  "properties": {
    "addr:full":"3705 S Western Ave Sioux Falls SD 57105",
    "addr:housenumber":"3705",
    "addr:postcode":"57105",
    "addr:street":"S Western Ave",
    "iso:country":"US",
    "sg:address":"3705 S Western Ave",
    "sg:city":"Sioux Falls",
    "sg:classifiers":[
        {
            "category":"Travel",
            "subcategory":"Hotels & Motels",
            "type":"Entertainment"
        }
    ],
    "sg:phone":"+1 605 332 4721",
    "sg:postcode":"57105",
    "sg:province":"SD",
    "sg:tags":[
        "operation"
    ],
    "wof:name":"Lucky Dollars Inc",
    "wof:placetype":"venue"
},
  "geometry": {"coordinates":[-96.75116199999999,43.512947],"type":"Point"}
}