{
  "type": "Feature",
  "properties": {
    "addr:full":"3220 W 57th St Sioux Falls SD 57108",
    "addr:housenumber":"3220",
    "addr:postcode":"57108",
    "addr:street":"W 57Th St",
    "iso:country":"US",
    "sg:address":"3220 W 57th St",
    "sg:city":"Sioux Falls",
    "sg:classifiers":[
        {
            "category":"Insurance",
            "subcategory":"Insurance Agent",
            "type":"Services"
        }
    ],
    "sg:phone":"+1 605 335 1111",
    "sg:postcode":"57108",
    "sg:province":"SD",
    "wof:name":"American Family Insurance",
    "wof:placetype":"venue"
},
  "geometry": {"coordinates":[-96.762804,43.500268],"type":"Point"}
}