{
  "type": "Feature",
  "properties": {
    "iso:country":"US",
    "sg:address":"718 S Prairie Ave",
    "sg:city":"Sioux Falls",
    "sg:classifiers":[
        {
            "category":"Building & Trades",
            "subcategory":"Plumbing",
            "type":"Services"
        }
    ],
    "sg:phone":"+1 605 332 1780",
    "sg:postcode":"57104",
    "sg:province":"SD",
    "sg:tags":[
        "conditioning",
        "air",
        "system",
        "contractor"
    ],
    "wof:name":"Essem Refrigeration/Air Cond",
    "wof:placetype":"venue"
},
  "geometry": {"coordinates":[-96.736991,43.539194],"type":"Point"}
}