{
  "type": "Feature",
  "properties": {
    "iso:country":"US",
    "sg:address":"2613 Black Saddle Rd",
    "sg:city":"Rapid City",
    "sg:classifiers":[
        {
            "category":"Professional",
            "subcategory":"Secretarial Services",
            "type":"Services"
        }
    ],
    "sg:phone":"+1 605 343 8002",
    "sg:postcode":"57703",
    "sg:province":"SD",
    "sg:tags":[
        "reporting",
        "court"
    ],
    "wof:name":"Niki R Zebrowski",
    "wof:placetype":"venue"
},
  "geometry": {"coordinates":[-103.171182,43.978662],"type":"Point"}
}