{
  "type": "Feature",
  "properties": {
    "addr:full":"301 2nd Ave E Mc Laughlin SD 57638",
    "addr:housenumber":"301",
    "addr:postcode":"57638",
    "addr:street":"2Nd Ave E Mc",
    "iso:country":"US",
    "sg:address":"301 2nd Ave E",
    "sg:city":"Mc Laughlin",
    "sg:classifiers":[
        {
            "category":"Social Services",
            "type":"Services"
        }
    ],
    "sg:phone":"+1 605 823 2098",
    "sg:postcode":"57638",
    "sg:province":"SD",
    "sg:tags":[
        "organization",
        "welfare"
    ],
    "wof:name":"Child Protection Svc Oniyapi",
    "wof:placetype":"venue"
},
  "geometry": {"coordinates":[-102.156075,45.941917],"type":"Point"}
}