{
  "type": "Feature",
  "properties": {
    "iso:country":"US",
    "sg:address":"700 Main St",
    "sg:city":"Platte",
    "sg:classifiers":[
        {
            "category":"Shopping",
            "subcategory":"Florist",
            "type":"Retail Goods"
        }
    ],
    "sg:phone":"+1 605 337 3497",
    "sg:postcode":"57369",
    "sg:province":"SD",
    "wof:name":"Platte Flower Shop",
    "wof:placetype":"venue"
},
  "geometry": {"coordinates":[-98.844742,43.384139],"type":"Point"}
}