{
  "type": "Feature",
  "properties": {
    "addr:full":"1201 W Melgaard Rd Aberdeen SD 57401",
    "addr:housenumber":"1201",
    "addr:postcode":"57401",
    "addr:street":"W Melgaard Rd",
    "iso:country":"US",
    "sg:address":"1201 W Melgaard Rd",
    "sg:city":"Aberdeen",
    "sg:classifiers":[
        {
            "category":"Wholesale",
            "subcategory":"Construction Materials",
            "type":"Manufacturing & Wholesale Goods"
        }
    ],
    "sg:phone":"+1 605 229 0271",
    "sg:postcode":"57401",
    "sg:province":"SD",
    "sg:tags":[
        "sand",
        "gravel"
    ],
    "wof:name":"H F Jacobs & Sons Constr Inc",
    "wof:placetype":"venue"
},
  "geometry": {"coordinates":[-98.497136,45.444883],"type":"Point"}
}