{
  "type": "Feature",
  "properties": {
    "iso:country":"US",
    "sg:address":"245 E Main St",
    "sg:city":"Corsica",
    "sg:classifiers":[
        {
            "category":"Restaurant",
            "type":"Food & Drink"
        }
    ],
    "sg:phone":"+1 605 946 5079",
    "sg:postcode":"57328",
    "sg:province":"SD",
    "wof:name":"Burkes",
    "wof:placetype":"venue"
},
  "geometry": {"coordinates":[-98.40756,43.423633],"type":"Point"}
}