{
  "type": "Feature",
  "properties": {
    "iso:country":"US",
    "sg:address":"1625 Christensen Dr",
    "sg:city":"Spearfish",
    "sg:classifiers":[
        {
            "category":"Retail",
            "subcategory":"Animal Services",
            "type":"Services"
        }
    ],
    "sg:phone":"+1 605 641 4134",
    "sg:postcode":"57783",
    "sg:province":"SD",
    "wof:name":"Animal Inn Board Groom & Train",
    "wof:placetype":"venue"
},
  "geometry": {"coordinates":[-103.83094800000001,44.460267],"type":"Point"}
}