{
  "type": "Feature",
  "properties": {
    "iso:country":"US",
    "sg:address":"505 N 7th Ave",
    "sg:city":"Woonsocket",
    "sg:classifiers":[
        {
            "category":"Building & Trades",
            "subcategory":"Plumbing",
            "type":"Services"
        }
    ],
    "sg:phone":"+1 605 796 4653",
    "sg:postcode":"57385",
    "sg:province":"SD",
    "sg:tags":[
        "electrical",
        "contractor"
    ],
    "wof:name":"Hinker Trenching & Electric",
    "wof:placetype":"venue"
},
  "geometry": {"coordinates":[-98.27100299999999,44.057006],"type":"Point"}
}