{
  "type": "Feature",
  "properties": {
    "iso:country":"US",
    "sg:address":"28380 427th Ave",
    "sg:city":"Olivet",
    "sg:phone":"+1 605 387 5229",
    "sg:postcode":"57052",
    "sg:province":"SD",
    "sg:tags":[
        "beef",
        "farm",
        "corn",
        "soybean",
        "cattle",
        "feedlot"
    ],
    "wof:name":"Jay Herrboldt",
    "wof:placetype":"venue"
},
  "geometry": {"coordinates":[-97.65849300000001,43.273267],"type":"Point"}
}