{
  "type": "Feature",
  "properties": {
    "iso:country":"US",
    "sg:address":"798 E 5th St",
    "sg:city":"Winner",
    "sg:classifiers":[
        {
            "category":"Organizations",
            "subcategory":"Religious Organization",
            "type":"Services"
        }
    ],
    "sg:phone":"+1 605 842 0780",
    "sg:postcode":"57580",
    "sg:province":"SD",
    "sg:tags":[
        "church"
    ],
    "wof:name":"Christ Lutheran Church L C",
    "wof:placetype":"venue"
},
  "geometry": {"coordinates":[-99.847461,43.373315],"type":"Point"}
}