{
  "type": "Feature",
  "properties": {
    "iso:country":"US",
    "sg:address":"26407 465th Ave",
    "sg:city":"Hartford",
    "sg:classifiers":[
        {
            "category":"Farming",
            "subcategory":"Dairy Farm",
            "type":"Manufacturing & Wholesale Goods"
        }
    ],
    "sg:phone":"+1 605 526 3564",
    "sg:postcode":"57033",
    "sg:province":"SD",
    "sg:tags":[
        "beef",
        "feedlot",
        "cattle"
    ],
    "wof:name":"Anderson Marlo",
    "wof:placetype":"venue"
},
  "geometry": {"coordinates":[-96.910589,43.557006],"type":"Point"}
}