{
  "type": "Feature",
  "properties": {
    "iso:country":"US",
    "sg:address":"2201 Jackson Blvd",
    "sg:city":"Rapid City",
    "sg:classifiers":[
        {
            "category":"Shopping",
            "subcategory":"Pharmacy",
            "type":"Retail Goods"
        }
    ],
    "sg:phone":"+1 605 399 3747",
    "sg:postcode":"57702",
    "sg:province":"SD",
    "sg:tags":[
        "drug",
        "store"
    ],
    "wof:name":"Medicap Pharmacy",
    "wof:placetype":"venue"
},
  "geometry": {"coordinates":[-103.256967,44.07184],"type":"Point"}
}