{
  "type": "Feature",
  "properties": {
    "addr:full":"1101 W 22nd St Sioux Falls SD 57105",
    "addr:housenumber":"1101",
    "addr:postcode":"57105",
    "addr:street":"W 22Nd St",
    "iso:country":"US",
    "sg:address":"1101 W 22nd St",
    "sg:city":"Sioux Falls",
    "sg:classifiers":[
        {
            "category":"Organizations",
            "subcategory":"Religious Organization",
            "type":"Services"
        }
    ],
    "sg:phone":"+1 605 575 2071",
    "sg:postcode":"57105",
    "sg:province":"SD",
    "wof:name":"American Baptist Churches",
    "wof:placetype":"venue"
},
  "geometry": {"coordinates":[-96.739993,43.533027],"type":"Point"}
}