{
  "type": "Feature",
  "properties": {
    "addr:full":"651 Margaret St Big Stone City SD 57216",
    "addr:housenumber":"651",
    "addr:postcode":"57216",
    "addr:street":"Margaret St",
    "iso:country":"US",
    "sg:address":"651 Margaret St",
    "sg:city":"Big Stone City",
    "sg:classifiers":[
        {
            "category":"Organizations",
            "subcategory":"Religious Organization",
            "type":"Services"
        }
    ],
    "sg:phone":"+1 605 862 8281",
    "sg:postcode":"57216",
    "sg:province":"SD",
    "sg:tags":[
        "church"
    ],
    "wof:name":"United Methodist Church",
    "wof:placetype":"venue"
},
  "geometry": {"coordinates":[-96.46507099999999,45.295794],"type":"Point"}
}