{
  "type": "Feature",
  "properties": {
    "iso:country":"US",
    "sg:address":"215 W 43rd St",
    "sg:city":"Sioux Falls",
    "sg:classifiers":[
        {
            "category":"Autos & Motor Vehicles",
            "subcategory":"Auto Supplies",
            "type":"Retail Goods"
        }
    ],
    "sg:phone":"+1 605 335 8405",
    "sg:postcode":"57105",
    "sg:province":"SD",
    "sg:tags":[
        "automobile",
        "parts"
    ],
    "wof:name":"Autowerks Imports Parts",
    "wof:placetype":"venue"
},
  "geometry": {"coordinates":[-96.727885,43.513001],"type":"Point"}
}