{
  "type": "Feature",
  "properties": {
    "addr:full":"803 W Cedar St Beresford SD 57004",
    "addr:housenumber":"803",
    "addr:postcode":"57004",
    "addr:street":"W Cedar St",
    "iso:country":"US",
    "sg:address":"803 W Cedar St",
    "sg:city":"Beresford",
    "sg:classifiers":[
        {
            "category":"Restaurant",
            "type":"Food & Drink"
        },
        {
            "category":"Food & Beverages",
            "subcategory":"Groceries & Convenience Stores",
            "type":"Retail Goods"
        }
    ],
    "sg:menulink":"http://www.allmenus.com/sd/pleasant/225084-caseys-general-store/menu/",
    "sg:phone":"+1 605 763 2036",
    "sg:postcode":"57004",
    "sg:province":"SD",
    "sg:tags":[
        "american",
        "pizza"
    ],
    "wof:name":"Casey's General Store",
    "wof:placetype":"venue"
},
  "geometry": {"coordinates":[-96.783908,43.083691],"type":"Point"}
}