{
  "type": "Feature",
  "properties": {
    "iso:country":"US",
    "sg:address":"311 S King St",
    "sg:city":"Dimock",
    "sg:classifiers":[
        {
            "category":"Building & Trades",
            "subcategory":"Construction",
            "type":"Services"
        }
    ],
    "sg:phone":"+1 605 928 3107",
    "sg:postcode":"57331",
    "sg:province":"SD",
    "sg:tags":[
        "general",
        "contractor"
    ],
    "wof:name":"Dan Weber Construction",
    "wof:placetype":"venue"
},
  "geometry": {"coordinates":[-97.986976,43.4762],"type":"Point"}
}