{
  "type": "Feature",
  "properties": {
    "iso:country":"US",
    "sg:address":"732 Jackson Blvd",
    "sg:city":"Rapid City",
    "sg:classifiers":[
        {
            "category":"Shopping",
            "subcategory":"Department Store",
            "type":"Retail Goods"
        }
    ],
    "sg:phone":"+1 605 343 4086",
    "sg:postcode":"57702",
    "sg:province":"SD",
    "sg:tags":[
        "shop"
    ],
    "wof:name":"X S Direct Discounts",
    "wof:placetype":"venue"
},
  "geometry": {"coordinates":[-103.249657,44.078628],"type":"Point"}
}