{
  "type": "Feature",
  "properties": {
    "addr:full":"758 S 3rd Ave Sioux Falls SD 57104",
    "addr:housenumber":"758",
    "addr:postcode":"57104",
    "addr:street":"S 3Rd Ave",
    "iso:country":"US",
    "sg:address":"758 S 3rd Ave",
    "sg:city":"Sioux Falls",
    "sg:classifiers":[
        {
            "category":"Professional",
            "subcategory":"Business Services",
            "type":"Services"
        }
    ],
    "sg:phone":"+1 605 275 6565",
    "sg:postcode":"57104",
    "sg:province":"SD",
    "sg:tags":[
        "translator",
        "interpreter"
    ],
    "wof:name":"A To Z Language Interpreters",
    "wof:placetype":"venue"
},
  "geometry": {"coordinates":[-96.72221500000001,43.540051],"type":"Point"}
}