{
  "type": "Feature",
  "properties": {
    "iso:country":"US",
    "sg:address":"518 6th St",
    "sg:city":"Rapid City",
    "sg:classifiers":[
        {
            "category":"Professional",
            "subcategory":"Business Services",
            "type":"Services"
        }
    ],
    "sg:phone":"+1 605 388 0106",
    "sg:postcode":"57701",
    "sg:province":"SD",
    "sg:tags":[
        "transcribing",
        "disc"
    ],
    "wof:name":"T M Transcription",
    "wof:placetype":"venue"
},
  "geometry": {"coordinates":[-103.227182,44.080195],"type":"Point"}
}