{
  "type": "Feature",
  "properties": {
    "iso:country":"US",
    "sg:address":"5 N Maple",
    "sg:city":"Watertown",
    "sg:classifiers":[
        {
            "category":"Shopping",
            "subcategory":"Hobbies, Toys, & Games",
            "type":"Retail Goods"
        }
    ],
    "sg:phone":"+1 605 882 2858",
    "sg:postcode":"57201",
    "sg:province":"SD",
    "wof:name":"Lemon Tree Enterprises",
    "wof:placetype":"venue"
},
  "geometry": {"coordinates":[-97.112452,44.901354],"type":"Point"}
}