{
  "type": "Feature",
  "properties": {
    "iso:country":"US",
    "sg:address":"1810 W 50th St",
    "sg:city":"Sioux Falls",
    "sg:classifiers":[
        {
            "category":"Autos & Motor Vehicles",
            "subcategory":"Auto Supplies",
            "type":"Retail Goods"
        }
    ],
    "sg:phone":"+1 605 339 0039",
    "sg:postcode":"57105",
    "sg:province":"SD",
    "sg:tags":[
        "tire"
    ],
    "wof:name":"Siem's Tire & Svc",
    "wof:placetype":"venue"
},
  "geometry": {"coordinates":[-96.746932,43.507415],"type":"Point"}
}