{
  "type": "Feature",
  "properties": {
    "iso:country":"US",
    "sg:address":"927 E Colorado Blvd",
    "sg:city":"Spearfish",
    "sg:classifiers":[
        {
            "category":"Shopping",
            "subcategory":"Department Store",
            "type":"Retail Goods"
        }
    ],
    "sg:phone":"+1 605 722 3001",
    "sg:postcode":"57783",
    "sg:province":"SD",
    "wof:name":"Dollar Spree",
    "wof:placetype":"venue"
},
  "geometry": {"coordinates":[-103.845288,44.482157],"type":"Point"}
}