{
  "type": "Feature",
  "properties": {
    "iso:country":"US",
    "sg:address":"915 E Birch Ave",
    "sg:city":"Mitchell",
    "sg:classifiers":[
        {
            "category":"Retail",
            "subcategory":"Auto Repair",
            "type":"Services"
        }
    ],
    "sg:phone":"+1 605 996 6055",
    "sg:postcode":"57301",
    "sg:province":"SD",
    "sg:tags":[
        "repairing",
        "automobile"
    ],
    "wof:name":"American Dream Restorations",
    "wof:placetype":"venue"
},
  "geometry": {"coordinates":[-98.01354600000001,43.706413],"type":"Point"}
}