{
  "type": "Feature",
  "properties": {
    "iso:country":"US",
    "sg:address":"2908 5th St",
    "sg:city":"Rapid City",
    "sg:classifiers":[
        {
            "category":"Health Services",
            "subcategory":"Hospital",
            "type":"Services"
        }
    ],
    "sg:phone":"+1 605 719 1100",
    "sg:postcode":"57701",
    "sg:province":"SD",
    "wof:name":"Black Hills Rehabilitation",
    "wof:placetype":"venue"
},
  "geometry": {"coordinates":[-103.226898,44.058333],"type":"Point"}
}