{
  "type": "Feature",
  "properties": {
    "iso:country":"US",
    "sg:address":"322 2nd St",
    "sg:city":"Rapid City",
    "sg:classifiers":[
        {
            "category":"Wholesale",
            "subcategory":"Tobacco Products",
            "type":"Manufacturing & Wholesale Goods"
        },
        {
            "category":"Shopping",
            "subcategory":"Computers & Home Electronics",
            "type":"Retail Goods"
        }
    ],
    "sg:phone":"+1 605 718 4775",
    "sg:postcode":"57701",
    "sg:province":"SD",
    "sg:tags":[
        "cigarette",
        "game",
        "cigar",
        "video",
        "dealer"
    ],
    "wof:name":"Automatic Vendors Inc",
    "wof:placetype":"venue"
},
  "geometry": {"coordinates":[-103.219042,44.081154],"type":"Point"}
}