{
  "type": "Feature",
  "properties": {
    "iso:country":"US",
    "sg:address":"1 S Main St",
    "sg:city":"Aberdeen",
    "sg:classifiers":[
        {
            "category":"Professional",
            "subcategory":"Management & Consulting",
            "type":"Services"
        }
    ],
    "sg:phone":"+1 605 226 3441",
    "sg:postcode":"57401",
    "sg:province":"SD",
    "sg:tags":[
        "development",
        "economic",
        "agency"
    ],
    "wof:name":"Aberdeen Downtown Assn",
    "wof:placetype":"venue"
},
  "geometry": {"coordinates":[-98.488,45.46513],"type":"Point"}
}