{
  "type": "Feature",
  "properties": {
    "addr:full":"2418 Minnewasta Ct Rapid City SD 57702",
    "addr:housenumber":"2418",
    "addr:postcode":"57702",
    "addr:street":"Minnewasta Ct",
    "iso:country":"US",
    "sg:address":"2418 Minnewasta Ct",
    "sg:city":"Rapid City",
    "sg:classifiers":[
        {
            "category":"Freight",
            "type":"Transportation"
        }
    ],
    "sg:phone":"+1 605 342 1524",
    "sg:postcode":"57702",
    "sg:province":"SD",
    "sg:tags":[
        "distance",
        "long",
        "trucker"
    ],
    "wof:name":"M&J Cartridge LLC",
    "wof:placetype":"venue"
},
  "geometry": {"coordinates":[-103.260606,44.05906],"type":"Point"}
}