{
  "type": "Feature",
  "properties": {
    "iso:country":"US",
    "sg:address":"114 10th St E",
    "sg:city":"Mobridge",
    "sg:classifiers":[
        {
            "category":"Education",
            "subcategory":"School",
            "type":"Public Place"
        }
    ],
    "sg:phone":"+1 605 845 5508",
    "sg:postcode":"57601",
    "sg:province":"SD",
    "wof:name":"Mobridge Public School",
    "wof:placetype":"venue"
},
  "geometry": {"coordinates":[-100.433764,45.542562],"type":"Point"}
}