{
  "type": "Feature",
  "properties": {
    "addr:full":"14554 366th Ave Cresbard SD 57435",
    "addr:housenumber":"14554",
    "addr:postcode":"57435",
    "addr:street":"366Th Ave",
    "iso:country":"US",
    "sg:address":"14554 366th Ave",
    "sg:city":"Cresbard",
    "sg:phone":"+1 605 324 3250",
    "sg:postcode":"57435",
    "sg:province":"SD",
    "sg:tags":[
        "wheat",
        "beef",
        "farm",
        "cash",
        "grain",
        "cattle",
        "feedlot"
    ],
    "wof:name":"Bryce K Nash",
    "wof:placetype":"venue"
},
  "geometry": {"coordinates":[-98.866039,45.279572],"type":"Point"}
}