{
  "type": "Feature",
  "properties": {
    "iso:country":"US",
    "sg:address":"1935 E 60th St",
    "sg:city":"Sioux Falls",
    "sg:classifiers":[
        {
            "category":"Building & Trades",
            "subcategory":"Construction",
            "type":"Services"
        }
    ],
    "sg:phone":"+1 605 331 5675",
    "sg:postcode":"57104",
    "sg:province":"SD",
    "sg:tags":[
        "contractor"
    ],
    "wof:name":"D & R Welding",
    "wof:placetype":"venue"
},
  "geometry": {"coordinates":[-96.702012,43.601818],"type":"Point"}
}