{
  "type": "Feature",
  "properties": {
    "addr:full":"13455 400th Ave Groton SD 57445",
    "addr:housenumber":"13455",
    "addr:postcode":"57445",
    "addr:street":"400Th Ave",
    "iso:country":"US",
    "sg:address":"13455 400th Ave",
    "sg:city":"Groton",
    "sg:phone":"+1 605 397 8255",
    "sg:postcode":"57445",
    "sg:province":"SD",
    "sg:tags":[
        "farm",
        "wheat"
    ],
    "wof:name":"Jack McKiver",
    "wof:placetype":"venue"
},
  "geometry": {"coordinates":[-98.22681799999999,45.435881],"type":"Point"}
}