{
  "type": "Feature",
  "properties": {
    "iso:country":"US",
    "sg:address":"522 N Main Ave",
    "sg:city":"Sioux Falls",
    "sg:classifiers":[
        {
            "category":"Social Services",
            "subcategory":"Child Care",
            "type":"Services"
        }
    ],
    "sg:phone":"+1 605 339 2095",
    "sg:postcode":"57104",
    "sg:province":"SD",
    "sg:tags":[
        "day"
    ],
    "wof:name":"Youth Enrichment Services Inc",
    "wof:placetype":"venue"
},
  "geometry": {"coordinates":[-96.728276,43.55354],"type":"Point"}
}