{
  "type": "Feature",
  "properties": {
    "addr:full":"200 S Laban St Colman SD 57017",
    "addr:housenumber":"200",
    "addr:postcode":"57017",
    "addr:street":"S Laban St",
    "iso:country":"US",
    "sg:address":"200 S Laban St",
    "sg:city":"Colman",
    "sg:classifiers":[
        {
            "category":"Education",
            "subcategory":"School",
            "type":"Public Place"
        }
    ],
    "sg:phone":"+1 605 534 3534",
    "sg:postcode":"57017",
    "sg:province":"SD",
    "sg:tags":[
        "educational",
        "administrative"
    ],
    "sg:website":"www.colman-egan.k12.sd.us",
    "wof:name":"Colman-Egan School",
    "wof:placetype":"venue"
},
  "geometry": {"coordinates":[-96.811088,43.980981],"type":"Point"}
}