{
  "type": "Feature",
  "properties": {
    "iso:country":"US",
    "sg:address":"302 E Park Ave",
    "sg:city":"Viborg",
    "sg:classifiers":[
        {
            "category":"Personal",
            "subcategory":"Beauty Salon",
            "type":"Services"
        }
    ],
    "sg:phone":"+1 605 766 5753",
    "sg:postcode":"57070",
    "sg:province":"SD",
    "wof:name":"All Around Hair Styles",
    "wof:placetype":"venue"
},
  "geometry": {"coordinates":[-97.07852,43.170377],"type":"Point"}
}