{
  "type": "Feature",
  "properties": {
    "addr:full":"13008 Pine Dr Rapid City SD 57702",
    "addr:housenumber":"13008",
    "addr:postcode":"57702",
    "addr:street":"Pine Dr",
    "iso:country":"US",
    "sg:address":"13008 Pine Dr",
    "sg:city":"Rapid City",
    "sg:classifiers":[
        {
            "category":"Building & Trades",
            "subcategory":"Construction",
            "type":"Services"
        }
    ],
    "sg:phone":"+1 605 399 2020",
    "sg:postcode":"57702",
    "sg:province":"SD",
    "sg:tags":[
        "excavating",
        "contractor"
    ],
    "wof:name":"Chucklin Excavation",
    "wof:placetype":"venue"
},
  "geometry": {"coordinates":[-103.439857,44.139151],"type":"Point"}
}