{
  "type": "Feature",
  "properties": {
    "iso:country":"US",
    "sg:address":"127 Main St",
    "sg:city":"Castlewood",
    "sg:classifiers":[
        {
            "category":"Insurance",
            "subcategory":"Insurance Agent",
            "type":"Services"
        }
    ],
    "sg:phone":"+1 605 793 2123",
    "sg:postcode":"57223",
    "sg:province":"SD",
    "wof:name":"Strait Insurance",
    "wof:placetype":"venue"
},
  "geometry": {"coordinates":[-97.031882,44.722825],"type":"Point"}
}