{
  "type": "Feature",
  "properties": {
    "addr:full":"5415 W 41st St Sioux Falls SD 57106",
    "addr:housenumber":"5415",
    "addr:postcode":"57106",
    "addr:street":"W 41St St",
    "iso:country":"US",
    "sg:address":"5415 W 41st St",
    "sg:city":"Sioux Falls",
    "sg:classifiers":[
        {
            "category":"Health Services",
            "subcategory":"Chiropractor",
            "type":"Services"
        }
    ],
    "sg:phone":"+1 605 361 2500",
    "sg:postcode":"57106",
    "sg:province":"SD",
    "wof:name":"Odland Chiropractic",
    "wof:placetype":"venue"
},
  "geometry": {"coordinates":[-96.792368,43.514735],"type":"Point"}
}