{
  "type": "Feature",
  "properties": {
    "iso:country":"US",
    "sg:address":"128 May St",
    "sg:city":"Lead",
    "sg:classifiers":[
        {
            "category":"Personal",
            "subcategory":"Beauty Salon",
            "type":"Services"
        }
    ],
    "sg:phone":"+1 605 584 2698",
    "sg:postcode":"57754",
    "sg:province":"SD",
    "sg:tags":[
        "shop"
    ],
    "wof:name":"Salon No 10",
    "wof:placetype":"venue"
},
  "geometry": {"coordinates":[-103.773958,44.349749],"type":"Point"}
}