{
  "type": "Feature",
  "properties": {
    "iso:country":"US",
    "sg:address":"20429 418th Ave",
    "sg:city":"Iroquois",
    "sg:classifiers":[
        {
            "category":"Farming",
            "subcategory":"Livestock Farm",
            "type":"Manufacturing & Wholesale Goods"
        }
    ],
    "sg:phone":"+1 605 546 2427",
    "sg:postcode":"57353",
    "sg:province":"SD",
    "sg:tags":[
        "beef",
        "feedlot",
        "cattle"
    ],
    "wof:name":"Jonathan Penner",
    "wof:placetype":"venue"
},
  "geometry": {"coordinates":[-97.85330399999999,44.422224],"type":"Point"}
}