{
  "type": "Feature",
  "properties": {
    "iso:country":"US",
    "sg:address":"500 N 5th St",
    "sg:city":"Hot Springs",
    "sg:classifiers":[
        {
            "category":"Social Services",
            "subcategory":"Child Care",
            "type":"Services"
        }
    ],
    "sg:phone":"+1 605 745 2894",
    "sg:postcode":"57747",
    "sg:province":"SD",
    "wof:name":"Tots N Toddlers Daycare",
    "wof:placetype":"venue"
},
  "geometry": {"coordinates":[-103.475488,43.437785],"type":"Point"}
}