{
  "type": "Feature",
  "properties": {
    "addr:full":"605 N Leadale Ave Sioux Falls SD 57103",
    "addr:housenumber":"605",
    "addr:postcode":"57103",
    "addr:street":"N Leadale Ave",
    "iso:country":"US",
    "sg:address":"605 N Leadale Ave",
    "sg:city":"Sioux Falls",
    "sg:classifiers":[
        {
            "category":"Manufacturing",
            "subcategory":"Paper Products",
            "type":"Manufacturing & Wholesale Goods"
        }
    ],
    "sg:phone":"+1 605 332 8990",
    "sg:postcode":"57103",
    "sg:province":"SD",
    "sg:tags":[
        "mill"
    ],
    "wof:name":"Paul Pierret Wallcovering",
    "wof:placetype":"venue"
},
  "geometry": {"coordinates":[-96.69831000000001,43.554315],"type":"Point"}
}