{
  "type": "Feature",
  "properties": {
    "iso:country":"US",
    "sg:address":"26427 484th Ave",
    "sg:city":"Valley Springs",
    "sg:classifiers":[
        {
            "category":"Building & Trades",
            "subcategory":"Construction",
            "type":"Services"
        }
    ],
    "sg:phone":"+1 605 582 7117",
    "sg:postcode":"57068",
    "sg:province":"SD",
    "sg:tags":[
        "resurfacing",
        "laying",
        "refinishing",
        "floor"
    ],
    "sg:website":"www.dakotafloors.com",
    "wof:name":"Dakota Floors Inc",
    "wof:placetype":"venue"
},
  "geometry": {"coordinates":[-96.532178,43.5547],"type":"Point"}
}