{
  "type": "Feature",
  "properties": {
    "iso:country":"US",
    "sg:address":"26985 Tallgrass Ave",
    "sg:city":"Sioux Falls",
    "sg:classifiers":[
        {
            "category":"Building & Trades",
            "subcategory":"Construction",
            "type":"Services"
        }
    ],
    "sg:phone":"+1 605 368 5147",
    "sg:postcode":"57108",
    "sg:province":"SD",
    "sg:tags":[
        "excavating",
        "contractor"
    ],
    "wof:name":"Verhey Construction Inc",
    "wof:placetype":"venue"
},
  "geometry": {"coordinates":[-96.78725300000001,43.478387],"type":"Point"}
}