{
  "type": "Feature",
  "properties": {
    "addr:full":"41103 125th St Groton SD 57445",
    "addr:housenumber":"41103",
    "addr:postcode":"57445",
    "addr:street":"125Th St",
    "iso:country":"US",
    "sg:address":"41103 125th St",
    "sg:city":"Groton",
    "sg:classifiers":[
        {
            "category":"Shopping",
            "subcategory":"Hobbies, Toys, & Games",
            "type":"Retail Goods"
        }
    ],
    "sg:phone":"+1 605 397 4585",
    "sg:postcode":"57445",
    "sg:province":"SD",
    "sg:tags":[
        "product",
        "ceramic"
    ],
    "wof:name":"Rose Creations",
    "wof:placetype":"venue"
},
  "geometry": {"coordinates":[-97.999995,45.573792],"type":"Point"}
}