{
  "type": "Feature",
  "properties": {
    "addr:full":"3424 N Cliff Ave Sioux Falls SD 57104",
    "addr:housenumber":"3424",
    "addr:postcode":"57104",
    "addr:street":"N Cliff Ave",
    "iso:country":"US",
    "sg:address":"3424 N Cliff Ave",
    "sg:city":"Sioux Falls",
    "sg:classifiers":[
        {
            "category":"Restaurant",
            "type":"Food & Drink"
        }
    ],
    "sg:menulink":"http://www.allmenus.com/sd/sioux-falls/144761-subway/menu/",
    "sg:phone":"+1 605 338 5933",
    "sg:postcode":"57104",
    "sg:province":"SD",
    "sg:tags":[
        "american",
        "sandwich"
    ],
    "wof:name":"Subway",
    "wof:placetype":"venue"
},
  "geometry": {"coordinates":[-96.711359,43.582436],"type":"Point"}
}