{
  "type": "Feature",
  "properties": {
    "iso:country":"US",
    "sg:address":"704 E 8th St",
    "sg:city":"Sioux Falls",
    "sg:classifiers":[
        {
            "category":"Cinema",
            "subcategory":"Movie Rental",
            "type":"Entertainment"
        }
    ],
    "sg:phone":"+1 605 373 9310",
    "sg:postcode":"57103",
    "sg:province":"SD",
    "sg:tags":[
        "video",
        "tape"
    ],
    "wof:name":"Apolinar Hernandez",
    "wof:placetype":"venue"
},
  "geometry": {"coordinates":[-96.717057,43.548707],"type":"Point"}
}