{
  "type": "Feature",
  "properties": {
    "iso:country":"US",
    "sg:address":"109 N Utah St",
    "sg:city":"Clark",
    "sg:classifiers":[
        {
            "category":"Freight",
            "type":"Transportation"
        }
    ],
    "sg:phone":"+1 605 532 5760",
    "sg:postcode":"57225",
    "sg:province":"SD",
    "sg:tags":[
        "operator",
        "trucking"
    ],
    "wof:name":"Lee Trucking",
    "wof:placetype":"venue"
},
  "geometry": {"coordinates":[-97.739844,44.878724],"type":"Point"}
}