{
  "type": "Feature",
  "properties": {
    "iso:country":"US",
    "sg:address":"17330 363rd Ave",
    "sg:city":"Rockham",
    "sg:classifiers":[
        {
            "category":"Farming",
            "subcategory":"Farm",
            "type":"Manufacturing & Wholesale Goods"
        }
    ],
    "sg:phone":"+1 605 472 1341",
    "sg:postcode":"57470",
    "sg:province":"SD",
    "sg:tags":[
        "crop",
        "general"
    ],
    "wof:name":"Oakley Farms",
    "wof:placetype":"venue"
},
  "geometry": {"coordinates":[-98.927307,44.874883],"type":"Point"}
}