{
  "type": "Feature",
  "properties": {
    "addr:full":"725 E Wells Ave Pierre SD 57501",
    "addr:housenumber":"725",
    "addr:postcode":"57501",
    "addr:street":"E Wells Ave",
    "iso:country":"US",
    "sg:address":"725 E Wells Ave",
    "sg:city":"Pierre",
    "sg:classifiers":[
        {
            "category":"Organizations",
            "subcategory":"Religious Organization",
            "type":"Services"
        }
    ],
    "sg:phone":"+1 605 945 0084",
    "sg:postcode":"57501",
    "sg:province":"SD",
    "wof:name":"Missions LDS",
    "wof:placetype":"venue"
},
  "geometry": {"coordinates":[-100.342865,44.36389],"type":"Point"}
}