{
  "type": "Feature",
  "properties": {
    "addr:full":"314 Main St Gregory SD 57533",
    "addr:housenumber":"314",
    "addr:postcode":"57533",
    "addr:street":"Main St",
    "iso:country":"US",
    "sg:address":"314 Main St",
    "sg:city":"Gregory",
    "sg:classifiers":[
        {
            "category":"Retail",
            "subcategory":"Auto Repair",
            "type":"Services"
        }
    ],
    "sg:phone":"+1 605 835 9288",
    "sg:postcode":"57533",
    "sg:province":"SD",
    "sg:tags":[
        "repairing",
        "automobile",
        "general"
    ],
    "wof:name":"Allen's Repair",
    "wof:placetype":"venue"
},
  "geometry": {"coordinates":[-99.430903,43.22991],"type":"Point"}
}