{
  "type": "Feature",
  "properties": {
    "addr:full":"1609 S Rock Creek Dr Sioux Falls SD 57103",
    "addr:housenumber":"1609",
    "addr:postcode":"57103",
    "addr:street":"S Rock Creek Dr",
    "iso:country":"US",
    "sg:address":"1609 S Rock Creek Dr",
    "sg:city":"Sioux Falls",
    "sg:classifiers":[
        {
            "category":"Building & Trades",
            "subcategory":"Construction",
            "type":"Services"
        }
    ],
    "sg:phone":"+1 605 332 3887",
    "sg:postcode":"57103",
    "sg:province":"SD",
    "sg:tags":[
        "house"
    ],
    "wof:name":"Riddle Enterprises",
    "wof:placetype":"venue"
},
  "geometry": {"coordinates":[-96.690934,43.530866],"type":"Point"}
}