{
  "type": "Feature",
  "properties": {
    "iso:country":"US",
    "sg:address":"22 N Broadway",
    "sg:city":"Watertown",
    "sg:classifiers":[
        {
            "category":"Bars & Pubs",
            "type":"Food & Drink"
        }
    ],
    "sg:phone":"+1 605 886 9990",
    "sg:postcode":"57201",
    "sg:province":"SD",
    "sg:tags":[
        "drinking"
    ],
    "wof:name":"Duffy's Bar",
    "wof:placetype":"venue"
},
  "geometry": {"coordinates":[-97.11404899999999,44.901441],"type":"Point"}
}