{
  "type": "Feature",
  "properties": {
    "iso:country":"US",
    "sg:address":"3400 S Norton Ave",
    "sg:city":"Sioux Falls",
    "sg:classifiers":[
        {
            "category":"Shopping",
            "subcategory":"Used Merchandise",
            "type":"Retail Goods"
        }
    ],
    "sg:phone":"+1 605 731 1930",
    "sg:postcode":"57105",
    "sg:province":"SD",
    "wof:name":"Goodwill Store",
    "wof:placetype":"venue"
},
  "geometry": {"coordinates":[-96.734937,43.513051],"type":"Point"}
}