{
  "type": "Feature",
  "properties": {
    "iso:country":"US",
    "sg:address":"43574 113th St",
    "sg:city":"Lake City",
    "sg:classifiers":[
        {
            "category":"Farming",
            "subcategory":"Farm",
            "type":"Manufacturing & Wholesale Goods"
        }
    ],
    "sg:phone":"+1 605 448 5565",
    "sg:postcode":"57247",
    "sg:province":"SD",
    "sg:tags":[
        "crop"
    ],
    "wof:name":"Schultz Herluf",
    "wof:placetype":"venue"
},
  "geometry": {"coordinates":[-97.487572,45.746828],"type":"Point"}
}