{
  "type": "Feature",
  "properties": {
    "iso:country":"US",
    "sg:address":"24735 453rd Ave",
    "sg:city":"Montrose",
    "sg:phone":"+1 605 363 5157",
    "sg:postcode":"57048",
    "sg:province":"SD",
    "sg:tags":[
        "farm",
        "corn"
    ],
    "wof:name":"James R Miles",
    "wof:placetype":"venue"
},
  "geometry": {"coordinates":[-97.149181,43.799632],"type":"Point"}
}