{
  "type": "Feature",
  "properties": {
    "iso:country":"US",
    "sg:address":"39393 149th St",
    "sg:city":"Mellette",
    "sg:classifiers":[
        {
            "category":"Freight",
            "type":"Transportation"
        }
    ],
    "sg:phone":"+1 605 887 3208",
    "sg:postcode":"57461",
    "sg:province":"SD",
    "sg:tags":[
        "operator",
        "local",
        "trucking"
    ],
    "wof:name":"Mandy Tolvstad",
    "wof:placetype":"venue"
},
  "geometry": {"coordinates":[-98.365414,45.2288],"type":"Point"}
}