{
  "type": "Feature",
  "properties": {
    "iso:country":"US",
    "sg:address":"44792 282nd St",
    "sg:city":"Hurley",
    "sg:phone":"+1 605 925 4647",
    "sg:postcode":"57036",
    "sg:province":"SD",
    "sg:tags":[
        "farm",
        "grain",
        "cash",
        "soybean"
    ],
    "wof:name":"Dennis Miller",
    "wof:placetype":"venue"
},
  "geometry": {"coordinates":[-97.24123899999999,43.299481],"type":"Point"}
}