{
  "type": "Feature",
  "properties": {
    "addr:full":"29842 437th Ave Utica SD 57067",
    "addr:housenumber":"29842",
    "addr:postcode":"57067",
    "addr:street":"437Th Ave",
    "iso:country":"US",
    "sg:address":"29842 437th Ave",
    "sg:city":"Utica",
    "sg:classifiers":[
        {
            "category":"Farming",
            "subcategory":"Livestock Farm",
            "type":"Manufacturing & Wholesale Goods"
        }
    ],
    "sg:phone":"+1 605 364 7457",
    "sg:postcode":"57067",
    "sg:province":"SD",
    "sg:tags":[
        "feedlot",
        "corn",
        "soybean",
        "beef",
        "cattle"
    ],
    "wof:name":"Alan Schenkel",
    "wof:placetype":"venue"
},
  "geometry": {"coordinates":[-97.458052,43.058479],"type":"Point"}
}