{
  "type": "Feature",
  "properties": {
    "iso:country":"US",
    "sg:address":"4215 Fairway Hills Dr",
    "sg:city":"Rapid City",
    "sg:classifiers":[
        {
            "category":"Real Estate",
            "subcategory":"Real Estate Operator",
            "type":"Services"
        }
    ],
    "sg:phone":"+1 605 343 0541",
    "sg:postcode":"57702",
    "sg:province":"SD",
    "sg:tags":[
        "building",
        "nonresidential"
    ],
    "wof:name":"Parker Properties LLC",
    "wof:placetype":"venue"
},
  "geometry": {"coordinates":[-103.265559,44.044201],"type":"Point"}
}