{
  "type": "Feature",
  "properties": {
    "addr:full":"20293 480th Ave White SD 57276",
    "addr:housenumber":"20293",
    "addr:postcode":"57276",
    "addr:street":"480Th Ave",
    "iso:country":"US",
    "sg:address":"20293 480th Ave",
    "sg:city":"White",
    "sg:phone":"+1 605 629 3181",
    "sg:postcode":"57276",
    "sg:province":"SD",
    "sg:tags":[
        "farm"
    ],
    "wof:name":"Mt Farms",
    "wof:placetype":"venue"
},
  "geometry": {"coordinates":[-96.606146,44.442336],"type":"Point"}
}