{
  "type": "Feature",
  "properties": {
    "addr:full":"11422 416th Ave Amherst SD 57421",
    "addr:housenumber":"11422",
    "addr:postcode":"57421",
    "addr:street":"416Th Ave",
    "iso:country":"US",
    "sg:address":"11422 416th Ave",
    "sg:city":"Amherst",
    "sg:phone":"+1 605 448 2553",
    "sg:postcode":"57421",
    "sg:province":"SD",
    "sg:tags":[
        "wheat",
        "beef",
        "farm",
        "corn",
        "soybean",
        "cattle"
    ],
    "wof:name":"Vietor Brothers Farms LLC",
    "wof:placetype":"venue"
},
  "geometry": {"coordinates":[-97.896311,45.717143],"type":"Point"}
}