{
  "type": "Feature",
  "properties": {
    "addr:full":"304 S Splitrock Blvd Brandon SD 57005",
    "addr:housenumber":"304",
    "addr:postcode":"57005",
    "addr:street":"S Splitrock Blvd",
    "iso:country":"US",
    "sg:address":"304 S Splitrock Blvd",
    "sg:city":"Brandon",
    "sg:classifiers":[
        {
            "category":"Communications",
            "subcategory":"Film & Video Production",
            "type":"Services"
        }
    ],
    "sg:phone":"+1 605 582 8366",
    "sg:postcode":"57005",
    "sg:province":"SD",
    "sg:tags":[
        "taping"
    ],
    "wof:name":"Family Focus Productions",
    "wof:placetype":"venue"
},
  "geometry": {"coordinates":[-96.572236,43.592066],"type":"Point"}
}