{
  "type": "Feature",
  "properties": {
    "iso:country":"US",
    "sg:address":"2405 E Colorado Blvd",
    "sg:city":"Spearfish",
    "sg:classifiers":[
        {
            "category":"Restaurant",
            "type":"Food & Drink"
        }
    ],
    "sg:menulink":"http://www.allmenus.com/sd/spearfish/176775-kfc---kentucky-fried-chicken/menu/",
    "sg:phone":"+1 605 642 4044",
    "sg:postcode":"57783",
    "sg:province":"SD",
    "sg:tags":[
        "american",
        "chicken"
    ],
    "wof:name":"KFC - Kentucky Fried Chicken",
    "wof:placetype":"venue"
},
  "geometry": {"coordinates":[-103.820308,44.477188],"type":"Point"}
}