{
  "type": "Feature",
  "properties": {
    "iso:country":"US",
    "sg:address":"3010 W 10th St",
    "sg:city":"Sioux Falls",
    "sg:classifiers":[
        {
            "category":"Manufacturing",
            "subcategory":"Signs",
            "type":"Manufacturing & Wholesale Goods"
        }
    ],
    "sg:phone":"+1 605 336 3563",
    "sg:postcode":"57104",
    "sg:province":"SD",
    "sg:tags":[
        "repair",
        "mfg",
        "neon",
        "plastic"
    ],
    "sg:website":"www.prideneon.com",
    "wof:name":"Pride Neon Inc",
    "wof:placetype":"venue"
},
  "geometry": {"coordinates":[-96.765877,43.546015],"type":"Point"}
}