{
  "type": "Feature",
  "properties": {
    "iso:country":"US",
    "sg:address":"3825 Odde Dr",
    "sg:city":"Rapid City",
    "sg:classifiers":[
        {
            "category":"Banks & Credit Unions",
            "subcategory":"Financial Services",
            "type":"Services"
        }
    ],
    "sg:phone":"+1 605 721 3236",
    "sg:postcode":"57701",
    "sg:province":"SD",
    "sg:tags":[
        "investor"
    ],
    "wof:name":"Keyser Investment Co",
    "wof:placetype":"venue"
},
  "geometry": {"coordinates":[-103.203329,44.047277],"type":"Point"}
}