{
  "type": "Feature",
  "properties": {
    "addr:full":"41033 312th St Springfield SD 57062",
    "addr:housenumber":"41033",
    "addr:postcode":"57062",
    "addr:street":"312Th St",
    "iso:country":"US",
    "sg:address":"41033 312th St",
    "sg:city":"Springfield",
    "sg:phone":"+1 605 369 2399",
    "sg:postcode":"57062",
    "sg:province":"SD",
    "sg:tags":[
        "beef",
        "farm",
        "corn",
        "soybean",
        "cattle",
        "feedlot"
    ],
    "wof:name":"Charles Thomas",
    "wof:placetype":"venue"
},
  "geometry": {"coordinates":[-97.987441,42.865338],"type":"Point"}
}