{
  "type": "Feature",
  "properties": {
    "addr:full":"101 S Plum St Vermillion SD 57069",
    "addr:housenumber":"101",
    "addr:postcode":"57069",
    "addr:street":"S Plum St",
    "iso:country":"US",
    "sg:address":"101 S Plum St",
    "sg:city":"Vermillion",
    "sg:classifiers":[
        {
            "category":"Health Services",
            "subcategory":"Doctor",
            "type":"Services"
        }
    ],
    "sg:phone":"+1 605 624 8643",
    "sg:postcode":"57069",
    "sg:province":"SD",
    "sg:tags":[
        "clinic"
    ],
    "sg:website":"www.yanktonmedicalclinic.com",
    "wof:name":"Vermillion Medical Clinic",
    "wof:placetype":"venue"
},
  "geometry": {"coordinates":[-96.92000899999999,42.778491],"type":"Point"}
}