{
  "type": "Feature",
  "properties": {
    "iso:country":"US",
    "sg:address":"605 Herrick St",
    "sg:city":"Gary",
    "sg:phone":"+1 605 272 5597",
    "sg:postcode":"57237",
    "sg:province":"SD",
    "sg:tags":[
        "farm",
        "corn",
        "wheat",
        "soybean"
    ],
    "wof:name":"Jean Hinsvark",
    "wof:placetype":"venue"
},
  "geometry": {"coordinates":[-96.460049,44.787456],"type":"Point"}
}