{
  "type": "Feature",
  "properties": {
    "iso:country":"US",
    "sg:address":"47264 152nd St",
    "sg:city":"Twin Brooks",
    "sg:classifiers":[
        {
            "category":"Building & Trades",
            "subcategory":"Construction",
            "type":"Services"
        }
    ],
    "sg:phone":"+1 605 432 4140",
    "sg:postcode":"57269",
    "sg:province":"SD",
    "sg:tags":[
        "contractor"
    ],
    "wof:name":"M E Bates Construction",
    "wof:placetype":"venue"
},
  "geometry": {"coordinates":[-96.754107,45.178684],"type":"Point"}
}