{
  "type": "Feature",
  "properties": {
    "iso:country":"US",
    "sg:address":"1008 Church Ave",
    "sg:city":"Gregory",
    "sg:classifiers":[
        {
            "category":"Organizations",
            "subcategory":"Religious Organization",
            "type":"Services"
        }
    ],
    "sg:phone":"+1 605 835 9373",
    "sg:postcode":"57533",
    "sg:province":"SD",
    "wof:name":"Assembly of God",
    "wof:placetype":"venue"
},
  "geometry": {"coordinates":[-99.432355,43.237663],"type":"Point"}
}