{
  "type": "Feature",
  "properties": {
    "iso:country":"US",
    "sg:address":"29966 423rd Ave",
    "sg:city":"Scotland",
    "sg:classifiers":[
        {
            "category":"Farming",
            "subcategory":"Farm",
            "type":"Manufacturing & Wholesale Goods"
        }
    ],
    "sg:phone":"+1 605 583 4468",
    "sg:postcode":"57059",
    "sg:province":"SD",
    "sg:tags":[
        "feedlot",
        "cattle",
        "crop",
        "beef",
        "general"
    ],
    "wof:name":"Frank J Kloucek",
    "wof:placetype":"venue"
},
  "geometry": {"coordinates":[-97.734138,43.040207],"type":"Point"}
}