{
  "type": "Feature",
  "properties": {
    "iso:country":"US",
    "sg:address":"1713 6th St",
    "sg:city":"Brookings",
    "sg:classifiers":[
        {
            "category":"Personal",
            "subcategory":"Tanning Parlor",
            "type":"Services"
        },
        {
            "category":"Personal",
            "type":"Services"
        }
    ],
    "sg:phone":"+1 605 692 8826",
    "sg:postcode":"57006",
    "sg:province":"SD",
    "sg:tags":[
        "salon"
    ],
    "wof:name":"Year Round Brown Inc",
    "wof:placetype":"venue"
},
  "geometry": {"coordinates":[-96.776291,44.31146],"type":"Point"}
}