{
  "type": "Feature",
  "properties": {
    "addr:full":"701 E 8th St Sioux Falls SD 57103",
    "addr:housenumber":"701",
    "addr:postcode":"57103",
    "addr:street":"E 8Th St",
    "iso:country":"US",
    "sg:address":"701 E 8th St",
    "sg:city":"Sioux Falls",
    "sg:classifiers":[
        {
            "category":"Social Services",
            "type":"Services"
        }
    ],
    "sg:phone":"+1 605 334 6732",
    "sg:postcode":"57103",
    "sg:province":"SD",
    "sg:tags":[
        "used",
        "merchandise"
    ],
    "wof:name":"Union Gospel Mission",
    "wof:placetype":"venue"
},
  "geometry": {"coordinates":[-96.71701400000001,43.548632],"type":"Point"}
}