{
  "type": "Feature",
  "properties": {
    "iso:country":"US",
    "sg:address":"112 Main St",
    "sg:city":"Tulare",
    "sg:classifiers":[
        {
            "category":"Government",
            "subcategory":"Office",
            "type":"Public Place"
        }
    ],
    "sg:phone":"+1 605 596 4105",
    "sg:postcode":"57476",
    "sg:province":"SD",
    "sg:tags":[
        "village"
    ],
    "wof:name":"Community Hall",
    "wof:placetype":"venue"
},
  "geometry": {"coordinates":[-98.506854,44.738102],"type":"Point"}
}