{
  "type": "Feature",
  "properties": {
    "addr:full":"3932 S Western Ave Sioux Falls SD 57105",
    "addr:housenumber":"3932",
    "addr:postcode":"57105",
    "addr:street":"S Western Ave",
    "iso:country":"US",
    "sg:address":"3932 S Western Ave",
    "sg:city":"Sioux Falls",
    "sg:classifiers":[
        {
            "category":"Education",
            "subcategory":"College",
            "type":"Public Place"
        }
    ],
    "sg:phone":"+1 605 322 8090",
    "sg:postcode":"57105",
    "sg:province":"SD",
    "sg:tags":[
        "academic",
        "school"
    ],
    "wof:name":"Mt Marty Clg Nurse Anesthesia",
    "wof:placetype":"venue"
},
  "geometry": {"coordinates":[-96.751001,43.509915],"type":"Point"}
}