{
  "type": "Feature",
  "properties": {
    "iso:country":"US",
    "sg:address":"1123 E 3rd St",
    "sg:city":"Miller",
    "sg:classifiers":[
        {
            "category":"Organizations",
            "subcategory":"Religious Organization",
            "type":"Services"
        }
    ],
    "sg:phone":"+1 605 853 2558",
    "sg:postcode":"57362",
    "sg:province":"SD",
    "sg:tags":[
        "church"
    ],
    "wof:name":"New Beginnings Worship Ctr",
    "wof:placetype":"venue"
},
  "geometry": {"coordinates":[-98.971907,44.518238],"type":"Point"}
}