{
  "type": "Feature",
  "properties": {
    "addr:full":"500 Main St Toronto SD 57279",
    "addr:housenumber":"500",
    "addr:postcode":"57279",
    "addr:street":"Main St",
    "iso:country":"US",
    "sg:address":"500 Main St",
    "sg:city":"Toronto",
    "sg:classifiers":[
        {
            "category":"Home & Garden",
            "subcategory":"Building Materials",
            "type":"Retail Goods"
        }
    ],
    "sg:phone":"+1 605 794 4020",
    "sg:postcode":"57279",
    "sg:province":"SD",
    "sg:tags":[
        "glass",
        "window",
        "plate"
    ],
    "wof:name":"Toronto Auto & Glass",
    "wof:placetype":"venue"
},
  "geometry": {"coordinates":[-96.860753,45.409703],"type":"Point"}
}