{
  "type": "Feature",
  "properties": {
    "iso:country":"US",
    "sg:address":"11 Alcoma Dr",
    "sg:city":"North Sioux City",
    "sg:classifiers":[
        {
            "category":"Social Services",
            "subcategory":"Child Care",
            "type":"Services"
        }
    ],
    "sg:phone":"+1 605 232 6146",
    "sg:postcode":"57049",
    "sg:province":"SD",
    "wof:name":"Hands On Learning Preschool",
    "wof:placetype":"venue"
},
  "geometry": {"coordinates":[-96.501953,42.540327],"type":"Point"}
}