{
  "type": "Feature",
  "properties": {
    "addr:full":"318 3rd Ave Hoven SD 57450",
    "addr:housenumber":"318",
    "addr:postcode":"57450",
    "addr:street":"3Rd Ave",
    "iso:country":"US",
    "sg:address":"318 3rd Ave",
    "sg:city":"Hoven",
    "sg:classifiers":[
        {
            "category":"Health Services",
            "subcategory":"Nursing And Care Facility",
            "type":"Services"
        }
    ],
    "sg:phone":"+1 605 948 2394",
    "sg:postcode":"57450",
    "sg:province":"SD",
    "sg:tags":[
        "home",
        "convalescent"
    ],
    "wof:name":"Community Health Nursing",
    "wof:placetype":"venue"
},
  "geometry": {"coordinates":[-99.781267,45.242259],"type":"Point"}
}