{
  "type": "Feature",
  "properties": {
    "addr:full":"14511 395th Ave Stratford SD 57474",
    "addr:housenumber":"14511",
    "addr:postcode":"57474",
    "addr:street":"395Th Ave",
    "iso:country":"US",
    "sg:address":"14511 395th Ave",
    "sg:city":"Stratford",
    "sg:classifiers":[
        {
            "category":"Building & Trades",
            "subcategory":"Pest Control",
            "type":"Services"
        }
    ],
    "sg:phone":"+1 605 395 6665",
    "sg:postcode":"57474",
    "sg:province":"SD",
    "sg:tags":[
        "spraying"
    ],
    "wof:name":"Husky Spraying Svc",
    "wof:placetype":"venue"
},
  "geometry": {"coordinates":[-98.33023900000001,45.283507],"type":"Point"}
}