{
  "type": "Feature",
  "properties": {
    "iso:country":"US",
    "sg:address":"222 Iowa Ave N",
    "sg:city":"Highmore",
    "sg:classifiers":[
        {
            "category":"Retail",
            "subcategory":"Veterinary Services",
            "type":"Services"
        }
    ],
    "sg:phone":"+1 605 852 2661",
    "sg:postcode":"57345",
    "sg:province":"SD",
    "sg:tags":[
        "veterinarian"
    ],
    "wof:name":"Stagg Veterinary Clinic",
    "wof:placetype":"venue"
},
  "geometry": {"coordinates":[-99.44169100000001,44.523614],"type":"Point"}
}