{
  "type": "Feature",
  "properties": {
    "addr:full":"26418 462nd Ave Hartford SD 57033",
    "addr:housenumber":"26418",
    "addr:postcode":"57033",
    "addr:street":"462Nd Ave",
    "iso:country":"US",
    "sg:address":"26418 462nd Ave",
    "sg:city":"Hartford",
    "sg:classifiers":[
        {
            "category":"Farming",
            "subcategory":"Farm",
            "type":"Manufacturing & Wholesale Goods"
        }
    ],
    "sg:phone":"+1 605 526 7221",
    "sg:postcode":"57033",
    "sg:province":"SD",
    "wof:name":"William Marketon",
    "wof:placetype":"venue"
},
  "geometry": {"coordinates":[-96.97013200000001,43.554066],"type":"Point"}
}