{
  "type": "Feature",
  "properties": {
    "iso:country":"US",
    "sg:address":"3642 S Southeastern Ave",
    "sg:city":"Sioux Falls",
    "sg:classifiers":[
        {
            "category":"Retail",
            "subcategory":"Veterinary Services",
            "type":"Services"
        }
    ],
    "sg:phone":"+1 605 371 3791",
    "sg:postcode":"57103",
    "sg:province":"SD",
    "sg:tags":[
        "hospital"
    ],
    "wof:name":"Dale Animal Hospital",
    "wof:placetype":"venue"
},
  "geometry": {"coordinates":[-96.689104,43.511295],"type":"Point"}
}