{
  "type": "Feature",
  "properties": {
    "iso:country":"US",
    "sg:address":"513 Spearfish Canyon Hwy",
    "sg:city":"Spearfish",
    "sg:classifiers":[
        {
            "category":"Shopping",
            "subcategory":"Used Merchandise",
            "type":"Retail Goods"
        }
    ],
    "sg:phone":"+1 605 642 7436",
    "sg:postcode":"57783",
    "sg:province":"SD",
    "sg:tags":[
        "shop",
        "consignment"
    ],
    "wof:name":"Kiefer Consignment",
    "wof:placetype":"venue"
},
  "geometry": {"coordinates":[-103.849247,44.477889],"type":"Point"}
}