{
  "type": "Feature",
  "properties": {
    "addr:full":"1441 E Hwy 44 Rapid City SD 57703",
    "addr:housenumber":"1441",
    "addr:postcode":"57703",
    "addr:street":"E Hwy 44",
    "iso:country":"US",
    "sg:address":"1441 E Hwy 44",
    "sg:city":"Rapid City",
    "sg:classifiers":[
        {
            "category":"Autos & Motor Vehicles",
            "subcategory":"Automobile Sales",
            "type":"Retail Goods"
        }
    ],
    "sg:phone":"+1 605 388 8243",
    "sg:postcode":"57703",
    "sg:province":"SD",
    "sg:tags":[
        "used"
    ],
    "wof:name":"Dakota Discount Auto",
    "wof:placetype":"venue"
},
  "geometry": {"coordinates":[-103.18681100000001,44.079361],"type":"Point"}
}