{
  "type": "Feature",
  "properties": {
    "iso:country":"US",
    "sg:address":"41222 274th St",
    "sg:city":"Parkston",
    "sg:classifiers":[
        {
            "category":"Farming",
            "subcategory":"Livestock Farm",
            "type":"Manufacturing & Wholesale Goods"
        }
    ],
    "sg:phone":"+1 605 928 7973",
    "sg:postcode":"57366",
    "sg:province":"SD",
    "sg:tags":[
        "hog",
        "beef",
        "far",
        "corn",
        "cattle",
        "or",
        "feedlot"
    ],
    "wof:name":"Thomas Kummer",
    "wof:placetype":"venue"
},
  "geometry": {"coordinates":[-97.944353,43.413247],"type":"Point"}
}