{
  "type": "Feature",
  "properties": {
    "iso:country":"US",
    "sg:address":"1300 Junction Ave",
    "sg:city":"Sturgis",
    "sg:classifiers":[
        {
            "category":"Health Services",
            "subcategory":"Doctor",
            "type":"Services"
        }
    ],
    "sg:phone":"+1 605 347 5103",
    "sg:postcode":"57785",
    "sg:province":"SD",
    "sg:tags":[
        "dentist"
    ],
    "wof:name":"Rick G Schmid DDS",
    "wof:placetype":"venue"
},
  "geometry": {"coordinates":[-103.50912,44.4117],"type":"Point"}
}