{
  "type": "Feature",
  "properties": {
    "iso:country":"US",
    "sg:address":"29238 444th Ave",
    "sg:city":"Irene",
    "sg:classifiers":[
        {
            "category":"Building & Trades",
            "subcategory":"Construction",
            "type":"Services"
        }
    ],
    "sg:phone":"+1 605 327 3445",
    "sg:postcode":"57037",
    "sg:province":"SD",
    "sg:tags":[
        "siding",
        "contractor"
    ],
    "wof:name":"G & S Siding & Seamless Gutter",
    "wof:placetype":"venue"
},
  "geometry": {"coordinates":[-97.318204,43.145931],"type":"Point"}
}