{
  "type": "Feature",
  "properties": {
    "iso:country":"US",
    "sg:address":"38350 172nd St",
    "sg:city":"Redfield",
    "sg:classifiers":[
        {
            "category":"Shopping",
            "subcategory":"Bicycles & Sporting Goods",
            "type":"Retail Goods"
        }
    ],
    "sg:phone":"+1 605 472 2697",
    "sg:postcode":"57469",
    "sg:province":"SD",
    "wof:name":"Gun Clinic",
    "wof:placetype":"venue"
},
  "geometry": {"coordinates":[-98.559867,44.897981],"type":"Point"}
}