{
  "type": "Feature",
  "properties": {
    "addr:full":"405 Pine St Piedmont SD 57769",
    "addr:housenumber":"405",
    "addr:postcode":"57769",
    "addr:street":"Pine St",
    "iso:country":"US",
    "sg:address":"405 Pine St",
    "sg:city":"Piedmont",
    "sg:classifiers":[
        {
            "category":"Freight",
            "type":"Transportation"
        }
    ],
    "sg:phone":"+1 605 787 4945",
    "sg:postcode":"57769",
    "sg:province":"SD",
    "sg:tags":[
        "hauling",
        "trucking"
    ],
    "wof:name":"J & S Trucking",
    "wof:placetype":"venue"
},
  "geometry": {"coordinates":[-103.389883,44.228781],"type":"Point"}
}