{
  "type": "Feature",
  "properties": {
    "iso:country":"US",
    "sg:address":"1301 S Summit Ave",
    "sg:city":"Sioux Falls",
    "sg:classifiers":[
        {
            "category":"Building & Trades",
            "subcategory":"Construction",
            "type":"Services"
        }
    ],
    "sg:phone":"+1 605 336 8621",
    "sg:postcode":"57105",
    "sg:province":"SD",
    "sg:tags":[
        "residential",
        "builder",
        "home"
    ],
    "wof:name":"Schmidt Construction Co Inc",
    "wof:placetype":"venue"
},
  "geometry": {"coordinates":[-96.73627500000001,43.533031],"type":"Point"}
}