{
  "type": "Feature",
  "properties": {
    "iso:country":"US",
    "sg:address":"751 Mountain View Rd",
    "sg:city":"Rapid City",
    "sg:classifiers":[
        {
            "category":"Food & Beverages",
            "subcategory":"Groceries & Convenience Stores",
            "type":"Retail Goods"
        },
        {
            "category":"Wholesale",
            "subcategory":"Groceries",
            "type":"Manufacturing & Wholesale Goods"
        }
    ],
    "sg:phone":"+1 605 399 1377",
    "sg:postcode":"57702",
    "sg:province":"SD",
    "sg:tags":[
        "grocer",
        "merchandise",
        "general"
    ],
    "wof:name":"Family Thrift Center",
    "wof:placetype":"venue"
},
  "geometry": {"coordinates":[-103.252105,44.078904],"type":"Point"}
}