{
  "type": "Feature",
  "properties": {
    "iso:country":"US",
    "sg:address":"780 22nd Ave S",
    "sg:city":"Brookings",
    "sg:classifiers":[
        {
            "category":"Professional",
            "subcategory":"Business Services",
            "type":"Services"
        }
    ],
    "sg:phone":"+1 605 696 2350",
    "sg:postcode":"57006",
    "sg:province":"SD",
    "sg:tags":[
        "credit",
        "short"
    ],
    "wof:name":"Midwest Card Services Inc",
    "wof:placetype":"venue"
},
  "geometry": {"coordinates":[-96.768379,44.297121],"type":"Point"}
}