{
  "type": "Feature",
  "properties": {
    "addr:full":"47818 Main St White SD 57276",
    "addr:housenumber":"47818",
    "addr:postcode":"57276",
    "addr:street":"Main St",
    "iso:country":"US",
    "sg:address":"47818 Main St",
    "sg:city":"White",
    "sg:classifiers":[
        {
            "category":"Bars & Pubs",
            "type":"Food & Drink"
        }
    ],
    "sg:phone":"+1 605 693 4065",
    "sg:postcode":"57276",
    "sg:province":"SD",
    "sg:tags":[
        "drinking"
    ],
    "wof:name":"Bushnell Garage",
    "wof:placetype":"venue"
},
  "geometry": {"coordinates":[-96.645672,44.328726],"type":"Point"}
}