{
  "type": "Feature",
  "properties": {
    "iso:country":"US",
    "sg:address":"3509 E Anoka Cir",
    "sg:city":"Sioux Falls",
    "sg:classifiers":[
        {
            "category":"Professional",
            "subcategory":"Engineering",
            "type":"Services"
        }
    ],
    "sg:phone":"+1 605 338 1040",
    "sg:postcode":"57103",
    "sg:province":"SD",
    "wof:name":"Cavanaugh & Associates",
    "wof:placetype":"venue"
},
  "geometry": {"coordinates":[-96.681967,43.520879],"type":"Point"}
}