{
  "type": "Feature",
  "properties": {
    "iso:country":"US",
    "sg:address":"900 W Cherokee St",
    "sg:city":"Sioux Falls",
    "sg:classifiers":[
        {
            "category":"Professional",
            "subcategory":"Business Services",
            "type":"Services"
        }
    ],
    "sg:phone":"+1 605 339 3989",
    "sg:postcode":"57104",
    "sg:province":"SD",
    "wof:name":"Maitland Partners LLC",
    "wof:placetype":"venue"
},
  "geometry": {"coordinates":[-96.74251,43.567343],"type":"Point"}
}