{
  "type": "Feature",
  "properties": {
    "addr:full":"24570 473rd Ave Dell Rapids SD 57022",
    "addr:housenumber":"24570",
    "addr:postcode":"57022",
    "addr:street":"473Rd Ave",
    "iso:country":"US",
    "sg:address":"24570 473rd Ave",
    "sg:city":"Dell Rapids",
    "sg:classifiers":[
        {
            "category":"Farming",
            "subcategory":"Farm",
            "type":"Manufacturing & Wholesale Goods"
        }
    ],
    "sg:phone":"+1 605 428 3719",
    "sg:postcode":"57022",
    "sg:province":"SD",
    "sg:tags":[
        "crop",
        "general"
    ],
    "wof:name":"William J Klein",
    "wof:placetype":"venue"
},
  "geometry": {"coordinates":[-96.748368,43.824451],"type":"Point"}
}