{
  "type": "Feature",
  "properties": {
    "iso:country":"US",
    "sg:address":"32260 102nd St",
    "sg:city":"Eureka",
    "sg:classifiers":[
        {
            "category":"Farming",
            "subcategory":"Livestock Farm",
            "type":"Manufacturing & Wholesale Goods"
        }
    ],
    "sg:phone":"+1 605 437 2374",
    "sg:postcode":"57437",
    "sg:province":"SD",
    "sg:tags":[
        "wheat",
        "beef",
        "cash",
        "grain",
        "cattle",
        "feedlot"
    ],
    "wof:name":"Wayne Lutz",
    "wof:placetype":"venue"
},
  "geometry": {"coordinates":[-99.720338,45.912293],"type":"Point"}
}