{
  "type": "Feature",
  "properties": {
    "addr:full":"524 B Ave Pollock SD 57648",
    "addr:housenumber":"524",
    "addr:postcode":"57648",
    "addr:street":"B Ave",
    "iso:country":"US",
    "sg:address":"524 B Ave",
    "sg:city":"Pollock",
    "sg:classifiers":[
        {
            "category":"Autos & Motor Vehicles",
            "subcategory":"Fuel & Gas Station",
            "type":"Retail Goods"
        }
    ],
    "sg:phone":"+1 605 889 2440",
    "sg:postcode":"57648",
    "sg:province":"SD",
    "sg:tags":[
        "oil"
    ],
    "wof:name":"Shell",
    "wof:placetype":"venue"
},
  "geometry": {"coordinates":[-100.288228,45.900492],"type":"Point"}
}