{
  "type": "Feature",
  "properties": {
    "addr:full":"221 E 11th St Sioux Falls SD 57104",
    "addr:housenumber":"221",
    "addr:postcode":"57104",
    "addr:street":"E 11Th St",
    "iso:country":"US",
    "sg:address":"221 E 11th St",
    "sg:city":"Sioux Falls",
    "sg:classifiers":[
        {
            "category":"Banks & Credit Unions",
            "subcategory":"Investment Brokerage",
            "type":"Services"
        }
    ],
    "sg:phone":"+1 605 221 0924",
    "sg:postcode":"57104",
    "sg:province":"SD",
    "sg:tags":[
        "advisory",
        "financial"
    ],
    "wof:name":"Anderson Financial Group",
    "wof:placetype":"venue"
},
  "geometry": {"coordinates":[-96.724037,43.544609],"type":"Point"}
}