{
  "type": "Feature",
  "properties": {
    "iso:country":"US",
    "sg:address":"101 Main St",
    "sg:city":"Martin",
    "sg:classifiers":[
        {
            "category":"Education",
            "subcategory":"School",
            "type":"Public Place"
        }
    ],
    "sg:phone":"+1 605 685 6330",
    "sg:postcode":"57551",
    "sg:province":"SD",
    "wof:name":"Bennett County Jr-Sr High Schl",
    "wof:placetype":"venue"
},
  "geometry": {"coordinates":[-101.733459,43.175108],"type":"Point"}
}