{
  "type": "Feature",
  "properties": {
    "iso:country":"US",
    "sg:address":"17 New York St",
    "sg:city":"Rapid City",
    "sg:classifiers":[
        {
            "category":"Building & Trades",
            "subcategory":"Equipment Rental",
            "type":"Services"
        }
    ],
    "sg:phone":"+1 605 737 1111",
    "sg:postcode":"57701",
    "sg:province":"SD",
    "sg:tags":[
        "appliance"
    ],
    "wof:name":"Aarons Sales & Lease Ownership",
    "wof:placetype":"venue"
},
  "geometry": {"coordinates":[-103.216476,44.084916],"type":"Point"}
}