{
  "type": "Feature",
  "properties": {
    "iso:country":"US",
    "sg:address":"21859 441st Ave",
    "sg:city":"Oldham",
    "sg:phone":"+1 605 482 8538",
    "sg:postcode":"57051",
    "sg:province":"SD",
    "sg:tags":[
        "farm",
        "corn",
        "soybean"
    ],
    "wof:name":"Reed Farm Inc",
    "wof:placetype":"venue"
},
  "geometry": {"coordinates":[-97.391453,44.215225],"type":"Point"}
}