{
  "type": "Feature",
  "properties": {
    "iso:country":"US",
    "sg:address":"202 Merrill Ave W",
    "sg:city":"Roscoe",
    "sg:classifiers":[
        {
            "category":"Health Services",
            "subcategory":"Doctor",
            "type":"Services"
        }
    ],
    "sg:phone":"+1 605 287 4610",
    "sg:postcode":"57471",
    "sg:province":"SD",
    "sg:tags":[
        "clinic"
    ],
    "wof:name":"Roscoe Clinic",
    "wof:placetype":"venue"
},
  "geometry": {"coordinates":[-99.33705999999999,45.448447],"type":"Point"}
}