{
  "type": "Feature",
  "properties": {
    "iso:country":"US",
    "sg:address":"1417 S Minnesota Ave",
    "sg:city":"Sioux Falls",
    "sg:classifiers":[
        {
            "category":"Health Services",
            "subcategory":"Doctor",
            "type":"Services"
        }
    ],
    "sg:phone":"+1 605 336 0515",
    "sg:postcode":"57105",
    "sg:province":"SD",
    "sg:tags":[
        "physician",
        "surgeon"
    ],
    "sg:website":"www.medx-ray.com",
    "wof:name":"Medical X-Ray Ctr",
    "wof:placetype":"venue"
},
  "geometry": {"coordinates":[-96.73135000000001,43.532296],"type":"Point"}
}