{
  "type": "Feature",
  "properties": {
    "iso:country":"US",
    "sg:address":"1415 E Fairmont Blvd",
    "sg:city":"Rapid City",
    "sg:classifiers":[
        {
            "category":"Autos & Motor Vehicles",
            "subcategory":"Motorcycle Sales",
            "type":"Retail Goods"
        }
    ],
    "sg:phone":"+1 605 348 5051",
    "sg:postcode":"57701",
    "sg:province":"SD",
    "wof:name":"Dakota Trike Shop",
    "wof:placetype":"venue"
},
  "geometry": {"coordinates":[-103.193121,44.052883],"type":"Point"}
}