{
  "type": "Feature",
  "properties": {
    "iso:country":"US",
    "sg:address":"2843 Samco Rd",
    "sg:city":"Rapid City",
    "sg:classifiers":[
        {
            "category":"Home & Garden",
            "subcategory":"Building Materials",
            "type":"Retail Goods"
        },
        {
            "category":"Retail",
            "subcategory":"Auto Repair",
            "type":"Services"
        }
    ],
    "sg:phone":"+1 605 341 3615",
    "sg:postcode":"57702",
    "sg:province":"SD",
    "sg:tags":[
        "glass",
        "window",
        "plate",
        "replacement"
    ],
    "wof:name":"Stretch's Glass & Custom Parts",
    "wof:placetype":"venue"
},
  "geometry": {"coordinates":[-103.265819,44.097817],"type":"Point"}
}