{
  "type": "Feature",
  "properties": {
    "iso:country":"US",
    "sg:address":"100 E Kemp Ave",
    "sg:city":"Watertown",
    "sg:classifiers":[
        {
            "category":"Shopping",
            "subcategory":"Books",
            "type":"Retail Goods"
        }
    ],
    "sg:phone":"+1 605 886 3645",
    "sg:postcode":"57201",
    "sg:province":"SD",
    "sg:tags":[
        "comic"
    ],
    "wof:name":"Card & Comic Empiric",
    "wof:placetype":"venue"
},
  "geometry": {"coordinates":[-97.11287799999999,44.900115],"type":"Point"}
}