{
  "type": "Feature",
  "properties": {
    "iso:country":"US",
    "sg:address":"21737 472nd Ave",
    "sg:city":"Brookings",
    "sg:classifiers":[
        {
            "category":"Building & Trades",
            "subcategory":"Cleaning & Sanitation",
            "type":"Services"
        }
    ],
    "sg:phone":"+1 605 693 3695",
    "sg:postcode":"57006",
    "sg:province":"SD",
    "sg:tags":[
        "janitor",
        "maintenance"
    ],
    "wof:name":"Top Notch Cleaning Service",
    "wof:placetype":"venue"
},
  "geometry": {"coordinates":[-96.76763800000001,44.234312],"type":"Point"}
}