{
  "type": "Feature",
  "properties": {
    "iso:country":"US",
    "sg:address":"1021 Halley Ave",
    "sg:city":"Rapid City",
    "sg:classifiers":[
        {
            "category":"Building & Trades",
            "subcategory":"Landscaping Services",
            "type":"Services"
        }
    ],
    "sg:phone":"+1 605 348 0634",
    "sg:postcode":"57701",
    "sg:province":"SD",
    "sg:tags":[
        "lawn",
        "maintenance",
        "grounds"
    ],
    "wof:name":"Sprinklers Cutting Edge Lawn",
    "wof:placetype":"venue"
},
  "geometry": {"coordinates":[-103.214677,44.096651],"type":"Point"}
}