{
  "type": "Feature",
  "properties": {
    "addr:full":"925 N Savannah Dr Sioux Falls SD 57103",
    "addr:housenumber":"925",
    "addr:postcode":"57103",
    "addr:street":"N Savannah Dr",
    "iso:country":"US",
    "sg:address":"925 N Savannah Dr",
    "sg:city":"Sioux Falls",
    "sg:classifiers":[
        {
            "category":"Real Estate",
            "subcategory":"Real Estate Agent",
            "type":"Services"
        },
        {
            "category":"Professional",
            "subcategory":"Business Services",
            "type":"Services"
        }
    ],
    "sg:phone":"+1 605 335 6889",
    "sg:postcode":"57103",
    "sg:province":"SD",
    "sg:tags":[
        "inspection"
    ],
    "wof:name":"Thor Home Inspection Service",
    "wof:placetype":"venue"
},
  "geometry": {"coordinates":[-96.679986,43.558675],"type":"Point"}
}