{
  "type": "Feature",
  "properties": {
    "iso:country":"US",
    "sg:address":"1024 S Lawson St",
    "sg:city":"Aberdeen",
    "sg:classifiers":[
        {
            "category":"Social Services",
            "type":"Services"
        }
    ],
    "sg:phone":"+1 605 225 9664",
    "sg:postcode":"57401",
    "sg:province":"SD",
    "sg:tags":[
        "organization",
        "welfare"
    ],
    "wof:name":"American Red Cross",
    "wof:placetype":"venue"
},
  "geometry": {"coordinates":[-98.464787,45.454385],"type":"Point"}
}