{
  "type": "Feature",
  "properties": {
    "addr:full":"3418 S Hwy 79 Rapid City SD 57701",
    "addr:housenumber":"3418",
    "addr:postcode":"57701",
    "addr:street":"S Hwy 79",
    "iso:country":"US",
    "sg:address":"3418 S Hwy 79",
    "sg:city":"Rapid City",
    "sg:classifiers":[
        {
            "category":"Freight",
            "type":"Transportation"
        }
    ],
    "sg:phone":"+1 605 399 1913",
    "sg:postcode":"57701",
    "sg:province":"SD",
    "sg:tags":[
        "mover"
    ],
    "wof:name":"B N Transfer & Storage",
    "wof:placetype":"venue"
},
  "geometry": {"coordinates":[-103.19168000000001,44.050983],"type":"Point"}
}