{
  "type": "Feature",
  "properties": {
    "iso:country":"US",
    "sg:address":"1008 N Sycamore Ave",
    "sg:city":"Sioux Falls",
    "sg:classifiers":[
        {
            "category":"Social Services",
            "subcategory":"Child Care",
            "type":"Services"
        }
    ],
    "sg:phone":"+1 605 330 9876",
    "sg:postcode":"57110",
    "sg:province":"SD",
    "sg:tags":[
        "day"
    ],
    "wof:name":"Kids Corner Preschool",
    "wof:placetype":"venue"
},
  "geometry": {"coordinates":[-96.67148400000001,43.559996],"type":"Point"}
}