{
  "type": "Feature",
  "properties": {
    "iso:country":"US",
    "sg:address":"905 State Hwy 50",
    "sg:city":"Vermillion",
    "sg:classifiers":[
        {
            "category":"Organizations",
            "subcategory":"Religious Organization",
            "type":"Services"
        }
    ],
    "sg:phone":"+1 605 624 7487",
    "sg:postcode":"57069",
    "sg:province":"SD",
    "wof:name":"Heidelberg Theological Smnry",
    "wof:placetype":"venue"
},
  "geometry": {"coordinates":[-96.941734,42.7938],"type":"Point"}
}