{
  "type": "Feature",
  "properties": {
    "iso:country":"US",
    "sg:address":"114 1st St S",
    "sg:city":"Brookings",
    "sg:classifiers":[
        {
            "category":"Building & Trades",
            "subcategory":"Construction",
            "type":"Services"
        }
    ],
    "sg:phone":"+1 605 692 2241",
    "sg:postcode":"57006",
    "sg:province":"SD",
    "sg:tags":[
        "general",
        "contractor"
    ],
    "wof:name":"Waltz Construction Inc",
    "wof:placetype":"venue"
},
  "geometry": {"coordinates":[-96.802761,44.307119],"type":"Point"}
}