{
  "type": "Feature",
  "properties": {
    "addr:full":"1411 E 10th St Sioux Falls SD 57103",
    "addr:housenumber":"1411",
    "addr:postcode":"57103",
    "addr:street":"E 10Th St",
    "iso:country":"US",
    "sg:address":"1411 E 10th St",
    "sg:city":"Sioux Falls",
    "sg:classifiers":[
        {
            "category":"Retail",
            "subcategory":"Photofinishing",
            "type":"Services"
        }
    ],
    "sg:phone":"+1 605 339 1697",
    "sg:postcode":"57103",
    "sg:province":"SD",
    "sg:tags":[
        "laboratory",
        "suppl"
    ],
    "wof:name":"Harolds Photo",
    "wof:placetype":"venue"
},
  "geometry": {"coordinates":[-96.70774,43.546598],"type":"Point"}
}