{
  "type": "Feature",
  "properties": {
    "iso:country":"US",
    "sg:address":"1161 Deadwood Ave N",
    "sg:city":"Rapid City",
    "sg:classifiers":[
        {
            "category":"Shopping",
            "subcategory":"Computers & Home Electronics",
            "type":"Retail Goods"
        }
    ],
    "sg:phone":"+1 605 348 4444",
    "sg:postcode":"57702",
    "sg:province":"SD",
    "sg:tags":[
        "equipment",
        "dealer"
    ],
    "wof:name":"P C Plus Training",
    "wof:placetype":"venue"
},
  "geometry": {"coordinates":[-103.271899,44.141797],"type":"Point"}
}