{
  "type": "Feature",
  "properties": {
    "addr:full":"304 Main St Platte SD 57369",
    "addr:housenumber":"304",
    "addr:postcode":"57369",
    "addr:street":"Main St",
    "iso:country":"US",
    "sg:address":"304 Main St",
    "sg:city":"Platte",
    "sg:classifiers":[
        {
            "category":"Restaurant",
            "type":"Food & Drink"
        }
    ],
    "sg:phone":"+1 605 337 2567",
    "sg:postcode":"57369",
    "sg:province":"SD",
    "wof:name":"Lone Tree Steakhouse",
    "wof:placetype":"venue"
},
  "geometry": {"coordinates":[-98.84483299999999,43.388128],"type":"Point"}
}