{
  "type": "Feature",
  "properties": {
    "addr:full":"621 Main St Scotland SD 57059",
    "addr:housenumber":"621",
    "addr:postcode":"57059",
    "addr:street":"Main St",
    "iso:country":"US",
    "sg:address":"621 Main St",
    "sg:city":"Scotland",
    "sg:classifiers":[
        {
            "category":"Insurance",
            "subcategory":"Insurance Agent",
            "type":"Services"
        }
    ],
    "sg:phone":"+1 605 583 4272",
    "sg:postcode":"57059",
    "sg:province":"SD",
    "wof:name":"Kronaizl Insurance",
    "wof:placetype":"venue"
},
  "geometry": {"coordinates":[-97.721425,43.1495],"type":"Point"}
}