{
  "type": "Feature",
  "properties": {
    "iso:country":"US",
    "sg:address":"158 Aberdeen Ave SE",
    "sg:city":"Huron",
    "sg:classifiers":[
        {
            "category":"Building & Trades",
            "subcategory":"Construction",
            "type":"Services"
        }
    ],
    "sg:phone":"+1 605 352 1584",
    "sg:postcode":"57350",
    "sg:province":"SD",
    "sg:tags":[
        "masonry",
        "contractor"
    ],
    "wof:name":"North Masonry",
    "wof:placetype":"venue"
},
  "geometry": {"coordinates":[-98.18777300000001,44.365041],"type":"Point"}
}