{
  "type": "Feature",
  "properties": {
    "iso:country":"US",
    "sg:address":"602 1st St",
    "sg:city":"Highmore",
    "sg:classifiers":[
        {
            "category":"Building & Trades",
            "subcategory":"Construction",
            "type":"Services"
        }
    ],
    "sg:phone":"+1 605 852 2111",
    "sg:postcode":"57345",
    "sg:province":"SD",
    "sg:tags":[
        "general",
        "contractor"
    ],
    "wof:name":"Ballew Construction",
    "wof:placetype":"venue"
},
  "geometry": {"coordinates":[-99.450042,44.520245],"type":"Point"}
}