{
  "type": "Feature",
  "properties": {
    "iso:country":"US",
    "sg:address":"1210 1st Ave NE",
    "sg:city":"Watertown",
    "sg:classifiers":[
        {
            "category":"Professional",
            "subcategory":"Business Services",
            "type":"Services"
        }
    ],
    "sg:phone":"+1 605 886 3847",
    "sg:postcode":"57201",
    "sg:province":"SD",
    "wof:name":"Bill L Wasland",
    "wof:placetype":"venue"
},
  "geometry": {"coordinates":[-97.094657,44.89772],"type":"Point"}
}