{
  "type": "Feature",
  "properties": {
    "addr:full":"151 8th St SE Huron SD 57350",
    "addr:housenumber":"151",
    "addr:postcode":"57350",
    "addr:street":"8Th St Se",
    "iso:country":"US",
    "sg:address":"151 8th St SE",
    "sg:city":"Huron",
    "sg:classifiers":[
        {
            "category":"Manufacturing",
            "subcategory":"Signs",
            "type":"Manufacturing & Wholesale Goods"
        }
    ],
    "sg:phone":"+1 605 352 0406",
    "sg:postcode":"57350",
    "sg:province":"SD",
    "sg:tags":[
        "specialty",
        "mfg"
    ],
    "wof:name":"Art & Sign",
    "wof:placetype":"venue"
},
  "geometry": {"coordinates":[-98.21164,44.357326],"type":"Point"}
}