{
  "type": "Feature",
  "properties": {
    "addr:full":"607 4th St S Alpena SD 57312",
    "addr:housenumber":"607",
    "addr:postcode":"57312",
    "addr:street":"4Th St S",
    "iso:country":"US",
    "sg:address":"607 4th St S",
    "sg:city":"Alpena",
    "sg:classifiers":[
        {
            "category":"Building & Trades",
            "subcategory":"Construction",
            "type":"Services"
        }
    ],
    "sg:phone":"+1 605 849 3389",
    "sg:postcode":"57312",
    "sg:province":"SD",
    "sg:tags":[
        "concrete",
        "contractor"
    ],
    "wof:name":"Central Concrete",
    "wof:placetype":"venue"
},
  "geometry": {"coordinates":[-98.36827599999999,44.180283],"type":"Point"}
}