{
  "type": "Feature",
  "properties": {
    "iso:country":"US",
    "sg:address":"2600 S Minnesota Ave",
    "sg:city":"Sioux Falls",
    "sg:classifiers":[
        {
            "category":"Shopping",
            "type":"Retail Goods"
        }
    ],
    "sg:phone":"+1 605 334 8655",
    "sg:postcode":"57105",
    "sg:province":"SD",
    "sg:tags":[
        "orthopedic",
        "appliance"
    ],
    "sg:website":"www.biomet.com",
    "wof:name":"Biomet",
    "wof:placetype":"venue"
},
  "geometry": {"coordinates":[-96.731251,43.520337],"type":"Point"}
}