{
  "type": "Feature",
  "properties": {
    "addr:full":"45984 282nd St Davis SD 57021",
    "addr:housenumber":"45984",
    "addr:postcode":"57021",
    "addr:street":"282Nd St",
    "iso:country":"US",
    "sg:address":"45984 282nd St",
    "sg:city":"Davis",
    "sg:classifiers":[
        {
            "category":"Farming",
            "subcategory":"Livestock Farm",
            "type":"Manufacturing & Wholesale Goods"
        }
    ],
    "sg:phone":"+1 605 238 5542",
    "sg:postcode":"57021",
    "sg:province":"SD",
    "sg:tags":[
        "beef",
        "feedlot",
        "cattle"
    ],
    "wof:name":"Brad Rops",
    "wof:placetype":"venue"
},
  "geometry": {"coordinates":[-97.00715700000001,43.301875],"type":"Point"}
}