{
  "type": "Feature",
  "properties": {
    "addr:full":"41573 121st St Langford SD 57454",
    "addr:housenumber":"41573",
    "addr:postcode":"57454",
    "addr:street":"121St St",
    "iso:country":"US",
    "sg:address":"41573 121st St",
    "sg:city":"Langford",
    "sg:classifiers":[
        {
            "category":"Farming",
            "subcategory":"Livestock Farm",
            "type":"Manufacturing & Wholesale Goods"
        }
    ],
    "sg:phone":"+1 605 493 6754",
    "sg:postcode":"57454",
    "sg:province":"SD",
    "sg:tags":[
        "beef",
        "feedlot",
        "cattle"
    ],
    "wof:name":"Robert & Arlene Stolsmark",
    "wof:placetype":"venue"
},
  "geometry": {"coordinates":[-97.90615200000001,45.631718],"type":"Point"}
}