{
  "type": "Feature",
  "properties": {
    "iso:country":"US",
    "sg:address":"82 Sherman St",
    "sg:city":"Deadwood",
    "sg:classifiers":[
        {
            "category":"Government",
            "subcategory":"Police Station",
            "type":"Public Place"
        }
    ],
    "sg:phone":"+1 605 578 2230",
    "sg:postcode":"57732",
    "sg:province":"SD",
    "sg:tags":[
        "sheriff"
    ],
    "sg:website":"www.lawrence.sd.us",
    "wof:name":"County Sheriff",
    "wof:placetype":"venue"
},
  "geometry": {"coordinates":[-103.729095,44.375881],"type":"Point"}
}