{
  "type": "Feature",
  "properties": {
    "addr:full":"2414 S Louise Ave Sioux Falls SD 57106",
    "addr:housenumber":"2414",
    "addr:postcode":"57106",
    "addr:street":"S Louise Ave",
    "iso:country":"US",
    "sg:address":"2414 S Louise Ave",
    "sg:city":"Sioux Falls",
    "sg:classifiers":[
        {
            "category":"Home & Garden",
            "subcategory":"Furniture",
            "type":"Retail Goods"
        }
    ],
    "sg:phone":"+1 605 275 4090",
    "sg:postcode":"57106",
    "sg:province":"SD",
    "sg:tags":[
        "cabinet"
    ],
    "wof:name":"Executive Kitchen & Bath",
    "wof:placetype":"venue"
},
  "geometry": {"coordinates":[-96.77102600000001,43.516673],"type":"Point"}
}