{
  "type": "Feature",
  "properties": {
    "iso:country":"US",
    "sg:address":"420 W Sioux Ave",
    "sg:city":"Pierre",
    "sg:classifiers":[
        {
            "category":"Manufacturing",
            "subcategory":"Printing",
            "type":"Manufacturing & Wholesale Goods"
        }
    ],
    "sg:phone":"+1 605 224 4851",
    "sg:postcode":"57501",
    "sg:province":"SD",
    "sg:tags":[
        "printer"
    ],
    "wof:name":"Co Op Printing & Advertising",
    "wof:placetype":"venue"
},
  "geometry": {"coordinates":[-100.358708,44.369578],"type":"Point"}
}