{
  "type": "Feature",
  "properties": {
    "addr:full":"232 S Main St Milbank SD 57252",
    "addr:housenumber":"232",
    "addr:postcode":"57252",
    "addr:street":"S Main St",
    "iso:country":"US",
    "sg:address":"232 S Main St",
    "sg:city":"Milbank",
    "sg:classifiers":[
        {
            "category":"Professional",
            "subcategory":"Lawyer & Legal Services",
            "type":"Services"
        }
    ],
    "sg:phone":"+1 605 432 5544",
    "sg:postcode":"57252",
    "sg:province":"SD",
    "sg:tags":[
        "attorney",
        "practice"
    ],
    "sg:website":"http://www.coester.com",
    "wof:name":"The Coester Law Firm",
    "wof:placetype":"venue"
},
  "geometry": {"coordinates":[-96.635862,45.220639],"type":"Point"}
}