{
  "type": "Feature",
  "properties": {
    "addr:full":"312 E State St Marion SD 57043",
    "addr:housenumber":"312",
    "addr:postcode":"57043",
    "addr:street":"E State St",
    "iso:country":"US",
    "sg:address":"312 E State St",
    "sg:city":"Marion",
    "sg:classifiers":[
        {
            "category":"Health Services",
            "subcategory":"Nursing And Care Facility",
            "type":"Services"
        }
    ],
    "sg:phone":"+1 605 648 3611",
    "sg:postcode":"57043",
    "sg:province":"SD",
    "sg:tags":[
        "skilled"
    ],
    "sg:website":"www.marionsd.org",
    "wof:name":"Tieszen Memorial Home Inc",
    "wof:placetype":"venue"
},
  "geometry": {"coordinates":[-97.258196,43.426611],"type":"Point"}
}