{
  "type": "Feature",
  "properties": {
    "addr:full":"43284 308th St Yankton SD 57078",
    "addr:housenumber":"43284",
    "addr:postcode":"57078",
    "addr:street":"308Th St",
    "iso:country":"US",
    "sg:address":"43284 308th St",
    "sg:city":"Yankton",
    "sg:classifiers":[
        {
            "category":"Manufacturing",
            "subcategory":"Tools & Machinery",
            "type":"Manufacturing & Wholesale Goods"
        }
    ],
    "sg:phone":"+1 605 665 1481",
    "sg:postcode":"57078",
    "sg:province":"SD",
    "sg:tags":[
        "die",
        "maker"
    ],
    "wof:name":"Nathan Martin",
    "wof:placetype":"venue"
},
  "geometry": {"coordinates":[-97.537299,42.923193],"type":"Point"}
}