{
  "type": "Feature",
  "properties": {
    "iso:country":"US",
    "sg:address":"140 11th St SW",
    "sg:city":"Watertown",
    "sg:classifiers":[
        {
            "category":"Shopping",
            "subcategory":"Bicycles & Sporting Goods",
            "type":"Retail Goods"
        }
    ],
    "sg:phone":"+1 605 882 4573",
    "sg:postcode":"57201",
    "sg:province":"SD",
    "sg:tags":[
        "repair"
    ],
    "wof:name":"Kahles Guns",
    "wof:placetype":"venue"
},
  "geometry": {"coordinates":[-97.132749,44.90078],"type":"Point"}
}