{
  "type": "Feature",
  "properties": {
    "addr:full":"18537 486th Ave Gary SD 57259",
    "addr:housenumber":"18537",
    "addr:postcode":"57259",
    "addr:street":"486Th Ave",
    "iso:country":"US",
    "sg:address":"18537 486th Ave",
    "sg:city":"Gary",
    "sg:classifiers":[
        {
            "category":"Professional",
            "subcategory":"Computer Services",
            "type":"Services"
        }
    ],
    "sg:phone":"+1 605 272 5817",
    "sg:postcode":"57259",
    "sg:province":"SD",
    "sg:tags":[
        "repair"
    ],
    "wof:name":"Gray's Computer Svc",
    "wof:placetype":"venue"
},
  "geometry": {"coordinates":[-96.47662,45.069552],"type":"Point"}
}