{
  "type": "Feature",
  "properties": {
    "addr:full":"109 S Main St Milbank SD 57252",
    "addr:housenumber":"109",
    "addr:postcode":"57252",
    "addr:street":"S Main St",
    "iso:country":"US",
    "sg:address":"109 S Main St",
    "sg:city":"Milbank",
    "sg:classifiers":[
        {
            "category":"Shopping",
            "subcategory":"Pharmacy",
            "type":"Retail Goods"
        }
    ],
    "sg:phone":"+1 605 432 5541",
    "sg:postcode":"57252",
    "sg:province":"SD",
    "sg:tags":[
        "drug",
        "merchandise",
        "variety"
    ],
    "wof:name":"JUDYS HALLMARK",
    "wof:placetype":"venue"
},
  "geometry": {"coordinates":[-96.63579300000001,45.221545],"type":"Point"}
}