{
  "type": "Feature",
  "properties": {
    "iso:country":"US",
    "sg:address":"110 Deadwood St",
    "sg:city":"Fort Pierre",
    "sg:classifiers":[
        {
            "category":"Restaurant",
            "type":"Food & Drink"
        }
    ],
    "sg:phone":"+1 605 223 2402",
    "sg:postcode":"57532",
    "sg:province":"SD",
    "wof:name":"Chateau Lounge",
    "wof:placetype":"venue"
},
  "geometry": {"coordinates":[-100.370766,44.354256],"type":"Point"}
}