{
  "type": "Feature",
  "properties": {
    "addr:full":"3205 S Lisa Dr Sioux Falls SD 57110",
    "addr:housenumber":"3205",
    "addr:postcode":"57110",
    "addr:street":"S Lisa Dr",
    "iso:country":"US",
    "sg:address":"3205 S Lisa Dr",
    "sg:city":"Sioux Falls",
    "sg:classifiers":[
        {
            "category":"Autos & Motor Vehicles",
            "subcategory":"Auto Supplies",
            "type":"Retail Goods"
        }
    ],
    "sg:phone":"+1 605 371 1415",
    "sg:postcode":"57110",
    "sg:province":"SD",
    "sg:tags":[
        "automotive",
        "repair"
    ],
    "wof:name":"Precision Engineering",
    "wof:placetype":"venue"
},
  "geometry": {"coordinates":[-96.651809,43.516233],"type":"Point"}
}