{
  "type": "Feature",
  "properties": {
    "addr:full":"2421 W 15th St Sioux Falls SD 57104",
    "addr:housenumber":"2421",
    "addr:postcode":"57104",
    "addr:street":"W 15Th St",
    "iso:country":"US",
    "sg:address":"2421 W 15th St",
    "sg:city":"Sioux Falls",
    "sg:classifiers":[
        {
            "category":"Recreation",
            "type":"Entertainment"
        }
    ],
    "sg:phone":"+1 605 367 6185",
    "sg:postcode":"57104",
    "sg:province":"SD",
    "sg:tags":[
        "hall",
        "auditorium"
    ],
    "wof:name":"Oyate Community Ctr",
    "wof:placetype":"venue"
},
  "geometry": {"coordinates":[-96.758134,43.540237],"type":"Point"}
}