{
  "type": "Feature",
  "properties": {
    "addr:full":"47190 198th St Bruce SD 57220",
    "addr:housenumber":"47190",
    "addr:postcode":"57220",
    "addr:street":"198Th St",
    "iso:country":"US",
    "sg:address":"47190 198th St",
    "sg:city":"Bruce",
    "sg:classifiers":[
        {
            "category":"Farming",
            "subcategory":"Farm",
            "type":"Manufacturing & Wholesale Goods"
        }
    ],
    "sg:phone":"+1 605 693 4144",
    "sg:postcode":"57220",
    "sg:province":"SD",
    "sg:tags":[
        "crop",
        "general"
    ],
    "wof:name":"Charles Rang",
    "wof:placetype":"venue"
},
  "geometry": {"coordinates":[-96.768314,44.514134],"type":"Point"}
}