{
  "type": "Feature",
  "properties": {
    "iso:country":"US",
    "sg:address":"317 W Clark St",
    "sg:city":"Vermillion",
    "sg:classifiers":[
        {
            "category":"Social Services",
            "type":"Services"
        }
    ],
    "sg:phone":"+1 605 624 6991",
    "sg:postcode":"57069",
    "sg:province":"SD",
    "sg:tags":[
        "organization",
        "welfare"
    ],
    "wof:name":"SESDAC Inc",
    "wof:placetype":"venue"
},
  "geometry": {"coordinates":[-96.937825,42.782586],"type":"Point"}
}