{
  "type": "Feature",
  "properties": {
    "iso:country":"US",
    "sg:address":"508 N Garfield Ave",
    "sg:city":"Sioux Falls",
    "sg:classifiers":[
        {
            "category":"Wholesale",
            "subcategory":"Machinery & Supplies",
            "type":"Manufacturing & Wholesale Goods"
        }
    ],
    "sg:phone":"+1 605 275 4800",
    "sg:postcode":"57104",
    "sg:province":"SD",
    "sg:tags":[
        "contractor"
    ],
    "wof:name":"Specialty Sealants Inc",
    "wof:placetype":"venue"
},
  "geometry": {"coordinates":[-96.758591,43.553581],"type":"Point"}
}