{
  "type": "Feature",
  "properties": {
    "iso:country":"US",
    "sg:address":"2403 N Maple Ave",
    "sg:city":"Rapid City",
    "sg:classifiers":[
        {
            "category":"Insurance",
            "subcategory":"Insurance Agent",
            "type":"Services"
        }
    ],
    "sg:phone":"+1 605 737 5400",
    "sg:postcode":"57701",
    "sg:province":"SD",
    "wof:name":"State Farm Insurance",
    "wof:placetype":"venue"
},
  "geometry": {"coordinates":[-103.20800800000001,44.107665],"type":"Point"}
}