{
  "type": "Feature",
  "properties": {
    "iso:country":"US",
    "sg:address":"28862 435th Ave",
    "sg:city":"Menno",
    "sg:classifiers":[
        {
            "category":"Farming",
            "subcategory":"Livestock Farm",
            "type":"Manufacturing & Wholesale Goods"
        }
    ],
    "sg:phone":"+1 605 387 5680",
    "sg:postcode":"57045",
    "sg:province":"SD",
    "sg:tags":[
        "beef",
        "feedlot",
        "cattle"
    ],
    "wof:name":"Mark Allen Ulmer",
    "wof:placetype":"venue"
},
  "geometry": {"coordinates":[-97.497966,43.198123],"type":"Point"}
}