{
  "type": "Feature",
  "properties": {
    "addr:full":"1200 Empire Mall Sioux Falls SD 57106",
    "addr:housenumber":"1200",
    "addr:postcode":"57106",
    "addr:street":"Empire Mall",
    "iso:country":"US",
    "sg:address":"1200 Empire Mall",
    "sg:city":"Sioux Falls",
    "sg:classifiers":[
        {
            "category":"Shopping",
            "subcategory":"Gifts & Souvenirs",
            "type":"Retail Goods"
        }
    ],
    "sg:phone":"+1 605 361 2260",
    "sg:postcode":"57106",
    "sg:province":"SD",
    "wof:name":"Coach House Gifts",
    "wof:placetype":"venue"
},
  "geometry": {"coordinates":[-96.77479599999999,43.514231],"type":"Point"}
}