{
  "type": "Feature",
  "properties": {
    "iso:country":"US",
    "sg:address":"2300 E Austin St",
    "sg:city":"Sioux Falls",
    "sg:classifiers":[
        {
            "category":"Building & Trades",
            "subcategory":"Plumbing",
            "type":"Services"
        }
    ],
    "sg:phone":"+1 605 339 4103",
    "sg:postcode":"57103",
    "sg:province":"SD",
    "sg:tags":[
        "heating",
        "contractor"
    ],
    "wof:name":"Energy Management",
    "wof:placetype":"venue"
},
  "geometry": {"coordinates":[-96.697138,43.549466],"type":"Point"}
}