{
  "type": "Feature",
  "properties": {
    "iso:country":"US",
    "sg:address":"525 E Illinois St",
    "sg:city":"Spearfish",
    "sg:classifiers":[
        {
            "category":"Social Services",
            "subcategory":"Child Care",
            "type":"Services"
        }
    ],
    "sg:phone":"+1 605 642 1220",
    "sg:postcode":"57783",
    "sg:province":"SD",
    "sg:tags":[
        "school",
        "program",
        "after"
    ],
    "wof:name":"Kids Club Kids",
    "wof:placetype":"venue"
},
  "geometry": {"coordinates":[-103.851702,44.490993],"type":"Point"}
}