{
  "type": "Feature",
  "properties": {
    "addr:full":"27140 390th Ave Corsica SD 57328",
    "addr:housenumber":"27140",
    "addr:postcode":"57328",
    "addr:street":"390Th Ave",
    "iso:country":"US",
    "sg:address":"27140 390th Ave",
    "sg:city":"Corsica",
    "sg:classifiers":[
        {
            "category":"Farming",
            "subcategory":"Farm",
            "type":"Manufacturing & Wholesale Goods"
        }
    ],
    "sg:phone":"+1 605 946 5253",
    "sg:postcode":"57328",
    "sg:province":"SD",
    "sg:tags":[
        "crop",
        "general"
    ],
    "wof:name":"Henry W Bamberg Jr",
    "wof:placetype":"venue"
},
  "geometry": {"coordinates":[-98.390529,43.450505],"type":"Point"}
}