{
  "type": "Feature",
  "properties": {
    "iso:country":"US",
    "sg:address":"1403 Cedar St",
    "sg:city":"Brandon",
    "sg:classifiers":[
        {
            "category":"Building & Trades",
            "subcategory":"Plumbing",
            "type":"Services"
        }
    ],
    "sg:phone":"+1 605 582 3315",
    "sg:postcode":"57005",
    "sg:province":"SD",
    "sg:tags":[
        "plumbing",
        "contractor"
    ],
    "wof:name":"De Jager Plumbing & Heating",
    "wof:placetype":"venue"
},
  "geometry": {"coordinates":[-96.571092,43.59031],"type":"Point"}
}