{
  "type": "Feature",
  "properties": {
    "iso:country":"US",
    "sg:address":"3609 Fraley Ct",
    "sg:city":"Rapid City",
    "sg:classifiers":[
        {
            "category":"Retail",
            "subcategory":"Auto Repair",
            "type":"Services"
        }
    ],
    "sg:phone":"+1 605 342 4379",
    "sg:postcode":"57701",
    "sg:province":"SD",
    "sg:tags":[
        "body"
    ],
    "wof:name":"Matco Tools",
    "wof:placetype":"venue"
},
  "geometry": {"coordinates":[-103.219688,44.050793],"type":"Point"}
}