{
  "type": "Feature",
  "properties": {
    "addr:full":"335 E 4th St Dell Rapids SD 57022",
    "addr:housenumber":"335",
    "addr:postcode":"57022",
    "addr:street":"E 4Th St",
    "iso:country":"US",
    "sg:address":"335 E 4th St",
    "sg:city":"Dell Rapids",
    "sg:classifiers":[
        {
            "category":"Shopping",
            "subcategory":"Pharmacy",
            "type":"Retail Goods"
        }
    ],
    "sg:phone":"+1 605 428 5440",
    "sg:postcode":"57022",
    "sg:province":"SD",
    "wof:name":"Lewis Family Drug",
    "wof:placetype":"venue"
},
  "geometry": {"coordinates":[-96.713323,43.823263],"type":"Point"}
}