{
  "type": "Feature",
  "properties": {
    "iso:country":"US",
    "sg:address":"30231 120th St",
    "sg:city":"Mound City",
    "sg:classifiers":[
        {
            "category":"Professional",
            "subcategory":"Management & Consulting",
            "type":"Services"
        }
    ],
    "sg:phone":"+1 605 955 3522",
    "sg:postcode":"57646",
    "sg:province":"SD",
    "sg:tags":[
        "business"
    ],
    "wof:name":"Angel Crop Consulting Inc",
    "wof:placetype":"venue"
},
  "geometry": {"coordinates":[-100.145573,45.652096],"type":"Point"}
}