{
  "type": "Feature",
  "properties": {
    "iso:country":"US",
    "sg:address":"2000 W 42nd St",
    "sg:city":"Sioux Falls",
    "sg:classifiers":[
        {
            "category":"Recreation",
            "type":"Entertainment"
        }
    ],
    "sg:phone":"+1 605 336 3987",
    "sg:postcode":"57105",
    "sg:province":"SD",
    "sg:tags":[
        "martial",
        "arts",
        "instruction"
    ],
    "wof:name":"Action Mixed Martial Arts",
    "wof:placetype":"venue"
},
  "geometry": {"coordinates":[-96.75109399999999,43.513722],"type":"Point"}
}