{
  "type": "Feature",
  "properties": {
    "iso:country":"US",
    "sg:address":"40950 267th St",
    "sg:city":"Dimock",
    "sg:classifiers":[
        {
            "category":"Farming",
            "subcategory":"Livestock Farm",
            "type":"Manufacturing & Wholesale Goods"
        }
    ],
    "sg:phone":"+1 605 227 4241",
    "sg:postcode":"57331",
    "sg:province":"SD",
    "sg:tags":[
        "beef",
        "feedlot",
        "cattle"
    ],
    "wof:name":"Robert J Fergen",
    "wof:placetype":"venue"
},
  "geometry": {"coordinates":[-98.004521,43.513342],"type":"Point"}
}