{
  "type": "Feature",
  "properties": {
    "iso:country":"US",
    "sg:address":"101 W 11th Ave",
    "sg:city":"Webster",
    "sg:classifiers":[
        {
            "category":"Sports & Exercise",
            "subcategory":"Gym",
            "type":"Entertainment"
        }
    ],
    "sg:phone":"+1 605 345 9990",
    "sg:postcode":"57274",
    "sg:province":"SD",
    "sg:tags":[
        "gymnasium"
    ],
    "wof:name":"Webster Armory",
    "wof:placetype":"venue"
},
  "geometry": {"coordinates":[-97.521579,45.336259],"type":"Point"}
}