{
  "type": "Feature",
  "properties": {
    "iso:country":"US",
    "sg:address":"37509 285th St",
    "sg:city":"Geddes",
    "sg:classifiers":[
        {
            "category":"Professional",
            "type":"Services"
        }
    ],
    "sg:phone":"+1 605 337 9627",
    "sg:postcode":"57342",
    "sg:province":"SD",
    "sg:tags":[
        "establishment"
    ],
    "wof:name":"Hugg-Inn",
    "wof:placetype":"venue"
},
  "geometry": {"coordinates":[-98.68193,43.255388],"type":"Point"}
}