{
  "type": "Feature",
  "properties": {
    "addr:full":"3900 Airport Rd Pierre SD 57501",
    "addr:housenumber":"3900",
    "addr:postcode":"57501",
    "addr:street":"Airport Rd",
    "iso:country":"US",
    "sg:address":"3900 Airport Rd",
    "sg:city":"Pierre",
    "sg:classifiers":[
        {
            "category":"Retail",
            "subcategory":"Auto Rental",
            "type":"Services"
        }
    ],
    "sg:phone":"+1 605 224 8099",
    "sg:postcode":"57501",
    "sg:province":"SD",
    "sg:tags":[
        "passenger",
        "car"
    ],
    "wof:name":"Budget Rent-A-Car",
    "wof:placetype":"venue"
},
  "geometry": {"coordinates":[-100.288937,44.37583],"type":"Point"}
}