{
  "type": "Feature",
  "properties": {
    "iso:country":"US",
    "sg:address":"38566 174th St",
    "sg:city":"Redfield",
    "sg:classifiers":[
        {
            "category":"Shopping",
            "subcategory":"Books",
            "type":"Retail Goods"
        }
    ],
    "sg:phone":"+1 605 472 2405",
    "sg:postcode":"57469",
    "sg:province":"SD",
    "sg:tags":[
        "dealer"
    ],
    "wof:name":"Fatima Family Apostolate",
    "wof:placetype":"venue"
},
  "geometry": {"coordinates":[-98.508879,44.864804],"type":"Point"}
}