{
  "type": "Feature",
  "properties": {
    "addr:full":"508 28th St NW Watertown SD 57201",
    "addr:housenumber":"508",
    "addr:postcode":"57201",
    "addr:street":"28Th St Nw",
    "iso:country":"US",
    "sg:address":"508 28th St NW",
    "sg:city":"Watertown",
    "sg:classifiers":[
        {
            "category":"Manufacturing",
            "subcategory":"Signs",
            "type":"Manufacturing & Wholesale Goods"
        }
    ],
    "sg:phone":"+1 605 886 9303",
    "sg:postcode":"57201",
    "sg:province":"SD",
    "sg:tags":[
        "specialty",
        "mfg"
    ],
    "wof:name":"Brekke Signs",
    "wof:placetype":"venue"
},
  "geometry": {"coordinates":[-97.160972,44.90781],"type":"Point"}
}