{
  "type": "Feature",
  "properties": {
    "addr:full":"720 Parkway Hudson SD 57034",
    "addr:housenumber":"720",
    "addr:postcode":"57034",
    "addr:street":"Parkway",
    "iso:country":"US",
    "sg:address":"720 Parkway",
    "sg:city":"Hudson",
    "sg:classifiers":[
        {
            "category":"Professional",
            "type":"Services"
        }
    ],
    "sg:phone":"+1 605 984 2332",
    "sg:postcode":"57034",
    "sg:province":"SD",
    "sg:tags":[
        "establishment"
    ],
    "wof:name":"Colonial Manor-Hudson",
    "wof:placetype":"venue"
},
  "geometry": {"coordinates":[-96.460267,43.127116],"type":"Point"}
}