{
  "type": "Feature",
  "properties": {
    "iso:country":"US",
    "sg:address":"1724 6th St",
    "sg:city":"Brookings",
    "sg:classifiers":[
        {
            "category":"Professional",
            "subcategory":"Business Services",
            "type":"Services"
        }
    ],
    "sg:phone":"+1 605 697 6826",
    "sg:postcode":"57006",
    "sg:province":"SD",
    "sg:tags":[
        "embroidery"
    ],
    "wof:name":"Embroidery & More",
    "wof:placetype":"venue"
},
  "geometry": {"coordinates":[-96.77623699999999,44.311311],"type":"Point"}
}