{
  "type": "Feature",
  "properties": {
    "addr:full":"711 W 1st St Webster SD 57274",
    "addr:housenumber":"711",
    "addr:postcode":"57274",
    "addr:street":"W 1St St",
    "iso:country":"US",
    "sg:address":"711 W 1st St",
    "sg:city":"Webster",
    "sg:classifiers":[
        {
            "category":"Government",
            "subcategory":"Court House",
            "type":"Public Place"
        }
    ],
    "sg:phone":"+1 605 345 3771",
    "sg:postcode":"57274",
    "sg:province":"SD",
    "sg:tags":[
        "state",
        "circuit"
    ],
    "wof:name":"Day County Circuit Court",
    "wof:placetype":"venue"
},
  "geometry": {"coordinates":[-97.521653,45.333101],"type":"Point"}
}