{
  "type": "Feature",
  "properties": {
    "iso:country":"US",
    "sg:address":"825 6th Ave",
    "sg:city":"Brookings",
    "sg:classifiers":[
        {
            "category":"Professional",
            "subcategory":"Management & Consulting",
            "type":"Services"
        }
    ],
    "sg:phone":"+1 605 692 1363",
    "sg:postcode":"57006",
    "sg:province":"SD",
    "wof:name":"Seegar Consulting",
    "wof:placetype":"venue"
},
  "geometry": {"coordinates":[-96.79526799999999,44.315238],"type":"Point"}
}