{
  "type": "Feature",
  "properties": {
    "addr:full":"31799 US Hwy 18 Winner SD 57580",
    "addr:postcode":"31799;57580",
    "addr:street":"Us Hwy 18",
    "iso:country":"US",
    "sg:address":"31799 US Hwy 18",
    "sg:city":"Winner",
    "sg:classifiers":[
        {
            "category":"Insurance",
            "subcategory":"Insurance Agent",
            "type":"Services"
        }
    ],
    "sg:phone":"+1 605 842 3804",
    "sg:postcode":"57580",
    "sg:province":"SD",
    "sg:website":"www.modern-woodmen.org",
    "wof:name":"Modern Woodmen Of America",
    "wof:placetype":"venue"
},
  "geometry": {"coordinates":[-99.81067400000001,43.348706],"type":"Point"}
}