{
  "type": "Feature",
  "properties": {
    "iso:country":"US",
    "sg:address":"13734 47th Ave W",
    "sg:city":"Rapid City",
    "sg:classifiers":[
        {
            "category":"Retail",
            "subcategory":"Auto Repair",
            "type":"Services"
        }
    ],
    "sg:phone":"+1 605 391 8351",
    "sg:postcode":"57702",
    "sg:province":"SD",
    "sg:tags":[
        "general"
    ],
    "wof:name":"Rv Doctor",
    "wof:placetype":"venue"
},
  "geometry": {"coordinates":[-103.31163599999999,43.981694],"type":"Point"}
}