{
  "type": "Feature",
  "properties": {
    "iso:country":"US",
    "sg:address":"310 D St",
    "sg:city":"Edgemont",
    "sg:classifiers":[
        {
            "category":"Organizations",
            "subcategory":"Religious Organization",
            "type":"Services"
        }
    ],
    "sg:phone":"+1 605 662 7716",
    "sg:postcode":"57735",
    "sg:province":"SD",
    "sg:tags":[
        "church"
    ],
    "wof:name":"United Church Umc Ucc Prsng",
    "wof:placetype":"venue"
},
  "geometry": {"coordinates":[-103.82793,43.301006],"type":"Point"}
}