{
  "type": "Feature",
  "properties": {
    "iso:country":"US",
    "sg:address":"2225 Dakota Ave S",
    "sg:city":"Huron",
    "sg:classifiers":[
        {
            "category":"Insurance",
            "subcategory":"Insurance Agent",
            "type":"Services"
        }
    ],
    "sg:phone":"+1 605 352 1318",
    "sg:postcode":"57350",
    "sg:province":"SD",
    "wof:name":"Farm Bureau Insurance",
    "wof:placetype":"venue"
},
  "geometry": {"coordinates":[-98.214326,44.339801],"type":"Point"}
}