{
  "type": "Feature",
  "properties": {
    "iso:country":"US",
    "sg:address":"1809 N Wisconsin St",
    "sg:city":"Mitchell",
    "sg:classifiers":[
        {
            "category":"Social Services",
            "type":"Services"
        }
    ],
    "sg:phone":"+1 605 996 4440",
    "sg:postcode":"57301",
    "sg:province":"SD",
    "wof:name":"Mitchell Area Safe House",
    "wof:placetype":"venue"
},
  "geometry": {"coordinates":[-98.03276700000001,43.727023],"type":"Point"}
}