{
  "type": "Feature",
  "properties": {
    "iso:country":"US",
    "sg:address":"2150 Dakota Ave S",
    "sg:city":"Huron",
    "sg:classifiers":[
        {
            "category":"Shopping",
            "subcategory":"Pharmacy",
            "type":"Retail Goods"
        }
    ],
    "sg:phone":"+1 605 352 1641",
    "sg:postcode":"57350",
    "sg:province":"SD",
    "wof:name":"Coburn's Pharmacy",
    "wof:placetype":"venue"
},
  "geometry": {"coordinates":[-98.21398499999999,44.340849],"type":"Point"}
}