{
  "type": "Feature",
  "properties": {
    "iso:country":"US",
    "sg:address":"120 3rd Ave NW",
    "sg:city":"Watertown",
    "sg:classifiers":[
        {
            "category":"Manufacturing",
            "subcategory":"Printing",
            "type":"Manufacturing & Wholesale Goods"
        }
    ],
    "sg:phone":"+1 605 886 6906",
    "sg:postcode":"57201",
    "sg:province":"SD",
    "sg:tags":[
        "printer"
    ],
    "sg:website":"www.thepublicopinion.com",
    "wof:name":"P/O Printing & Graphic",
    "wof:placetype":"venue"
},
  "geometry": {"coordinates":[-97.11683600000001,44.904559],"type":"Point"}
}