{
  "type": "Feature",
  "properties": {
    "addr:full":"701 Matthews St Armour SD 57313",
    "addr:housenumber":"701",
    "addr:postcode":"57313",
    "addr:street":"Matthews St",
    "iso:country":"US",
    "sg:address":"701 Matthews St",
    "sg:city":"Armour",
    "sg:classifiers":[
        {
            "category":"Personal",
            "subcategory":"Beauty Salon",
            "type":"Services"
        }
    ],
    "sg:phone":"+1 605 724 2430",
    "sg:postcode":"57313",
    "sg:province":"SD",
    "wof:name":"Tangles",
    "wof:placetype":"venue"
},
  "geometry": {"coordinates":[-98.34935,43.318853],"type":"Point"}
}