{
  "type": "Feature",
  "properties": {
    "addr:full":"3315 6th Ave SE Aberdeen SD 57401",
    "addr:housenumber":"3315",
    "addr:postcode":"57401",
    "addr:street":"6Th Ave Se",
    "iso:country":"US",
    "sg:address":"3315 6th Ave SE",
    "sg:city":"Aberdeen",
    "sg:classifiers":[
        {
            "category":"Shopping",
            "subcategory":"Shoes",
            "type":"Retail Goods"
        }
    ],
    "sg:phone":"+1 605 225 0620",
    "sg:postcode":"57401",
    "sg:province":"SD",
    "sg:tags":[
        "shoe",
        "store"
    ],
    "wof:name":"Bur-Mars Shoes",
    "wof:placetype":"venue"
},
  "geometry": {"coordinates":[-98.441343,45.459193],"type":"Point"}
}