{
  "type": "Feature",
  "properties": {
    "iso:country":"US",
    "sg:address":"25357 473rd Ave",
    "sg:city":"Baltic",
    "sg:classifiers":[
        {
            "category":"Farming",
            "subcategory":"Farm",
            "type":"Manufacturing & Wholesale Goods"
        }
    ],
    "sg:phone":"+1 605 529 5755",
    "sg:postcode":"57003",
    "sg:province":"SD",
    "sg:tags":[
        "crop",
        "general"
    ],
    "wof:name":"David Haagenson",
    "wof:placetype":"venue"
},
  "geometry": {"coordinates":[-96.751335,43.717682],"type":"Point"}
}