{
  "type": "Feature",
  "properties": {
    "iso:country":"US",
    "sg:address":"2101 W 49th St",
    "sg:city":"Sioux Falls",
    "sg:classifiers":[
        {
            "category":"Food & Beverages",
            "subcategory":"Groceries & Convenience Stores",
            "type":"Retail Goods"
        }
    ],
    "sg:phone":"+1 605 331 3910",
    "sg:postcode":"57105",
    "sg:province":"SD",
    "sg:website":"www.kumandgo.com",
    "wof:name":"Kum & Go",
    "wof:placetype":"venue"
},
  "geometry": {"coordinates":[-96.751082,43.508447],"type":"Point"}
}