{
  "type": "Feature",
  "properties": {
    "addr:full":"44312 263rd St Canistota SD 57012",
    "addr:housenumber":"44312",
    "addr:postcode":"57012",
    "addr:street":"263Rd St",
    "iso:country":"US",
    "sg:address":"44312 263rd St",
    "sg:city":"Canistota",
    "sg:classifiers":[
        {
            "category":"Farming",
            "subcategory":"Farm",
            "type":"Manufacturing & Wholesale Goods"
        }
    ],
    "sg:phone":"+1 605 296 3366",
    "sg:postcode":"57012",
    "sg:province":"SD",
    "sg:tags":[
        "crop",
        "general"
    ],
    "wof:name":"Jerman Farms",
    "wof:placetype":"venue"
},
  "geometry": {"coordinates":[-97.338506,43.572606],"type":"Point"}
}