{
  "type": "Feature",
  "properties": {
    "iso:country":"US",
    "sg:address":"115 1st Ave SE",
    "sg:city":"Aberdeen",
    "sg:classifiers":[
        {
            "category":"Banks & Credit Unions",
            "subcategory":"Bank",
            "type":"Services"
        }
    ],
    "sg:phone":"+1 605 225 7254",
    "sg:postcode":"57401",
    "sg:province":"SD",
    "sg:tags":[
        "personal",
        "institution"
    ],
    "wof:name":"US Bank Student Loan Center",
    "wof:placetype":"venue"
},
  "geometry": {"coordinates":[-98.48619600000001,45.464202],"type":"Point"}
}