{
  "type": "Feature",
  "properties": {
    "addr:full":"5108 N Cliff Ave Sioux Falls SD 57104",
    "addr:housenumber":"5108",
    "addr:postcode":"57104",
    "addr:street":"N Cliff Ave",
    "iso:country":"US",
    "sg:address":"5108 N Cliff Ave",
    "sg:city":"Sioux Falls",
    "sg:phone":"+1 605 332 1320",
    "sg:postcode":"57104",
    "sg:province":"SD",
    "sg:tags":[
        "product",
        "petroleum"
    ],
    "wof:name":"C H S",
    "wof:placetype":"venue"
},
  "geometry": {"coordinates":[-96.711247,43.603801],"type":"Point"}
}