{
  "type": "Feature",
  "properties": {
    "iso:country":"US",
    "sg:address":"5200 N Harvestore Rd",
    "sg:city":"Sioux Falls",
    "sg:classifiers":[
        {
            "category":"Building & Trades",
            "subcategory":"Plumbing",
            "type":"Services"
        }
    ],
    "sg:phone":"+1 605 331 0078",
    "sg:postcode":"57107",
    "sg:province":"SD",
    "sg:tags":[
        "septic"
    ],
    "wof:name":"Ace Septic",
    "wof:placetype":"venue"
},
  "geometry": {"coordinates":[-96.77488,43.604112],"type":"Point"}
}