{
  "type": "Feature",
  "properties": {
    "iso:country":"US",
    "sg:address":"4601 N Cliff Ave",
    "sg:city":"Sioux Falls",
    "sg:classifiers":[
        {
            "category":"Wholesale",
            "subcategory":"Machinery & Supplies",
            "type":"Manufacturing & Wholesale Goods"
        }
    ],
    "sg:phone":"+1 605 336 8668",
    "sg:postcode":"57104",
    "sg:province":"SD",
    "sg:tags":[
        "equipment",
        "industrial",
        "bearing"
    ],
    "sg:website":"www.precisionind.com",
    "wof:name":"Precision Industries Inc",
    "wof:placetype":"venue"
},
  "geometry": {"coordinates":[-96.71140699999999,43.596998],"type":"Point"}
}