{
  "type": "Feature",
  "properties": {
    "iso:country":"US",
    "sg:address":"27283 State Hwy 115",
    "sg:city":"Harrisburg",
    "sg:classifiers":[
        {
            "category":"Shopping",
            "subcategory":"Hobbies, Toys, & Games",
            "type":"Retail Goods"
        }
    ],
    "sg:phone":"+1 605 360 7644",
    "sg:postcode":"57032",
    "sg:province":"SD",
    "wof:name":"Vintage Toys",
    "wof:placetype":"venue"
},
  "geometry": {"coordinates":[-96.72753899999999,43.434267],"type":"Point"}
}