{
  "type": "Feature",
  "properties": {
    "iso:country":"US",
    "sg:address":"109 3rd St S",
    "sg:city":"Bristol",
    "sg:classifiers":[
        {
            "category":"Social Services",
            "subcategory":"Child Care",
            "type":"Services"
        }
    ],
    "sg:phone":"+1 605 492 3218",
    "sg:postcode":"57219",
    "sg:province":"SD",
    "sg:tags":[
        "day"
    ],
    "wof:name":"Tina Luttrell Day Care",
    "wof:placetype":"venue"
},
  "geometry": {"coordinates":[-97.748478,45.346406],"type":"Point"}
}