{
  "type": "Feature",
  "properties": {
    "addr:full":"13095 391st Ave Aberdeen SD 57401",
    "addr:housenumber":"13095",
    "addr:postcode":"57401",
    "addr:street":"391St Ave",
    "iso:country":"US",
    "sg:address":"13095 391st Ave",
    "sg:city":"Aberdeen",
    "sg:classifiers":[
        {
            "category":"Building & Trades",
            "subcategory":"Construction",
            "type":"Services"
        }
    ],
    "sg:phone":"+1 605 226 2561",
    "sg:postcode":"57401",
    "sg:province":"SD",
    "sg:tags":[
        "general",
        "contractor"
    ],
    "wof:name":"Rathert Construction",
    "wof:placetype":"venue"
},
  "geometry": {"coordinates":[-98.41290600000001,45.488626],"type":"Point"}
}