{
  "type": "Feature",
  "properties": {
    "iso:country":"US",
    "sg:address":"209 Spring Ave S",
    "sg:city":"Lake Preston",
    "sg:classifiers":[
        {
            "category":"Organizations",
            "subcategory":"Religious Organization",
            "type":"Services"
        }
    ],
    "sg:phone":"+1 605 847 4587",
    "sg:postcode":"57249",
    "sg:province":"SD",
    "wof:name":"Preston Lake Lutheran Church",
    "wof:placetype":"venue"
},
  "geometry": {"coordinates":[-97.37250899999999,44.35981],"type":"Point"}
}