{
  "type": "Feature",
  "properties": {
    "iso:country":"US",
    "sg:address":"29478 457th Ave",
    "sg:city":"Centerville",
    "sg:phone":"+1 605 326 5374",
    "sg:postcode":"57014",
    "sg:province":"SD",
    "sg:tags":[
        "farm"
    ],
    "wof:name":"Hansen Virginia",
    "wof:placetype":"venue"
},
  "geometry": {"coordinates":[-97.06223799999999,43.115104],"type":"Point"}
}