{
  "type": "Feature",
  "properties": {
    "iso:country":"US",
    "sg:address":"13755 395th Ave",
    "sg:city":"Bath",
    "sg:classifiers":[
        {
            "category":"Shopping",
            "subcategory":"Hobbies, Toys, & Games",
            "type":"Retail Goods"
        }
    ],
    "sg:phone":"+1 605 225 3093",
    "sg:postcode":"57427",
    "sg:province":"SD",
    "sg:tags":[
        "repair"
    ],
    "wof:name":"Dollys Hospital",
    "wof:placetype":"venue"
},
  "geometry": {"coordinates":[-98.329669,45.388431],"type":"Point"}
}