{
  "type": "Feature",
  "properties": {
    "iso:country":"US",
    "sg:address":"805 N Helen Ave",
    "sg:city":"Sioux Falls",
    "sg:classifiers":[
        {
            "category":"Freight",
            "type":"Transportation"
        }
    ],
    "sg:phone":"+1 605 336 1980",
    "sg:postcode":"57104",
    "sg:province":"SD",
    "sg:tags":[
        "dry",
        "bulk",
        "trucking"
    ],
    "sg:website":"www.transwood.com",
    "wof:name":"Transwood Inc",
    "wof:placetype":"venue"
},
  "geometry": {"coordinates":[-96.766212,43.556582],"type":"Point"}
}