{
  "type": "Feature",
  "properties": {
    "addr:full":"101 State Hwy 44 Chancellor SD 57015",
    "addr:housenumber":"101",
    "addr:postcode":"57015",
    "addr:street":"State Hwy 44 Chancellor",
    "iso:country":"US",
    "sg:address":"101 State Hwy 44",
    "sg:city":"Chancellor",
    "sg:classifiers":[
        {
            "category":"Building & Trades",
            "subcategory":"Construction",
            "type":"Services"
        }
    ],
    "sg:phone":"+1 605 647 2781",
    "sg:postcode":"57015",
    "sg:province":"SD",
    "sg:tags":[
        "roofing",
        "contractor"
    ],
    "wof:name":"C & S Roofing",
    "wof:placetype":"venue"
},
  "geometry": {"coordinates":[-96.984641,43.373115],"type":"Point"}
}