{
  "type": "Feature",
  "properties": {
    "iso:country":"US",
    "sg:address":"21420 441st Ave",
    "sg:city":"Lake Preston",
    "sg:classifiers":[
        {
            "category":"Shopping",
            "subcategory":"Florist",
            "type":"Retail Goods"
        }
    ],
    "sg:phone":"+1 605 847 4722",
    "sg:postcode":"57249",
    "sg:province":"SD",
    "wof:name":"Casper Floral",
    "wof:placetype":"venue"
},
  "geometry": {"coordinates":[-97.391008,44.278725],"type":"Point"}
}