{
  "type": "Feature",
  "properties": {
    "iso:country":"US",
    "sg:address":"5704 W 41st St",
    "sg:city":"Sioux Falls",
    "sg:classifiers":[
        {
            "category":"Health Services",
            "subcategory":"Doctor",
            "type":"Services"
        }
    ],
    "sg:phone":"+1 605 361 9288",
    "sg:postcode":"57106",
    "sg:province":"SD",
    "sg:tags":[
        "dentist"
    ],
    "wof:name":"Kappenman Dental Clinic",
    "wof:placetype":"venue"
},
  "geometry": {"coordinates":[-96.79703000000001,43.514888],"type":"Point"}
}