{
  "type": "Feature",
  "properties": {
    "iso:country":"US",
    "sg:address":"404 5th St",
    "sg:city":"Brookings",
    "sg:classifiers":[
        {
            "category":"Professional",
            "subcategory":"Management & Consulting",
            "type":"Services"
        }
    ],
    "sg:phone":"+1 605 697 2000",
    "sg:postcode":"57006",
    "sg:province":"SD",
    "sg:tags":[
        "consultant",
        "political"
    ],
    "wof:name":"Smidt Professional Svc",
    "wof:placetype":"venue"
},
  "geometry": {"coordinates":[-96.798557,44.310206],"type":"Point"}
}