{
  "type": "Feature",
  "properties": {
    "addr:full":"313 Spruce St W Sisseton SD 57262",
    "addr:housenumber":"313",
    "addr:postcode":"57262",
    "addr:street":"Spruce St W",
    "iso:country":"US",
    "sg:address":"313 Spruce St W",
    "sg:city":"Sisseton",
    "sg:classifiers":[
        {
            "category":"Wholesale",
            "subcategory":"Dairy",
            "type":"Manufacturing & Wholesale Goods"
        }
    ],
    "sg:phone":"+1 605 698 7361",
    "sg:postcode":"57262",
    "sg:province":"SD",
    "sg:tags":[
        "product"
    ],
    "wof:name":"Cass Clay Creamery",
    "wof:placetype":"venue"
},
  "geometry": {"coordinates":[-97.05492599999999,45.666501],"type":"Point"}
}