{
  "type": "Feature",
  "properties": {
    "iso:country":"US",
    "sg:address":"202 Main St",
    "sg:city":"Volin",
    "sg:classifiers":[
        {
            "category":"Restaurant",
            "type":"Food & Drink"
        }
    ],
    "sg:phone":"+1 605 267 1248",
    "sg:postcode":"57045",
    "sg:province":"SD",
    "wof:name":"Volin Cafe",
    "wof:placetype":"venue"
},
  "geometry": {"coordinates":[-97.575717,43.237236],"type":"Point"}
}