{
  "type": "Feature",
  "properties": {
    "iso:country":"US",
    "sg:address":"8408 W 46th St",
    "sg:city":"Sioux Falls",
    "sg:classifiers":[
        {
            "category":"Manufacturing",
            "subcategory":"Toys & Sporting Goods",
            "type":"Manufacturing & Wholesale Goods"
        }
    ],
    "sg:phone":"+1 605 361 1683",
    "sg:postcode":"57106",
    "sg:province":"SD",
    "sg:tags":[
        "mfg"
    ],
    "wof:name":"Dibberts Designs",
    "wof:placetype":"venue"
},
  "geometry": {"coordinates":[-96.82970899999999,43.510605],"type":"Point"}
}