{
  "type": "Feature",
  "properties": {
    "addr:full":"616 West St Rapid City SD 57701",
    "addr:housenumber":"616",
    "addr:postcode":"57701",
    "addr:street":"West St",
    "iso:country":"US",
    "sg:address":"616 West St",
    "sg:city":"Rapid City",
    "sg:classifiers":[
        {
            "category":"Manufacturing",
            "subcategory":"Toys & Sporting Goods",
            "type":"Manufacturing & Wholesale Goods"
        }
    ],
    "sg:phone":"+1 605 343 8200",
    "sg:postcode":"57701",
    "sg:province":"SD",
    "sg:website":"www.legendsandlore.com",
    "wof:name":"Legends",
    "wof:placetype":"venue"
},
  "geometry": {"coordinates":[-103.239628,44.081093],"type":"Point"}
}