{
  "type": "Feature",
  "properties": {
    "iso:country":"US",
    "sg:address":"1900 W 41st St",
    "sg:city":"Sioux Falls",
    "sg:classifiers":[
        {
            "category":"Restaurant",
            "type":"Food & Drink"
        }
    ],
    "sg:menulink":"http://www.allmenus.com/sd/sioux-falls/98191-qdoba/menu/",
    "sg:phone":"+1 605 331 5700",
    "sg:postcode":"57105",
    "sg:province":"SD",
    "sg:tags":[
        "mexican"
    ],
    "wof:name":"Qdoba",
    "wof:placetype":"venue"
},
  "geometry": {"coordinates":[-96.748631,43.514861],"type":"Point"}
}