{
  "type": "Feature",
  "properties": {
    "addr:full":"43880 245th St Salem SD 57058",
    "addr:housenumber":"43880",
    "addr:postcode":"57058",
    "addr:street":"245Th St",
    "iso:country":"US",
    "sg:address":"43880 245th St",
    "sg:city":"Salem",
    "sg:classifiers":[
        {
            "category":"Farming",
            "subcategory":"Livestock Farm",
            "type":"Manufacturing & Wholesale Goods"
        }
    ],
    "sg:phone":"+1 605 247 3338",
    "sg:postcode":"57058",
    "sg:province":"SD",
    "sg:tags":[
        "general"
    ],
    "wof:name":"Daniel Zelmer",
    "wof:placetype":"venue"
},
  "geometry": {"coordinates":[-97.430671,43.833162],"type":"Point"}
}