{
  "type": "Feature",
  "properties": {
    "addr:full":"21202 475th Ave Aurora SD 57002",
    "addr:housenumber":"21202",
    "addr:postcode":"57002",
    "addr:street":"475Th Ave",
    "iso:country":"US",
    "sg:address":"21202 475th Ave",
    "sg:city":"Aurora",
    "sg:classifiers":[
        {
            "category":"Professional",
            "subcategory":"Research",
            "type":"Services"
        }
    ],
    "sg:phone":"+1 605 693 3774",
    "sg:postcode":"57002",
    "sg:province":"SD",
    "sg:tags":[
        "development",
        "laboratory"
    ],
    "wof:name":"Syngenta Seeds Inc",
    "wof:placetype":"venue"
},
  "geometry": {"coordinates":[-96.70774900000001,44.311101],"type":"Point"}
}