{
  "type": "Feature",
  "properties": {
    "addr:full":"15469 444th Ave Florence SD 57235",
    "addr:housenumber":"15469",
    "addr:postcode":"57235",
    "addr:street":"444Th Ave",
    "iso:country":"US",
    "sg:address":"15469 444th Ave",
    "sg:city":"Florence",
    "sg:classifiers":[
        {
            "category":"Farming",
            "subcategory":"Farm",
            "type":"Manufacturing & Wholesale Goods"
        }
    ],
    "sg:phone":"+1 605 758 2477",
    "sg:postcode":"57235",
    "sg:province":"SD",
    "sg:tags":[
        "crop",
        "general"
    ],
    "wof:name":"Martin Tschakert",
    "wof:placetype":"venue"
},
  "geometry": {"coordinates":[-97.33101499999999,45.141815],"type":"Point"}
}