{
  "type": "Feature",
  "properties": {
    "addr:full":"11 Dakota St Aberdeen SD 57401",
    "addr:housenumber":"11",
    "addr:postcode":"57401",
    "addr:street":"Dakota St",
    "iso:country":"US",
    "sg:address":"11 Dakota St",
    "sg:city":"Aberdeen",
    "sg:classifiers":[
        {
            "category":"Shopping",
            "type":"Retail Goods"
        }
    ],
    "sg:phone":"+1 605 225 1635",
    "sg:postcode":"57401",
    "sg:province":"SD",
    "sg:tags":[
        "merchandise"
    ],
    "wof:name":"Dakota Art & Frame",
    "wof:placetype":"venue"
},
  "geometry": {"coordinates":[-98.47462899999999,45.465818],"type":"Point"}
}