{
  "type": "Feature",
  "properties": {
    "iso:country":"US",
    "sg:address":"1823 Samco Rd",
    "sg:city":"Rapid City",
    "sg:classifiers":[
        {
            "category":"Insurance",
            "subcategory":"Insurance Agent",
            "type":"Services"
        }
    ],
    "sg:phone":"+1 605 342 2438",
    "sg:postcode":"57702",
    "sg:province":"SD",
    "wof:name":"Financial Markets Inc",
    "wof:placetype":"venue"
},
  "geometry": {"coordinates":[-103.267354,44.103114],"type":"Point"}
}