{
  "type": "Feature",
  "properties": {
    "addr:full":"1505 S Minnesota Ave Sioux Falls SD 57105",
    "addr:housenumber":"1505",
    "addr:postcode":"57105",
    "addr:street":"S Minnesota Ave",
    "iso:country":"US",
    "sg:address":"1505 S Minnesota Ave",
    "sg:city":"Sioux Falls",
    "sg:classifiers":[
        {
            "category":"Personal",
            "subcategory":"Beauty Salon",
            "type":"Services"
        }
    ],
    "sg:phone":"+1 605 335 8110",
    "sg:postcode":"57105",
    "sg:province":"SD",
    "sg:tags":[
        "shop"
    ],
    "wof:name":"Rose's Beauty Salon",
    "wof:placetype":"venue"
},
  "geometry": {"coordinates":[-96.73136700000001,43.531281],"type":"Point"}
}