{
  "type": "Feature",
  "properties": {
    "iso:country":"US",
    "sg:address":"1828 W Kansas City St",
    "sg:city":"Rapid City",
    "sg:classifiers":[
        {
            "category":"Health Services",
            "subcategory":"Doctor",
            "type":"Services"
        }
    ],
    "sg:phone":"+1 605 348 1350",
    "sg:postcode":"57702",
    "sg:province":"SD",
    "sg:tags":[
        "physician",
        "surgeon"
    ],
    "wof:name":"Allergy Clinic",
    "wof:placetype":"venue"
},
  "geometry": {"coordinates":[-103.249782,44.080377],"type":"Point"}
}