{
  "type": "Feature",
  "properties": {
    "addr:full":"802 E Washington St Elk Point SD 57025",
    "addr:housenumber":"802",
    "addr:postcode":"57025",
    "addr:street":"E Washington St",
    "iso:country":"US",
    "sg:address":"802 E Washington St",
    "sg:city":"Elk Point",
    "sg:classifiers":[
        {
            "category":"Retail",
            "subcategory":"Funeral Services",
            "type":"Services"
        }
    ],
    "sg:phone":"+1 605 356 2633",
    "sg:postcode":"57025",
    "sg:province":"SD",
    "sg:tags":[
        "director"
    ],
    "wof:name":"Anderson Siecke Funeral Home",
    "wof:placetype":"venue"
},
  "geometry": {"coordinates":[-96.677603,42.681624],"type":"Point"}
}