{
  "type": "Feature",
  "properties": {
    "iso:country":"US",
    "sg:address":"217 Main St",
    "sg:city":"Hill City",
    "sg:classifiers":[
        {
            "category":"Museum",
            "type":"Entertainment"
        }
    ],
    "sg:phone":"+1 605 574 3919",
    "sg:postcode":"57745",
    "sg:province":"SD",
    "sg:website":"www.everythingprehistoric.com",
    "wof:name":"Everything Prehistoric",
    "wof:placetype":"venue"
},
  "geometry": {"coordinates":[-103.57522400000001,43.933873],"type":"Point"}
}