{
  "type": "Feature",
  "properties": {
    "iso:country":"US",
    "sg:address":"116 E Main St",
    "sg:city":"Elk Point",
    "sg:classifiers":[
        {
            "category":"Insurance",
            "subcategory":"Insurance Agent",
            "type":"Services"
        }
    ],
    "sg:phone":"+1 605 356 2261",
    "sg:postcode":"57025",
    "sg:province":"SD",
    "wof:name":"Rubida Insurance",
    "wof:placetype":"venue"
},
  "geometry": {"coordinates":[-96.684651,42.686103],"type":"Point"}
}