{
  "type": "Feature",
  "properties": {
    "addr:full":"104 N Splitrock Blvd Brandon SD 57005",
    "addr:housenumber":"104",
    "addr:postcode":"57005",
    "addr:street":"N Splitrock Blvd",
    "iso:country":"US",
    "sg:address":"104 N Splitrock Blvd",
    "sg:city":"Brandon",
    "sg:classifiers":[
        {
            "category":"Manufacturing",
            "subcategory":"Tools & Machinery",
            "type":"Manufacturing & Wholesale Goods"
        }
    ],
    "sg:phone":"+1 605 336 8769",
    "sg:postcode":"57005",
    "sg:province":"SD",
    "sg:tags":[
        "machine",
        "shop"
    ],
    "wof:name":"Sturdevants Auto Parts",
    "wof:placetype":"venue"
},
  "geometry": {"coordinates":[-96.57235,43.594592],"type":"Point"}
}