{
  "type": "Feature",
  "properties": {
    "iso:country":"US",
    "sg:address":"23449 392nd Ave",
    "sg:city":"Woonsocket",
    "sg:phone":"+1 605 796 4948",
    "sg:postcode":"57385",
    "sg:province":"SD",
    "sg:tags":[
        "beef",
        "farm",
        "corn",
        "soybean",
        "cattle",
        "feedlot"
    ],
    "wof:name":"Merlin Feistner",
    "wof:placetype":"venue"
},
  "geometry": {"coordinates":[-98.371932,43.988468],"type":"Point"}
}