{
  "type": "Feature",
  "properties": {
    "iso:country":"US",
    "sg:address":"110 S Park Ave",
    "sg:city":"Lake Andes",
    "sg:classifiers":[
        {
            "category":"Retail",
            "subcategory":"Repair Shop",
            "type":"Services"
        }
    ],
    "sg:phone":"+1 605 487 7693",
    "sg:postcode":"57328",
    "sg:province":"SD",
    "sg:tags":[
        "welding"
    ],
    "wof:name":"Scotty's Welding & Repair",
    "wof:placetype":"venue"
},
  "geometry": {"coordinates":[-98.402546,43.423583],"type":"Point"}
}