{
  "type": "Feature",
  "properties": {
    "addr:full":"2030 Jackson Blvd Rapid City SD 57702",
    "addr:housenumber":"2030",
    "addr:postcode":"57702",
    "addr:street":"Jackson Blvd",
    "iso:country":"US",
    "sg:address":"2030 Jackson Blvd",
    "sg:city":"Rapid City",
    "sg:classifiers":[
        {
            "category":"Personal",
            "subcategory":"Beauty Salon",
            "type":"Services"
        }
    ],
    "sg:phone":"+1 605 343 0714",
    "sg:postcode":"57702",
    "sg:province":"SD",
    "wof:name":"Le Salon",
    "wof:placetype":"venue"
},
  "geometry": {"coordinates":[-103.253334,44.074234],"type":"Point"}
}