{
  "type": "Feature",
  "properties": {
    "iso:country":"US",
    "sg:address":"513 3rd St SE",
    "sg:city":"Huron",
    "sg:classifiers":[
        {
            "category":"Home & Garden",
            "subcategory":"Building Materials",
            "type":"Retail Goods"
        }
    ],
    "sg:phone":"+1 605 352 0836",
    "sg:postcode":"57350",
    "sg:province":"SD",
    "sg:tags":[
        "glass",
        "window",
        "plate"
    ],
    "wof:name":"Gary Zell's Auto Glass",
    "wof:placetype":"venue"
},
  "geometry": {"coordinates":[-98.20578500000001,44.363324],"type":"Point"}
}