{
  "type": "Feature",
  "properties": {
    "iso:country":"US",
    "sg:address":"323 4th Ave E",
    "sg:city":"Mobridge",
    "sg:classifiers":[
        {
            "category":"Organizations",
            "subcategory":"Non-profit Organization",
            "type":"Services"
        }
    ],
    "sg:phone":"+1 605 845 3831",
    "sg:postcode":"57601",
    "sg:province":"SD",
    "sg:tags":[
        "information",
        "alcoholism",
        "treatment"
    ],
    "sg:website":"www.aa.org",
    "wof:name":"Alcoholics Anonymous",
    "wof:placetype":"venue"
},
  "geometry": {"coordinates":[-100.428175,45.536161],"type":"Point"}
}