{
  "type": "Feature",
  "properties": {
    "iso:country":"US",
    "sg:address":"4921 E 26th St",
    "sg:city":"Sioux Falls",
    "sg:classifiers":[
        {
            "category":"Health Services",
            "subcategory":"Doctor",
            "type":"Services"
        }
    ],
    "sg:phone":"+1 605 371 3443",
    "sg:postcode":"57110",
    "sg:province":"SD",
    "wof:name":"Family and Implant Dentistry",
    "wof:placetype":"venue"
},
  "geometry": {"coordinates":[-96.666129,43.529297],"type":"Point"}
}