{
  "type": "Feature",
  "properties": {
    "iso:country":"US",
    "sg:address":"1419 Court St",
    "sg:city":"Faulkton",
    "sg:classifiers":[
        {
            "category":"Home & Garden",
            "subcategory":"Garden Supply",
            "type":"Retail Goods"
        }
    ],
    "sg:phone":"+1 605 598 4371",
    "sg:postcode":"57438",
    "sg:province":"SD",
    "sg:tags":[
        "lawn",
        "mower"
    ],
    "wof:name":"Bill Schilder Sales",
    "wof:placetype":"venue"
},
  "geometry": {"coordinates":[-99.134304,45.033737],"type":"Point"}
}