{
  "type": "Feature",
  "properties": {
    "iso:country":"US",
    "sg:address":"2303 Jackson Blvd",
    "sg:city":"Rapid City",
    "sg:classifiers":[
        {
            "category":"Food & Beverages",
            "subcategory":"Groceries & Convenience Stores",
            "type":"Retail Goods"
        }
    ],
    "sg:phone":"+1 605 343 1222",
    "sg:postcode":"57702",
    "sg:province":"SD",
    "wof:name":"Stoicks of Rapid City",
    "wof:placetype":"venue"
},
  "geometry": {"coordinates":[-103.25879999999999,44.071209],"type":"Point"}
}