{
  "type": "Feature",
  "properties": {
    "iso:country":"US",
    "sg:address":"25580 472nd Ave",
    "sg:city":"Renner",
    "sg:classifiers":[
        {
            "category":"Building & Trades",
            "subcategory":"Construction",
            "type":"Services"
        }
    ],
    "sg:phone":"+1 605 543 6979",
    "sg:postcode":"57055",
    "sg:province":"SD",
    "sg:tags":[
        "contractor"
    ],
    "wof:name":"OHara Masonry Inc",
    "wof:placetype":"venue"
},
  "geometry": {"coordinates":[-96.77142499999999,43.675763],"type":"Point"}
}