{
  "type": "Feature",
  "properties": {
    "iso:country":"US",
    "sg:address":"27373 372nd Ave",
    "sg:city":"Platte",
    "sg:classifiers":[
        {
            "category":"Farming",
            "subcategory":"Farm",
            "type":"Manufacturing & Wholesale Goods"
        }
    ],
    "sg:phone":"+1 605 337 2648",
    "sg:postcode":"57369",
    "sg:province":"SD",
    "sg:tags":[
        "crop",
        "general"
    ],
    "wof:name":"Gary Schieffer",
    "wof:placetype":"venue"
},
  "geometry": {"coordinates":[-98.746392,43.417141],"type":"Point"}
}