{
  "type": "Feature",
  "properties": {
    "iso:country":"US",
    "sg:address":"1 US Hwy 16",
    "sg:city":"Custer",
    "sg:classifiers":[
        {
            "category":"Professional",
            "type":"Services"
        }
    ],
    "sg:phone":"+1 605 673 4761",
    "sg:postcode":"57730",
    "sg:province":"SD",
    "sg:tags":[
        "establishment"
    ],
    "wof:name":"Heritage Village",
    "wof:placetype":"venue"
},
  "geometry": {"coordinates":[-103.600542,43.766798],"type":"Point"}
}