{
  "type": "Feature",
  "properties": {
    "iso:country":"US",
    "sg:address":"913 5th St SE",
    "sg:city":"Watertown",
    "sg:classifiers":[
        {
            "category":"Government",
            "subcategory":"Office",
            "type":"Public Place"
        }
    ],
    "sg:phone":"+1 605 882 5111",
    "sg:postcode":"57201",
    "sg:province":"SD",
    "sg:tags":[
        "state"
    ],
    "wof:name":"Dept Envir Natural Resources",
    "wof:placetype":"venue"
},
  "geometry": {"coordinates":[-97.109274,44.889763],"type":"Point"}
}