{
  "type": "Feature",
  "properties": {
    "iso:country":"US",
    "sg:address":"3400 E 11th St",
    "sg:city":"Sioux Falls",
    "sg:classifiers":[
        {
            "category":"Real Estate",
            "subcategory":"Real Estate Operator",
            "type":"Services"
        }
    ],
    "sg:phone":"+1 605 334 3883",
    "sg:postcode":"57103",
    "sg:province":"SD",
    "sg:tags":[
        "apartment"
    ],
    "wof:name":"East Park Apartments",
    "wof:placetype":"venue"
},
  "geometry": {"coordinates":[-96.68315200000001,43.545077],"type":"Point"}
}