{
  "type": "Feature",
  "properties": {
    "iso:country":"US",
    "sg:address":"415 Main St",
    "sg:city":"Platte",
    "sg:classifiers":[
        {
            "category":"Home & Garden",
            "subcategory":"Hardware",
            "type":"Retail Goods"
        }
    ],
    "sg:phone":"+1 605 337 3141",
    "sg:postcode":"57369",
    "sg:province":"SD",
    "wof:name":"Lieuwin's Ace Hardware",
    "wof:placetype":"venue"
},
  "geometry": {"coordinates":[-98.844673,43.387044],"type":"Point"}
}