{
  "type": "Feature",
  "properties": {
    "iso:country":"US",
    "sg:address":"44894 262nd St",
    "sg:city":"Canistota",
    "sg:classifiers":[
        {
            "category":"Farming",
            "subcategory":"Livestock Farm",
            "type":"Manufacturing & Wholesale Goods"
        }
    ],
    "sg:phone":"+1 605 296 3369",
    "sg:postcode":"57012",
    "sg:province":"SD",
    "sg:tags":[
        "feedlot",
        "corn",
        "soybean",
        "beef",
        "cattle"
    ],
    "wof:name":"Hoffer Ferlyn",
    "wof:placetype":"venue"
},
  "geometry": {"coordinates":[-97.228132,43.586756],"type":"Point"}
}