{
  "type": "Feature",
  "properties": {
    "iso:country":"US",
    "sg:address":"1710 6th St",
    "sg:city":"Brookings",
    "sg:classifiers":[
        {
            "category":"Deli",
            "type":"Food & Drink"
        },
        {
            "category":"Restaurant",
            "type":"Food & Drink"
        }
    ],
    "sg:menulink":"http://www.allmenus.com/sd/brookings/23603-mad-jacks-deli--grill/menu/",
    "sg:phone":"+1 605 692 2878",
    "sg:postcode":"57006",
    "sg:province":"SD",
    "sg:tags":[
        "deli",
        "american"
    ],
    "wof:name":"Mad Jack's Deli & Grill",
    "wof:placetype":"venue"
},
  "geometry": {"coordinates":[-96.776118,44.311479],"type":"Point"}
}