{
  "type": "Feature",
  "properties": {
    "iso:country":"US",
    "sg:address":"6804 W 9th St",
    "sg:city":"Sioux Falls",
    "sg:classifiers":[
        {
            "category":"Government",
            "subcategory":"Fire Station",
            "type":"Public Place"
        }
    ],
    "sg:phone":"+1 605 334 6108",
    "sg:postcode":"57107",
    "sg:province":"SD",
    "sg:tags":[
        "protection"
    ],
    "wof:name":"Wayne Township Fire Department",
    "wof:placetype":"venue"
},
  "geometry": {"coordinates":[-96.809148,43.547534],"type":"Point"}
}