{
  "type": "Feature",
  "properties": {
    "iso:country":"US",
    "sg:address":"4 Woodrun Ln",
    "sg:city":"Rapid City",
    "sg:classifiers":[
        {
            "category":"Travel",
            "subcategory":"Travel Agent",
            "type":"Entertainment"
        }
    ],
    "sg:phone":"+1 605 343 4852",
    "sg:postcode":"57702",
    "sg:province":"SD",
    "sg:tags":[
        "tours",
        "promoter"
    ],
    "sg:website":"www.shebbyleetours.com",
    "wof:name":"Shebby Lee Tours",
    "wof:placetype":"venue"
},
  "geometry": {"coordinates":[-103.295344,44.048501],"type":"Point"}
}