{
  "type": "Feature",
  "properties": {
    "iso:country":"US",
    "sg:address":"2740 N Haines Ave",
    "sg:city":"Rapid City",
    "sg:classifiers":[
        {
            "category":"Professional",
            "subcategory":"Advertising",
            "type":"Services"
        }
    ],
    "sg:phone":"+1 605 388 3369",
    "sg:postcode":"57701",
    "sg:province":"SD",
    "sg:tags":[
        "counselor"
    ],
    "wof:name":"Straight Shooters Advg Agency",
    "wof:placetype":"venue"
},
  "geometry": {"coordinates":[-103.221633,44.112529],"type":"Point"}
}