{
  "type": "Feature",
  "properties": {
    "iso:country":"US",
    "sg:address":"33582 121st St",
    "sg:city":"Hosmer",
    "sg:classifiers":[
        {
            "category":"Farming",
            "subcategory":"Livestock Farm",
            "type":"Manufacturing & Wholesale Goods"
        }
    ],
    "sg:phone":"+1 605 283 2382",
    "sg:postcode":"57448",
    "sg:province":"SD",
    "sg:tags":[
        "beef",
        "feedlot",
        "cattle"
    ],
    "wof:name":"Kenneth Hieb",
    "wof:placetype":"venue"
},
  "geometry": {"coordinates":[-99.460735,45.636581],"type":"Point"}
}