{
  "type": "Feature",
  "properties": {
    "iso:country":"US",
    "sg:address":"446 W 4th St",
    "sg:city":"Winner",
    "sg:classifiers":[
        {
            "category":"Real Estate",
            "subcategory":"Real Estate Operator",
            "type":"Services"
        }
    ],
    "sg:phone":"+1 605 842 0988",
    "sg:postcode":"57580",
    "sg:province":"SD",
    "sg:tags":[
        "farm",
        "field",
        "property",
        "crop",
        "lessor"
    ],
    "wof:name":"Lawrence Neyens",
    "wof:placetype":"venue"
},
  "geometry": {"coordinates":[-99.862261,43.374499],"type":"Point"}
}