{
  "type": "Feature",
  "properties": {
    "iso:country":"US",
    "sg:address":"16841 398th Ave",
    "sg:city":"Frankfort",
    "sg:classifiers":[
        {
            "category":"Farming",
            "subcategory":"Farm",
            "type":"Manufacturing & Wholesale Goods"
        }
    ],
    "sg:phone":"+1 605 472 1373",
    "sg:postcode":"57440",
    "sg:province":"SD",
    "sg:tags":[
        "crop",
        "general"
    ],
    "wof:name":"Wayne Ragatz",
    "wof:placetype":"venue"
},
  "geometry": {"coordinates":[-98.268465,44.945437],"type":"Point"}
}