{
  "type": "Feature",
  "properties": {
    "iso:country":"US",
    "sg:address":"104 S Galena St",
    "sg:city":"Lead",
    "sg:classifiers":[
        {
            "category":"Building & Trades",
            "subcategory":"Construction",
            "type":"Services"
        }
    ],
    "sg:phone":"+1 605 584 2985",
    "sg:postcode":"57754",
    "sg:province":"SD",
    "sg:tags":[
        "house"
    ],
    "wof:name":"Black Hills Builders",
    "wof:placetype":"venue"
},
  "geometry": {"coordinates":[-103.768899,44.351072],"type":"Point"}
}