{
  "type": "Feature",
  "properties": {
    "addr:full":"46411 262nd St Hartford SD 57033",
    "addr:housenumber":"46411",
    "addr:postcode":"57033",
    "addr:street":"262Nd St",
    "iso:country":"US",
    "sg:address":"46411 262nd St",
    "sg:city":"Hartford",
    "sg:classifiers":[
        {
            "category":"Farming",
            "subcategory":"Farm",
            "type":"Manufacturing & Wholesale Goods"
        }
    ],
    "sg:phone":"+1 605 528 6347",
    "sg:postcode":"57033",
    "sg:province":"SD",
    "sg:tags":[
        "crop",
        "general"
    ],
    "wof:name":"Werhkamp Brothers",
    "wof:placetype":"venue"
},
  "geometry": {"coordinates":[-96.928884,43.587147],"type":"Point"}
}