{
  "type": "Feature",
  "properties": {
    "iso:country":"US",
    "sg:address":"103 E Main St",
    "sg:city":"Delmont",
    "sg:classifiers":[
        {
            "category":"Home & Garden",
            "subcategory":"Building Materials",
            "type":"Retail Goods"
        }
    ],
    "sg:phone":"+1 605 779 2791",
    "sg:postcode":"57330",
    "sg:province":"SD",
    "sg:tags":[
        "lumber"
    ],
    "wof:name":"Delmont Lumber Co",
    "wof:placetype":"venue"
},
  "geometry": {"coordinates":[-98.16150399999999,43.267473],"type":"Point"}
}