{
  "type": "Feature",
  "properties": {
    "addr:full":"401 E 8th St Sioux Falls SD 57103",
    "addr:housenumber":"401",
    "addr:postcode":"57103",
    "addr:street":"E 8Th St",
    "iso:country":"US",
    "sg:address":"401 E 8th St",
    "sg:city":"Sioux Falls",
    "sg:classifiers":[
        {
            "category":"Wholesale",
            "subcategory":"Machinery & Supplies",
            "type":"Manufacturing & Wholesale Goods"
        }
    ],
    "sg:phone":"+1 605 336 3127",
    "sg:postcode":"57103",
    "sg:province":"SD",
    "sg:tags":[
        "equipment",
        "industrial"
    ],
    "wof:name":"Nde",
    "wof:placetype":"venue"
},
  "geometry": {"coordinates":[-96.72122299999999,43.548626],"type":"Point"}
}