{
  "type": "Feature",
  "properties": {
    "iso:country":"US",
    "sg:address":"27090 Morton Ct",
    "sg:city":"Sioux Falls",
    "sg:classifiers":[
        {
            "category":"Wholesale",
            "subcategory":"Machinery & Supplies",
            "type":"Manufacturing & Wholesale Goods"
        }
    ],
    "sg:phone":"+1 605 368 5707",
    "sg:postcode":"57108",
    "sg:province":"SD",
    "sg:tags":[
        "equipment",
        "sales",
        "cleaning"
    ],
    "wof:name":"Midwest Cleaning Equipment",
    "wof:placetype":"venue"
},
  "geometry": {"coordinates":[-96.79566,43.461232],"type":"Point"}
}