{
  "type": "Feature",
  "properties": {
    "iso:country":"US",
    "sg:address":"105 Center Ave",
    "sg:city":"Philip",
    "sg:classifiers":[
        {
            "category":"Building & Trades",
            "subcategory":"Construction",
            "type":"Services"
        }
    ],
    "sg:phone":"+1 605 859 2472",
    "sg:postcode":"57567",
    "sg:province":"SD",
    "sg:tags":[
        "grading",
        "contractor"
    ],
    "wof:name":"Haakon County Highway Dept",
    "wof:placetype":"venue"
},
  "geometry": {"coordinates":[-101.66417800000001,44.039741],"type":"Point"}
}