{
  "type": "Feature",
  "properties": {
    "addr:full":"1801 S Valley View Rd Sioux Falls SD 57106",
    "addr:housenumber":"1801",
    "addr:postcode":"57106",
    "addr:street":"S Valley View Rd",
    "iso:country":"US",
    "sg:address":"1801 S Valley View Rd",
    "sg:city":"Sioux Falls",
    "sg:classifiers":[
        {
            "category":"Organizations",
            "subcategory":"Religious Organization",
            "type":"Services"
        }
    ],
    "sg:phone":"+1 605 362 8231",
    "sg:postcode":"57106",
    "sg:province":"SD",
    "wof:name":"Bethel Lutheran Church",
    "wof:placetype":"venue"
},
  "geometry": {"coordinates":[-96.800968,43.529071],"type":"Point"}
}