{
  "type": "Feature",
  "properties": {
    "iso:country":"US",
    "sg:address":"211 E 7th Ave",
    "sg:city":"Redfield",
    "sg:classifiers":[
        {
            "category":"Freight",
            "type":"Transportation"
        }
    ],
    "sg:phone":"+1 605 472 3196",
    "sg:postcode":"57469",
    "sg:province":"SD",
    "sg:tags":[
        "operator",
        "trucking"
    ],
    "wof:name":"Hartman Trucking",
    "wof:placetype":"venue"
},
  "geometry": {"coordinates":[-98.515083,44.875842],"type":"Point"}
}