{
  "type": "Feature",
  "properties": {
    "iso:country":"US",
    "sg:address":"938 Pebble Beach Dr",
    "sg:city":"North Sioux City",
    "sg:phone":"+1 702 548 6681",
    "sg:postcode":"57049",
    "sg:province":"SD",
    "sg:tags":[
        "wholesale",
        "industrial",
        "equipment"
    ],
    "wof:name":"Gentech International Inc",
    "wof:placetype":"venue"
},
  "geometry": {"coordinates":[-96.48483,42.485243],"type":"Point"}
}