{
  "type": "Feature",
  "properties": {
    "iso:country":"US",
    "sg:address":"4100 S Cliff Ave",
    "sg:city":"Sioux Falls",
    "sg:phone":"+1 605 334 3102",
    "sg:postcode":"57103",
    "sg:province":"SD",
    "sg:tags":[
        "farm",
        "corn"
    ],
    "wof:name":"Vanloh John",
    "wof:placetype":"venue"
},
  "geometry": {"coordinates":[-96.71101299999999,43.506755],"type":"Point"}
}