{
  "type": "Feature",
  "properties": {
    "iso:country":"US",
    "sg:address":"45225 287th St",
    "sg:city":"Hurley",
    "sg:classifiers":[
        {
            "category":"Farming",
            "subcategory":"Livestock Farm",
            "type":"Manufacturing & Wholesale Goods"
        }
    ],
    "sg:phone":"+1 605 327 3599",
    "sg:postcode":"57036",
    "sg:province":"SD",
    "sg:tags":[
        "feedlot",
        "corn",
        "soybean",
        "beef",
        "cattle"
    ],
    "wof:name":"Greg Farrar",
    "wof:placetype":"venue"
},
  "geometry": {"coordinates":[-97.14771500000001,43.227986],"type":"Point"}
}