{
  "type": "Feature",
  "properties": {
    "iso:country":"US",
    "sg:address":"11 Elm St",
    "sg:city":"Vermillion",
    "sg:classifiers":[
        {
            "category":"Insurance",
            "subcategory":"Insurance Agent",
            "type":"Services"
        }
    ],
    "sg:phone":"+1 605 624 5489",
    "sg:postcode":"57069",
    "sg:province":"SD",
    "wof:name":"State Farm Insurance",
    "wof:placetype":"venue"
},
  "geometry": {"coordinates":[-96.930494,42.7798],"type":"Point"}
}