{
  "type": "Feature",
  "properties": {
    "addr:full":"1515 N Sanborn Blvd Mitchell SD 57301",
    "addr:housenumber":"1515",
    "addr:postcode":"57301",
    "addr:street":"N Sanborn Blvd",
    "iso:country":"US",
    "sg:address":"1515 N Sanborn Blvd",
    "sg:city":"Mitchell",
    "sg:classifiers":[
        {
            "category":"Professional",
            "subcategory":"Engineering",
            "type":"Services"
        }
    ],
    "sg:phone":"+1 605 996 9646",
    "sg:postcode":"57301",
    "sg:province":"SD",
    "sg:tags":[
        "engineer"
    ],
    "sg:website":"www.martin-group.com",
    "wof:name":"Martin Group Inc",
    "wof:placetype":"venue"
},
  "geometry": {"coordinates":[-98.029994,43.723691],"type":"Point"}
}