{
  "type": "Feature",
  "properties": {
    "addr:full":"130 N Sycamore Ave Sioux Falls SD 57110",
    "addr:housenumber":"130",
    "addr:postcode":"57110",
    "addr:street":"N Sycamore Ave",
    "iso:country":"US",
    "sg:address":"130 N Sycamore Ave",
    "sg:city":"Sioux Falls",
    "sg:classifiers":[
        {
            "category":"Wholesale",
            "subcategory":"Sporting Goods",
            "type":"Manufacturing & Wholesale Goods"
        }
    ],
    "sg:phone":"+1 605 335 4111",
    "sg:postcode":"57110",
    "sg:province":"SD",
    "wof:name":"In Zone Sports",
    "wof:placetype":"venue"
},
  "geometry": {"coordinates":[-96.671426,43.548195],"type":"Point"}
}