{
  "type": "Feature",
  "properties": {
    "addr:full":"5120 S Cliff Ave Sioux Falls SD 57108",
    "addr:housenumber":"5120",
    "addr:postcode":"57108",
    "addr:street":"S Cliff Ave",
    "iso:country":"US",
    "sg:address":"5120 S Cliff Ave",
    "sg:city":"Sioux Falls",
    "sg:classifiers":[
        {
            "category":"Health Services",
            "subcategory":"Doctor",
            "type":"Services"
        }
    ],
    "sg:phone":"+1 605 334 2607",
    "sg:postcode":"57108",
    "sg:province":"SD",
    "sg:tags":[
        "dentist"
    ],
    "wof:name":"Troy L Keyes DDS",
    "wof:placetype":"venue"
},
  "geometry": {"coordinates":[-96.70760900000001,43.496822],"type":"Point"}
}