{
  "type": "Feature",
  "properties": {
    "iso:country":"US",
    "sg:address":"710 N Lacrosse St",
    "sg:city":"Rapid City",
    "sg:classifiers":[
        {
            "category":"Food & Beverages",
            "subcategory":"Groceries & Convenience Stores",
            "type":"Retail Goods"
        }
    ],
    "sg:phone":"+1 605 341 5591",
    "sg:postcode":"57701",
    "sg:province":"SD",
    "sg:tags":[
        "grocer"
    ],
    "wof:name":"Benja's Mexican Store",
    "wof:placetype":"venue"
},
  "geometry": {"coordinates":[-103.201632,44.091037],"type":"Point"}
}