{
  "type": "Feature",
  "properties": {
    "iso:country":"US",
    "sg:address":"27147 365th Ave",
    "sg:city":"Platte",
    "sg:classifiers":[
        {
            "category":"Restaurant",
            "type":"Food & Drink"
        }
    ],
    "sg:phone":"+1 605 337 3250",
    "sg:postcode":"57369",
    "sg:province":"SD",
    "sg:tags":[
        "eating"
    ],
    "wof:name":"Pizza Ranch",
    "wof:placetype":"venue"
},
  "geometry": {"coordinates":[-98.884728,43.45005],"type":"Point"}
}