{
  "type": "Feature",
  "properties": {
    "iso:country":"US",
    "sg:address":"16315 454th Ave",
    "sg:city":"Watertown",
    "sg:classifiers":[
        {
            "category":"Farming",
            "subcategory":"Dairy Farm",
            "type":"Manufacturing & Wholesale Goods"
        }
    ],
    "sg:phone":"+1 605 882 3936",
    "sg:postcode":"57201",
    "sg:province":"SD",
    "wof:name":"Conan Stein",
    "wof:placetype":"venue"
},
  "geometry": {"coordinates":[-97.126441,45.018405],"type":"Point"}
}