{
  "type": "Feature",
  "properties": {
    "iso:country":"US",
    "sg:address":"400 W Redwood Blvd",
    "sg:city":"Brandon",
    "sg:classifiers":[
        {
            "category":"Freight",
            "type":"Transportation"
        }
    ],
    "sg:phone":"+1 605 582 2007",
    "sg:postcode":"57005",
    "sg:province":"SD",
    "sg:tags":[
        "trucking"
    ],
    "wof:name":"Blachowske Truckline Inc",
    "wof:placetype":"venue"
},
  "geometry": {"coordinates":[-96.59222800000001,43.601783],"type":"Point"}
}