{
  "type": "Feature",
  "properties": {
    "iso:country":"US",
    "sg:address":"419 E Juniper Ave",
    "sg:city":"Mitchell",
    "sg:classifiers":[
        {
            "category":"Building & Trades",
            "subcategory":"Electrical",
            "type":"Services"
        }
    ],
    "sg:phone":"+1 605 995 0595",
    "sg:postcode":"57301",
    "sg:province":"SD",
    "sg:tags":[
        "electric",
        "contractor"
    ],
    "wof:name":"T K Electric",
    "wof:placetype":"venue"
},
  "geometry": {"coordinates":[-98.020126,43.69911],"type":"Point"}
}