{
  "type": "Feature",
  "properties": {
    "iso:country":"US",
    "sg:address":"2725 Diamond Dr",
    "sg:city":"Spearfish",
    "sg:classifiers":[
        {
            "category":"Retail",
            "subcategory":"Auto Repair",
            "type":"Services"
        }
    ],
    "sg:phone":"+1 605 642 4326",
    "sg:postcode":"57783",
    "sg:province":"SD",
    "sg:tags":[
        "wrecker"
    ],
    "wof:name":"Johnny's Towing",
    "wof:placetype":"venue"
},
  "geometry": {"coordinates":[-103.901472,44.517887],"type":"Point"}
}