{
  "type": "Feature",
  "properties": {
    "iso:country":"US",
    "sg:address":"901 N Spring Ave",
    "sg:city":"Sioux Falls",
    "sg:classifiers":[
        {
            "category":"Freight",
            "type":"Transportation"
        }
    ],
    "sg:phone":"+1 605 334 5211",
    "sg:postcode":"57104",
    "sg:province":"SD",
    "sg:tags":[
        "broker",
        "trucking"
    ],
    "wof:name":"Cid Brokerage",
    "wof:placetype":"venue"
},
  "geometry": {"coordinates":[-96.732843,43.55903],"type":"Point"}
}