{
  "type": "Feature",
  "properties": {
    "addr:full":"1110 E Sioux Ave Pierre SD 57501",
    "addr:housenumber":"1110",
    "addr:postcode":"57501",
    "addr:street":"E Sioux Ave",
    "iso:country":"US",
    "sg:address":"1110 E Sioux Ave",
    "sg:city":"Pierre",
    "sg:classifiers":[
        {
            "category":"Wholesale",
            "subcategory":"Office Equipment",
            "type":"Manufacturing & Wholesale Goods"
        }
    ],
    "sg:phone":"+1 605 224 7327",
    "sg:postcode":"57501",
    "sg:province":"SD",
    "sg:tags":[
        "machine",
        "duplicating",
        "copying"
    ],
    "sg:website":"www.bbpsd.com",
    "wof:name":"Best Business Products Inc",
    "wof:placetype":"venue"
},
  "geometry": {"coordinates":[-100.33748199999999,44.360407],"type":"Point"}
}