{
  "type": "Feature",
  "properties": {
    "addr:full":"501 4th St Wilmot SD 57279",
    "addr:housenumber":"501",
    "addr:postcode":"57279",
    "addr:street":"4Th St",
    "iso:country":"US",
    "sg:address":"501 4th St",
    "sg:city":"Wilmot",
    "sg:classifiers":[
        {
            "category":"Health Services",
            "subcategory":"Nursing And Care Facility",
            "type":"Services"
        }
    ],
    "sg:phone":"+1 605 938 4418",
    "sg:postcode":"57279",
    "sg:province":"SD",
    "sg:tags":[
        "intermediate"
    ],
    "wof:name":"Wilmot Care Center",
    "wof:placetype":"venue"
},
  "geometry": {"coordinates":[-96.86072299999999,45.411739],"type":"Point"}
}