{
  "type": "Feature",
  "properties": {
    "iso:country":"US",
    "sg:address":"1691 N Main St",
    "sg:city":"Mitchell",
    "sg:classifiers":[
        {
            "category":"Restaurant",
            "type":"Food & Drink"
        }
    ],
    "sg:phone":"+1 605 996 7538",
    "sg:postcode":"57301",
    "sg:province":"SD",
    "sg:tags":[
        "eating"
    ],
    "wof:name":"Fanny Horners Eating Estab",
    "wof:placetype":"venue"
},
  "geometry": {"coordinates":[-98.025842,43.728417],"type":"Point"}
}