{
  "type": "Feature",
  "properties": {
    "addr:full":"400 S Splitrock Blvd Brandon SD 57005",
    "addr:housenumber":"400",
    "addr:postcode":"57005",
    "addr:street":"S Splitrock Blvd",
    "iso:country":"US",
    "sg:address":"400 S Splitrock Blvd",
    "sg:city":"Brandon",
    "sg:classifiers":[
        {
            "category":"Organizations",
            "subcategory":"Religious Organization",
            "type":"Services"
        }
    ],
    "sg:phone":"+1 605 582 2248",
    "sg:postcode":"57005",
    "sg:province":"SD",
    "sg:tags":[
        "church"
    ],
    "wof:name":"Brandon Valley Baptist Church",
    "wof:placetype":"venue"
},
  "geometry": {"coordinates":[-96.572205,43.591031],"type":"Point"}
}