{
  "type": "Feature",
  "properties": {
    "iso:country":"US",
    "sg:address":"1507 5th St SE",
    "sg:city":"Watertown",
    "sg:classifiers":[
        {
            "category":"Building & Trades",
            "subcategory":"Construction",
            "type":"Services"
        }
    ],
    "sg:phone":"+1 605 882 0552",
    "sg:postcode":"57201",
    "sg:province":"SD",
    "sg:tags":[
        "house"
    ],
    "wof:name":"81 Welding Inc",
    "wof:placetype":"venue"
},
  "geometry": {"coordinates":[-97.109029,44.883429],"type":"Point"}
}