{
  "type": "Feature",
  "properties": {
    "iso:country":"US",
    "sg:address":"409 12th St S",
    "sg:city":"Brookings",
    "sg:classifiers":[
        {
            "category":"Home & Garden",
            "subcategory":"Carpets & Floor Coverings",
            "type":"Retail Goods"
        }
    ],
    "sg:phone":"+1 605 692 7377",
    "sg:postcode":"57006",
    "sg:province":"SD",
    "sg:tags":[
        "dealer",
        "rug"
    ],
    "wof:name":"Barrett's Flooring",
    "wof:placetype":"venue"
},
  "geometry": {"coordinates":[-96.798608,44.29253],"type":"Point"}
}