{
  "type": "Feature",
  "properties": {
    "addr:full":"20320 445th Ave Lake Preston SD 57249",
    "addr:housenumber":"20320",
    "addr:postcode":"57249",
    "addr:street":"445Th Ave",
    "iso:country":"US",
    "sg:address":"20320 445th Ave",
    "sg:city":"Lake Preston",
    "sg:classifiers":[
        {
            "category":"Organizations",
            "subcategory":"Religious Organization",
            "type":"Services"
        }
    ],
    "sg:phone":"+1 605 847 4545",
    "sg:postcode":"57249",
    "sg:province":"SD",
    "wof:name":"North Preston Church",
    "wof:placetype":"venue"
},
  "geometry": {"coordinates":[-97.31008799999999,44.437695],"type":"Point"}
}