{
  "type": "Feature",
  "properties": {
    "iso:country":"US",
    "sg:address":"3300 S Holly Ave",
    "sg:city":"Sioux Falls",
    "sg:classifiers":[
        {
            "category":"Real Estate",
            "subcategory":"Real Estate Agent",
            "type":"Services"
        }
    ],
    "sg:phone":"+1 605 275 4955",
    "sg:postcode":"57105",
    "sg:province":"SD",
    "wof:name":"Home Team Real Estate LLC",
    "wof:placetype":"venue"
},
  "geometry": {"coordinates":[-96.754745,43.515779],"type":"Point"}
}