{
  "type": "Feature",
  "properties": {
    "iso:country":"US",
    "sg:address":"200 S Phillips Ave",
    "sg:city":"Sioux Falls",
    "sg:classifiers":[
        {
            "category":"Farming",
            "subcategory":"Farm",
            "type":"Manufacturing & Wholesale Goods"
        }
    ],
    "sg:phone":"+1 605 575 2687",
    "sg:postcode":"57104",
    "sg:province":"SD",
    "sg:tags":[
        "crop",
        "general"
    ],
    "wof:name":"Four Bar Ranch LLC",
    "wof:placetype":"venue"
},
  "geometry": {"coordinates":[-96.72678999999999,43.544689],"type":"Point"}
}