{
  "type": "Feature",
  "properties": {
    "iso:country":"US",
    "sg:address":"2604 S 4th Ave",
    "sg:city":"Sioux Falls",
    "sg:classifiers":[
        {
            "category":"Real Estate",
            "subcategory":"Real Estate Agent",
            "type":"Services"
        }
    ],
    "sg:phone":"+1 605 334 7733",
    "sg:postcode":"57105",
    "sg:province":"SD",
    "sg:tags":[
        "management"
    ],
    "wof:name":"Cook Realty",
    "wof:placetype":"venue"
},
  "geometry": {"coordinates":[-96.721121,43.520327],"type":"Point"}
}