{
  "type": "Feature",
  "properties": {
    "addr:full":"31672 282nd St Winner SD 57580",
    "addr:housenumber":"31672",
    "addr:postcode":"57580",
    "addr:street":"282Nd St",
    "iso:country":"US",
    "sg:address":"31672 282nd St",
    "sg:city":"Winner",
    "sg:phone":"+1 605 842 1670",
    "sg:postcode":"57580",
    "sg:province":"SD",
    "sg:tags":[
        "farm",
        "corn"
    ],
    "wof:name":"Albert Novotny",
    "wof:placetype":"venue"
},
  "geometry": {"coordinates":[-99.84593700000001,43.314009],"type":"Point"}
}