{
  "type": "Feature",
  "properties": {
    "iso:country":"US",
    "sg:address":"7104 W 41st St",
    "sg:city":"Sioux Falls",
    "sg:classifiers":[
        {
            "category":"Restaurant",
            "type":"Food & Drink"
        }
    ],
    "sg:menulink":"http://www.allmenus.com/sd/wayne/123022-quiznos-sub/menu/",
    "sg:phone":"+1 605 361 5695",
    "sg:postcode":"57106",
    "sg:province":"SD",
    "sg:tags":[
        "wrap",
        "american",
        "sandwich"
    ],
    "wof:name":"Quiznos Sub",
    "wof:placetype":"venue"
},
  "geometry": {"coordinates":[-96.81584100000001,43.514806],"type":"Point"}
}