{
  "type": "Feature",
  "properties": {
    "addr:full":"1125 Kennel Dr Rapid City SD 57703",
    "addr:housenumber":"1125",
    "addr:postcode":"57703",
    "addr:street":"Kennel Dr",
    "iso:country":"US",
    "sg:address":"1125 Kennel Dr",
    "sg:city":"Rapid City",
    "sg:classifiers":[
        {
            "category":"Retail",
            "subcategory":"Repair Shop",
            "type":"Services"
        }
    ],
    "sg:phone":"+1 605 348 3946",
    "sg:postcode":"57703",
    "sg:province":"SD",
    "sg:tags":[
        "scooter",
        "motorcycle",
        "motor"
    ],
    "wof:name":"Roscos Motorcycle & Atv Repair",
    "wof:placetype":"venue"
},
  "geometry": {"coordinates":[-103.183155,44.073852],"type":"Point"}
}