{
  "type": "Feature",
  "properties": {
    "addr:full":"30038 408th Ave Avon SD 57315",
    "addr:housenumber":"30038",
    "addr:postcode":"57315",
    "addr:street":"408Th Ave",
    "iso:country":"US",
    "sg:address":"30038 408th Ave",
    "sg:city":"Avon",
    "sg:classifiers":[
        {
            "category":"Retail",
            "subcategory":"Repair Shop",
            "type":"Services"
        }
    ],
    "sg:phone":"+1 605 286 3359",
    "sg:postcode":"57315",
    "sg:province":"SD",
    "wof:name":"Williams Septic Service",
    "wof:placetype":"venue"
},
  "geometry": {"coordinates":[-98.030056,43.033575],"type":"Point"}
}