{
  "type": "Feature",
  "properties": {
    "iso:country":"US",
    "sg:address":"604 Blair St",
    "sg:city":"Keystone",
    "sg:classifiers":[
        {
            "category":"Professional",
            "subcategory":"Business Services",
            "type":"Services"
        }
    ],
    "sg:phone":"+1 605 666 4847",
    "sg:postcode":"57751",
    "sg:province":"SD",
    "sg:tags":[
        "information",
        "bureau",
        "convention"
    ],
    "wof:name":"Big Thunder Gold Mine",
    "wof:placetype":"venue"
},
  "geometry": {"coordinates":[-103.418063,43.894778],"type":"Point"}
}