{
  "type": "Feature",
  "properties": {
    "addr:full":"4023 Main Ave S Brookings SD 57006",
    "addr:housenumber":"4023",
    "addr:postcode":"57006",
    "addr:street":"Main Ave S",
    "iso:country":"US",
    "sg:address":"4023 Main Ave S",
    "sg:city":"Brookings",
    "sg:classifiers":[
        {
            "category":"Freight",
            "type":"Transportation"
        }
    ],
    "sg:phone":"+1 605 693 3640",
    "sg:postcode":"57006",
    "sg:province":"SD",
    "sg:tags":[
        "operator",
        "local",
        "trucking"
    ],
    "wof:name":"Dan Foster Trucking",
    "wof:placetype":"venue"
},
  "geometry": {"coordinates":[-96.79822799999999,44.258152],"type":"Point"}
}