{
  "type": "Feature",
  "properties": {
    "iso:country":"US",
    "sg:address":"19328 466th Ave",
    "sg:city":"Estelline",
    "sg:phone":"+1 605 873 2297",
    "sg:postcode":"57234",
    "sg:province":"SD",
    "sg:tags":[
        "beef",
        "farm",
        "cash",
        "grain",
        "cattle",
        "feedlot"
    ],
    "wof:name":"Doug Pedersen",
    "wof:placetype":"venue"
},
  "geometry": {"coordinates":[-96.885559,44.580149],"type":"Point"}
}