{
  "type": "Feature",
  "properties": {
    "addr:full":"2101 S West Ave Sioux Falls SD 57105",
    "addr:housenumber":"2101",
    "addr:postcode":"57105",
    "addr:street":"S West Ave",
    "iso:country":"US",
    "sg:address":"2101 S West Ave",
    "sg:city":"Sioux Falls",
    "sg:classifiers":[
        {
            "category":"Education",
            "subcategory":"School",
            "type":"Public Place"
        }
    ],
    "sg:phone":"+1 605 367 4282",
    "sg:postcode":"57105",
    "sg:province":"SD",
    "wof:name":"Indian Education",
    "wof:placetype":"venue"
},
  "geometry": {"coordinates":[-96.746273,43.526538],"type":"Point"}
}