{
  "type": "Feature",
  "properties": {
    "addr:full":"1616 3rd Ave NE Watertown SD 57201",
    "addr:housenumber":"1616",
    "addr:postcode":"57201",
    "addr:street":"3Rd Ave Ne",
    "iso:country":"US",
    "sg:address":"1616 3rd Ave NE",
    "sg:city":"Watertown",
    "sg:classifiers":[
        {
            "category":"Organizations",
            "subcategory":"Religious Organization",
            "type":"Services"
        }
    ],
    "sg:phone":"+1 605 886 3779",
    "sg:postcode":"57201",
    "sg:province":"SD",
    "sg:tags":[
        "church"
    ],
    "sg:website":"www.watertownwesleyan.com",
    "wof:name":"Wesleyan Church",
    "wof:placetype":"venue"
},
  "geometry": {"coordinates":[-97.090367,44.904543],"type":"Point"}
}