{
  "type": "Feature",
  "properties": {
    "addr:full":"602 Main St Midland SD 57551",
    "addr:housenumber":"602",
    "addr:postcode":"57551",
    "addr:street":"Main St",
    "iso:country":"US",
    "sg:address":"602 Main St",
    "sg:city":"Midland",
    "sg:classifiers":[
        {
            "category":"Travel",
            "subcategory":"Hotels & Motels",
            "type":"Entertainment"
        }
    ],
    "sg:phone":"+1 605 843 2802",
    "sg:postcode":"57551",
    "sg:province":"SD",
    "wof:name":"Stroppel Inn",
    "wof:placetype":"venue"
},
  "geometry": {"coordinates":[-101.741606,43.175184],"type":"Point"}
}