{
  "type": "Feature",
  "properties": {
    "iso:country":"US",
    "sg:address":"46587 US Hwy 18",
    "sg:city":"Lennox",
    "sg:classifiers":[
        {
            "category":"Organizations",
            "subcategory":"Religious Organization",
            "type":"Services"
        }
    ],
    "sg:phone":"+1 605 647 5868",
    "sg:postcode":"57039",
    "sg:province":"SD",
    "sg:tags":[
        "church"
    ],
    "wof:name":"Delaware Reformed Church",
    "wof:placetype":"venue"
},
  "geometry": {"coordinates":[-96.888613,43.257951],"type":"Point"}
}