{
  "type": "Feature",
  "properties": {
    "iso:country":"US",
    "sg:address":"202 W 7th St",
    "sg:city":"Woonsocket",
    "sg:classifiers":[
        {
            "category":"Organizations",
            "subcategory":"Religious Organization",
            "type":"Services"
        }
    ],
    "sg:phone":"+1 605 796 4429",
    "sg:postcode":"57385",
    "sg:province":"SD",
    "wof:name":"Bethany Lutheran Church",
    "wof:placetype":"venue"
},
  "geometry": {"coordinates":[-98.273802,44.054015],"type":"Point"}
}