{
  "type": "Feature",
  "properties": {
    "iso:country":"US",
    "sg:address":"15935 Bixby Rd",
    "sg:city":"Faith",
    "sg:classifiers":[
        {
            "category":"Farming",
            "subcategory":"Livestock Farm",
            "type":"Manufacturing & Wholesale Goods"
        }
    ],
    "sg:phone":"+1 605 748 2412",
    "sg:postcode":"57626",
    "sg:province":"SD",
    "sg:tags":[
        "feedlot",
        "field",
        "crop",
        "beef",
        "cattle"
    ],
    "wof:name":"Fairmview Ranch",
    "wof:placetype":"venue"
},
  "geometry": {"coordinates":[-102.584761,45.091465],"type":"Point"}
}