{
  "type": "Feature",
  "properties": {
    "iso:country":"US",
    "sg:address":"812 S 12th St",
    "sg:city":"Aberdeen",
    "sg:classifiers":[
        {
            "category":"Building & Trades",
            "subcategory":"Construction",
            "type":"Services"
        }
    ],
    "sg:phone":"+1 605 225 5642",
    "sg:postcode":"57401",
    "sg:province":"SD",
    "sg:tags":[
        "house",
        "construct",
        "contractor"
    ],
    "wof:name":"Borchard & Associates",
    "wof:placetype":"venue"
},
  "geometry": {"coordinates":[-98.50568,45.457024],"type":"Point"}
}