{
  "type": "Feature",
  "properties": {
    "addr:full":"117 S Main St Chamberlain SD 57325",
    "addr:housenumber":"117",
    "addr:postcode":"57325",
    "addr:street":"S Main St",
    "iso:country":"US",
    "sg:address":"117 S Main St",
    "sg:city":"Chamberlain",
    "sg:classifiers":[
        {
            "category":"Restaurant",
            "type":"Food & Drink"
        }
    ],
    "sg:phone":"+1 605 734 5481",
    "sg:postcode":"57325",
    "sg:province":"SD",
    "sg:tags":[
        "eating"
    ],
    "wof:name":"Anchor Grille",
    "wof:placetype":"venue"
},
  "geometry": {"coordinates":[-99.33035099999999,43.810592],"type":"Point"}
}