{
  "type": "Feature",
  "properties": {
    "iso:country":"US",
    "sg:address":"235 E Railroad Ave",
    "sg:city":"Groton",
    "sg:classifiers":[
        {
            "category":"Retail",
            "subcategory":"Repair Shop",
            "type":"Services"
        }
    ],
    "sg:phone":"+1 605 397 4511",
    "sg:postcode":"57445",
    "sg:province":"SD",
    "sg:tags":[
        "taxidermist"
    ],
    "wof:name":"Rivers Edge Taxidermy",
    "wof:placetype":"venue"
},
  "geometry": {"coordinates":[-98.099641,45.44539],"type":"Point"}
}