{
  "type": "Feature",
  "properties": {
    "iso:country":"US",
    "sg:address":"213 S Egan Ave",
    "sg:city":"Madison",
    "sg:classifiers":[
        {
            "category":"Home & Garden",
            "subcategory":"Household Appliances",
            "type":"Retail Goods"
        }
    ],
    "sg:phone":"+1 605 256 2752",
    "sg:postcode":"57042",
    "sg:province":"SD",
    "wof:name":"Lakebrook TV & Appliance Inc",
    "wof:placetype":"venue"
},
  "geometry": {"coordinates":[-97.114096,44.003845],"type":"Point"}
}