{
  "type": "Feature",
  "properties": {
    "iso:country":"US",
    "sg:address":"2805 5th St",
    "sg:city":"Rapid City",
    "sg:classifiers":[
        {
            "category":"Health Services",
            "subcategory":"Doctor",
            "type":"Services"
        }
    ],
    "sg:phone":"+1 605 348 1084",
    "sg:postcode":"57701",
    "sg:province":"SD",
    "sg:tags":[
        "medical"
    ],
    "wof:name":"Andrew R Yamada MD",
    "wof:placetype":"venue"
},
  "geometry": {"coordinates":[-103.227377,44.057644],"type":"Point"}
}