{
  "type": "Feature",
  "properties": {
    "iso:country":"US",
    "sg:address":"905 N Madison Ave",
    "sg:city":"Pierre",
    "sg:classifiers":[
        {
            "category":"Farming",
            "subcategory":"Livestock Farm",
            "type":"Manufacturing & Wholesale Goods"
        }
    ],
    "sg:phone":"+1 605 224 5588",
    "sg:postcode":"57501",
    "sg:province":"SD",
    "sg:tags":[
        "beef",
        "feedlot",
        "cattle"
    ],
    "wof:name":"Gaylord Sonnenschein Farms",
    "wof:placetype":"venue"
},
  "geometry": {"coordinates":[-100.33448799999999,44.370448],"type":"Point"}
}