{
  "type": "Feature",
  "properties": {
    "iso:country":"US",
    "sg:address":"21152 349th Ave",
    "sg:city":"Ree Heights",
    "sg:classifiers":[
        {
            "category":"Farming",
            "subcategory":"Livestock Farm",
            "type":"Manufacturing & Wholesale Goods"
        }
    ],
    "sg:phone":"+1 605 943 5571",
    "sg:postcode":"57371",
    "sg:province":"SD",
    "sg:tags":[
        "beef",
        "feedlot",
        "cattle"
    ],
    "wof:name":"Rod Rogers",
    "wof:placetype":"venue"
},
  "geometry": {"coordinates":[-99.20558,44.319248],"type":"Point"}
}