{
  "type": "Feature",
  "properties": {
    "addr:full":"305 S Main St Milbank SD 57252",
    "addr:housenumber":"305",
    "addr:postcode":"57252",
    "addr:street":"S Main St",
    "iso:country":"US",
    "sg:address":"305 S Main St",
    "sg:city":"Milbank",
    "sg:classifiers":[
        {
            "category":"Health Services",
            "subcategory":"Chiropractor",
            "type":"Services"
        }
    ],
    "sg:phone":"+1 605 432 6431",
    "sg:postcode":"57252",
    "sg:province":"SD",
    "wof:name":"Hunt Chiropractic Clinic",
    "wof:placetype":"venue"
},
  "geometry": {"coordinates":[-96.635794,45.219898],"type":"Point"}
}