{
  "type": "Feature",
  "properties": {
    "iso:country":"US",
    "sg:address":"130 N 3rd Ave",
    "sg:city":"Olivet",
    "sg:classifiers":[
        {
            "category":"Professional",
            "subcategory":"Lawyer & Legal Services",
            "type":"Services"
        }
    ],
    "sg:phone":"+1 605 387 5530",
    "sg:postcode":"57052",
    "sg:province":"SD",
    "sg:tags":[
        "attorney"
    ],
    "wof:name":"Glenn L Roth Law Offices",
    "wof:placetype":"venue"
},
  "geometry": {"coordinates":[-97.675369,43.240815],"type":"Point"}
}