{
  "type": "Feature",
  "properties": {
    "iso:country":"US",
    "sg:address":"403 N Plum St",
    "sg:city":"Vermillion",
    "sg:classifiers":[
        {
            "category":"Health Services",
            "subcategory":"Health Practitioner",
            "type":"Services"
        }
    ],
    "sg:phone":"+1 605 624 0090",
    "sg:postcode":"57069",
    "sg:province":"SD",
    "sg:tags":[
        "psychologist"
    ],
    "wof:name":"Vermillion Counseling",
    "wof:placetype":"venue"
},
  "geometry": {"coordinates":[-96.919889,42.78552],"type":"Point"}
}