{
  "type": "Feature",
  "properties": {
    "iso:country":"US",
    "sg:address":"47147 258th St",
    "sg:city":"Sioux Falls",
    "sg:classifiers":[
        {
            "category":"Building & Trades",
            "subcategory":"Electrical",
            "type":"Services"
        }
    ],
    "sg:phone":"+1 605 543 5842",
    "sg:postcode":"57107",
    "sg:province":"SD",
    "sg:tags":[
        "electrical",
        "contractor"
    ],
    "wof:name":"Hoekman Electric",
    "wof:placetype":"venue"
},
  "geometry": {"coordinates":[-96.786174,43.645309],"type":"Point"}
}