{
  "type": "Feature",
  "properties": {
    "iso:country":"US",
    "sg:address":"31301 US Hwy 18",
    "sg:city":"Winner",
    "sg:classifiers":[
        {
            "category":"Autos & Motor Vehicles",
            "subcategory":"Automobile Sales",
            "type":"Retail Goods"
        },
        {
            "category":"Retail",
            "subcategory":"Auto Repair",
            "type":"Services"
        }
    ],
    "sg:phone":"+1 605 842 2054",
    "sg:postcode":"57580",
    "sg:province":"SD",
    "sg:tags":[
        "wrecker",
        "business",
        "general"
    ],
    "wof:name":"Wayne's Auto Salvage Auto Prts",
    "wof:placetype":"venue"
},
  "geometry": {"coordinates":[-99.9096,43.383626],"type":"Point"}
}