{
  "type": "Feature",
  "properties": {
    "iso:country":"US",
    "sg:address":"1339 4th St",
    "sg:city":"Brookings",
    "sg:classifiers":[
        {
            "category":"Professional",
            "subcategory":"Computer Services",
            "type":"Services"
        }
    ],
    "sg:phone":"+1 605 697 6097",
    "sg:postcode":"57006",
    "sg:province":"SD",
    "sg:tags":[
        "related"
    ],
    "wof:name":"Eng & Associates",
    "wof:placetype":"venue"
},
  "geometry": {"coordinates":[-96.78262100000001,44.309156],"type":"Point"}
}