{
  "type": "Feature",
  "properties": {
    "addr:full":"4605 S Louise Ave Sioux Falls SD 57106",
    "addr:housenumber":"4605",
    "addr:postcode":"57106",
    "addr:street":"S Louise Ave",
    "iso:country":"US",
    "sg:address":"4605 S Louise Ave",
    "sg:city":"Sioux Falls",
    "sg:classifiers":[
        {
            "category":"Insurance",
            "subcategory":"Insurance Agent",
            "type":"Services"
        }
    ],
    "sg:phone":"+1 605 361 6097",
    "sg:postcode":"57106",
    "sg:province":"SD",
    "wof:name":"Deb Strasser",
    "wof:placetype":"venue"
},
  "geometry": {"coordinates":[-96.771072,43.502],"type":"Point"}
}