{
  "type": "Feature",
  "properties": {
    "iso:country":"US",
    "sg:address":"2413 Maple Ave",
    "sg:city":"Rapid City",
    "sg:classifiers":[
        {
            "category":"Recreation",
            "type":"Entertainment"
        }
    ],
    "sg:phone":"+1 605 343 4010",
    "sg:postcode":"57701",
    "sg:province":"SD",
    "sg:tags":[
        "paint",
        "ball",
        "sport"
    ],
    "wof:name":"Ballisticks",
    "wof:placetype":"venue"
},
  "geometry": {"coordinates":[-103.213082,44.061137],"type":"Point"}
}