{
  "type": "Feature",
  "properties": {
    "iso:country":"US",
    "sg:address":"516 W 15th Ave",
    "sg:city":"Mitchell",
    "sg:classifiers":[
        {
            "category":"Organizations",
            "subcategory":"Professional Association",
            "type":"Services"
        }
    ],
    "sg:phone":"+1 605 996 6920",
    "sg:postcode":"57301",
    "sg:province":"SD",
    "wof:name":"Loyal Order Of Moose",
    "wof:placetype":"venue"
},
  "geometry": {"coordinates":[-98.031244,43.723789],"type":"Point"}
}