{
  "type": "Feature",
  "properties": {
    "iso:country":"US",
    "sg:address":"314 S Main St",
    "sg:city":"Aberdeen",
    "sg:classifiers":[
        {
            "category":"Education",
            "subcategory":"School",
            "type":"Public Place"
        }
    ],
    "sg:phone":"+1 605 225 8333",
    "sg:postcode":"57401",
    "sg:province":"SD",
    "wof:name":"Aberdeehn Public Schools Found",
    "wof:placetype":"venue"
},
  "geometry": {"coordinates":[-98.488109,45.461982],"type":"Point"}
}