{
  "type": "Feature",
  "properties": {
    "iso:country":"US",
    "sg:address":"120 Knollwood Dr",
    "sg:city":"Rapid City",
    "sg:classifiers":[
        {
            "category":"Professional",
            "subcategory":"Lawyer & Legal Services",
            "type":"Services"
        }
    ],
    "sg:phone":"+1 605 341 7971",
    "sg:postcode":"57701",
    "sg:province":"SD",
    "sg:tags":[
        "attorney"
    ],
    "wof:name":"Feehan & Cline",
    "wof:placetype":"venue"
},
  "geometry": {"coordinates":[-103.216432,44.103029],"type":"Point"}
}