{
  "type": "Feature",
  "properties": {
    "iso:country":"US",
    "sg:address":"141 W 3rd St",
    "sg:city":"Winner",
    "sg:classifiers":[
        {
            "category":"Insurance",
            "subcategory":"Insurance Agent",
            "type":"Services"
        }
    ],
    "sg:phone":"+1 605 842 3260",
    "sg:postcode":"57580",
    "sg:province":"SD",
    "wof:name":"Insurance Center",
    "wof:placetype":"venue"
},
  "geometry": {"coordinates":[-99.856878,43.375448],"type":"Point"}
}