{
  "type": "Feature",
  "properties": {
    "addr:full":"116 Dubois Ln Spearfish SD 57783",
    "addr:housenumber":"116",
    "addr:postcode":"57783",
    "addr:street":"Dubois Ln",
    "iso:country":"US",
    "sg:address":"116 Dubois Ln",
    "sg:city":"Spearfish",
    "sg:classifiers":[
        {
            "category":"Retail",
            "subcategory":"Repair Shop",
            "type":"Services"
        },
        {
            "category":"Home & Garden",
            "subcategory":"Household Appliances",
            "type":"Retail Goods"
        }
    ],
    "sg:phone":"+1 605 642 8057",
    "sg:postcode":"57783",
    "sg:province":"SD",
    "sg:tags":[
        "electrical"
    ],
    "wof:name":"Rick's Appliance Repair",
    "wof:placetype":"venue"
},
  "geometry": {"coordinates":[-103.865909,44.513789],"type":"Point"}
}