{
  "type": "Feature",
  "properties": {
    "iso:country":"US",
    "sg:address":"2440 Westview Dr",
    "sg:city":"Spearfish",
    "sg:classifiers":[
        {
            "category":"Retail",
            "subcategory":"Laundry & Dry Cleaning",
            "type":"Services"
        }
    ],
    "sg:phone":"+1 605 642 7939",
    "sg:postcode":"57783",
    "sg:province":"SD",
    "sg:tags":[
        "trade",
        "contractor"
    ],
    "wof:name":"L & S Restoration Inc",
    "wof:placetype":"venue"
},
  "geometry": {"coordinates":[-103.907789,44.52293],"type":"Point"}
}