{
  "type": "Feature",
  "properties": {
    "addr:full":"38435 295th St Lake Andes SD 57356",
    "addr:housenumber":"38435",
    "addr:postcode":"57356",
    "addr:street":"295Th St",
    "iso:country":"US",
    "sg:address":"38435 295th St",
    "sg:city":"Lake Andes",
    "sg:phone":"+1 605 487 7220",
    "sg:postcode":"57356",
    "sg:province":"SD",
    "sg:tags":[
        "farm",
        "corn",
        "soybean"
    ],
    "wof:name":"Soukup Livestock Farms",
    "wof:placetype":"venue"
},
  "geometry": {"coordinates":[-98.491146,43.111234],"type":"Point"}
}