{
  "type": "Feature",
  "properties": {
    "iso:country":"US",
    "sg:address":"2300 6th Ave SE",
    "sg:city":"Aberdeen",
    "sg:classifiers":[
        {
            "category":"Restaurant",
            "type":"Food & Drink"
        }
    ],
    "sg:menulink":"http://www.allmenus.com/sd/aberdeen/96384-taco-johns/menu/",
    "sg:phone":"+1 605 225 2533",
    "sg:postcode":"57401",
    "sg:province":"SD",
    "sg:tags":[
        "american",
        "mexican"
    ],
    "wof:name":"Taco John's",
    "wof:placetype":"venue"
},
  "geometry": {"coordinates":[-98.45564,45.459157],"type":"Point"}
}