{
  "type": "Feature",
  "properties": {
    "iso:country":"US",
    "sg:address":"615 Main Ave S",
    "sg:city":"Brookings",
    "sg:classifiers":[
        {
            "category":"Recreation",
            "subcategory":"Arcade",
            "type":"Entertainment"
        }
    ],
    "sg:phone":"+1 605 692 5880",
    "sg:postcode":"57006",
    "sg:province":"SD",
    "sg:tags":[
        "casino"
    ],
    "wof:name":"South Main Casino & Pub",
    "wof:placetype":"venue"
},
  "geometry": {"coordinates":[-96.798594,44.299383],"type":"Point"}
}