{
  "type": "Feature",
  "properties": {
    "iso:country":"US",
    "sg:address":"409 W Cedar St",
    "sg:city":"Beresford",
    "sg:classifiers":[
        {
            "category":"Building & Trades",
            "subcategory":"Construction",
            "type":"Services"
        }
    ],
    "sg:phone":"+1 605 763 5775",
    "sg:postcode":"57004",
    "sg:province":"SD",
    "sg:tags":[
        "contractor"
    ],
    "wof:name":"R JS Toolbox",
    "wof:placetype":"venue"
},
  "geometry": {"coordinates":[-96.779848,43.083598],"type":"Point"}
}