{
  "type": "Feature",
  "properties": {
    "addr:full":"315 Ohio Ave SW Huron SD 57350",
    "addr:housenumber":"315",
    "addr:postcode":"57350",
    "addr:street":"Ohio Ave Sw",
    "iso:country":"US",
    "sg:address":"315 Ohio Ave SW",
    "sg:city":"Huron",
    "sg:classifiers":[
        {
            "category":"Home & Garden",
            "subcategory":"Building Materials",
            "type":"Retail Goods"
        },
        {
            "category":"Retail",
            "subcategory":"Auto Repair",
            "type":"Services"
        }
    ],
    "sg:phone":"+1 605 352 6477",
    "sg:postcode":"57350",
    "sg:province":"SD",
    "sg:tags":[
        "glass",
        "window",
        "plate",
        "replacement"
    ],
    "wof:name":"Safelite Auto Glass",
    "wof:placetype":"venue"
},
  "geometry": {"coordinates":[-98.219177,44.363075],"type":"Point"}
}