{
  "type": "Feature",
  "properties": {
    "iso:country":"US",
    "sg:address":"6185 Timberline Rd W",
    "sg:city":"Rapid City",
    "sg:classifiers":[
        {
            "category":"Banks & Credit Unions",
            "subcategory":"Financial Services",
            "type":"Services"
        }
    ],
    "sg:phone":"+1 605 737 3092",
    "sg:postcode":"57702",
    "sg:province":"SD",
    "sg:tags":[
        "company",
        "holding"
    ],
    "wof:name":"Dream Dak Holdings LLC",
    "wof:placetype":"venue"
},
  "geometry": {"coordinates":[-103.316549,44.085051],"type":"Point"}
}