{
  "type": "Feature",
  "properties": {
    "addr:full":"40304 226th St Woonsocket SD 57385",
    "addr:housenumber":"40304",
    "addr:postcode":"57385",
    "addr:street":"226Th St",
    "iso:country":"US",
    "sg:address":"40304 226th St",
    "sg:city":"Woonsocket",
    "sg:classifiers":[
        {
            "category":"Farming",
            "subcategory":"Livestock Farm",
            "type":"Manufacturing & Wholesale Goods"
        }
    ],
    "sg:phone":"+1 605 796 4943",
    "sg:postcode":"57385",
    "sg:province":"SD",
    "sg:tags":[
        "beef",
        "feedlot",
        "cattle"
    ],
    "wof:name":"Keith Senska",
    "wof:placetype":"venue"
},
  "geometry": {"coordinates":[-98.14388099999999,44.112325],"type":"Point"}
}