{
  "type": "Feature",
  "properties": {
    "iso:country":"US",
    "sg:address":"6 Dakota St",
    "sg:city":"Aberdeen",
    "sg:classifiers":[
        {
            "category":"Wholesale",
            "subcategory":"Machinery & Supplies",
            "type":"Manufacturing & Wholesale Goods"
        }
    ],
    "sg:phone":"+1 605 226 8238",
    "sg:postcode":"57401",
    "sg:province":"SD",
    "sg:tags":[
        "industrial"
    ],
    "wof:name":"Fastenal Company",
    "wof:placetype":"venue"
},
  "geometry": {"coordinates":[-98.47470300000001,45.465873],"type":"Point"}
}