{
  "type": "Feature",
  "properties": {
    "addr:full":"805 W Bridgeview Ave Pierre SD 57501",
    "addr:housenumber":"805",
    "addr:postcode":"57501",
    "addr:street":"W Bridgeview Ave",
    "iso:country":"US",
    "sg:address":"805 W Bridgeview Ave",
    "sg:city":"Pierre",
    "sg:classifiers":[
        {
            "category":"Professional",
            "subcategory":"Business Services",
            "type":"Services"
        }
    ],
    "sg:phone":"+1 605 224 0175",
    "sg:postcode":"57501",
    "sg:province":"SD",
    "wof:name":"Longevity Corporation",
    "wof:placetype":"venue"
},
  "geometry": {"coordinates":[-100.36096000000001,44.375911],"type":"Point"}
}