{
  "type": "Feature",
  "properties": {
    "addr:full":"12841 383rd Ave Aberdeen SD 57401",
    "addr:housenumber":"12841",
    "addr:postcode":"57401",
    "addr:street":"383Rd Ave",
    "iso:country":"US",
    "sg:address":"12841 383rd Ave",
    "sg:city":"Aberdeen",
    "sg:classifiers":[
        {
            "category":"Travel",
            "subcategory":"Hotels & Motels",
            "type":"Entertainment"
        }
    ],
    "sg:phone":"+1 605 225 1617",
    "sg:postcode":"57401",
    "sg:province":"SD",
    "sg:tags":[
        "breakfast",
        "operation",
        "bed",
        "accommodation"
    ],
    "wof:name":"Foote Creek Bed and Breakfast",
    "wof:placetype":"venue"
},
  "geometry": {"coordinates":[-98.57766100000001,45.526292],"type":"Point"}
}