{
  "type": "Feature",
  "properties": {
    "addr:full":"1805 6th Ave SE Aberdeen SD 57401",
    "addr:housenumber":"1805",
    "addr:postcode":"57401",
    "addr:street":"6Th Ave Se",
    "iso:country":"US",
    "sg:address":"1805 6th Ave SE",
    "sg:city":"Aberdeen",
    "sg:classifiers":[
        {
            "category":"Banks & Credit Unions",
            "subcategory":"Bank",
            "type":"Services"
        }
    ],
    "sg:phone":"+1 605 225 5277",
    "sg:postcode":"57401",
    "sg:province":"SD",
    "wof:name":"Home Federal Bank",
    "wof:placetype":"venue"
},
  "geometry": {"coordinates":[-98.461518,45.459264],"type":"Point"}
}