{
  "type": "Feature",
  "properties": {
    "iso:country":"US",
    "sg:address":"105 E Beebe Ave",
    "sg:city":"Chamberlain",
    "sg:classifiers":[
        {
            "category":"Personal",
            "subcategory":"Beauty Salon",
            "type":"Services"
        }
    ],
    "sg:phone":"+1 605 234 5748",
    "sg:postcode":"57325",
    "sg:province":"SD",
    "sg:tags":[
        "shop"
    ],
    "wof:name":"Bronze Beautiful",
    "wof:placetype":"venue"
},
  "geometry": {"coordinates":[-99.32968700000001,43.811758],"type":"Point"}
}