{
  "type": "Feature",
  "properties": {
    "addr:full":"715 S Maple Watertown SD 57201",
    "addr:housenumber":"715",
    "addr:postcode":"57201",
    "addr:street":"S Maple",
    "iso:country":"US",
    "sg:address":"715 S Maple",
    "sg:city":"Watertown",
    "sg:classifiers":[
        {
            "category":"Government",
            "subcategory":"Office",
            "type":"Public Place"
        }
    ],
    "sg:phone":"+1 605 882 5151",
    "sg:postcode":"57201",
    "sg:province":"SD",
    "sg:tags":[
        "state",
        "resource"
    ],
    "wof:name":"Unemployment Insurance Tax Unt",
    "wof:placetype":"venue"
},
  "geometry": {"coordinates":[-97.116079,44.892026],"type":"Point"}
}