{
  "type": "Feature",
  "properties": {
    "iso:country":"US",
    "sg:address":"12330 411th Ave",
    "sg:city":"Claremont",
    "sg:classifiers":[
        {
            "category":"Farming",
            "subcategory":"Farm",
            "type":"Manufacturing & Wholesale Goods"
        }
    ],
    "sg:phone":"+1 605 294 5897",
    "sg:postcode":"57432",
    "sg:province":"SD",
    "sg:tags":[
        "crop",
        "general"
    ],
    "wof:name":"Farming",
    "wof:placetype":"venue"
},
  "geometry": {"coordinates":[-98.000213,45.59856],"type":"Point"}
}