{
  "type": "Feature",
  "properties": {
    "iso:country":"US",
    "sg:address":"802 W Kemp Ave",
    "sg:city":"Watertown",
    "sg:classifiers":[
        {
            "category":"Retail",
            "subcategory":"Self-service Laundry",
            "type":"Services"
        }
    ],
    "sg:phone":"+1 605 884 0586",
    "sg:postcode":"57201",
    "sg:province":"SD",
    "wof:name":"Westside Coin Laundry",
    "wof:placetype":"venue"
},
  "geometry": {"coordinates":[-97.128249,44.902798],"type":"Point"}
}