{
  "type": "Feature",
  "properties": {
    "iso:country":"US",
    "sg:address":"45112 State Hwy 44",
    "sg:city":"Parker",
    "sg:classifiers":[
        {
            "category":"Sports & Exercise",
            "subcategory":"Golf",
            "type":"Entertainment"
        }
    ],
    "sg:phone":"+1 605 297 4819",
    "sg:postcode":"57053",
    "sg:province":"SD",
    "sg:tags":[
        "course"
    ],
    "wof:name":"PAR Mar Valley Country Club",
    "wof:placetype":"venue"
},
  "geometry": {"coordinates":[-97.17997,43.401084],"type":"Point"}
}