{
  "type": "Feature",
  "properties": {
    "addr:city":"Gettysburg",
    "addr:full":"205 W Commercial Ave Ste 104 Gettysburg, Sd 57442-1103",
    "addr:house_number":"205",
    "addr:housenumber":"205",
    "addr:phone":"+1 605-765-9480",
    "addr:postcode":"57442-1103",
    "addr:road":"W Commercial Ave",
    "addr:state":"SD",
    "addr:street":"W Commercial Ave",
    "addr:unit":"Ste 104",
    "iso:country":"US",
    "sg:address":"205 W Commercial Ave",
    "sg:city":"Gettysburg",
    "sg:classifiers":[
        {
            "category":"Museum",
            "type":"Entertainment"
        }
    ],
    "sg:phone":"+1 605 765 9480",
    "sg:postcode":"57442",
    "sg:province":"SD",
    "wof:name":"Dakota Sunset Museum",
    "wof:placetype":"venue"
},
  "geometry": {"coordinates":[-99.95722000000001,45.01149],"type":"Point"}
}