{
  "type": "Feature",
  "properties": {
    "iso:country":"US",
    "sg:address":"205 W Commercial Ave",
    "sg:city":"Gettysburg",
    "sg:classifiers":[
        {
            "category":"Museum",
            "type":"Entertainment"
        }
    ],
    "sg:phone":"+1 605 765 9480",
    "sg:postcode":"57442",
    "sg:province":"SD",
    "wof:name":"Dakota Sunset Museum",
    "wof:placetype":"venue"
},
  "geometry": {"coordinates":[-99.958549,45.011481],"type":"Point"}
}