{
  "type": "Feature",
  "properties": {
    "iso:country":"US",
    "sg:address":"27071 Mueller Pl",
    "sg:city":"Sioux Falls",
    "sg:classifiers":[
        {
            "category":"Professional",
            "subcategory":"Business Services",
            "type":"Services"
        },
        {
            "category":"Wholesale",
            "subcategory":"Electrical",
            "type":"Manufacturing & Wholesale Goods"
        }
    ],
    "sg:phone":"+1 605 368 2330",
    "sg:postcode":"57108",
    "sg:province":"SD",
    "sg:tags":[
        "equipment",
        "electronic",
        "supply"
    ],
    "wof:name":"Kee Technologies USA Inc",
    "wof:placetype":"venue"
},
  "geometry": {"coordinates":[-96.791257,43.463259],"type":"Point"}
}