{
  "type": "Feature",
  "properties": {
    "iso:country":"US",
    "sg:address":"2425 Mount Rushmore Rd",
    "sg:city":"Rapid City",
    "sg:classifiers":[
        {
            "category":"Shopping",
            "subcategory":"Catalog Store",
            "type":"Retail Goods"
        }
    ],
    "sg:phone":"+1 605 343 6347",
    "sg:postcode":"57701",
    "sg:province":"SD",
    "sg:tags":[
        "internet"
    ],
    "wof:name":"Dakota Pride",
    "wof:placetype":"venue"
},
  "geometry": {"coordinates":[-103.232485,44.061602],"type":"Point"}
}