{
  "type": "Feature",
  "properties": {
    "iso:country":"US",
    "sg:address":"46663 275th St",
    "sg:city":"Lennox",
    "sg:classifiers":[
        {
            "category":"Bars & Pubs",
            "type":"Food & Drink"
        }
    ],
    "sg:phone":"+1 605 647 5125",
    "sg:postcode":"57039",
    "sg:province":"SD",
    "sg:tags":[
        "drinking"
    ],
    "wof:name":"Only One Lounge",
    "wof:placetype":"venue"
},
  "geometry": {"coordinates":[-96.873097,43.402987],"type":"Point"}
}