{
  "type": "Feature",
  "properties": {
    "iso:country":"US",
    "sg:address":"1429 Dakota St",
    "sg:city":"Aberdeen",
    "sg:classifiers":[
        {
            "category":"Organizations",
            "subcategory":"Religious Organization",
            "type":"Services"
        }
    ],
    "sg:phone":"+1 605 229 0846",
    "sg:postcode":"57401",
    "sg:province":"SD",
    "wof:name":"Good Shepherd Lutheran Church",
    "wof:placetype":"venue"
},
  "geometry": {"coordinates":[-98.474608,45.450056],"type":"Point"}
}