{
  "type": "Feature",
  "properties": {
    "iso:country":"US",
    "sg:address":"2475 W Chicago St",
    "sg:city":"Rapid City",
    "sg:classifiers":[
        {
            "category":"Shopping",
            "subcategory":"Optical Goods",
            "type":"Retail Goods"
        }
    ],
    "sg:phone":"+1 605 343 9117",
    "sg:postcode":"57702",
    "sg:province":"SD",
    "wof:name":"J & J Optical",
    "wof:placetype":"venue"
},
  "geometry": {"coordinates":[-103.258486,44.084519],"type":"Point"}
}