{
  "type": "Feature",
  "properties": {
    "iso:country":"US",
    "sg:address":"121 N Huron Ave",
    "sg:city":"Pierre",
    "sg:classifiers":[
        {
            "category":"Organizations",
            "subcategory":"Religious Organization",
            "type":"Services"
        }
    ],
    "sg:phone":"+1 605 224 2427",
    "sg:postcode":"57501",
    "sg:province":"SD",
    "sg:tags":[
        "church"
    ],
    "wof:name":"Church Of The Nazarene",
    "wof:placetype":"venue"
},
  "geometry": {"coordinates":[-100.352053,44.370459],"type":"Point"}
}