{
  "type": "Feature",
  "properties": {
    "addr:full":"46414 State Hwy 38 Hartford SD 57033",
    "addr:housenumber":"46414",
    "addr:postcode":"57033",
    "addr:street":"State Hwy 38",
    "iso:country":"US",
    "sg:address":"46414 State Hwy 38",
    "sg:city":"Hartford",
    "sg:classifiers":[
        {
            "category":"Retail",
            "subcategory":"Auto Repair",
            "type":"Services"
        }
    ],
    "sg:phone":"+1 605 996 8456",
    "sg:postcode":"57033",
    "sg:province":"SD",
    "sg:tags":[
        "glass",
        "replacement"
    ],
    "wof:name":"Autoglass Express LLC",
    "wof:placetype":"venue"
},
  "geometry": {"coordinates":[-96.928088,43.618992],"type":"Point"}
}