{
  "type": "Feature",
  "properties": {
    "iso:country":"US",
    "sg:address":"20291 438th Ave",
    "sg:city":"Erwin",
    "sg:classifiers":[
        {
            "category":"Real Estate",
            "subcategory":"Real Estate Operator",
            "type":"Services"
        }
    ],
    "sg:phone":"+1 605 847 4754",
    "sg:postcode":"57233",
    "sg:province":"SD",
    "sg:tags":[
        "property",
        "lessor"
    ],
    "wof:name":"Lyle Muser",
    "wof:placetype":"venue"
},
  "geometry": {"coordinates":[-97.451044,44.444589],"type":"Point"}
}