{
  "type": "Feature",
  "properties": {
    "addr:full":"303 State St Martin SD 57551",
    "addr:housenumber":"303",
    "addr:postcode":"57551",
    "addr:street":"State St",
    "iso:country":"US",
    "sg:address":"303 State St",
    "sg:city":"Martin",
    "sg:classifiers":[
        {
            "category":"Bars & Pubs",
            "type":"Food & Drink"
        }
    ],
    "sg:phone":"+1 605 685 2000",
    "sg:postcode":"57551",
    "sg:province":"SD",
    "sg:tags":[
        "lounge",
        "cocktail"
    ],
    "wof:name":"Dakota Restaurant & Lounge",
    "wof:placetype":"venue"
},
  "geometry": {"coordinates":[-101.736783,43.175943],"type":"Point"}
}