{
  "type": "Feature",
  "properties": {
    "iso:country":"US",
    "sg:address":"17994 354th Ave",
    "sg:city":"Orient",
    "sg:classifiers":[
        {
            "category":"Government",
            "subcategory":"Fire Station",
            "type":"Public Place"
        }
    ],
    "sg:phone":"+1 605 000 1111",
    "sg:postcode":"57467",
    "sg:province":"SD",
    "sg:tags":[
        "county",
        "protection"
    ],
    "wof:name":"Polo Fire Dept",
    "wof:placetype":"venue"
},
  "geometry": {"coordinates":[-99.109281,44.780314],"type":"Point"}
}