{
  "type": "Feature",
  "properties": {
    "iso:country":"US",
    "sg:address":"3101 W 41st St",
    "sg:city":"Sioux Falls",
    "sg:classifiers":[
        {
            "category":"Banks & Credit Unions",
            "subcategory":"Bank",
            "type":"Services"
        }
    ],
    "sg:phone":"+1 605 334 8087",
    "sg:postcode":"57105",
    "sg:province":"SD",
    "sg:tags":[
        "depository",
        "banking",
        "check",
        "cashing"
    ],
    "sg:website":"www.reddcash.com",
    "wof:name":"Red D Cash",
    "wof:placetype":"venue"
},
  "geometry": {"coordinates":[-96.762236,43.51475],"type":"Point"}
}