{
  "type": "Feature",
  "properties": {
    "addr:full":"400 Adams Ave Volga SD 57071",
    "addr:housenumber":"400",
    "addr:postcode":"57071",
    "addr:street":"Adams Ave",
    "iso:country":"US",
    "sg:address":"400 Adams Ave",
    "sg:city":"Volga",
    "sg:classifiers":[
        {
            "category":"Building & Trades",
            "subcategory":"Construction",
            "type":"Services"
        }
    ],
    "sg:phone":"+1 605 627 5780",
    "sg:postcode":"57071",
    "sg:province":"SD",
    "sg:tags":[
        "house"
    ],
    "wof:name":"Shawns Custom Homes Inc",
    "wof:placetype":"venue"
},
  "geometry": {"coordinates":[-96.916478,44.321179],"type":"Point"}
}