{
  "type": "Feature",
  "properties": {
    "iso:country":"US",
    "sg:address":"721 20th St E",
    "sg:city":"Mobridge",
    "sg:classifiers":[
        {
            "category":"Retail",
            "subcategory":"Veterinary Services",
            "type":"Services"
        }
    ],
    "sg:phone":"+1 605 845 3634",
    "sg:postcode":"57601",
    "sg:province":"SD",
    "sg:tags":[
        "veterinarian"
    ],
    "wof:name":"Oahe Veterinary Hospital Inc",
    "wof:placetype":"venue"
},
  "geometry": {"coordinates":[-100.425652,45.551812],"type":"Point"}
}