{
  "type": "Feature",
  "properties": {
    "addr:full":"1241 Vermillion St Centerville SD 57014",
    "addr:housenumber":"1241",
    "addr:postcode":"57014",
    "addr:street":"Vermillion St",
    "iso:country":"US",
    "sg:address":"1241 Vermillion St",
    "sg:city":"Centerville",
    "sg:classifiers":[
        {
            "category":"Freight",
            "type":"Transportation"
        }
    ],
    "sg:phone":"+1 605 563 2113",
    "sg:postcode":"57014",
    "sg:province":"SD",
    "sg:tags":[
        "operator",
        "local",
        "trucking"
    ],
    "wof:name":"Pk & K Trucking Inc",
    "wof:placetype":"venue"
},
  "geometry": {"coordinates":[-96.967553,43.119204],"type":"Point"}
}