{
  "type": "Feature",
  "properties": {
    "addr:full":"117 E Main St Parkston SD 57366",
    "addr:housenumber":"117",
    "addr:postcode":"57366",
    "addr:street":"E Main St",
    "iso:country":"US",
    "sg:address":"117 E Main St",
    "sg:city":"Parkston",
    "sg:classifiers":[
        {
            "category":"Home & Garden",
            "subcategory":"Furniture",
            "type":"Retail Goods"
        }
    ],
    "sg:phone":"+1 605 928 3921",
    "sg:postcode":"57366",
    "sg:province":"SD",
    "wof:name":"Koehn Furniture",
    "wof:placetype":"venue"
},
  "geometry": {"coordinates":[-97.985806,43.394804],"type":"Point"}
}