{
  "type": "Feature",
  "properties": {
    "iso:country":"US",
    "sg:address":"39169 259th St",
    "sg:city":"Stickney",
    "sg:classifiers":[
        {
            "category":"Farming",
            "subcategory":"Livestock Farm",
            "type":"Manufacturing & Wholesale Goods"
        }
    ],
    "sg:phone":"+1 605 732 4524",
    "sg:postcode":"57375",
    "sg:province":"SD",
    "sg:tags":[
        "beef",
        "feedlot",
        "cattle"
    ],
    "wof:name":"Roger Safar",
    "wof:placetype":"venue"
},
  "geometry": {"coordinates":[-98.38152,43.629618],"type":"Point"}
}