{
  "type": "Feature",
  "properties": {
    "iso:country":"US",
    "sg:address":"1400 Cedar St Ste A",
    "sg:city":"Brandon",
    "sg:classifiers":[
        {
            "category":"Wholesale",
            "subcategory":"Books, Periodicals, & Newspapers",
            "type":"Manufacturing & Wholesale Goods"
        }
    ],
    "sg:phone":"+1 605 582 6025",
    "sg:postcode":"57005",
    "sg:province":"SD",
    "sg:tags":[
        "dealers-wholesale",
        "news"
    ],
    "wof:name":"Brandon Valley Challenger",
    "wof:placetype":"venue"
},
  "geometry": {"coordinates":[-96.56964600000001,43.590319],"type":"Point"}
}