{
  "type": "Feature",
  "properties": {
    "iso:country":"US",
    "sg:address":"27009 382nd Ave",
    "sg:city":"Corsica",
    "sg:phone":"+1 605 946 5139",
    "sg:postcode":"57328",
    "sg:province":"SD",
    "sg:tags":[
        "farm",
        "corn",
        "soybean"
    ],
    "wof:name":"Steven Veestra",
    "wof:placetype":"venue"
},
  "geometry": {"coordinates":[-98.54926,43.469716],"type":"Point"}
}