{
  "type": "Feature",
  "properties": {
    "iso:country":"US",
    "sg:address":"803 S 2nd St",
    "sg:city":"Milbank",
    "sg:classifiers":[
        {
            "category":"Health Services",
            "subcategory":"Chiropractor",
            "type":"Services"
        }
    ],
    "sg:phone":"+1 605 432 9561",
    "sg:postcode":"57252",
    "sg:province":"SD",
    "wof:name":"Alan D Bergquist DC",
    "wof:placetype":"venue"
},
  "geometry": {"coordinates":[-96.637182,45.214389],"type":"Point"}
}