{
  "type": "Feature",
  "properties": {
    "iso:country":"US",
    "sg:address":"47936 327th St",
    "sg:city":"Elk Point",
    "sg:phone":"+1 605 966 5759",
    "sg:postcode":"57025",
    "sg:province":"SD",
    "sg:tags":[
        "farm"
    ],
    "wof:name":"Mike Norton",
    "wof:placetype":"venue"
},
  "geometry": {"coordinates":[-96.61313699999999,42.649533],"type":"Point"}
}