{
  "type": "Feature",
  "properties": {
    "iso:country":"US",
    "sg:address":"188 Main St",
    "sg:city":"Porcupine",
    "sg:classifiers":[
        {
            "category":"Food & Beverages",
            "subcategory":"Groceries & Convenience Stores",
            "type":"Retail Goods"
        }
    ],
    "sg:phone":"+1 605 867 1326",
    "sg:postcode":"57722",
    "sg:province":"SD",
    "wof:name":"Porcupine Trading Post",
    "wof:placetype":"venue"
},
  "geometry": {"coordinates":[-103.31084199999999,43.491902],"type":"Point"}
}