{
  "type": "Feature",
  "properties": {
    "iso:country":"US",
    "sg:address":"200 N Walnut St",
    "sg:city":"Worthing",
    "sg:classifiers":[
        {
            "category":"Manufacturing",
            "subcategory":"Retail Goods",
            "type":"Manufacturing & Wholesale Goods"
        }
    ],
    "sg:phone":"+1 605 372 4808",
    "sg:postcode":"57077",
    "sg:province":"SD",
    "sg:tags":[
        "product",
        "mfg"
    ],
    "wof:name":"Foss Communications",
    "wof:placetype":"venue"
},
  "geometry": {"coordinates":[-96.76926400000001,43.331285],"type":"Point"}
}