{
  "type": "Feature",
  "properties": {
    "iso:country":"US",
    "sg:address":"1039 Main St",
    "sg:city":"Sturgis",
    "sg:classifiers":[
        {
            "category":"Restaurant",
            "type":"Food & Drink"
        }
    ],
    "sg:phone":"+1 605 720 2930",
    "sg:postcode":"57785",
    "sg:province":"SD",
    "wof:name":"Bobs Family Restaurant",
    "wof:placetype":"venue"
},
  "geometry": {"coordinates":[-103.51043799999999,44.414506],"type":"Point"}
}