{
  "type": "Feature",
  "properties": {
    "addr:full":"135 1st Ave S Brookings SD 57006",
    "addr:housenumber":"135",
    "addr:postcode":"57006",
    "addr:street":"1St Ave S",
    "iso:country":"US",
    "sg:address":"135 1st Ave S",
    "sg:city":"Brookings",
    "sg:classifiers":[
        {
            "category":"Organizations",
            "subcategory":"Non-profit Organization",
            "type":"Services"
        }
    ],
    "sg:phone":"+1 605 692 6070",
    "sg:postcode":"57006",
    "sg:province":"SD",
    "sg:tags":[
        "information",
        "alcoholism",
        "treatment"
    ],
    "sg:website":"www.aa.org",
    "wof:name":"Alcoholics Anonymous",
    "wof:placetype":"venue"
},
  "geometry": {"coordinates":[-96.80296300000001,44.305536],"type":"Point"}
}