{
  "type": "Feature",
  "properties": {
    "iso:country":"US",
    "sg:address":"702 S Main St",
    "sg:city":"Onida",
    "sg:phone":"+1 605 258 2225",
    "sg:postcode":"57564",
    "sg:province":"SD",
    "sg:tags":[
        "farm",
        "wheat"
    ],
    "wof:name":"Cheryl A Hyde",
    "wof:placetype":"venue"
},
  "geometry": {"coordinates":[-100.066086,44.700648],"type":"Point"}
}