{
  "type": "Feature",
  "properties": {
    "iso:country":"US",
    "sg:address":"27107 Independence Ave",
    "sg:city":"Sioux Falls",
    "sg:classifiers":[
        {
            "category":"Building & Trades",
            "subcategory":"Construction",
            "type":"Services"
        }
    ],
    "sg:phone":"+1 605 498 8000",
    "sg:postcode":"57108",
    "sg:province":"SD",
    "sg:tags":[
        "resurfacing",
        "laying",
        "refinishing",
        "floor"
    ],
    "sg:website":"www.flooringamerica.com",
    "wof:name":"Flooring America Of Sioux Fls",
    "wof:placetype":"venue"
},
  "geometry": {"coordinates":[-96.794987,43.458417],"type":"Point"}
}