{
  "type": "Feature",
  "properties": {
    "iso:country":"US",
    "sg:address":"3703 Hall St",
    "sg:city":"Rapid City",
    "sg:classifiers":[
        {
            "category":"Building & Trades",
            "subcategory":"Cleaning & Sanitation",
            "type":"Services"
        }
    ],
    "sg:phone":"+1 605 348 1651",
    "sg:postcode":"57702",
    "sg:province":"SD",
    "sg:tags":[
        "maintenance"
    ],
    "wof:name":"After Five Commercial Cleaning",
    "wof:placetype":"venue"
},
  "geometry": {"coordinates":[-103.282663,44.081134],"type":"Point"}
}