{
  "type": "Feature",
  "properties": {
    "addr:full":"35211 181st St Orient SD 57467",
    "addr:housenumber":"35211",
    "addr:postcode":"57467",
    "addr:street":"181St St",
    "iso:country":"US",
    "sg:address":"35211 181st St",
    "sg:city":"Orient",
    "sg:phone":"+1 605 392 2532",
    "sg:postcode":"57467",
    "sg:province":"SD",
    "sg:tags":[
        "farm",
        "corn",
        "beef",
        "feedlot",
        "cattle"
    ],
    "wof:name":"Jerry Kolda",
    "wof:placetype":"venue"
},
  "geometry": {"coordinates":[-99.146153,44.76518],"type":"Point"}
}