{
  "type": "Feature",
  "properties": {
    "addr:full":"101 Main St Eagle Butte SD 57625",
    "addr:housenumber":"101",
    "addr:postcode":"57625",
    "addr:street":"Main St",
    "iso:country":"US",
    "sg:address":"101 Main St",
    "sg:city":"Eagle Butte",
    "sg:classifiers":[
        {
            "category":"Personal",
            "subcategory":"Beauty Salon",
            "type":"Services"
        }
    ],
    "sg:phone":"+1 605 964 3533",
    "sg:postcode":"57625",
    "sg:province":"SD",
    "wof:name":"Total Look",
    "wof:placetype":"venue"
},
  "geometry": {"coordinates":[-101.234762,44.996953],"type":"Point"}
}