{
  "type": "Feature",
  "properties": {
    "addr:full":"925 Dilger Ave Rapid City SD 57701",
    "addr:housenumber":"925",
    "addr:postcode":"57701",
    "addr:street":"Dilger Ave",
    "iso:country":"US",
    "sg:address":"925 Dilger Ave",
    "sg:city":"Rapid City",
    "sg:classifiers":[
        {
            "category":"Education",
            "subcategory":"Special Training",
            "type":"Public Place"
        }
    ],
    "sg:phone":"+1 605 399 2787",
    "sg:postcode":"57701",
    "sg:province":"SD",
    "sg:tags":[
        "school",
        "instruction",
        "art"
    ],
    "wof:name":"Garfield School Of Arts",
    "wof:placetype":"venue"
},
  "geometry": {"coordinates":[-103.224788,44.09394],"type":"Point"}
}