{
  "type": "Feature",
  "properties": {
    "addr:full":"800 E 4th St Sioux Falls SD 57103",
    "addr:housenumber":"800",
    "addr:postcode":"57103",
    "addr:street":"E 4Th St",
    "iso:country":"US",
    "sg:address":"800 E 4th St",
    "sg:city":"Sioux Falls",
    "sg:classifiers":[
        {
            "category":"Insurance",
            "subcategory":"Insurance Agent",
            "type":"Services"
        }
    ],
    "sg:phone":"+1 605 331 2064",
    "sg:postcode":"57103",
    "sg:province":"SD",
    "sg:tags":[
        "company"
    ],
    "wof:name":"Allstate",
    "wof:placetype":"venue"
},
  "geometry": {"coordinates":[-96.71565699999999,43.55384],"type":"Point"}
}