{
  "type": "Feature",
  "properties": {
    "addr:full":"107 E 8th St Crooks SD 57020",
    "addr:housenumber":"107",
    "addr:postcode":"57020",
    "addr:street":"E 8Th St",
    "iso:country":"US",
    "sg:address":"107 E 8th St",
    "sg:city":"Crooks",
    "sg:classifiers":[
        {
            "category":"Recreation",
            "subcategory":"Arcade",
            "type":"Entertainment"
        }
    ],
    "sg:phone":"+1 605 543 5371",
    "sg:postcode":"57020",
    "sg:province":"SD",
    "sg:tags":[
        "amusement",
        "devices"
    ],
    "wof:name":"C & D Amusement",
    "wof:placetype":"venue"
},
  "geometry": {"coordinates":[-96.808149,43.655954],"type":"Point"}
}