{
  "type": "Feature",
  "properties": {
    "iso:country":"US",
    "sg:address":"75 Market St SE",
    "sg:city":"Huron",
    "sg:classifiers":[
        {
            "category":"Home & Garden",
            "subcategory":"Household Appliances",
            "type":"Retail Goods"
        }
    ],
    "sg:phone":"+1 605 352 4001",
    "sg:postcode":"57350",
    "sg:province":"SD",
    "sg:tags":[
        "repair",
        "electrical"
    ],
    "wof:name":"Marvs G E Appliance",
    "wof:placetype":"venue"
},
  "geometry": {"coordinates":[-98.212979,44.365657],"type":"Point"}
}