{
  "type": "Feature",
  "properties": {
    "iso:country":"US",
    "sg:address":"2801 E Havens St",
    "sg:city":"Mitchell",
    "sg:classifiers":[
        {
            "category":"Utilities",
            "subcategory":"Refuse",
            "type":"Services"
        },
        {
            "category":"Wholesale",
            "subcategory":"Scrap",
            "type":"Manufacturing & Wholesale Goods"
        }
    ],
    "sg:phone":"+1 605 995 1073",
    "sg:postcode":"57301",
    "sg:province":"SD",
    "sg:tags":[
        "recycling",
        "center"
    ],
    "wof:name":"Dependable Sanitation Inc",
    "wof:placetype":"venue"
},
  "geometry": {"coordinates":[-97.979115,43.70245],"type":"Point"}
}