{
  "type": "Feature",
  "properties": {
    "iso:country":"US",
    "sg:address":"47530 308th St",
    "sg:city":"Alcester",
    "sg:classifiers":[
        {
            "category":"Bars & Pubs",
            "type":"Food & Drink"
        }
    ],
    "sg:phone":"+1 605 253 2520",
    "sg:postcode":"57001",
    "sg:province":"SD",
    "sg:tags":[
        "nightclub"
    ],
    "wof:name":"R & D Enterprises Inc",
    "wof:placetype":"venue"
},
  "geometry": {"coordinates":[-96.688468,42.924565],"type":"Point"}
}