{
  "type": "Feature",
  "properties": {
    "iso:country":"US",
    "sg:address":"3220 W 57th St",
    "sg:city":"Sioux Falls",
    "sg:classifiers":[
        {
            "category":"Insurance",
            "subcategory":"Insurance Agent",
            "type":"Services"
        }
    ],
    "sg:phone":"+1 605 336 8204",
    "sg:postcode":"57108",
    "sg:province":"SD",
    "wof:name":"Doug Verley",
    "wof:placetype":"venue"
},
  "geometry": {"coordinates":[-96.762804,43.500268],"type":"Point"}
}