{
  "type": "Feature",
  "properties": {
    "iso:country":"US",
    "sg:address":"3135 E Colorado Blvd",
    "sg:city":"Spearfish",
    "sg:classifiers":[
        {
            "category":"Autos & Motor Vehicles",
            "subcategory":"Automobile Sales",
            "type":"Retail Goods"
        }
    ],
    "sg:phone":"+1 605 642 1428",
    "sg:postcode":"57783",
    "sg:province":"SD",
    "sg:tags":[
        "car",
        "dealer"
    ],
    "wof:name":"Vincent's Auto Venue",
    "wof:placetype":"venue"
},
  "geometry": {"coordinates":[-103.807196,44.47591],"type":"Point"}
}