{
  "type": "Feature",
  "properties": {
    "addr:full":"513 W 4th Ave Milbank SD 57252",
    "addr:housenumber":"513",
    "addr:postcode":"57252",
    "addr:street":"W 4Th Ave",
    "iso:country":"US",
    "sg:address":"513 W 4th Ave",
    "sg:city":"Milbank",
    "sg:classifiers":[
        {
            "category":"Home & Garden",
            "subcategory":"Building Materials",
            "type":"Retail Goods"
        }
    ],
    "sg:phone":"+1 605 432 5871",
    "sg:postcode":"57252",
    "sg:province":"SD",
    "sg:tags":[
        "hardware",
        "lumber"
    ],
    "wof:name":"Milbank Lumber Inc",
    "wof:placetype":"venue"
},
  "geometry": {"coordinates":[-96.646925,45.218844],"type":"Point"}
}