{
  "type": "Feature",
  "properties": {
    "iso:country":"US",
    "sg:address":"202 Dakota St",
    "sg:city":"Milbank",
    "sg:classifiers":[
        {
            "category":"Retail",
            "subcategory":"Auto Repair",
            "type":"Services"
        }
    ],
    "sg:phone":"+1 605 432 6032",
    "sg:postcode":"57268",
    "sg:province":"SD",
    "sg:tags":[
        "body",
        "automobile",
        "painting"
    ],
    "wof:name":"Al's Body Shop",
    "wof:placetype":"venue"
},
  "geometry": {"coordinates":[-96.642483,44.57636],"type":"Point"}
}