{
  "type": "Feature",
  "properties": {
    "iso:country":"US",
    "sg:address":"46332 280th St",
    "sg:city":"Lennox",
    "sg:classifiers":[
        {
            "category":"Farming",
            "subcategory":"Farm",
            "type":"Manufacturing & Wholesale Goods"
        }
    ],
    "sg:phone":"+1 605 647 2321",
    "sg:postcode":"57039",
    "sg:province":"SD",
    "sg:tags":[
        "farmer"
    ],
    "wof:name":"Calvin Henry Mechels",
    "wof:placetype":"venue"
},
  "geometry": {"coordinates":[-96.937941,43.331394],"type":"Point"}
}