{
  "type": "Feature",
  "properties": {
    "iso:country":"US",
    "sg:address":"1600 S Larkspur Trl",
    "sg:city":"Sioux Falls",
    "sg:classifiers":[
        {
            "category":"Home & Garden",
            "subcategory":"Mobile Homes",
            "type":"Retail Goods"
        }
    ],
    "sg:phone":"+1 605 334 4400",
    "sg:postcode":"57106",
    "sg:province":"SD",
    "wof:name":"Happy Homes",
    "wof:placetype":"venue"
},
  "geometry": {"coordinates":[-96.806817,43.530972],"type":"Point"}
}