{
  "type": "Feature",
  "properties": {
    "addr:full":"45026 270th St Parker SD 57053",
    "addr:housenumber":"45026",
    "addr:postcode":"57053",
    "addr:street":"270Th St",
    "iso:country":"US",
    "sg:address":"45026 270th St",
    "sg:city":"Parker",
    "sg:classifiers":[
        {
            "category":"Farming",
            "subcategory":"Farm",
            "type":"Manufacturing & Wholesale Goods"
        }
    ],
    "sg:phone":"+1 605 297 4377",
    "sg:postcode":"57053",
    "sg:province":"SD",
    "sg:tags":[
        "crop",
        "general"
    ],
    "wof:name":"Leader Regan",
    "wof:placetype":"venue"
},
  "geometry": {"coordinates":[-97.18456,43.473782],"type":"Point"}
}