{
  "type": "Feature",
  "properties": {
    "iso:country":"US",
    "sg:address":"900 Sheridan Lake Rd",
    "sg:city":"Rapid City",
    "sg:classifiers":[
        {
            "category":"Recreation",
            "type":"Entertainment"
        }
    ],
    "sg:phone":"+1 605 394 1894",
    "sg:postcode":"57702",
    "sg:province":"SD",
    "sg:tags":[
        "pool",
        "swimming"
    ],
    "wof:name":"Jimmy Hilton Municipal Pool",
    "wof:placetype":"venue"
},
  "geometry": {"coordinates":[-103.26205299999999,44.077398],"type":"Point"}
}