{
  "type": "Feature",
  "properties": {
    "iso:country":"US",
    "sg:address":"839 Houston Ave",
    "sg:city":"Hot Springs",
    "sg:classifiers":[
        {
            "category":"Freight",
            "type":"Transportation"
        }
    ],
    "sg:phone":"+1 605 745 6800",
    "sg:postcode":"57747",
    "sg:province":"SD",
    "sg:tags":[
        "operator",
        "trucking"
    ],
    "wof:name":"Lockhart MBL Hm Trnspt & Svc",
    "wof:placetype":"venue"
},
  "geometry": {"coordinates":[-103.47054799999999,43.421238],"type":"Point"}
}