{
  "type": "Feature",
  "properties": {
    "addr:full":"31 S 5th St Custer SD 57730",
    "addr:housenumber":"31",
    "addr:postcode":"57730",
    "addr:street":"S 5Th St",
    "iso:country":"US",
    "sg:address":"31 S 5th St",
    "sg:city":"Custer",
    "sg:classifiers":[
        {
            "category":"Government",
            "subcategory":"Police Station",
            "type":"Public Place"
        }
    ],
    "sg:phone":"+1 605 673 8142",
    "sg:postcode":"57730",
    "sg:province":"SD",
    "sg:tags":[
        "regional",
        "sheriff",
        "protection"
    ],
    "sg:website":"www.custercountysd.com",
    "wof:name":"Custer County Sheriff's Dept",
    "wof:placetype":"venue"
},
  "geometry": {"coordinates":[-103.600138,43.765885],"type":"Point"}
}