{
  "type": "Feature",
  "properties": {
    "iso:country":"US",
    "sg:address":"6216 W Chad Cir",
    "sg:city":"Sioux Falls",
    "sg:classifiers":[
        {
            "category":"Professional",
            "subcategory":"Management & Consulting",
            "type":"Services"
        }
    ],
    "sg:phone":"+1 605 336 6653",
    "sg:postcode":"57106",
    "sg:province":"SD",
    "sg:tags":[
        "home",
        "demonstration"
    ],
    "wof:name":"Amway-Quixtar Independent",
    "wof:placetype":"venue"
},
  "geometry": {"coordinates":[-96.801428,43.501174],"type":"Point"}
}