{
  "type": "Feature",
  "properties": {
    "addr:full":"520 N Lawler St Mitchell SD 57301",
    "addr:housenumber":"520",
    "addr:postcode":"57301",
    "addr:street":"N Lawler St",
    "iso:country":"US",
    "sg:address":"520 N Lawler St",
    "sg:city":"Mitchell",
    "sg:classifiers":[
        {
            "category":"Professional",
            "subcategory":"Management & Consulting",
            "type":"Services"
        }
    ],
    "sg:phone":"+1 605 996 2640",
    "sg:postcode":"57301",
    "sg:province":"SD",
    "sg:tags":[
        "planning",
        "organizing",
        "business"
    ],
    "wof:name":"Margheim Financial Resources",
    "wof:placetype":"venue"
},
  "geometry": {"coordinates":[-98.023971,43.71427],"type":"Point"}
}