{
  "type": "Feature",
  "properties": {
    "iso:country":"US",
    "sg:address":"4501 E 26th St",
    "sg:city":"Sioux Falls",
    "sg:classifiers":[
        {
            "category":"Restaurant",
            "type":"Food & Drink"
        }
    ],
    "sg:menulink":"http://www.allmenus.com/sd/sioux-falls/67292-pizza-hut/menu/",
    "sg:phone":"+1 605 371 1777",
    "sg:postcode":"57110",
    "sg:province":"SD",
    "sg:tags":[
        "american",
        "pizza"
    ],
    "wof:name":"Pizza Hut",
    "wof:placetype":"venue"
},
  "geometry": {"coordinates":[-96.67160699999999,43.529383],"type":"Point"}
}