{
  "type": "Feature",
  "properties": {
    "iso:country":"US",
    "sg:address":"320 S 3rd Ave",
    "sg:city":"Sioux Falls",
    "sg:classifiers":[
        {
            "category":"Real Estate",
            "subcategory":"Real Estate Operator",
            "type":"Services"
        }
    ],
    "sg:phone":"+1 605 334 8085",
    "sg:postcode":"57104",
    "sg:province":"SD",
    "sg:tags":[
        "apartment"
    ],
    "wof:name":"Tower Of David",
    "wof:placetype":"venue"
},
  "geometry": {"coordinates":[-96.72228800000001,43.543461],"type":"Point"}
}