{
  "type": "Feature",
  "properties": {
    "iso:country":"US",
    "sg:address":"4401 W Empire Pl",
    "sg:city":"Sioux Falls",
    "sg:classifiers":[
        {
            "category":"Shopping",
            "subcategory":"Hobbies, Toys, & Games",
            "type":"Retail Goods"
        }
    ],
    "sg:phone":"+1 605 361 9277",
    "sg:postcode":"57106",
    "sg:province":"SD",
    "wof:name":"Toys R Us",
    "wof:placetype":"venue"
},
  "geometry": {"coordinates":[-96.77895700000001,43.508964],"type":"Point"}
}