{
  "type": "Feature",
  "properties": {
    "addr:full":"45544 176th St Watertown SD 57201",
    "addr:housenumber":"45544",
    "addr:postcode":"57201",
    "addr:street":"176Th St",
    "iso:country":"US",
    "sg:address":"45544 176th St",
    "sg:city":"Watertown",
    "sg:classifiers":[
        {
            "category":"Professional",
            "type":"Services"
        }
    ],
    "sg:phone":"+1 605 886 0573",
    "sg:postcode":"57201",
    "sg:province":"SD",
    "sg:tags":[
        "establishment"
    ],
    "wof:name":"Hawkeye Enterprises Inc",
    "wof:placetype":"venue"
},
  "geometry": {"coordinates":[-97.094396,44.832877],"type":"Point"}
}