{
  "type": "Feature",
  "properties": {
    "iso:country":"US",
    "sg:address":"901 26th St SE",
    "sg:city":"Watertown",
    "sg:classifiers":[
        {
            "category":"Ice Cream",
            "type":"Food & Drink"
        }
    ],
    "sg:menulink":"http://www.allmenus.com/sd/elmira/182904-culvers/menu/",
    "sg:phone":"+1 605 753 0440",
    "sg:postcode":"57201",
    "sg:province":"SD",
    "sg:tags":[
        "burger",
        "american"
    ],
    "wof:name":"Culver's",
    "wof:placetype":"venue"
},
  "geometry": {"coordinates":[-97.09996599999999,44.933737],"type":"Point"}
}