{
  "type": "Feature",
  "properties": {
    "addr:full":"1719 Broadway St Yankton SD 57078",
    "addr:housenumber":"1719",
    "addr:postcode":"57078",
    "addr:street":"Broadway St",
    "iso:country":"US",
    "sg:address":"1719 Broadway St",
    "sg:city":"Yankton",
    "sg:classifiers":[
        {
            "category":"Wholesale",
            "subcategory":"Farm Supplies",
            "type":"Manufacturing & Wholesale Goods"
        }
    ],
    "sg:phone":"+1 605 664 3395",
    "sg:postcode":"57078",
    "sg:province":"SD",
    "sg:tags":[
        "buyer",
        "livestock"
    ],
    "wof:name":"Heine Cattle Co",
    "wof:placetype":"venue"
},
  "geometry": {"coordinates":[-97.39666099999999,42.886862],"type":"Point"}
}