{
  "type": "Feature",
  "properties": {
    "iso:country":"US",
    "sg:address":"714 E Kay Ave",
    "sg:city":"Mitchell",
    "sg:classifiers":[
        {
            "category":"Shopping",
            "type":"Retail Goods"
        }
    ],
    "sg:phone":"+1 605 996 3218",
    "sg:postcode":"57301",
    "sg:province":"SD",
    "sg:tags":[
        "trophy",
        "medal",
        "award"
    ],
    "wof:name":"Sun Gold Trophies Inc",
    "wof:placetype":"venue"
},
  "geometry": {"coordinates":[-98.013386,43.697059],"type":"Point"}
}