{
  "type": "Feature",
  "properties": {
    "addr:full":"38926 243rd St Plankinton SD 57368",
    "addr:housenumber":"38926",
    "addr:postcode":"57368",
    "addr:street":"243Rd St",
    "iso:country":"US",
    "sg:address":"38926 243rd St",
    "sg:city":"Plankinton",
    "sg:classifiers":[
        {
            "category":"Professional",
            "subcategory":"Business Services",
            "type":"Services"
        }
    ],
    "sg:phone":"+1 605 248 2462",
    "sg:postcode":"57368",
    "sg:province":"SD",
    "wof:name":"Olsen Auctioneering Service",
    "wof:placetype":"venue"
},
  "geometry": {"coordinates":[-98.416515,43.864645],"type":"Point"}
}