{
  "type": "Feature",
  "properties": {
    "iso:country":"US",
    "sg:address":"5302 W 36th St",
    "sg:city":"Sioux Falls",
    "sg:classifiers":[
        {
            "category":"Professional",
            "subcategory":"Management & Consulting",
            "type":"Services"
        }
    ],
    "sg:phone":"+1 605 361 1344",
    "sg:postcode":"57106",
    "sg:province":"SD",
    "sg:tags":[
        "firm"
    ],
    "wof:name":"Source Inc",
    "wof:placetype":"venue"
},
  "geometry": {"coordinates":[-96.795764,43.519157],"type":"Point"}
}