{
  "type": "Feature",
  "properties": {
    "iso:country":"US",
    "sg:address":"115 S 1st St",
    "sg:city":"Parkston",
    "sg:classifiers":[
        {
            "category":"Wholesale",
            "subcategory":"Farm Supplies",
            "type":"Manufacturing & Wholesale Goods"
        }
    ],
    "sg:phone":"+1 605 928 3381",
    "sg:postcode":"57366",
    "sg:province":"SD",
    "sg:tags":[
        "fertilizer",
        "fuel"
    ],
    "wof:name":"Agland Co-Op",
    "wof:placetype":"venue"
},
  "geometry": {"coordinates":[-97.98604400000001,43.39458],"type":"Point"}
}