{
  "type": "Feature",
  "properties": {
    "iso:country":"US",
    "sg:address":"1508 S Comet Rd",
    "sg:city":"Sioux Falls",
    "sg:classifiers":[
        {
            "category":"Building & Trades",
            "subcategory":"Construction",
            "type":"Services"
        }
    ],
    "sg:phone":"+1 605 351 2234",
    "sg:postcode":"57103",
    "sg:province":"SD",
    "sg:tags":[
        "site",
        "clean"
    ],
    "wof:name":"Premiere Office Cleaning",
    "wof:placetype":"venue"
},
  "geometry": {"coordinates":[-96.684995,43.53035],"type":"Point"}
}