{
  "type": "Feature",
  "properties": {
    "addr:full":"334 S Pierre St Pierre SD 57501",
    "addr:housenumber":"334",
    "addr:postcode":"57501",
    "addr:street":"S Pierre St",
    "iso:country":"US",
    "sg:address":"334 S Pierre St",
    "sg:city":"Pierre",
    "sg:classifiers":[
        {
            "category":"Utilities",
            "subcategory":"Electric",
            "type":"Services"
        }
    ],
    "sg:phone":"+1 605 224 0947",
    "sg:postcode":"57501",
    "sg:province":"SD",
    "sg:tags":[
        "company"
    ],
    "wof:name":"Montana-Dakota Utilities Co",
    "wof:placetype":"venue"
},
  "geometry": {"coordinates":[-100.35401299999999,44.366328],"type":"Point"}
}