{
  "type": "Feature",
  "properties": {
    "iso:country":"US",
    "sg:address":"410 E 21st St",
    "sg:city":"Yankton",
    "sg:classifiers":[
        {
            "category":"Farming",
            "subcategory":"Livestock Farm",
            "type":"Manufacturing & Wholesale Goods"
        }
    ],
    "sg:phone":"+1 605 665 1040",
    "sg:postcode":"57078",
    "sg:province":"SD",
    "sg:tags":[
        "hog",
        "or",
        "feedlot"
    ],
    "wof:name":"Pic Usa Inc",
    "wof:placetype":"venue"
},
  "geometry": {"coordinates":[-97.38699,42.890732],"type":"Point"}
}