{
  "type": "Feature",
  "properties": {
    "iso:country":"US",
    "sg:address":"720 N Euclid Ave",
    "sg:city":"Pierre",
    "sg:classifiers":[
        {
            "category":"Insurance",
            "subcategory":"Insurance Agent",
            "type":"Services"
        }
    ],
    "sg:phone":"+1 605 224 7345",
    "sg:postcode":"57501",
    "sg:province":"SD",
    "wof:name":"Delta Dental Plan Of SD",
    "wof:placetype":"venue"
},
  "geometry": {"coordinates":[-100.348425,44.3774],"type":"Point"}
}