{
  "type": "Feature",
  "properties": {
    "addr:full":"32206 194th St Harrold SD 57536",
    "addr:housenumber":"32206",
    "addr:postcode":"57536",
    "addr:street":"194Th St",
    "iso:country":"US",
    "sg:address":"32206 194th St",
    "sg:city":"Harrold",
    "sg:phone":"+1 605 875 3449",
    "sg:postcode":"57536",
    "sg:province":"SD",
    "sg:tags":[
        "farm",
        "wheat"
    ],
    "wof:name":"Jerry R Barnes",
    "wof:placetype":"venue"
},
  "geometry": {"coordinates":[-99.715604,44.577159],"type":"Point"}
}