{
  "type": "Feature",
  "properties": {
    "iso:country":"US",
    "sg:address":"37273 216th St",
    "sg:city":"Wessington",
    "sg:classifiers":[
        {
            "category":"Farming",
            "subcategory":"Livestock Farm",
            "type":"Manufacturing & Wholesale Goods"
        }
    ],
    "sg:phone":"+1 605 458 2218",
    "sg:postcode":"57381",
    "sg:province":"SD",
    "sg:tags":[
        "ranch"
    ],
    "wof:name":"3 C Christensen Ranch",
    "wof:placetype":"venue"
},
  "geometry": {"coordinates":[-98.737796,44.254456],"type":"Point"}
}