{
  "type": "Feature",
  "properties": {
    "addr:full":"14241 479th Ave Milbank SD 57252",
    "addr:housenumber":"14241",
    "addr:postcode":"57252",
    "addr:street":"479Th Ave",
    "iso:country":"US",
    "sg:address":"14241 479th Ave",
    "sg:city":"Milbank",
    "sg:classifiers":[
        {
            "category":"Farming",
            "subcategory":"Livestock Farm",
            "type":"Manufacturing & Wholesale Goods"
        }
    ],
    "sg:phone":"+1 605 432 6376",
    "sg:postcode":"57252",
    "sg:province":"SD",
    "sg:tags":[
        "feedlot",
        "beef",
        "cattle"
    ],
    "wof:name":"Dennis & Arlene Fonder",
    "wof:placetype":"venue"
},
  "geometry": {"coordinates":[-96.61670700000001,45.320633],"type":"Point"}
}