{
  "type": "Feature",
  "properties": {
    "iso:country":"US",
    "sg:address":"1316 N 10th St",
    "sg:city":"Spearfish",
    "sg:classifiers":[
        {
            "category":"Health Services",
            "subcategory":"Hospital",
            "type":"Services"
        }
    ],
    "sg:phone":"+1 605 642 3113",
    "sg:postcode":"57783",
    "sg:province":"SD",
    "sg:tags":[
        "medical"
    ],
    "wof:name":"Spearfish Surgery Center LLC",
    "wof:placetype":"venue"
},
  "geometry": {"coordinates":[-103.854669,44.497546],"type":"Point"}
}