{
  "type": "Feature",
  "properties": {
    "addr:full":"3601 E Dudley Ln Sioux Falls SD 57103",
    "addr:housenumber":"3601",
    "addr:postcode":"57103",
    "addr:street":"E Dudley Ln",
    "iso:country":"US",
    "sg:address":"3601 E Dudley Ln",
    "sg:city":"Sioux Falls",
    "sg:classifiers":[
        {
            "category":"Organizations",
            "subcategory":"Religious Organization",
            "type":"Services"
        }
    ],
    "sg:phone":"+1 605 371 2320",
    "sg:postcode":"57103",
    "sg:province":"SD",
    "sg:tags":[
        "catholic",
        "church"
    ],
    "sg:website":"www.holyspiritsf.org",
    "wof:name":"Holy Spirit Church Inc",
    "wof:placetype":"venue"
},
  "geometry": {"coordinates":[-96.685137,43.505315],"type":"Point"}
}