{
  "type": "Feature",
  "properties": {
    "iso:country":"US",
    "sg:address":"2900 S Hwy 281",
    "sg:city":"Aberdeen",
    "sg:classifiers":[
        {
            "category":"Retail",
            "subcategory":"Repair Shop",
            "type":"Services"
        }
    ],
    "sg:phone":"+1 605 225 1655",
    "sg:postcode":"57401",
    "sg:province":"SD",
    "sg:tags":[
        "plumbing",
        "drain",
        "cleaning",
        "sewer"
    ],
    "wof:name":"Sewer Duck",
    "wof:placetype":"venue"
},
  "geometry": {"coordinates":[-98.51547600000001,45.431841],"type":"Point"}
}