{
  "type": "Feature",
  "properties": {
    "iso:country":"US",
    "sg:address":"33316 155th St",
    "sg:city":"Onaka",
    "sg:phone":"+1 605 436 6724",
    "sg:postcode":"57466",
    "sg:province":"SD",
    "sg:tags":[
        "farm",
        "grain",
        "cash"
    ],
    "wof:name":"Dale Gutenkauf",
    "wof:placetype":"venue"
},
  "geometry": {"coordinates":[-99.510459,45.14387],"type":"Point"}
}