{
  "type": "Feature",
  "properties": {
    "addr:full":"717 S Broadway Watertown SD 57201",
    "addr:housenumber":"717",
    "addr:postcode":"57201",
    "addr:street":"S Broadway",
    "iso:country":"US",
    "sg:address":"717 S Broadway",
    "sg:city":"Watertown",
    "sg:classifiers":[
        {
            "category":"Insurance",
            "subcategory":"Insurance Agent",
            "type":"Services"
        }
    ],
    "sg:phone":"+1 605 886 2318",
    "sg:postcode":"57201",
    "sg:province":"SD",
    "sg:tags":[
        "adjuster"
    ],
    "sg:website":"www.dakotaclaims.com",
    "wof:name":"Dakota Claims Serv",
    "wof:placetype":"venue"
},
  "geometry": {"coordinates":[-97.11775,44.892355],"type":"Point"}
}