{
  "type": "Feature",
  "properties": {
    "addr:full":"210 Main Ave N Lake Preston SD 57249",
    "addr:housenumber":"210",
    "addr:postcode":"57249",
    "addr:street":"Main Ave N Lake",
    "iso:country":"US",
    "sg:address":"210 Main Ave N",
    "sg:city":"Lake Preston",
    "sg:classifiers":[
        {
            "category":"Banks & Credit Unions",
            "subcategory":"Bank",
            "type":"Services"
        }
    ],
    "sg:phone":"+1 605 847 4411",
    "sg:postcode":"57249",
    "sg:province":"SD",
    "wof:name":"First Savings Bank",
    "wof:placetype":"venue"
},
  "geometry": {"coordinates":[-97.37723800000001,44.363381],"type":"Point"}
}