{
  "type": "Feature",
  "properties": {
    "addr:full":"1601 S Sycamore Ave Sioux Falls SD 57110",
    "addr:housenumber":"1601",
    "addr:postcode":"57110",
    "addr:street":"S Sycamore Ave",
    "iso:country":"US",
    "sg:address":"1601 S Sycamore Ave",
    "sg:city":"Sioux Falls",
    "sg:classifiers":[
        {
            "category":"Coffee & Tea",
            "type":"Food & Drink"
        }
    ],
    "sg:menulink":"http://www.allmenus.com/sd/sioux-falls/115173-starbucks-coffee/menu/",
    "sg:phone":"+1 605 334 4570",
    "sg:postcode":"57110",
    "sg:province":"SD",
    "sg:tags":[
        "american"
    ],
    "wof:name":"Starbucks Coffee",
    "wof:placetype":"venue"
},
  "geometry": {"coordinates":[-96.671441,43.531223],"type":"Point"}
}