{
  "type": "Feature",
  "properties": {
    "iso:country":"US",
    "sg:address":"39261 284th St",
    "sg:city":"Armour",
    "sg:classifiers":[
        {
            "category":"Building & Trades",
            "subcategory":"Construction",
            "type":"Services"
        }
    ],
    "sg:phone":"+1 605 724 2740",
    "sg:postcode":"57313",
    "sg:province":"SD",
    "sg:tags":[
        "general",
        "contractor"
    ],
    "wof:name":"BRB Contractors",
    "wof:placetype":"venue"
},
  "geometry": {"coordinates":[-98.335032,43.268367],"type":"Point"}
}