{
  "type": "Feature",
  "properties": {
    "iso:country":"US",
    "sg:address":"37111 193rd St",
    "sg:city":"Wessington",
    "sg:classifiers":[
        {
            "category":"Farming",
            "subcategory":"Livestock Farm",
            "type":"Manufacturing & Wholesale Goods"
        }
    ],
    "sg:phone":"+1 605 458 2635",
    "sg:postcode":"57381",
    "sg:province":"SD",
    "sg:tags":[
        "beef",
        "feedlot",
        "cattle"
    ],
    "wof:name":"Kirk Sargent Farms",
    "wof:placetype":"venue"
},
  "geometry": {"coordinates":[-98.75809099999999,44.590952],"type":"Point"}
}