{
  "type": "Feature",
  "properties": {
    "addr:full":"603 W Main St Lead SD 57754",
    "addr:housenumber":"603",
    "addr:postcode":"57754",
    "addr:street":"W Main St",
    "iso:country":"US",
    "sg:address":"603 W Main St",
    "sg:city":"Lead",
    "sg:classifiers":[
        {
            "category":"Personal",
            "subcategory":"Beauty Salon",
            "type":"Services"
        }
    ],
    "sg:phone":"+1 605 584 2926",
    "sg:postcode":"57754",
    "sg:province":"SD",
    "sg:tags":[
        "shop"
    ],
    "wof:name":"Sues Kurly Salon",
    "wof:placetype":"venue"
},
  "geometry": {"coordinates":[-103.769899,44.351822],"type":"Point"}
}