{
  "type": "Feature",
  "properties": {
    "iso:country":"US",
    "sg:address":"3410 Corral Dr",
    "sg:city":"Rapid City",
    "sg:classifiers":[
        {
            "category":"Building & Trades",
            "subcategory":"Construction",
            "type":"Services"
        }
    ],
    "sg:phone":"+1 605 431 5781",
    "sg:postcode":"57702",
    "sg:province":"SD",
    "sg:tags":[
        "tile",
        "restoration",
        "co",
        "janitorial",
        "holding"
    ],
    "wof:name":"B J Planet LLC",
    "wof:placetype":"venue"
},
  "geometry": {"coordinates":[-103.275032,44.038787],"type":"Point"}
}