{
  "type": "Feature",
  "properties": {
    "iso:country":"US",
    "sg:address":"20565 480th Ave",
    "sg:city":"White",
    "sg:classifiers":[
        {
            "category":"Farming",
            "subcategory":"Livestock Farm",
            "type":"Manufacturing & Wholesale Goods"
        }
    ],
    "sg:phone":"+1 605 629 4171",
    "sg:postcode":"57276",
    "sg:province":"SD",
    "sg:tags":[
        "beef",
        "corn",
        "cash",
        "grain",
        "w",
        "cattle",
        "feedlot"
    ],
    "wof:name":"Roderick & Darlene Meyer",
    "wof:placetype":"venue"
},
  "geometry": {"coordinates":[-96.606786,44.40302],"type":"Point"}
}