{
  "type": "Feature",
  "properties": {
    "iso:country":"US",
    "sg:address":"4814 Powderhorn Dr",
    "sg:city":"Rapid City",
    "sg:classifiers":[
        {
            "category":"Restaurant",
            "type":"Food & Drink"
        }
    ],
    "sg:phone":"+1 605 394 9324",
    "sg:postcode":"57702",
    "sg:province":"SD",
    "sg:tags":[
        "eating"
    ],
    "wof:name":"T B K Inc",
    "wof:placetype":"venue"
},
  "geometry": {"coordinates":[-103.300505,44.052465],"type":"Point"}
}