{
  "type": "Feature",
  "properties": {
    "addr:full":"510 Empire Mall Sioux Falls SD 57106",
    "addr:housenumber":"510",
    "addr:postcode":"57106",
    "addr:street":"Empire Mall",
    "iso:country":"US",
    "sg:address":"510 Empire Mall",
    "sg:city":"Sioux Falls",
    "sg:classifiers":[
        {
            "category":"Health Services",
            "subcategory":"Optometrist",
            "type":"Services"
        }
    ],
    "sg:phone":"+1 605 362 7944",
    "sg:postcode":"57106",
    "sg:province":"SD",
    "wof:name":"Doctors Of Optometry",
    "wof:placetype":"venue"
},
  "geometry": {"coordinates":[-96.774795,43.514209],"type":"Point"}
}