{
  "type": "Feature",
  "properties": {
    "addr:full":"215 Van Eps Ave S Madison SD 57042",
    "addr:housenumber":"215",
    "addr:postcode":"57042",
    "addr:street":"Van Eps Ave S",
    "iso:country":"US",
    "sg:address":"215 Van Eps Ave S",
    "sg:city":"Madison",
    "sg:classifiers":[
        {
            "category":"Cinema",
            "subcategory":"Movie Rental",
            "type":"Entertainment"
        }
    ],
    "sg:phone":"+1 605 256 6252",
    "sg:postcode":"57042",
    "sg:province":"SD",
    "sg:tags":[
        "leasing",
        "video",
        "disc",
        "tape"
    ],
    "wof:name":"Mr Movies",
    "wof:placetype":"venue"
},
  "geometry": {"coordinates":[-97.115471,44.003809],"type":"Point"}
}