{
  "type": "Feature",
  "properties": {
    "addr:full":"1102 Main St Burke SD 57523",
    "addr:housenumber":"1102",
    "addr:postcode":"57523",
    "addr:street":"Main St",
    "iso:country":"US",
    "sg:address":"1102 Main St",
    "sg:city":"Burke",
    "sg:classifiers":[
        {
            "category":"Insurance",
            "subcategory":"Insurance Agent",
            "type":"Services"
        }
    ],
    "sg:phone":"+1 605 775 2636",
    "sg:postcode":"57523",
    "sg:province":"SD",
    "sg:website":"www.mvmic.com",
    "wof:name":"Missouri Valley Mutual Ins Co",
    "wof:placetype":"venue"
},
  "geometry": {"coordinates":[-99.292114,43.179374],"type":"Point"}
}