{
  "type": "Feature",
  "properties": {
    "iso:country":"US",
    "sg:address":"216 N Lake Dr",
    "sg:city":"Watertown",
    "sg:classifiers":[
        {
            "category":"Building & Trades",
            "subcategory":"Construction",
            "type":"Services"
        }
    ],
    "sg:phone":"+1 605 886 2555",
    "sg:postcode":"57201",
    "sg:province":"SD",
    "sg:tags":[
        "general",
        "contractor"
    ],
    "wof:name":"Dakota Framing Specialties Inc",
    "wof:placetype":"venue"
},
  "geometry": {"coordinates":[-97.189808,44.950289],"type":"Point"}
}