{
  "type": "Feature",
  "properties": {
    "addr:full":"39064 156th St Mellette SD 57461",
    "addr:housenumber":"39064",
    "addr:postcode":"57461",
    "addr:street":"156Th St",
    "iso:country":"US",
    "sg:address":"39064 156th St",
    "sg:city":"Mellette",
    "sg:classifiers":[
        {
            "category":"Professional",
            "subcategory":"Detective & Security Services",
            "type":"Services"
        }
    ],
    "sg:phone":"+1 605 887 3589",
    "sg:postcode":"57461",
    "sg:province":"SD",
    "sg:tags":[
        "system"
    ],
    "wof:name":"K Square",
    "wof:placetype":"venue"
},
  "geometry": {"coordinates":[-98.41587699999999,45.128207],"type":"Point"}
}