{
  "type": "Feature",
  "properties": {
    "addr:full":"1312 N Arch St Aberdeen SD 57401",
    "addr:housenumber":"1312",
    "addr:postcode":"57401",
    "addr:street":"N Arch St",
    "iso:country":"US",
    "sg:address":"1312 N Arch St",
    "sg:city":"Aberdeen",
    "sg:classifiers":[
        {
            "category":"Real Estate",
            "subcategory":"Real Estate Operator",
            "type":"Services"
        }
    ],
    "sg:phone":"+1 605 225 6921",
    "sg:postcode":"57401",
    "sg:province":"SD",
    "sg:tags":[
        "building",
        "apartment"
    ],
    "wof:name":"McLeod Avenue Apartments",
    "wof:placetype":"venue"
},
  "geometry": {"coordinates":[-98.480701,45.479736],"type":"Point"}
}