{
  "type": "Feature",
  "properties": {
    "addr:full":"508 W 6th Ave Mitchell SD 57301",
    "addr:housenumber":"508",
    "addr:postcode":"57301",
    "addr:street":"W 6Th Ave",
    "iso:country":"US",
    "sg:address":"508 W 6th Ave",
    "sg:city":"Mitchell",
    "sg:classifiers":[
        {
            "category":"Shopping",
            "subcategory":"Books",
            "type":"Retail Goods"
        }
    ],
    "sg:phone":"+1 605 996 2409",
    "sg:postcode":"57301",
    "sg:province":"SD",
    "wof:name":"That Book Place",
    "wof:placetype":"venue"
},
  "geometry": {"coordinates":[-98.032386,43.714471],"type":"Point"}
}