{
  "type": "Feature",
  "properties": {
    "iso:country":"US",
    "sg:address":"44257 120th St",
    "sg:city":"Eden",
    "sg:classifiers":[
        {
            "category":"Farming",
            "subcategory":"Livestock Farm",
            "type":"Manufacturing & Wholesale Goods"
        }
    ],
    "sg:phone":"+1 605 698 3654",
    "sg:postcode":"57232",
    "sg:province":"SD",
    "sg:tags":[
        "hog",
        "beef",
        "far",
        "corn",
        "cattle",
        "or",
        "feedlot"
    ],
    "wof:name":"Krista Farm",
    "wof:placetype":"venue"
},
  "geometry": {"coordinates":[-97.351286,45.646089],"type":"Point"}
}