{
  "type": "Feature",
  "properties": {
    "addr:full":"210 2nd St Ipswich SD 57451",
    "addr:housenumber":"210",
    "addr:postcode":"57451",
    "addr:street":"2Nd St",
    "iso:country":"US",
    "sg:address":"210 2nd St",
    "sg:city":"Ipswich",
    "sg:classifiers":[
        {
            "category":"Government",
            "subcategory":"Office",
            "type":"Public Place"
        }
    ],
    "sg:phone":"+1 605 426 6096",
    "sg:postcode":"57451",
    "sg:province":"SD",
    "sg:tags":[
        "state"
    ],
    "wof:name":"Game Fish & Parks Dept",
    "wof:placetype":"venue"
},
  "geometry": {"coordinates":[-99.024897,45.445893],"type":"Point"}
}