{
  "type": "Feature",
  "properties": {
    "addr:full":"21874 465th Ave Volga SD 57071",
    "addr:housenumber":"21874",
    "addr:postcode":"57071",
    "addr:street":"465Th Ave",
    "iso:country":"US",
    "sg:address":"21874 465th Ave",
    "sg:city":"Volga",
    "sg:phone":"+1 605 826 4110",
    "sg:postcode":"57071",
    "sg:province":"SD",
    "sg:tags":[
        "farm",
        "corn",
        "soybean"
    ],
    "wof:name":"Dhm Farm",
    "wof:placetype":"venue"
},
  "geometry": {"coordinates":[-96.908422,44.21378],"type":"Point"}
}