{
  "type": "Feature",
  "properties": {
    "iso:country":"US",
    "sg:address":"2428 9th Ave SE",
    "sg:city":"Watertown",
    "sg:classifiers":[
        {
            "category":"Wholesale",
            "subcategory":"Construction Materials",
            "type":"Manufacturing & Wholesale Goods"
        }
    ],
    "sg:phone":"+1 605 882 8989",
    "sg:postcode":"57201",
    "sg:province":"SD",
    "sg:tags":[
        "sand",
        "gravel"
    ],
    "wof:name":"Willow Creek Dairy",
    "wof:placetype":"venue"
},
  "geometry": {"coordinates":[-97.076108,44.889962],"type":"Point"}
}