{
  "type": "Feature",
  "properties": {
    "addr:full":"1507 S Broadway Watertown SD 57201",
    "addr:housenumber":"1507",
    "addr:postcode":"57201",
    "addr:street":"S Broadway",
    "iso:country":"US",
    "sg:address":"1507 S Broadway",
    "sg:city":"Watertown",
    "sg:classifiers":[
        {
            "category":"Wholesale",
            "subcategory":"Auto Parts",
            "type":"Manufacturing & Wholesale Goods"
        }
    ],
    "sg:phone":"+1 605 886 2475",
    "sg:postcode":"57201",
    "sg:province":"SD",
    "sg:tags":[
        "automobile",
        "rebuilt"
    ],
    "wof:name":"Roger's Salvage LLC",
    "wof:placetype":"venue"
},
  "geometry": {"coordinates":[-97.119197,44.88274],"type":"Point"}
}