{
  "type": "Feature",
  "properties": {
    "iso:country":"US",
    "sg:address":"5023 S Louise Ave",
    "sg:city":"Sioux Falls",
    "sg:classifiers":[
        {
            "category":"Shopping",
            "subcategory":"Bicycles & Sporting Goods",
            "type":"Retail Goods"
        }
    ],
    "sg:phone":"+1 605 271 3333",
    "sg:postcode":"57108",
    "sg:province":"SD",
    "sg:tags":[
        "equipment",
        "exercise"
    ],
    "wof:name":"Northern Plains Fitness",
    "wof:placetype":"venue"
},
  "geometry": {"coordinates":[-96.77102600000001,43.498943],"type":"Point"}
}