{
  "type": "Feature",
  "properties": {
    "iso:country":"US",
    "sg:address":"320 Dollard St",
    "sg:city":"Scotland",
    "sg:classifiers":[
        {
            "category":"Building & Trades",
            "subcategory":"Construction",
            "type":"Services"
        }
    ],
    "sg:phone":"+1 605 583 2500",
    "sg:postcode":"57059",
    "sg:province":"SD",
    "sg:tags":[
        "contractor"
    ],
    "wof:name":"Grosz Welding & Repair",
    "wof:placetype":"venue"
},
  "geometry": {"coordinates":[-97.71636100000001,43.15492],"type":"Point"}
}