{
  "type": "Feature",
  "properties": {
    "iso:country":"US",
    "sg:address":"44395 State Hwy 25",
    "sg:city":"Veblen",
    "sg:classifiers":[
        {
            "category":"Farming",
            "subcategory":"Livestock Farm",
            "type":"Manufacturing & Wholesale Goods"
        }
    ],
    "sg:phone":"+1 605 738 2558",
    "sg:postcode":"57270",
    "sg:province":"SD",
    "sg:tags":[
        "beef",
        "feedlot",
        "cattle"
    ],
    "wof:name":"Louis Vrchota",
    "wof:placetype":"venue"
},
  "geometry": {"coordinates":[-97.334056,45.863738],"type":"Point"}
}