{
  "type": "Feature",
  "properties": {
    "iso:country":"US",
    "sg:address":"3100 E 10th St",
    "sg:city":"Sioux Falls",
    "sg:classifiers":[
        {
            "category":"Building & Trades",
            "subcategory":"Construction",
            "type":"Services"
        }
    ],
    "sg:phone":"+1 605 336 7886",
    "sg:postcode":"57103",
    "sg:province":"SD",
    "sg:tags":[
        "install",
        "fence"
    ],
    "wof:name":"Michaels Fence Co",
    "wof:placetype":"venue"
},
  "geometry": {"coordinates":[-96.686386,43.546777],"type":"Point"}
}