{
  "type": "Feature",
  "properties": {
    "iso:country":"US",
    "sg:address":"4601 E 12th St",
    "sg:city":"Sioux Falls",
    "sg:classifiers":[
        {
            "category":"Personal",
            "subcategory":"Beauty Salon",
            "type":"Services"
        }
    ],
    "sg:phone":"+1 605 336 9792",
    "sg:postcode":"57110",
    "sg:province":"SD",
    "sg:tags":[
        "shop"
    ],
    "wof:name":"Cost Cutters",
    "wof:placetype":"venue"
},
  "geometry": {"coordinates":[-96.662807,43.544163],"type":"Point"}
}