{
  "type": "Feature",
  "properties": {
    "addr:full":"1601 S Coates Rd Sioux Falls SD 57105",
    "addr:housenumber":"1601",
    "addr:postcode":"57105",
    "addr:street":"S Coates Rd",
    "iso:country":"US",
    "sg:address":"1601 S Coates Rd",
    "sg:city":"Sioux Falls",
    "sg:classifiers":[
        {
            "category":"Building & Trades",
            "subcategory":"Construction",
            "type":"Services"
        }
    ],
    "sg:phone":"+1 605 335 7222",
    "sg:postcode":"57105",
    "sg:province":"SD",
    "sg:tags":[
        "house"
    ],
    "wof:name":"Creative Homes",
    "wof:placetype":"venue"
},
  "geometry": {"coordinates":[-96.70326300000001,43.531778],"type":"Point"}
}