{
  "type": "Feature",
  "properties": {
    "addr:full":"39304 105th St Frederick SD 57441",
    "addr:housenumber":"39304",
    "addr:postcode":"57441",
    "addr:street":"105Th St",
    "iso:country":"US",
    "sg:address":"39304 105th St",
    "sg:city":"Frederick",
    "sg:classifiers":[
        {
            "category":"Farming",
            "subcategory":"Livestock Farm",
            "type":"Manufacturing & Wholesale Goods"
        }
    ],
    "sg:phone":"+1 605 329 2304",
    "sg:postcode":"57441",
    "sg:province":"SD",
    "sg:tags":[
        "beef",
        "feedlot",
        "cattle"
    ],
    "wof:name":"Avis Wolter",
    "wof:placetype":"venue"
},
  "geometry": {"coordinates":[-98.369623,45.86479],"type":"Point"}
}