{
  "type": "Feature",
  "properties": {
    "addr:full":"4515 E 26th St Sioux Falls SD 57110",
    "addr:housenumber":"4515",
    "addr:postcode":"57110",
    "addr:street":"E 26Th St",
    "iso:country":"US",
    "sg:address":"4515 E 26th St",
    "sg:city":"Sioux Falls",
    "sg:classifiers":[
        {
            "category":"Home & Garden",
            "subcategory":"Furniture",
            "type":"Retail Goods"
        }
    ],
    "sg:phone":"+1 605 371 4540",
    "sg:postcode":"57110",
    "sg:province":"SD",
    "sg:tags":[
        "bed"
    ],
    "sg:website":"www.comfortking.net",
    "wof:name":"Comfort King Mattress Factory",
    "wof:placetype":"venue"
},
  "geometry": {"coordinates":[-96.66918800000001,43.529289],"type":"Point"}
}