{
  "type": "Feature",
  "properties": {
    "iso:country":"US",
    "sg:address":"46869 137th St",
    "sg:city":"Wilmot",
    "sg:classifiers":[
        {
            "category":"Restaurant",
            "type":"Food & Drink"
        }
    ],
    "sg:phone":"+1 605 938 4105",
    "sg:postcode":"57279",
    "sg:province":"SD",
    "wof:name":"Cattlemen's Diner",
    "wof:placetype":"venue"
},
  "geometry": {"coordinates":[-96.790572,45.398652],"type":"Point"}
}