{
  "type": "Feature",
  "properties": {
    "iso:country":"US",
    "sg:address":"1310 N Cliff Ave",
    "sg:city":"Sioux Falls",
    "sg:classifiers":[
        {
            "category":"Retail",
            "subcategory":"Auto Repair",
            "type":"Services"
        }
    ],
    "sg:phone":"+1 605 332 2173",
    "sg:postcode":"57103",
    "sg:province":"SD",
    "sg:tags":[
        "wrecker"
    ],
    "wof:name":"Ace Crane & Towing Inc",
    "wof:placetype":"venue"
},
  "geometry": {"coordinates":[-96.711365,43.560144],"type":"Point"}
}