{
  "type": "Feature",
  "properties": {
    "addr:full":"208 W Capitol Ave Pierre SD 57501",
    "addr:housenumber":"208",
    "addr:postcode":"57501",
    "addr:street":"W Capitol Ave",
    "iso:country":"US",
    "sg:address":"208 W Capitol Ave",
    "sg:city":"Pierre",
    "sg:classifiers":[
        {
            "category":"Wholesale",
            "subcategory":"Furniture",
            "type":"Manufacturing & Wholesale Goods"
        }
    ],
    "sg:phone":"+1 605 945 3118",
    "sg:postcode":"57501",
    "sg:province":"SD",
    "sg:website":"www.kleinsoffice.com",
    "wof:name":"Klein's Office Furniture",
    "wof:placetype":"venue"
},
  "geometry": {"coordinates":[-100.353964,44.370427],"type":"Point"}
}