{
  "type": "Feature",
  "properties": {
    "addr:full":"44636 298th St Irene SD 57037",
    "addr:housenumber":"44636",
    "addr:postcode":"57037",
    "addr:street":"298Th St",
    "iso:country":"US",
    "sg:address":"44636 298th St",
    "sg:city":"Irene",
    "sg:classifiers":[
        {
            "category":"Real Estate",
            "subcategory":"Real Estate Operator",
            "type":"Services"
        }
    ],
    "sg:phone":"+1 605 263 3861",
    "sg:postcode":"57037",
    "sg:province":"SD",
    "sg:tags":[
        "property",
        "lessor"
    ],
    "wof:name":"Dennis Pospishil",
    "wof:placetype":"venue"
},
  "geometry": {"coordinates":[-97.259685,43.069715],"type":"Point"}
}