{
  "type": "Feature",
  "properties": {
    "iso:country":"US",
    "sg:address":"26110 423rd Ave",
    "sg:city":"Alexandria",
    "sg:classifiers":[
        {
            "category":"Farming",
            "subcategory":"Farm",
            "type":"Manufacturing & Wholesale Goods"
        }
    ],
    "sg:phone":"+1 605 239 4650",
    "sg:postcode":"57311",
    "sg:province":"SD",
    "sg:tags":[
        "equipment",
        "machinery",
        "crop",
        "general"
    ],
    "wof:name":"Schroeder Farm Equipment",
    "wof:placetype":"venue"
},
  "geometry": {"coordinates":[-97.746993,43.599691],"type":"Point"}
}