{
  "type": "Feature",
  "properties": {
    "iso:country":"US",
    "sg:address":"555 Main St",
    "sg:city":"Big Stone City",
    "sg:classifiers":[
        {
            "category":"Autos & Motor Vehicles",
            "subcategory":"Auto Supplies",
            "type":"Retail Goods"
        }
    ],
    "sg:phone":"+1 605 862 8353",
    "sg:postcode":"57216",
    "sg:province":"SD",
    "sg:tags":[
        "automobile",
        "parts"
    ],
    "wof:name":"Main Street Svc Ctr",
    "wof:placetype":"venue"
},
  "geometry": {"coordinates":[-96.46379899999999,45.29157],"type":"Point"}
}