{
  "type": "Feature",
  "properties": {
    "addr:full":"300 E 3rd St Yankton SD 57078",
    "addr:housenumber":"300",
    "addr:postcode":"57078",
    "addr:street":"E 3Rd St",
    "iso:country":"US",
    "sg:address":"300 E 3rd St",
    "sg:city":"Yankton",
    "sg:classifiers":[
        {
            "category":"Restaurant",
            "type":"Food & Drink"
        }
    ],
    "sg:phone":"+1 605 665 5771",
    "sg:postcode":"57078",
    "sg:province":"SD",
    "wof:name":"Black Steer",
    "wof:placetype":"venue"
},
  "geometry": {"coordinates":[-97.38911400000001,42.869727],"type":"Point"}
}