{
  "type": "Feature",
  "properties": {
    "iso:country":"US",
    "sg:address":"129 Blackbird Rd",
    "sg:city":"Pierre",
    "sg:classifiers":[
        {
            "category":"Recreation",
            "type":"Entertainment"
        }
    ],
    "sg:phone":"+1 605 224 6810",
    "sg:postcode":"57501",
    "sg:province":"SD",
    "sg:tags":[
        "party",
        "fishing"
    ],
    "wof:name":"Mcclelland's Guide Svc",
    "wof:placetype":"venue"
},
  "geometry": {"coordinates":[-100.35443100000001,44.463208],"type":"Point"}
}