{
  "type": "Feature",
  "properties": {
    "addr:full":"41272 243rd St Artesian SD 57314",
    "addr:housenumber":"41272",
    "addr:postcode":"57314",
    "addr:street":"243Rd St",
    "iso:country":"US",
    "sg:address":"41272 243rd St",
    "sg:city":"Artesian",
    "sg:phone":"+1 605 527 2643",
    "sg:postcode":"57314",
    "sg:province":"SD",
    "sg:tags":[
        "farm",
        "corn"
    ],
    "wof:name":"Jerry Nicholson",
    "wof:placetype":"venue"
},
  "geometry": {"coordinates":[-97.957054,43.865222],"type":"Point"}
}