{
  "type": "Feature",
  "properties": {
    "iso:country":"US",
    "sg:address":"3216 E Fairground Loop",
    "sg:city":"Spearfish",
    "sg:classifiers":[
        {
            "category":"Retail",
            "subcategory":"Repair Shop",
            "type":"Services"
        }
    ],
    "sg:phone":"+1 605 642 1776",
    "sg:postcode":"57783",
    "sg:province":"SD",
    "sg:tags":[
        "trade",
        "welding",
        "contractor"
    ],
    "wof:name":"Northwest Welding Inc",
    "wof:placetype":"venue"
},
  "geometry": {"coordinates":[-103.88644600000001,44.519903],"type":"Point"}
}