{
  "type": "Feature",
  "properties": {
    "iso:country":"US",
    "sg:address":"2220 Yorkshire Dr",
    "sg:city":"Brookings",
    "sg:classifiers":[
        {
            "category":"Health Services",
            "subcategory":"Doctor",
            "type":"Services"
        }
    ],
    "sg:phone":"+1 605 697 6262",
    "sg:postcode":"57006",
    "sg:province":"SD",
    "sg:tags":[
        "dentist"
    ],
    "wof:name":"Thomas A Schmanski DDS",
    "wof:placetype":"venue"
},
  "geometry": {"coordinates":[-96.763014,44.30598],"type":"Point"}
}