{
  "type": "Feature",
  "properties": {
    "addr:full":"522 S Main St Aberdeen SD 57401",
    "addr:housenumber":"522",
    "addr:postcode":"57401",
    "addr:street":"S Main St",
    "iso:country":"US",
    "sg:address":"522 S Main St",
    "sg:city":"Aberdeen",
    "sg:classifiers":[
        {
            "category":"Restaurant",
            "type":"Food & Drink"
        }
    ],
    "sg:menulink":"http://www.allmenus.com/sd/aberdeen/78201-dominos-pizza/menu/",
    "sg:phone":"+1 605 225 5555",
    "sg:postcode":"57401",
    "sg:province":"SD",
    "sg:tags":[
        "american",
        "wing",
        "pizza"
    ],
    "wof:name":"Domino's Pizza",
    "wof:placetype":"venue"
},
  "geometry": {"coordinates":[-98.48805299999999,45.459884],"type":"Point"}
}