{
  "type": "Feature",
  "properties": {
    "iso:country":"US",
    "sg:address":"538 Crook St",
    "sg:city":"Custer",
    "sg:classifiers":[
        {
            "category":"Retail",
            "subcategory":"Auto Repair",
            "type":"Services"
        }
    ],
    "sg:phone":"+1 605 673 5147",
    "sg:postcode":"57730",
    "sg:province":"SD",
    "sg:tags":[
        "body"
    ],
    "wof:name":"Quality Auto Body",
    "wof:placetype":"venue"
},
  "geometry": {"coordinates":[-103.600836,43.767368],"type":"Point"}
}