{
  "type": "Feature",
  "properties": {
    "iso:country":"US",
    "sg:address":"43765 298th St",
    "sg:city":"Utica",
    "sg:classifiers":[
        {
            "category":"Farming",
            "subcategory":"Livestock Farm",
            "type":"Manufacturing & Wholesale Goods"
        }
    ],
    "sg:phone":"+1 605 364 7468",
    "sg:postcode":"57067",
    "sg:province":"SD",
    "sg:tags":[
        "feedlot",
        "corn",
        "soybean",
        "beef",
        "cattle"
    ],
    "wof:name":"Harold Klimisch",
    "wof:placetype":"venue"
},
  "geometry": {"coordinates":[-97.44291,43.067785],"type":"Point"}
}