{
  "type": "Feature",
  "properties": {
    "addr:full":"1600 North Dr Sioux Falls SD 57104",
    "addr:housenumber":"1600",
    "addr:postcode":"57104",
    "addr:street":"North Dr",
    "iso:country":"US",
    "sg:address":"1600 North Dr",
    "sg:city":"Sioux Falls",
    "sg:classifiers":[
        {
            "category":"Government",
            "subcategory":"Office",
            "type":"Public Place"
        }
    ],
    "sg:phone":"+1 605 367 5040",
    "sg:postcode":"57104",
    "sg:province":"SD",
    "wof:name":"Pardons & Paroles Board",
    "wof:placetype":"venue"
},
  "geometry": {"coordinates":[-96.722729,43.568599],"type":"Point"}
}