{
  "type": "Feature",
  "properties": {
    "iso:country":"US",
    "sg:address":"46298 265th St",
    "sg:city":"Hartford",
    "sg:classifiers":[
        {
            "category":"Autos & Motor Vehicles",
            "subcategory":"Fuel & Gas Station",
            "type":"Retail Goods"
        }
    ],
    "sg:phone":"+1 605 526 3547",
    "sg:postcode":"57033",
    "sg:province":"SD",
    "sg:tags":[
        "gasoline",
        "product",
        "station",
        "petroleum",
        "oil"
    ],
    "wof:name":"Wall Lake Oil Company",
    "wof:placetype":"venue"
},
  "geometry": {"coordinates":[-96.950272,43.543296],"type":"Point"}
}