{
  "type": "Feature",
  "properties": {
    "iso:country":"US",
    "sg:address":"2323 Junction Ave",
    "sg:city":"Sturgis",
    "sg:classifiers":[
        {
            "category":"Wholesale",
            "subcategory":"Farm Supplies",
            "type":"Manufacturing & Wholesale Goods"
        }
    ],
    "sg:phone":"+1 605 347 4578",
    "sg:postcode":"57785",
    "sg:province":"SD",
    "sg:tags":[
        "feed"
    ],
    "wof:name":"Foothills Seed Inc",
    "wof:placetype":"venue"
},
  "geometry": {"coordinates":[-103.509047,44.400029],"type":"Point"}
}