{
  "type": "Feature",
  "properties": {
    "addr:full":"340 E Norton Ave Salem SD 57058",
    "addr:housenumber":"340",
    "addr:postcode":"57058",
    "addr:street":"E Norton Ave",
    "iso:country":"US",
    "sg:address":"340 E Norton Ave",
    "sg:city":"Salem",
    "sg:classifiers":[
        {
            "category":"Farming",
            "subcategory":"Farm",
            "type":"Manufacturing & Wholesale Goods"
        }
    ],
    "sg:phone":"+1 605 425 2446",
    "sg:postcode":"57058",
    "sg:province":"SD",
    "sg:tags":[
        "crop",
        "general"
    ],
    "wof:name":"Eichacker John",
    "wof:placetype":"venue"
},
  "geometry": {"coordinates":[-97.383313,43.725454],"type":"Point"}
}