{
  "type": "Feature",
  "properties": {
    "iso:country":"US",
    "sg:address":"119 E Main St",
    "sg:city":"Vermillion",
    "sg:classifiers":[
        {
            "category":"Professional",
            "subcategory":"Lawyer & Legal Services",
            "type":"Services"
        }
    ],
    "sg:phone":"+1 605 624 2667",
    "sg:postcode":"57069",
    "sg:province":"SD",
    "sg:tags":[
        "attorney"
    ],
    "wof:name":"Linda Kogel Law Office",
    "wof:placetype":"venue"
},
  "geometry": {"coordinates":[-96.93038900000001,42.779334],"type":"Point"}
}