{
  "type": "Feature",
  "properties": {
    "addr:full":"200 W Holly Blvd Brandon SD 57005",
    "addr:housenumber":"200",
    "addr:postcode":"57005",
    "addr:street":"W Holly Blvd",
    "iso:country":"US",
    "sg:address":"200 W Holly Blvd",
    "sg:city":"Brandon",
    "sg:classifiers":[
        {
            "category":"Home & Garden",
            "subcategory":"Garden Supply",
            "type":"Retail Goods"
        }
    ],
    "sg:phone":"+1 605 582 7039",
    "sg:postcode":"57005",
    "sg:province":"SD",
    "sg:tags":[
        "nurseryman"
    ],
    "wof:name":"Natural Spring Nursery",
    "wof:placetype":"venue"
},
  "geometry": {"coordinates":[-96.594595,43.594646],"type":"Point"}
}