{
  "type": "Feature",
  "properties": {
    "iso:country":"US",
    "sg:address":"435 Washington Ave N",
    "sg:city":"Madison",
    "sg:classifiers":[
        {
            "category":"Shopping",
            "subcategory":"Discount & Variety Stores",
            "type":"Retail Goods"
        }
    ],
    "sg:phone":"+1 605 256 4398",
    "sg:postcode":"57042",
    "sg:province":"SD",
    "sg:tags":[
        "fabric"
    ],
    "wof:name":"B F Sams Inc",
    "wof:placetype":"venue"
},
  "geometry": {"coordinates":[-97.109846,44.008433],"type":"Point"}
}