{
  "type": "Feature",
  "properties": {
    "iso:country":"US",
    "sg:address":"12211 410th Ave",
    "sg:city":"Claremont",
    "sg:phone":"+1 605 294 5342",
    "sg:postcode":"57432",
    "sg:province":"SD",
    "sg:tags":[
        "farm",
        "corn",
        "wheat",
        "soybean"
    ],
    "wof:name":"James Cutler Farm",
    "wof:placetype":"venue"
},
  "geometry": {"coordinates":[-98.02102600000001,45.616035],"type":"Point"}
}