{
  "type": "Feature",
  "properties": {
    "addr:full":"9 E Main St Vermillion SD 57069",
    "addr:housenumber":"9",
    "addr:postcode":"57069",
    "addr:street":"E Main St",
    "iso:country":"US",
    "sg:address":"9 E Main St",
    "sg:city":"Vermillion",
    "sg:classifiers":[
        {
            "category":"Health Services",
            "subcategory":"Chiropractor",
            "type":"Services"
        }
    ],
    "sg:phone":"+1 605 624 8805",
    "sg:postcode":"57069",
    "sg:province":"SD",
    "wof:name":"Mehlhaf Duane C Dr",
    "wof:placetype":"venue"
},
  "geometry": {"coordinates":[-96.93196500000001,42.779328],"type":"Point"}
}