{
  "type": "Feature",
  "properties": {
    "addr:full":"12963 Prairewood Cir Aberdeen SD 57401",
    "addr:housenumber":"12963",
    "addr:postcode":"57401",
    "addr:street":"Prairewood Cir",
    "iso:country":"US",
    "sg:address":"12963 Prairewood Cir",
    "sg:city":"Aberdeen",
    "sg:classifiers":[
        {
            "category":"Home & Garden",
            "subcategory":"Household Appliances",
            "type":"Retail Goods"
        }
    ],
    "sg:phone":"+1 605 225 7182",
    "sg:postcode":"57401",
    "sg:province":"SD",
    "sg:tags":[
        "filtration",
        "unit",
        "air"
    ],
    "wof:name":"Northland Associates",
    "wof:placetype":"venue"
},
  "geometry": {"coordinates":[-98.423552,45.509004],"type":"Point"}
}