{
  "type": "Feature",
  "properties": {
    "iso:country":"US",
    "sg:address":"23658 436th Ave",
    "sg:city":"Howard",
    "sg:classifiers":[
        {
            "category":"Farming",
            "subcategory":"Livestock Farm",
            "type":"Manufacturing & Wholesale Goods"
        }
    ],
    "sg:phone":"+1 605 772 4625",
    "sg:postcode":"57349",
    "sg:province":"SD",
    "sg:tags":[
        "beef",
        "feedlot",
        "cattle"
    ],
    "wof:name":"Bob Gassman",
    "wof:placetype":"venue"
},
  "geometry": {"coordinates":[-97.489988,43.955899],"type":"Point"}
}