{
  "type": "Feature",
  "properties": {
    "addr:full":"1 S Main St Aberdeen SD 57401",
    "addr:housenumber":"1",
    "addr:postcode":"57401",
    "addr:street":"S Main St",
    "iso:country":"US",
    "sg:address":"1 S Main St",
    "sg:city":"Aberdeen",
    "sg:classifiers":[
        {
            "category":"Insurance",
            "subcategory":"Insurance Agent",
            "type":"Services"
        }
    ],
    "sg:phone":"+1 605 229 3610",
    "sg:postcode":"57401",
    "sg:province":"SD",
    "wof:name":"Equitable Life Assurance Soc",
    "wof:placetype":"venue"
},
  "geometry": {"coordinates":[-98.488,45.46513],"type":"Point"}
}