{
  "type": "Feature",
  "properties": {
    "iso:country":"US",
    "sg:address":"919 9th Ave",
    "sg:city":"Brookings",
    "sg:classifiers":[
        {
            "category":"Organizations",
            "subcategory":"Religious Organization",
            "type":"Services"
        }
    ],
    "sg:phone":"+1 605 692 2201",
    "sg:postcode":"57006",
    "sg:province":"SD",
    "wof:name":"Wels Lutheran Student Center",
    "wof:placetype":"venue"
},
  "geometry": {"coordinates":[-96.790411,44.316588],"type":"Point"}
}