{
  "type": "Feature",
  "properties": {
    "addr:full":"1035 N Main St Spearfish SD 57783",
    "addr:housenumber":"1035",
    "addr:postcode":"57783",
    "addr:street":"N Main St",
    "iso:country":"US",
    "sg:address":"1035 N Main St",
    "sg:city":"Spearfish",
    "sg:classifiers":[
        {
            "category":"Travel",
            "subcategory":"Travel Agent",
            "type":"Entertainment"
        }
    ],
    "sg:phone":"+1 605 717 0685",
    "sg:postcode":"57783",
    "sg:province":"SD",
    "sg:tags":[
        "agency",
        "bureau"
    ],
    "wof:name":"Cruisin Easy",
    "wof:placetype":"venue"
},
  "geometry": {"coordinates":[-103.86015,44.493951],"type":"Point"}
}