{
  "type": "Feature",
  "properties": {
    "iso:country":"US",
    "sg:address":"3101 E 10th St",
    "sg:city":"Sioux Falls",
    "sg:classifiers":[
        {
            "category":"Home & Garden",
            "subcategory":"Hardware",
            "type":"Retail Goods"
        },
        {
            "category":"Education",
            "subcategory":"School",
            "type":"Public Place"
        }
    ],
    "sg:phone":"+1 605 336 1429",
    "sg:postcode":"57103",
    "sg:province":"SD",
    "sg:tags":[
        "app",
        "material"
    ],
    "wof:name":"Campbell Supply Company",
    "wof:placetype":"venue"
},
  "geometry": {"coordinates":[-96.686386,43.546627],"type":"Point"}
}