{
  "type": "Feature",
  "properties": {
    "iso:country":"US",
    "sg:address":"408 State Hwy 77",
    "sg:city":"Dell Rapids",
    "sg:classifiers":[
        {
            "category":"Professional",
            "subcategory":"Management & Consulting",
            "type":"Services"
        }
    ],
    "sg:phone":"+1 605 428 5353",
    "sg:postcode":"57022",
    "sg:province":"SD",
    "wof:name":"Newman Associates",
    "wof:placetype":"venue"
},
  "geometry": {"coordinates":[-96.720342,43.823976],"type":"Point"}
}