{
  "type": "Feature",
  "properties": {
    "iso:country":"US",
    "sg:address":"4605 W Custer Ln",
    "sg:city":"Sioux Falls",
    "sg:classifiers":[
        {
            "category":"Organizations",
            "subcategory":"Community Association",
            "type":"Services"
        }
    ],
    "sg:phone":"+1 605 361 1390",
    "sg:postcode":"57106",
    "sg:province":"SD",
    "wof:name":"South Dakota Federation of Gar",
    "wof:placetype":"venue"
},
  "geometry": {"coordinates":[-96.783151,43.503085],"type":"Point"}
}