{
  "type": "Feature",
  "properties": {
    "addr:full":"301 S Kansas St Clark SD 57225",
    "addr:housenumber":"301",
    "addr:postcode":"57225",
    "addr:street":"S Kansas St",
    "iso:country":"US",
    "sg:address":"301 S Kansas St",
    "sg:city":"Clark",
    "sg:phone":"+1 605 532 5795",
    "sg:postcode":"57225",
    "sg:province":"SD",
    "sg:tags":[
        "farm",
        "wheat"
    ],
    "wof:name":"Jerry Bowers",
    "wof:placetype":"venue"
},
  "geometry": {"coordinates":[-97.729832,44.874797],"type":"Point"}
}