{
  "type": "Feature",
  "properties": {
    "iso:country":"US",
    "sg:address":"1201 Mickelson Dr",
    "sg:city":"Watertown",
    "sg:classifiers":[
        {
            "category":"Health Services",
            "subcategory":"Doctor",
            "type":"Services"
        }
    ],
    "sg:phone":"+1 605 882 2630",
    "sg:postcode":"57201",
    "sg:province":"SD",
    "sg:tags":[
        "medical"
    ],
    "wof:name":"Michael J Vener MD",
    "wof:placetype":"venue"
},
  "geometry": {"coordinates":[-97.06271599999999,44.887109],"type":"Point"}
}