{
  "type": "Feature",
  "properties": {
    "iso:country":"US",
    "sg:address":"41362 270th St",
    "sg:city":"Dimock",
    "sg:classifiers":[
        {
            "category":"Farming",
            "subcategory":"Livestock Farm",
            "type":"Manufacturing & Wholesale Goods"
        }
    ],
    "sg:phone":"+1 605 928 3201",
    "sg:postcode":"57331",
    "sg:province":"SD",
    "sg:tags":[
        "wheat",
        "beef",
        "corn",
        "soybean",
        "cattle",
        "feedlot"
    ],
    "wof:name":"Kevin Zwinger",
    "wof:placetype":"venue"
},
  "geometry": {"coordinates":[-97.922998,43.471175],"type":"Point"}
}