{
  "type": "Feature",
  "properties": {
    "addr:full":"707 Mulberry St Yankton SD 57078",
    "addr:housenumber":"707",
    "addr:postcode":"57078",
    "addr:street":"Mulberry St",
    "iso:country":"US",
    "sg:address":"707 Mulberry St",
    "sg:city":"Yankton",
    "sg:classifiers":[
        {
            "category":"Building & Trades",
            "subcategory":"Construction",
            "type":"Services"
        }
    ],
    "sg:phone":"+1 605 665 1572",
    "sg:postcode":"57078",
    "sg:province":"SD",
    "sg:tags":[
        "general",
        "contractor"
    ],
    "wof:name":"Mondragon Construction",
    "wof:placetype":"venue"
},
  "geometry": {"coordinates":[-97.3874,42.874162],"type":"Point"}
}