{
  "type": "Feature",
  "properties": {
    "iso:country":"US",
    "sg:address":"40395 275th St",
    "sg:city":"Parkston",
    "sg:phone":"+1 605 928 3750",
    "sg:postcode":"57366",
    "sg:province":"SD",
    "sg:tags":[
        "beef",
        "farm",
        "cash",
        "grain",
        "cattle",
        "feedlot"
    ],
    "wof:name":"Kummer Florian Farm",
    "wof:placetype":"venue"
},
  "geometry": {"coordinates":[-98.13049700000001,43.398149],"type":"Point"}
}