{
  "type": "Feature",
  "properties": {
    "addr:full":"1105 E 4th Ave Milbank SD 57252",
    "addr:housenumber":"1105",
    "addr:postcode":"57252",
    "addr:street":"E 4Th Ave",
    "iso:country":"US",
    "sg:address":"1105 E 4th Ave",
    "sg:city":"Milbank",
    "sg:classifiers":[
        {
            "category":"Travel",
            "subcategory":"Hotels & Motels",
            "type":"Entertainment"
        }
    ],
    "sg:phone":"+1 605 432 4527",
    "sg:postcode":"57252",
    "sg:province":"SD",
    "sg:tags":[
        "lodging"
    ],
    "sg:website":"http://www.manormotel.com",
    "wof:name":"Manor Motel",
    "wof:placetype":"venue"
},
  "geometry": {"coordinates":[-96.62286,45.21897],"type":"Point"}
}