{
  "type": "Feature",
  "properties": {
    "addr:full":"665 Disk Dr Rapid City SD 57701",
    "addr:housenumber":"665",
    "addr:postcode":"57701",
    "addr:street":"Disk Dr",
    "iso:country":"US",
    "sg:address":"665 Disk Dr",
    "sg:city":"Rapid City",
    "sg:classifiers":[
        {
            "category":"Restaurant",
            "type":"Food & Drink"
        }
    ],
    "sg:menulink":"http://www.allmenus.com/sd/rapid-city/27994-outback-steakhouse/menu/",
    "sg:phone":"+1 605 341 1192",
    "sg:postcode":"57701",
    "sg:province":"SD",
    "sg:tags":[
        "american",
        "steakhouse"
    ],
    "wof:name":"Outback Steakhouse",
    "wof:placetype":"venue"
},
  "geometry": {"coordinates":[-103.222266,44.107732],"type":"Point"}
}