{
  "type": "Feature",
  "properties": {
    "iso:country":"US",
    "sg:address":"47544 316th St",
    "sg:city":"Elk Point",
    "sg:classifiers":[
        {
            "category":"Professional",
            "type":"Services"
        }
    ],
    "sg:phone":"+1 605 356 3312",
    "sg:postcode":"57025",
    "sg:province":"SD",
    "sg:tags":[
        "establishment"
    ],
    "wof:name":"Central Union",
    "wof:placetype":"venue"
},
  "geometry": {"coordinates":[-96.68840899999999,42.805722],"type":"Point"}
}