{
  "type": "Feature",
  "properties": {
    "iso:country":"US",
    "sg:address":"125 E 4th Ave",
    "sg:city":"Groton",
    "sg:classifiers":[
        {
            "category":"Education",
            "subcategory":"School",
            "type":"Public Place"
        }
    ],
    "sg:phone":"+1 605 397 2351",
    "sg:postcode":"57445",
    "sg:province":"SD",
    "wof:name":"Groton Public School Supt",
    "wof:placetype":"venue"
},
  "geometry": {"coordinates":[-98.101209,45.449352],"type":"Point"}
}