{
  "type": "Feature",
  "properties": {
    "addr:full":"520 10th St NW Watertown SD 57201",
    "addr:housenumber":"520",
    "addr:postcode":"57201",
    "addr:street":"10Th St Nw",
    "iso:country":"US",
    "sg:address":"520 10th St NW",
    "sg:city":"Watertown",
    "sg:classifiers":[
        {
            "category":"Recreation",
            "subcategory":"Arcade",
            "type":"Entertainment"
        }
    ],
    "sg:phone":"+1 605 882 3572",
    "sg:postcode":"57201",
    "sg:province":"SD",
    "sg:tags":[
        "casino"
    ],
    "wof:name":"Grand Casino",
    "wof:placetype":"venue"
},
  "geometry": {"coordinates":[-97.13182399999999,44.907837],"type":"Point"}
}