{
  "type": "Feature",
  "properties": {
    "iso:country":"US",
    "sg:address":"1123 Ohio Ave SW",
    "sg:city":"Huron",
    "sg:classifiers":[
        {
            "category":"Retail",
            "subcategory":"Repair Shop",
            "type":"Services"
        }
    ],
    "sg:phone":"+1 605 352 6292",
    "sg:postcode":"57350",
    "sg:province":"SD",
    "sg:tags":[
        "taxidermist"
    ],
    "wof:name":"Del's Taxidermy",
    "wof:placetype":"venue"
},
  "geometry": {"coordinates":[-98.219182,44.353547],"type":"Point"}
}