{
  "type": "Feature",
  "properties": {
    "iso:country":"US",
    "sg:address":"6829 W Honeysuckle Ct",
    "sg:city":"Sioux Falls",
    "sg:classifiers":[
        {
            "category":"Professional",
            "subcategory":"Business Services",
            "type":"Services"
        }
    ],
    "sg:phone":"+1 605 361 9387",
    "sg:postcode":"57106",
    "sg:province":"SD",
    "wof:name":"Kubly Enterprises Inc",
    "wof:placetype":"venue"
},
  "geometry": {"coordinates":[-96.809509,43.535129],"type":"Point"}
}