{
  "type": "Feature",
  "properties": {
    "iso:country":"US",
    "sg:address":"422 W Main St",
    "sg:city":"Lead",
    "sg:classifiers":[
        {
            "category":"Museum",
            "type":"Entertainment"
        }
    ],
    "sg:phone":"+1 605 584 1461",
    "sg:postcode":"57754",
    "sg:province":"SD",
    "sg:tags":[
        "organization",
        "arts",
        "information"
    ],
    "wof:name":"Historic Deadwood Lead Arts",
    "wof:placetype":"venue"
},
  "geometry": {"coordinates":[-103.768838,44.352002],"type":"Point"}
}