{
  "type": "Feature",
  "properties": {
    "iso:country":"US",
    "sg:address":"1025 S Cleveland Ave",
    "sg:city":"Sioux Falls",
    "sg:classifiers":[
        {
            "category":"Food & Beverages",
            "subcategory":"Groceries & Convenience Stores",
            "type":"Retail Goods"
        }
    ],
    "sg:phone":"+1 605 332 4212",
    "sg:postcode":"57103",
    "sg:province":"SD",
    "sg:tags":[
        "grocer"
    ],
    "wof:name":"Andy's Affiliated Foods",
    "wof:placetype":"venue"
},
  "geometry": {"coordinates":[-96.69139199999999,43.536669],"type":"Point"}
}