{
  "type": "Feature",
  "properties": {
    "iso:country":"US",
    "sg:address":"500 A St",
    "sg:city":"Edgemont",
    "sg:classifiers":[
        {
            "category":"Travel",
            "subcategory":"Hotels & Motels",
            "type":"Entertainment"
        }
    ],
    "sg:phone":"+1 605 662 7244",
    "sg:postcode":"57735",
    "sg:province":"SD",
    "wof:name":"Rainbow Motel",
    "wof:placetype":"venue"
},
  "geometry": {"coordinates":[-103.830596,43.304071],"type":"Point"}
}