{
  "type": "Feature",
  "properties": {
    "addr:full":"30532 University Rd Centerville SD 57014",
    "addr:housenumber":"30532",
    "addr:postcode":"57014",
    "addr:street":"University Rd",
    "iso:country":"US",
    "sg:address":"30532 University Rd",
    "sg:city":"Centerville",
    "sg:phone":"+1 605 253 2271",
    "sg:postcode":"57014",
    "sg:province":"SD",
    "sg:tags":[
        "farm",
        "grain",
        "cash"
    ],
    "wof:name":"Jeffrey Hansen",
    "wof:placetype":"venue"
},
  "geometry": {"coordinates":[-96.904431,42.963172],"type":"Point"}
}