{
  "type": "Feature",
  "properties": {
    "iso:country":"US",
    "sg:address":"301 E 14th St",
    "sg:city":"Sioux Falls",
    "sg:classifiers":[
        {
            "category":"Professional",
            "subcategory":"Accounting & Tax Preparation",
            "type":"Services"
        }
    ],
    "sg:phone":"+1 605 338 1932",
    "sg:postcode":"57104",
    "sg:province":"SD",
    "wof:name":"Liberko Peter CPA",
    "wof:placetype":"venue"
},
  "geometry": {"coordinates":[-96.722307,43.541442],"type":"Point"}
}