{
  "type": "Feature",
  "properties": {
    "addr:full":"43228 282nd St Menno SD 57045",
    "addr:housenumber":"43228",
    "addr:postcode":"57045",
    "addr:street":"282Nd St",
    "iso:country":"US",
    "sg:address":"43228 282nd St",
    "sg:city":"Menno",
    "sg:phone":"+1 605 387 5716",
    "sg:postcode":"57045",
    "sg:province":"SD",
    "sg:tags":[
        "hog",
        "farm",
        "corn",
        "soybean",
        "or",
        "feedlot"
    ],
    "wof:name":"Lori Mehlhaff",
    "wof:placetype":"venue"
},
  "geometry": {"coordinates":[-97.555353,43.29904],"type":"Point"}
}