{
  "type": "Feature",
  "properties": {
    "iso:country":"US",
    "sg:address":"408 N Main St",
    "sg:city":"Mitchell",
    "sg:classifiers":[
        {
            "category":"Personal",
            "subcategory":"Tattoo Parlor",
            "type":"Services"
        }
    ],
    "sg:phone":"+1 605 996 1778",
    "sg:postcode":"57301",
    "sg:province":"SD",
    "sg:tags":[
        "tattooing"
    ],
    "wof:name":"T C Body Art",
    "wof:placetype":"venue"
},
  "geometry": {"coordinates":[-98.02548,43.713429],"type":"Point"}
}