{
  "type": "Feature",
  "properties": {
    "addr:full":"37126 182nd St Tulare SD 57476",
    "addr:housenumber":"37126",
    "addr:postcode":"57476",
    "addr:street":"182Nd St",
    "iso:country":"US",
    "sg:address":"37126 182nd St",
    "sg:city":"Tulare",
    "sg:phone":"+1 605 472 1563",
    "sg:postcode":"57476",
    "sg:province":"SD",
    "sg:tags":[
        "farm",
        "field",
        "corn",
        "wheat",
        "crop"
    ],
    "wof:name":"Doug Zens",
    "wof:placetype":"venue"
},
  "geometry": {"coordinates":[-98.754581,44.750567],"type":"Point"}
}