{
  "type": "Feature",
  "properties": {
    "addr:full":"201 NE 13th St Beresford SD 57004",
    "addr:housenumber":"201",
    "addr:postcode":"57004",
    "addr:street":"Ne 13Th St",
    "iso:country":"US",
    "sg:address":"201 NE 13th St",
    "sg:city":"Beresford",
    "sg:classifiers":[
        {
            "category":"Sports & Exercise",
            "subcategory":"Gym",
            "type":"Entertainment"
        }
    ],
    "sg:phone":"+1 605 763 8082",
    "sg:postcode":"57004",
    "sg:province":"SD",
    "sg:tags":[
        "fitness",
        "physical",
        "facility"
    ],
    "wof:name":"Ultimate Fitness Inc",
    "wof:placetype":"venue"
},
  "geometry": {"coordinates":[-96.76656199999999,43.08218],"type":"Point"}
}