{
  "type": "Feature",
  "properties": {
    "iso:country":"US",
    "sg:address":"301 Elk St",
    "sg:city":"Elkton",
    "sg:classifiers":[
        {
            "category":"Organizations",
            "subcategory":"Religious Organization",
            "type":"Services"
        }
    ],
    "sg:phone":"+1 605 542 5351",
    "sg:postcode":"57026",
    "sg:province":"SD",
    "sg:tags":[
        "church"
    ],
    "wof:name":"First Baptist Church Inc",
    "wof:placetype":"venue"
},
  "geometry": {"coordinates":[-96.481004,44.235078],"type":"Point"}
}