{
  "type": "Feature",
  "properties": {
    "addr:full":"37759 159th St Northville SD 57465",
    "addr:housenumber":"37759",
    "addr:postcode":"57465",
    "addr:street":"159Th St",
    "iso:country":"US",
    "sg:address":"37759 159th St",
    "sg:city":"Northville",
    "sg:phone":"+1 605 887 3142",
    "sg:postcode":"57465",
    "sg:province":"SD",
    "sg:tags":[
        "farm",
        "grain",
        "cash"
    ],
    "wof:name":"Hoellein Eldon",
    "wof:placetype":"venue"
},
  "geometry": {"coordinates":[-98.637986,45.086022],"type":"Point"}
}