{
  "type": "Feature",
  "properties": {
    "addr:full":"5060 Pine Tree Dr Rapid City SD 57702",
    "addr:housenumber":"5060",
    "addr:postcode":"57702",
    "addr:street":"Pine Tree Dr",
    "iso:country":"US",
    "sg:address":"5060 Pine Tree Dr",
    "sg:city":"Rapid City",
    "sg:classifiers":[
        {
            "category":"Building & Trades",
            "subcategory":"Construction",
            "type":"Services"
        }
    ],
    "sg:phone":"+1 605 341 6403",
    "sg:postcode":"57702",
    "sg:province":"SD",
    "sg:tags":[
        "house"
    ],
    "wof:name":"McGough Construction",
    "wof:placetype":"venue"
},
  "geometry": {"coordinates":[-103.27855599999999,44.034553],"type":"Point"}
}