{
  "type": "Feature",
  "properties": {
    "iso:country":"US",
    "sg:address":"806 Kansas Ave SE",
    "sg:city":"Huron",
    "sg:classifiers":[
        {
            "category":"Real Estate",
            "subcategory":"Real Estate Operator",
            "type":"Services"
        }
    ],
    "sg:phone":"+1 605 352 3316",
    "sg:postcode":"57350",
    "sg:province":"SD",
    "sg:tags":[
        "building",
        "apartment"
    ],
    "wof:name":"Midwest Distributors",
    "wof:placetype":"venue"
},
  "geometry": {"coordinates":[-98.21237000000001,44.357185],"type":"Point"}
}