{
  "type": "Feature",
  "properties": {
    "iso:country":"US",
    "sg:address":"419 E 13th Ave",
    "sg:city":"Mitchell",
    "sg:classifiers":[
        {
            "category":"Real Estate",
            "subcategory":"Real Estate Agent",
            "type":"Services"
        }
    ],
    "sg:phone":"+1 605 996 6202",
    "sg:postcode":"57301",
    "sg:province":"SD",
    "wof:name":"B & E Properties",
    "wof:placetype":"venue"
},
  "geometry": {"coordinates":[-98.01739,43.721679],"type":"Point"}
}