{
  "type": "Feature",
  "properties": {
    "iso:country":"US",
    "sg:address":"3423 W Main St",
    "sg:city":"Rapid City",
    "sg:classifiers":[
        {
            "category":"Banks & Credit Unions",
            "subcategory":"Bank",
            "type":"Services"
        }
    ],
    "sg:phone":"+1 605 341 0901",
    "sg:postcode":"57702",
    "sg:province":"SD",
    "sg:tags":[
        "loan",
        "real estate"
    ],
    "wof:name":"Lawton Mortgage",
    "wof:placetype":"venue"
},
  "geometry": {"coordinates":[-103.276495,44.08208],"type":"Point"}
}