{
  "type": "Feature",
  "properties": {
    "iso:country":"US",
    "sg:address":"829 S Foster Ave",
    "sg:city":"Sioux Falls",
    "sg:classifiers":[
        {
            "category":"Professional",
            "subcategory":"Advertising",
            "type":"Services"
        }
    ],
    "sg:phone":"+1 605 357 7070",
    "sg:postcode":"57103",
    "sg:province":"SD",
    "sg:tags":[
        "agency"
    ],
    "wof:name":"Jamison Advertising Inc",
    "wof:placetype":"venue"
},
  "geometry": {"coordinates":[-96.697535,43.539568],"type":"Point"}
}