{
  "type": "Feature",
  "properties": {
    "addr:full":"121 3rd St Newell SD 57760",
    "addr:housenumber":"121",
    "addr:postcode":"57760",
    "addr:street":"3Rd St",
    "iso:country":"US",
    "sg:address":"121 3rd St",
    "sg:city":"Newell",
    "sg:classifiers":[
        {
            "category":"Utilities",
            "subcategory":"Electric",
            "type":"Services"
        }
    ],
    "sg:phone":"+1 605 456 2896",
    "sg:postcode":"57760",
    "sg:province":"SD",
    "sg:tags":[
        "company"
    ],
    "wof:name":"Black Hills Power",
    "wof:placetype":"venue"
},
  "geometry": {"coordinates":[-103.420917,44.714609],"type":"Point"}
}