{
  "type": "Feature",
  "properties": {
    "addr:full":"47184 Wild Clover Cir Sioux Falls SD 57107",
    "addr:housenumber":"47184",
    "addr:postcode":"57107",
    "addr:street":"Wild Clover Cir",
    "iso:country":"US",
    "sg:address":"47184 Wild Clover Cir",
    "sg:city":"Sioux Falls",
    "sg:classifiers":[
        {
            "category":"Freight",
            "type":"Transportation"
        }
    ],
    "sg:phone":"+1 605 543 6046",
    "sg:postcode":"57107",
    "sg:province":"SD",
    "sg:tags":[
        "company",
        "trucking"
    ],
    "wof:name":"Tri State Freight Shuttle Inc",
    "wof:placetype":"venue"
},
  "geometry": {"coordinates":[-96.77524699999999,43.647208],"type":"Point"}
}