{
  "type": "Feature",
  "properties": {
    "iso:country":"US",
    "sg:address":"45678 275th St",
    "sg:city":"Parker",
    "sg:phone":"+1 605 297 4175",
    "sg:postcode":"57053",
    "sg:province":"SD",
    "sg:tags":[
        "farm",
        "organization",
        "corn",
        "religious"
    ],
    "wof:name":"Plucker Charloais",
    "wof:placetype":"venue"
},
  "geometry": {"coordinates":[-97.082516,43.402004],"type":"Point"}
}