{
  "type": "Feature",
  "properties": {
    "iso:country":"US",
    "sg:address":"11 Chestnut St W",
    "sg:city":"Sisseton",
    "sg:classifiers":[
        {
            "category":"Government",
            "subcategory":"Office",
            "type":"Public Place"
        }
    ],
    "sg:phone":"+1 605 698 3531",
    "sg:postcode":"57262",
    "sg:province":"SD",
    "sg:tags":[
        "village"
    ],
    "wof:name":"Sisseton-Wahpeton Sioux Tribe",
    "wof:placetype":"venue"
},
  "geometry": {"coordinates":[-97.051071,45.667475],"type":"Point"}
}