{
  "type": "Feature",
  "properties": {
    "addr:full":"283 Main St Claire City SD 57274",
    "addr:housenumber":"283",
    "addr:postcode":"57274",
    "addr:street":"Main St",
    "iso:country":"US",
    "sg:address":"283 Main St",
    "sg:city":"Claire City",
    "sg:classifiers":[
        {
            "category":"Organizations",
            "subcategory":"Religious Organization",
            "type":"Services"
        }
    ],
    "sg:phone":"+1 605 652 4633",
    "sg:postcode":"57274",
    "sg:province":"SD",
    "sg:tags":[
        "church"
    ],
    "wof:name":"First Lutheran Church",
    "wof:placetype":"venue"
},
  "geometry": {"coordinates":[-97.52017600000001,45.327493],"type":"Point"}
}