{
  "type": "Feature",
  "properties": {
    "iso:country":"US",
    "sg:address":"1208 Wambli Dr",
    "sg:city":"Rapid City",
    "sg:classifiers":[
        {
            "category":"Recreation",
            "type":"Entertainment"
        }
    ],
    "sg:phone":"+1 605 342 5944",
    "sg:postcode":"57701",
    "sg:province":"SD",
    "sg:tags":[
        "instructor",
        "fitness"
    ],
    "wof:name":"Mitchell Brewer",
    "wof:placetype":"venue"
},
  "geometry": {"coordinates":[-103.229473,44.107946],"type":"Point"}
}