{
  "type": "Feature",
  "properties": {
    "iso:country":"US",
    "sg:address":"604 W Birch Ave",
    "sg:city":"Mitchell",
    "sg:classifiers":[
        {
            "category":"Building & Trades",
            "subcategory":"Landscaping Services",
            "type":"Services"
        }
    ],
    "sg:phone":"+1 605 996 2260",
    "sg:postcode":"57301",
    "sg:province":"SD",
    "wof:name":"Dakota Green Landscaping",
    "wof:placetype":"venue"
},
  "geometry": {"coordinates":[-98.032441,43.706765],"type":"Point"}
}