{
  "type": "Feature",
  "properties": {
    "addr:full":"1540 Riverview Dr Huron SD 57350",
    "addr:housenumber":"1540",
    "addr:postcode":"57350",
    "addr:street":"Riverview Dr",
    "iso:country":"US",
    "sg:address":"1540 Riverview Dr",
    "sg:city":"Huron",
    "sg:classifiers":[
        {
            "category":"Health Services",
            "subcategory":"Doctor",
            "type":"Services"
        }
    ],
    "sg:phone":"+1 605 352 5162",
    "sg:postcode":"57350",
    "sg:province":"SD",
    "sg:tags":[
        "physician",
        "surgeon"
    ],
    "wof:name":"Elane Hanson MD",
    "wof:placetype":"venue"
},
  "geometry": {"coordinates":[-98.20039800000001,44.3485],"type":"Point"}
}