{
  "type": "Feature",
  "properties": {
    "addr:full":"1901 US Hwy 18 Hot Springs SD 57747",
    "addr:housenumber":"1901",
    "addr:postcode":"57747",
    "addr:street":"Us Hwy 18",
    "iso:country":"US",
    "sg:address":"1901 US Hwy 18",
    "sg:city":"Hot Springs",
    "sg:classifiers":[
        {
            "category":"Retail",
            "subcategory":"Auto Rental",
            "type":"Services"
        }
    ],
    "sg:phone":"+1 605 673 4919",
    "sg:postcode":"57747",
    "sg:province":"SD",
    "sg:tags":[
        "renting",
        "truck",
        "leasing"
    ],
    "wof:name":"U-Haul Co",
    "wof:placetype":"venue"
},
  "geometry": {"coordinates":[-103.48665800000001,43.42994],"type":"Point"}
}