{
  "type": "Feature",
  "properties": {
    "iso:country":"US",
    "sg:address":"4501 S Technology Dr",
    "sg:city":"Sioux Falls",
    "sg:classifiers":[
        {
            "category":"Building & Trades",
            "subcategory":"Construction",
            "type":"Services"
        }
    ],
    "sg:phone":"+1 605 361 6672",
    "sg:postcode":"57106",
    "sg:province":"SD",
    "sg:tags":[
        "company"
    ],
    "wof:name":"Construction Sioux Falls",
    "wof:placetype":"venue"
},
  "geometry": {"coordinates":[-96.775292,43.506151],"type":"Point"}
}