{
  "type": "Feature",
  "properties": {
    "iso:country":"US",
    "sg:address":"109 W 42nd St",
    "sg:city":"Sioux Falls",
    "sg:classifiers":[
        {
            "category":"Organizations",
            "subcategory":"Religious Organization",
            "type":"Services"
        }
    ],
    "sg:phone":"+1 605 335 0915",
    "sg:postcode":"57105",
    "sg:province":"SD",
    "wof:name":"Richard O Moberly Rev",
    "wof:placetype":"venue"
},
  "geometry": {"coordinates":[-96.72901,43.513893],"type":"Point"}
}