{
  "type": "Feature",
  "properties": {
    "addr:full":"325 Main Ave Brookings SD 57006",
    "addr:housenumber":"325",
    "addr:postcode":"57006",
    "addr:street":"Main Ave",
    "iso:country":"US",
    "sg:address":"325 Main Ave",
    "sg:city":"Brookings",
    "sg:classifiers":[
        {
            "category":"Shopping",
            "type":"Retail Goods"
        }
    ],
    "sg:phone":"+1 605 697 5222",
    "sg:postcode":"57006",
    "sg:province":"SD",
    "sg:tags":[
        "picture",
        "frame"
    ],
    "wof:name":"Artworks",
    "wof:placetype":"venue"
},
  "geometry": {"coordinates":[-96.798694,44.308823],"type":"Point"}
}