{
  "type": "Feature",
  "properties": {
    "iso:country":"US",
    "sg:address":"203 Prairie St",
    "sg:city":"Harrisburg",
    "sg:classifiers":[
        {
            "category":"Government",
            "subcategory":"Office",
            "type":"Public Place"
        }
    ],
    "sg:phone":"+1 605 743 5872",
    "sg:postcode":"57032",
    "sg:province":"SD",
    "sg:tags":[
        "city"
    ],
    "wof:name":"Harrisburg City Hall",
    "wof:placetype":"venue"
},
  "geometry": {"coordinates":[-96.699499,43.430587],"type":"Point"}
}