{
  "type": "Feature",
  "properties": {
    "iso:country":"US",
    "sg:address":"1501 S Van Eps Ave",
    "sg:city":"Sioux Falls",
    "sg:classifiers":[
        {
            "category":"Building & Trades",
            "subcategory":"Construction",
            "type":"Services"
        }
    ],
    "sg:phone":"+1 605 334 3869",
    "sg:postcode":"57105",
    "sg:province":"SD",
    "sg:tags":[
        "nonresidential"
    ],
    "wof:name":"Wollan Construction & Repair",
    "wof:placetype":"venue"
},
  "geometry": {"coordinates":[-96.708801,43.531161],"type":"Point"}
}