{
  "type": "Feature",
  "properties": {
    "addr:full":"44469 290th St Viborg SD 57070",
    "addr:housenumber":"44469",
    "addr:postcode":"57070",
    "addr:street":"290Th St",
    "iso:country":"US",
    "sg:address":"44469 290th St",
    "sg:city":"Viborg",
    "sg:phone":"+1 605 327 3212",
    "sg:postcode":"57070",
    "sg:province":"SD",
    "sg:tags":[
        "beef",
        "farm",
        "corn",
        "soybean",
        "cattle",
        "feedlot"
    ],
    "wof:name":"Murray Westergaard",
    "wof:placetype":"venue"
},
  "geometry": {"coordinates":[-97.30436899999999,43.183935],"type":"Point"}
}