{
  "type": "Feature",
  "properties": {
    "iso:country":"US",
    "sg:address":"3100 US Hwy 14 Byp",
    "sg:city":"Brookings",
    "sg:classifiers":[
        {
            "category":"Wholesale",
            "subcategory":"Machinery & Supplies",
            "type":"Manufacturing & Wholesale Goods"
        }
    ],
    "sg:phone":"+1 605 693 3514",
    "sg:postcode":"57006",
    "sg:province":"SD",
    "sg:tags":[
        "farm",
        "equipment"
    ],
    "wof:name":"Eugene Beckman & Sons Implmnt",
    "wof:placetype":"venue"
},
  "geometry": {"coordinates":[-96.753512,44.325751],"type":"Point"}
}