{
  "type": "Feature",
  "properties": {
    "iso:country":"US",
    "sg:address":"504 Catalina Ave",
    "sg:city":"Baltic",
    "sg:classifiers":[
        {
            "category":"Building & Trades",
            "subcategory":"Construction",
            "type":"Services"
        }
    ],
    "sg:phone":"+1 605 529 5075",
    "sg:postcode":"57069",
    "sg:province":"SD",
    "sg:tags":[
        "house"
    ],
    "wof:name":"Lupkes Construction",
    "wof:placetype":"venue"
},
  "geometry": {"coordinates":[-96.915328,42.774317],"type":"Point"}
}