{
  "type": "Feature",
  "properties": {
    "iso:country":"US",
    "sg:address":"216 E Holly Blvd",
    "sg:city":"Brandon",
    "sg:classifiers":[
        {
            "category":"Shopping",
            "subcategory":"Gifts & Souvenirs",
            "type":"Retail Goods"
        }
    ],
    "sg:phone":"+1 605 582 8644",
    "sg:postcode":"57005",
    "sg:province":"SD",
    "sg:tags":[
        "shop"
    ],
    "wof:name":"1948 Trading Company",
    "wof:placetype":"venue"
},
  "geometry": {"coordinates":[-96.588939,43.59466],"type":"Point"}
}