{
  "type": "Feature",
  "properties": {
    "iso:country":"US",
    "sg:address":"4310 Cedar Ridge Pl",
    "sg:city":"Rapid City",
    "sg:classifiers":[
        {
            "category":"Professional",
            "subcategory":"Research",
            "type":"Services"
        }
    ],
    "sg:phone":"+1 605 348 4367",
    "sg:postcode":"57702",
    "sg:province":"SD",
    "sg:tags":[
        "environmental"
    ],
    "wof:name":"Lashley  Ulrike",
    "wof:placetype":"venue"
},
  "geometry": {"coordinates":[-103.291423,44.069064],"type":"Point"}
}