{
  "type": "Feature",
  "properties": {
    "iso:country":"US",
    "sg:address":"18580 345th Ave",
    "sg:city":"Miller",
    "sg:classifiers":[
        {
            "category":"Farming",
            "subcategory":"Livestock Farm",
            "type":"Manufacturing & Wholesale Goods"
        }
    ],
    "sg:phone":"+1 605 943 5654",
    "sg:postcode":"57362",
    "sg:province":"SD",
    "sg:tags":[
        "animal",
        "general"
    ],
    "wof:name":"Pratt Ranch",
    "wof:placetype":"venue"
},
  "geometry": {"coordinates":[-99.293041,44.690181],"type":"Point"}
}