{
  "type": "Feature",
  "properties": {
    "iso:country":"US",
    "sg:address":"31558 462nd Ave",
    "sg:city":"Vermillion",
    "sg:phone":"+1 605 624 4753",
    "sg:postcode":"57069",
    "sg:province":"SD",
    "sg:tags":[
        "farm",
        "field",
        "corn",
        "soybean",
        "crop"
    ],
    "wof:name":"Jerry Sommervold",
    "wof:placetype":"venue"
},
  "geometry": {"coordinates":[-96.963442,42.816258],"type":"Point"}
}