{
  "type": "Feature",
  "properties": {
    "iso:country":"US",
    "sg:address":"26494 Landon Ln",
    "sg:city":"Sioux Falls",
    "sg:classifiers":[
        {
            "category":"Building & Trades",
            "subcategory":"Electrical",
            "type":"Services"
        }
    ],
    "sg:phone":"+1 605 335 3525",
    "sg:postcode":"57107",
    "sg:province":"SD",
    "sg:tags":[
        "electrical",
        "contractor"
    ],
    "wof:name":"JP Electric",
    "wof:placetype":"venue"
},
  "geometry": {"coordinates":[-96.867819,43.54366],"type":"Point"}
}