{
  "type": "Feature",
  "properties": {
    "addr:full":"208 S Splitrock Blvd Brandon SD 57005",
    "addr:housenumber":"208",
    "addr:postcode":"57005",
    "addr:street":"S Splitrock Blvd",
    "iso:country":"US",
    "sg:address":"208 S Splitrock Blvd",
    "sg:city":"Brandon",
    "sg:classifiers":[
        {
            "category":"Health Services",
            "subcategory":"Health Practitioner",
            "type":"Services"
        }
    ],
    "sg:phone":"+1 605 582 3064",
    "sg:postcode":"57005",
    "sg:province":"SD",
    "wof:name":"Brandon Black Belt Academy",
    "wof:placetype":"venue"
},
  "geometry": {"coordinates":[-96.572259,43.592925],"type":"Point"}
}