{
  "type": "Feature",
  "properties": {
    "iso:country":"US",
    "sg:address":"40581 210th St",
    "sg:city":"Huron",
    "sg:phone":"+1 605 352 7492",
    "sg:postcode":"57350",
    "sg:province":"SD",
    "sg:tags":[
        "wheat",
        "farm",
        "corn",
        "crop",
        "field",
        "soybean"
    ],
    "wof:name":"Bob Moody Farm",
    "wof:placetype":"venue"
},
  "geometry": {"coordinates":[-98.09691100000001,44.340976],"type":"Point"}
}