{
  "type": "Feature",
  "properties": {
    "addr:full":"826 32nd Ave Brookings SD 57006",
    "addr:housenumber":"826",
    "addr:postcode":"57006",
    "addr:street":"32Nd Ave",
    "iso:country":"US",
    "sg:address":"826 32nd Ave",
    "sg:city":"Brookings",
    "sg:classifiers":[
        {
            "category":"Government",
            "subcategory":"Office",
            "type":"Public Place"
        }
    ],
    "sg:phone":"+1 605 697 6706",
    "sg:postcode":"57006",
    "sg:province":"SD",
    "wof:name":"Brookings County Extention Off",
    "wof:placetype":"venue"
},
  "geometry": {"coordinates":[-96.751628,44.314586],"type":"Point"}
}