{
  "type": "Feature",
  "properties": {
    "addr:full":"301 E 5th St Egan SD 57024",
    "addr:housenumber":"301",
    "addr:postcode":"57024",
    "addr:street":"E 5Th St",
    "iso:country":"US",
    "sg:address":"301 E 5th St",
    "sg:city":"Egan",
    "sg:classifiers":[
        {
            "category":"Personal",
            "type":"Services"
        }
    ],
    "sg:phone":"+1 605 997 3253",
    "sg:postcode":"57024",
    "sg:province":"SD",
    "sg:tags":[
        "assistant"
    ],
    "wof:name":"Joy Chamley",
    "wof:placetype":"venue"
},
  "geometry": {"coordinates":[-96.646458,44.001381],"type":"Point"}
}