{
  "type": "Feature",
  "properties": {
    "iso:country":"US",
    "sg:address":"10 Austin St",
    "sg:city":"Vermillion",
    "sg:classifiers":[
        {
            "category":"Professional",
            "subcategory":"Lawyer & Legal Services",
            "type":"Services"
        }
    ],
    "sg:phone":"+1 605 624 3295",
    "sg:postcode":"57069",
    "sg:province":"SD",
    "wof:name":"Teddi J Gertsma",
    "wof:placetype":"venue"
},
  "geometry": {"coordinates":[-96.935253,42.779307],"type":"Point"}
}