{
  "type": "Feature",
  "properties": {
    "iso:country":"US",
    "sg:address":"817 Main St",
    "sg:city":"Rapid City",
    "sg:classifiers":[
        {
            "category":"Shopping",
            "subcategory":"Clothing, Apparel, & Fashions",
            "type":"Retail Goods"
        }
    ],
    "sg:phone":"+1 605 341 3032",
    "sg:postcode":"57701",
    "sg:province":"SD",
    "sg:tags":[
        "sporting"
    ],
    "wof:name":"Connection Army Navy",
    "wof:placetype":"venue"
},
  "geometry": {"coordinates":[-103.232389,44.081838],"type":"Point"}
}