{
  "type": "Feature",
  "properties": {
    "addr:full":"407 Cliff St Deadwood SD 57732",
    "addr:housenumber":"407",
    "addr:postcode":"57732",
    "addr:street":"Cliff St",
    "iso:country":"US",
    "sg:address":"407 Cliff St",
    "sg:city":"Deadwood",
    "sg:classifiers":[
        {
            "category":"Home & Garden",
            "subcategory":"Carpets & Floor Coverings",
            "type":"Retail Goods"
        },
        {
            "category":"Building & Trades",
            "subcategory":"Construction",
            "type":"Services"
        }
    ],
    "sg:phone":"+1 605 578 1051",
    "sg:postcode":"57732",
    "sg:province":"SD",
    "sg:tags":[
        "dealer",
        "laying",
        "rug",
        "contractor"
    ],
    "wof:name":"Tony's Carpet",
    "wof:placetype":"venue"
},
  "geometry": {"coordinates":[-103.73903,44.362332],"type":"Point"}
}