{
  "type": "Feature",
  "properties": {
    "iso:country":"US",
    "sg:address":"311 E 4th St",
    "sg:city":"Colton",
    "sg:classifiers":[
        {
            "category":"Bars & Pubs",
            "type":"Food & Drink"
        }
    ],
    "sg:phone":"+1 605 446 9997",
    "sg:postcode":"57018",
    "sg:province":"SD",
    "sg:tags":[
        "drinking"
    ],
    "wof:name":"Municipal Bar",
    "wof:placetype":"venue"
},
  "geometry": {"coordinates":[-96.92775,43.7869],"type":"Point"}
}