{
  "type": "Feature",
  "properties": {
    "addr:full":"500 E Capitol Ave Pierre SD 57501",
    "addr:housenumber":"500",
    "addr:postcode":"57501",
    "addr:street":"E Capitol Ave",
    "iso:country":"US",
    "sg:address":"500 E Capitol Ave",
    "sg:city":"Pierre",
    "sg:classifiers":[
        {
            "category":"Government",
            "subcategory":"Office",
            "type":"Public Place"
        }
    ],
    "sg:phone":"+1 605 773 3851",
    "sg:postcode":"57501",
    "sg:province":"SD",
    "sg:tags":[
        "legislative",
        "body"
    ],
    "wof:name":"J P Duniphan",
    "wof:placetype":"venue"
},
  "geometry": {"coordinates":[-100.346907,44.366159],"type":"Point"}
}